Workbook
Name a: #N/A
Name CC: #REF!
Name Conta: #REF!
Name Efeito: #REF!
Name EXPLIC: #N/A
Name Macro3: #N/A
Name Mes: #REF!
Name Mês: #REF!

Sheet Input
B1: =_xll.VIEW("CONS_VC:STG.100.DataBase_Uploads",D9) -> CONS_VC:STG.100.DataBase_Uploads:682804457956426348 | C1: =_xll.VIEW("CONS_VC:ALL.015.Region_Assumptions") -> CONS_VC:ALL.015.Region_Assumptions:6828044571849741741 | K1: Value | L1: N/A | M1: =_xll.SUBNM("CONS_VC:ALL.D.Version","","T4") -> T4 | N1: PROD099
B2: =_xll.VIEW("CONS_VC:REV.100.Revenue_Consolidated") -> CONS_VC:REV.100.Revenue_Consolidated:68280445742607536 | C2: =_xll.VIEW("CONS_VC:ALL.010.Economic_Assumptions") -> CONS_VC:ALL.010.Economic_Assumptions:682804457315016469 | K2: Total Market | N2: Total Products
B3: =_xll.VIEW("CONS_VC:DFS.100.Profit_and_Loss") -> CONS_VC:DFS.100.Profit_and_Loss:682804457537612563 | G3: Flag
B4: =_xll.VIEW("CONS_VC:ALL.001.Actual_Control") -> CONS_VC:ALL.001.Actual_Control:6828044571419146646
C5: =_xll.DBRW(Input!$B$4,Input!$D$9,Input!C11,$M$1,$G$3) -> PLAN | D5: =_xll.DBRW(Input!$B$4,Input!$D$9,Input!D11,$M$1,$G$3) -> PLAN | E5: =_xll.DBRW(Input!$B$4,Input!$D$9,Input!E11,$M$1,$G$3) -> PLAN | F5: =_xll.DBRW(Input!$B$4,Input!$D$9,Input!F11,$M$1,$G$3) -> PLAN | G5: =_xll.DBRW(Input!$B$4,Input!$D$9,Input!G11,$M$1,$G$3) -> PLAN | H5: =_xll.DBRW(Input!$B$4,Input!$D$9,Input!H11,$M$1,$G$3) -> PLAN | I5: =_xll.DBRW(Input!$B$4,Input!$D$9,Input!I11,$M$1,$G$3) -> PLAN | J5: =_xll.DBRW(Input!$B$4,Input!$D$9,Input!J11,$M$1,$G$3) -> PLAN | ... N5: =_xll.DBRW(Input!$B$4,Input!$D$9,Input!N11,$M$1,$G$3) -> PLAN
B8: GLOBAL ASSUMPTIONS
C9: Year: | D9: =_xll.SUBNM("CONS_VC:ALL.D.Year","SYS_Picklist","2025","MEMBER_NAME") -> 2025 | F9: Currency: | G9: =_xll.SUBNM("CONS_VC:ALL.D.Currency","","BRL") -> BRL | I9: Region: | J9: =_xll.SUBNM("CONS_VC:ALL.D.Region","Nível 0","VCBR","MEMBER_NAME") -> VCBR
C11: 01 | D11: 02 | E11: 03 | F11: 04 | G11: 05 | H11: 06 | I11: 07 | J11: 08 | K11: 09 | L11: 10 | M11: 11 | N11: 12
C12: =$D$9&"."&C11 -> 2025.01 | D12: =$D$9&"."&D11 -> 2025.02 | E12: =$D$9&"."&E11 -> 2025.03 | F12: =$D$9&"."&F11 -> 2025.04 | G12: =$D$9&"."&G11 -> 2025.05 | H12: =$D$9&"."&H11 -> 2025.06 | I12: =$D$9&"."&I11 -> 2025.07 | J12: =$D$9&"."&J11 -> 2025.08 | ... N12: =$D$9&"."&N11 -> 2025.12
B13: Begining FX Rate R$/US$ | C13: =_xll.DBRW($C$2,Input!$D$9,Input!$C$11,$M$1,$B13,$K$1) -> 0 | D13: =_xll.DBRW($C$2,Input!$D$9,Input!$C$11,$M$1,$B13,$K$1) -> 0 | E13: =_xll.DBRW($C$2,Input!$D$9,Input!$C$11,$M$1,$B13,$K$1) -> 0 | F13: =_xll.DBRW($C$2,Input!$D$9,Input!$C$11,$M$1,$B13,$K$1) -> 0 | G13: =_xll.DBRW($C$2,Input!$D$9,Input!$C$11,$M$1,$B13,$K$1) -> 0 | H13: =_xll.DBRW($C$2,Input!$D$9,Input!$C$11,$M$1,$B13,$K$1) -> 0 | I13: =_xll.DBRW($C$2,Input!$D$9,Input!$C$11,$M$1,$B13,$K$1) -> 0 | J13: =_xll.DBRW($C$2,Input!$D$9,Input!$C$11,$M$1,$B13,$K$1) -> 0 | ... N13: =_xll.DBRW($C$2,Input!$D$9,Input!$C$11,$M$1,$B13,$K$1) -> 0
B14: Average FX Rate R$/US$ | C14: =_xll.DBRW($C$2,Input!$D$9,Input!$C$11,$M$1,$B14,$K$1) -> 0 | D14: =_xll.DBRW($C$2,Input!$D$9,Input!$C$11,$M$1,$B14,$K$1) -> 0 | E14: =_xll.DBRW($C$2,Input!$D$9,Input!$C$11,$M$1,$B14,$K$1) -> 0 | F14: =_xll.DBRW($C$2,Input!$D$9,Input!$C$11,$M$1,$B14,$K$1) -> 0 | G14: =_xll.DBRW($C$2,Input!$D$9,Input!$C$11,$M$1,$B14,$K$1) -> 0 | H14: =_xll.DBRW($C$2,Input!$D$9,Input!$C$11,$M$1,$B14,$K$1) -> 0 | I14: =_xll.DBRW($C$2,Input!$D$9,Input!$C$11,$M$1,$B14,$K$1) -> 0 | J14: =_xll.DBRW($C$2,Input!$D$9,Input!$C$11,$M$1,$B14,$K$1) -> 0 | ... N14: =_xll.DBRW($C$2,Input!$D$9,Input!$C$11,$M$1,$B14,$K$1) -> 0
B15: Final FX Rate R$/US$ | C15: =_xll.DBRW($C$2,Input!$D$9,Input!$C$11,$M$1,$B15,$K$1) -> 0 | D15: =_xll.DBRW($C$2,Input!$D$9,Input!$C$11,$M$1,$B15,$K$1) -> 0 | E15: =_xll.DBRW($C$2,Input!$D$9,Input!$C$11,$M$1,$B15,$K$1) -> 0 | F15: =_xll.DBRW($C$2,Input!$D$9,Input!$C$11,$M$1,$B15,$K$1) -> 0 | G15: =_xll.DBRW($C$2,Input!$D$9,Input!$C$11,$M$1,$B15,$K$1) -> 0 | H15: =_xll.DBRW($C$2,Input!$D$9,Input!$C$11,$M$1,$B15,$K$1) -> 0 | I15: =_xll.DBRW($C$2,Input!$D$9,Input!$C$11,$M$1,$B15,$K$1) -> 0 | J15: =_xll.DBRW($C$2,Input!$D$9,Input!$C$11,$M$1,$B15,$K$1) -> 0 | ... N15: =_xll.DBRW($C$2,Input!$D$9,Input!$C$11,$M$1,$B15,$K$1) -> 0
B16: Begining FX Rate US$/EUR | C16: =_xll.DBRW($C$2,Input!$D$9,Input!$C$11,$M$1,$B16,$K$1) -> 0 | D16: =_xll.DBRW($C$2,Input!$D$9,Input!$C$11,$M$1,$B16,$K$1) -> 0 | E16: =_xll.DBRW($C$2,Input!$D$9,Input!$C$11,$M$1,$B16,$K$1) -> 0 | F16: =_xll.DBRW($C$2,Input!$D$9,Input!$C$11,$M$1,$B16,$K$1) -> 0 | G16: =_xll.DBRW($C$2,Input!$D$9,Input!$C$11,$M$1,$B16,$K$1) -> 0 | H16: =_xll.DBRW($C$2,Input!$D$9,Input!$C$11,$M$1,$B16,$K$1) -> 0 | I16: =_xll.DBRW($C$2,Input!$D$9,Input!$C$11,$M$1,$B16,$K$1) -> 0 | J16: =_xll.DBRW($C$2,Input!$D$9,Input!$C$11,$M$1,$B16,$K$1) -> 0 | ... N16: =_xll.DBRW($C$2,Input!$D$9,Input!$C$11,$M$1,$B16,$K$1) -> 0
B17: Average FX Rate US$/EUR | C17: =_xll.DBRW($C$2,Input!$D$9,Input!$C$11,$M$1,$B17,$K$1) -> 0 | D17: =_xll.DBRW($C$2,Input!$D$9,Input!$C$11,$M$1,$B17,$K$1) -> 0 | E17: =_xll.DBRW($C$2,Input!$D$9,Input!$C$11,$M$1,$B17,$K$1) -> 0 | F17: =_xll.DBRW($C$2,Input!$D$9,Input!$C$11,$M$1,$B17,$K$1) -> 0 | G17: =_xll.DBRW($C$2,Input!$D$9,Input!$C$11,$M$1,$B17,$K$1) -> 0 | H17: =_xll.DBRW($C$2,Input!$D$9,Input!$C$11,$M$1,$B17,$K$1) -> 0 | I17: =_xll.DBRW($C$2,Input!$D$9,Input!$C$11,$M$1,$B17,$K$1) -> 0 | J17: =_xll.DBRW($C$2,Input!$D$9,Input!$C$11,$M$1,$B17,$K$1) -> 0 | ... N17: =_xll.DBRW($C$2,Input!$D$9,Input!$C$11,$M$1,$B17,$K$1) -> 0
B18: Final FX Rate US$/EUR | C18: =_xll.DBRW($C$2,Input!$D$9,Input!$C$11,$M$1,$B18,$K$1) -> 0 | D18: =_xll.DBRW($C$2,Input!$D$9,Input!$C$11,$M$1,$B18,$K$1) -> 0 | E18: =_xll.DBRW($C$2,Input!$D$9,Input!$C$11,$M$1,$B18,$K$1) -> 0 | F18: =_xll.DBRW($C$2,Input!$D$9,Input!$C$11,$M$1,$B18,$K$1) -> 0 | G18: =_xll.DBRW($C$2,Input!$D$9,Input!$C$11,$M$1,$B18,$K$1) -> 0 | H18: =_xll.DBRW($C$2,Input!$D$9,Input!$C$11,$M$1,$B18,$K$1) -> 0 | I18: =_xll.DBRW($C$2,Input!$D$9,Input!$C$11,$M$1,$B18,$K$1) -> 0 | J18: =_xll.DBRW($C$2,Input!$D$9,Input!$C$11,$M$1,$B18,$K$1) -> 0 | ... N18: =_xll.DBRW($C$2,Input!$D$9,Input!$C$11,$M$1,$B18,$K$1) -> 0
B19: Câmbio Inicial UYU$/US$ | C19: =_xll.DBRW($C$2,Input!$D$9,Input!$C$11,$M$1,$B19,$K$1) -> 0 | D19: =_xll.DBRW($C$2,Input!$D$9,Input!$C$11,$M$1,$B19,$K$1) -> 0 | E19: =_xll.DBRW($C$2,Input!$D$9,Input!$C$11,$M$1,$B19,$K$1) -> 0 | F19: =_xll.DBRW($C$2,Input!$D$9,Input!$C$11,$M$1,$B19,$K$1) -> 0 | G19: =_xll.DBRW($C$2,Input!$D$9,Input!$C$11,$M$1,$B19,$K$1) -> 0 | H19: =_xll.DBRW($C$2,Input!$D$9,Input!$C$11,$M$1,$B19,$K$1) -> 0 | I19: =_xll.DBRW($C$2,Input!$D$9,Input!$C$11,$M$1,$B19,$K$1) -> 0 | J19: =_xll.DBRW($C$2,Input!$D$9,Input!$C$11,$M$1,$B19,$K$1) -> 0 | ... N19: =_xll.DBRW($C$2,Input!$D$9,Input!$C$11,$M$1,$B19,$K$1) -> 0
B20: Câmbio Médio UYU$/US$ | C20: =_xll.DBRW($C$2,Input!$D$9,Input!$C$11,$M$1,$B20,$K$1) -> 0 | D20: =_xll.DBRW($C$2,Input!$D$9,Input!$C$11,$M$1,$B20,$K$1) -> 0 | E20: =_xll.DBRW($C$2,Input!$D$9,Input!$C$11,$M$1,$B20,$K$1) -> 0 | F20: =_xll.DBRW($C$2,Input!$D$9,Input!$C$11,$M$1,$B20,$K$1) -> 0 | G20: =_xll.DBRW($C$2,Input!$D$9,Input!$C$11,$M$1,$B20,$K$1) -> 0 | H20: =_xll.DBRW($C$2,Input!$D$9,Input!$C$11,$M$1,$B20,$K$1) -> 0 | I20: =_xll.DBRW($C$2,Input!$D$9,Input!$C$11,$M$1,$B20,$K$1) -> 0 | J20: =_xll.DBRW($C$2,Input!$D$9,Input!$C$11,$M$1,$B20,$K$1) -> 0 | ... N20: =_xll.DBRW($C$2,Input!$D$9,Input!$C$11,$M$1,$B20,$K$1) -> 0
B21: Câmbio Final UYU$/US$ | C21: =_xll.DBRW($C$2,Input!$D$9,Input!$C$11,$M$1,$B21,$K$1) -> 0 | D21: =_xll.DBRW($C$2,Input!$D$9,Input!$C$11,$M$1,$B21,$K$1) -> 0 | E21: =_xll.DBRW($C$2,Input!$D$9,Input!$C$11,$M$1,$B21,$K$1) -> 0 | F21: =_xll.DBRW($C$2,Input!$D$9,Input!$C$11,$M$1,$B21,$K$1) -> 0 | G21: =_xll.DBRW($C$2,Input!$D$9,Input!$C$11,$M$1,$B21,$K$1) -> 0 | H21: =_xll.DBRW($C$2,Input!$D$9,Input!$C$11,$M$1,$B21,$K$1) -> 0 | I21: =_xll.DBRW($C$2,Input!$D$9,Input!$C$11,$M$1,$B21,$K$1) -> 0 | J21: =_xll.DBRW($C$2,Input!$D$9,Input!$C$11,$M$1,$B21,$K$1) -> 0 | ... N21: =_xll.DBRW($C$2,Input!$D$9,Input!$C$11,$M$1,$B21,$K$1) -> 0
B22: Câmbio Inicial ARS$/US$ | C22: =_xll.DBRW($C$2,Input!$D$9,Input!$C$11,$M$1,$B22,$K$1) -> 0 | D22: =_xll.DBRW($C$2,Input!$D$9,Input!$C$11,$M$1,$B22,$K$1) -> 0 | E22: =_xll.DBRW($C$2,Input!$D$9,Input!$C$11,$M$1,$B22,$K$1) -> 0 | F22: =_xll.DBRW($C$2,Input!$D$9,Input!$C$11,$M$1,$B22,$K$1) -> 0 | G22: =_xll.DBRW($C$2,Input!$D$9,Input!$C$11,$M$1,$B22,$K$1) -> 0 | H22: =_xll.DBRW($C$2,Input!$D$9,Input!$C$11,$M$1,$B22,$K$1) -> 0 | I22: =_xll.DBRW($C$2,Input!$D$9,Input!$C$11,$M$1,$B22,$K$1) -> 0 | J22: =_xll.DBRW($C$2,Input!$D$9,Input!$C$11,$M$1,$B22,$K$1) -> 0 | ... N22: =_xll.DBRW($C$2,Input!$D$9,Input!$C$11,$M$1,$B22,$K$1) -> 0
B23: Câmbio Médio ARS$/US$ | C23: =_xll.DBRW($C$2,Input!$D$9,Input!$C$11,$M$1,$B23,$K$1) -> 0 | D23: =_xll.DBRW($C$2,Input!$D$9,Input!$C$11,$M$1,$B23,$K$1) -> 0 | E23: =_xll.DBRW($C$2,Input!$D$9,Input!$C$11,$M$1,$B23,$K$1) -> 0 | F23: =_xll.DBRW($C$2,Input!$D$9,Input!$C$11,$M$1,$B23,$K$1) -> 0 | G23: =_xll.DBRW($C$2,Input!$D$9,Input!$C$11,$M$1,$B23,$K$1) -> 0 | H23: =_xll.DBRW($C$2,Input!$D$9,Input!$C$11,$M$1,$B23,$K$1) -> 0 | I23: =_xll.DBRW($C$2,Input!$D$9,Input!$C$11,$M$1,$B23,$K$1) -> 0 | J23: =_xll.DBRW($C$2,Input!$D$9,Input!$C$11,$M$1,$B23,$K$1) -> 0 | ... N23: =_xll.DBRW($C$2,Input!$D$9,Input!$C$11,$M$1,$B23,$K$1) -> 0
B24: Câmbio Final ARS$/US$ | C24: =_xll.DBRW($C$2,Input!$D$9,Input!$C$11,$M$1,$B24,$K$1) -> 0 | D24: =_xll.DBRW($C$2,Input!$D$9,Input!$C$11,$M$1,$B24,$K$1) -> 0 | E24: =_xll.DBRW($C$2,Input!$D$9,Input!$C$11,$M$1,$B24,$K$1) -> 0 | F24: =_xll.DBRW($C$2,Input!$D$9,Input!$C$11,$M$1,$B24,$K$1) -> 0 | G24: =_xll.DBRW($C$2,Input!$D$9,Input!$C$11,$M$1,$B24,$K$1) -> 0 | H24: =_xll.DBRW($C$2,Input!$D$9,Input!$C$11,$M$1,$B24,$K$1) -> 0 | I24: =_xll.DBRW($C$2,Input!$D$9,Input!$C$11,$M$1,$B24,$K$1) -> 0 | J24: =_xll.DBRW($C$2,Input!$D$9,Input!$C$11,$M$1,$B24,$K$1) -> 0 | ... N24: =_xll.DBRW($C$2,Input!$D$9,Input!$C$11,$M$1,$B24,$K$1) -> 0
... B27: Number of Days | C27: =_xll.DBRW($C$2,Input!$D$9,Input!$C$11,$M$1,$B27,$K$1) -> 31 | D27: =_xll.DBRW($C$2,Input!$D$9,Input!$C$11,$M$1,$B27,$K$1) -> 31 | E27: =_xll.DBRW($C$2,Input!$D$9,Input!$C$11,$M$1,$B27,$K$1) -> 31 | F27: =_xll.DBRW($C$2,Input!$D$9,Input!$C$11,$M$1,$B27,$K$1) -> 31 | G27: =_xll.DBRW($C$2,Input!$D$9,Input!$C$11,$M$1,$B27,$K$1) -> 31 | H27: =_xll.DBRW($C$2,Input!$D$9,Input!$C$11,$M$1,$B27,$K$1) -> 31 | I27: =_xll.DBRW($C$2,Input!$D$9,Input!$C$11,$M$1,$B27,$K$1) -> 31 | J27: =_xll.DBRW($C$2,Input!$D$9,Input!$C$11,$M$1,$B27,$K$1) -> 31 | ... N27: =_xll.DBRW($C$2,Input!$D$9,Input!$C$11,$M$1,$B27,$K$1) -> 31
B30: NET REVENUES
C31: Products: | D31: =_xll.SUBNM("CONS_VC:ALL.D.Products","Nivel_0","PRODAG010 - Aggregates","Código e Descrição") -> PRODAG010 - Aggregates
C33: =$D$9&"."&C11 -> 2025.01 | D33: =$D$9&"."&D11 -> 2025.02 | E33: =$D$9&"."&E11 -> 2025.03 | F33: =$D$9&"."&F11 -> 2025.04 | G33: =$D$9&"."&G11 -> 2025.05 | H33: =$D$9&"."&H11 -> 2025.06 | I33: =$D$9&"."&I11 -> 2025.07 | J33: =$D$9&"."&J11 -> 2025.08 | ... N33: =$D$9&"."&N11 -> 2025.12
B34: Reference Price [$/ton] | C34: =_xll.DBRW($B$1,Input!$D$9,Input!C$11,$M$1,Input!$G$9,Input!$J$9,Input!$D$31,Input!$B34,$L$1,$K$1) -> 0 | D34: =_xll.DBRW($B$1,Input!$D$9,Input!D$11,$M$1,Input!$G$9,Input!$J$9,Input!$D$31,Input!$B34,$L$1,$K$1) -> 0 | E34: =_xll.DBRW($B$1,Input!$D$9,Input!E$11,$M$1,Input!$G$9,Input!$J$9,Input!$D$31,Input!$B34,$L$1,$K$1) -> 0 | F34: =_xll.DBRW($B$1,Input!$D$9,Input!F$11,$M$1,Input!$G$9,Input!$J$9,Input!$D$31,Input!$B34,$L$1,$K$1) -> 0 | G34: =_xll.DBRW($B$1,Input!$D$9,Input!G$11,$M$1,Input!$G$9,Input!$J$9,Input!$D$31,Input!$B34,$L$1,$K$1) -> 0 | H34: =_xll.DBRW($B$1,Input!$D$9,Input!H$11,$M$1,Input!$G$9,Input!$J$9,Input!$D$31,Input!$B34,$L$1,$K$1) -> 0 | I34: =_xll.DBRW($B$1,Input!$D$9,Input!I$11,$M$1,Input!$G$9,Input!$J$9,Input!$D$31,Input!$B34,$L$1,$K$1) -> 0 | J34: =_xll.DBRW($B$1,Input!$D$9,Input!J$11,$M$1,Input!$G$9,Input!$J$9,Input!$D$31,Input!$B34,$L$1,$K$1) -> 0 | ... N34: =_xll.DBRW($B$1,Input!$D$9,Input!N$11,$M$1,Input!$G$9,Input!$J$9,Input!$D$31,Input!$B34,$L$1,$K$1) -> 0
B35: Local Market Sales Volume [kt] | C35: =_xll.DBRW($B$1,Input!$D$9,Input!C$11,$M$1,Input!$G$9,Input!$J$9,Input!$D$31,Input!$B35,$L$1,$K$1) -> 150 | D35: =_xll.DBRW($B$1,Input!$D$9,Input!D$11,$M$1,Input!$G$9,Input!$J$9,Input!$D$31,Input!$B35,$L$1,$K$1) -> 160 | E35: =_xll.DBRW($B$1,Input!$D$9,Input!E$11,$M$1,Input!$G$9,Input!$J$9,Input!$D$31,Input!$B35,$L$1,$K$1) -> 153.1727 | F35: =_xll.DBRW($B$1,Input!$D$9,Input!F$11,$M$1,Input!$G$9,Input!$J$9,Input!$D$31,Input!$B35,$L$1,$K$1) -> 149.82662 | G35: =_xll.DBRW($B$1,Input!$D$9,Input!G$11,$M$1,Input!$G$9,Input!$J$9,Input!$D$31,Input!$B35,$L$1,$K$1) -> 156.83034 | H35: =_xll.DBRW($B$1,Input!$D$9,Input!H$11,$M$1,Input!$G$9,Input!$J$9,Input!$D$31,Input!$B35,$L$1,$K$1) -> 145.46241 | I35: =_xll.DBRW($B$1,Input!$D$9,Input!I$11,$M$1,Input!$G$9,Input!$J$9,Input!$D$31,Input!$B35,$L$1,$K$1) -> 173.86229 | J35: =_xll.DBRW($B$1,Input!$D$9,Input!J$11,$M$1,Input!$G$9,Input!$J$9,Input!$D$31,Input!$B35,$L$1,$K$1) -> 176.33103 | ... N35: =_xll.DBRW($B$1,Input!$D$9,Input!N$11,$M$1,Input!$G$9,Input!$J$9,Input!$D$31,Input!$B35,$L$1,$K$1) -> 144.62306
B36: Export Market Sales Volume [kt] | C36: =_xll.DBRW($B$1,Input!$D$9,Input!C$11,$M$1,Input!$G$9,Input!$J$9,Input!$D$31,Input!$B36,$L$1,$K$1) -> 0 | D36: =_xll.DBRW($B$1,Input!$D$9,Input!D$11,$M$1,Input!$G$9,Input!$J$9,Input!$D$31,Input!$B36,$L$1,$K$1) -> 0 | E36: =_xll.DBRW($B$1,Input!$D$9,Input!E$11,$M$1,Input!$G$9,Input!$J$9,Input!$D$31,Input!$B36,$L$1,$K$1) -> 0 | F36: =_xll.DBRW($B$1,Input!$D$9,Input!F$11,$M$1,Input!$G$9,Input!$J$9,Input!$D$31,Input!$B36,$L$1,$K$1) -> 0 | G36: =_xll.DBRW($B$1,Input!$D$9,Input!G$11,$M$1,Input!$G$9,Input!$J$9,Input!$D$31,Input!$B36,$L$1,$K$1) -> 0 | H36: =_xll.DBRW($B$1,Input!$D$9,Input!H$11,$M$1,Input!$G$9,Input!$J$9,Input!$D$31,Input!$B36,$L$1,$K$1) -> 0 | I36: =_xll.DBRW($B$1,Input!$D$9,Input!I$11,$M$1,Input!$G$9,Input!$J$9,Input!$D$31,Input!$B36,$L$1,$K$1) -> 0 | J36: =_xll.DBRW($B$1,Input!$D$9,Input!J$11,$M$1,Input!$G$9,Input!$J$9,Input!$D$31,Input!$B36,$L$1,$K$1) -> 0 | ... N36: =_xll.DBRW($B$1,Input!$D$9,Input!N$11,$M$1,Input!$G$9,Input!$J$9,Input!$D$31,Input!$B36,$L$1,$K$1) -> 0
B37: Third Part Sales Volume [kt] | C37: =_xll.DBRW($B$1,Input!$D$9,Input!C$11,$M$1,Input!$G$9,Input!$J$9,Input!$D$31,Input!$B37,$L$1,$K$1) -> 0 | D37: =_xll.DBRW($B$1,Input!$D$9,Input!D$11,$M$1,Input!$G$9,Input!$J$9,Input!$D$31,Input!$B37,$L$1,$K$1) -> 0 | E37: =_xll.DBRW($B$1,Input!$D$9,Input!E$11,$M$1,Input!$G$9,Input!$J$9,Input!$D$31,Input!$B37,$L$1,$K$1) -> 0 | F37: =_xll.DBRW($B$1,Input!$D$9,Input!F$11,$M$1,Input!$G$9,Input!$J$9,Input!$D$31,Input!$B37,$L$1,$K$1) -> 0 | G37: =_xll.DBRW($B$1,Input!$D$9,Input!G$11,$M$1,Input!$G$9,Input!$J$9,Input!$D$31,Input!$B37,$L$1,$K$1) -> 0 | H37: =_xll.DBRW($B$1,Input!$D$9,Input!H$11,$M$1,Input!$G$9,Input!$J$9,Input!$D$31,Input!$B37,$L$1,$K$1) -> 0 | I37: =_xll.DBRW($B$1,Input!$D$9,Input!I$11,$M$1,Input!$G$9,Input!$J$9,Input!$D$31,Input!$B37,$L$1,$K$1) -> 0 | J37: =_xll.DBRW($B$1,Input!$D$9,Input!J$11,$M$1,Input!$G$9,Input!$J$9,Input!$D$31,Input!$B37,$L$1,$K$1) -> 0 | ... N37: =_xll.DBRW($B$1,Input!$D$9,Input!N$11,$M$1,Input!$G$9,Input!$J$9,Input!$D$31,Input!$B37,$L$1,$K$1) -> 0
B38: Local Market Price Premium [$/ton] | C38: =_xll.DBRW($B$1,Input!$D$9,Input!C$11,$M$1,Input!$G$9,Input!$J$9,Input!$D$31,Input!$B38,$L$1,$K$1) -> 474.42337 | D38: =_xll.DBRW($B$1,Input!$D$9,Input!D$11,$M$1,Input!$G$9,Input!$J$9,Input!$D$31,Input!$B38,$L$1,$K$1) -> 468.87019 | E38: =_xll.DBRW($B$1,Input!$D$9,Input!E$11,$M$1,Input!$G$9,Input!$J$9,Input!$D$31,Input!$B38,$L$1,$K$1) -> 466.54818 | F38: =_xll.DBRW($B$1,Input!$D$9,Input!F$11,$M$1,Input!$G$9,Input!$J$9,Input!$D$31,Input!$B38,$L$1,$K$1) -> 477.3484 | G38: =_xll.DBRW($B$1,Input!$D$9,Input!G$11,$M$1,Input!$G$9,Input!$J$9,Input!$D$31,Input!$B38,$L$1,$K$1) -> 490.41292 | H38: =_xll.DBRW($B$1,Input!$D$9,Input!H$11,$M$1,Input!$G$9,Input!$J$9,Input!$D$31,Input!$B38,$L$1,$K$1) -> 486.17861 | I38: =_xll.DBRW($B$1,Input!$D$9,Input!I$11,$M$1,Input!$G$9,Input!$J$9,Input!$D$31,Input!$B38,$L$1,$K$1) -> 473.00262 | J38: =_xll.DBRW($B$1,Input!$D$9,Input!J$11,$M$1,Input!$G$9,Input!$J$9,Input!$D$31,Input!$B38,$L$1,$K$1) -> 473.27297 | ... N38: =_xll.DBRW($B$1,Input!$D$9,Input!N$11,$M$1,Input!$G$9,Input!$J$9,Input!$D$31,Input!$B38,$L$1,$K$1) -> 481.59629
B39: Export Market Price Premium [$/ton] | C39: =_xll.DBRW($B$1,Input!$D$9,Input!C$11,$M$1,Input!$G$9,Input!$J$9,Input!$D$31,Input!$B39,$L$1,$K$1) -> 0 | D39: =_xll.DBRW($B$1,Input!$D$9,Input!D$11,$M$1,Input!$G$9,Input!$J$9,Input!$D$31,Input!$B39,$L$1,$K$1) -> 0 | E39: =_xll.DBRW($B$1,Input!$D$9,Input!E$11,$M$1,Input!$G$9,Input!$J$9,Input!$D$31,Input!$B39,$L$1,$K$1) -> 0 | F39: =_xll.DBRW($B$1,Input!$D$9,Input!F$11,$M$1,Input!$G$9,Input!$J$9,Input!$D$31,Input!$B39,$L$1,$K$1) -> 0 | G39: =_xll.DBRW($B$1,Input!$D$9,Input!G$11,$M$1,Input!$G$9,Input!$J$9,Input!$D$31,Input!$B39,$L$1,$K$1) -> 0 | H39: =_xll.DBRW($B$1,Input!$D$9,Input!H$11,$M$1,Input!$G$9,Input!$J$9,Input!$D$31,Input!$B39,$L$1,$K$1) -> 0 | I39: =_xll.DBRW($B$1,Input!$D$9,Input!I$11,$M$1,Input!$G$9,Input!$J$9,Input!$D$31,Input!$B39,$L$1,$K$1) -> 0 | J39: =_xll.DBRW($B$1,Input!$D$9,Input!J$11,$M$1,Input!$G$9,Input!$J$9,Input!$D$31,Input!$B39,$L$1,$K$1) -> 0 | ... N39: =_xll.DBRW($B$1,Input!$D$9,Input!N$11,$M$1,Input!$G$9,Input!$J$9,Input!$D$31,Input!$B39,$L$1,$K$1) -> 0
B40: % Operational Tax | C40: =_xll.DBRW($B$1,Input!$D$9,Input!C$11,$M$1,Input!$G$9,Input!$J$9,Input!$D$31,Input!$B40,$L$1,$K$1) -> 0.3 | D40: =_xll.DBRW($B$1,Input!$D$9,Input!D$11,$M$1,Input!$G$9,Input!$J$9,Input!$D$31,Input!$B40,$L$1,$K$1) -> 0.3 | E40: =_xll.DBRW($B$1,Input!$D$9,Input!E$11,$M$1,Input!$G$9,Input!$J$9,Input!$D$31,Input!$B40,$L$1,$K$1) -> 0.3 | F40: =_xll.DBRW($B$1,Input!$D$9,Input!F$11,$M$1,Input!$G$9,Input!$J$9,Input!$D$31,Input!$B40,$L$1,$K$1) -> 0.3 | G40: =_xll.DBRW($B$1,Input!$D$9,Input!G$11,$M$1,Input!$G$9,Input!$J$9,Input!$D$31,Input!$B40,$L$1,$K$1) -> 0.3 | H40: =_xll.DBRW($B$1,Input!$D$9,Input!H$11,$M$1,Input!$G$9,Input!$J$9,Input!$D$31,Input!$B40,$L$1,$K$1) -> 0.3 | I40: =_xll.DBRW($B$1,Input!$D$9,Input!I$11,$M$1,Input!$G$9,Input!$J$9,Input!$D$31,Input!$B40,$L$1,$K$1) -> 0.3 | J40: =_xll.DBRW($B$1,Input!$D$9,Input!J$11,$M$1,Input!$G$9,Input!$J$9,Input!$D$31,Input!$B40,$L$1,$K$1) -> 0.3 | ... N40: =_xll.DBRW($B$1,Input!$D$9,Input!N$11,$M$1,Input!$G$9,Input!$J$9,Input!$D$31,Input!$B40,$L$1,$K$1) -> 0.3
B41: Gross Revenue [$MM] | C41: =_xll.DBRW($B$2,Input!$D$9,Input!C$11,$M$1,Input!$G$9,Input!$J$9,$D$31,$K$2,$B$41) -> 92.512557 | D41: =_xll.DBRW($B$2,Input!$D$9,Input!D$11,$M$1,Input!$G$9,Input!$J$9,$D$31,$K$2,$B$41) -> 97.524999 | E41: =_xll.DBRW($B$2,Input!$D$9,Input!E$11,$M$1,Input!$G$9,Input!$J$9,$D$31,$K$2,$B$41) -> 92.90118 | F41: =_xll.DBRW($B$2,Input!$D$9,Input!F$11,$M$1,Input!$G$9,Input!$J$9,$D$31,$K$2,$B$41) -> 92.975347 | G41: =_xll.DBRW($B$2,Input!$D$9,Input!G$11,$M$1,Input!$G$9,Input!$J$9,$D$31,$K$2,$B$41) -> 99.985113 | H41: =_xll.DBRW($B$2,Input!$D$9,Input!H$11,$M$1,Input!$G$9,Input!$J$9,$D$31,$K$2,$B$41) -> 91.936929 | I41: =_xll.DBRW($B$2,Input!$D$9,Input!I$11,$M$1,Input!$G$9,Input!$J$9,$D$31,$K$2,$B$41) -> 106.90852 | J41: =_xll.DBRW($B$2,Input!$D$9,Input!J$11,$M$1,Input!$G$9,Input!$J$9,$D$31,$K$2,$B$41) -> 108.48852 | ... N41: =_xll.DBRW($B$2,Input!$D$9,Input!N$11,$M$1,Input!$G$9,Input!$J$9,$D$31,$K$2,$B$41) -> 90.544909
B42: Net Revenue [$MM] | C42: =_xll.DBRW($B$2,Input!$D$9,Input!C$11,$M$1,Input!$G$9,Input!$J$9,$D$31,$K$2,$B$42) -> 71.163505 | D42: =_xll.DBRW($B$2,Input!$D$9,Input!D$11,$M$1,Input!$G$9,Input!$J$9,$D$31,$K$2,$B$42) -> 75.01923 | E42: =_xll.DBRW($B$2,Input!$D$9,Input!E$11,$M$1,Input!$G$9,Input!$J$9,$D$31,$K$2,$B$42) -> 71.462446 | F42: =_xll.DBRW($B$2,Input!$D$9,Input!F$11,$M$1,Input!$G$9,Input!$J$9,$D$31,$K$2,$B$42) -> 71.519497 | G42: =_xll.DBRW($B$2,Input!$D$9,Input!G$11,$M$1,Input!$G$9,Input!$J$9,$D$31,$K$2,$B$42) -> 76.911626 | H42: =_xll.DBRW($B$2,Input!$D$9,Input!H$11,$M$1,Input!$G$9,Input!$J$9,$D$31,$K$2,$B$42) -> 70.720714 | I42: =_xll.DBRW($B$2,Input!$D$9,Input!I$11,$M$1,Input!$G$9,Input!$J$9,$D$31,$K$2,$B$42) -> 82.237321 | J42: =_xll.DBRW($B$2,Input!$D$9,Input!J$11,$M$1,Input!$G$9,Input!$J$9,$D$31,$K$2,$B$42) -> 83.452709 | ... N42: =_xll.DBRW($B$2,Input!$D$9,Input!N$11,$M$1,Input!$G$9,Input!$J$9,$D$31,$K$2,$B$42) -> 69.64993
C44: Products: | D44: =_xll.SUBNM("CONS_VC:ALL.D.Products","Nivel_0","PRODAG010 - Aggregates","Código e Descrição") -> PRODAG010 - Aggregates
C46: =$D$9&"."&C$11 -> 2025.01 | D46: =$D$9&"."&D11 -> 2025.02 | E46: =$D$9&"."&E11 -> 2025.03 | F46: =$D$9&"."&F11 -> 2025.04 | G46: =$D$9&"."&G11 -> 2025.05 | H46: =$D$9&"."&H11 -> 2025.06 | I46: =$D$9&"."&I11 -> 2025.07 | J46: =$D$9&"."&J11 -> 2025.08 | K46: =$D$9&"."&K11 -> 2025.09 | ... N46: =$D$9&"."&N11 -> 2025.12
B47: Reference Price [$/ton] | C47: =_xll.DBRW($B$1,Input!$D$9,Input!C$11,$M$1,Input!$G$9,Input!$J$9,$D$44,Input!$B47,$L$1,$K$1) -> 0 | D47: =_xll.DBRW($B$1,Input!$D$9,Input!D$11,$M$1,Input!$G$9,Input!$J$9,$D$44,Input!$B47,$L$1,$K$1) -> 0 | E47: =_xll.DBRW($B$1,Input!$D$9,Input!E$11,$M$1,Input!$G$9,Input!$J$9,$D$44,Input!$B47,$L$1,$K$1) -> 0 | F47: =_xll.DBRW($B$1,Input!$D$9,Input!F$11,$M$1,Input!$G$9,Input!$J$9,$D$44,Input!$B47,$L$1,$K$1) -> 0 | G47: =_xll.DBRW($B$1,Input!$D$9,Input!G$11,$M$1,Input!$G$9,Input!$J$9,$D$44,Input!$B47,$L$1,$K$1) -> 0 | H47: =_xll.DBRW($B$1,Input!$D$9,Input!H$11,$M$1,Input!$G$9,Input!$J$9,$D$44,Input!$B47,$L$1,$K$1) -> 0 | I47: =_xll.DBRW($B$1,Input!$D$9,Input!I$11,$M$1,Input!$G$9,Input!$J$9,$D$44,Input!$B47,$L$1,$K$1) -> 0 | J47: =_xll.DBRW($B$1,Input!$D$9,Input!J$11,$M$1,Input!$G$9,Input!$J$9,$D$44,Input!$B47,$L$1,$K$1) -> 0 | ... N47: =_xll.DBRW($B$1,Input!$D$9,Input!N$11,$M$1,Input!$G$9,Input!$J$9,$D$44,Input!$B47,$L$1,$K$1) -> 0
B48: Local Market Sales Volume [kt] | C48: =_xll.DBRW($B$1,Input!$D$9,Input!C$11,$M$1,Input!$G$9,Input!$J$9,$D$44,Input!$B48,$L$1,$K$1) -> 150 | D48: =_xll.DBRW($B$1,Input!$D$9,Input!D$11,$M$1,Input!$G$9,Input!$J$9,$D$44,Input!$B48,$L$1,$K$1) -> 160 | E48: =_xll.DBRW($B$1,Input!$D$9,Input!E$11,$M$1,Input!$G$9,Input!$J$9,$D$44,Input!$B48,$L$1,$K$1) -> 153.1727 | F48: =_xll.DBRW($B$1,Input!$D$9,Input!F$11,$M$1,Input!$G$9,Input!$J$9,$D$44,Input!$B48,$L$1,$K$1) -> 149.82662 | G48: =_xll.DBRW($B$1,Input!$D$9,Input!G$11,$M$1,Input!$G$9,Input!$J$9,$D$44,Input!$B48,$L$1,$K$1) -> 156.83034 | H48: =_xll.DBRW($B$1,Input!$D$9,Input!H$11,$M$1,Input!$G$9,Input!$J$9,$D$44,Input!$B48,$L$1,$K$1) -> 145.46241 | I48: =_xll.DBRW($B$1,Input!$D$9,Input!I$11,$M$1,Input!$G$9,Input!$J$9,$D$44,Input!$B48,$L$1,$K$1) -> 173.86229 | J48: =_xll.DBRW($B$1,Input!$D$9,Input!J$11,$M$1,Input!$G$9,Input!$J$9,$D$44,Input!$B48,$L$1,$K$1) -> 176.33103 | ... N48: =_xll.DBRW($B$1,Input!$D$9,Input!N$11,$M$1,Input!$G$9,Input!$J$9,$D$44,Input!$B48,$L$1,$K$1) -> 144.62306
B49: Export Market Sales Volume [kt] | C49: =_xll.DBRW($B$1,Input!$D$9,Input!C$11,$M$1,Input!$G$9,Input!$J$9,$D$44,Input!$B49,$L$1,$K$1) -> 0 | D49: =_xll.DBRW($B$1,Input!$D$9,Input!D$11,$M$1,Input!$G$9,Input!$J$9,$D$44,Input!$B49,$L$1,$K$1) -> 0 | E49: =_xll.DBRW($B$1,Input!$D$9,Input!E$11,$M$1,Input!$G$9,Input!$J$9,$D$44,Input!$B49,$L$1,$K$1) -> 0 | F49: =_xll.DBRW($B$1,Input!$D$9,Input!F$11,$M$1,Input!$G$9,Input!$J$9,$D$44,Input!$B49,$L$1,$K$1) -> 0 | G49: =_xll.DBRW($B$1,Input!$D$9,Input!G$11,$M$1,Input!$G$9,Input!$J$9,$D$44,Input!$B49,$L$1,$K$1) -> 0 | H49: =_xll.DBRW($B$1,Input!$D$9,Input!H$11,$M$1,Input!$G$9,Input!$J$9,$D$44,Input!$B49,$L$1,$K$1) -> 0 | I49: =_xll.DBRW($B$1,Input!$D$9,Input!I$11,$M$1,Input!$G$9,Input!$J$9,$D$44,Input!$B49,$L$1,$K$1) -> 0 | J49: =_xll.DBRW($B$1,Input!$D$9,Input!J$11,$M$1,Input!$G$9,Input!$J$9,$D$44,Input!$B49,$L$1,$K$1) -> 0 | ... N49: =_xll.DBRW($B$1,Input!$D$9,Input!N$11,$M$1,Input!$G$9,Input!$J$9,$D$44,Input!$B49,$L$1,$K$1) -> 0
B50: Third Part Sales Volume [kt] | C50: =_xll.DBRW($B$1,Input!$D$9,Input!C$11,$M$1,Input!$G$9,Input!$J$9,$D$44,Input!$B50,$L$1,$K$1) -> 0 | D50: =_xll.DBRW($B$1,Input!$D$9,Input!D$11,$M$1,Input!$G$9,Input!$J$9,$D$44,Input!$B50,$L$1,$K$1) -> 0 | E50: =_xll.DBRW($B$1,Input!$D$9,Input!E$11,$M$1,Input!$G$9,Input!$J$9,$D$44,Input!$B50,$L$1,$K$1) -> 0 | F50: =_xll.DBRW($B$1,Input!$D$9,Input!F$11,$M$1,Input!$G$9,Input!$J$9,$D$44,Input!$B50,$L$1,$K$1) -> 0 | G50: =_xll.DBRW($B$1,Input!$D$9,Input!G$11,$M$1,Input!$G$9,Input!$J$9,$D$44,Input!$B50,$L$1,$K$1) -> 0 | H50: =_xll.DBRW($B$1,Input!$D$9,Input!H$11,$M$1,Input!$G$9,Input!$J$9,$D$44,Input!$B50,$L$1,$K$1) -> 0 | I50: =_xll.DBRW($B$1,Input!$D$9,Input!I$11,$M$1,Input!$G$9,Input!$J$9,$D$44,Input!$B50,$L$1,$K$1) -> 0 | J50: =_xll.DBRW($B$1,Input!$D$9,Input!J$11,$M$1,Input!$G$9,Input!$J$9,$D$44,Input!$B50,$L$1,$K$1) -> 0 | ... N50: =_xll.DBRW($B$1,Input!$D$9,Input!N$11,$M$1,Input!$G$9,Input!$J$9,$D$44,Input!$B50,$L$1,$K$1) -> 0
B51: Local Market Price Premium [$/ton] | C51: =_xll.DBRW($B$1,Input!$D$9,Input!C$11,$M$1,Input!$G$9,Input!$J$9,$D$44,Input!$B51,$L$1,$K$1) -> 474.42337 | D51: =_xll.DBRW($B$1,Input!$D$9,Input!D$11,$M$1,Input!$G$9,Input!$J$9,$D$44,Input!$B51,$L$1,$K$1) -> 468.87019 | E51: =_xll.DBRW($B$1,Input!$D$9,Input!E$11,$M$1,Input!$G$9,Input!$J$9,$D$44,Input!$B51,$L$1,$K$1) -> 466.54818 | F51: =_xll.DBRW($B$1,Input!$D$9,Input!F$11,$M$1,Input!$G$9,Input!$J$9,$D$44,Input!$B51,$L$1,$K$1) -> 477.3484 | G51: =_xll.DBRW($B$1,Input!$D$9,Input!G$11,$M$1,Input!$G$9,Input!$J$9,$D$44,Input!$B51,$L$1,$K$1) -> 490.41292 | H51: =_xll.DBRW($B$1,Input!$D$9,Input!H$11,$M$1,Input!$G$9,Input!$J$9,$D$44,Input!$B51,$L$1,$K$1) -> 486.17861 | I51: =_xll.DBRW($B$1,Input!$D$9,Input!I$11,$M$1,Input!$G$9,Input!$J$9,$D$44,Input!$B51,$L$1,$K$1) -> 473.00262 | J51: =_xll.DBRW($B$1,Input!$D$9,Input!J$11,$M$1,Input!$G$9,Input!$J$9,$D$44,Input!$B51,$L$1,$K$1) -> 473.27297 | ... N51: =_xll.DBRW($B$1,Input!$D$9,Input!N$11,$M$1,Input!$G$9,Input!$J$9,$D$44,Input!$B51,$L$1,$K$1) -> 481.59629
B52: Export Market Price Premium [$/ton] | C52: =_xll.DBRW($B$1,Input!$D$9,Input!C$11,$M$1,Input!$G$9,Input!$J$9,$D$44,Input!$B52,$L$1,$K$1) -> 0 | D52: =_xll.DBRW($B$1,Input!$D$9,Input!D$11,$M$1,Input!$G$9,Input!$J$9,$D$44,Input!$B52,$L$1,$K$1) -> 0 | E52: =_xll.DBRW($B$1,Input!$D$9,Input!E$11,$M$1,Input!$G$9,Input!$J$9,$D$44,Input!$B52,$L$1,$K$1) -> 0 | F52: =_xll.DBRW($B$1,Input!$D$9,Input!F$11,$M$1,Input!$G$9,Input!$J$9,$D$44,Input!$B52,$L$1,$K$1) -> 0 | G52: =_xll.DBRW($B$1,Input!$D$9,Input!G$11,$M$1,Input!$G$9,Input!$J$9,$D$44,Input!$B52,$L$1,$K$1) -> 0 | H52: =_xll.DBRW($B$1,Input!$D$9,Input!H$11,$M$1,Input!$G$9,Input!$J$9,$D$44,Input!$B52,$L$1,$K$1) -> 0 | I52: =_xll.DBRW($B$1,Input!$D$9,Input!I$11,$M$1,Input!$G$9,Input!$J$9,$D$44,Input!$B52,$L$1,$K$1) -> 0 | J52: =_xll.DBRW($B$1,Input!$D$9,Input!J$11,$M$1,Input!$G$9,Input!$J$9,$D$44,Input!$B52,$L$1,$K$1) -> 0 | ... N52: =_xll.DBRW($B$1,Input!$D$9,Input!N$11,$M$1,Input!$G$9,Input!$J$9,$D$44,Input!$B52,$L$1,$K$1) -> 0
B53: % Operational Tax | C53: =_xll.DBRW($B$1,Input!$D$9,Input!C$11,$M$1,Input!$G$9,Input!$J$9,$D$44,Input!$B53,$L$1,$K$1) -> 0.3 | D53: =_xll.DBRW($B$1,Input!$D$9,Input!D$11,$M$1,Input!$G$9,Input!$J$9,$D$44,Input!$B53,$L$1,$K$1) -> 0.3 | E53: =_xll.DBRW($B$1,Input!$D$9,Input!E$11,$M$1,Input!$G$9,Input!$J$9,$D$44,Input!$B53,$L$1,$K$1) -> 0.3 | F53: =_xll.DBRW($B$1,Input!$D$9,Input!F$11,$M$1,Input!$G$9,Input!$J$9,$D$44,Input!$B53,$L$1,$K$1) -> 0.3 | G53: =_xll.DBRW($B$1,Input!$D$9,Input!G$11,$M$1,Input!$G$9,Input!$J$9,$D$44,Input!$B53,$L$1,$K$1) -> 0.3 | H53: =_xll.DBRW($B$1,Input!$D$9,Input!H$11,$M$1,Input!$G$9,Input!$J$9,$D$44,Input!$B53,$L$1,$K$1) -> 0.3 | I53: =_xll.DBRW($B$1,Input!$D$9,Input!I$11,$M$1,Input!$G$9,Input!$J$9,$D$44,Input!$B53,$L$1,$K$1) -> 0.3 | J53: =_xll.DBRW($B$1,Input!$D$9,Input!J$11,$M$1,Input!$G$9,Input!$J$9,$D$44,Input!$B53,$L$1,$K$1) -> 0.3 | ... N53: =_xll.DBRW($B$1,Input!$D$9,Input!N$11,$M$1,Input!$G$9,Input!$J$9,$D$44,Input!$B53,$L$1,$K$1) -> 0.3
B54: Gross Revenue [$MM] | C54: =_xll.DBRW($B$2,Input!$D$9,Input!C$11,$M$1,Input!$G$9,Input!$J$9,$D$44,$K$2,$B$54) -> 92.512557 | D54: =_xll.DBRW($B$2,Input!$D$9,Input!D$11,$M$1,Input!$G$9,Input!$J$9,$D$44,$K$2,$B$54) -> 97.524999 | E54: =_xll.DBRW($B$2,Input!$D$9,Input!E$11,$M$1,Input!$G$9,Input!$J$9,$D$44,$K$2,$B$54) -> 92.90118 | F54: =_xll.DBRW($B$2,Input!$D$9,Input!F$11,$M$1,Input!$G$9,Input!$J$9,$D$44,$K$2,$B$54) -> 92.975347 | G54: =_xll.DBRW($B$2,Input!$D$9,Input!G$11,$M$1,Input!$G$9,Input!$J$9,$D$44,$K$2,$B$54) -> 99.985113 | H54: =_xll.DBRW($B$2,Input!$D$9,Input!H$11,$M$1,Input!$G$9,Input!$J$9,$D$44,$K$2,$B$54) -> 91.936929 | I54: =_xll.DBRW($B$2,Input!$D$9,Input!I$11,$M$1,Input!$G$9,Input!$J$9,$D$44,$K$2,$B$54) -> 106.90852 | J54: =_xll.DBRW($B$2,Input!$D$9,Input!J$11,$M$1,Input!$G$9,Input!$J$9,$D$44,$K$2,$B$54) -> 108.48852 | ... N54: =_xll.DBRW($B$2,Input!$D$9,Input!N$11,$M$1,Input!$G$9,Input!$J$9,$D$44,$K$2,$B$54) -> 90.544909
B55: Net Revenue [$MM] | C55: =_xll.DBRW($B$2,Input!$D$9,Input!C$11,$M$1,Input!$G$9,Input!$J$9,$D$44,$K$2,$B$55) -> 71.163505 | D55: =_xll.DBRW($B$2,Input!$D$9,Input!D$11,$M$1,Input!$G$9,Input!$J$9,$D$44,$K$2,$B$55) -> 75.01923 | E55: =_xll.DBRW($B$2,Input!$D$9,Input!E$11,$M$1,Input!$G$9,Input!$J$9,$D$44,$K$2,$B$55) -> 71.462446 | F55: =_xll.DBRW($B$2,Input!$D$9,Input!F$11,$M$1,Input!$G$9,Input!$J$9,$D$44,$K$2,$B$55) -> 71.519497 | G55: =_xll.DBRW($B$2,Input!$D$9,Input!G$11,$M$1,Input!$G$9,Input!$J$9,$D$44,$K$2,$B$55) -> 76.911626 | H55: =_xll.DBRW($B$2,Input!$D$9,Input!H$11,$M$1,Input!$G$9,Input!$J$9,$D$44,$K$2,$B$55) -> 70.720714 | I55: =_xll.DBRW($B$2,Input!$D$9,Input!I$11,$M$1,Input!$G$9,Input!$J$9,$D$44,$K$2,$B$55) -> 82.237321 | J55: =_xll.DBRW($B$2,Input!$D$9,Input!J$11,$M$1,Input!$G$9,Input!$J$9,$D$44,$K$2,$B$55) -> 83.452709 | ... N55: =_xll.DBRW($B$2,Input!$D$9,Input!N$11,$M$1,Input!$G$9,Input!$J$9,$D$44,$K$2,$B$55) -> 69.64993
B59: CONTRIBUTION MARGIN
C60: Products: | D60: =_xll.SUBNM("CONS_VC:ALL.D.Products",,"Total Products","Código e Descrição") -> Total Products
C62: =$D$9&"."&C$11 -> 2025.01 | D62: =$D$9&"."&D$11 -> 2025.02 | E62: =$D$9&"."&E$11 -> 2025.03 | F62: =$D$9&"."&F$11 -> 2025.04 | G62: =$D$9&"."&G$11 -> 2025.05 | H62: =$D$9&"."&H$11 -> 2025.06 | I62: =$D$9&"."&I$11 -> 2025.07 | J62: =$D$9&"."&J$11 -> 2025.08 | ... N62: =$D$9&"."&N$11 -> 2025.12
B63: Final Variable Sales Expenses | C63: =_xll.DBRW($B$1,Input!$D$9,Input!C$11,$M$1,Input!$G$9,Input!$J$9,$N$1,Input!$B63,$L$1,$K$1) -> 168.7595 | D63: =_xll.DBRW($B$1,Input!$D$9,Input!D$11,$M$1,Input!$G$9,Input!$J$9,$N$1,Input!$B63,$L$1,$K$1) -> 164.15152 | E63: =_xll.DBRW($B$1,Input!$D$9,Input!E$11,$M$1,Input!$G$9,Input!$J$9,$N$1,Input!$B63,$L$1,$K$1) -> 176.63658 | F63: =_xll.DBRW($B$1,Input!$D$9,Input!F$11,$M$1,Input!$G$9,Input!$J$9,$N$1,Input!$B63,$L$1,$K$1) -> 172.40642 | G63: =_xll.DBRW($B$1,Input!$D$9,Input!G$11,$M$1,Input!$G$9,Input!$J$9,$N$1,Input!$B63,$L$1,$K$1) -> 193.13237 | H63: =_xll.DBRW($B$1,Input!$D$9,Input!H$11,$M$1,Input!$G$9,Input!$J$9,$N$1,Input!$B63,$L$1,$K$1) -> 180.51235 | I63: =_xll.DBRW($B$1,Input!$D$9,Input!I$11,$M$1,Input!$G$9,Input!$J$9,$N$1,Input!$B63,$L$1,$K$1) -> 213.29097 | J63: =_xll.DBRW($B$1,Input!$D$9,Input!J$11,$M$1,Input!$G$9,Input!$J$9,$N$1,Input!$B63,$L$1,$K$1) -> 206.37441 | ... N63: =_xll.DBRW($B$1,Input!$D$9,Input!N$11,$M$1,Input!$G$9,Input!$J$9,$N$1,Input!$B63,$L$1,$K$1) -> 165.64817
B64: Other Variable Costs | C64: =_xll.DBSW(#REF!,$B$1,Input!$D$9,Input!C$11,$M$1,Input!$G$9,Input!$J$9,$N$1,Input!$B64,$L$1,$K$1) -> 95 | D64: =_xll.DBRW($B$1,Input!$D$9,Input!D$11,$M$1,Input!$G$9,Input!$J$9,$N$1,Input!$B64,$L$1,$K$1) -> 515.19376 | E64: =_xll.DBRW($B$1,Input!$D$9,Input!E$11,$M$1,Input!$G$9,Input!$J$9,$N$1,Input!$B64,$L$1,$K$1) -> 556.9112 | F64: =_xll.DBRW($B$1,Input!$D$9,Input!F$11,$M$1,Input!$G$9,Input!$J$9,$N$1,Input!$B64,$L$1,$K$1) -> 536.80996 | G64: =_xll.DBRW($B$1,Input!$D$9,Input!G$11,$M$1,Input!$G$9,Input!$J$9,$N$1,Input!$B64,$L$1,$K$1) -> 588.73485 | H64: =_xll.DBRW($B$1,Input!$D$9,Input!H$11,$M$1,Input!$G$9,Input!$J$9,$N$1,Input!$B64,$L$1,$K$1) -> 562.46326 | I64: =_xll.DBRW($B$1,Input!$D$9,Input!I$11,$M$1,Input!$G$9,Input!$J$9,$N$1,Input!$B64,$L$1,$K$1) -> 637.9055 | J64: =_xll.DBRW($B$1,Input!$D$9,Input!J$11,$M$1,Input!$G$9,Input!$J$9,$N$1,Input!$B64,$L$1,$K$1) -> 645.98212 | K64: =_xll.DBRW($B$1,Input!$D$9,Input!K$11,$M$1,Input!$G$9,Input!$J$9,$N$1,Input!$B64,$L$1,$K$1) -> 637.24578 | ... N64: =_xll.DBRW($B$1,Input!$D$9,Input!N$11,$M$1,Input!$G$9,Input!$J$9,$N$1,Input!$B64,$L$1,$K$1) -> 465.30253
B65: Fixed Costs | C65: =_xll.DBRW($B$1,Input!$D$9,Input!C$11,$M$1,Input!$G$9,Input!$J$9,$N$1,Input!$B65,$L$1,$K$1) -> 167.32801 | D65: =_xll.DBRW($B$1,Input!$D$9,Input!D$11,$M$1,Input!$G$9,Input!$J$9,$N$1,Input!$B65,$L$1,$K$1) -> 175.37425 | E65: =_xll.DBRW($B$1,Input!$D$9,Input!E$11,$M$1,Input!$G$9,Input!$J$9,$N$1,Input!$B65,$L$1,$K$1) -> 183.54922 | F65: =_xll.DBRW($B$1,Input!$D$9,Input!F$11,$M$1,Input!$G$9,Input!$J$9,$N$1,Input!$B65,$L$1,$K$1) -> 176.89449 | G65: =_xll.DBRW($B$1,Input!$D$9,Input!G$11,$M$1,Input!$G$9,Input!$J$9,$N$1,Input!$B65,$L$1,$K$1) -> 194.8486 | H65: =_xll.DBRW($B$1,Input!$D$9,Input!H$11,$M$1,Input!$G$9,Input!$J$9,$N$1,Input!$B65,$L$1,$K$1) -> 171.53715 | I65: =_xll.DBRW($B$1,Input!$D$9,Input!I$11,$M$1,Input!$G$9,Input!$J$9,$N$1,Input!$B65,$L$1,$K$1) -> 177.54011 | J65: =_xll.DBRW($B$1,Input!$D$9,Input!J$11,$M$1,Input!$G$9,Input!$J$9,$N$1,Input!$B65,$L$1,$K$1) -> 156.42842 | ... N65: =_xll.DBRW($B$1,Input!$D$9,Input!N$11,$M$1,Input!$G$9,Input!$J$9,$N$1,Input!$B65,$L$1,$K$1) -> 122.75516
B66: Operating Expenses | C66: =_xll.DBRW($B$1,Input!$D$9,Input!C$11,$M$1,Input!$G$9,Input!$J$9,$N$1,Input!$B66,$L$1,$K$1) -> 93.594604 | D66: =_xll.DBRW($B$1,Input!$D$9,Input!D$11,$M$1,Input!$G$9,Input!$J$9,$N$1,Input!$B66,$L$1,$K$1) -> 119.715 | E66: =_xll.DBRW($B$1,Input!$D$9,Input!E$11,$M$1,Input!$G$9,Input!$J$9,$N$1,Input!$B66,$L$1,$K$1) -> 99.091998 | F66: =_xll.DBRW($B$1,Input!$D$9,Input!F$11,$M$1,Input!$G$9,Input!$J$9,$N$1,Input!$B66,$L$1,$K$1) -> 109.75508 | G66: =_xll.DBRW($B$1,Input!$D$9,Input!G$11,$M$1,Input!$G$9,Input!$J$9,$N$1,Input!$B66,$L$1,$K$1) -> 86.904565 | H66: =_xll.DBRW($B$1,Input!$D$9,Input!H$11,$M$1,Input!$G$9,Input!$J$9,$N$1,Input!$B66,$L$1,$K$1) -> 110.68604 | I66: =_xll.DBRW($B$1,Input!$D$9,Input!I$11,$M$1,Input!$G$9,Input!$J$9,$N$1,Input!$B66,$L$1,$K$1) -> 129.7434 | J66: =_xll.DBRW($B$1,Input!$D$9,Input!J$11,$M$1,Input!$G$9,Input!$J$9,$N$1,Input!$B66,$L$1,$K$1) -> 116.54886 | ... N66: =_xll.DBRW($B$1,Input!$D$9,Input!N$11,$M$1,Input!$G$9,Input!$J$9,$N$1,Input!$B66,$L$1,$K$1) -> 112.64238
B67: Other | C67: =_xll.DBRW($B$1,Input!$D$9,Input!C$11,$M$1,Input!$G$9,Input!$J$9,$N$1,Input!$B67,$L$1,$K$1) -> 0 | D67: =_xll.DBRW($B$1,Input!$D$9,Input!D$11,$M$1,Input!$G$9,Input!$J$9,$N$1,Input!$B67,$L$1,$K$1) -> 0 | E67: =_xll.DBRW($B$1,Input!$D$9,Input!E$11,$M$1,Input!$G$9,Input!$J$9,$N$1,Input!$B67,$L$1,$K$1) -> 0 | F67: =_xll.DBRW($B$1,Input!$D$9,Input!F$11,$M$1,Input!$G$9,Input!$J$9,$N$1,Input!$B67,$L$1,$K$1) -> 0 | G67: =_xll.DBRW($B$1,Input!$D$9,Input!G$11,$M$1,Input!$G$9,Input!$J$9,$N$1,Input!$B67,$L$1,$K$1) -> 0 | H67: =_xll.DBRW($B$1,Input!$D$9,Input!H$11,$M$1,Input!$G$9,Input!$J$9,$N$1,Input!$B67,$L$1,$K$1) -> 0 | I67: =_xll.DBRW($B$1,Input!$D$9,Input!I$11,$M$1,Input!$G$9,Input!$J$9,$N$1,Input!$B67,$L$1,$K$1) -> 0 | J67: =_xll.DBRW($B$1,Input!$D$9,Input!J$11,$M$1,Input!$G$9,Input!$J$9,$N$1,Input!$B67,$L$1,$K$1) -> 0 | ... N67: =_xll.DBRW($B$1,Input!$D$9,Input!N$11,$M$1,Input!$G$9,Input!$J$9,$N$1,Input!$B67,$L$1,$K$1) -> 0
B68: EBITDA | C68: =_xll.DBRW($B$3,Input!$D$9,Input!C$11,$M$1,Input!$G$9,Input!$J$9,$D$60,Input!$B68,$K$1) -> 596.32421 | D68: =_xll.DBRW($B$3,Input!$D$9,Input!D$11,$M$1,Input!$G$9,Input!$J$9,$D$60,Input!$B68,$K$1) -> 116.2034 | E68: =_xll.DBRW($B$3,Input!$D$9,Input!E$11,$M$1,Input!$G$9,Input!$J$9,$D$60,Input!$B68,$K$1) -> 184.49262 | F68: =_xll.DBRW($B$3,Input!$D$9,Input!F$11,$M$1,Input!$G$9,Input!$J$9,$D$60,Input!$B68,$K$1) -> 170.51662 | G68: =_xll.DBRW($B$3,Input!$D$9,Input!G$11,$M$1,Input!$G$9,Input!$J$9,$D$60,Input!$B68,$K$1) -> 206.56333 | H68: =_xll.DBRW($B$3,Input!$D$9,Input!H$11,$M$1,Input!$G$9,Input!$J$9,$D$60,Input!$B68,$K$1) -> 177.86994 | I68: =_xll.DBRW($B$3,Input!$D$9,Input!I$11,$M$1,Input!$G$9,Input!$J$9,$D$60,Input!$B68,$K$1) -> 276.53016 | J68: =_xll.DBRW($B$3,Input!$D$9,Input!J$11,$M$1,Input!$G$9,Input!$J$9,$D$60,Input!$B68,$K$1) -> 325.7324 | ... N68: =_xll.DBRW($B$3,Input!$D$9,Input!N$11,$M$1,Input!$G$9,Input!$J$9,$D$60,Input!$B68,$K$1) -> 284.79111
B71: Operating Profit
C73: =$D$9&"."&C$11 -> 2025.01 | D73: =$D$9&"."&D$11 -> 2025.02 | E73: =$D$9&"."&E$11 -> 2025.03 | F73: =$D$9&"."&F$11 -> 2025.04 | G73: =$D$9&"."&G$11 -> 2025.05 | H73: =$D$9&"."&H$11 -> 2025.06 | I73: =$D$9&"."&I$11 -> 2025.07 | J73: =$D$9&"."&J$11 -> 2025.08 | ... N73: =$D$9&"."&N$11 -> 2025.12
B74: Depreciation / amortization / depletion - Corporate | C74: =_xll.DBRW($B$1,Input!$D$9,Input!C$11,$M$1,Input!$G$9,Input!$J$9,$N$1,Input!$B74,$L$1,$K$1) -> 89.445895 | D74: =_xll.DBRW($B$1,Input!$D$9,Input!D$11,$M$1,Input!$G$9,Input!$J$9,$N$1,Input!$B74,$L$1,$K$1) -> 202.3497 | E74: =_xll.DBRW($B$1,Input!$D$9,Input!E$11,$M$1,Input!$G$9,Input!$J$9,$N$1,Input!$B74,$L$1,$K$1) -> 93.431534 | F74: =_xll.DBRW($B$1,Input!$D$9,Input!F$11,$M$1,Input!$G$9,Input!$J$9,$N$1,Input!$B74,$L$1,$K$1) -> 91.031849 | G74: =_xll.DBRW($B$1,Input!$D$9,Input!G$11,$M$1,Input!$G$9,Input!$J$9,$N$1,Input!$B74,$L$1,$K$1) -> 96.52127 | H74: =_xll.DBRW($B$1,Input!$D$9,Input!H$11,$M$1,Input!$G$9,Input!$J$9,$N$1,Input!$B74,$L$1,$K$1) -> 97.935037 | I74: =_xll.DBRW($B$1,Input!$D$9,Input!I$11,$M$1,Input!$G$9,Input!$J$9,$N$1,Input!$B74,$L$1,$K$1) -> 106.95223 | J74: =_xll.DBRW($B$1,Input!$D$9,Input!J$11,$M$1,Input!$G$9,Input!$J$9,$N$1,Input!$B74,$L$1,$K$1) -> 105.446 | ... N74: =_xll.DBRW($B$1,Input!$D$9,Input!N$11,$M$1,Input!$G$9,Input!$J$9,$N$1,Input!$B74,$L$1,$K$1) -> 105.7136
B75: EBITDA | C75: =_xll.DBRW($B$3,Input!$D$9,Input!C$11,$M$1,Input!$G$9,Input!$J$9,$D$60,Input!$B75,$K$1) -> 596.32421 | D75: =_xll.DBRW($B$3,Input!$D$9,Input!D$11,$M$1,Input!$G$9,Input!$J$9,$D$60,Input!$B75,$K$1) -> 116.2034 | E75: =_xll.DBRW($B$3,Input!$D$9,Input!E$11,$M$1,Input!$G$9,Input!$J$9,$D$60,Input!$B75,$K$1) -> 184.49262 | F75: =_xll.DBRW($B$3,Input!$D$9,Input!F$11,$M$1,Input!$G$9,Input!$J$9,$D$60,Input!$B75,$K$1) -> 170.51662 | G75: =_xll.DBRW($B$3,Input!$D$9,Input!G$11,$M$1,Input!$G$9,Input!$J$9,$D$60,Input!$B75,$K$1) -> 206.56333 | H75: =_xll.DBRW($B$3,Input!$D$9,Input!H$11,$M$1,Input!$G$9,Input!$J$9,$D$60,Input!$B75,$K$1) -> 177.86994 | I75: =_xll.DBRW($B$3,Input!$D$9,Input!I$11,$M$1,Input!$G$9,Input!$J$9,$D$60,Input!$B75,$K$1) -> 276.53016 | J75: =_xll.DBRW($B$3,Input!$D$9,Input!J$11,$M$1,Input!$G$9,Input!$J$9,$D$60,Input!$B75,$K$1) -> 325.7324 | ... N75: =_xll.DBRW($B$3,Input!$D$9,Input!N$11,$M$1,Input!$G$9,Input!$J$9,$D$60,Input!$B75,$K$1) -> 284.79111
B76: Operating Profit | C76: =_xll.DBRW($B$3,Input!$D$9,Input!C$11,$M$1,Input!$G$9,Input!$J$9,$D$60,Input!$B76,$K$1) -> 506.87831 | D76: =_xll.DBRW($B$3,Input!$D$9,Input!D$11,$M$1,Input!$G$9,Input!$J$9,$D$60,Input!$B76,$K$1) -> -86.146296 | E76: =_xll.DBRW($B$3,Input!$D$9,Input!E$11,$M$1,Input!$G$9,Input!$J$9,$D$60,Input!$B76,$K$1) -> 91.061082 | F76: =_xll.DBRW($B$3,Input!$D$9,Input!F$11,$M$1,Input!$G$9,Input!$J$9,$D$60,Input!$B76,$K$1) -> 79.484771 | G76: =_xll.DBRW($B$3,Input!$D$9,Input!G$11,$M$1,Input!$G$9,Input!$J$9,$D$60,Input!$B76,$K$1) -> 110.04206 | H76: =_xll.DBRW($B$3,Input!$D$9,Input!H$11,$M$1,Input!$G$9,Input!$J$9,$D$60,Input!$B76,$K$1) -> 79.934901 | I76: =_xll.DBRW($B$3,Input!$D$9,Input!I$11,$M$1,Input!$G$9,Input!$J$9,$D$60,Input!$B76,$K$1) -> 169.57793 | J76: =_xll.DBRW($B$3,Input!$D$9,Input!J$11,$M$1,Input!$G$9,Input!$J$9,$D$60,Input!$B76,$K$1) -> 220.2864 | ... N76: =_xll.DBRW($B$3,Input!$D$9,Input!N$11,$M$1,Input!$G$9,Input!$J$9,$D$60,Input!$B76,$K$1) -> 179.07751
B79: Profit Before Income Tax
C81: =$D$9&"."&C$11 -> 2025.01 | D81: =$D$9&"."&D$11 -> 2025.02 | E81: =$D$9&"."&E$11 -> 2025.03 | F81: =$D$9&"."&F$11 -> 2025.04 | G81: =$D$9&"."&G$11 -> 2025.05 | H81: =$D$9&"."&H$11 -> 2025.06 | I81: =$D$9&"."&I$11 -> 2025.07 | J81: =$D$9&"."&J$11 -> 2025.08 | ... N81: =$D$9&"."&N$11 -> 2025.12
B82: Equity Pick-Up Results | C82: =_xll.DBRW($B$1,Input!$D$9,Input!C$11,$M$1,Input!$G$9,Input!$J$9,$N$1,Input!$B82,$L$1,$K$1) -> 0.99 | D82: =_xll.DBRW($B$1,Input!$D$9,Input!D$11,$M$1,Input!$G$9,Input!$J$9,$N$1,Input!$B82,$L$1,$K$1) -> 0.84 | E82: =_xll.DBRW($B$1,Input!$D$9,Input!E$11,$M$1,Input!$G$9,Input!$J$9,$N$1,Input!$B82,$L$1,$K$1) -> 1.23 | F82: =_xll.DBRW($B$1,Input!$D$9,Input!F$11,$M$1,Input!$G$9,Input!$J$9,$N$1,Input!$B82,$L$1,$K$1) -> -0.82414216 | G82: =_xll.DBRW($B$1,Input!$D$9,Input!G$11,$M$1,Input!$G$9,Input!$J$9,$N$1,Input!$B82,$L$1,$K$1) -> -0.47566965 | H82: =_xll.DBRW($B$1,Input!$D$9,Input!H$11,$M$1,Input!$G$9,Input!$J$9,$N$1,Input!$B82,$L$1,$K$1) -> -0.048143072 | I82: =_xll.DBRW($B$1,Input!$D$9,Input!I$11,$M$1,Input!$G$9,Input!$J$9,$N$1,Input!$B82,$L$1,$K$1) -> -0.64218542 | J82: =_xll.DBRW($B$1,Input!$D$9,Input!J$11,$M$1,Input!$G$9,Input!$J$9,$N$1,Input!$B82,$L$1,$K$1) -> -0.64218542 | ... N82: =_xll.DBRW($B$1,Input!$D$9,Input!N$11,$M$1,Input!$G$9,Input!$J$9,$N$1,Input!$B82,$L$1,$K$1) -> -0.64218542
B83: Other Non Operating Results | C83: =_xll.DBRW($B$1,Input!$D$9,Input!C$11,$M$1,Input!$G$9,Input!$J$9,$N$1,Input!$B83,$L$1,$K$1) -> 0 | D83: =_xll.DBRW($B$1,Input!$D$9,Input!D$11,$M$1,Input!$G$9,Input!$J$9,$N$1,Input!$B83,$L$1,$K$1) -> 0 | E83: =_xll.DBRW($B$1,Input!$D$9,Input!E$11,$M$1,Input!$G$9,Input!$J$9,$N$1,Input!$B83,$L$1,$K$1) -> 0 | F83: =_xll.DBRW($B$1,Input!$D$9,Input!F$11,$M$1,Input!$G$9,Input!$J$9,$N$1,Input!$B83,$L$1,$K$1) -> 0 | G83: =_xll.DBRW($B$1,Input!$D$9,Input!G$11,$M$1,Input!$G$9,Input!$J$9,$N$1,Input!$B83,$L$1,$K$1) -> 0 | H83: =_xll.DBRW($B$1,Input!$D$9,Input!H$11,$M$1,Input!$G$9,Input!$J$9,$N$1,Input!$B83,$L$1,$K$1) -> 0 | I83: =_xll.DBRW($B$1,Input!$D$9,Input!I$11,$M$1,Input!$G$9,Input!$J$9,$N$1,Input!$B83,$L$1,$K$1) -> 0 | J83: =_xll.DBRW($B$1,Input!$D$9,Input!J$11,$M$1,Input!$G$9,Input!$J$9,$N$1,Input!$B83,$L$1,$K$1) -> 0 | ... N83: =_xll.DBRW($B$1,Input!$D$9,Input!N$11,$M$1,Input!$G$9,Input!$J$9,$N$1,Input!$B83,$L$1,$K$1) -> 0
B84: Financial Results | C84: =_xll.DBRW($B$3,Input!$D$9,Input!C$11,$M$1,Input!$G$9,Input!$J$9,$D$60,Input!$B84,$K$1) -> -144.99224 | D84: =_xll.DBRW($B$3,Input!$D$9,Input!D$11,$M$1,Input!$G$9,Input!$J$9,$D$60,Input!$B84,$K$1) -> -58.168853 | E84: =_xll.DBRW($B$3,Input!$D$9,Input!E$11,$M$1,Input!$G$9,Input!$J$9,$D$60,Input!$B84,$K$1) -> -104.66724 | F84: =_xll.DBRW($B$3,Input!$D$9,Input!F$11,$M$1,Input!$G$9,Input!$J$9,$D$60,Input!$B84,$K$1) -> -86.984799 | G84: =_xll.DBRW($B$3,Input!$D$9,Input!G$11,$M$1,Input!$G$9,Input!$J$9,$D$60,Input!$B84,$K$1) -> -99.399761 | H84: =_xll.DBRW($B$3,Input!$D$9,Input!H$11,$M$1,Input!$G$9,Input!$J$9,$D$60,Input!$B84,$K$1) -> -178.72349 | I84: =_xll.DBRW($B$3,Input!$D$9,Input!I$11,$M$1,Input!$G$9,Input!$J$9,$D$60,Input!$B84,$K$1) -> -72.368867 | J84: =_xll.DBRW($B$3,Input!$D$9,Input!J$11,$M$1,Input!$G$9,Input!$J$9,$D$60,Input!$B84,$K$1) -> -90.383311 | ... N84: =_xll.DBRW($B$3,Input!$D$9,Input!N$11,$M$1,Input!$G$9,Input!$J$9,$D$60,Input!$B84,$K$1) -> -95.271235
B85: Profit Before Income Tax | C85: =_xll.DBRW($B$3,Input!$D$9,Input!C$11,$M$1,Input!$G$9,Input!$J$9,$D$60,Input!$B85,$K$1) -> 362.87607 | D85: =_xll.DBRW($B$3,Input!$D$9,Input!D$11,$M$1,Input!$G$9,Input!$J$9,$D$60,Input!$B85,$K$1) -> -143.47515 | E85: =_xll.DBRW($B$3,Input!$D$9,Input!E$11,$M$1,Input!$G$9,Input!$J$9,$D$60,Input!$B85,$K$1) -> -12.376155 | F85: =_xll.DBRW($B$3,Input!$D$9,Input!F$11,$M$1,Input!$G$9,Input!$J$9,$D$60,Input!$B85,$K$1) -> -8.3241693 | G85: =_xll.DBRW($B$3,Input!$D$9,Input!G$11,$M$1,Input!$G$9,Input!$J$9,$D$60,Input!$B85,$K$1) -> 10.166633 | H85: =_xll.DBRW($B$3,Input!$D$9,Input!H$11,$M$1,Input!$G$9,Input!$J$9,$D$60,Input!$B85,$K$1) -> -98.836737 | I85: =_xll.DBRW($B$3,Input!$D$9,Input!I$11,$M$1,Input!$G$9,Input!$J$9,$D$60,Input!$B85,$K$1) -> 96.56688 | J85: =_xll.DBRW($B$3,Input!$D$9,Input!J$11,$M$1,Input!$G$9,Input!$J$9,$D$60,Input!$B85,$K$1) -> 129.2609 | ... N85: =_xll.DBRW($B$3,Input!$D$9,Input!N$11,$M$1,Input!$G$9,Input!$J$9,$D$60,Input!$B85,$K$1) -> 83.164091
B88: Net Profit Before Minority Int.
C90: =$D$9&"."&C$11 -> 2025.01 | D90: =$D$9&"."&D$11 -> 2025.02 | E90: =$D$9&"."&E$11 -> 2025.03 | F90: =$D$9&"."&F$11 -> 2025.04 | G90: =$D$9&"."&G$11 -> 2025.05 | H90: =$D$9&"."&H$11 -> 2025.06 | I90: =$D$9&"."&I$11 -> 2025.07 | J90: =$D$9&"."&J$11 -> 2025.08 | ... N90: =$D$9&"."&N$11 -> 2025.12
B91: Additions/Low IT Income Statement | C91: =_xll.DBRW($B$1,Input!$D$9,Input!C$11,$M$1,Input!$G$9,Input!$J$9,$N$1,Input!$B91,$L$1,$K$1) -> -4.2342718 | D91: =_xll.DBRW($B$1,Input!$D$9,Input!D$11,$M$1,Input!$G$9,Input!$J$9,$N$1,Input!$B91,$L$1,$K$1) -> -46.954801 | E91: =_xll.DBRW($B$1,Input!$D$9,Input!E$11,$M$1,Input!$G$9,Input!$J$9,$N$1,Input!$B91,$L$1,$K$1) -> 10.136579 | F91: =_xll.DBRW($B$1,Input!$D$9,Input!F$11,$M$1,Input!$G$9,Input!$J$9,$N$1,Input!$B91,$L$1,$K$1) -> 5.9282813 | G91: =_xll.DBRW($B$1,Input!$D$9,Input!G$11,$M$1,Input!$G$9,Input!$J$9,$N$1,Input!$B91,$L$1,$K$1) -> 3.3006989 | H91: =_xll.DBRW($B$1,Input!$D$9,Input!H$11,$M$1,Input!$G$9,Input!$J$9,$N$1,Input!$B91,$L$1,$K$1) -> -367.43198 | I91: =_xll.DBRW($B$1,Input!$D$9,Input!I$11,$M$1,Input!$G$9,Input!$J$9,$N$1,Input!$B91,$L$1,$K$1) -> 31.760536 | J91: =_xll.DBRW($B$1,Input!$D$9,Input!J$11,$M$1,Input!$G$9,Input!$J$9,$N$1,Input!$B91,$L$1,$K$1) -> 49.358661 | ... N91: =_xll.DBRW($B$1,Input!$D$9,Input!N$11,$M$1,Input!$G$9,Input!$J$9,$N$1,Input!$B91,$L$1,$K$1) -> 112.90588
B92: % Income Tax | C92: =_xll.DBRW($C$1,Input!$D$9,Input!C$11,$M$1,Input!$J$9,Input!$B92,$K$1) -> 0.3 | D92: =_xll.DBRW($C$1,Input!$D$9,Input!D$11,$M$1,Input!$J$9,Input!$B92,$K$1) -> 0.3 | E92: =_xll.DBRW($C$1,Input!$D$9,Input!E$11,$M$1,Input!$J$9,Input!$B92,$K$1) -> 0.3 | F92: =_xll.DBRW($C$1,Input!$D$9,Input!F$11,$M$1,Input!$J$9,Input!$B92,$K$1) -> 0.3 | G92: =_xll.DBRW($C$1,Input!$D$9,Input!G$11,$M$1,Input!$J$9,Input!$B92,$K$1) -> 0.3 | H92: =_xll.DBRW($C$1,Input!$D$9,Input!H$11,$M$1,Input!$J$9,Input!$B92,$K$1) -> 0.3 | I92: =_xll.DBRW($C$1,Input!$D$9,Input!I$11,$M$1,Input!$J$9,Input!$B92,$K$1) -> 0.3 | J92: =_xll.DBRW($C$1,Input!$D$9,Input!J$11,$M$1,Input!$J$9,Input!$B92,$K$1) -> 0.3 | ... N92: =_xll.DBRW($C$1,Input!$D$9,Input!N$11,$M$1,Input!$J$9,Input!$B92,$K$1) -> 0.3
B93: Income Tax | C93: =_xll.DBRW($B$3,Input!$D$9,Input!C$11,$M$1,Input!$G$9,Input!$J$9,$D$60,Input!$B93,$K$1) -> 107.29554 | D93: =_xll.DBRW($B$3,Input!$D$9,Input!D$11,$M$1,Input!$G$9,Input!$J$9,$D$60,Input!$B93,$K$1) -> -57.380985 | E93: =_xll.DBRW($B$3,Input!$D$9,Input!E$11,$M$1,Input!$G$9,Input!$J$9,$D$60,Input!$B93,$K$1) -> -1.0408727 | F93: =_xll.DBRW($B$3,Input!$D$9,Input!F$11,$M$1,Input!$G$9,Input!$J$9,$D$60,Input!$B93,$K$1) -> -0.47152377 | G93: =_xll.DBRW($B$3,Input!$D$9,Input!G$11,$M$1,Input!$G$9,Input!$J$9,$D$60,Input!$B93,$K$1) -> 4.1829004 | H93: =_xll.DBRW($B$3,Input!$D$9,Input!H$11,$M$1,Input!$G$9,Input!$J$9,$D$60,Input!$B93,$K$1) -> -139.86617 | I93: =_xll.DBRW($B$3,Input!$D$9,Input!I$11,$M$1,Input!$G$9,Input!$J$9,$D$60,Input!$B93,$K$1) -> 38.690881 | J93: =_xll.DBRW($B$3,Input!$D$9,Input!J$11,$M$1,Input!$G$9,Input!$J$9,$D$60,Input!$B93,$K$1) -> 53.778525 | ... N93: =_xll.DBRW($B$3,Input!$D$9,Input!N$11,$M$1,Input!$G$9,Input!$J$9,$D$60,Input!$B93,$K$1) -> 59.013648
B94: Net Profit Before Minority Int. | C94: =_xll.DBRW($B$3,Input!$D$9,Input!C$11,$M$1,Input!$G$9,Input!$J$9,$D$60,Input!$B94,$K$1) -> 470.17162 | D94: =_xll.DBRW($B$3,Input!$D$9,Input!D$11,$M$1,Input!$G$9,Input!$J$9,$D$60,Input!$B94,$K$1) -> -200.85613 | E94: =_xll.DBRW($B$3,Input!$D$9,Input!E$11,$M$1,Input!$G$9,Input!$J$9,$D$60,Input!$B94,$K$1) -> -13.417027 | F94: =_xll.DBRW($B$3,Input!$D$9,Input!F$11,$M$1,Input!$G$9,Input!$J$9,$D$60,Input!$B94,$K$1) -> -8.7956931 | G94: =_xll.DBRW($B$3,Input!$D$9,Input!G$11,$M$1,Input!$G$9,Input!$J$9,$D$60,Input!$B94,$K$1) -> 14.349533 | H94: =_xll.DBRW($B$3,Input!$D$9,Input!H$11,$M$1,Input!$G$9,Input!$J$9,$D$60,Input!$B94,$K$1) -> -238.70291 | I94: =_xll.DBRW($B$3,Input!$D$9,Input!I$11,$M$1,Input!$G$9,Input!$J$9,$D$60,Input!$B94,$K$1) -> 135.25776 | J94: =_xll.DBRW($B$3,Input!$D$9,Input!J$11,$M$1,Input!$G$9,Input!$J$9,$D$60,Input!$B94,$K$1) -> 183.03943 | ... N94: =_xll.DBRW($B$3,Input!$D$9,Input!N$11,$M$1,Input!$G$9,Input!$J$9,$D$60,Input!$B94,$K$1) -> 142.17774
B97: Net Profit
C99: =$D$9&"."&C$11 -> 2025.01 | D99: =$D$9&"."&D$11 -> 2025.02 | E99: =$D$9&"."&E$11 -> 2025.03 | F99: =$D$9&"."&F$11 -> 2025.04 | G99: =$D$9&"."&G$11 -> 2025.05 | H99: =$D$9&"."&H$11 -> 2025.06 | I99: =$D$9&"."&I$11 -> 2025.07 | J99: =$D$9&"."&J$11 -> 2025.08 | ... N99: =$D$9&"."&N$11 -> 2025.12
B100: % Minoritários | C100: =_xll.DBRW($C$1,Input!$D$9,Input!C$11,$M$1,Input!$J$9,Input!$B100,$K$1) -> 0.4 | D100: =_xll.DBRW($C$1,Input!$D$9,Input!D$11,$M$1,Input!$J$9,Input!$B100,$K$1) -> 0.4 | E100: =_xll.DBRW($C$1,Input!$D$9,Input!E$11,$M$1,Input!$J$9,Input!$B100,$K$1) -> 0.4 | F100: =_xll.DBRW($C$1,Input!$D$9,Input!F$11,$M$1,Input!$J$9,Input!$B100,$K$1) -> 0.4 | G100: =_xll.DBRW($C$1,Input!$D$9,Input!G$11,$M$1,Input!$J$9,Input!$B100,$K$1) -> 0.4 | H100: =_xll.DBRW($C$1,Input!$D$9,Input!H$11,$M$1,Input!$J$9,Input!$B100,$K$1) -> 0.4 | I100: =_xll.DBRW($C$1,Input!$D$9,Input!I$11,$M$1,Input!$J$9,Input!$B100,$K$1) -> 0.4 | J100: =_xll.DBRW($C$1,Input!$D$9,Input!J$11,$M$1,Input!$J$9,Input!$B100,$K$1) -> 0.4 | ... N100: =_xll.DBRW($C$1,Input!$D$9,Input!N$11,$M$1,Input!$J$9,Input!$B100,$K$1) -> 0.4
B101: Minority Interests | C101: =_xll.DBRW($B$3,Input!$D$9,Input!C$11,$M$1,Input!$G$9,Input!$J$9,$D$60,Input!$B101,$K$1) -> 188.06865 | D101: =_xll.DBRW($B$3,Input!$D$9,Input!D$11,$M$1,Input!$G$9,Input!$J$9,$D$60,Input!$B101,$K$1) -> -80.342454 | E101: =_xll.DBRW($B$3,Input!$D$9,Input!E$11,$M$1,Input!$G$9,Input!$J$9,$D$60,Input!$B101,$K$1) -> -5.3668109 | F101: =_xll.DBRW($B$3,Input!$D$9,Input!F$11,$M$1,Input!$G$9,Input!$J$9,$D$60,Input!$B101,$K$1) -> -3.5182772 | G101: =_xll.DBRW($B$3,Input!$D$9,Input!G$11,$M$1,Input!$G$9,Input!$J$9,$D$60,Input!$B101,$K$1) -> 5.7398132 | H101: =_xll.DBRW($B$3,Input!$D$9,Input!H$11,$M$1,Input!$G$9,Input!$J$9,$D$60,Input!$B101,$K$1) -> -95.481163 | I101: =_xll.DBRW($B$3,Input!$D$9,Input!I$11,$M$1,Input!$G$9,Input!$J$9,$D$60,Input!$B101,$K$1) -> 54.103104 | J101: =_xll.DBRW($B$3,Input!$D$9,Input!J$11,$M$1,Input!$G$9,Input!$J$9,$D$60,Input!$B101,$K$1) -> 73.215771 | ... N101: =_xll.DBRW($B$3,Input!$D$9,Input!N$11,$M$1,Input!$G$9,Input!$J$9,$D$60,Input!$B101,$K$1) -> 56.871096
B102: Net Profit | C102: =_xll.DBRW($B$3,Input!$D$9,Input!C$11,$M$1,Input!$G$9,Input!$J$9,$D$60,Input!$B102,$K$1) -> 658.24026 | D102: =_xll.DBRW($B$3,Input!$D$9,Input!D$11,$M$1,Input!$G$9,Input!$J$9,$D$60,Input!$B102,$K$1) -> -281.19859 | E102: =_xll.DBRW($B$3,Input!$D$9,Input!E$11,$M$1,Input!$G$9,Input!$J$9,$D$60,Input!$B102,$K$1) -> -18.783838 | F102: =_xll.DBRW($B$3,Input!$D$9,Input!F$11,$M$1,Input!$G$9,Input!$J$9,$D$60,Input!$B102,$K$1) -> -12.31397 | G102: =_xll.DBRW($B$3,Input!$D$9,Input!G$11,$M$1,Input!$G$9,Input!$J$9,$D$60,Input!$B102,$K$1) -> 20.089346 | H102: =_xll.DBRW($B$3,Input!$D$9,Input!H$11,$M$1,Input!$G$9,Input!$J$9,$D$60,Input!$B102,$K$1) -> -334.18407 | I102: =_xll.DBRW($B$3,Input!$D$9,Input!I$11,$M$1,Input!$G$9,Input!$J$9,$D$60,Input!$B102,$K$1) -> 189.36087 | J102: =_xll.DBRW($B$3,Input!$D$9,Input!J$11,$M$1,Input!$G$9,Input!$J$9,$D$60,Input!$B102,$K$1) -> 256.2552 | ... N102: =_xll.DBRW($B$3,Input!$D$9,Input!N$11,$M$1,Input!$G$9,Input!$J$9,$D$60,Input!$B102,$K$1) -> 199.04883

Sheet Data Table Style #2
C3: ADD TEXT 2022-2023
C4: Add table headers with icon
D7: 2020 | E7: 2021 | F7: 2022 | G7: 2023 | H7: 2024 | I7: 2025 | J7: 2026 | K7: 2027
C8: Header 1 | D8: Data | E8: Data | F8: Data | G8: Data | H8: Data | I8: Data | J8: Data | K8: Data
C9: Header 2 | D9: Data | E9: Data | F9: Data | G9: Data | H9: Data | I9: Data | J9: Data | K9: Data
C10: Header 3 | D10: Data | E10: Data | F10: Data | G10: Data | H10: Data | I10: Data | J10: Data | K10: Data
C11: Header 4 | D11: Data | E11: Data | F11: Data | G11: Data | H11: Data | I11: Data | J11: Data | K11: Data
C12: Header 5 | D12: Data | E12: Data | F12: Data | G12: Data | H12: Data | I12: Data | J12: Data | K12: Data
C13: Header 6 | D13: Data | E13: Data | F13: Data | G13: Data | H13: Data | I13: Data | J13: Data | K13: Data
C14: Header 7 | D14: Data | E14: Data | F14: Data | G14: Data | H14: Data | I14: Data | J14: Data | K14: Data
C15: Header 8 | D15: Data | E15: Data | F15: Data | G15: Data | H15: Data | I15: Data | J15: Data | K15: Data
C16: Header 9 | D16: Data | E16: Data | F16: Data | G16: Data | H16: Data | I16: Data | J16: Data | K16: Data
C17: Header 10 | D17: Data | E17: Data | F17: Data | G17: Data | H17: Data | I17: Data | J17: Data | K17: Data
C18: Header 11 | D18: Data | E18: Data | F18: Data | G18: Data | H18: Data | I18: Data | J18: Data | K18: Data
C21: Add some text here. Add some text here.Add some text here. Add some text here.Add some text here. Add some text here.Add some text here. Add some text here.Add some text here. Add some text here.Add some text here. Add some text here.Add some text here. Add some text here.

Sheet Cognos_Office_Connection_Cache
