Workbook

Sheet Cons_Region
B1: =_xll.VIEW("CONS_VC:STG.100.DataBase_Uploads",D9) -> CONS_VC:STG.100.DataBase_Uploads:-7526985491597873023 | C1: =_xll.VIEW("CONS_VC:ALL.015.Region_Assumptions") -> CONS_VC:ALL.015.Region_Assumptions:-752698549-412528343 | D1: =_xll.VIEW("CONS_VC:DFS.120.Financial_Results") -> CONS_VC:DFS.120.Financial_Results:-752698549-1678799984 | K1: Value | L1: N/A | M1: =_xll.SUBNM("CONS_VC:ALL.D.Version","","T4") -> T4 | N1: PROD099
B2: =_xll.VIEW("CONS_VC:REV.100.Revenue_Consolidated") -> CONS_VC:REV.100.Revenue_Consolidated:-752698549-1045742215 | C2: =_xll.VIEW("CONS_VC:ALL.010.Economic_Assumptions") -> CONS_VC:ALL.010.Economic_Assumptions:-752698549-2110203674 | D2: =_xll.VIEW("CONS_VC:DFS.140.Indirect_Cash_Flow") -> CONS_VC:DFS.140.Indirect_Cash_Flow:-7526985491192101094 | K2: Total Market | N2: Total Products
B3: =_xll.VIEW("CONS_VC:DFS.100.Profit_and_Loss") -> CONS_VC:DFS.100.Profit_and_Loss:-7526985491293352199 | C3: =_xll.VIEW("CONS_VC:DFS.160.Working_Capital") -> CONS_VC:DFS.160.Working_Capital:-752698549-593608013 | D3: =_xll.VIEW("CONS_VC:ALL.004.Uploads_Status_Planning") -> CONS_VC:ALL.004.Uploads_Status_Planning:-7526985492074531375 | G3: Flag
B4: =_xll.VIEW("CONS_VC:ALL.001.Actual_Control") -> CONS_VC:ALL.001.Actual_Control:-7526985491690317456 | C4: =_xll.VIEW("CONS_VC:DFS.180.Gross_Debt") -> CONS_VC:DFS.180.Gross_Debt:-7526985491758842948
C5: =_xll.DBRW(Cons_Region!$B$4,Cons_Region!$D$9,Cons_Region!C11,$M$1,$G$3) -> PLAN | D5: =_xll.DBRW(Cons_Region!$B$4,Cons_Region!$D$9,Cons_Region!D11,$M$1,$G$3) -> PLAN | E5: =_xll.DBRW(Cons_Region!$B$4,Cons_Region!$D$9,Cons_Region!E11,$M$1,$G$3) -> PLAN | F5: =_xll.DBRW(Cons_Region!$B$4,Cons_Region!$D$9,Cons_Region!F11,$M$1,$G$3) -> PLAN | G5: =_xll.DBRW(Cons_Region!$B$4,Cons_Region!$D$9,Cons_Region!G11,$M$1,$G$3) -> PLAN | H5: =_xll.DBRW(Cons_Region!$B$4,Cons_Region!$D$9,Cons_Region!H11,$M$1,$G$3) -> PLAN | I5: =_xll.DBRW(Cons_Region!$B$4,Cons_Region!$D$9,Cons_Region!I11,$M$1,$G$3) -> PLAN | J5: =_xll.DBRW(Cons_Region!$B$4,Cons_Region!$D$9,Cons_Region!J11,$M$1,$G$3) -> PLAN | ... N5: =_xll.DBRW(Cons_Region!$B$4,Cons_Region!$D$9,Cons_Region!N11,$M$1,$G$3) -> PLAN
L7: System Input Status: | N7: =_xll.DBRW($D$3,$M$1,$J$9,"Status") -> Closed
B8: GLOBAL ASSUMPTIONS
C9: Year: | D9: =_xll.SUBNM("CONS_VC:ALL.D.Year","SYS_Picklist","2026","MEMBER_NAME") -> 2026 | F9: Currency: | G9: =_xll.SUBNM("CONS_VC:ALL.D.Currency","PAX","USD","Nome alternativo") -> USD | I9: Region: | J9: =_xll.SUBNM("CONS_VC:ALL.D.Region","Nível 0","VCNA","MEMBER_NAME") -> VCNA
C11: 01 | D11: 02 | E11: 03 | F11: 04 | G11: 05 | H11: 06 | I11: 07 | J11: 08 | K11: 09 | L11: 10 | M11: 11 | N11: 12
C12: =$D$9&"."&C11 -> 2026.01 | D12: =$D$9&"."&D11 -> 2026.02 | E12: =$D$9&"."&E11 -> 2026.03 | F12: =$D$9&"."&F11 -> 2026.04 | G12: =$D$9&"."&G11 -> 2026.05 | H12: =$D$9&"."&H11 -> 2026.06 | I12: =$D$9&"."&I11 -> 2026.07 | J12: =$D$9&"."&J11 -> 2026.08 | ... N12: =$D$9&"."&N11 -> 2026.12
B13: Begining FX Rate R$/US$ | C13: =_xll.DBRW($C$2,Cons_Region!$D$9,Cons_Region!$C$11,$M$1,$B13,$K$1) -> 0 | D13: =_xll.DBRW($C$2,Cons_Region!$D$9,Cons_Region!$C$11,$M$1,$B13,$K$1) -> 0 | E13: =_xll.DBRW($C$2,Cons_Region!$D$9,Cons_Region!$C$11,$M$1,$B13,$K$1) -> 0 | F13: =_xll.DBRW($C$2,Cons_Region!$D$9,Cons_Region!$C$11,$M$1,$B13,$K$1) -> 0 | G13: =_xll.DBRW($C$2,Cons_Region!$D$9,Cons_Region!$C$11,$M$1,$B13,$K$1) -> 0 | H13: =_xll.DBRW($C$2,Cons_Region!$D$9,Cons_Region!$C$11,$M$1,$B13,$K$1) -> 0 | I13: =_xll.DBRW($C$2,Cons_Region!$D$9,Cons_Region!$C$11,$M$1,$B13,$K$1) -> 0 | J13: =_xll.DBRW($C$2,Cons_Region!$D$9,Cons_Region!$C$11,$M$1,$B13,$K$1) -> 0 | ... N13: =_xll.DBRW($C$2,Cons_Region!$D$9,Cons_Region!$C$11,$M$1,$B13,$K$1) -> 0
B14: Average FX Rate R$/US$ | C14: =_xll.DBRW($C$2,Cons_Region!$D$9,Cons_Region!$C$11,$M$1,$B14,$K$1) -> 0 | D14: =_xll.DBRW($C$2,Cons_Region!$D$9,Cons_Region!$C$11,$M$1,$B14,$K$1) -> 0 | E14: =_xll.DBRW($C$2,Cons_Region!$D$9,Cons_Region!$C$11,$M$1,$B14,$K$1) -> 0 | F14: =_xll.DBRW($C$2,Cons_Region!$D$9,Cons_Region!$C$11,$M$1,$B14,$K$1) -> 0 | G14: =_xll.DBRW($C$2,Cons_Region!$D$9,Cons_Region!$C$11,$M$1,$B14,$K$1) -> 0 | H14: =_xll.DBRW($C$2,Cons_Region!$D$9,Cons_Region!$C$11,$M$1,$B14,$K$1) -> 0 | I14: =_xll.DBRW($C$2,Cons_Region!$D$9,Cons_Region!$C$11,$M$1,$B14,$K$1) -> 0 | J14: =_xll.DBRW($C$2,Cons_Region!$D$9,Cons_Region!$C$11,$M$1,$B14,$K$1) -> 0 | ... N14: =_xll.DBRW($C$2,Cons_Region!$D$9,Cons_Region!$C$11,$M$1,$B14,$K$1) -> 0
B15: Final FX Rate R$/US$ | C15: =_xll.DBRW($C$2,Cons_Region!$D$9,Cons_Region!$C$11,$M$1,$B15,$K$1) -> 0 | D15: =_xll.DBRW($C$2,Cons_Region!$D$9,Cons_Region!$C$11,$M$1,$B15,$K$1) -> 0 | E15: =_xll.DBRW($C$2,Cons_Region!$D$9,Cons_Region!$C$11,$M$1,$B15,$K$1) -> 0 | F15: =_xll.DBRW($C$2,Cons_Region!$D$9,Cons_Region!$C$11,$M$1,$B15,$K$1) -> 0 | G15: =_xll.DBRW($C$2,Cons_Region!$D$9,Cons_Region!$C$11,$M$1,$B15,$K$1) -> 0 | H15: =_xll.DBRW($C$2,Cons_Region!$D$9,Cons_Region!$C$11,$M$1,$B15,$K$1) -> 0 | I15: =_xll.DBRW($C$2,Cons_Region!$D$9,Cons_Region!$C$11,$M$1,$B15,$K$1) -> 0 | J15: =_xll.DBRW($C$2,Cons_Region!$D$9,Cons_Region!$C$11,$M$1,$B15,$K$1) -> 0 | ... N15: =_xll.DBRW($C$2,Cons_Region!$D$9,Cons_Region!$C$11,$M$1,$B15,$K$1) -> 0
B16: Begining FX Rate US$/EUR | C16: =_xll.DBRW($C$2,Cons_Region!$D$9,Cons_Region!$C$11,$M$1,$B16,$K$1) -> 0 | D16: =_xll.DBRW($C$2,Cons_Region!$D$9,Cons_Region!$C$11,$M$1,$B16,$K$1) -> 0 | E16: =_xll.DBRW($C$2,Cons_Region!$D$9,Cons_Region!$C$11,$M$1,$B16,$K$1) -> 0 | F16: =_xll.DBRW($C$2,Cons_Region!$D$9,Cons_Region!$C$11,$M$1,$B16,$K$1) -> 0 | G16: =_xll.DBRW($C$2,Cons_Region!$D$9,Cons_Region!$C$11,$M$1,$B16,$K$1) -> 0 | H16: =_xll.DBRW($C$2,Cons_Region!$D$9,Cons_Region!$C$11,$M$1,$B16,$K$1) -> 0 | I16: =_xll.DBRW($C$2,Cons_Region!$D$9,Cons_Region!$C$11,$M$1,$B16,$K$1) -> 0 | J16: =_xll.DBRW($C$2,Cons_Region!$D$9,Cons_Region!$C$11,$M$1,$B16,$K$1) -> 0 | ... N16: =_xll.DBRW($C$2,Cons_Region!$D$9,Cons_Region!$C$11,$M$1,$B16,$K$1) -> 0
B17: Average FX Rate US$/EUR | C17: =_xll.DBRW($C$2,Cons_Region!$D$9,Cons_Region!$C$11,$M$1,$B17,$K$1) -> 5 | D17: =_xll.DBRW($C$2,Cons_Region!$D$9,Cons_Region!$C$11,$M$1,$B17,$K$1) -> 5 | E17: =_xll.DBRW($C$2,Cons_Region!$D$9,Cons_Region!$C$11,$M$1,$B17,$K$1) -> 5 | F17: =_xll.DBRW($C$2,Cons_Region!$D$9,Cons_Region!$C$11,$M$1,$B17,$K$1) -> 5 | G17: =_xll.DBRW($C$2,Cons_Region!$D$9,Cons_Region!$C$11,$M$1,$B17,$K$1) -> 5 | H17: =_xll.DBRW($C$2,Cons_Region!$D$9,Cons_Region!$C$11,$M$1,$B17,$K$1) -> 5 | I17: =_xll.DBRW($C$2,Cons_Region!$D$9,Cons_Region!$C$11,$M$1,$B17,$K$1) -> 5 | J17: =_xll.DBRW($C$2,Cons_Region!$D$9,Cons_Region!$C$11,$M$1,$B17,$K$1) -> 5 | ... N17: =_xll.DBRW($C$2,Cons_Region!$D$9,Cons_Region!$C$11,$M$1,$B17,$K$1) -> 5
B18: Final FX Rate US$/EUR | C18: =_xll.DBRW($C$2,Cons_Region!$D$9,Cons_Region!$C$11,$M$1,$B18,$K$1) -> 0 | D18: =_xll.DBRW($C$2,Cons_Region!$D$9,Cons_Region!$C$11,$M$1,$B18,$K$1) -> 0 | E18: =_xll.DBRW($C$2,Cons_Region!$D$9,Cons_Region!$C$11,$M$1,$B18,$K$1) -> 0 | F18: =_xll.DBRW($C$2,Cons_Region!$D$9,Cons_Region!$C$11,$M$1,$B18,$K$1) -> 0 | G18: =_xll.DBRW($C$2,Cons_Region!$D$9,Cons_Region!$C$11,$M$1,$B18,$K$1) -> 0 | H18: =_xll.DBRW($C$2,Cons_Region!$D$9,Cons_Region!$C$11,$M$1,$B18,$K$1) -> 0 | I18: =_xll.DBRW($C$2,Cons_Region!$D$9,Cons_Region!$C$11,$M$1,$B18,$K$1) -> 0 | J18: =_xll.DBRW($C$2,Cons_Region!$D$9,Cons_Region!$C$11,$M$1,$B18,$K$1) -> 0 | ... N18: =_xll.DBRW($C$2,Cons_Region!$D$9,Cons_Region!$C$11,$M$1,$B18,$K$1) -> 0
B19: Câmbio Inicial UYU$/US$ | C19: =_xll.DBRW($C$2,Cons_Region!$D$9,Cons_Region!$C$11,$M$1,$B19,$K$1) -> 0 | D19: =_xll.DBRW($C$2,Cons_Region!$D$9,Cons_Region!$C$11,$M$1,$B19,$K$1) -> 0 | E19: =_xll.DBRW($C$2,Cons_Region!$D$9,Cons_Region!$C$11,$M$1,$B19,$K$1) -> 0 | F19: =_xll.DBRW($C$2,Cons_Region!$D$9,Cons_Region!$C$11,$M$1,$B19,$K$1) -> 0 | G19: =_xll.DBRW($C$2,Cons_Region!$D$9,Cons_Region!$C$11,$M$1,$B19,$K$1) -> 0 | H19: =_xll.DBRW($C$2,Cons_Region!$D$9,Cons_Region!$C$11,$M$1,$B19,$K$1) -> 0 | I19: =_xll.DBRW($C$2,Cons_Region!$D$9,Cons_Region!$C$11,$M$1,$B19,$K$1) -> 0 | J19: =_xll.DBRW($C$2,Cons_Region!$D$9,Cons_Region!$C$11,$M$1,$B19,$K$1) -> 0 | ... N19: =_xll.DBRW($C$2,Cons_Region!$D$9,Cons_Region!$C$11,$M$1,$B19,$K$1) -> 0
B20: Câmbio Médio UYU$/US$ | C20: =_xll.DBRW($C$2,Cons_Region!$D$9,Cons_Region!$C$11,$M$1,$B20,$K$1) -> 0 | D20: =_xll.DBRW($C$2,Cons_Region!$D$9,Cons_Region!$C$11,$M$1,$B20,$K$1) -> 0 | E20: =_xll.DBRW($C$2,Cons_Region!$D$9,Cons_Region!$C$11,$M$1,$B20,$K$1) -> 0 | F20: =_xll.DBRW($C$2,Cons_Region!$D$9,Cons_Region!$C$11,$M$1,$B20,$K$1) -> 0 | G20: =_xll.DBRW($C$2,Cons_Region!$D$9,Cons_Region!$C$11,$M$1,$B20,$K$1) -> 0 | H20: =_xll.DBRW($C$2,Cons_Region!$D$9,Cons_Region!$C$11,$M$1,$B20,$K$1) -> 0 | I20: =_xll.DBRW($C$2,Cons_Region!$D$9,Cons_Region!$C$11,$M$1,$B20,$K$1) -> 0 | J20: =_xll.DBRW($C$2,Cons_Region!$D$9,Cons_Region!$C$11,$M$1,$B20,$K$1) -> 0 | ... N20: =_xll.DBRW($C$2,Cons_Region!$D$9,Cons_Region!$C$11,$M$1,$B20,$K$1) -> 0
B21: Câmbio Final UYU$/US$ | C21: =_xll.DBRW($C$2,Cons_Region!$D$9,Cons_Region!$C$11,$M$1,$B21,$K$1) -> 0 | D21: =_xll.DBRW($C$2,Cons_Region!$D$9,Cons_Region!$C$11,$M$1,$B21,$K$1) -> 0 | E21: =_xll.DBRW($C$2,Cons_Region!$D$9,Cons_Region!$C$11,$M$1,$B21,$K$1) -> 0 | F21: =_xll.DBRW($C$2,Cons_Region!$D$9,Cons_Region!$C$11,$M$1,$B21,$K$1) -> 0 | G21: =_xll.DBRW($C$2,Cons_Region!$D$9,Cons_Region!$C$11,$M$1,$B21,$K$1) -> 0 | H21: =_xll.DBRW($C$2,Cons_Region!$D$9,Cons_Region!$C$11,$M$1,$B21,$K$1) -> 0 | I21: =_xll.DBRW($C$2,Cons_Region!$D$9,Cons_Region!$C$11,$M$1,$B21,$K$1) -> 0 | J21: =_xll.DBRW($C$2,Cons_Region!$D$9,Cons_Region!$C$11,$M$1,$B21,$K$1) -> 0 | ... N21: =_xll.DBRW($C$2,Cons_Region!$D$9,Cons_Region!$C$11,$M$1,$B21,$K$1) -> 0
B22: Câmbio Inicial ARS$/US$ | C22: =_xll.DBRW($C$2,Cons_Region!$D$9,Cons_Region!$C$11,$M$1,$B22,$K$1) -> 0 | D22: =_xll.DBRW($C$2,Cons_Region!$D$9,Cons_Region!$C$11,$M$1,$B22,$K$1) -> 0 | E22: =_xll.DBRW($C$2,Cons_Region!$D$9,Cons_Region!$C$11,$M$1,$B22,$K$1) -> 0 | F22: =_xll.DBRW($C$2,Cons_Region!$D$9,Cons_Region!$C$11,$M$1,$B22,$K$1) -> 0 | G22: =_xll.DBRW($C$2,Cons_Region!$D$9,Cons_Region!$C$11,$M$1,$B22,$K$1) -> 0 | H22: =_xll.DBRW($C$2,Cons_Region!$D$9,Cons_Region!$C$11,$M$1,$B22,$K$1) -> 0 | I22: =_xll.DBRW($C$2,Cons_Region!$D$9,Cons_Region!$C$11,$M$1,$B22,$K$1) -> 0 | J22: =_xll.DBRW($C$2,Cons_Region!$D$9,Cons_Region!$C$11,$M$1,$B22,$K$1) -> 0 | ... N22: =_xll.DBRW($C$2,Cons_Region!$D$9,Cons_Region!$C$11,$M$1,$B22,$K$1) -> 0
B23: Câmbio Médio ARS$/US$ | C23: =_xll.DBRW($C$2,Cons_Region!$D$9,Cons_Region!$C$11,$M$1,$B23,$K$1) -> 0 | D23: =_xll.DBRW($C$2,Cons_Region!$D$9,Cons_Region!$C$11,$M$1,$B23,$K$1) -> 0 | E23: =_xll.DBRW($C$2,Cons_Region!$D$9,Cons_Region!$C$11,$M$1,$B23,$K$1) -> 0 | F23: =_xll.DBRW($C$2,Cons_Region!$D$9,Cons_Region!$C$11,$M$1,$B23,$K$1) -> 0 | G23: =_xll.DBRW($C$2,Cons_Region!$D$9,Cons_Region!$C$11,$M$1,$B23,$K$1) -> 0 | H23: =_xll.DBRW($C$2,Cons_Region!$D$9,Cons_Region!$C$11,$M$1,$B23,$K$1) -> 0 | I23: =_xll.DBRW($C$2,Cons_Region!$D$9,Cons_Region!$C$11,$M$1,$B23,$K$1) -> 0 | J23: =_xll.DBRW($C$2,Cons_Region!$D$9,Cons_Region!$C$11,$M$1,$B23,$K$1) -> 0 | ... N23: =_xll.DBRW($C$2,Cons_Region!$D$9,Cons_Region!$C$11,$M$1,$B23,$K$1) -> 0
B24: Câmbio Final ARS$/US$ | C24: =_xll.DBRW($C$2,Cons_Region!$D$9,Cons_Region!$C$11,$M$1,$B24,$K$1) -> 0 | D24: =_xll.DBRW($C$2,Cons_Region!$D$9,Cons_Region!$C$11,$M$1,$B24,$K$1) -> 0 | E24: =_xll.DBRW($C$2,Cons_Region!$D$9,Cons_Region!$C$11,$M$1,$B24,$K$1) -> 0 | F24: =_xll.DBRW($C$2,Cons_Region!$D$9,Cons_Region!$C$11,$M$1,$B24,$K$1) -> 0 | G24: =_xll.DBRW($C$2,Cons_Region!$D$9,Cons_Region!$C$11,$M$1,$B24,$K$1) -> 0 | H24: =_xll.DBRW($C$2,Cons_Region!$D$9,Cons_Region!$C$11,$M$1,$B24,$K$1) -> 0 | I24: =_xll.DBRW($C$2,Cons_Region!$D$9,Cons_Region!$C$11,$M$1,$B24,$K$1) -> 0 | J24: =_xll.DBRW($C$2,Cons_Region!$D$9,Cons_Region!$C$11,$M$1,$B24,$K$1) -> 0 | ... N24: =_xll.DBRW($C$2,Cons_Region!$D$9,Cons_Region!$C$11,$M$1,$B24,$K$1) -> 0
... B26: American CPI | C26: =_xll.DBRW($C$2,Cons_Region!$D$9,Cons_Region!$C$11,$M$1,$B26,$K$1) -> 0 | D26: =_xll.DBRW($C$2,Cons_Region!$D$9,Cons_Region!$C$11,$M$1,$B26,$K$1) -> 0 | E26: =_xll.DBRW($C$2,Cons_Region!$D$9,Cons_Region!$C$11,$M$1,$B26,$K$1) -> 0 | F26: =_xll.DBRW($C$2,Cons_Region!$D$9,Cons_Region!$C$11,$M$1,$B26,$K$1) -> 0 | G26: =_xll.DBRW($C$2,Cons_Region!$D$9,Cons_Region!$C$11,$M$1,$B26,$K$1) -> 0 | H26: =_xll.DBRW($C$2,Cons_Region!$D$9,Cons_Region!$C$11,$M$1,$B26,$K$1) -> 0 | I26: =_xll.DBRW($C$2,Cons_Region!$D$9,Cons_Region!$C$11,$M$1,$B26,$K$1) -> 0 | J26: =_xll.DBRW($C$2,Cons_Region!$D$9,Cons_Region!$C$11,$M$1,$B26,$K$1) -> 0 | ... N26: =_xll.DBRW($C$2,Cons_Region!$D$9,Cons_Region!$C$11,$M$1,$B26,$K$1) -> 0
B27: Number of Days | C27: =_xll.DBRW($C$2,Cons_Region!$D$9,C$11,$M$1,$B27,$K$1) -> 31 | D27: =_xll.DBRW($C$2,Cons_Region!$D$9,D$11,$M$1,$B27,$K$1) -> 30 | E27: =_xll.DBRW($C$2,Cons_Region!$D$9,E$11,$M$1,$B27,$K$1) -> 31 | F27: =_xll.DBRW($C$2,Cons_Region!$D$9,F$11,$M$1,$B27,$K$1) -> 30 | G27: =_xll.DBRW($C$2,Cons_Region!$D$9,G$11,$M$1,$B27,$K$1) -> 31 | H27: =_xll.DBRW($C$2,Cons_Region!$D$9,H$11,$M$1,$B27,$K$1) -> 31 | I27: =_xll.DBRW($C$2,Cons_Region!$D$9,I$11,$M$1,$B27,$K$1) -> 30 | J27: =_xll.DBRW($C$2,Cons_Region!$D$9,J$11,$M$1,$B27,$K$1) -> 31 | ... N27: =_xll.DBRW($C$2,Cons_Region!$D$9,N$11,$M$1,$B27,$K$1) -> 0
B30: NET REVENUES
C33: =$D$9&"."&C11 -> 2026.01 | D33: =$D$9&"."&D11 -> 2026.02 | E33: =$D$9&"."&E11 -> 2026.03 | F33: =$D$9&"."&F11 -> 2026.04 | G33: =$D$9&"."&G11 -> 2026.05 | H33: =$D$9&"."&H11 -> 2026.06 | I33: =$D$9&"."&I11 -> 2026.07 | J33: =$D$9&"."&J11 -> 2026.08 | ... N33: =$D$9&"."&N11 -> 2026.12
B34: % Operational Tax | C34: =_xll.DBRW($B$2,Cons_Region!$D$9,Cons_Region!C$11,$M$1,Cons_Region!$G$9,Cons_Region!$J$9,$N$2,$K$2,$B$34) -> 0 | D34: =_xll.DBRW($B$2,Cons_Region!$D$9,Cons_Region!D$11,$M$1,Cons_Region!$G$9,Cons_Region!$J$9,$N$2,$K$2,$B$34) -> 0 | E34: =_xll.DBRW($B$2,Cons_Region!$D$9,Cons_Region!E$11,$M$1,Cons_Region!$G$9,Cons_Region!$J$9,$N$2,$K$2,$B$34) -> 0 | F34: =_xll.DBRW($B$2,Cons_Region!$D$9,Cons_Region!F$11,$M$1,Cons_Region!$G$9,Cons_Region!$J$9,$N$2,$K$2,$B$34) -> 0 | G34: =_xll.DBRW($B$2,Cons_Region!$D$9,Cons_Region!G$11,$M$1,Cons_Region!$G$9,Cons_Region!$J$9,$N$2,$K$2,$B$34) -> 0 | H34: =_xll.DBRW($B$2,Cons_Region!$D$9,Cons_Region!H$11,$M$1,Cons_Region!$G$9,Cons_Region!$J$9,$N$2,$K$2,$B$34) -> 0 | I34: =_xll.DBRW($B$2,Cons_Region!$D$9,Cons_Region!I$11,$M$1,Cons_Region!$G$9,Cons_Region!$J$9,$N$2,$K$2,$B$34) -> 0 | J34: =_xll.DBRW($B$2,Cons_Region!$D$9,Cons_Region!J$11,$M$1,Cons_Region!$G$9,Cons_Region!$J$9,$N$2,$K$2,$B$34) -> 0 | ... N34: =_xll.DBRW($B$2,Cons_Region!$D$9,Cons_Region!N$11,$M$1,Cons_Region!$G$9,Cons_Region!$J$9,$N$2,$K$2,$B$34) -> 0
B35: Gross Revenue [$MM] | C35: =_xll.DBRW($B$2,Cons_Region!$D$9,Cons_Region!C$11,$M$1,Cons_Region!$G$9,Cons_Region!$J$9,$N$2,$K$2,$B$35) -> 53.485063 | D35: =_xll.DBRW($B$2,Cons_Region!$D$9,Cons_Region!D$11,$M$1,Cons_Region!$G$9,Cons_Region!$J$9,$N$2,$K$2,$B$35) -> 65.839564 | E35: =_xll.DBRW($B$2,Cons_Region!$D$9,Cons_Region!E$11,$M$1,Cons_Region!$G$9,Cons_Region!$J$9,$N$2,$K$2,$B$35) -> 90.971339 | F35: =_xll.DBRW($B$2,Cons_Region!$D$9,Cons_Region!F$11,$M$1,Cons_Region!$G$9,Cons_Region!$J$9,$N$2,$K$2,$B$35) -> 130.42887 | G35: =_xll.DBRW($B$2,Cons_Region!$D$9,Cons_Region!G$11,$M$1,Cons_Region!$G$9,Cons_Region!$J$9,$N$2,$K$2,$B$35) -> 157.2599 | H35: =_xll.DBRW($B$2,Cons_Region!$D$9,Cons_Region!H$11,$M$1,Cons_Region!$G$9,Cons_Region!$J$9,$N$2,$K$2,$B$35) -> 174.71501 | I35: =_xll.DBRW($B$2,Cons_Region!$D$9,Cons_Region!I$11,$M$1,Cons_Region!$G$9,Cons_Region!$J$9,$N$2,$K$2,$B$35) -> 176.77009 | J35: =_xll.DBRW($B$2,Cons_Region!$D$9,Cons_Region!J$11,$M$1,Cons_Region!$G$9,Cons_Region!$J$9,$N$2,$K$2,$B$35) -> 177.59375 | ... N35: =_xll.DBRW($B$2,Cons_Region!$D$9,Cons_Region!N$11,$M$1,Cons_Region!$G$9,Cons_Region!$J$9,$N$2,$K$2,$B$35) -> 83.919777
B36: Net Revenue [$MM] | C36: =_xll.DBRW($B$2,Cons_Region!$D$9,Cons_Region!C$11,$M$1,Cons_Region!$G$9,Cons_Region!$J$9,$N$2,$K$2,$B$36) -> 53.485063 | D36: =_xll.DBRW($B$2,Cons_Region!$D$9,Cons_Region!D$11,$M$1,Cons_Region!$G$9,Cons_Region!$J$9,$N$2,$K$2,$B$36) -> 65.839564 | E36: =_xll.DBRW($B$2,Cons_Region!$D$9,Cons_Region!E$11,$M$1,Cons_Region!$G$9,Cons_Region!$J$9,$N$2,$K$2,$B$36) -> 90.971339 | F36: =_xll.DBRW($B$2,Cons_Region!$D$9,Cons_Region!F$11,$M$1,Cons_Region!$G$9,Cons_Region!$J$9,$N$2,$K$2,$B$36) -> 130.42887 | G36: =_xll.DBRW($B$2,Cons_Region!$D$9,Cons_Region!G$11,$M$1,Cons_Region!$G$9,Cons_Region!$J$9,$N$2,$K$2,$B$36) -> 157.2599 | H36: =_xll.DBRW($B$2,Cons_Region!$D$9,Cons_Region!H$11,$M$1,Cons_Region!$G$9,Cons_Region!$J$9,$N$2,$K$2,$B$36) -> 174.71501 | I36: =_xll.DBRW($B$2,Cons_Region!$D$9,Cons_Region!I$11,$M$1,Cons_Region!$G$9,Cons_Region!$J$9,$N$2,$K$2,$B$36) -> 176.77009 | J36: =_xll.DBRW($B$2,Cons_Region!$D$9,Cons_Region!J$11,$M$1,Cons_Region!$G$9,Cons_Region!$J$9,$N$2,$K$2,$B$36) -> 177.59375 | ... N36: =_xll.DBRW($B$2,Cons_Region!$D$9,Cons_Region!N$11,$M$1,Cons_Region!$G$9,Cons_Region!$J$9,$N$2,$K$2,$B$36) -> 83.919777
B40: CONTRIBUTION MARGIN
C43: =$D$9&"."&C$11 -> 2026.01 | D43: =$D$9&"."&D$11 -> 2026.02 | E43: =$D$9&"."&E$11 -> 2026.03 | F43: =$D$9&"."&F$11 -> 2026.04 | G43: =$D$9&"."&G$11 -> 2026.05 | H43: =$D$9&"."&H$11 -> 2026.06 | I43: =$D$9&"."&I$11 -> 2026.07 | J43: =$D$9&"."&J$11 -> 2026.08 | ... N43: =$D$9&"."&N$11 -> 2026.12
B44: Final Variable Sales Expenses | C44: =_xll.DBRW($B$1,Cons_Region!$D$9,Cons_Region!C$11,$M$1,Cons_Region!$G$9,Cons_Region!$J$9,$N$2,Cons_Region!$B44,$L$1,$K$1) -> 10.755415 | D44: =_xll.DBRW($B$1,Cons_Region!$D$9,Cons_Region!D$11,$M$1,Cons_Region!$G$9,Cons_Region!$J$9,$N$1,Cons_Region!$B44,$L$1,$K$1) -> 11.194354 | E44: =_xll.DBRW($B$1,Cons_Region!$D$9,Cons_Region!E$11,$M$1,Cons_Region!$G$9,Cons_Region!$J$9,$N$1,Cons_Region!$B44,$L$1,$K$1) -> 17.865267 | F44: =_xll.DBRW($B$1,Cons_Region!$D$9,Cons_Region!F$11,$M$1,Cons_Region!$G$9,Cons_Region!$J$9,$N$1,Cons_Region!$B44,$L$1,$K$1) -> 25.541581 | G44: =_xll.DBRW($B$1,Cons_Region!$D$9,Cons_Region!G$11,$M$1,Cons_Region!$G$9,Cons_Region!$J$9,$N$1,Cons_Region!$B44,$L$1,$K$1) -> 32.065037 | H44: =_xll.DBRW($B$1,Cons_Region!$D$9,Cons_Region!H$11,$M$1,Cons_Region!$G$9,Cons_Region!$J$9,$N$1,Cons_Region!$B44,$L$1,$K$1) -> 32.16427 | I44: =_xll.DBRW($B$1,Cons_Region!$D$9,Cons_Region!I$11,$M$1,Cons_Region!$G$9,Cons_Region!$J$9,$N$1,Cons_Region!$B44,$L$1,$K$1) -> 33.559233 | J44: =_xll.DBRW($B$1,Cons_Region!$D$9,Cons_Region!J$11,$M$1,Cons_Region!$G$9,Cons_Region!$J$9,$N$1,Cons_Region!$B44,$L$1,$K$1) -> 33.758894 | K44: =_xll.DBRW($B$1,Cons_Region!$D$9,Cons_Region!K$11,$M$1,Cons_Region!$G$9,Cons_Region!$J$9,$N$1,Cons_Region!$B44,$L$1,$K$1) -> 34.329246 | ... N44: =_xll.DBRW($B$1,Cons_Region!$D$9,Cons_Region!N$11,$M$1,Cons_Region!$G$9,Cons_Region!$J$9,$N$1,Cons_Region!$B44,$L$1,$K$1) -> 17.751297
B45: Other Variable Costs | C45: =_xll.DBRW($B$1,Cons_Region!$D$9,Cons_Region!C$11,$M$1,Cons_Region!$G$9,Cons_Region!$J$9,$N$2,Cons_Region!$B45,$L$1,$K$1) -> 20.773323 | D45: =_xll.DBRW($B$1,Cons_Region!$D$9,Cons_Region!D$11,$M$1,Cons_Region!$G$9,Cons_Region!$J$9,$N$2,Cons_Region!$B45,$L$1,$K$1) -> 29.510057 | E45: =_xll.DBRW($B$1,Cons_Region!$D$9,Cons_Region!E$11,$M$1,Cons_Region!$G$9,Cons_Region!$J$9,$N$2,Cons_Region!$B45,$L$1,$K$1) -> 29.698686 | F45: =_xll.DBRW($B$1,Cons_Region!$D$9,Cons_Region!F$11,$M$1,Cons_Region!$G$9,Cons_Region!$J$9,$N$2,Cons_Region!$B45,$L$1,$K$1) -> 38.31103 | G45: =_xll.DBRW($B$1,Cons_Region!$D$9,Cons_Region!G$11,$M$1,Cons_Region!$G$9,Cons_Region!$J$9,$N$2,Cons_Region!$B45,$L$1,$K$1) -> 41.167295 | H45: =_xll.DBRW($B$1,Cons_Region!$D$9,Cons_Region!H$11,$M$1,Cons_Region!$G$9,Cons_Region!$J$9,$N$2,Cons_Region!$B45,$L$1,$K$1) -> 44.456398 | I45: =_xll.DBRW($B$1,Cons_Region!$D$9,Cons_Region!I$11,$M$1,Cons_Region!$G$9,Cons_Region!$J$9,$N$2,Cons_Region!$B45,$L$1,$K$1) -> 46.820857 | J45: =_xll.DBRW($B$1,Cons_Region!$D$9,Cons_Region!J$11,$M$1,Cons_Region!$G$9,Cons_Region!$J$9,$N$2,Cons_Region!$B45,$L$1,$K$1) -> 50.225845 | ... N45: =_xll.DBRW($B$1,Cons_Region!$D$9,Cons_Region!N$11,$M$1,Cons_Region!$G$9,Cons_Region!$J$9,$N$2,Cons_Region!$B45,$L$1,$K$1) -> 20.96795
B46: Fixed Costs | C46: =_xll.DBRW($B$1,Cons_Region!$D$9,Cons_Region!C$11,$M$1,Cons_Region!$G$9,Cons_Region!$J$9,$N$1,Cons_Region!$B46,$L$1,$K$1) -> 34.8395 | D46: =_xll.DBRW($B$1,Cons_Region!$D$9,Cons_Region!D$11,$M$1,Cons_Region!$G$9,Cons_Region!$J$9,$N$1,Cons_Region!$B46,$L$1,$K$1) -> 37.194558 | E46: =_xll.DBRW($B$1,Cons_Region!$D$9,Cons_Region!E$11,$M$1,Cons_Region!$G$9,Cons_Region!$J$9,$N$1,Cons_Region!$B46,$L$1,$K$1) -> 31.431682 | F46: =_xll.DBRW($B$1,Cons_Region!$D$9,Cons_Region!F$11,$M$1,Cons_Region!$G$9,Cons_Region!$J$9,$N$1,Cons_Region!$B46,$L$1,$K$1) -> 30.091597 | G46: =_xll.DBRW($B$1,Cons_Region!$D$9,Cons_Region!G$11,$M$1,Cons_Region!$G$9,Cons_Region!$J$9,$N$1,Cons_Region!$B46,$L$1,$K$1) -> 20.521551 | H46: =_xll.DBRW($B$1,Cons_Region!$D$9,Cons_Region!H$11,$M$1,Cons_Region!$G$9,Cons_Region!$J$9,$N$1,Cons_Region!$B46,$L$1,$K$1) -> 23.325895 | I46: =_xll.DBRW($B$1,Cons_Region!$D$9,Cons_Region!I$11,$M$1,Cons_Region!$G$9,Cons_Region!$J$9,$N$1,Cons_Region!$B46,$L$1,$K$1) -> 21.784902 | J46: =_xll.DBRW($B$1,Cons_Region!$D$9,Cons_Region!J$11,$M$1,Cons_Region!$G$9,Cons_Region!$J$9,$N$1,Cons_Region!$B46,$L$1,$K$1) -> 20.351641 | ... N46: =_xll.DBRW($B$1,Cons_Region!$D$9,Cons_Region!N$11,$M$1,Cons_Region!$G$9,Cons_Region!$J$9,$N$1,Cons_Region!$B46,$L$1,$K$1) -> 16.299832
B47: Operating Expenses | C47: =_xll.DBRW($B$1,Cons_Region!$D$9,Cons_Region!C$11,$M$1,Cons_Region!$G$9,Cons_Region!$J$9,$N$1,Cons_Region!$B47,$L$1,$K$1) -> 7.6474137 | D47: =_xll.DBRW($B$1,Cons_Region!$D$9,Cons_Region!D$11,$M$1,Cons_Region!$G$9,Cons_Region!$J$9,$N$1,Cons_Region!$B47,$L$1,$K$1) -> 8.1854403 | E47: =_xll.DBRW($B$1,Cons_Region!$D$9,Cons_Region!E$11,$M$1,Cons_Region!$G$9,Cons_Region!$J$9,$N$1,Cons_Region!$B47,$L$1,$K$1) -> 9.5925389 | F47: =_xll.DBRW($B$1,Cons_Region!$D$9,Cons_Region!F$11,$M$1,Cons_Region!$G$9,Cons_Region!$J$9,$N$1,Cons_Region!$B47,$L$1,$K$1) -> 8.5181996 | G47: =_xll.DBRW($B$1,Cons_Region!$D$9,Cons_Region!G$11,$M$1,Cons_Region!$G$9,Cons_Region!$J$9,$N$1,Cons_Region!$B47,$L$1,$K$1) -> 8.4528475 | H47: =_xll.DBRW($B$1,Cons_Region!$D$9,Cons_Region!H$11,$M$1,Cons_Region!$G$9,Cons_Region!$J$9,$N$1,Cons_Region!$B47,$L$1,$K$1) -> 9.6997918 | I47: =_xll.DBRW($B$1,Cons_Region!$D$9,Cons_Region!I$11,$M$1,Cons_Region!$G$9,Cons_Region!$J$9,$N$1,Cons_Region!$B47,$L$1,$K$1) -> 9.0077324 | J47: =_xll.DBRW($B$1,Cons_Region!$D$9,Cons_Region!J$11,$M$1,Cons_Region!$G$9,Cons_Region!$J$9,$N$1,Cons_Region!$B47,$L$1,$K$1) -> 8.7638409 | ... N47: =_xll.DBRW($B$1,Cons_Region!$D$9,Cons_Region!N$11,$M$1,Cons_Region!$G$9,Cons_Region!$J$9,$N$1,Cons_Region!$B47,$L$1,$K$1) -> 9.7192234
B48: Other | C48: =_xll.DBRW($B$1,Cons_Region!$D$9,Cons_Region!C$11,$M$1,Cons_Region!$G$9,Cons_Region!$J$9,$N$2,Cons_Region!$B48,"Total Accounts Line",$K$1) -> 0.013321036 | D48: =_xll.DBRW($B$1,Cons_Region!$D$9,Cons_Region!D$11,$M$1,Cons_Region!$G$9,Cons_Region!$J$9,$N$2,Cons_Region!$B48,"Total Accounts Line",$K$1) -> 0.67014606 | E48: =_xll.DBRW($B$1,Cons_Region!$D$9,Cons_Region!E$11,$M$1,Cons_Region!$G$9,Cons_Region!$J$9,$N$2,Cons_Region!$B48,"Total Accounts Line",$K$1) -> -0.0042525423 | F48: =_xll.DBRW($B$1,Cons_Region!$D$9,Cons_Region!F$11,$M$1,Cons_Region!$G$9,Cons_Region!$J$9,$N$2,Cons_Region!$B48,"Total Accounts Line",$K$1) -> -0.26754939 | G48: =_xll.DBRW($B$1,Cons_Region!$D$9,Cons_Region!G$11,$M$1,Cons_Region!$G$9,Cons_Region!$J$9,$N$2,Cons_Region!$B48,"Total Accounts Line",$K$1) -> -0.38664297 | H48: =_xll.DBRW($B$1,Cons_Region!$D$9,Cons_Region!H$11,$M$1,Cons_Region!$G$9,Cons_Region!$J$9,$N$2,Cons_Region!$B48,"Total Accounts Line",$K$1) -> -0.78180852 | I48: =_xll.DBRW($B$1,Cons_Region!$D$9,Cons_Region!I$11,$M$1,Cons_Region!$G$9,Cons_Region!$J$9,$N$2,Cons_Region!$B48,"Total Accounts Line",$K$1) -> -0.23141709 | J48: =_xll.DBRW($B$1,Cons_Region!$D$9,Cons_Region!J$11,$M$1,Cons_Region!$G$9,Cons_Region!$J$9,$N$2,Cons_Region!$B48,"Total Accounts Line",$K$1) -> -0.3926189 | ... N48: =_xll.DBRW($B$1,Cons_Region!$D$9,Cons_Region!N$11,$M$1,Cons_Region!$G$9,Cons_Region!$J$9,$N$2,Cons_Region!$B48,"Total Accounts Line",$K$1) -> 1.0399677
B49: EBITDA | C49: =_xll.DBRW($B$3,Cons_Region!$D$9,Cons_Region!C$11,$M$1,Cons_Region!$G$9,Cons_Region!$J$9,$N$2,Cons_Region!$B49,$K$1) -> -20.517267 | D49: =_xll.DBRW($B$3,Cons_Region!$D$9,Cons_Region!D$11,$M$1,Cons_Region!$G$9,Cons_Region!$J$9,$N$2,Cons_Region!$B49,$K$1) -> -19.574699 | E49: =_xll.DBRW($B$3,Cons_Region!$D$9,Cons_Region!E$11,$M$1,Cons_Region!$G$9,Cons_Region!$J$9,$N$2,Cons_Region!$B49,$K$1) -> 2.3789114 | F49: =_xll.DBRW($B$3,Cons_Region!$D$9,Cons_Region!F$11,$M$1,Cons_Region!$G$9,Cons_Region!$J$9,$N$2,Cons_Region!$B49,$K$1) -> 27.698911 | G49: =_xll.DBRW($B$3,Cons_Region!$D$9,Cons_Region!G$11,$M$1,Cons_Region!$G$9,Cons_Region!$J$9,$N$2,Cons_Region!$B49,$K$1) -> 54.666531 | H49: =_xll.DBRW($B$3,Cons_Region!$D$9,Cons_Region!H$11,$M$1,Cons_Region!$G$9,Cons_Region!$J$9,$N$2,Cons_Region!$B49,$K$1) -> 64.286844 | I49: =_xll.DBRW($B$3,Cons_Region!$D$9,Cons_Region!I$11,$M$1,Cons_Region!$G$9,Cons_Region!$J$9,$N$2,Cons_Region!$B49,$K$1) -> 65.365946 | J49: =_xll.DBRW($B$3,Cons_Region!$D$9,Cons_Region!J$11,$M$1,Cons_Region!$G$9,Cons_Region!$J$9,$N$2,Cons_Region!$B49,$K$1) -> 64.100911 | ... N49: =_xll.DBRW($B$3,Cons_Region!$D$9,Cons_Region!N$11,$M$1,Cons_Region!$G$9,Cons_Region!$J$9,$N$2,Cons_Region!$B49,$K$1) -> 20.221443
B52: Operating Profit
C54: =$D$9&"."&C$11 -> 2026.01 | D54: =$D$9&"."&D$11 -> 2026.02 | E54: =$D$9&"."&E$11 -> 2026.03 | F54: =$D$9&"."&F$11 -> 2026.04 | G54: =$D$9&"."&G$11 -> 2026.05 | H54: =$D$9&"."&H$11 -> 2026.06 | I54: =$D$9&"."&I$11 -> 2026.07 | J54: =$D$9&"."&J$11 -> 2026.08 | ... N54: =$D$9&"."&N$11 -> 2026.12
B55: Depreciation / amortization / depletion - Corporate | C55: =_xll.DBRW($B$1,Cons_Region!$D$9,Cons_Region!C$11,$M$1,Cons_Region!$G$9,Cons_Region!$J$9,$N$1,Cons_Region!$B55,$L$1,$K$1) -> 15.352669 | D55: =_xll.DBRW($B$1,Cons_Region!$D$9,Cons_Region!D$11,$M$1,Cons_Region!$G$9,Cons_Region!$J$9,$N$1,Cons_Region!$B55,$L$1,$K$1) -> 15.536694 | E55: =_xll.DBRW($B$1,Cons_Region!$D$9,Cons_Region!E$11,$M$1,Cons_Region!$G$9,Cons_Region!$J$9,$N$1,Cons_Region!$B55,$L$1,$K$1) -> 16.603118 | F55: =_xll.DBRW($B$1,Cons_Region!$D$9,Cons_Region!F$11,$M$1,Cons_Region!$G$9,Cons_Region!$J$9,$N$1,Cons_Region!$B55,$L$1,$K$1) -> 16.662678 | G55: =_xll.DBRW($B$1,Cons_Region!$D$9,Cons_Region!G$11,$M$1,Cons_Region!$G$9,Cons_Region!$J$9,$N$1,Cons_Region!$B55,$L$1,$K$1) -> 16.728464 | H55: =_xll.DBRW($B$1,Cons_Region!$D$9,Cons_Region!H$11,$M$1,Cons_Region!$G$9,Cons_Region!$J$9,$N$1,Cons_Region!$B55,$L$1,$K$1) -> 17.065599 | I55: =_xll.DBRW($B$1,Cons_Region!$D$9,Cons_Region!I$11,$M$1,Cons_Region!$G$9,Cons_Region!$J$9,$N$1,Cons_Region!$B55,$L$1,$K$1) -> 16.709348 | J55: =_xll.DBRW($B$1,Cons_Region!$D$9,Cons_Region!J$11,$M$1,Cons_Region!$G$9,Cons_Region!$J$9,$N$1,Cons_Region!$B55,$L$1,$K$1) -> 16.725034 | ... N55: =_xll.DBRW($B$1,Cons_Region!$D$9,Cons_Region!N$11,$M$1,Cons_Region!$G$9,Cons_Region!$J$9,$N$1,Cons_Region!$B55,$L$1,$K$1) -> 16.325931
B56: EBITDA | C56: =_xll.DBRW($B$3,Cons_Region!$D$9,Cons_Region!C$11,$M$1,Cons_Region!$G$9,Cons_Region!$J$9,$N$2,Cons_Region!$B56,$K$1) -> -20.517267 | D56: =_xll.DBRW($B$3,Cons_Region!$D$9,Cons_Region!D$11,$M$1,Cons_Region!$G$9,Cons_Region!$J$9,$N$2,Cons_Region!$B56,$K$1) -> -19.574699 | E56: =_xll.DBRW($B$3,Cons_Region!$D$9,Cons_Region!E$11,$M$1,Cons_Region!$G$9,Cons_Region!$J$9,$N$2,Cons_Region!$B56,$K$1) -> 2.3789114 | F56: =_xll.DBRW($B$3,Cons_Region!$D$9,Cons_Region!F$11,$M$1,Cons_Region!$G$9,Cons_Region!$J$9,$N$2,Cons_Region!$B56,$K$1) -> 27.698911 | G56: =_xll.DBRW($B$3,Cons_Region!$D$9,Cons_Region!G$11,$M$1,Cons_Region!$G$9,Cons_Region!$J$9,$N$2,Cons_Region!$B56,$K$1) -> 54.666531 | H56: =_xll.DBRW($B$3,Cons_Region!$D$9,Cons_Region!H$11,$M$1,Cons_Region!$G$9,Cons_Region!$J$9,$N$2,Cons_Region!$B56,$K$1) -> 64.286844 | I56: =_xll.DBRW($B$3,Cons_Region!$D$9,Cons_Region!I$11,$M$1,Cons_Region!$G$9,Cons_Region!$J$9,$N$2,Cons_Region!$B56,$K$1) -> 65.365946 | J56: =_xll.DBRW($B$3,Cons_Region!$D$9,Cons_Region!J$11,$M$1,Cons_Region!$G$9,Cons_Region!$J$9,$N$2,Cons_Region!$B56,$K$1) -> 64.100911 | ... N56: =_xll.DBRW($B$3,Cons_Region!$D$9,Cons_Region!N$11,$M$1,Cons_Region!$G$9,Cons_Region!$J$9,$N$2,Cons_Region!$B56,$K$1) -> 20.221443
B57: Operating Profit | C57: =_xll.DBRW($B$3,Cons_Region!$D$9,Cons_Region!C$11,$M$1,Cons_Region!$G$9,Cons_Region!$J$9,$N$2,Cons_Region!$B57,$K$1) -> -35.869936 | D57: =_xll.DBRW($B$3,Cons_Region!$D$9,Cons_Region!D$11,$M$1,Cons_Region!$G$9,Cons_Region!$J$9,$N$2,Cons_Region!$B57,$K$1) -> -35.111393 | E57: =_xll.DBRW($B$3,Cons_Region!$D$9,Cons_Region!E$11,$M$1,Cons_Region!$G$9,Cons_Region!$J$9,$N$2,Cons_Region!$B57,$K$1) -> -14.224206 | F57: =_xll.DBRW($B$3,Cons_Region!$D$9,Cons_Region!F$11,$M$1,Cons_Region!$G$9,Cons_Region!$J$9,$N$2,Cons_Region!$B57,$K$1) -> 11.036234 | G57: =_xll.DBRW($B$3,Cons_Region!$D$9,Cons_Region!G$11,$M$1,Cons_Region!$G$9,Cons_Region!$J$9,$N$2,Cons_Region!$B57,$K$1) -> 37.938067 | H57: =_xll.DBRW($B$3,Cons_Region!$D$9,Cons_Region!H$11,$M$1,Cons_Region!$G$9,Cons_Region!$J$9,$N$2,Cons_Region!$B57,$K$1) -> 47.221246 | I57: =_xll.DBRW($B$3,Cons_Region!$D$9,Cons_Region!I$11,$M$1,Cons_Region!$G$9,Cons_Region!$J$9,$N$2,Cons_Region!$B57,$K$1) -> 48.656598 | J57: =_xll.DBRW($B$3,Cons_Region!$D$9,Cons_Region!J$11,$M$1,Cons_Region!$G$9,Cons_Region!$J$9,$N$2,Cons_Region!$B57,$K$1) -> 47.375877 | ... N57: =_xll.DBRW($B$3,Cons_Region!$D$9,Cons_Region!N$11,$M$1,Cons_Region!$G$9,Cons_Region!$J$9,$N$2,Cons_Region!$B57,$K$1) -> 3.8955123
B60: Profit Before Income Tax
C62: =$D$9&"."&C$11 -> 2026.01 | D62: =$D$9&"."&D$11 -> 2026.02 | E62: =$D$9&"."&E$11 -> 2026.03 | F62: =$D$9&"."&F$11 -> 2026.04 | G62: =$D$9&"."&G$11 -> 2026.05 | H62: =$D$9&"."&H$11 -> 2026.06 | I62: =$D$9&"."&I$11 -> 2026.07 | J62: =$D$9&"."&J$11 -> 2026.08 | ... N62: =$D$9&"."&N$11 -> 2026.12
B63: Equity Pick-Up Results | C63: =_xll.DBRW($B$1,Cons_Region!$D$9,Cons_Region!C$11,$M$1,Cons_Region!$G$9,Cons_Region!$J$9,$N$1,Cons_Region!$B63,$L$1,$K$1) -> -0.32575548 | D63: =_xll.DBRW($B$1,Cons_Region!$D$9,Cons_Region!D$11,$M$1,Cons_Region!$G$9,Cons_Region!$J$9,$N$1,Cons_Region!$B63,$L$1,$K$1) -> -0.58191422 | E63: =_xll.DBRW($B$1,Cons_Region!$D$9,Cons_Region!E$11,$M$1,Cons_Region!$G$9,Cons_Region!$J$9,$N$1,Cons_Region!$B63,$L$1,$K$1) -> -0.028114877 | F63: =_xll.DBRW($B$1,Cons_Region!$D$9,Cons_Region!F$11,$M$1,Cons_Region!$G$9,Cons_Region!$J$9,$N$1,Cons_Region!$B63,$L$1,$K$1) -> 0.0034494773 | G63: =_xll.DBRW($B$1,Cons_Region!$D$9,Cons_Region!G$11,$M$1,Cons_Region!$G$9,Cons_Region!$J$9,$N$1,Cons_Region!$B63,$L$1,$K$1) -> 0.33324574 | H63: =_xll.DBRW($B$1,Cons_Region!$D$9,Cons_Region!H$11,$M$1,Cons_Region!$G$9,Cons_Region!$J$9,$N$1,Cons_Region!$B63,$L$1,$K$1) -> 0.35928553 | I63: =_xll.DBRW($B$1,Cons_Region!$D$9,Cons_Region!I$11,$M$1,Cons_Region!$G$9,Cons_Region!$J$9,$N$1,Cons_Region!$B63,$L$1,$K$1) -> 0.33968065 | J63: =_xll.DBRW($B$1,Cons_Region!$D$9,Cons_Region!J$11,$M$1,Cons_Region!$G$9,Cons_Region!$J$9,$N$1,Cons_Region!$B63,$L$1,$K$1) -> 0.52090553 | ... N63: =_xll.DBRW($B$1,Cons_Region!$D$9,Cons_Region!N$11,$M$1,Cons_Region!$G$9,Cons_Region!$J$9,$N$1,Cons_Region!$B63,$L$1,$K$1) -> 0.23763179
B64: Other Non Operating Results | C64: =_xll.DBRW($B$1,Cons_Region!$D$9,Cons_Region!C$11,$M$1,Cons_Region!$G$9,Cons_Region!$J$9,$N$1,Cons_Region!$B64,$L$1,$K$1) -> 0 | D64: =_xll.DBRW($B$1,Cons_Region!$D$9,Cons_Region!D$11,$M$1,Cons_Region!$G$9,Cons_Region!$J$9,$N$1,Cons_Region!$B64,$L$1,$K$1) -> 0 | E64: =_xll.DBRW($B$1,Cons_Region!$D$9,Cons_Region!E$11,$M$1,Cons_Region!$G$9,Cons_Region!$J$9,$N$1,Cons_Region!$B64,$L$1,$K$1) -> 0 | F64: =_xll.DBRW($B$1,Cons_Region!$D$9,Cons_Region!F$11,$M$1,Cons_Region!$G$9,Cons_Region!$J$9,$N$1,Cons_Region!$B64,$L$1,$K$1) -> 0 | G64: =_xll.DBRW($B$1,Cons_Region!$D$9,Cons_Region!G$11,$M$1,Cons_Region!$G$9,Cons_Region!$J$9,$N$1,Cons_Region!$B64,$L$1,$K$1) -> 0 | H64: =_xll.DBRW($B$1,Cons_Region!$D$9,Cons_Region!H$11,$M$1,Cons_Region!$G$9,Cons_Region!$J$9,$N$1,Cons_Region!$B64,$L$1,$K$1) -> 0 | I64: =_xll.DBRW($B$1,Cons_Region!$D$9,Cons_Region!I$11,$M$1,Cons_Region!$G$9,Cons_Region!$J$9,$N$1,Cons_Region!$B64,$L$1,$K$1) -> 0 | J64: =_xll.DBRW($B$1,Cons_Region!$D$9,Cons_Region!J$11,$M$1,Cons_Region!$G$9,Cons_Region!$J$9,$N$1,Cons_Region!$B64,$L$1,$K$1) -> 0 | ... N64: =_xll.DBRW($B$1,Cons_Region!$D$9,Cons_Region!N$11,$M$1,Cons_Region!$G$9,Cons_Region!$J$9,$N$1,Cons_Region!$B64,$L$1,$K$1) -> 0
B65: Financial Results | C65: =_xll.DBRW($B$3,Cons_Region!$D$9,Cons_Region!C$11,$M$1,Cons_Region!$G$9,Cons_Region!$J$9,$N$2,Cons_Region!$B65,$K$1) -> 1.7295282 | D65: =_xll.DBRW($B$3,Cons_Region!$D$9,Cons_Region!D$11,$M$1,Cons_Region!$G$9,Cons_Region!$J$9,$N$2,Cons_Region!$B65,$K$1) -> -5.4000291 | E65: =_xll.DBRW($B$3,Cons_Region!$D$9,Cons_Region!E$11,$M$1,Cons_Region!$G$9,Cons_Region!$J$9,$N$2,Cons_Region!$B65,$K$1) -> -6.8554214 | F65: =_xll.DBRW($B$3,Cons_Region!$D$9,Cons_Region!F$11,$M$1,Cons_Region!$G$9,Cons_Region!$J$9,$N$2,Cons_Region!$B65,$K$1) -> -6.9932327 | G65: =_xll.DBRW($B$3,Cons_Region!$D$9,Cons_Region!G$11,$M$1,Cons_Region!$G$9,Cons_Region!$J$9,$N$2,Cons_Region!$B65,$K$1) -> -6.2571223 | H65: =_xll.DBRW($B$3,Cons_Region!$D$9,Cons_Region!H$11,$M$1,Cons_Region!$G$9,Cons_Region!$J$9,$N$2,Cons_Region!$B65,$K$1) -> -8.4361242 | I65: =_xll.DBRW($B$3,Cons_Region!$D$9,Cons_Region!I$11,$M$1,Cons_Region!$G$9,Cons_Region!$J$9,$N$2,Cons_Region!$B65,$K$1) -> -4.9359176 | J65: =_xll.DBRW($B$3,Cons_Region!$D$9,Cons_Region!J$11,$M$1,Cons_Region!$G$9,Cons_Region!$J$9,$N$2,Cons_Region!$B65,$K$1) -> -7.0739169 | ... N65: =_xll.DBRW($B$3,Cons_Region!$D$9,Cons_Region!N$11,$M$1,Cons_Region!$G$9,Cons_Region!$J$9,$N$2,Cons_Region!$B65,$K$1) -> -7.2190236
B66: Profit Before Income Tax | C66: =_xll.DBRW($B$3,Cons_Region!$D$9,Cons_Region!C$11,$M$1,Cons_Region!$G$9,Cons_Region!$J$9,$N$2,Cons_Region!$B66,$K$1) -> -34.466164 | D66: =_xll.DBRW($B$3,Cons_Region!$D$9,Cons_Region!D$11,$M$1,Cons_Region!$G$9,Cons_Region!$J$9,$N$2,Cons_Region!$B66,$K$1) -> -41.093336 | E66: =_xll.DBRW($B$3,Cons_Region!$D$9,Cons_Region!E$11,$M$1,Cons_Region!$G$9,Cons_Region!$J$9,$N$2,Cons_Region!$B66,$K$1) -> -21.107742 | F66: =_xll.DBRW($B$3,Cons_Region!$D$9,Cons_Region!F$11,$M$1,Cons_Region!$G$9,Cons_Region!$J$9,$N$2,Cons_Region!$B66,$K$1) -> 4.0464503 | G66: =_xll.DBRW($B$3,Cons_Region!$D$9,Cons_Region!G$11,$M$1,Cons_Region!$G$9,Cons_Region!$J$9,$N$2,Cons_Region!$B66,$K$1) -> 32.014191 | H66: =_xll.DBRW($B$3,Cons_Region!$D$9,Cons_Region!H$11,$M$1,Cons_Region!$G$9,Cons_Region!$J$9,$N$2,Cons_Region!$B66,$K$1) -> 39.144407 | I66: =_xll.DBRW($B$3,Cons_Region!$D$9,Cons_Region!I$11,$M$1,Cons_Region!$G$9,Cons_Region!$J$9,$N$2,Cons_Region!$B66,$K$1) -> 44.060361 | J66: =_xll.DBRW($B$3,Cons_Region!$D$9,Cons_Region!J$11,$M$1,Cons_Region!$G$9,Cons_Region!$J$9,$N$2,Cons_Region!$B66,$K$1) -> 40.822866 | ... N66: =_xll.DBRW($B$3,Cons_Region!$D$9,Cons_Region!N$11,$M$1,Cons_Region!$G$9,Cons_Region!$J$9,$N$2,Cons_Region!$B66,$K$1) -> -3.0858795
B69: Net Profit Before Minority Int.
C71: =$D$9&"."&C$11 -> 2026.01 | D71: =$D$9&"."&D$11 -> 2026.02 | E71: =$D$9&"."&E$11 -> 2026.03 | F71: =$D$9&"."&F$11 -> 2026.04 | G71: =$D$9&"."&G$11 -> 2026.05 | H71: =$D$9&"."&H$11 -> 2026.06 | I71: =$D$9&"."&I$11 -> 2026.07 | J71: =$D$9&"."&J$11 -> 2026.08 | ... N71: =$D$9&"."&N$11 -> 2026.12
B72: Additions/Low IT Income Statement | C72: =_xll.DBRW($B$1,Cons_Region!$D$9,Cons_Region!C$11,$M$1,Cons_Region!$G$9,Cons_Region!$J$9,$N$1,Cons_Region!$B72,$L$1,$K$1) -> 0 | D72: =_xll.DBRW($B$1,Cons_Region!$D$9,Cons_Region!D$11,$M$1,Cons_Region!$G$9,Cons_Region!$J$9,$N$1,Cons_Region!$B72,$L$1,$K$1) -> 0 | E72: =_xll.DBRW($B$1,Cons_Region!$D$9,Cons_Region!E$11,$M$1,Cons_Region!$G$9,Cons_Region!$J$9,$N$1,Cons_Region!$B72,$L$1,$K$1) -> 0 | F72: =_xll.DBRW($B$1,Cons_Region!$D$9,Cons_Region!F$11,$M$1,Cons_Region!$G$9,Cons_Region!$J$9,$N$1,Cons_Region!$B72,$L$1,$K$1) -> 0 | G72: =_xll.DBRW($B$1,Cons_Region!$D$9,Cons_Region!G$11,$M$1,Cons_Region!$G$9,Cons_Region!$J$9,$N$1,Cons_Region!$B72,$L$1,$K$1) -> 0 | H72: =_xll.DBRW($B$1,Cons_Region!$D$9,Cons_Region!H$11,$M$1,Cons_Region!$G$9,Cons_Region!$J$9,$N$1,Cons_Region!$B72,$L$1,$K$1) -> 0 | I72: =_xll.DBRW($B$1,Cons_Region!$D$9,Cons_Region!I$11,$M$1,Cons_Region!$G$9,Cons_Region!$J$9,$N$1,Cons_Region!$B72,$L$1,$K$1) -> 0 | J72: =_xll.DBRW($B$1,Cons_Region!$D$9,Cons_Region!J$11,$M$1,Cons_Region!$G$9,Cons_Region!$J$9,$N$1,Cons_Region!$B72,$L$1,$K$1) -> 0 | ... N72: =_xll.DBRW($B$1,Cons_Region!$D$9,Cons_Region!N$11,$M$1,Cons_Region!$G$9,Cons_Region!$J$9,$N$1,Cons_Region!$B72,$L$1,$K$1) -> 0
B73: % Income Tax | C73: =_xll.DBRW($C$1,Cons_Region!$D$9,Cons_Region!C$11,$M$1,Cons_Region!$J$9,Cons_Region!$B73,$K$1) -> 0 | D73: =_xll.DBRW($C$1,Cons_Region!$D$9,Cons_Region!D$11,$M$1,Cons_Region!$J$9,Cons_Region!$B73,$K$1) -> 0 | E73: =_xll.DBRW($C$1,Cons_Region!$D$9,Cons_Region!E$11,$M$1,Cons_Region!$J$9,Cons_Region!$B73,$K$1) -> 0 | F73: =_xll.DBRW($C$1,Cons_Region!$D$9,Cons_Region!F$11,$M$1,Cons_Region!$J$9,Cons_Region!$B73,$K$1) -> 0 | G73: =_xll.DBRW($C$1,Cons_Region!$D$9,Cons_Region!G$11,$M$1,Cons_Region!$J$9,Cons_Region!$B73,$K$1) -> 0 | H73: =_xll.DBRW($C$1,Cons_Region!$D$9,Cons_Region!H$11,$M$1,Cons_Region!$J$9,Cons_Region!$B73,$K$1) -> 0 | I73: =_xll.DBRW($C$1,Cons_Region!$D$9,Cons_Region!I$11,$M$1,Cons_Region!$J$9,Cons_Region!$B73,$K$1) -> 0 | J73: =_xll.DBRW($C$1,Cons_Region!$D$9,Cons_Region!J$11,$M$1,Cons_Region!$J$9,Cons_Region!$B73,$K$1) -> 0 | ... N73: =_xll.DBRW($C$1,Cons_Region!$D$9,Cons_Region!N$11,$M$1,Cons_Region!$J$9,Cons_Region!$B73,$K$1) -> 0
B74: Income Tax | C74: =_xll.DBRW($B$1,Cons_Region!$D$9,Cons_Region!C$11,$M$1,Cons_Region!$G$9,Cons_Region!$J$9,$N$1,Cons_Region!$B74,$L$1,$K$1) -> -10.00364 | D74: =_xll.DBRW($B$1,Cons_Region!$D$9,Cons_Region!D$11,$M$1,Cons_Region!$G$9,Cons_Region!$J$9,$N$1,Cons_Region!$B74,$L$1,$K$1) -> -11.607375 | E74: =_xll.DBRW($B$1,Cons_Region!$D$9,Cons_Region!E$11,$M$1,Cons_Region!$G$9,Cons_Region!$J$9,$N$1,Cons_Region!$B74,$L$1,$K$1) -> -5.2767613 | F74: =_xll.DBRW($B$1,Cons_Region!$D$9,Cons_Region!F$11,$M$1,Cons_Region!$G$9,Cons_Region!$J$9,$N$1,Cons_Region!$B74,$L$1,$K$1) -> 1.0117659 | G74: =_xll.DBRW($B$1,Cons_Region!$D$9,Cons_Region!G$11,$M$1,Cons_Region!$G$9,Cons_Region!$J$9,$N$1,Cons_Region!$B74,$L$1,$K$1) -> 8.0034337 | H74: =_xll.DBRW($B$1,Cons_Region!$D$9,Cons_Region!H$11,$M$1,Cons_Region!$G$9,Cons_Region!$J$9,$N$1,Cons_Region!$B74,$L$1,$K$1) -> 9.7859702 | I74: =_xll.DBRW($B$1,Cons_Region!$D$9,Cons_Region!I$11,$M$1,Cons_Region!$G$9,Cons_Region!$J$9,$N$1,Cons_Region!$B74,$L$1,$K$1) -> 11.015266 | J74: =_xll.DBRW($B$1,Cons_Region!$D$9,Cons_Region!J$11,$M$1,Cons_Region!$G$9,Cons_Region!$J$9,$N$1,Cons_Region!$B74,$L$1,$K$1) -> 10.205866 | ... N74: =_xll.DBRW($B$1,Cons_Region!$D$9,Cons_Region!N$11,$M$1,Cons_Region!$G$9,Cons_Region!$J$9,$N$1,Cons_Region!$B74,$L$1,$K$1) -> 4.3826529
B75: Net Profit Before Minority Int. | C75: =_xll.DBRW($B$3,Cons_Region!$D$9,Cons_Region!C$11,$M$1,Cons_Region!$G$9,Cons_Region!$J$9,$N$2,Cons_Region!$B75,$K$1) -> -24.462524 | D75: =_xll.DBRW($B$3,Cons_Region!$D$9,Cons_Region!D$11,$M$1,Cons_Region!$G$9,Cons_Region!$J$9,$N$2,Cons_Region!$B75,$K$1) -> -29.485961 | E75: =_xll.DBRW($B$3,Cons_Region!$D$9,Cons_Region!E$11,$M$1,Cons_Region!$G$9,Cons_Region!$J$9,$N$2,Cons_Region!$B75,$K$1) -> -15.830981 | F75: =_xll.DBRW($B$3,Cons_Region!$D$9,Cons_Region!F$11,$M$1,Cons_Region!$G$9,Cons_Region!$J$9,$N$2,Cons_Region!$B75,$K$1) -> 3.0346845 | G75: =_xll.DBRW($B$3,Cons_Region!$D$9,Cons_Region!G$11,$M$1,Cons_Region!$G$9,Cons_Region!$J$9,$N$2,Cons_Region!$B75,$K$1) -> 24.010757 | H75: =_xll.DBRW($B$3,Cons_Region!$D$9,Cons_Region!H$11,$M$1,Cons_Region!$G$9,Cons_Region!$J$9,$N$2,Cons_Region!$B75,$K$1) -> 29.358437 | I75: =_xll.DBRW($B$3,Cons_Region!$D$9,Cons_Region!I$11,$M$1,Cons_Region!$G$9,Cons_Region!$J$9,$N$2,Cons_Region!$B75,$K$1) -> 33.045095 | J75: =_xll.DBRW($B$3,Cons_Region!$D$9,Cons_Region!J$11,$M$1,Cons_Region!$G$9,Cons_Region!$J$9,$N$2,Cons_Region!$B75,$K$1) -> 30.617 | ... N75: =_xll.DBRW($B$3,Cons_Region!$D$9,Cons_Region!N$11,$M$1,Cons_Region!$G$9,Cons_Region!$J$9,$N$2,Cons_Region!$B75,$K$1) -> -7.4685325
B78: Net Profit
C80: =$D$9&"."&C$11 -> 2026.01 | D80: =$D$9&"."&D$11 -> 2026.02 | E80: =$D$9&"."&E$11 -> 2026.03 | F80: =$D$9&"."&F$11 -> 2026.04 | G80: =$D$9&"."&G$11 -> 2026.05 | H80: =$D$9&"."&H$11 -> 2026.06 | I80: =$D$9&"."&I$11 -> 2026.07 | J80: =$D$9&"."&J$11 -> 2026.08 | ... N80: =$D$9&"."&N$11 -> 2026.12
B81: % Minoritários | C81: =_xll.DBRW($C$1,Cons_Region!$D$9,Cons_Region!C$11,$M$1,Cons_Region!$J$9,Cons_Region!$B81,$K$1) -> 0.17 | D81: =_xll.DBRW($C$1,Cons_Region!$D$9,Cons_Region!D$11,$M$1,Cons_Region!$J$9,Cons_Region!$B81,$K$1) -> 0.17 | E81: =_xll.DBRW($C$1,Cons_Region!$D$9,Cons_Region!E$11,$M$1,Cons_Region!$J$9,Cons_Region!$B81,$K$1) -> 0.17 | F81: =_xll.DBRW($C$1,Cons_Region!$D$9,Cons_Region!F$11,$M$1,Cons_Region!$J$9,Cons_Region!$B81,$K$1) -> 0.17 | G81: =_xll.DBRW($C$1,Cons_Region!$D$9,Cons_Region!G$11,$M$1,Cons_Region!$J$9,Cons_Region!$B81,$K$1) -> 0.17 | H81: =_xll.DBRW($C$1,Cons_Region!$D$9,Cons_Region!H$11,$M$1,Cons_Region!$J$9,Cons_Region!$B81,$K$1) -> 0.17 | I81: =_xll.DBRW($C$1,Cons_Region!$D$9,Cons_Region!I$11,$M$1,Cons_Region!$J$9,Cons_Region!$B81,$K$1) -> 0.17 | J81: =_xll.DBRW($C$1,Cons_Region!$D$9,Cons_Region!J$11,$M$1,Cons_Region!$J$9,Cons_Region!$B81,$K$1) -> 0.17 | ... N81: =_xll.DBRW($C$1,Cons_Region!$D$9,Cons_Region!N$11,$M$1,Cons_Region!$J$9,Cons_Region!$B81,$K$1) -> 0.17
B82: Minority Interests | C82: =_xll.DBRW($B$3,Cons_Region!$D$9,Cons_Region!C$11,$M$1,Cons_Region!$G$9,Cons_Region!$J$9,$N$2,Cons_Region!$B82,$K$1) -> -4.1586291 | D82: =_xll.DBRW($B$3,Cons_Region!$D$9,Cons_Region!D$11,$M$1,Cons_Region!$G$9,Cons_Region!$J$9,$N$2,Cons_Region!$B82,$K$1) -> -5.0126134 | E82: =_xll.DBRW($B$3,Cons_Region!$D$9,Cons_Region!E$11,$M$1,Cons_Region!$G$9,Cons_Region!$J$9,$N$2,Cons_Region!$B82,$K$1) -> -2.6912668 | F82: =_xll.DBRW($B$3,Cons_Region!$D$9,Cons_Region!F$11,$M$1,Cons_Region!$G$9,Cons_Region!$J$9,$N$2,Cons_Region!$B82,$K$1) -> 0.51589636 | G82: =_xll.DBRW($B$3,Cons_Region!$D$9,Cons_Region!G$11,$M$1,Cons_Region!$G$9,Cons_Region!$J$9,$N$2,Cons_Region!$B82,$K$1) -> 4.0818287 | H82: =_xll.DBRW($B$3,Cons_Region!$D$9,Cons_Region!H$11,$M$1,Cons_Region!$G$9,Cons_Region!$J$9,$N$2,Cons_Region!$B82,$K$1) -> 4.9909343 | I82: =_xll.DBRW($B$3,Cons_Region!$D$9,Cons_Region!I$11,$M$1,Cons_Region!$G$9,Cons_Region!$J$9,$N$2,Cons_Region!$B82,$K$1) -> 5.6176662 | J82: =_xll.DBRW($B$3,Cons_Region!$D$9,Cons_Region!J$11,$M$1,Cons_Region!$G$9,Cons_Region!$J$9,$N$2,Cons_Region!$B82,$K$1) -> 5.2048901 | ... N82: =_xll.DBRW($B$3,Cons_Region!$D$9,Cons_Region!N$11,$M$1,Cons_Region!$G$9,Cons_Region!$J$9,$N$2,Cons_Region!$B82,$K$1) -> -1.2696505
B83: Net Profit | C83: =_xll.DBRW($B$3,Cons_Region!$D$9,Cons_Region!C$11,$M$1,Cons_Region!$G$9,Cons_Region!$J$9,$N$2,Cons_Region!$B83,$K$1) -> -20.303895 | D83: =_xll.DBRW($B$3,Cons_Region!$D$9,Cons_Region!D$11,$M$1,Cons_Region!$G$9,Cons_Region!$J$9,$N$2,Cons_Region!$B83,$K$1) -> -24.473348 | E83: =_xll.DBRW($B$3,Cons_Region!$D$9,Cons_Region!E$11,$M$1,Cons_Region!$G$9,Cons_Region!$J$9,$N$2,Cons_Region!$B83,$K$1) -> -13.139714 | F83: =_xll.DBRW($B$3,Cons_Region!$D$9,Cons_Region!F$11,$M$1,Cons_Region!$G$9,Cons_Region!$J$9,$N$2,Cons_Region!$B83,$K$1) -> 2.5187881 | G83: =_xll.DBRW($B$3,Cons_Region!$D$9,Cons_Region!G$11,$M$1,Cons_Region!$G$9,Cons_Region!$J$9,$N$2,Cons_Region!$B83,$K$1) -> 19.928928 | H83: =_xll.DBRW($B$3,Cons_Region!$D$9,Cons_Region!H$11,$M$1,Cons_Region!$G$9,Cons_Region!$J$9,$N$2,Cons_Region!$B83,$K$1) -> 24.367503 | I83: =_xll.DBRW($B$3,Cons_Region!$D$9,Cons_Region!I$11,$M$1,Cons_Region!$G$9,Cons_Region!$J$9,$N$2,Cons_Region!$B83,$K$1) -> 27.427429 | J83: =_xll.DBRW($B$3,Cons_Region!$D$9,Cons_Region!J$11,$M$1,Cons_Region!$G$9,Cons_Region!$J$9,$N$2,Cons_Region!$B83,$K$1) -> 25.41211 | ... N83: =_xll.DBRW($B$3,Cons_Region!$D$9,Cons_Region!N$11,$M$1,Cons_Region!$G$9,Cons_Region!$J$9,$N$2,Cons_Region!$B83,$K$1) -> -6.1988819
B86: Working Capital - KPIs Assets Accounts
C88: =$D$9&"."&C$11 -> 2026.01 | D88: =$D$9&"."&D$11 -> 2026.02 | E88: =$D$9&"."&E$11 -> 2026.03 | F88: =$D$9&"."&F$11 -> 2026.04 | G88: =$D$9&"."&G$11 -> 2026.05 | H88: =$D$9&"."&H$11 -> 2026.06 | I88: =$D$9&"."&I$11 -> 2026.07 | J88: =$D$9&"."&J$11 -> 2026.08 | ... N88: =$D$9&"."&N$11 -> 2026.12
B89: Account Receivable - Days o/ Rev | C89: =_xll.DBRW($B$1,Cons_Region!$D$9,Cons_Region!C$11,$M$1,Cons_Region!$G$9,Cons_Region!$J$9,$N$1,Cons_Region!$B89,$L$1,$K$1) -> #NUM! | D89: =_xll.DBRW($B$1,Cons_Region!$D$9,Cons_Region!D$11,$M$1,Cons_Region!$G$9,Cons_Region!$J$9,$N$1,Cons_Region!$B89,$L$1,$K$1) -> #NUM! | E89: =_xll.DBRW($B$1,Cons_Region!$D$9,Cons_Region!E$11,$M$1,Cons_Region!$G$9,Cons_Region!$J$9,$N$1,Cons_Region!$B89,$L$1,$K$1) -> #NUM! | F89: =_xll.DBRW($B$1,Cons_Region!$D$9,Cons_Region!F$11,$M$1,Cons_Region!$G$9,Cons_Region!$J$9,$N$1,Cons_Region!$B89,$L$1,$K$1) -> #NUM! | G89: =_xll.DBRW($B$1,Cons_Region!$D$9,Cons_Region!G$11,$M$1,Cons_Region!$G$9,Cons_Region!$J$9,$N$1,Cons_Region!$B89,$L$1,$K$1) -> #NUM! | H89: =_xll.DBRW($B$1,Cons_Region!$D$9,Cons_Region!H$11,$M$1,Cons_Region!$G$9,Cons_Region!$J$9,$N$1,Cons_Region!$B89,$L$1,$K$1) -> #NUM! | I89: =_xll.DBRW($B$1,Cons_Region!$D$9,Cons_Region!I$11,$M$1,Cons_Region!$G$9,Cons_Region!$J$9,$N$1,Cons_Region!$B89,$L$1,$K$1) -> #NUM! | J89: =_xll.DBRW($B$1,Cons_Region!$D$9,Cons_Region!J$11,$M$1,Cons_Region!$G$9,Cons_Region!$J$9,$N$1,Cons_Region!$B89,$L$1,$K$1) -> #NUM! | ... N89: =_xll.DBRW($B$1,Cons_Region!$D$9,Cons_Region!N$11,$M$1,Cons_Region!$G$9,Cons_Region!$J$9,$N$1,Cons_Region!$B89,$L$1,$K$1) -> #NUM!
B90: Finished Product Inventory - Days o/ CPS - Other | C90: =_xll.DBRW($B$1,Cons_Region!$D$9,Cons_Region!C$11,$M$1,Cons_Region!$G$9,Cons_Region!$J$9,$N$1,Cons_Region!$B90,$L$1,$K$1) -> #NUM! | D90: =_xll.DBRW($B$1,Cons_Region!$D$9,Cons_Region!D$11,$M$1,Cons_Region!$G$9,Cons_Region!$J$9,$N$1,Cons_Region!$B90,$L$1,$K$1) -> #NUM! | E90: =_xll.DBRW($B$1,Cons_Region!$D$9,Cons_Region!E$11,$M$1,Cons_Region!$G$9,Cons_Region!$J$9,$N$1,Cons_Region!$B90,$L$1,$K$1) -> #NUM! | F90: =_xll.DBRW($B$1,Cons_Region!$D$9,Cons_Region!F$11,$M$1,Cons_Region!$G$9,Cons_Region!$J$9,$N$1,Cons_Region!$B90,$L$1,$K$1) -> #NUM! | G90: =_xll.DBRW($B$1,Cons_Region!$D$9,Cons_Region!G$11,$M$1,Cons_Region!$G$9,Cons_Region!$J$9,$N$1,Cons_Region!$B90,$L$1,$K$1) -> #NUM! | H90: =_xll.DBRW($B$1,Cons_Region!$D$9,Cons_Region!H$11,$M$1,Cons_Region!$G$9,Cons_Region!$J$9,$N$1,Cons_Region!$B90,$L$1,$K$1) -> #NUM! | I90: =_xll.DBRW($B$1,Cons_Region!$D$9,Cons_Region!I$11,$M$1,Cons_Region!$G$9,Cons_Region!$J$9,$N$1,Cons_Region!$B90,$L$1,$K$1) -> #NUM! | J90: =_xll.DBRW($B$1,Cons_Region!$D$9,Cons_Region!J$11,$M$1,Cons_Region!$G$9,Cons_Region!$J$9,$N$1,Cons_Region!$B90,$L$1,$K$1) -> #NUM! | ... N90: =_xll.DBRW($B$1,Cons_Region!$D$9,Cons_Region!N$11,$M$1,Cons_Region!$G$9,Cons_Region!$J$9,$N$1,Cons_Region!$B90,$L$1,$K$1) -> #NUM!
B91: Product in Process Inventory- Days o/ CPS | C91: =_xll.DBRW($B$1,Cons_Region!$D$9,Cons_Region!C$11,$M$1,Cons_Region!$G$9,Cons_Region!$J$9,$N$1,Cons_Region!$B91,$L$1,$K$1) -> #NUM! | D91: =_xll.DBRW($B$1,Cons_Region!$D$9,Cons_Region!D$11,$M$1,Cons_Region!$G$9,Cons_Region!$J$9,$N$1,Cons_Region!$B91,$L$1,$K$1) -> #NUM! | E91: =_xll.DBRW($B$1,Cons_Region!$D$9,Cons_Region!E$11,$M$1,Cons_Region!$G$9,Cons_Region!$J$9,$N$1,Cons_Region!$B91,$L$1,$K$1) -> #NUM! | F91: =_xll.DBRW($B$1,Cons_Region!$D$9,Cons_Region!F$11,$M$1,Cons_Region!$G$9,Cons_Region!$J$9,$N$1,Cons_Region!$B91,$L$1,$K$1) -> #NUM! | G91: =_xll.DBRW($B$1,Cons_Region!$D$9,Cons_Region!G$11,$M$1,Cons_Region!$G$9,Cons_Region!$J$9,$N$1,Cons_Region!$B91,$L$1,$K$1) -> #NUM! | H91: =_xll.DBRW($B$1,Cons_Region!$D$9,Cons_Region!H$11,$M$1,Cons_Region!$G$9,Cons_Region!$J$9,$N$1,Cons_Region!$B91,$L$1,$K$1) -> #NUM! | I91: =_xll.DBRW($B$1,Cons_Region!$D$9,Cons_Region!I$11,$M$1,Cons_Region!$G$9,Cons_Region!$J$9,$N$1,Cons_Region!$B91,$L$1,$K$1) -> #NUM! | J91: =_xll.DBRW($B$1,Cons_Region!$D$9,Cons_Region!J$11,$M$1,Cons_Region!$G$9,Cons_Region!$J$9,$N$1,Cons_Region!$B91,$L$1,$K$1) -> #NUM! | ... N91: =_xll.DBRW($B$1,Cons_Region!$D$9,Cons_Region!N$11,$M$1,Cons_Region!$G$9,Cons_Region!$J$9,$N$1,Cons_Region!$B91,$L$1,$K$1) -> #NUM!
B92: Concentrate Inventory - Days o/ VC | C92: =_xll.DBRW($B$1,Cons_Region!$D$9,Cons_Region!C$11,$M$1,Cons_Region!$G$9,Cons_Region!$J$9,$N$1,Cons_Region!$B92,$L$1,$K$1) -> #NUM! | D92: =_xll.DBRW($B$1,Cons_Region!$D$9,Cons_Region!D$11,$M$1,Cons_Region!$G$9,Cons_Region!$J$9,$N$1,Cons_Region!$B92,$L$1,$K$1) -> #NUM! | E92: =_xll.DBRW($B$1,Cons_Region!$D$9,Cons_Region!E$11,$M$1,Cons_Region!$G$9,Cons_Region!$J$9,$N$1,Cons_Region!$B92,$L$1,$K$1) -> #NUM! | F92: =_xll.DBRW($B$1,Cons_Region!$D$9,Cons_Region!F$11,$M$1,Cons_Region!$G$9,Cons_Region!$J$9,$N$1,Cons_Region!$B92,$L$1,$K$1) -> #NUM! | G92: =_xll.DBRW($B$1,Cons_Region!$D$9,Cons_Region!G$11,$M$1,Cons_Region!$G$9,Cons_Region!$J$9,$N$1,Cons_Region!$B92,$L$1,$K$1) -> #NUM! | H92: =_xll.DBRW($B$1,Cons_Region!$D$9,Cons_Region!H$11,$M$1,Cons_Region!$G$9,Cons_Region!$J$9,$N$1,Cons_Region!$B92,$L$1,$K$1) -> #NUM! | I92: =_xll.DBRW($B$1,Cons_Region!$D$9,Cons_Region!I$11,$M$1,Cons_Region!$G$9,Cons_Region!$J$9,$N$1,Cons_Region!$B92,$L$1,$K$1) -> #NUM! | J92: =_xll.DBRW($B$1,Cons_Region!$D$9,Cons_Region!J$11,$M$1,Cons_Region!$G$9,Cons_Region!$J$9,$N$1,Cons_Region!$B92,$L$1,$K$1) -> #NUM! | ... N92: =_xll.DBRW($B$1,Cons_Region!$D$9,Cons_Region!N$11,$M$1,Cons_Region!$G$9,Cons_Region!$J$9,$N$1,Cons_Region!$B92,$L$1,$K$1) -> #NUM!
B93: MRO Inventory - Days o/ FC | C93: =_xll.DBRW($B$1,Cons_Region!$D$9,Cons_Region!C$11,$M$1,Cons_Region!$G$9,Cons_Region!$J$9,$N$1,Cons_Region!$B93,$L$1,$K$1) -> #NUM! | D93: =_xll.DBRW($B$1,Cons_Region!$D$9,Cons_Region!D$11,$M$1,Cons_Region!$G$9,Cons_Region!$J$9,$N$1,Cons_Region!$B93,$L$1,$K$1) -> #NUM! | E93: =_xll.DBRW($B$1,Cons_Region!$D$9,Cons_Region!E$11,$M$1,Cons_Region!$G$9,Cons_Region!$J$9,$N$1,Cons_Region!$B93,$L$1,$K$1) -> #NUM! | F93: =_xll.DBRW($B$1,Cons_Region!$D$9,Cons_Region!F$11,$M$1,Cons_Region!$G$9,Cons_Region!$J$9,$N$1,Cons_Region!$B93,$L$1,$K$1) -> #NUM! | G93: =_xll.DBRW($B$1,Cons_Region!$D$9,Cons_Region!G$11,$M$1,Cons_Region!$G$9,Cons_Region!$J$9,$N$1,Cons_Region!$B93,$L$1,$K$1) -> #NUM! | H93: =_xll.DBRW($B$1,Cons_Region!$D$9,Cons_Region!H$11,$M$1,Cons_Region!$G$9,Cons_Region!$J$9,$N$1,Cons_Region!$B93,$L$1,$K$1) -> #NUM! | I93: =_xll.DBRW($B$1,Cons_Region!$D$9,Cons_Region!I$11,$M$1,Cons_Region!$G$9,Cons_Region!$J$9,$N$1,Cons_Region!$B93,$L$1,$K$1) -> #NUM! | J93: =_xll.DBRW($B$1,Cons_Region!$D$9,Cons_Region!J$11,$M$1,Cons_Region!$G$9,Cons_Region!$J$9,$N$1,Cons_Region!$B93,$L$1,$K$1) -> #NUM! | ... N93: =_xll.DBRW($B$1,Cons_Region!$D$9,Cons_Region!N$11,$M$1,Cons_Region!$G$9,Cons_Region!$J$9,$N$1,Cons_Region!$B93,$L$1,$K$1) -> #NUM!
B94: Input Inventory- Days o/ VC | C94: =_xll.DBRW($B$1,Cons_Region!$D$9,Cons_Region!C$11,$M$1,Cons_Region!$G$9,Cons_Region!$J$9,$N$1,Cons_Region!$B94,$L$1,$K$1) -> 51.319578 | D94: =_xll.DBRW($B$1,Cons_Region!$D$9,Cons_Region!D$11,$M$1,Cons_Region!$G$9,Cons_Region!$J$9,$N$1,Cons_Region!$B94,$L$1,$K$1) -> 31.636361 | E94: =_xll.DBRW($B$1,Cons_Region!$D$9,Cons_Region!E$11,$M$1,Cons_Region!$G$9,Cons_Region!$J$9,$N$1,Cons_Region!$B94,$L$1,$K$1) -> 28.514488 | F94: =_xll.DBRW($B$1,Cons_Region!$D$9,Cons_Region!F$11,$M$1,Cons_Region!$G$9,Cons_Region!$J$9,$N$1,Cons_Region!$B94,$L$1,$K$1) -> 21.397704 | G94: =_xll.DBRW($B$1,Cons_Region!$D$9,Cons_Region!G$11,$M$1,Cons_Region!$G$9,Cons_Region!$J$9,$N$1,Cons_Region!$B94,$L$1,$K$1) -> 18.740042 | H94: =_xll.DBRW($B$1,Cons_Region!$D$9,Cons_Region!H$11,$M$1,Cons_Region!$G$9,Cons_Region!$J$9,$N$1,Cons_Region!$B94,$L$1,$K$1) -> 17.351903 | I94: =_xll.DBRW($B$1,Cons_Region!$D$9,Cons_Region!I$11,$M$1,Cons_Region!$G$9,Cons_Region!$J$9,$N$1,Cons_Region!$B94,$L$1,$K$1) -> 15.497963 | J94: =_xll.DBRW($B$1,Cons_Region!$D$9,Cons_Region!J$11,$M$1,Cons_Region!$G$9,Cons_Region!$J$9,$N$1,Cons_Region!$B94,$L$1,$K$1) -> 14.88216 | ... N94: =_xll.DBRW($B$1,Cons_Region!$D$9,Cons_Region!N$11,$M$1,Cons_Region!$G$9,Cons_Region!$J$9,$N$1,Cons_Region!$B94,$L$1,$K$1) -> 20.476447
B95: Opex Advancement - Days o/ VC | C95: =_xll.DBRW($B$1,Cons_Region!$D$9,Cons_Region!C$11,$M$1,Cons_Region!$G$9,Cons_Region!$J$9,$N$1,Cons_Region!$B95,$L$1,$K$1) -> #NUM! | D95: =_xll.DBRW($B$1,Cons_Region!$D$9,Cons_Region!D$11,$M$1,Cons_Region!$G$9,Cons_Region!$J$9,$N$1,Cons_Region!$B95,$L$1,$K$1) -> #NUM! | E95: =_xll.DBRW($B$1,Cons_Region!$D$9,Cons_Region!E$11,$M$1,Cons_Region!$G$9,Cons_Region!$J$9,$N$1,Cons_Region!$B95,$L$1,$K$1) -> #NUM! | F95: =_xll.DBRW($B$1,Cons_Region!$D$9,Cons_Region!F$11,$M$1,Cons_Region!$G$9,Cons_Region!$J$9,$N$1,Cons_Region!$B95,$L$1,$K$1) -> #NUM! | G95: =_xll.DBRW($B$1,Cons_Region!$D$9,Cons_Region!G$11,$M$1,Cons_Region!$G$9,Cons_Region!$J$9,$N$1,Cons_Region!$B95,$L$1,$K$1) -> #NUM! | H95: =_xll.DBRW($B$1,Cons_Region!$D$9,Cons_Region!H$11,$M$1,Cons_Region!$G$9,Cons_Region!$J$9,$N$1,Cons_Region!$B95,$L$1,$K$1) -> #NUM! | I95: =_xll.DBRW($B$1,Cons_Region!$D$9,Cons_Region!I$11,$M$1,Cons_Region!$G$9,Cons_Region!$J$9,$N$1,Cons_Region!$B95,$L$1,$K$1) -> #NUM! | J95: =_xll.DBRW($B$1,Cons_Region!$D$9,Cons_Region!J$11,$M$1,Cons_Region!$G$9,Cons_Region!$J$9,$N$1,Cons_Region!$B95,$L$1,$K$1) -> #NUM! | ... N95: =_xll.DBRW($B$1,Cons_Region!$D$9,Cons_Region!N$11,$M$1,Cons_Region!$G$9,Cons_Region!$J$9,$N$1,Cons_Region!$B95,$L$1,$K$1) -> #NUM!
B96: Other Accounts Receivables - Days o/ DSO | C96: =_xll.DBRW($B$1,Cons_Region!$D$9,Cons_Region!C$11,$M$1,Cons_Region!$G$9,Cons_Region!$J$9,$N$1,Cons_Region!$B96,$L$1,$K$1) -> #NUM! | D96: =_xll.DBRW($B$1,Cons_Region!$D$9,Cons_Region!D$11,$M$1,Cons_Region!$G$9,Cons_Region!$J$9,$N$1,Cons_Region!$B96,$L$1,$K$1) -> #NUM! | E96: =_xll.DBRW($B$1,Cons_Region!$D$9,Cons_Region!E$11,$M$1,Cons_Region!$G$9,Cons_Region!$J$9,$N$1,Cons_Region!$B96,$L$1,$K$1) -> #NUM! | F96: =_xll.DBRW($B$1,Cons_Region!$D$9,Cons_Region!F$11,$M$1,Cons_Region!$G$9,Cons_Region!$J$9,$N$1,Cons_Region!$B96,$L$1,$K$1) -> #NUM! | G96: =_xll.DBRW($B$1,Cons_Region!$D$9,Cons_Region!G$11,$M$1,Cons_Region!$G$9,Cons_Region!$J$9,$N$1,Cons_Region!$B96,$L$1,$K$1) -> #NUM! | H96: =_xll.DBRW($B$1,Cons_Region!$D$9,Cons_Region!H$11,$M$1,Cons_Region!$G$9,Cons_Region!$J$9,$N$1,Cons_Region!$B96,$L$1,$K$1) -> #NUM! | I96: =_xll.DBRW($B$1,Cons_Region!$D$9,Cons_Region!I$11,$M$1,Cons_Region!$G$9,Cons_Region!$J$9,$N$1,Cons_Region!$B96,$L$1,$K$1) -> #NUM! | J96: =_xll.DBRW($B$1,Cons_Region!$D$9,Cons_Region!J$11,$M$1,Cons_Region!$G$9,Cons_Region!$J$9,$N$1,Cons_Region!$B96,$L$1,$K$1) -> #NUM! | ... N96: =_xll.DBRW($B$1,Cons_Region!$D$9,Cons_Region!N$11,$M$1,Cons_Region!$G$9,Cons_Region!$J$9,$N$1,Cons_Region!$B96,$L$1,$K$1) -> #NUM!
B98: Working Capital - KPIs Liabilities Accounts
C100: =$D$9&"."&C$11 -> 2026.01 | D100: =$D$9&"."&D$11 -> 2026.02 | E100: =$D$9&"."&E$11 -> 2026.03 | F100: =$D$9&"."&F$11 -> 2026.04 | G100: =$D$9&"."&G$11 -> 2026.05 | H100: =$D$9&"."&H$11 -> 2026.06 | I100: =$D$9&"."&I$11 -> 2026.07 | J100: =$D$9&"."&J$11 -> 2026.08 | ... N100: =$D$9&"."&N$11 -> 2026.12
B101: Suppliers - Days o/ VC (DPO) | C101: =_xll.DBRW($B$1,Cons_Region!$D$9,Cons_Region!C$11,$M$1,Cons_Region!$G$9,Cons_Region!$J$9,$N$1,Cons_Region!$B101,$L$1,$K$1) -> 224.39618 | D101: =_xll.DBRW($B$1,Cons_Region!$D$9,Cons_Region!D$11,$M$1,Cons_Region!$G$9,Cons_Region!$J$9,$N$1,Cons_Region!$B101,$L$1,$K$1) -> 126.69767 | E101: =_xll.DBRW($B$1,Cons_Region!$D$9,Cons_Region!E$11,$M$1,Cons_Region!$G$9,Cons_Region!$J$9,$N$1,Cons_Region!$B101,$L$1,$K$1) -> 136.55151 | F101: =_xll.DBRW($B$1,Cons_Region!$D$9,Cons_Region!F$11,$M$1,Cons_Region!$G$9,Cons_Region!$J$9,$N$1,Cons_Region!$B101,$L$1,$K$1) -> 108.75887 | G101: =_xll.DBRW($B$1,Cons_Region!$D$9,Cons_Region!G$11,$M$1,Cons_Region!$G$9,Cons_Region!$J$9,$N$1,Cons_Region!$B101,$L$1,$K$1) -> 102.36739 | H101: =_xll.DBRW($B$1,Cons_Region!$D$9,Cons_Region!H$11,$M$1,Cons_Region!$G$9,Cons_Region!$J$9,$N$1,Cons_Region!$B101,$L$1,$K$1) -> 90.052615 | I101: =_xll.DBRW($B$1,Cons_Region!$D$9,Cons_Region!I$11,$M$1,Cons_Region!$G$9,Cons_Region!$J$9,$N$1,Cons_Region!$B101,$L$1,$K$1) -> 82.780048 | J101: =_xll.DBRW($B$1,Cons_Region!$D$9,Cons_Region!J$11,$M$1,Cons_Region!$G$9,Cons_Region!$J$9,$N$1,Cons_Region!$B101,$L$1,$K$1) -> 78.121781 | ... N101: =_xll.DBRW($B$1,Cons_Region!$D$9,Cons_Region!N$11,$M$1,Cons_Region!$G$9,Cons_Region!$J$9,$N$1,Cons_Region!$B101,$L$1,$K$1) -> 307.21589
B102: Operating Taxes Payable - % o/ Rev. | C102: =_xll.DBRW($B$1,Cons_Region!$D$9,Cons_Region!C$11,$M$1,Cons_Region!$G$9,Cons_Region!$J$9,$N$1,Cons_Region!$B102,$L$1,$K$1) -> 0.07677181 | D102: =_xll.DBRW($B$1,Cons_Region!$D$9,Cons_Region!D$11,$M$1,Cons_Region!$G$9,Cons_Region!$J$9,$N$1,Cons_Region!$B102,$L$1,$K$1) -> 0.085306504 | E102: =_xll.DBRW($B$1,Cons_Region!$D$9,Cons_Region!E$11,$M$1,Cons_Region!$G$9,Cons_Region!$J$9,$N$1,Cons_Region!$B102,$L$1,$K$1) -> 0.060458139 | F102: =_xll.DBRW($B$1,Cons_Region!$D$9,Cons_Region!F$11,$M$1,Cons_Region!$G$9,Cons_Region!$J$9,$N$1,Cons_Region!$B102,$L$1,$K$1) -> 0.04600187 | G102: =_xll.DBRW($B$1,Cons_Region!$D$9,Cons_Region!G$11,$M$1,Cons_Region!$G$9,Cons_Region!$J$9,$N$1,Cons_Region!$B102,$L$1,$K$1) -> 0.03815351 | H102: =_xll.DBRW($B$1,Cons_Region!$D$9,Cons_Region!H$11,$M$1,Cons_Region!$G$9,Cons_Region!$J$9,$N$1,Cons_Region!$B102,$L$1,$K$1) -> 0.034341744 | I102: =_xll.DBRW($B$1,Cons_Region!$D$9,Cons_Region!I$11,$M$1,Cons_Region!$G$9,Cons_Region!$J$9,$N$1,Cons_Region!$B102,$L$1,$K$1) -> 0.03394226 | J102: =_xll.DBRW($B$1,Cons_Region!$D$9,Cons_Region!J$11,$M$1,Cons_Region!$G$9,Cons_Region!$J$9,$N$1,Cons_Region!$B102,$L$1,$K$1) -> 0.033784859 | ... N102: =_xll.DBRW($B$1,Cons_Region!$D$9,Cons_Region!N$11,$M$1,Cons_Region!$G$9,Cons_Region!$J$9,$N$1,Cons_Region!$B102,$L$1,$K$1) -> 0.073880835
B103: Labor Obligations - Days o/ FC | C103: =_xll.DBRW($B$1,Cons_Region!$D$9,Cons_Region!C$11,$M$1,Cons_Region!$G$9,Cons_Region!$J$9,$N$1,Cons_Region!$B103,$L$1,$K$1) -> 58.077144 | D103: =_xll.DBRW($B$1,Cons_Region!$D$9,Cons_Region!D$11,$M$1,Cons_Region!$G$9,Cons_Region!$J$9,$N$1,Cons_Region!$B103,$L$1,$K$1) -> 37.100978 | E103: =_xll.DBRW($B$1,Cons_Region!$D$9,Cons_Region!E$11,$M$1,Cons_Region!$G$9,Cons_Region!$J$9,$N$1,Cons_Region!$B103,$L$1,$K$1) -> 50.209904 | F103: =_xll.DBRW($B$1,Cons_Region!$D$9,Cons_Region!F$11,$M$1,Cons_Region!$G$9,Cons_Region!$J$9,$N$1,Cons_Region!$B103,$L$1,$K$1) -> 52.374179 | G103: =_xll.DBRW($B$1,Cons_Region!$D$9,Cons_Region!G$11,$M$1,Cons_Region!$G$9,Cons_Region!$J$9,$N$1,Cons_Region!$B103,$L$1,$K$1) -> 81.813103 | H103: =_xll.DBRW($B$1,Cons_Region!$D$9,Cons_Region!H$11,$M$1,Cons_Region!$G$9,Cons_Region!$J$9,$N$1,Cons_Region!$B103,$L$1,$K$1) -> 71.745272 | I103: =_xll.DBRW($B$1,Cons_Region!$D$9,Cons_Region!I$11,$M$1,Cons_Region!$G$9,Cons_Region!$J$9,$N$1,Cons_Region!$B103,$L$1,$K$1) -> 81.693358 | J103: =_xll.DBRW($B$1,Cons_Region!$D$9,Cons_Region!J$11,$M$1,Cons_Region!$G$9,Cons_Region!$J$9,$N$1,Cons_Region!$B103,$L$1,$K$1) -> 89.92183 | ... N103: =_xll.DBRW($B$1,Cons_Region!$D$9,Cons_Region!N$11,$M$1,Cons_Region!$G$9,Cons_Region!$J$9,$N$1,Cons_Region!$B103,$L$1,$K$1) -> 124.63667
B104: Other Accounts Payable - Days o/ CPS | C104: =_xll.DBRW($B$1,Cons_Region!$D$9,Cons_Region!C$11,$M$1,Cons_Region!$G$9,Cons_Region!$J$9,$N$1,Cons_Region!$B104,$L$1,$K$1) -> 31.490487 | D104: =_xll.DBRW($B$1,Cons_Region!$D$9,Cons_Region!D$11,$M$1,Cons_Region!$G$9,Cons_Region!$J$9,$N$1,Cons_Region!$B104,$L$1,$K$1) -> 21.720341 | E104: =_xll.DBRW($B$1,Cons_Region!$D$9,Cons_Region!E$11,$M$1,Cons_Region!$G$9,Cons_Region!$J$9,$N$1,Cons_Region!$B104,$L$1,$K$1) -> 25.355646 | F104: =_xll.DBRW($B$1,Cons_Region!$D$9,Cons_Region!F$11,$M$1,Cons_Region!$G$9,Cons_Region!$J$9,$N$1,Cons_Region!$B104,$L$1,$K$1) -> 19.736084 | G104: =_xll.DBRW($B$1,Cons_Region!$D$9,Cons_Region!G$11,$M$1,Cons_Region!$G$9,Cons_Region!$J$9,$N$1,Cons_Region!$B104,$L$1,$K$1) -> 22.613488 | H104: =_xll.DBRW($B$1,Cons_Region!$D$9,Cons_Region!H$11,$M$1,Cons_Region!$G$9,Cons_Region!$J$9,$N$1,Cons_Region!$B104,$L$1,$K$1) -> 22.129673 | I104: =_xll.DBRW($B$1,Cons_Region!$D$9,Cons_Region!I$11,$M$1,Cons_Region!$G$9,Cons_Region!$J$9,$N$1,Cons_Region!$B104,$L$1,$K$1) -> 22.592856 | J104: =_xll.DBRW($B$1,Cons_Region!$D$9,Cons_Region!J$11,$M$1,Cons_Region!$G$9,Cons_Region!$J$9,$N$1,Cons_Region!$B104,$L$1,$K$1) -> 24.157845 | ... N104: =_xll.DBRW($B$1,Cons_Region!$D$9,Cons_Region!N$11,$M$1,Cons_Region!$G$9,Cons_Region!$J$9,$N$1,Cons_Region!$B104,$L$1,$K$1) -> 44.086338
B107: Working Capital - Assets Account Balance
C109: =$D$9&"."&C$11 -> 2026.01 | D109: =$D$9&"."&D$11 -> 2026.02 | E109: =$D$9&"."&E$11 -> 2026.03 | F109: =$D$9&"."&F$11 -> 2026.04 | G109: =$D$9&"."&G$11 -> 2026.05 | H109: =$D$9&"."&H$11 -> 2026.06 | I109: =$D$9&"."&I$11 -> 2026.07 | J109: =$D$9&"."&J$11 -> 2026.08 | ... N109: =$D$9&"."&N$11 -> 2026.12
B110: Accounts Receivable | C110: =_xll.DBRW($C$3,Cons_Region!$D$9,Cons_Region!C$11,$M$1,Cons_Region!$G$9,Cons_Region!$J$9,$B110,$K$1) -> 49.721167 | D110: =_xll.DBRW($C$3,Cons_Region!$D$9,Cons_Region!D$11,$M$1,Cons_Region!$G$9,Cons_Region!$J$9,$B110,$K$1) -> 50.423219 | E110: =_xll.DBRW($C$3,Cons_Region!$D$9,Cons_Region!E$11,$M$1,Cons_Region!$G$9,Cons_Region!$J$9,$B110,$K$1) -> 65.874174 | F110: =_xll.DBRW($C$3,Cons_Region!$D$9,Cons_Region!F$11,$M$1,Cons_Region!$G$9,Cons_Region!$J$9,$B110,$K$1) -> 73.427309 | G110: =_xll.DBRW($C$3,Cons_Region!$D$9,Cons_Region!G$11,$M$1,Cons_Region!$G$9,Cons_Region!$J$9,$B110,$K$1) -> 86.304159 | H110: =_xll.DBRW($C$3,Cons_Region!$D$9,Cons_Region!H$11,$M$1,Cons_Region!$G$9,Cons_Region!$J$9,$B110,$K$1) -> 91.533618 | I110: =_xll.DBRW($C$3,Cons_Region!$D$9,Cons_Region!I$11,$M$1,Cons_Region!$G$9,Cons_Region!$J$9,$B110,$K$1) -> 111.43626 | J110: =_xll.DBRW($C$3,Cons_Region!$D$9,Cons_Region!J$11,$M$1,Cons_Region!$G$9,Cons_Region!$J$9,$B110,$K$1) -> 92.628003 | ... N110: =_xll.DBRW($C$3,Cons_Region!$D$9,Cons_Region!N$11,$M$1,Cons_Region!$G$9,Cons_Region!$J$9,$B110,$K$1) -> 0
B111: Finished Product Inventory | C111: =_xll.DBRW($C$3,Cons_Region!$D$9,Cons_Region!C$11,$M$1,Cons_Region!$G$9,Cons_Region!$J$9,$B111,$K$1) -> 32.157168 | D111: =_xll.DBRW($C$3,Cons_Region!$D$9,Cons_Region!D$11,$M$1,Cons_Region!$G$9,Cons_Region!$J$9,$B111,$K$1) -> 32.092469 | E111: =_xll.DBRW($C$3,Cons_Region!$D$9,Cons_Region!E$11,$M$1,Cons_Region!$G$9,Cons_Region!$J$9,$B111,$K$1) -> 30.266238 | F111: =_xll.DBRW($C$3,Cons_Region!$D$9,Cons_Region!F$11,$M$1,Cons_Region!$G$9,Cons_Region!$J$9,$B111,$K$1) -> 31.650163 | G111: =_xll.DBRW($C$3,Cons_Region!$D$9,Cons_Region!G$11,$M$1,Cons_Region!$G$9,Cons_Region!$J$9,$B111,$K$1) -> 32.32915 | H111: =_xll.DBRW($C$3,Cons_Region!$D$9,Cons_Region!H$11,$M$1,Cons_Region!$G$9,Cons_Region!$J$9,$B111,$K$1) -> 32.813057 | I111: =_xll.DBRW($C$3,Cons_Region!$D$9,Cons_Region!I$11,$M$1,Cons_Region!$G$9,Cons_Region!$J$9,$B111,$K$1) -> 33.265272 | J111: =_xll.DBRW($C$3,Cons_Region!$D$9,Cons_Region!J$11,$M$1,Cons_Region!$G$9,Cons_Region!$J$9,$B111,$K$1) -> 33.332143 | ... N111: =_xll.DBRW($C$3,Cons_Region!$D$9,Cons_Region!N$11,$M$1,Cons_Region!$G$9,Cons_Region!$J$9,$B111,$K$1) -> 33.049768
B112: Product in Process Inventory | C112: =_xll.DBRW($B$1,Cons_Region!$D$9,Cons_Region!C$11,$M$1,Cons_Region!$G$9,Cons_Region!$J$9,$N$1,Cons_Region!$B112,$L$1,$K$1) -> 131.90934 | D112: =_xll.DBRW($B$1,Cons_Region!$D$9,Cons_Region!D$11,$M$1,Cons_Region!$G$9,Cons_Region!$J$9,$N$1,Cons_Region!$B112,$L$1,$K$1) -> 124.68585 | E112: =_xll.DBRW($B$1,Cons_Region!$D$9,Cons_Region!E$11,$M$1,Cons_Region!$G$9,Cons_Region!$J$9,$N$1,Cons_Region!$B112,$L$1,$K$1) -> 126.03323 | F112: =_xll.DBRW($B$1,Cons_Region!$D$9,Cons_Region!F$11,$M$1,Cons_Region!$G$9,Cons_Region!$J$9,$N$1,Cons_Region!$B112,$L$1,$K$1) -> 126.25921 | G112: =_xll.DBRW($B$1,Cons_Region!$D$9,Cons_Region!G$11,$M$1,Cons_Region!$G$9,Cons_Region!$J$9,$N$1,Cons_Region!$B112,$L$1,$K$1) -> 128.85265 | H112: =_xll.DBRW($B$1,Cons_Region!$D$9,Cons_Region!H$11,$M$1,Cons_Region!$G$9,Cons_Region!$J$9,$N$1,Cons_Region!$B112,$L$1,$K$1) -> 125.60512 | I112: =_xll.DBRW($B$1,Cons_Region!$D$9,Cons_Region!I$11,$M$1,Cons_Region!$G$9,Cons_Region!$J$9,$N$1,Cons_Region!$B112,$L$1,$K$1) -> 125.41618 | J112: =_xll.DBRW($B$1,Cons_Region!$D$9,Cons_Region!J$11,$M$1,Cons_Region!$G$9,Cons_Region!$J$9,$N$1,Cons_Region!$B112,$L$1,$K$1) -> 127.15852 | ... N112: =_xll.DBRW($B$1,Cons_Region!$D$9,Cons_Region!N$11,$M$1,Cons_Region!$G$9,Cons_Region!$J$9,$N$1,Cons_Region!$B112,$L$1,$K$1) -> 137.59383
B113: Concentrate Inventory | C113: =_xll.DBRW($B$1,Cons_Region!$D$9,Cons_Region!C$11,$M$1,Cons_Region!$G$9,Cons_Region!$J$9,$N$1,Cons_Region!$B113,$L$1,$K$1) -> 36.753784 | D113: =_xll.DBRW($B$1,Cons_Region!$D$9,Cons_Region!D$11,$M$1,Cons_Region!$G$9,Cons_Region!$J$9,$N$1,Cons_Region!$B113,$L$1,$K$1) -> 34.324329 | E113: =_xll.DBRW($B$1,Cons_Region!$D$9,Cons_Region!E$11,$M$1,Cons_Region!$G$9,Cons_Region!$J$9,$N$1,Cons_Region!$B113,$L$1,$K$1) -> 35.477576 | F113: =_xll.DBRW($B$1,Cons_Region!$D$9,Cons_Region!F$11,$M$1,Cons_Region!$G$9,Cons_Region!$J$9,$N$1,Cons_Region!$B113,$L$1,$K$1) -> 33.059757 | G113: =_xll.DBRW($B$1,Cons_Region!$D$9,Cons_Region!G$11,$M$1,Cons_Region!$G$9,Cons_Region!$J$9,$N$1,Cons_Region!$B113,$L$1,$K$1) -> 36.128429 | H113: =_xll.DBRW($B$1,Cons_Region!$D$9,Cons_Region!H$11,$M$1,Cons_Region!$G$9,Cons_Region!$J$9,$N$1,Cons_Region!$B113,$L$1,$K$1) -> 38.679508 | I113: =_xll.DBRW($B$1,Cons_Region!$D$9,Cons_Region!I$11,$M$1,Cons_Region!$G$9,Cons_Region!$J$9,$N$1,Cons_Region!$B113,$L$1,$K$1) -> 38.991431 | J113: =_xll.DBRW($B$1,Cons_Region!$D$9,Cons_Region!J$11,$M$1,Cons_Region!$G$9,Cons_Region!$J$9,$N$1,Cons_Region!$B113,$L$1,$K$1) -> 34.9993 | ... N113: =_xll.DBRW($B$1,Cons_Region!$D$9,Cons_Region!N$11,$M$1,Cons_Region!$G$9,Cons_Region!$J$9,$N$1,Cons_Region!$B113,$L$1,$K$1) -> 36.521684
B114: MRO Inventory | C114: =_xll.DBRW($B$1,Cons_Region!$D$9,Cons_Region!C$11,$M$1,Cons_Region!$G$9,Cons_Region!$J$9,$N$1,Cons_Region!$B114,$L$1,$K$1) -> 67.765153 | D114: =_xll.DBRW($B$1,Cons_Region!$D$9,Cons_Region!D$11,$M$1,Cons_Region!$G$9,Cons_Region!$J$9,$N$1,Cons_Region!$B114,$L$1,$K$1) -> 0 | E114: =_xll.DBRW($B$1,Cons_Region!$D$9,Cons_Region!E$11,$M$1,Cons_Region!$G$9,Cons_Region!$J$9,$N$1,Cons_Region!$B114,$L$1,$K$1) -> 0 | F114: =_xll.DBRW($B$1,Cons_Region!$D$9,Cons_Region!F$11,$M$1,Cons_Region!$G$9,Cons_Region!$J$9,$N$1,Cons_Region!$B114,$L$1,$K$1) -> 0 | G114: =_xll.DBRW($B$1,Cons_Region!$D$9,Cons_Region!G$11,$M$1,Cons_Region!$G$9,Cons_Region!$J$9,$N$1,Cons_Region!$B114,$L$1,$K$1) -> 0 | H114: =_xll.DBRW($B$1,Cons_Region!$D$9,Cons_Region!H$11,$M$1,Cons_Region!$G$9,Cons_Region!$J$9,$N$1,Cons_Region!$B114,$L$1,$K$1) -> 0 | I114: =_xll.DBRW($B$1,Cons_Region!$D$9,Cons_Region!I$11,$M$1,Cons_Region!$G$9,Cons_Region!$J$9,$N$1,Cons_Region!$B114,$L$1,$K$1) -> 0 | J114: =_xll.DBRW($B$1,Cons_Region!$D$9,Cons_Region!J$11,$M$1,Cons_Region!$G$9,Cons_Region!$J$9,$N$1,Cons_Region!$B114,$L$1,$K$1) -> 0 | ... N114: =_xll.DBRW($B$1,Cons_Region!$D$9,Cons_Region!N$11,$M$1,Cons_Region!$G$9,Cons_Region!$J$9,$N$1,Cons_Region!$B114,$L$1,$K$1) -> 0
B115: Other Inputs Inventory | C115: =_xll.DBRW($B$1,Cons_Region!$D$9,Cons_Region!C$11,$M$1,Cons_Region!$G$9,Cons_Region!$J$9,$N$1,Cons_Region!$B115,$L$1,$K$1) -> #NUM!
B116: Opex Adavancement | C116: =_xll.DBRW($B$1,Cons_Region!$D$9,Cons_Region!C$11,$M$1,Cons_Region!$G$9,Cons_Region!$J$9,$N$1,Cons_Region!$B116,$L$1,$K$1) -> 30.309062 | D116: =_xll.DBRW($B$1,Cons_Region!$D$9,Cons_Region!D$11,$M$1,Cons_Region!$G$9,Cons_Region!$J$9,$N$1,Cons_Region!$B116,$L$1,$K$1) -> 33.994084 | E116: =_xll.DBRW($B$1,Cons_Region!$D$9,Cons_Region!E$11,$M$1,Cons_Region!$G$9,Cons_Region!$J$9,$N$1,Cons_Region!$B116,$L$1,$K$1) -> 32.794075 | F116: =_xll.DBRW($B$1,Cons_Region!$D$9,Cons_Region!F$11,$M$1,Cons_Region!$G$9,Cons_Region!$J$9,$N$1,Cons_Region!$B116,$L$1,$K$1) -> 35.025498 | G116: =_xll.DBRW($B$1,Cons_Region!$D$9,Cons_Region!G$11,$M$1,Cons_Region!$G$9,Cons_Region!$J$9,$N$1,Cons_Region!$B116,$L$1,$K$1) -> 29.487893 | H116: =_xll.DBRW($B$1,Cons_Region!$D$9,Cons_Region!H$11,$M$1,Cons_Region!$G$9,Cons_Region!$J$9,$N$1,Cons_Region!$B116,$L$1,$K$1) -> 26.945599 | I116: =_xll.DBRW($B$1,Cons_Region!$D$9,Cons_Region!I$11,$M$1,Cons_Region!$G$9,Cons_Region!$J$9,$N$1,Cons_Region!$B116,$L$1,$K$1) -> 24.220174 | J116: =_xll.DBRW($B$1,Cons_Region!$D$9,Cons_Region!J$11,$M$1,Cons_Region!$G$9,Cons_Region!$J$9,$N$1,Cons_Region!$B116,$L$1,$K$1) -> 20.480485 | ... N116: =_xll.DBRW($B$1,Cons_Region!$D$9,Cons_Region!N$11,$M$1,Cons_Region!$G$9,Cons_Region!$J$9,$N$1,Cons_Region!$B116,$L$1,$K$1) -> 26.677437
B117: Other Accounts Receivable | C117: =_xll.DBRW($C$3,Cons_Region!$D$9,Cons_Region!C$11,$M$1,Cons_Region!$G$9,Cons_Region!$J$9,$B117,$K$1) -> 54.331312 | D117: =_xll.DBRW($C$3,Cons_Region!$D$9,Cons_Region!D$11,$M$1,Cons_Region!$G$9,Cons_Region!$J$9,$B117,$K$1) -> 47.668593 | E117: =_xll.DBRW($C$3,Cons_Region!$D$9,Cons_Region!E$11,$M$1,Cons_Region!$G$9,Cons_Region!$J$9,$B117,$K$1) -> 74.407648 | F117: =_xll.DBRW($C$3,Cons_Region!$D$9,Cons_Region!F$11,$M$1,Cons_Region!$G$9,Cons_Region!$J$9,$B117,$K$1) -> 85.80517 | G117: =_xll.DBRW($C$3,Cons_Region!$D$9,Cons_Region!G$11,$M$1,Cons_Region!$G$9,Cons_Region!$J$9,$B117,$K$1) -> 114.71597 | H117: =_xll.DBRW($C$3,Cons_Region!$D$9,Cons_Region!H$11,$M$1,Cons_Region!$G$9,Cons_Region!$J$9,$B117,$K$1) -> 124.72213 | I117: =_xll.DBRW($C$3,Cons_Region!$D$9,Cons_Region!I$11,$M$1,Cons_Region!$G$9,Cons_Region!$J$9,$B117,$K$1) -> 133.1247 | J117: =_xll.DBRW($C$3,Cons_Region!$D$9,Cons_Region!J$11,$M$1,Cons_Region!$G$9,Cons_Region!$J$9,$B117,$K$1) -> 138.39621 | ... N117: =_xll.DBRW($C$3,Cons_Region!$D$9,Cons_Region!N$11,$M$1,Cons_Region!$G$9,Cons_Region!$J$9,$B117,$K$1) -> 0
B120: Working Capital - Liabilities Account Balance
C122: =$D$9&"."&C$11 -> 2026.01 | D122: =$D$9&"."&D$11 -> 2026.02 | E122: =$D$9&"."&E$11 -> 2026.03 | F122: =$D$9&"."&F$11 -> 2026.04 | G122: =$D$9&"."&G$11 -> 2026.05 | H122: =$D$9&"."&H$11 -> 2026.06 | I122: =$D$9&"."&I$11 -> 2026.07 | J122: =$D$9&"."&J$11 -> 2026.08 | ... N122: =$D$9&"."&N$11 -> 2026.12
B123: Accounts Receivable | C123: =_xll.DBRW($C$3,Cons_Region!$D$9,Cons_Region!C$11,$M$1,Cons_Region!$G$9,Cons_Region!$J$9,$B123,$K$1) -> 49.721167 | D123: =_xll.DBRW($C$3,Cons_Region!$D$9,Cons_Region!D$11,$M$1,Cons_Region!$G$9,Cons_Region!$J$9,$B123,$K$1) -> 50.423219 | E123: =_xll.DBRW($C$3,Cons_Region!$D$9,Cons_Region!E$11,$M$1,Cons_Region!$G$9,Cons_Region!$J$9,$B123,$K$1) -> 65.874174 | F123: =_xll.DBRW($C$3,Cons_Region!$D$9,Cons_Region!F$11,$M$1,Cons_Region!$G$9,Cons_Region!$J$9,$B123,$K$1) -> 73.427309 | G123: =_xll.DBRW($C$3,Cons_Region!$D$9,Cons_Region!G$11,$M$1,Cons_Region!$G$9,Cons_Region!$J$9,$B123,$K$1) -> 86.304159 | H123: =_xll.DBRW($C$3,Cons_Region!$D$9,Cons_Region!H$11,$M$1,Cons_Region!$G$9,Cons_Region!$J$9,$B123,$K$1) -> 91.533618 | I123: =_xll.DBRW($C$3,Cons_Region!$D$9,Cons_Region!I$11,$M$1,Cons_Region!$G$9,Cons_Region!$J$9,$B123,$K$1) -> 111.43626 | J123: =_xll.DBRW($C$3,Cons_Region!$D$9,Cons_Region!J$11,$M$1,Cons_Region!$G$9,Cons_Region!$J$9,$B123,$K$1) -> 92.628003 | ... N123: =_xll.DBRW($C$3,Cons_Region!$D$9,Cons_Region!N$11,$M$1,Cons_Region!$G$9,Cons_Region!$J$9,$B123,$K$1) -> 0
B124: Suppliers | C124: =_xll.DBRW($C$3,Cons_Region!$D$9,Cons_Region!C$11,$M$1,Cons_Region!$G$9,Cons_Region!$J$9,$B124,$K$1) -> 150.36949 | D124: =_xll.DBRW($C$3,Cons_Region!$D$9,Cons_Region!D$11,$M$1,Cons_Region!$G$9,Cons_Region!$J$9,$B124,$K$1) -> 124.62852 | E124: =_xll.DBRW($C$3,Cons_Region!$D$9,Cons_Region!E$11,$M$1,Cons_Region!$G$9,Cons_Region!$J$9,$B124,$K$1) -> 130.81937 | F124: =_xll.DBRW($C$3,Cons_Region!$D$9,Cons_Region!F$11,$M$1,Cons_Region!$G$9,Cons_Region!$J$9,$B124,$K$1) -> 138.88881 | G124: =_xll.DBRW($C$3,Cons_Region!$D$9,Cons_Region!G$11,$M$1,Cons_Region!$G$9,Cons_Region!$J$9,$B124,$K$1) -> 135.94156 | H124: =_xll.DBRW($C$3,Cons_Region!$D$9,Cons_Region!H$11,$M$1,Cons_Region!$G$9,Cons_Region!$J$9,$B124,$K$1) -> 129.14242 | I124: =_xll.DBRW($C$3,Cons_Region!$D$9,Cons_Region!I$11,$M$1,Cons_Region!$G$9,Cons_Region!$J$9,$B124,$K$1) -> 129.19442 | J124: =_xll.DBRW($C$3,Cons_Region!$D$9,Cons_Region!J$11,$M$1,Cons_Region!$G$9,Cons_Region!$J$9,$B124,$K$1) -> 126.57202 | ... N124: =_xll.DBRW($C$3,Cons_Region!$D$9,Cons_Region!N$11,$M$1,Cons_Region!$G$9,Cons_Region!$J$9,$B124,$K$1) -> 0
B125: Operating Taxes Payable | C125: =_xll.DBRW($C$3,Cons_Region!$D$9,Cons_Region!C$11,$M$1,Cons_Region!$G$9,Cons_Region!$J$9,$B125,$K$1) -> 4.1061451 | D125: =_xll.DBRW($C$3,Cons_Region!$D$9,Cons_Region!D$11,$M$1,Cons_Region!$G$9,Cons_Region!$J$9,$B125,$K$1) -> 5.616543 | E125: =_xll.DBRW($C$3,Cons_Region!$D$9,Cons_Region!E$11,$M$1,Cons_Region!$G$9,Cons_Region!$J$9,$B125,$K$1) -> 5.4999578 | F125: =_xll.DBRW($C$3,Cons_Region!$D$9,Cons_Region!F$11,$M$1,Cons_Region!$G$9,Cons_Region!$J$9,$B125,$K$1) -> 5.9999718 | G125: =_xll.DBRW($C$3,Cons_Region!$D$9,Cons_Region!G$11,$M$1,Cons_Region!$G$9,Cons_Region!$J$9,$B125,$K$1) -> 6.0000174 | H125: =_xll.DBRW($C$3,Cons_Region!$D$9,Cons_Region!H$11,$M$1,Cons_Region!$G$9,Cons_Region!$J$9,$B125,$K$1) -> 6.0000181 | I125: =_xll.DBRW($C$3,Cons_Region!$D$9,Cons_Region!I$11,$M$1,Cons_Region!$G$9,Cons_Region!$J$9,$B125,$K$1) -> 5.9999762 | J125: =_xll.DBRW($C$3,Cons_Region!$D$9,Cons_Region!J$11,$M$1,Cons_Region!$G$9,Cons_Region!$J$9,$B125,$K$1) -> 5.9999799 | ... N125: =_xll.DBRW($C$3,Cons_Region!$D$9,Cons_Region!N$11,$M$1,Cons_Region!$G$9,Cons_Region!$J$9,$B125,$K$1) -> 6.2000632
B126: Labor Obligations | C126: =_xll.DBRW($C$3,Cons_Region!$D$9,Cons_Region!C$11,$M$1,Cons_Region!$G$9,Cons_Region!$J$9,$B126,$K$1) -> 65.270279 | D126: =_xll.DBRW($C$3,Cons_Region!$D$9,Cons_Region!D$11,$M$1,Cons_Region!$G$9,Cons_Region!$J$9,$B126,$K$1) -> 45.998483 | E126: =_xll.DBRW($C$3,Cons_Region!$D$9,Cons_Region!E$11,$M$1,Cons_Region!$G$9,Cons_Region!$J$9,$B126,$K$1) -> 50.909089 | F126: =_xll.DBRW($C$3,Cons_Region!$D$9,Cons_Region!F$11,$M$1,Cons_Region!$G$9,Cons_Region!$J$9,$B126,$K$1) -> 52.534089 | G126: =_xll.DBRW($C$3,Cons_Region!$D$9,Cons_Region!G$11,$M$1,Cons_Region!$G$9,Cons_Region!$J$9,$B126,$K$1) -> 54.159089 | H126: =_xll.DBRW($C$3,Cons_Region!$D$9,Cons_Region!H$11,$M$1,Cons_Region!$G$9,Cons_Region!$J$9,$B126,$K$1) -> 53.984603 | I126: =_xll.DBRW($C$3,Cons_Region!$D$9,Cons_Region!I$11,$M$1,Cons_Region!$G$9,Cons_Region!$J$9,$B126,$K$1) -> 59.322726 | J126: =_xll.DBRW($C$3,Cons_Region!$D$9,Cons_Region!J$11,$M$1,Cons_Region!$G$9,Cons_Region!$J$9,$B126,$K$1) -> 59.034089 | ... N126: =_xll.DBRW($C$3,Cons_Region!$D$9,Cons_Region!N$11,$M$1,Cons_Region!$G$9,Cons_Region!$J$9,$B126,$K$1) -> 0
B127: Other Accounts Payable | C127: =_xll.DBRW($C$3,Cons_Region!$D$9,Cons_Region!C$11,$M$1,Cons_Region!$G$9,Cons_Region!$J$9,$B127,$K$1) -> 56.492738 | D127: =_xll.DBRW($C$3,Cons_Region!$D$9,Cons_Region!D$11,$M$1,Cons_Region!$G$9,Cons_Region!$J$9,$B127,$K$1) -> 48.2949 | E127: =_xll.DBRW($C$3,Cons_Region!$D$9,Cons_Region!E$11,$M$1,Cons_Region!$G$9,Cons_Region!$J$9,$B127,$K$1) -> 50 | F127: =_xll.DBRW($C$3,Cons_Region!$D$9,Cons_Region!F$11,$M$1,Cons_Region!$G$9,Cons_Region!$J$9,$B127,$K$1) -> 45 | G127: =_xll.DBRW($C$3,Cons_Region!$D$9,Cons_Region!G$11,$M$1,Cons_Region!$G$9,Cons_Region!$J$9,$B127,$K$1) -> 45 | H127: =_xll.DBRW($C$3,Cons_Region!$D$9,Cons_Region!H$11,$M$1,Cons_Region!$G$9,Cons_Region!$J$9,$B127,$K$1) -> 48.387097 | I127: =_xll.DBRW($C$3,Cons_Region!$D$9,Cons_Region!I$11,$M$1,Cons_Region!$G$9,Cons_Region!$J$9,$B127,$K$1) -> 51.666667 | J127: =_xll.DBRW($C$3,Cons_Region!$D$9,Cons_Region!J$11,$M$1,Cons_Region!$G$9,Cons_Region!$J$9,$B127,$K$1) -> 55 | ... N127: =_xll.DBRW($C$3,Cons_Region!$D$9,Cons_Region!N$11,$M$1,Cons_Region!$G$9,Cons_Region!$J$9,$B127,$K$1) -> 0
B130: WC - CLOSING BALANCE AND CASH FLOW
C132: =$D$9&"."&C$11 -> 2026.01 | D132: =$D$9&"."&D$11 -> 2026.02 | E132: =$D$9&"."&E$11 -> 2026.03 | F132: =$D$9&"."&F$11 -> 2026.04 | G132: =$D$9&"."&G$11 -> 2026.05 | H132: =$D$9&"."&H$11 -> 2026.06 | I132: =$D$9&"."&I$11 -> 2026.07 | J132: =$D$9&"."&J$11 -> 2026.08 | ... N132: =$D$9&"."&N$11 -> 2026.12
B133: Initial Working Capital Balance | C133: =_xll.DBRW($B$1,Cons_Region!$D$9,Cons_Region!C$11,$M$1,Cons_Region!$G$9,Cons_Region!$J$9,$N$1,Cons_Region!$B133,$L$1,$K$1) -> 38.13 | D133: =_xll.DBRW($C$3,Cons_Region!$D$9,Cons_Region!D$11,$M$1,Cons_Region!$G$9,Cons_Region!$J$9,$B133,$K$1) -> 218.7737 | E133: =_xll.DBRW($C$3,Cons_Region!$D$9,Cons_Region!E$11,$M$1,Cons_Region!$G$9,Cons_Region!$J$9,$B133,$K$1) -> 168.99315 | F133: =_xll.DBRW($C$3,Cons_Region!$D$9,Cons_Region!F$11,$M$1,Cons_Region!$G$9,Cons_Region!$J$9,$B133,$K$1) -> 183.85359 | G133: =_xll.DBRW($C$3,Cons_Region!$D$9,Cons_Region!G$11,$M$1,Cons_Region!$G$9,Cons_Region!$J$9,$B133,$K$1) -> 191.59287 | H133: =_xll.DBRW($C$3,Cons_Region!$D$9,Cons_Region!H$11,$M$1,Cons_Region!$G$9,Cons_Region!$J$9,$B133,$K$1) -> 224.00956 | I133: =_xll.DBRW($C$3,Cons_Region!$D$9,Cons_Region!I$11,$M$1,Cons_Region!$G$9,Cons_Region!$J$9,$B133,$K$1) -> 240.72528 | J133: =_xll.DBRW($C$3,Cons_Region!$D$9,Cons_Region!J$11,$M$1,Cons_Region!$G$9,Cons_Region!$J$9,$B133,$K$1) -> 255.71187 | K133: =_xll.DBRW($C$3,Cons_Region!$D$9,Cons_Region!K$11,$M$1,Cons_Region!$G$9,Cons_Region!$J$9,$B133,$K$1) -> 234.27068 | ... N133: =_xll.DBRW($C$3,Cons_Region!$D$9,Cons_Region!N$11,$M$1,Cons_Region!$G$9,Cons_Region!$J$9,$B133,$K$1) -> 208.54915
B134: Working Capital | C134: =_xll.DBRW($C$3,Cons_Region!$D$9,Cons_Region!C$11,$M$1,Cons_Region!$G$9,Cons_Region!$J$9,$B134,$K$1) -> 218.7737 | D134: =_xll.DBRW($C$3,Cons_Region!$D$9,Cons_Region!D$11,$M$1,Cons_Region!$G$9,Cons_Region!$J$9,$B134,$K$1) -> 168.99315 | E134: =_xll.DBRW($C$3,Cons_Region!$D$9,Cons_Region!E$11,$M$1,Cons_Region!$G$9,Cons_Region!$J$9,$B134,$K$1) -> 183.85359 | F134: =_xll.DBRW($C$3,Cons_Region!$D$9,Cons_Region!F$11,$M$1,Cons_Region!$G$9,Cons_Region!$J$9,$B134,$K$1) -> 191.59287 | G134: =_xll.DBRW($C$3,Cons_Region!$D$9,Cons_Region!G$11,$M$1,Cons_Region!$G$9,Cons_Region!$J$9,$B134,$K$1) -> 224.00956 | H134: =_xll.DBRW($C$3,Cons_Region!$D$9,Cons_Region!H$11,$M$1,Cons_Region!$G$9,Cons_Region!$J$9,$B134,$K$1) -> 240.72528 | I134: =_xll.DBRW($C$3,Cons_Region!$D$9,Cons_Region!I$11,$M$1,Cons_Region!$G$9,Cons_Region!$J$9,$B134,$K$1) -> 255.71187 | J134: =_xll.DBRW($C$3,Cons_Region!$D$9,Cons_Region!J$11,$M$1,Cons_Region!$G$9,Cons_Region!$J$9,$B134,$K$1) -> 234.27068 | ... N134: =_xll.DBRW($C$3,Cons_Region!$D$9,Cons_Region!N$11,$M$1,Cons_Region!$G$9,Cons_Region!$J$9,$B134,$K$1) -> 227.64265
B135: WC adjust by buy/sale of company | C135: =_xll.DBRW($B$1,Cons_Region!$D$9,Cons_Region!C$11,$M$1,Cons_Region!$G$9,Cons_Region!$J$9,$N$1,Cons_Region!$B135,$L$1,$K$1) -> 0 | D135: =_xll.DBRW($B$1,Cons_Region!$D$9,Cons_Region!D$11,$M$1,Cons_Region!$G$9,Cons_Region!$J$9,$N$1,Cons_Region!$B135,$L$1,$K$1) -> 0 | E135: =_xll.DBRW($B$1,Cons_Region!$D$9,Cons_Region!E$11,$M$1,Cons_Region!$G$9,Cons_Region!$J$9,$N$1,Cons_Region!$B135,$L$1,$K$1) -> 0 | F135: =_xll.DBRW($B$1,Cons_Region!$D$9,Cons_Region!F$11,$M$1,Cons_Region!$G$9,Cons_Region!$J$9,$N$1,Cons_Region!$B135,$L$1,$K$1) -> 0 | G135: =_xll.DBRW($B$1,Cons_Region!$D$9,Cons_Region!G$11,$M$1,Cons_Region!$G$9,Cons_Region!$J$9,$N$1,Cons_Region!$B135,$L$1,$K$1) -> 0 | H135: =_xll.DBRW($B$1,Cons_Region!$D$9,Cons_Region!H$11,$M$1,Cons_Region!$G$9,Cons_Region!$J$9,$N$1,Cons_Region!$B135,$L$1,$K$1) -> 0 | I135: =_xll.DBRW($B$1,Cons_Region!$D$9,Cons_Region!I$11,$M$1,Cons_Region!$G$9,Cons_Region!$J$9,$N$1,Cons_Region!$B135,$L$1,$K$1) -> 0 | J135: =_xll.DBRW($B$1,Cons_Region!$D$9,Cons_Region!J$11,$M$1,Cons_Region!$G$9,Cons_Region!$J$9,$N$1,Cons_Region!$B135,$L$1,$K$1) -> 0 | ... N135: =_xll.DBRW($B$1,Cons_Region!$D$9,Cons_Region!N$11,$M$1,Cons_Region!$G$9,Cons_Region!$J$9,$N$1,Cons_Region!$B135,$L$1,$K$1) -> 0
B136: (Invest.)/Divest. Working Capital | C136: =_xll.DBRW($C$3,Cons_Region!$D$9,Cons_Region!C$11,$M$1,Cons_Region!$G$9,Cons_Region!$J$9,$B136,$K$1) -> -180.6437 | D136: =_xll.DBRW($C$3,Cons_Region!$D$9,Cons_Region!D$11,$M$1,Cons_Region!$G$9,Cons_Region!$J$9,$B136,$K$1) -> 49.780558 | E136: =_xll.DBRW($C$3,Cons_Region!$D$9,Cons_Region!E$11,$M$1,Cons_Region!$G$9,Cons_Region!$J$9,$B136,$K$1) -> -14.86044 | F136: =_xll.DBRW($C$3,Cons_Region!$D$9,Cons_Region!F$11,$M$1,Cons_Region!$G$9,Cons_Region!$J$9,$B136,$K$1) -> -7.7392859 | G136: =_xll.DBRW($C$3,Cons_Region!$D$9,Cons_Region!G$11,$M$1,Cons_Region!$G$9,Cons_Region!$J$9,$B136,$K$1) -> -32.41669 | H136: =_xll.DBRW($C$3,Cons_Region!$D$9,Cons_Region!H$11,$M$1,Cons_Region!$G$9,Cons_Region!$J$9,$B136,$K$1) -> -16.715716 | I136: =_xll.DBRW($C$3,Cons_Region!$D$9,Cons_Region!I$11,$M$1,Cons_Region!$G$9,Cons_Region!$J$9,$B136,$K$1) -> -14.986596 | J136: =_xll.DBRW($C$3,Cons_Region!$D$9,Cons_Region!J$11,$M$1,Cons_Region!$G$9,Cons_Region!$J$9,$B136,$K$1) -> 21.441193 | ... N136: =_xll.DBRW($C$3,Cons_Region!$D$9,Cons_Region!N$11,$M$1,Cons_Region!$G$9,Cons_Region!$J$9,$B136,$K$1) -> -19.093499
B139: GROSS DEBT | F139: Currency: | G139: =_xll.SUBNM("CONS_VC:ALL.D.Currency","PAX","USD Conv.","Nome alternativo") -> USD Conv.
C142: =$D$9&"."&C$11 -> 2026.01 | D142: =$D$9&"."&D$11 -> 2026.02 | E142: =$D$9&"."&E$11 -> 2026.03 | F142: =$D$9&"."&F$11 -> 2026.04 | G142: =$D$9&"."&G$11 -> 2026.05 | H142: =$D$9&"."&H$11 -> 2026.06 | I142: =$D$9&"."&I$11 -> 2026.07 | J142: =$D$9&"."&J$11 -> 2026.08 | ... N142: =$D$9&"."&N$11 -> 2026.12
...

Sheet Input_Prod_01
B1: =_xll.VIEW("CONS_VC:STG.100.DataBase_Uploads",D9) -> CONS_VC:STG.100.DataBase_Uploads:-7526985492024324052 | C1: =_xll.VIEW("CONS_VC:ALL.015.Region_Assumptions") -> CONS_VC:ALL.015.Region_Assumptions:-752698549-1942758411 | D1: =_xll.VIEW("CONS_VC:DFS.120.Financial_Results") -> CONS_VC:DFS.120.Financial_Results:-752698549-1075501928 | K1: Value | L1: N/A | M1: =_xll.SUBNM("CONS_VC:ALL.D.Version","","T4") -> T4 | N1: PROD099
B2: =_xll.VIEW("CONS_VC:REV.100.Revenue_Consolidated") -> CONS_VC:REV.100.Revenue_Consolidated:-752698549333326983 | C2: =_xll.VIEW("CONS_VC:ALL.010.Economic_Assumptions") -> CONS_VC:ALL.010.Economic_Assumptions:-752698549-1273320382 | D2: =_xll.VIEW("CONS_VC:DFS.140.Indirect_Cash_Flow") -> CONS_VC:DFS.140.Indirect_Cash_Flow:-752698549946636930 | K2: Total Market | N2: Total Products
B3: =_xll.VIEW("CONS_VC:DFS.100.Profit_and_Loss") -> CONS_VC:DFS.100.Profit_and_Loss:-752698549611332035 | C3: =_xll.VIEW("CONS_VC:DFS.160.Working_Capital") -> CONS_VC:DFS.160.Working_Capital:-752698549-1218331026 | D3: =_xll.VIEW("CONS_VC:ALL.004.Uploads_Status_Planning") -> CONS_VC:ALL.004.Uploads_Status_Planning:-7526985491996989984 | G3: Flag
B4: =_xll.VIEW("CONS_VC:ALL.001.Actual_Control") -> CONS_VC:ALL.001.Actual_Control:-7526985491439511960 | C4: =_xll.VIEW("CONS_VC:DFS.180.Gross_Debt") -> CONS_VC:DFS.180.Gross_Debt:-752698549-1828767557
C5: =_xll.DBRW(Input_Prod_01!$B$4,Input_Prod_01!$D$9,Input_Prod_01!C11,$M$1,$G$3) -> PLAN | D5: =_xll.DBRW(Input_Prod_01!$B$4,Input_Prod_01!$D$9,Input_Prod_01!D11,$M$1,$G$3) -> PLAN | E5: =_xll.DBRW(Input_Prod_01!$B$4,Input_Prod_01!$D$9,Input_Prod_01!E11,$M$1,$G$3) -> PLAN | F5: =_xll.DBRW(Input_Prod_01!$B$4,Input_Prod_01!$D$9,Input_Prod_01!F11,$M$1,$G$3) -> PLAN | G5: =_xll.DBRW(Input_Prod_01!$B$4,Input_Prod_01!$D$9,Input_Prod_01!G11,$M$1,$G$3) -> PLAN | H5: =_xll.DBRW(Input_Prod_01!$B$4,Input_Prod_01!$D$9,Input_Prod_01!H11,$M$1,$G$3) -> PLAN | I5: =_xll.DBRW(Input_Prod_01!$B$4,Input_Prod_01!$D$9,Input_Prod_01!I11,$M$1,$G$3) -> PLAN | J5: =_xll.DBRW(Input_Prod_01!$B$4,Input_Prod_01!$D$9,Input_Prod_01!J11,$M$1,$G$3) -> PLAN | ... N5: =_xll.DBRW(Input_Prod_01!$B$4,Input_Prod_01!$D$9,Input_Prod_01!N11,$M$1,$G$3) -> PLAN
L7: System Input Status: | N7: =_xll.DBRW($D$3,$M$1,$J$9,"Status") -> Closed
B8: GLOBAL ASSUMPTIONS
C9: Year: | D9: =_xll.SUBNM("CONS_VC:ALL.D.Year","SYS_Picklist","2026","MEMBER_NAME") -> 2026 | F9: Currency: | G9: =_xll.SUBNM("CONS_VC:ALL.D.Currency","PAX","USD","Nome alternativo") -> USD | I9: Region: | J9: =_xll.SUBNM("CONS_VC:ALL.D.Region","Nível 0","VCNA","MEMBER_NAME") -> VCNA
C11: 01 | D11: 02 | E11: 03 | F11: 04 | G11: 05 | H11: 06 | I11: 07 | J11: 08 | K11: 09 | L11: 10 | M11: 11 | N11: 12
C12: =$D$9&"."&C11 -> 2026.01 | D12: =$D$9&"."&D11 -> 2026.02 | E12: =$D$9&"."&E11 -> 2026.03 | F12: =$D$9&"."&F11 -> 2026.04 | G12: =$D$9&"."&G11 -> 2026.05 | H12: =$D$9&"."&H11 -> 2026.06 | I12: =$D$9&"."&I11 -> 2026.07 | J12: =$D$9&"."&J11 -> 2026.08 | ... N12: =$D$9&"."&N11 -> 2026.12
B13: Begining FX Rate R$/US$ | C13: =_xll.DBRW($C$2,Input_Prod_01!$D$9,Input_Prod_01!$C$11,$M$1,$B13,$K$1) -> 0 | D13: =_xll.DBRW($C$2,Input_Prod_01!$D$9,Input_Prod_01!$C$11,$M$1,$B13,$K$1) -> 0 | E13: =_xll.DBRW($C$2,Input_Prod_01!$D$9,Input_Prod_01!$C$11,$M$1,$B13,$K$1) -> 0 | F13: =_xll.DBRW($C$2,Input_Prod_01!$D$9,Input_Prod_01!$C$11,$M$1,$B13,$K$1) -> 0 | G13: =_xll.DBRW($C$2,Input_Prod_01!$D$9,Input_Prod_01!$C$11,$M$1,$B13,$K$1) -> 0 | H13: =_xll.DBRW($C$2,Input_Prod_01!$D$9,Input_Prod_01!$C$11,$M$1,$B13,$K$1) -> 0 | I13: =_xll.DBRW($C$2,Input_Prod_01!$D$9,Input_Prod_01!$C$11,$M$1,$B13,$K$1) -> 0 | J13: =_xll.DBRW($C$2,Input_Prod_01!$D$9,Input_Prod_01!$C$11,$M$1,$B13,$K$1) -> 0 | ... N13: =_xll.DBRW($C$2,Input_Prod_01!$D$9,Input_Prod_01!$C$11,$M$1,$B13,$K$1) -> 0
B14: Average FX Rate R$/US$ | C14: =_xll.DBRW($C$2,Input_Prod_01!$D$9,Input_Prod_01!$C$11,$M$1,$B14,$K$1) -> 0 | D14: =_xll.DBRW($C$2,Input_Prod_01!$D$9,Input_Prod_01!$C$11,$M$1,$B14,$K$1) -> 0 | E14: =_xll.DBRW($C$2,Input_Prod_01!$D$9,Input_Prod_01!$C$11,$M$1,$B14,$K$1) -> 0 | F14: =_xll.DBRW($C$2,Input_Prod_01!$D$9,Input_Prod_01!$C$11,$M$1,$B14,$K$1) -> 0 | G14: =_xll.DBRW($C$2,Input_Prod_01!$D$9,Input_Prod_01!$C$11,$M$1,$B14,$K$1) -> 0 | H14: =_xll.DBRW($C$2,Input_Prod_01!$D$9,Input_Prod_01!$C$11,$M$1,$B14,$K$1) -> 0 | I14: =_xll.DBRW($C$2,Input_Prod_01!$D$9,Input_Prod_01!$C$11,$M$1,$B14,$K$1) -> 0 | J14: =_xll.DBRW($C$2,Input_Prod_01!$D$9,Input_Prod_01!$C$11,$M$1,$B14,$K$1) -> 0 | ... N14: =_xll.DBRW($C$2,Input_Prod_01!$D$9,Input_Prod_01!$C$11,$M$1,$B14,$K$1) -> 0
B15: Final FX Rate R$/US$ | C15: =_xll.DBRW($C$2,Input_Prod_01!$D$9,Input_Prod_01!$C$11,$M$1,$B15,$K$1) -> 0 | D15: =_xll.DBRW($C$2,Input_Prod_01!$D$9,Input_Prod_01!$C$11,$M$1,$B15,$K$1) -> 0 | E15: =_xll.DBRW($C$2,Input_Prod_01!$D$9,Input_Prod_01!$C$11,$M$1,$B15,$K$1) -> 0 | F15: =_xll.DBRW($C$2,Input_Prod_01!$D$9,Input_Prod_01!$C$11,$M$1,$B15,$K$1) -> 0 | G15: =_xll.DBRW($C$2,Input_Prod_01!$D$9,Input_Prod_01!$C$11,$M$1,$B15,$K$1) -> 0 | H15: =_xll.DBRW($C$2,Input_Prod_01!$D$9,Input_Prod_01!$C$11,$M$1,$B15,$K$1) -> 0 | I15: =_xll.DBRW($C$2,Input_Prod_01!$D$9,Input_Prod_01!$C$11,$M$1,$B15,$K$1) -> 0 | J15: =_xll.DBRW($C$2,Input_Prod_01!$D$9,Input_Prod_01!$C$11,$M$1,$B15,$K$1) -> 0 | ... N15: =_xll.DBRW($C$2,Input_Prod_01!$D$9,Input_Prod_01!$C$11,$M$1,$B15,$K$1) -> 0
B16: Begining FX Rate US$/EUR | C16: =_xll.DBRW($C$2,Input_Prod_01!$D$9,Input_Prod_01!$C$11,$M$1,$B16,$K$1) -> 0 | D16: =_xll.DBRW($C$2,Input_Prod_01!$D$9,Input_Prod_01!$C$11,$M$1,$B16,$K$1) -> 0 | E16: =_xll.DBRW($C$2,Input_Prod_01!$D$9,Input_Prod_01!$C$11,$M$1,$B16,$K$1) -> 0 | F16: =_xll.DBRW($C$2,Input_Prod_01!$D$9,Input_Prod_01!$C$11,$M$1,$B16,$K$1) -> 0 | G16: =_xll.DBRW($C$2,Input_Prod_01!$D$9,Input_Prod_01!$C$11,$M$1,$B16,$K$1) -> 0 | H16: =_xll.DBRW($C$2,Input_Prod_01!$D$9,Input_Prod_01!$C$11,$M$1,$B16,$K$1) -> 0 | I16: =_xll.DBRW($C$2,Input_Prod_01!$D$9,Input_Prod_01!$C$11,$M$1,$B16,$K$1) -> 0 | J16: =_xll.DBRW($C$2,Input_Prod_01!$D$9,Input_Prod_01!$C$11,$M$1,$B16,$K$1) -> 0 | ... N16: =_xll.DBRW($C$2,Input_Prod_01!$D$9,Input_Prod_01!$C$11,$M$1,$B16,$K$1) -> 0
B17: Average FX Rate US$/EUR | C17: =_xll.DBRW($C$2,Input_Prod_01!$D$9,Input_Prod_01!$C$11,$M$1,$B17,$K$1) -> 5 | D17: =_xll.DBRW($C$2,Input_Prod_01!$D$9,Input_Prod_01!$C$11,$M$1,$B17,$K$1) -> 5 | E17: =_xll.DBRW($C$2,Input_Prod_01!$D$9,Input_Prod_01!$C$11,$M$1,$B17,$K$1) -> 5 | F17: =_xll.DBRW($C$2,Input_Prod_01!$D$9,Input_Prod_01!$C$11,$M$1,$B17,$K$1) -> 5 | G17: =_xll.DBRW($C$2,Input_Prod_01!$D$9,Input_Prod_01!$C$11,$M$1,$B17,$K$1) -> 5 | H17: =_xll.DBRW($C$2,Input_Prod_01!$D$9,Input_Prod_01!$C$11,$M$1,$B17,$K$1) -> 5 | I17: =_xll.DBRW($C$2,Input_Prod_01!$D$9,Input_Prod_01!$C$11,$M$1,$B17,$K$1) -> 5 | J17: =_xll.DBRW($C$2,Input_Prod_01!$D$9,Input_Prod_01!$C$11,$M$1,$B17,$K$1) -> 5 | ... N17: =_xll.DBRW($C$2,Input_Prod_01!$D$9,Input_Prod_01!$C$11,$M$1,$B17,$K$1) -> 5
B18: Final FX Rate US$/EUR | C18: =_xll.DBRW($C$2,Input_Prod_01!$D$9,Input_Prod_01!$C$11,$M$1,$B18,$K$1) -> 0 | D18: =_xll.DBRW($C$2,Input_Prod_01!$D$9,Input_Prod_01!$C$11,$M$1,$B18,$K$1) -> 0 | E18: =_xll.DBRW($C$2,Input_Prod_01!$D$9,Input_Prod_01!$C$11,$M$1,$B18,$K$1) -> 0 | F18: =_xll.DBRW($C$2,Input_Prod_01!$D$9,Input_Prod_01!$C$11,$M$1,$B18,$K$1) -> 0 | G18: =_xll.DBRW($C$2,Input_Prod_01!$D$9,Input_Prod_01!$C$11,$M$1,$B18,$K$1) -> 0 | H18: =_xll.DBRW($C$2,Input_Prod_01!$D$9,Input_Prod_01!$C$11,$M$1,$B18,$K$1) -> 0 | I18: =_xll.DBRW($C$2,Input_Prod_01!$D$9,Input_Prod_01!$C$11,$M$1,$B18,$K$1) -> 0 | J18: =_xll.DBRW($C$2,Input_Prod_01!$D$9,Input_Prod_01!$C$11,$M$1,$B18,$K$1) -> 0 | ... N18: =_xll.DBRW($C$2,Input_Prod_01!$D$9,Input_Prod_01!$C$11,$M$1,$B18,$K$1) -> 0
B19: Câmbio Inicial UYU$/US$ | C19: =_xll.DBRW($C$2,Input_Prod_01!$D$9,Input_Prod_01!$C$11,$M$1,$B19,$K$1) -> 0 | D19: =_xll.DBRW($C$2,Input_Prod_01!$D$9,Input_Prod_01!$C$11,$M$1,$B19,$K$1) -> 0 | E19: =_xll.DBRW($C$2,Input_Prod_01!$D$9,Input_Prod_01!$C$11,$M$1,$B19,$K$1) -> 0 | F19: =_xll.DBRW($C$2,Input_Prod_01!$D$9,Input_Prod_01!$C$11,$M$1,$B19,$K$1) -> 0 | G19: =_xll.DBRW($C$2,Input_Prod_01!$D$9,Input_Prod_01!$C$11,$M$1,$B19,$K$1) -> 0 | H19: =_xll.DBRW($C$2,Input_Prod_01!$D$9,Input_Prod_01!$C$11,$M$1,$B19,$K$1) -> 0 | I19: =_xll.DBRW($C$2,Input_Prod_01!$D$9,Input_Prod_01!$C$11,$M$1,$B19,$K$1) -> 0 | J19: =_xll.DBRW($C$2,Input_Prod_01!$D$9,Input_Prod_01!$C$11,$M$1,$B19,$K$1) -> 0 | ... N19: =_xll.DBRW($C$2,Input_Prod_01!$D$9,Input_Prod_01!$C$11,$M$1,$B19,$K$1) -> 0
B20: Câmbio Médio UYU$/US$ | C20: =_xll.DBRW($C$2,Input_Prod_01!$D$9,Input_Prod_01!$C$11,$M$1,$B20,$K$1) -> 0 | D20: =_xll.DBRW($C$2,Input_Prod_01!$D$9,Input_Prod_01!$C$11,$M$1,$B20,$K$1) -> 0 | E20: =_xll.DBRW($C$2,Input_Prod_01!$D$9,Input_Prod_01!$C$11,$M$1,$B20,$K$1) -> 0 | F20: =_xll.DBRW($C$2,Input_Prod_01!$D$9,Input_Prod_01!$C$11,$M$1,$B20,$K$1) -> 0 | G20: =_xll.DBRW($C$2,Input_Prod_01!$D$9,Input_Prod_01!$C$11,$M$1,$B20,$K$1) -> 0 | H20: =_xll.DBRW($C$2,Input_Prod_01!$D$9,Input_Prod_01!$C$11,$M$1,$B20,$K$1) -> 0 | I20: =_xll.DBRW($C$2,Input_Prod_01!$D$9,Input_Prod_01!$C$11,$M$1,$B20,$K$1) -> 0 | J20: =_xll.DBRW($C$2,Input_Prod_01!$D$9,Input_Prod_01!$C$11,$M$1,$B20,$K$1) -> 0 | ... N20: =_xll.DBRW($C$2,Input_Prod_01!$D$9,Input_Prod_01!$C$11,$M$1,$B20,$K$1) -> 0
B21: Câmbio Final UYU$/US$ | C21: =_xll.DBRW($C$2,Input_Prod_01!$D$9,Input_Prod_01!$C$11,$M$1,$B21,$K$1) -> 0 | D21: =_xll.DBRW($C$2,Input_Prod_01!$D$9,Input_Prod_01!$C$11,$M$1,$B21,$K$1) -> 0 | E21: =_xll.DBRW($C$2,Input_Prod_01!$D$9,Input_Prod_01!$C$11,$M$1,$B21,$K$1) -> 0 | F21: =_xll.DBRW($C$2,Input_Prod_01!$D$9,Input_Prod_01!$C$11,$M$1,$B21,$K$1) -> 0 | G21: =_xll.DBRW($C$2,Input_Prod_01!$D$9,Input_Prod_01!$C$11,$M$1,$B21,$K$1) -> 0 | H21: =_xll.DBRW($C$2,Input_Prod_01!$D$9,Input_Prod_01!$C$11,$M$1,$B21,$K$1) -> 0 | I21: =_xll.DBRW($C$2,Input_Prod_01!$D$9,Input_Prod_01!$C$11,$M$1,$B21,$K$1) -> 0 | J21: =_xll.DBRW($C$2,Input_Prod_01!$D$9,Input_Prod_01!$C$11,$M$1,$B21,$K$1) -> 0 | ... N21: =_xll.DBRW($C$2,Input_Prod_01!$D$9,Input_Prod_01!$C$11,$M$1,$B21,$K$1) -> 0
B22: Câmbio Inicial ARS$/US$ | C22: =_xll.DBRW($C$2,Input_Prod_01!$D$9,Input_Prod_01!$C$11,$M$1,$B22,$K$1) -> 0 | D22: =_xll.DBRW($C$2,Input_Prod_01!$D$9,Input_Prod_01!$C$11,$M$1,$B22,$K$1) -> 0 | E22: =_xll.DBRW($C$2,Input_Prod_01!$D$9,Input_Prod_01!$C$11,$M$1,$B22,$K$1) -> 0 | F22: =_xll.DBRW($C$2,Input_Prod_01!$D$9,Input_Prod_01!$C$11,$M$1,$B22,$K$1) -> 0 | G22: =_xll.DBRW($C$2,Input_Prod_01!$D$9,Input_Prod_01!$C$11,$M$1,$B22,$K$1) -> 0 | H22: =_xll.DBRW($C$2,Input_Prod_01!$D$9,Input_Prod_01!$C$11,$M$1,$B22,$K$1) -> 0 | I22: =_xll.DBRW($C$2,Input_Prod_01!$D$9,Input_Prod_01!$C$11,$M$1,$B22,$K$1) -> 0 | J22: =_xll.DBRW($C$2,Input_Prod_01!$D$9,Input_Prod_01!$C$11,$M$1,$B22,$K$1) -> 0 | ... N22: =_xll.DBRW($C$2,Input_Prod_01!$D$9,Input_Prod_01!$C$11,$M$1,$B22,$K$1) -> 0
B23: Câmbio Médio ARS$/US$ | C23: =_xll.DBRW($C$2,Input_Prod_01!$D$9,Input_Prod_01!$C$11,$M$1,$B23,$K$1) -> 0 | D23: =_xll.DBRW($C$2,Input_Prod_01!$D$9,Input_Prod_01!$C$11,$M$1,$B23,$K$1) -> 0 | E23: =_xll.DBRW($C$2,Input_Prod_01!$D$9,Input_Prod_01!$C$11,$M$1,$B23,$K$1) -> 0 | F23: =_xll.DBRW($C$2,Input_Prod_01!$D$9,Input_Prod_01!$C$11,$M$1,$B23,$K$1) -> 0 | G23: =_xll.DBRW($C$2,Input_Prod_01!$D$9,Input_Prod_01!$C$11,$M$1,$B23,$K$1) -> 0 | H23: =_xll.DBRW($C$2,Input_Prod_01!$D$9,Input_Prod_01!$C$11,$M$1,$B23,$K$1) -> 0 | I23: =_xll.DBRW($C$2,Input_Prod_01!$D$9,Input_Prod_01!$C$11,$M$1,$B23,$K$1) -> 0 | J23: =_xll.DBRW($C$2,Input_Prod_01!$D$9,Input_Prod_01!$C$11,$M$1,$B23,$K$1) -> 0 | ... N23: =_xll.DBRW($C$2,Input_Prod_01!$D$9,Input_Prod_01!$C$11,$M$1,$B23,$K$1) -> 0
B24: Câmbio Final ARS$/US$ | C24: =_xll.DBRW($C$2,Input_Prod_01!$D$9,Input_Prod_01!$C$11,$M$1,$B24,$K$1) -> 0 | D24: =_xll.DBRW($C$2,Input_Prod_01!$D$9,Input_Prod_01!$C$11,$M$1,$B24,$K$1) -> 0 | E24: =_xll.DBRW($C$2,Input_Prod_01!$D$9,Input_Prod_01!$C$11,$M$1,$B24,$K$1) -> 0 | F24: =_xll.DBRW($C$2,Input_Prod_01!$D$9,Input_Prod_01!$C$11,$M$1,$B24,$K$1) -> 0 | G24: =_xll.DBRW($C$2,Input_Prod_01!$D$9,Input_Prod_01!$C$11,$M$1,$B24,$K$1) -> 0 | H24: =_xll.DBRW($C$2,Input_Prod_01!$D$9,Input_Prod_01!$C$11,$M$1,$B24,$K$1) -> 0 | I24: =_xll.DBRW($C$2,Input_Prod_01!$D$9,Input_Prod_01!$C$11,$M$1,$B24,$K$1) -> 0 | J24: =_xll.DBRW($C$2,Input_Prod_01!$D$9,Input_Prod_01!$C$11,$M$1,$B24,$K$1) -> 0 | ... N24: =_xll.DBRW($C$2,Input_Prod_01!$D$9,Input_Prod_01!$C$11,$M$1,$B24,$K$1) -> 0
... B27: Number of Days | C27: =_xll.DBRW($C$2,Input_Prod_01!$D$9,Input_Prod_01!$C$11,$M$1,$B27,$K$1) -> 31 | D27: =_xll.DBRW($C$2,Input_Prod_01!$D$9,Input_Prod_01!$C$11,$M$1,$B27,$K$1) -> 31 | E27: =_xll.DBRW($C$2,Input_Prod_01!$D$9,Input_Prod_01!$C$11,$M$1,$B27,$K$1) -> 31 | F27: =_xll.DBRW($C$2,Input_Prod_01!$D$9,Input_Prod_01!$C$11,$M$1,$B27,$K$1) -> 31 | G27: =_xll.DBRW($C$2,Input_Prod_01!$D$9,Input_Prod_01!$C$11,$M$1,$B27,$K$1) -> 31 | H27: =_xll.DBRW($C$2,Input_Prod_01!$D$9,Input_Prod_01!$C$11,$M$1,$B27,$K$1) -> 31 | I27: =_xll.DBRW($C$2,Input_Prod_01!$D$9,Input_Prod_01!$C$11,$M$1,$B27,$K$1) -> 31 | J27: =_xll.DBRW($C$2,Input_Prod_01!$D$9,Input_Prod_01!$C$11,$M$1,$B27,$K$1) -> 31 | ... N27: =_xll.DBRW($C$2,Input_Prod_01!$D$9,Input_Prod_01!$C$11,$M$1,$B27,$K$1) -> 31
B30: NET REVENUES | D30: Products: | E30: =_xll.SUBNM("CONS_VC:ALL.D.Products","Nivel_0","PRODCE010 - Cement","Código e Descrição") -> PRODCE010 - Cement
C33: =$D$9&"."&C11 -> 2026.01 | D33: =$D$9&"."&D11 -> 2026.02 | E33: =$D$9&"."&E11 -> 2026.03 | F33: =$D$9&"."&F11 -> 2026.04 | G33: =$D$9&"."&G11 -> 2026.05 | H33: =$D$9&"."&H11 -> 2026.06 | I33: =$D$9&"."&I11 -> 2026.07 | J33: =$D$9&"."&J11 -> 2026.08 | ... N33: =$D$9&"."&N11 -> 2026.12
B34: Reference Price [$/ton] | C34: =_xll.DBRW($B$1,Input_Prod_01!$D$9,Input_Prod_01!C$11,$M$1,Input_Prod_01!$G$9,$J$9,Input_Prod_01!$E$30,Input_Prod_01!$B34,$L$1,$K$1) -> 0 | D34: =_xll.DBRW($B$1,Input_Prod_01!$D$9,Input_Prod_01!D$11,$M$1,Input_Prod_01!$G$9,$J$9,Input_Prod_01!$E$30,Input_Prod_01!$B34,$L$1,$K$1) -> 0 | E34: =_xll.DBRW($B$1,Input_Prod_01!$D$9,Input_Prod_01!E$11,$M$1,Input_Prod_01!$G$9,$J$9,Input_Prod_01!$E$30,Input_Prod_01!$B34,$L$1,$K$1) -> 0 | F34: =_xll.DBRW($B$1,Input_Prod_01!$D$9,Input_Prod_01!F$11,$M$1,Input_Prod_01!$G$9,$J$9,Input_Prod_01!$E$30,Input_Prod_01!$B34,$L$1,$K$1) -> 0 | G34: =_xll.DBRW($B$1,Input_Prod_01!$D$9,Input_Prod_01!G$11,$M$1,Input_Prod_01!$G$9,$J$9,Input_Prod_01!$E$30,Input_Prod_01!$B34,$L$1,$K$1) -> 0 | H34: =_xll.DBRW($B$1,Input_Prod_01!$D$9,Input_Prod_01!H$11,$M$1,Input_Prod_01!$G$9,$J$9,Input_Prod_01!$E$30,Input_Prod_01!$B34,$L$1,$K$1) -> 0 | I34: =_xll.DBRW($B$1,Input_Prod_01!$D$9,Input_Prod_01!I$11,$M$1,Input_Prod_01!$G$9,$J$9,Input_Prod_01!$E$30,Input_Prod_01!$B34,$L$1,$K$1) -> 0 | J34: =_xll.DBRW($B$1,Input_Prod_01!$D$9,Input_Prod_01!J$11,$M$1,Input_Prod_01!$G$9,$J$9,Input_Prod_01!$E$30,Input_Prod_01!$B34,$L$1,$K$1) -> 0 | ... N34: =_xll.DBRW($B$1,Input_Prod_01!$D$9,Input_Prod_01!N$11,$M$1,Input_Prod_01!$G$9,$J$9,Input_Prod_01!$E$30,Input_Prod_01!$B34,$L$1,$K$1) -> 0
B35: Local Market Sales Volume [kt] | C35: =_xll.DBRW($B$1,Input_Prod_01!$D$9,Input_Prod_01!C$11,$M$1,Input_Prod_01!$G$9,$J$9,Input_Prod_01!$E$30,Input_Prod_01!$B35,$L$1,$K$1) -> 0 | D35: =_xll.DBRW($B$1,Input_Prod_01!$D$9,Input_Prod_01!D$11,$M$1,Input_Prod_01!$G$9,$J$9,Input_Prod_01!$E$30,Input_Prod_01!$B35,$L$1,$K$1) -> 0 | E35: =_xll.DBRW($B$1,Input_Prod_01!$D$9,Input_Prod_01!E$11,$M$1,Input_Prod_01!$G$9,$J$9,Input_Prod_01!$E$30,Input_Prod_01!$B35,$L$1,$K$1) -> 0 | F35: =_xll.DBRW($B$1,Input_Prod_01!$D$9,Input_Prod_01!F$11,$M$1,Input_Prod_01!$G$9,$J$9,Input_Prod_01!$E$30,Input_Prod_01!$B35,$L$1,$K$1) -> 0 | G35: =_xll.DBRW($B$1,Input_Prod_01!$D$9,Input_Prod_01!G$11,$M$1,Input_Prod_01!$G$9,$J$9,Input_Prod_01!$E$30,Input_Prod_01!$B35,$L$1,$K$1) -> 0 | H35: =_xll.DBRW($B$1,Input_Prod_01!$D$9,Input_Prod_01!H$11,$M$1,Input_Prod_01!$G$9,$J$9,Input_Prod_01!$E$30,Input_Prod_01!$B35,$L$1,$K$1) -> 0 | I35: =_xll.DBRW($B$1,Input_Prod_01!$D$9,Input_Prod_01!I$11,$M$1,Input_Prod_01!$G$9,$J$9,Input_Prod_01!$E$30,Input_Prod_01!$B35,$L$1,$K$1) -> 0 | J35: =_xll.DBRW($B$1,Input_Prod_01!$D$9,Input_Prod_01!J$11,$M$1,Input_Prod_01!$G$9,$J$9,Input_Prod_01!$E$30,Input_Prod_01!$B35,$L$1,$K$1) -> 0 | ... N35: =_xll.DBRW($B$1,Input_Prod_01!$D$9,Input_Prod_01!N$11,$M$1,Input_Prod_01!$G$9,$J$9,Input_Prod_01!$E$30,Input_Prod_01!$B35,$L$1,$K$1) -> 0
B36: Export Market Sales Volume [kt] | C36: =_xll.DBRW($B$1,Input_Prod_01!$D$9,Input_Prod_01!C$11,$M$1,Input_Prod_01!$G$9,$J$9,Input_Prod_01!$E$30,Input_Prod_01!$B36,$L$1,$K$1) -> 207.21655 | D36: =_xll.DBRW($B$1,Input_Prod_01!$D$9,Input_Prod_01!D$11,$M$1,Input_Prod_01!$G$9,$J$9,Input_Prod_01!$E$30,Input_Prod_01!$B36,$L$1,$K$1) -> 244.64194 | E36: =_xll.DBRW($B$1,Input_Prod_01!$D$9,Input_Prod_01!E$11,$M$1,Input_Prod_01!$G$9,$J$9,Input_Prod_01!$E$30,Input_Prod_01!$B36,$L$1,$K$1) -> 362.2005 | F36: =_xll.DBRW($B$1,Input_Prod_01!$D$9,Input_Prod_01!F$11,$M$1,Input_Prod_01!$G$9,$J$9,Input_Prod_01!$E$30,Input_Prod_01!$B36,$L$1,$K$1) -> 503.21174 | G36: =_xll.DBRW($B$1,Input_Prod_01!$D$9,Input_Prod_01!G$11,$M$1,Input_Prod_01!$G$9,$J$9,Input_Prod_01!$E$30,Input_Prod_01!$B36,$L$1,$K$1) -> 603.05328 | H36: =_xll.DBRW($B$1,Input_Prod_01!$D$9,Input_Prod_01!H$11,$M$1,Input_Prod_01!$G$9,$J$9,Input_Prod_01!$E$30,Input_Prod_01!$B36,$L$1,$K$1) -> 680.11963 | I36: =_xll.DBRW($B$1,Input_Prod_01!$D$9,Input_Prod_01!I$11,$M$1,Input_Prod_01!$G$9,$J$9,Input_Prod_01!$E$30,Input_Prod_01!$B36,$L$1,$K$1) -> 655.73708 | J36: =_xll.DBRW($B$1,Input_Prod_01!$D$9,Input_Prod_01!J$11,$M$1,Input_Prod_01!$G$9,$J$9,Input_Prod_01!$E$30,Input_Prod_01!$B36,$L$1,$K$1) -> 619.07454 | ... N36: =_xll.DBRW($B$1,Input_Prod_01!$D$9,Input_Prod_01!N$11,$M$1,Input_Prod_01!$G$9,$J$9,Input_Prod_01!$E$30,Input_Prod_01!$B36,$L$1,$K$1) -> 329.92947
B37: Third Part Sales Volume [kt] | C37: =_xll.DBRW($B$1,Input_Prod_01!$D$9,Input_Prod_01!C$11,$M$1,Input_Prod_01!$G$9,$J$9,Input_Prod_01!$E$30,Input_Prod_01!$B37,$L$1,$K$1) -> 0 | D37: =_xll.DBRW($B$1,Input_Prod_01!$D$9,Input_Prod_01!D$11,$M$1,Input_Prod_01!$G$9,$J$9,Input_Prod_01!$E$30,Input_Prod_01!$B37,$L$1,$K$1) -> 0 | E37: =_xll.DBRW($B$1,Input_Prod_01!$D$9,Input_Prod_01!E$11,$M$1,Input_Prod_01!$G$9,$J$9,Input_Prod_01!$E$30,Input_Prod_01!$B37,$L$1,$K$1) -> 0 | F37: =_xll.DBRW($B$1,Input_Prod_01!$D$9,Input_Prod_01!F$11,$M$1,Input_Prod_01!$G$9,$J$9,Input_Prod_01!$E$30,Input_Prod_01!$B37,$L$1,$K$1) -> 0 | G37: =_xll.DBRW($B$1,Input_Prod_01!$D$9,Input_Prod_01!G$11,$M$1,Input_Prod_01!$G$9,$J$9,Input_Prod_01!$E$30,Input_Prod_01!$B37,$L$1,$K$1) -> 0 | H37: =_xll.DBRW($B$1,Input_Prod_01!$D$9,Input_Prod_01!H$11,$M$1,Input_Prod_01!$G$9,$J$9,Input_Prod_01!$E$30,Input_Prod_01!$B37,$L$1,$K$1) -> 0 | I37: =_xll.DBRW($B$1,Input_Prod_01!$D$9,Input_Prod_01!I$11,$M$1,Input_Prod_01!$G$9,$J$9,Input_Prod_01!$E$30,Input_Prod_01!$B37,$L$1,$K$1) -> 0 | J37: =_xll.DBRW($B$1,Input_Prod_01!$D$9,Input_Prod_01!J$11,$M$1,Input_Prod_01!$G$9,$J$9,Input_Prod_01!$E$30,Input_Prod_01!$B37,$L$1,$K$1) -> 0 | ... N37: =_xll.DBRW($B$1,Input_Prod_01!$D$9,Input_Prod_01!N$11,$M$1,Input_Prod_01!$G$9,$J$9,Input_Prod_01!$E$30,Input_Prod_01!$B37,$L$1,$K$1) -> 0
B38: Local Market Price Premium [$/ton] | C38: =_xll.DBRW($B$1,Input_Prod_01!$D$9,Input_Prod_01!C$11,$M$1,Input_Prod_01!$G$9,$J$9,Input_Prod_01!$E$30,Input_Prod_01!$B38,$L$1,$K$1) -> 0 | D38: =_xll.DBRW($B$1,Input_Prod_01!$D$9,Input_Prod_01!D$11,$M$1,Input_Prod_01!$G$9,$J$9,Input_Prod_01!$E$30,Input_Prod_01!$B38,$L$1,$K$1) -> 0 | E38: =_xll.DBRW($B$1,Input_Prod_01!$D$9,Input_Prod_01!E$11,$M$1,Input_Prod_01!$G$9,$J$9,Input_Prod_01!$E$30,Input_Prod_01!$B38,$L$1,$K$1) -> 0 | F38: =_xll.DBRW($B$1,Input_Prod_01!$D$9,Input_Prod_01!F$11,$M$1,Input_Prod_01!$G$9,$J$9,Input_Prod_01!$E$30,Input_Prod_01!$B38,$L$1,$K$1) -> 0 | G38: =_xll.DBRW($B$1,Input_Prod_01!$D$9,Input_Prod_01!G$11,$M$1,Input_Prod_01!$G$9,$J$9,Input_Prod_01!$E$30,Input_Prod_01!$B38,$L$1,$K$1) -> 0 | H38: =_xll.DBRW($B$1,Input_Prod_01!$D$9,Input_Prod_01!H$11,$M$1,Input_Prod_01!$G$9,$J$9,Input_Prod_01!$E$30,Input_Prod_01!$B38,$L$1,$K$1) -> 0 | I38: =_xll.DBRW($B$1,Input_Prod_01!$D$9,Input_Prod_01!I$11,$M$1,Input_Prod_01!$G$9,$J$9,Input_Prod_01!$E$30,Input_Prod_01!$B38,$L$1,$K$1) -> 0 | J38: =_xll.DBRW($B$1,Input_Prod_01!$D$9,Input_Prod_01!J$11,$M$1,Input_Prod_01!$G$9,$J$9,Input_Prod_01!$E$30,Input_Prod_01!$B38,$L$1,$K$1) -> 0 | ... N38: =_xll.DBRW($B$1,Input_Prod_01!$D$9,Input_Prod_01!N$11,$M$1,Input_Prod_01!$G$9,$J$9,Input_Prod_01!$E$30,Input_Prod_01!$B38,$L$1,$K$1) -> 0
B39: Export Market Price Premium [$/ton] | C39: =_xll.DBRW($B$1,Input_Prod_01!$D$9,Input_Prod_01!C$11,$M$1,Input_Prod_01!$G$9,$J$9,Input_Prod_01!$E$30,Input_Prod_01!$B39,$L$1,$K$1) -> 155.32501 | D39: =_xll.DBRW($B$1,Input_Prod_01!$D$9,Input_Prod_01!D$11,$M$1,Input_Prod_01!$G$9,$J$9,Input_Prod_01!$E$30,Input_Prod_01!$B39,$L$1,$K$1) -> 155.54341 | E39: =_xll.DBRW($B$1,Input_Prod_01!$D$9,Input_Prod_01!E$11,$M$1,Input_Prod_01!$G$9,$J$9,Input_Prod_01!$E$30,Input_Prod_01!$B39,$L$1,$K$1) -> 154.10349 | F39: =_xll.DBRW($B$1,Input_Prod_01!$D$9,Input_Prod_01!F$11,$M$1,Input_Prod_01!$G$9,$J$9,Input_Prod_01!$E$30,Input_Prod_01!$B39,$L$1,$K$1) -> 156.28361 | G39: =_xll.DBRW($B$1,Input_Prod_01!$D$9,Input_Prod_01!G$11,$M$1,Input_Prod_01!$G$9,$J$9,Input_Prod_01!$E$30,Input_Prod_01!$B39,$L$1,$K$1) -> 155.93802 | H39: =_xll.DBRW($B$1,Input_Prod_01!$D$9,Input_Prod_01!H$11,$M$1,Input_Prod_01!$G$9,$J$9,Input_Prod_01!$E$30,Input_Prod_01!$B39,$L$1,$K$1) -> 157.38036 | I39: =_xll.DBRW($B$1,Input_Prod_01!$D$9,Input_Prod_01!I$11,$M$1,Input_Prod_01!$G$9,$J$9,Input_Prod_01!$E$30,Input_Prod_01!$B39,$L$1,$K$1) -> 156.82383 | J39: =_xll.DBRW($B$1,Input_Prod_01!$D$9,Input_Prod_01!J$11,$M$1,Input_Prod_01!$G$9,$J$9,Input_Prod_01!$E$30,Input_Prod_01!$B39,$L$1,$K$1) -> 158.55054 | ... N39: =_xll.DBRW($B$1,Input_Prod_01!$D$9,Input_Prod_01!N$11,$M$1,Input_Prod_01!$G$9,$J$9,Input_Prod_01!$E$30,Input_Prod_01!$B39,$L$1,$K$1) -> 153.02143
B40: % Operational Tax | C40: =_xll.DBRW($B$1,Input_Prod_01!$D$9,Input_Prod_01!C$11,$M$1,Input_Prod_01!$G$9,$J$9,Input_Prod_01!$E$30,Input_Prod_01!$B40,$L$1,$K$1) -> 0 | D40: =_xll.DBRW($B$1,Input_Prod_01!$D$9,Input_Prod_01!D$11,$M$1,Input_Prod_01!$G$9,$J$9,Input_Prod_01!$E$30,Input_Prod_01!$B40,$L$1,$K$1) -> 0 | E40: =_xll.DBRW($B$1,Input_Prod_01!$D$9,Input_Prod_01!E$11,$M$1,Input_Prod_01!$G$9,$J$9,Input_Prod_01!$E$30,Input_Prod_01!$B40,$L$1,$K$1) -> 0 | F40: =_xll.DBRW($B$1,Input_Prod_01!$D$9,Input_Prod_01!F$11,$M$1,Input_Prod_01!$G$9,$J$9,Input_Prod_01!$E$30,Input_Prod_01!$B40,$L$1,$K$1) -> 0 | G40: =_xll.DBRW($B$1,Input_Prod_01!$D$9,Input_Prod_01!G$11,$M$1,Input_Prod_01!$G$9,$J$9,Input_Prod_01!$E$30,Input_Prod_01!$B40,$L$1,$K$1) -> 0 | H40: =_xll.DBRW($B$1,Input_Prod_01!$D$9,Input_Prod_01!H$11,$M$1,Input_Prod_01!$G$9,$J$9,Input_Prod_01!$E$30,Input_Prod_01!$B40,$L$1,$K$1) -> 0 | I40: =_xll.DBRW($B$1,Input_Prod_01!$D$9,Input_Prod_01!I$11,$M$1,Input_Prod_01!$G$9,$J$9,Input_Prod_01!$E$30,Input_Prod_01!$B40,$L$1,$K$1) -> 0 | J40: =_xll.DBRW($B$1,Input_Prod_01!$D$9,Input_Prod_01!J$11,$M$1,Input_Prod_01!$G$9,$J$9,Input_Prod_01!$E$30,Input_Prod_01!$B40,$L$1,$K$1) -> 0 | ... N40: =_xll.DBRW($B$1,Input_Prod_01!$D$9,Input_Prod_01!N$11,$M$1,Input_Prod_01!$G$9,$J$9,Input_Prod_01!$E$30,Input_Prod_01!$B40,$L$1,$K$1) -> 0
B41: Gross Revenue [$MM] | C41: =_xll.DBRW($B$2,Input_Prod_01!$D$9,Input_Prod_01!C$11,$M$1,Input_Prod_01!$G$9,$J$9,$E$30,$K$2,$B$41) -> 32.185912 | D41: =_xll.DBRW($B$2,Input_Prod_01!$D$9,Input_Prod_01!D$11,$M$1,Input_Prod_01!$G$9,$J$9,$E$30,$K$2,$B$41) -> 38.052441 | E41: =_xll.DBRW($B$2,Input_Prod_01!$D$9,Input_Prod_01!E$11,$M$1,Input_Prod_01!$G$9,$J$9,$E$30,$K$2,$B$41) -> 55.816362 | F41: =_xll.DBRW($B$2,Input_Prod_01!$D$9,Input_Prod_01!F$11,$M$1,Input_Prod_01!$G$9,$J$9,$E$30,$K$2,$B$41) -> 78.643745 | G41: =_xll.DBRW($B$2,Input_Prod_01!$D$9,Input_Prod_01!G$11,$M$1,Input_Prod_01!$G$9,$J$9,$E$30,$K$2,$B$41) -> 94.038934 | H41: =_xll.DBRW($B$2,Input_Prod_01!$D$9,Input_Prod_01!H$11,$M$1,Input_Prod_01!$G$9,$J$9,$E$30,$K$2,$B$41) -> 107.03747 | I41: =_xll.DBRW($B$2,Input_Prod_01!$D$9,Input_Prod_01!I$11,$M$1,Input_Prod_01!$G$9,$J$9,$E$30,$K$2,$B$41) -> 102.8352 | J41: =_xll.DBRW($B$2,Input_Prod_01!$D$9,Input_Prod_01!J$11,$M$1,Input_Prod_01!$G$9,$J$9,$E$30,$K$2,$B$41) -> 98.154603 | ... N41: =_xll.DBRW($B$2,Input_Prod_01!$D$9,Input_Prod_01!N$11,$M$1,Input_Prod_01!$G$9,$J$9,$E$30,$K$2,$B$41) -> 50.48628
B42: Net Revenue [$MM] | C42: =_xll.DBRW($B$2,Input_Prod_01!$D$9,Input_Prod_01!C$11,$M$1,Input_Prod_01!$G$9,$J$9,$E$30,$K$2,$B$42) -> 32.185912 | D42: =_xll.DBRW($B$2,Input_Prod_01!$D$9,Input_Prod_01!D$11,$M$1,Input_Prod_01!$G$9,$J$9,$E$30,$K$2,$B$42) -> 38.052441 | E42: =_xll.DBRW($B$2,Input_Prod_01!$D$9,Input_Prod_01!E$11,$M$1,Input_Prod_01!$G$9,$J$9,$E$30,$K$2,$B$42) -> 55.816362 | F42: =_xll.DBRW($B$2,Input_Prod_01!$D$9,Input_Prod_01!F$11,$M$1,Input_Prod_01!$G$9,$J$9,$E$30,$K$2,$B$42) -> 78.643745 | G42: =_xll.DBRW($B$2,Input_Prod_01!$D$9,Input_Prod_01!G$11,$M$1,Input_Prod_01!$G$9,$J$9,$E$30,$K$2,$B$42) -> 94.038934 | H42: =_xll.DBRW($B$2,Input_Prod_01!$D$9,Input_Prod_01!H$11,$M$1,Input_Prod_01!$G$9,$J$9,$E$30,$K$2,$B$42) -> 107.03747 | I42: =_xll.DBRW($B$2,Input_Prod_01!$D$9,Input_Prod_01!I$11,$M$1,Input_Prod_01!$G$9,$J$9,$E$30,$K$2,$B$42) -> 102.8352 | J42: =_xll.DBRW($B$2,Input_Prod_01!$D$9,Input_Prod_01!J$11,$M$1,Input_Prod_01!$G$9,$J$9,$E$30,$K$2,$B$42) -> 98.154603 | ... N42: =_xll.DBRW($B$2,Input_Prod_01!$D$9,Input_Prod_01!N$11,$M$1,Input_Prod_01!$G$9,$J$9,$E$30,$K$2,$B$42) -> 50.48628
B46: CONTRIBUTION MARGIN
C49: =$D$9&"."&C$11 -> 2026.01 | D49: =$D$9&"."&D$11 -> 2026.02 | E49: =$D$9&"."&E$11 -> 2026.03 | F49: =$D$9&"."&F$11 -> 2026.04 | G49: =$D$9&"."&G$11 -> 2026.05 | H49: =$D$9&"."&H$11 -> 2026.06 | I49: =$D$9&"."&I$11 -> 2026.07 | J49: =$D$9&"."&J$11 -> 2026.08 | ... N49: =$D$9&"."&N$11 -> 2026.12
B50: Final Variable Sales Expenses | C50: =_xll.DBRW($B$1,Input_Prod_01!$D$9,Input_Prod_01!C$11,$M$1,Input_Prod_01!$G$9,$J$9,$E$30,Input_Prod_01!$B50,$L$1,$K$1) -> 0 | D50: =_xll.DBRW($B$1,Input_Prod_01!$D$9,Input_Prod_01!D$11,$M$1,Input_Prod_01!$G$9,$J$9,$E$30,Input_Prod_01!$B50,$L$1,$K$1) -> 0 | E50: =_xll.DBRW($B$1,Input_Prod_01!$D$9,Input_Prod_01!E$11,$M$1,Input_Prod_01!$G$9,$J$9,$E$30,Input_Prod_01!$B50,$L$1,$K$1) -> 0 | F50: =_xll.DBRW($B$1,Input_Prod_01!$D$9,Input_Prod_01!F$11,$M$1,Input_Prod_01!$G$9,$J$9,$E$30,Input_Prod_01!$B50,$L$1,$K$1) -> 0 | G50: =_xll.DBRW($B$1,Input_Prod_01!$D$9,Input_Prod_01!G$11,$M$1,Input_Prod_01!$G$9,$J$9,$E$30,Input_Prod_01!$B50,$L$1,$K$1) -> 0 | H50: =_xll.DBRW($B$1,Input_Prod_01!$D$9,Input_Prod_01!H$11,$M$1,Input_Prod_01!$G$9,$J$9,$E$30,Input_Prod_01!$B50,$L$1,$K$1) -> 0 | I50: =_xll.DBRW($B$1,Input_Prod_01!$D$9,Input_Prod_01!I$11,$M$1,Input_Prod_01!$G$9,$J$9,$E$30,Input_Prod_01!$B50,$L$1,$K$1) -> 0 | J50: =_xll.DBRW($B$1,Input_Prod_01!$D$9,Input_Prod_01!J$11,$M$1,Input_Prod_01!$G$9,$J$9,$E$30,Input_Prod_01!$B50,$L$1,$K$1) -> 0 | ... N50: =_xll.DBRW($B$1,Input_Prod_01!$D$9,Input_Prod_01!N$11,$M$1,Input_Prod_01!$G$9,$J$9,$E$30,Input_Prod_01!$B50,$L$1,$K$1) -> 0
B51: Other Variable Costs | C51: =_xll.DBRW($B$1,Input_Prod_01!$D$9,Input_Prod_01!C$11,$M$1,Input_Prod_01!$G$9,$J$9,$E$30,Input_Prod_01!$B51,$L$1,$K$1) -> 9.9428448 | D51: =_xll.DBRW($B$1,Input_Prod_01!$D$9,Input_Prod_01!D$11,$M$1,Input_Prod_01!$G$9,$J$9,$E$30,Input_Prod_01!$B51,$L$1,$K$1) -> 18.330327 | E51: =_xll.DBRW($B$1,Input_Prod_01!$D$9,Input_Prod_01!E$11,$M$1,Input_Prod_01!$G$9,$J$9,$E$30,Input_Prod_01!$B51,$L$1,$K$1) -> 16.901681 | F51: =_xll.DBRW($B$1,Input_Prod_01!$D$9,Input_Prod_01!F$11,$M$1,Input_Prod_01!$G$9,$J$9,$E$30,Input_Prod_01!$B51,$L$1,$K$1) -> 21.671895 | G51: =_xll.DBRW($B$1,Input_Prod_01!$D$9,Input_Prod_01!G$11,$M$1,Input_Prod_01!$G$9,$J$9,$E$30,Input_Prod_01!$B51,$L$1,$K$1) -> 21.517253 | H51: =_xll.DBRW($B$1,Input_Prod_01!$D$9,Input_Prod_01!H$11,$M$1,Input_Prod_01!$G$9,$J$9,$E$30,Input_Prod_01!$B51,$L$1,$K$1) -> 24.83239 | I51: =_xll.DBRW($B$1,Input_Prod_01!$D$9,Input_Prod_01!I$11,$M$1,Input_Prod_01!$G$9,$J$9,$E$30,Input_Prod_01!$B51,$L$1,$K$1) -> 23.311851 | J51: =_xll.DBRW($B$1,Input_Prod_01!$D$9,Input_Prod_01!J$11,$M$1,Input_Prod_01!$G$9,$J$9,$E$30,Input_Prod_01!$B51,$L$1,$K$1) -> 22.717522 | ... N51: =_xll.DBRW($B$1,Input_Prod_01!$D$9,Input_Prod_01!N$11,$M$1,Input_Prod_01!$G$9,$J$9,$E$30,Input_Prod_01!$B51,$L$1,$K$1) -> 9.8084707
B52: Fixed Costs | C52: =_xll.DBRW($B$1,Input_Prod_01!$D$9,Input_Prod_01!C$11,$M$1,Input_Prod_01!$G$9,$J$9,$E$30,Input_Prod_01!$B52,$L$1,$K$1) -> 0 | D52: =_xll.DBRW($B$1,Input_Prod_01!$D$9,Input_Prod_01!D$11,$M$1,Input_Prod_01!$G$9,$J$9,$E$30,Input_Prod_01!$B52,$L$1,$K$1) -> 0 | E52: =_xll.DBRW($B$1,Input_Prod_01!$D$9,Input_Prod_01!E$11,$M$1,Input_Prod_01!$G$9,$J$9,$E$30,Input_Prod_01!$B52,$L$1,$K$1) -> 0 | F52: =_xll.DBRW($B$1,Input_Prod_01!$D$9,Input_Prod_01!F$11,$M$1,Input_Prod_01!$G$9,$J$9,$E$30,Input_Prod_01!$B52,$L$1,$K$1) -> 0 | G52: =_xll.DBRW($B$1,Input_Prod_01!$D$9,Input_Prod_01!G$11,$M$1,Input_Prod_01!$G$9,$J$9,$E$30,Input_Prod_01!$B52,$L$1,$K$1) -> 0 | H52: =_xll.DBRW($B$1,Input_Prod_01!$D$9,Input_Prod_01!H$11,$M$1,Input_Prod_01!$G$9,$J$9,$E$30,Input_Prod_01!$B52,$L$1,$K$1) -> 0 | I52: =_xll.DBRW($B$1,Input_Prod_01!$D$9,Input_Prod_01!I$11,$M$1,Input_Prod_01!$G$9,$J$9,$E$30,Input_Prod_01!$B52,$L$1,$K$1) -> 0 | J52: =_xll.DBRW($B$1,Input_Prod_01!$D$9,Input_Prod_01!J$11,$M$1,Input_Prod_01!$G$9,$J$9,$E$30,Input_Prod_01!$B52,$L$1,$K$1) -> 0 | ... N52: =_xll.DBRW($B$1,Input_Prod_01!$D$9,Input_Prod_01!N$11,$M$1,Input_Prod_01!$G$9,$J$9,$E$30,Input_Prod_01!$B52,$L$1,$K$1) -> 0
B53: Operating Expenses | C53: =_xll.DBRW($B$1,Input_Prod_01!$D$9,Input_Prod_01!C$11,$M$1,Input_Prod_01!$G$9,$J$9,$E$30,Input_Prod_01!$B53,$L$1,$K$1) -> 0 | D53: =_xll.DBRW($B$1,Input_Prod_01!$D$9,Input_Prod_01!D$11,$M$1,Input_Prod_01!$G$9,$J$9,$E$30,Input_Prod_01!$B53,$L$1,$K$1) -> 0 | E53: =_xll.DBRW($B$1,Input_Prod_01!$D$9,Input_Prod_01!E$11,$M$1,Input_Prod_01!$G$9,$J$9,$E$30,Input_Prod_01!$B53,$L$1,$K$1) -> 0 | F53: =_xll.DBRW($B$1,Input_Prod_01!$D$9,Input_Prod_01!F$11,$M$1,Input_Prod_01!$G$9,$J$9,$E$30,Input_Prod_01!$B53,$L$1,$K$1) -> 0 | G53: =_xll.DBRW($B$1,Input_Prod_01!$D$9,Input_Prod_01!G$11,$M$1,Input_Prod_01!$G$9,$J$9,$E$30,Input_Prod_01!$B53,$L$1,$K$1) -> 0 | H53: =_xll.DBRW($B$1,Input_Prod_01!$D$9,Input_Prod_01!H$11,$M$1,Input_Prod_01!$G$9,$J$9,$E$30,Input_Prod_01!$B53,$L$1,$K$1) -> 0 | I53: =_xll.DBRW($B$1,Input_Prod_01!$D$9,Input_Prod_01!I$11,$M$1,Input_Prod_01!$G$9,$J$9,$E$30,Input_Prod_01!$B53,$L$1,$K$1) -> 0 | J53: =_xll.DBRW($B$1,Input_Prod_01!$D$9,Input_Prod_01!J$11,$M$1,Input_Prod_01!$G$9,$J$9,$E$30,Input_Prod_01!$B53,$L$1,$K$1) -> 0 | ... N53: =_xll.DBRW($B$1,Input_Prod_01!$D$9,Input_Prod_01!N$11,$M$1,Input_Prod_01!$G$9,$J$9,$E$30,Input_Prod_01!$B53,$L$1,$K$1) -> 0
B54: Other | C54: =_xll.DBRW($B$1,Input_Prod_01!$D$9,Input_Prod_01!C$11,$M$1,Input_Prod_01!$G$9,$J$9,$E$30,$B$54,"Total Accounts Line",$K$1) -> 0 | D54: =_xll.DBRW($B$1,Input_Prod_01!$D$9,Input_Prod_01!D$11,$M$1,Input_Prod_01!$G$9,$J$9,$E$30,$B$54,"Total Accounts Line",$K$1) -> 0 | E54: =_xll.DBRW($B$1,Input_Prod_01!$D$9,Input_Prod_01!E$11,$M$1,Input_Prod_01!$G$9,$J$9,$E$30,$B$54,"Total Accounts Line",$K$1) -> 0 | F54: =_xll.DBRW($B$1,Input_Prod_01!$D$9,Input_Prod_01!F$11,$M$1,Input_Prod_01!$G$9,$J$9,$E$30,$B$54,"Total Accounts Line",$K$1) -> 0 | G54: =_xll.DBRW($B$1,Input_Prod_01!$D$9,Input_Prod_01!G$11,$M$1,Input_Prod_01!$G$9,$J$9,$E$30,$B$54,"Total Accounts Line",$K$1) -> 0 | H54: =_xll.DBRW($B$1,Input_Prod_01!$D$9,Input_Prod_01!H$11,$M$1,Input_Prod_01!$G$9,$J$9,$E$30,$B$54,"Total Accounts Line",$K$1) -> 0 | I54: =_xll.DBRW($B$1,Input_Prod_01!$D$9,Input_Prod_01!I$11,$M$1,Input_Prod_01!$G$9,$J$9,$E$30,$B$54,"Total Accounts Line",$K$1) -> 0 | J54: =_xll.DBRW($B$1,Input_Prod_01!$D$9,Input_Prod_01!J$11,$M$1,Input_Prod_01!$G$9,$J$9,$E$30,$B$54,"Total Accounts Line",$K$1) -> 0 | ... N54: =_xll.DBRW($B$1,Input_Prod_01!$D$9,Input_Prod_01!N$11,$M$1,Input_Prod_01!$G$9,$J$9,$E$30,$B$54,"Total Accounts Line",$K$1) -> 0
B55: Other Op. Results - Asset Write-off | C55: =_xll.DBRW($B$1,Input_Prod_01!$D$9,Input_Prod_01!C$11,$M$1,Input_Prod_01!$G$9,$J$9,$E$30,$B$54,$B55,$K$1) -> 0 | D55: =_xll.DBRW($B$1,Input_Prod_01!$D$9,Input_Prod_01!D$11,$M$1,Input_Prod_01!$G$9,$J$9,$E$30,$B$54,$B55,$K$1) -> 0 | E55: =_xll.DBRW($B$1,Input_Prod_01!$D$9,Input_Prod_01!E$11,$M$1,Input_Prod_01!$G$9,$J$9,$E$30,$B$54,$B55,$K$1) -> 0 | F55: =_xll.DBRW($B$1,Input_Prod_01!$D$9,Input_Prod_01!F$11,$M$1,Input_Prod_01!$G$9,$J$9,$E$30,$B$54,$B55,$K$1) -> 0 | G55: =_xll.DBRW($B$1,Input_Prod_01!$D$9,Input_Prod_01!G$11,$M$1,Input_Prod_01!$G$9,$J$9,$E$30,$B$54,$B55,$K$1) -> 0 | H55: =_xll.DBRW($B$1,Input_Prod_01!$D$9,Input_Prod_01!H$11,$M$1,Input_Prod_01!$G$9,$J$9,$E$30,$B$54,$B55,$K$1) -> 0 | I55: =_xll.DBRW($B$1,Input_Prod_01!$D$9,Input_Prod_01!I$11,$M$1,Input_Prod_01!$G$9,$J$9,$E$30,$B$54,$B55,$K$1) -> 0 | J55: =_xll.DBRW($B$1,Input_Prod_01!$D$9,Input_Prod_01!J$11,$M$1,Input_Prod_01!$G$9,$J$9,$E$30,$B$54,$B55,$K$1) -> 0 | ... N55: =_xll.DBRW($B$1,Input_Prod_01!$D$9,Input_Prod_01!N$11,$M$1,Input_Prod_01!$G$9,$J$9,$E$30,$B$54,$B55,$K$1) -> 0
B56: Slow moving | C56: =_xll.DBRW($B$1,Input_Prod_01!$D$9,Input_Prod_01!C$11,$M$1,Input_Prod_01!$G$9,$J$9,$E$30,$B$54,$B56,$K$1) -> 0 | D56: =_xll.DBRW($B$1,Input_Prod_01!$D$9,Input_Prod_01!D$11,$M$1,Input_Prod_01!$G$9,$J$9,$E$30,$B$54,$B56,$K$1) -> 0 | E56: =_xll.DBRW($B$1,Input_Prod_01!$D$9,Input_Prod_01!E$11,$M$1,Input_Prod_01!$G$9,$J$9,$E$30,$B$54,$B56,$K$1) -> 0 | F56: =_xll.DBRW($B$1,Input_Prod_01!$D$9,Input_Prod_01!F$11,$M$1,Input_Prod_01!$G$9,$J$9,$E$30,$B$54,$B56,$K$1) -> 0 | G56: =_xll.DBRW($B$1,Input_Prod_01!$D$9,Input_Prod_01!G$11,$M$1,Input_Prod_01!$G$9,$J$9,$E$30,$B$54,$B56,$K$1) -> 0 | H56: =_xll.DBRW($B$1,Input_Prod_01!$D$9,Input_Prod_01!H$11,$M$1,Input_Prod_01!$G$9,$J$9,$E$30,$B$54,$B56,$K$1) -> 0 | I56: =_xll.DBRW($B$1,Input_Prod_01!$D$9,Input_Prod_01!I$11,$M$1,Input_Prod_01!$G$9,$J$9,$E$30,$B$54,$B56,$K$1) -> 0 | J56: =_xll.DBRW($B$1,Input_Prod_01!$D$9,Input_Prod_01!J$11,$M$1,Input_Prod_01!$G$9,$J$9,$E$30,$B$54,$B56,$K$1) -> 0 | ... N56: =_xll.DBRW($B$1,Input_Prod_01!$D$9,Input_Prod_01!N$11,$M$1,Input_Prod_01!$G$9,$J$9,$E$30,$B$54,$B56,$K$1) -> 0
B57: Clinker | C57: =_xll.DBRW($B$1,Input_Prod_01!$D$9,Input_Prod_01!C$11,$M$1,Input_Prod_01!$G$9,$J$9,$E$30,$B$54,$B57,$K$1) -> 0 | D57: =_xll.DBRW($B$1,Input_Prod_01!$D$9,Input_Prod_01!D$11,$M$1,Input_Prod_01!$G$9,$J$9,$E$30,$B$54,$B57,$K$1) -> 0 | E57: =_xll.DBRW($B$1,Input_Prod_01!$D$9,Input_Prod_01!E$11,$M$1,Input_Prod_01!$G$9,$J$9,$E$30,$B$54,$B57,$K$1) -> 0 | F57: =_xll.DBRW($B$1,Input_Prod_01!$D$9,Input_Prod_01!F$11,$M$1,Input_Prod_01!$G$9,$J$9,$E$30,$B$54,$B57,$K$1) -> 0 | G57: =_xll.DBRW($B$1,Input_Prod_01!$D$9,Input_Prod_01!G$11,$M$1,Input_Prod_01!$G$9,$J$9,$E$30,$B$54,$B57,$K$1) -> 0 | H57: =_xll.DBRW($B$1,Input_Prod_01!$D$9,Input_Prod_01!H$11,$M$1,Input_Prod_01!$G$9,$J$9,$E$30,$B$54,$B57,$K$1) -> 0 | I57: =_xll.DBRW($B$1,Input_Prod_01!$D$9,Input_Prod_01!I$11,$M$1,Input_Prod_01!$G$9,$J$9,$E$30,$B$54,$B57,$K$1) -> 0 | J57: =_xll.DBRW($B$1,Input_Prod_01!$D$9,Input_Prod_01!J$11,$M$1,Input_Prod_01!$G$9,$J$9,$E$30,$B$54,$B57,$K$1) -> 0 | ... N57: =_xll.DBRW($B$1,Input_Prod_01!$D$9,Input_Prod_01!N$11,$M$1,Input_Prod_01!$G$9,$J$9,$E$30,$B$54,$B57,$K$1) -> 0
B58: Contingencies | C58: =_xll.DBRW($B$1,Input_Prod_01!$D$9,Input_Prod_01!C$11,$M$1,Input_Prod_01!$G$9,$J$9,$E$30,$B$54,$B58,$K$1) -> 0 | D58: =_xll.DBRW($B$1,Input_Prod_01!$D$9,Input_Prod_01!D$11,$M$1,Input_Prod_01!$G$9,$J$9,$E$30,$B$54,$B58,$K$1) -> 0 | E58: =_xll.DBRW($B$1,Input_Prod_01!$D$9,Input_Prod_01!E$11,$M$1,Input_Prod_01!$G$9,$J$9,$E$30,$B$54,$B58,$K$1) -> 0 | F58: =_xll.DBRW($B$1,Input_Prod_01!$D$9,Input_Prod_01!F$11,$M$1,Input_Prod_01!$G$9,$J$9,$E$30,$B$54,$B58,$K$1) -> 0 | G58: =_xll.DBRW($B$1,Input_Prod_01!$D$9,Input_Prod_01!G$11,$M$1,Input_Prod_01!$G$9,$J$9,$E$30,$B$54,$B58,$K$1) -> 0 | H58: =_xll.DBRW($B$1,Input_Prod_01!$D$9,Input_Prod_01!H$11,$M$1,Input_Prod_01!$G$9,$J$9,$E$30,$B$54,$B58,$K$1) -> 0 | I58: =_xll.DBRW($B$1,Input_Prod_01!$D$9,Input_Prod_01!I$11,$M$1,Input_Prod_01!$G$9,$J$9,$E$30,$B$54,$B58,$K$1) -> 0 | J58: =_xll.DBRW($B$1,Input_Prod_01!$D$9,Input_Prod_01!J$11,$M$1,Input_Prod_01!$G$9,$J$9,$E$30,$B$54,$B58,$K$1) -> 0 | ... N58: =_xll.DBRW($B$1,Input_Prod_01!$D$9,Input_Prod_01!N$11,$M$1,Input_Prod_01!$G$9,$J$9,$E$30,$B$54,$B58,$K$1) -> 0
B59: Non-recurring Expenses | C59: =_xll.DBRW($B$1,Input_Prod_01!$D$9,Input_Prod_01!C$11,$M$1,Input_Prod_01!$G$9,$J$9,$E$30,$B$54,$B59,$K$1) -> 0 | D59: =_xll.DBRW($B$1,Input_Prod_01!$D$9,Input_Prod_01!D$11,$M$1,Input_Prod_01!$G$9,$J$9,$E$30,$B$54,$B59,$K$1) -> 0 | E59: =_xll.DBRW($B$1,Input_Prod_01!$D$9,Input_Prod_01!E$11,$M$1,Input_Prod_01!$G$9,$J$9,$E$30,$B$54,$B59,$K$1) -> 0 | F59: =_xll.DBRW($B$1,Input_Prod_01!$D$9,Input_Prod_01!F$11,$M$1,Input_Prod_01!$G$9,$J$9,$E$30,$B$54,$B59,$K$1) -> 0 | G59: =_xll.DBRW($B$1,Input_Prod_01!$D$9,Input_Prod_01!G$11,$M$1,Input_Prod_01!$G$9,$J$9,$E$30,$B$54,$B59,$K$1) -> 0 | H59: =_xll.DBRW($B$1,Input_Prod_01!$D$9,Input_Prod_01!H$11,$M$1,Input_Prod_01!$G$9,$J$9,$E$30,$B$54,$B59,$K$1) -> 0 | I59: =_xll.DBRW($B$1,Input_Prod_01!$D$9,Input_Prod_01!I$11,$M$1,Input_Prod_01!$G$9,$J$9,$E$30,$B$54,$B59,$K$1) -> 0 | J59: =_xll.DBRW($B$1,Input_Prod_01!$D$9,Input_Prod_01!J$11,$M$1,Input_Prod_01!$G$9,$J$9,$E$30,$B$54,$B59,$K$1) -> 0 | ... N59: =_xll.DBRW($B$1,Input_Prod_01!$D$9,Input_Prod_01!N$11,$M$1,Input_Prod_01!$G$9,$J$9,$E$30,$B$54,$B59,$K$1) -> 0
B60: Gain on assets | C60: =_xll.DBRW($B$1,Input_Prod_01!$D$9,Input_Prod_01!C$11,$M$1,Input_Prod_01!$G$9,$J$9,$E$30,$B$54,$B60,$K$1) -> 0 | D60: =_xll.DBRW($B$1,Input_Prod_01!$D$9,Input_Prod_01!D$11,$M$1,Input_Prod_01!$G$9,$J$9,$E$30,$B$54,$B60,$K$1) -> 0 | E60: =_xll.DBRW($B$1,Input_Prod_01!$D$9,Input_Prod_01!E$11,$M$1,Input_Prod_01!$G$9,$J$9,$E$30,$B$54,$B60,$K$1) -> 0 | F60: =_xll.DBRW($B$1,Input_Prod_01!$D$9,Input_Prod_01!F$11,$M$1,Input_Prod_01!$G$9,$J$9,$E$30,$B$54,$B60,$K$1) -> 0 | G60: =_xll.DBRW($B$1,Input_Prod_01!$D$9,Input_Prod_01!G$11,$M$1,Input_Prod_01!$G$9,$J$9,$E$30,$B$54,$B60,$K$1) -> 0 | H60: =_xll.DBRW($B$1,Input_Prod_01!$D$9,Input_Prod_01!H$11,$M$1,Input_Prod_01!$G$9,$J$9,$E$30,$B$54,$B60,$K$1) -> 0 | I60: =_xll.DBRW($B$1,Input_Prod_01!$D$9,Input_Prod_01!I$11,$M$1,Input_Prod_01!$G$9,$J$9,$E$30,$B$54,$B60,$K$1) -> 0 | J60: =_xll.DBRW($B$1,Input_Prod_01!$D$9,Input_Prod_01!J$11,$M$1,Input_Prod_01!$G$9,$J$9,$E$30,$B$54,$B60,$K$1) -> 0 | ... N60: =_xll.DBRW($B$1,Input_Prod_01!$D$9,Input_Prod_01!N$11,$M$1,Input_Prod_01!$G$9,$J$9,$E$30,$B$54,$B60,$K$1) -> 0
B61: Tax benefits | C61: =_xll.DBRW($B$1,Input_Prod_01!$D$9,Input_Prod_01!C$11,$M$1,Input_Prod_01!$G$9,$J$9,$E$30,$B$54,$B61,$K$1) -> 0 | D61: =_xll.DBRW($B$1,Input_Prod_01!$D$9,Input_Prod_01!D$11,$M$1,Input_Prod_01!$G$9,$J$9,$E$30,$B$54,$B61,$K$1) -> 0 | E61: =_xll.DBRW($B$1,Input_Prod_01!$D$9,Input_Prod_01!E$11,$M$1,Input_Prod_01!$G$9,$J$9,$E$30,$B$54,$B61,$K$1) -> 0 | F61: =_xll.DBRW($B$1,Input_Prod_01!$D$9,Input_Prod_01!F$11,$M$1,Input_Prod_01!$G$9,$J$9,$E$30,$B$54,$B61,$K$1) -> 0 | G61: =_xll.DBRW($B$1,Input_Prod_01!$D$9,Input_Prod_01!G$11,$M$1,Input_Prod_01!$G$9,$J$9,$E$30,$B$54,$B61,$K$1) -> 0 | H61: =_xll.DBRW($B$1,Input_Prod_01!$D$9,Input_Prod_01!H$11,$M$1,Input_Prod_01!$G$9,$J$9,$E$30,$B$54,$B61,$K$1) -> 0 | I61: =_xll.DBRW($B$1,Input_Prod_01!$D$9,Input_Prod_01!I$11,$M$1,Input_Prod_01!$G$9,$J$9,$E$30,$B$54,$B61,$K$1) -> 0 | J61: =_xll.DBRW($B$1,Input_Prod_01!$D$9,Input_Prod_01!J$11,$M$1,Input_Prod_01!$G$9,$J$9,$E$30,$B$54,$B61,$K$1) -> 0 | ... N61: =_xll.DBRW($B$1,Input_Prod_01!$D$9,Input_Prod_01!N$11,$M$1,Input_Prod_01!$G$9,$J$9,$E$30,$B$54,$B61,$K$1) -> 0
B62: Other Op. Results - Machadinho | C62: =_xll.DBRW($B$1,Input_Prod_01!$D$9,Input_Prod_01!C$11,$M$1,Input_Prod_01!$G$9,$J$9,$E$30,$B$54,$B62,$K$1) -> 0 | D62: =_xll.DBRW($B$1,Input_Prod_01!$D$9,Input_Prod_01!D$11,$M$1,Input_Prod_01!$G$9,$J$9,$E$30,$B$54,$B62,$K$1) -> 0 | E62: =_xll.DBRW($B$1,Input_Prod_01!$D$9,Input_Prod_01!E$11,$M$1,Input_Prod_01!$G$9,$J$9,$E$30,$B$54,$B62,$K$1) -> 0 | F62: =_xll.DBRW($B$1,Input_Prod_01!$D$9,Input_Prod_01!F$11,$M$1,Input_Prod_01!$G$9,$J$9,$E$30,$B$54,$B62,$K$1) -> 0 | G62: =_xll.DBRW($B$1,Input_Prod_01!$D$9,Input_Prod_01!G$11,$M$1,Input_Prod_01!$G$9,$J$9,$E$30,$B$54,$B62,$K$1) -> 0 | H62: =_xll.DBRW($B$1,Input_Prod_01!$D$9,Input_Prod_01!H$11,$M$1,Input_Prod_01!$G$9,$J$9,$E$30,$B$54,$B62,$K$1) -> 0 | I62: =_xll.DBRW($B$1,Input_Prod_01!$D$9,Input_Prod_01!I$11,$M$1,Input_Prod_01!$G$9,$J$9,$E$30,$B$54,$B62,$K$1) -> 0 | J62: =_xll.DBRW($B$1,Input_Prod_01!$D$9,Input_Prod_01!J$11,$M$1,Input_Prod_01!$G$9,$J$9,$E$30,$B$54,$B62,$K$1) -> 0 | ... N62: =_xll.DBRW($B$1,Input_Prod_01!$D$9,Input_Prod_01!N$11,$M$1,Input_Prod_01!$G$9,$J$9,$E$30,$B$54,$B62,$K$1) -> 0
B63: MOTZ | C63: =_xll.DBRW($B$1,Input_Prod_01!$D$9,Input_Prod_01!C$11,$M$1,Input_Prod_01!$G$9,$J$9,$E$30,$B$54,$B63,$K$1) -> 0 | D63: =_xll.DBRW($B$1,Input_Prod_01!$D$9,Input_Prod_01!D$11,$M$1,Input_Prod_01!$G$9,$J$9,$E$30,$B$54,$B63,$K$1) -> 0 | E63: =_xll.DBRW($B$1,Input_Prod_01!$D$9,Input_Prod_01!E$11,$M$1,Input_Prod_01!$G$9,$J$9,$E$30,$B$54,$B63,$K$1) -> 0 | F63: =_xll.DBRW($B$1,Input_Prod_01!$D$9,Input_Prod_01!F$11,$M$1,Input_Prod_01!$G$9,$J$9,$E$30,$B$54,$B63,$K$1) -> 0 | G63: =_xll.DBRW($B$1,Input_Prod_01!$D$9,Input_Prod_01!G$11,$M$1,Input_Prod_01!$G$9,$J$9,$E$30,$B$54,$B63,$K$1) -> 0 | H63: =_xll.DBRW($B$1,Input_Prod_01!$D$9,Input_Prod_01!H$11,$M$1,Input_Prod_01!$G$9,$J$9,$E$30,$B$54,$B63,$K$1) -> 0 | I63: =_xll.DBRW($B$1,Input_Prod_01!$D$9,Input_Prod_01!I$11,$M$1,Input_Prod_01!$G$9,$J$9,$E$30,$B$54,$B63,$K$1) -> 0 | J63: =_xll.DBRW($B$1,Input_Prod_01!$D$9,Input_Prod_01!J$11,$M$1,Input_Prod_01!$G$9,$J$9,$E$30,$B$54,$B63,$K$1) -> 0 | ... N63: =_xll.DBRW($B$1,Input_Prod_01!$D$9,Input_Prod_01!N$11,$M$1,Input_Prod_01!$G$9,$J$9,$E$30,$B$54,$B63,$K$1) -> 0
B64: Non Op. Taxes | C64: =_xll.DBRW($B$1,Input_Prod_01!$D$9,Input_Prod_01!C$11,$M$1,Input_Prod_01!$G$9,$J$9,$E$30,$B$54,$B64,$K$1) -> 0 | D64: =_xll.DBRW($B$1,Input_Prod_01!$D$9,Input_Prod_01!D$11,$M$1,Input_Prod_01!$G$9,$J$9,$E$30,$B$54,$B64,$K$1) -> 0 | E64: =_xll.DBRW($B$1,Input_Prod_01!$D$9,Input_Prod_01!E$11,$M$1,Input_Prod_01!$G$9,$J$9,$E$30,$B$54,$B64,$K$1) -> 0 | F64: =_xll.DBRW($B$1,Input_Prod_01!$D$9,Input_Prod_01!F$11,$M$1,Input_Prod_01!$G$9,$J$9,$E$30,$B$54,$B64,$K$1) -> 0 | G64: =_xll.DBRW($B$1,Input_Prod_01!$D$9,Input_Prod_01!G$11,$M$1,Input_Prod_01!$G$9,$J$9,$E$30,$B$54,$B64,$K$1) -> 0 | H64: =_xll.DBRW($B$1,Input_Prod_01!$D$9,Input_Prod_01!H$11,$M$1,Input_Prod_01!$G$9,$J$9,$E$30,$B$54,$B64,$K$1) -> 0 | I64: =_xll.DBRW($B$1,Input_Prod_01!$D$9,Input_Prod_01!I$11,$M$1,Input_Prod_01!$G$9,$J$9,$E$30,$B$54,$B64,$K$1) -> 0 | J64: =_xll.DBRW($B$1,Input_Prod_01!$D$9,Input_Prod_01!J$11,$M$1,Input_Prod_01!$G$9,$J$9,$E$30,$B$54,$B64,$K$1) -> 0 | ... N64: =_xll.DBRW($B$1,Input_Prod_01!$D$9,Input_Prod_01!N$11,$M$1,Input_Prod_01!$G$9,$J$9,$E$30,$B$54,$B64,$K$1) -> 0
B65: Other products | C65: =_xll.DBRW($B$1,Input_Prod_01!$D$9,Input_Prod_01!C$11,$M$1,Input_Prod_01!$G$9,$J$9,$E$30,$B$54,$B65,$K$1) -> 0 | D65: =_xll.DBRW($B$1,Input_Prod_01!$D$9,Input_Prod_01!D$11,$M$1,Input_Prod_01!$G$9,$J$9,$E$30,$B$54,$B65,$K$1) -> 0 | E65: =_xll.DBRW($B$1,Input_Prod_01!$D$9,Input_Prod_01!E$11,$M$1,Input_Prod_01!$G$9,$J$9,$E$30,$B$54,$B65,$K$1) -> 0 | F65: =_xll.DBRW($B$1,Input_Prod_01!$D$9,Input_Prod_01!F$11,$M$1,Input_Prod_01!$G$9,$J$9,$E$30,$B$54,$B65,$K$1) -> 0 | G65: =_xll.DBRW($B$1,Input_Prod_01!$D$9,Input_Prod_01!G$11,$M$1,Input_Prod_01!$G$9,$J$9,$E$30,$B$54,$B65,$K$1) -> 0 | H65: =_xll.DBRW($B$1,Input_Prod_01!$D$9,Input_Prod_01!H$11,$M$1,Input_Prod_01!$G$9,$J$9,$E$30,$B$54,$B65,$K$1) -> 0 | I65: =_xll.DBRW($B$1,Input_Prod_01!$D$9,Input_Prod_01!I$11,$M$1,Input_Prod_01!$G$9,$J$9,$E$30,$B$54,$B65,$K$1) -> 0 | J65: =_xll.DBRW($B$1,Input_Prod_01!$D$9,Input_Prod_01!J$11,$M$1,Input_Prod_01!$G$9,$J$9,$E$30,$B$54,$B65,$K$1) -> 0 | ... N65: =_xll.DBRW($B$1,Input_Prod_01!$D$9,Input_Prod_01!N$11,$M$1,Input_Prod_01!$G$9,$J$9,$E$30,$B$54,$B65,$K$1) -> 0
B66: Non-recurring Revenues | C66: =_xll.DBRW($B$1,Input_Prod_01!$D$9,Input_Prod_01!C$11,$M$1,Input_Prod_01!$G$9,$J$9,$E$30,$B$54,$B66,$K$1) -> 0 | D66: =_xll.DBRW($B$1,Input_Prod_01!$D$9,Input_Prod_01!D$11,$M$1,Input_Prod_01!$G$9,$J$9,$E$30,$B$54,$B66,$K$1) -> 0 | E66: =_xll.DBRW($B$1,Input_Prod_01!$D$9,Input_Prod_01!E$11,$M$1,Input_Prod_01!$G$9,$J$9,$E$30,$B$54,$B66,$K$1) -> 0 | F66: =_xll.DBRW($B$1,Input_Prod_01!$D$9,Input_Prod_01!F$11,$M$1,Input_Prod_01!$G$9,$J$9,$E$30,$B$54,$B66,$K$1) -> 0 | G66: =_xll.DBRW($B$1,Input_Prod_01!$D$9,Input_Prod_01!G$11,$M$1,Input_Prod_01!$G$9,$J$9,$E$30,$B$54,$B66,$K$1) -> 0 | H66: =_xll.DBRW($B$1,Input_Prod_01!$D$9,Input_Prod_01!H$11,$M$1,Input_Prod_01!$G$9,$J$9,$E$30,$B$54,$B66,$K$1) -> 0 | I66: =_xll.DBRW($B$1,Input_Prod_01!$D$9,Input_Prod_01!I$11,$M$1,Input_Prod_01!$G$9,$J$9,$E$30,$B$54,$B66,$K$1) -> 0 | J66: =_xll.DBRW($B$1,Input_Prod_01!$D$9,Input_Prod_01!J$11,$M$1,Input_Prod_01!$G$9,$J$9,$E$30,$B$54,$B66,$K$1) -> 0 | ... N66: =_xll.DBRW($B$1,Input_Prod_01!$D$9,Input_Prod_01!N$11,$M$1,Input_Prod_01!$G$9,$J$9,$E$30,$B$54,$B66,$K$1) -> 0
... B70: N/A | C70: =_xll.DBRW($B$1,Input_Prod_01!$D$9,Input_Prod_01!C$11,$M$1,Input_Prod_01!$G$9,$J$9,$E$30,$B$54,$B70,$K$1) -> 0 | D70: =_xll.DBRW($B$1,Input_Prod_01!$D$9,Input_Prod_01!D$11,$M$1,Input_Prod_01!$G$9,$J$9,$E$30,$B$54,$B70,$K$1) -> 0 | E70: =_xll.DBRW($B$1,Input_Prod_01!$D$9,Input_Prod_01!E$11,$M$1,Input_Prod_01!$G$9,$J$9,$E$30,$B$54,$B70,$K$1) -> 0 | F70: =_xll.DBRW($B$1,Input_Prod_01!$D$9,Input_Prod_01!F$11,$M$1,Input_Prod_01!$G$9,$J$9,$E$30,$B$54,$B70,$K$1) -> 0 | G70: =_xll.DBRW($B$1,Input_Prod_01!$D$9,Input_Prod_01!G$11,$M$1,Input_Prod_01!$G$9,$J$9,$E$30,$B$54,$B70,$K$1) -> 0 | H70: =_xll.DBRW($B$1,Input_Prod_01!$D$9,Input_Prod_01!H$11,$M$1,Input_Prod_01!$G$9,$J$9,$E$30,$B$54,$B70,$K$1) -> 0 | I70: =_xll.DBRW($B$1,Input_Prod_01!$D$9,Input_Prod_01!I$11,$M$1,Input_Prod_01!$G$9,$J$9,$E$30,$B$54,$B70,$K$1) -> 0 | J70: =_xll.DBRW($B$1,Input_Prod_01!$D$9,Input_Prod_01!J$11,$M$1,Input_Prod_01!$G$9,$J$9,$E$30,$B$54,$B70,$K$1) -> 0 | ... N70: =_xll.DBRW($B$1,Input_Prod_01!$D$9,Input_Prod_01!N$11,$M$1,Input_Prod_01!$G$9,$J$9,$E$30,$B$54,$B70,$K$1) -> 0
B71: EBITDA | C71: =_xll.DBRW($B$3,Input_Prod_01!$D$9,Input_Prod_01!C$11,$M$1,Input_Prod_01!$G$9,$J$9,$E$30,Input_Prod_01!$B71,$K$1) -> 22.243068 | D71: =_xll.DBRW($B$3,Input_Prod_01!$D$9,Input_Prod_01!D$11,$M$1,Input_Prod_01!$G$9,$J$9,$E$30,Input_Prod_01!$B71,$K$1) -> 19.722114 | E71: =_xll.DBRW($B$3,Input_Prod_01!$D$9,Input_Prod_01!E$11,$M$1,Input_Prod_01!$G$9,$J$9,$E$30,Input_Prod_01!$B71,$K$1) -> 38.91468 | F71: =_xll.DBRW($B$3,Input_Prod_01!$D$9,Input_Prod_01!F$11,$M$1,Input_Prod_01!$G$9,$J$9,$E$30,Input_Prod_01!$B71,$K$1) -> 56.971849 | G71: =_xll.DBRW($B$3,Input_Prod_01!$D$9,Input_Prod_01!G$11,$M$1,Input_Prod_01!$G$9,$J$9,$E$30,Input_Prod_01!$B71,$K$1) -> 72.521681 | H71: =_xll.DBRW($B$3,Input_Prod_01!$D$9,Input_Prod_01!H$11,$M$1,Input_Prod_01!$G$9,$J$9,$E$30,Input_Prod_01!$B71,$K$1) -> 82.205083 | I71: =_xll.DBRW($B$3,Input_Prod_01!$D$9,Input_Prod_01!I$11,$M$1,Input_Prod_01!$G$9,$J$9,$E$30,Input_Prod_01!$B71,$K$1) -> 79.523352 | J71: =_xll.DBRW($B$3,Input_Prod_01!$D$9,Input_Prod_01!J$11,$M$1,Input_Prod_01!$G$9,$J$9,$E$30,Input_Prod_01!$B71,$K$1) -> 75.437081 | ... N71: =_xll.DBRW($B$3,Input_Prod_01!$D$9,Input_Prod_01!N$11,$M$1,Input_Prod_01!$G$9,$J$9,$E$30,Input_Prod_01!$B71,$K$1) -> 40.67781
B74: Operating Profit
C76: =$D$9&"."&C$11 -> 2026.01 | D76: =$D$9&"."&D$11 -> 2026.02 | E76: =$D$9&"."&E$11 -> 2026.03 | F76: =$D$9&"."&F$11 -> 2026.04 | G76: =$D$9&"."&G$11 -> 2026.05 | H76: =$D$9&"."&H$11 -> 2026.06 | I76: =$D$9&"."&I$11 -> 2026.07 | J76: =$D$9&"."&J$11 -> 2026.08 | ... N76: =$D$9&"."&N$11 -> 2026.12
B77: Depreciation / amortization / depletion - Corporate | C77: =_xll.DBRW($B$1,Input_Prod_01!$D$9,Input_Prod_01!C$11,$M$1,Input_Prod_01!$G$9,$J$9,$E$30,Input_Prod_01!$B77,$L$1,$K$1) -> 0 | D77: =_xll.DBRW($B$1,Input_Prod_01!$D$9,Input_Prod_01!D$11,$M$1,Input_Prod_01!$G$9,$J$9,$E$30,Input_Prod_01!$B77,$L$1,$K$1) -> 0 | E77: =_xll.DBRW($B$1,Input_Prod_01!$D$9,Input_Prod_01!E$11,$M$1,Input_Prod_01!$G$9,$J$9,$E$30,Input_Prod_01!$B77,$L$1,$K$1) -> 0 | F77: =_xll.DBRW($B$1,Input_Prod_01!$D$9,Input_Prod_01!F$11,$M$1,Input_Prod_01!$G$9,$J$9,$E$30,Input_Prod_01!$B77,$L$1,$K$1) -> 0 | G77: =_xll.DBRW($B$1,Input_Prod_01!$D$9,Input_Prod_01!G$11,$M$1,Input_Prod_01!$G$9,$J$9,$E$30,Input_Prod_01!$B77,$L$1,$K$1) -> 0 | H77: =_xll.DBRW($B$1,Input_Prod_01!$D$9,Input_Prod_01!H$11,$M$1,Input_Prod_01!$G$9,$J$9,$E$30,Input_Prod_01!$B77,$L$1,$K$1) -> 0 | I77: =_xll.DBRW($B$1,Input_Prod_01!$D$9,Input_Prod_01!I$11,$M$1,Input_Prod_01!$G$9,$J$9,$E$30,Input_Prod_01!$B77,$L$1,$K$1) -> 0 | J77: =_xll.DBRW($B$1,Input_Prod_01!$D$9,Input_Prod_01!J$11,$M$1,Input_Prod_01!$G$9,$J$9,$E$30,Input_Prod_01!$B77,$L$1,$K$1) -> 0 | ... N77: =_xll.DBRW($B$1,Input_Prod_01!$D$9,Input_Prod_01!N$11,$M$1,Input_Prod_01!$G$9,$J$9,$E$30,Input_Prod_01!$B77,$L$1,$K$1) -> 0
B78: EBITDA | C78: =_xll.DBRW($B$3,Input_Prod_01!$D$9,Input_Prod_01!C$11,$M$1,Input_Prod_01!$G$9,$J$9,$E$30,Input_Prod_01!$B78,$K$1) -> 22.243068 | D78: =_xll.DBRW($B$3,Input_Prod_01!$D$9,Input_Prod_01!D$11,$M$1,Input_Prod_01!$G$9,$J$9,$E$30,Input_Prod_01!$B78,$K$1) -> 19.722114 | E78: =_xll.DBRW($B$3,Input_Prod_01!$D$9,Input_Prod_01!E$11,$M$1,Input_Prod_01!$G$9,$J$9,$E$30,Input_Prod_01!$B78,$K$1) -> 38.91468 | F78: =_xll.DBRW($B$3,Input_Prod_01!$D$9,Input_Prod_01!F$11,$M$1,Input_Prod_01!$G$9,$J$9,$E$30,Input_Prod_01!$B78,$K$1) -> 56.971849 | G78: =_xll.DBRW($B$3,Input_Prod_01!$D$9,Input_Prod_01!G$11,$M$1,Input_Prod_01!$G$9,$J$9,$E$30,Input_Prod_01!$B78,$K$1) -> 72.521681 | H78: =_xll.DBRW($B$3,Input_Prod_01!$D$9,Input_Prod_01!H$11,$M$1,Input_Prod_01!$G$9,$J$9,$E$30,Input_Prod_01!$B78,$K$1) -> 82.205083 | I78: =_xll.DBRW($B$3,Input_Prod_01!$D$9,Input_Prod_01!I$11,$M$1,Input_Prod_01!$G$9,$J$9,$E$30,Input_Prod_01!$B78,$K$1) -> 79.523352 | J78: =_xll.DBRW($B$3,Input_Prod_01!$D$9,Input_Prod_01!J$11,$M$1,Input_Prod_01!$G$9,$J$9,$E$30,Input_Prod_01!$B78,$K$1) -> 75.437081 | ... N78: =_xll.DBRW($B$3,Input_Prod_01!$D$9,Input_Prod_01!N$11,$M$1,Input_Prod_01!$G$9,$J$9,$E$30,Input_Prod_01!$B78,$K$1) -> 40.67781
B79: Operating Profit | C79: =_xll.DBRW($B$3,Input_Prod_01!$D$9,Input_Prod_01!C$11,$M$1,Input_Prod_01!$G$9,Input_Prod_01!$J$9,$E$30,Input_Prod_01!$B79,$K$1) -> 22.243068 | D79: =_xll.DBRW($B$3,Input_Prod_01!$D$9,Input_Prod_01!D$11,$M$1,Input_Prod_01!$G$9,Input_Prod_01!$J$9,$E$30,Input_Prod_01!$B79,$K$1) -> 19.722114 | E79: =_xll.DBRW($B$3,Input_Prod_01!$D$9,Input_Prod_01!E$11,$M$1,Input_Prod_01!$G$9,Input_Prod_01!$J$9,$E$30,Input_Prod_01!$B79,$K$1) -> 38.91468 | F79: =_xll.DBRW($B$3,Input_Prod_01!$D$9,Input_Prod_01!F$11,$M$1,Input_Prod_01!$G$9,Input_Prod_01!$J$9,$E$30,Input_Prod_01!$B79,$K$1) -> 56.971849 | G79: =_xll.DBRW($B$3,Input_Prod_01!$D$9,Input_Prod_01!G$11,$M$1,Input_Prod_01!$G$9,Input_Prod_01!$J$9,$E$30,Input_Prod_01!$B79,$K$1) -> 72.521681 | H79: =_xll.DBRW($B$3,Input_Prod_01!$D$9,Input_Prod_01!H$11,$M$1,Input_Prod_01!$G$9,Input_Prod_01!$J$9,$E$30,Input_Prod_01!$B79,$K$1) -> 82.205083 | I79: =_xll.DBRW($B$3,Input_Prod_01!$D$9,Input_Prod_01!I$11,$M$1,Input_Prod_01!$G$9,Input_Prod_01!$J$9,$E$30,Input_Prod_01!$B79,$K$1) -> 79.523352 | J79: =_xll.DBRW($B$3,Input_Prod_01!$D$9,Input_Prod_01!J$11,$M$1,Input_Prod_01!$G$9,Input_Prod_01!$J$9,$E$30,Input_Prod_01!$B79,$K$1) -> 75.437081 | ... N79: =_xll.DBRW($B$3,Input_Prod_01!$D$9,Input_Prod_01!N$11,$M$1,Input_Prod_01!$G$9,Input_Prod_01!$J$9,$E$30,Input_Prod_01!$B79,$K$1) -> 40.67781

Sheet Input_Prod_02
B1: =_xll.VIEW("CONS_VC:STG.100.DataBase_Uploads",D9) -> CONS_VC:STG.100.DataBase_Uploads:-752698549379028367 | C1: =_xll.VIEW("CONS_VC:ALL.015.Region_Assumptions") -> CONS_VC:ALL.015.Region_Assumptions:-752698549-4785970 | D1: =_xll.VIEW("CONS_VC:DFS.120.Financial_Results") -> CONS_VC:DFS.120.Financial_Results:-752698549890993963 | K1: Value | L1: N/A | M1: =_xll.SUBNM("CONS_VC:ALL.D.Version","","T4") -> T4 | N1: PROD099
B2: =_xll.VIEW("CONS_VC:REV.100.Revenue_Consolidated") -> CONS_VC:REV.100.Revenue_Consolidated:-752698549-1043644815 | C2: =_xll.VIEW("CONS_VC:ALL.010.Economic_Assumptions") -> CONS_VC:ALL.010.Economic_Assumptions:-752698549-1652293987 | D2: =_xll.VIEW("CONS_VC:DFS.140.Indirect_Cash_Flow") -> CONS_VC:DFS.140.Indirect_Cash_Flow:-752698549-767194537 | K2: Total Market | N2: Total Products
B3: =_xll.VIEW("CONS_VC:DFS.100.Profit_and_Loss") -> CONS_VC:DFS.100.Profit_and_Loss:-7526985491143614695 | C3: =_xll.VIEW("CONS_VC:DFS.160.Working_Capital") -> CONS_VC:DFS.160.Working_Capital:-752698549-1628048918 | D3: =_xll.VIEW("CONS_VC:ALL.004.Uploads_Status_Planning") -> CONS_VC:ALL.004.Uploads_Status_Planning:-752698549-1635088025 | G3: Flag
B4: =_xll.VIEW("CONS_VC:ALL.001.Actual_Control") -> CONS_VC:ALL.001.Actual_Control:-752698549-938340181 | C4: =_xll.VIEW("CONS_VC:DFS.180.Gross_Debt") -> CONS_VC:DFS.180.Gross_Debt:-7526985491862422329
C5: =_xll.DBRW(Input_Prod_02!$B$4,Input_Prod_02!$D$9,Input_Prod_02!C11,$M$1,$G$3) -> PLAN | D5: =_xll.DBRW(Input_Prod_02!$B$4,Input_Prod_02!$D$9,Input_Prod_02!D11,$M$1,$G$3) -> PLAN | E5: =_xll.DBRW(Input_Prod_02!$B$4,Input_Prod_02!$D$9,Input_Prod_02!E11,$M$1,$G$3) -> PLAN | F5: =_xll.DBRW(Input_Prod_02!$B$4,Input_Prod_02!$D$9,Input_Prod_02!F11,$M$1,$G$3) -> PLAN | G5: =_xll.DBRW(Input_Prod_02!$B$4,Input_Prod_02!$D$9,Input_Prod_02!G11,$M$1,$G$3) -> PLAN | H5: =_xll.DBRW(Input_Prod_02!$B$4,Input_Prod_02!$D$9,Input_Prod_02!H11,$M$1,$G$3) -> PLAN | I5: =_xll.DBRW(Input_Prod_02!$B$4,Input_Prod_02!$D$9,Input_Prod_02!I11,$M$1,$G$3) -> PLAN | J5: =_xll.DBRW(Input_Prod_02!$B$4,Input_Prod_02!$D$9,Input_Prod_02!J11,$M$1,$G$3) -> PLAN | ... N5: =_xll.DBRW(Input_Prod_02!$B$4,Input_Prod_02!$D$9,Input_Prod_02!N11,$M$1,$G$3) -> PLAN
L7: System Input Status: | N7: =_xll.DBRW($D$3,$M$1,$J$9,"Status") -> Closed
B8: GLOBAL ASSUMPTIONS
C9: Year: | D9: =_xll.SUBNM("CONS_VC:ALL.D.Year","SYS_Picklist","2026","MEMBER_NAME") -> 2026 | F9: Currency: | G9: =_xll.SUBNM("CONS_VC:ALL.D.Currency","PAX","USD","Nome alternativo") -> USD | I9: Region: | J9: =_xll.SUBNM("CONS_VC:ALL.D.Region","Nível 0","VCNA","MEMBER_NAME") -> VCNA
C11: 01 | D11: 02 | E11: 03 | F11: 04 | G11: 05 | H11: 06 | I11: 07 | J11: 08 | K11: 09 | L11: 10 | M11: 11 | N11: 12
C12: =$D$9&"."&C11 -> 2026.01 | D12: =$D$9&"."&D11 -> 2026.02 | E12: =$D$9&"."&E11 -> 2026.03 | F12: =$D$9&"."&F11 -> 2026.04 | G12: =$D$9&"."&G11 -> 2026.05 | H12: =$D$9&"."&H11 -> 2026.06 | I12: =$D$9&"."&I11 -> 2026.07 | J12: =$D$9&"."&J11 -> 2026.08 | ... N12: =$D$9&"."&N11 -> 2026.12
B13: Begining FX Rate R$/US$ | C13: =_xll.DBRW($C$2,Input_Prod_02!$D$9,Input_Prod_02!$C$11,$M$1,$B13,$K$1) -> 0 | D13: =_xll.DBRW($C$2,Input_Prod_02!$D$9,Input_Prod_02!$C$11,$M$1,$B13,$K$1) -> 0 | E13: =_xll.DBRW($C$2,Input_Prod_02!$D$9,Input_Prod_02!$C$11,$M$1,$B13,$K$1) -> 0 | F13: =_xll.DBRW($C$2,Input_Prod_02!$D$9,Input_Prod_02!$C$11,$M$1,$B13,$K$1) -> 0 | G13: =_xll.DBRW($C$2,Input_Prod_02!$D$9,Input_Prod_02!$C$11,$M$1,$B13,$K$1) -> 0 | H13: =_xll.DBRW($C$2,Input_Prod_02!$D$9,Input_Prod_02!$C$11,$M$1,$B13,$K$1) -> 0 | I13: =_xll.DBRW($C$2,Input_Prod_02!$D$9,Input_Prod_02!$C$11,$M$1,$B13,$K$1) -> 0 | J13: =_xll.DBRW($C$2,Input_Prod_02!$D$9,Input_Prod_02!$C$11,$M$1,$B13,$K$1) -> 0 | ... N13: =_xll.DBRW($C$2,Input_Prod_02!$D$9,Input_Prod_02!$C$11,$M$1,$B13,$K$1) -> 0
B14: Average FX Rate R$/US$ | C14: =_xll.DBRW($C$2,Input_Prod_02!$D$9,Input_Prod_02!$C$11,$M$1,$B14,$K$1) -> 0 | D14: =_xll.DBRW($C$2,Input_Prod_02!$D$9,Input_Prod_02!$C$11,$M$1,$B14,$K$1) -> 0 | E14: =_xll.DBRW($C$2,Input_Prod_02!$D$9,Input_Prod_02!$C$11,$M$1,$B14,$K$1) -> 0 | F14: =_xll.DBRW($C$2,Input_Prod_02!$D$9,Input_Prod_02!$C$11,$M$1,$B14,$K$1) -> 0 | G14: =_xll.DBRW($C$2,Input_Prod_02!$D$9,Input_Prod_02!$C$11,$M$1,$B14,$K$1) -> 0 | H14: =_xll.DBRW($C$2,Input_Prod_02!$D$9,Input_Prod_02!$C$11,$M$1,$B14,$K$1) -> 0 | I14: =_xll.DBRW($C$2,Input_Prod_02!$D$9,Input_Prod_02!$C$11,$M$1,$B14,$K$1) -> 0 | J14: =_xll.DBRW($C$2,Input_Prod_02!$D$9,Input_Prod_02!$C$11,$M$1,$B14,$K$1) -> 0 | ... N14: =_xll.DBRW($C$2,Input_Prod_02!$D$9,Input_Prod_02!$C$11,$M$1,$B14,$K$1) -> 0
B15: Final FX Rate R$/US$ | C15: =_xll.DBRW($C$2,Input_Prod_02!$D$9,Input_Prod_02!$C$11,$M$1,$B15,$K$1) -> 0 | D15: =_xll.DBRW($C$2,Input_Prod_02!$D$9,Input_Prod_02!$C$11,$M$1,$B15,$K$1) -> 0 | E15: =_xll.DBRW($C$2,Input_Prod_02!$D$9,Input_Prod_02!$C$11,$M$1,$B15,$K$1) -> 0 | F15: =_xll.DBRW($C$2,Input_Prod_02!$D$9,Input_Prod_02!$C$11,$M$1,$B15,$K$1) -> 0 | G15: =_xll.DBRW($C$2,Input_Prod_02!$D$9,Input_Prod_02!$C$11,$M$1,$B15,$K$1) -> 0 | H15: =_xll.DBRW($C$2,Input_Prod_02!$D$9,Input_Prod_02!$C$11,$M$1,$B15,$K$1) -> 0 | I15: =_xll.DBRW($C$2,Input_Prod_02!$D$9,Input_Prod_02!$C$11,$M$1,$B15,$K$1) -> 0 | J15: =_xll.DBRW($C$2,Input_Prod_02!$D$9,Input_Prod_02!$C$11,$M$1,$B15,$K$1) -> 0 | ... N15: =_xll.DBRW($C$2,Input_Prod_02!$D$9,Input_Prod_02!$C$11,$M$1,$B15,$K$1) -> 0
B16: Begining FX Rate US$/EUR | C16: =_xll.DBRW($C$2,Input_Prod_02!$D$9,Input_Prod_02!$C$11,$M$1,$B16,$K$1) -> 0 | D16: =_xll.DBRW($C$2,Input_Prod_02!$D$9,Input_Prod_02!$C$11,$M$1,$B16,$K$1) -> 0 | E16: =_xll.DBRW($C$2,Input_Prod_02!$D$9,Input_Prod_02!$C$11,$M$1,$B16,$K$1) -> 0 | F16: =_xll.DBRW($C$2,Input_Prod_02!$D$9,Input_Prod_02!$C$11,$M$1,$B16,$K$1) -> 0 | G16: =_xll.DBRW($C$2,Input_Prod_02!$D$9,Input_Prod_02!$C$11,$M$1,$B16,$K$1) -> 0 | H16: =_xll.DBRW($C$2,Input_Prod_02!$D$9,Input_Prod_02!$C$11,$M$1,$B16,$K$1) -> 0 | I16: =_xll.DBRW($C$2,Input_Prod_02!$D$9,Input_Prod_02!$C$11,$M$1,$B16,$K$1) -> 0 | J16: =_xll.DBRW($C$2,Input_Prod_02!$D$9,Input_Prod_02!$C$11,$M$1,$B16,$K$1) -> 0 | ... N16: =_xll.DBRW($C$2,Input_Prod_02!$D$9,Input_Prod_02!$C$11,$M$1,$B16,$K$1) -> 0
B17: Average FX Rate US$/EUR | C17: =_xll.DBRW($C$2,Input_Prod_02!$D$9,Input_Prod_02!$C$11,$M$1,$B17,$K$1) -> 5 | D17: =_xll.DBRW($C$2,Input_Prod_02!$D$9,Input_Prod_02!$C$11,$M$1,$B17,$K$1) -> 5 | E17: =_xll.DBRW($C$2,Input_Prod_02!$D$9,Input_Prod_02!$C$11,$M$1,$B17,$K$1) -> 5 | F17: =_xll.DBRW($C$2,Input_Prod_02!$D$9,Input_Prod_02!$C$11,$M$1,$B17,$K$1) -> 5 | G17: =_xll.DBRW($C$2,Input_Prod_02!$D$9,Input_Prod_02!$C$11,$M$1,$B17,$K$1) -> 5 | H17: =_xll.DBRW($C$2,Input_Prod_02!$D$9,Input_Prod_02!$C$11,$M$1,$B17,$K$1) -> 5 | I17: =_xll.DBRW($C$2,Input_Prod_02!$D$9,Input_Prod_02!$C$11,$M$1,$B17,$K$1) -> 5 | J17: =_xll.DBRW($C$2,Input_Prod_02!$D$9,Input_Prod_02!$C$11,$M$1,$B17,$K$1) -> 5 | ... N17: =_xll.DBRW($C$2,Input_Prod_02!$D$9,Input_Prod_02!$C$11,$M$1,$B17,$K$1) -> 5
B18: Final FX Rate US$/EUR | C18: =_xll.DBRW($C$2,Input_Prod_02!$D$9,Input_Prod_02!$C$11,$M$1,$B18,$K$1) -> 0 | D18: =_xll.DBRW($C$2,Input_Prod_02!$D$9,Input_Prod_02!$C$11,$M$1,$B18,$K$1) -> 0 | E18: =_xll.DBRW($C$2,Input_Prod_02!$D$9,Input_Prod_02!$C$11,$M$1,$B18,$K$1) -> 0 | F18: =_xll.DBRW($C$2,Input_Prod_02!$D$9,Input_Prod_02!$C$11,$M$1,$B18,$K$1) -> 0 | G18: =_xll.DBRW($C$2,Input_Prod_02!$D$9,Input_Prod_02!$C$11,$M$1,$B18,$K$1) -> 0 | H18: =_xll.DBRW($C$2,Input_Prod_02!$D$9,Input_Prod_02!$C$11,$M$1,$B18,$K$1) -> 0 | I18: =_xll.DBRW($C$2,Input_Prod_02!$D$9,Input_Prod_02!$C$11,$M$1,$B18,$K$1) -> 0 | J18: =_xll.DBRW($C$2,Input_Prod_02!$D$9,Input_Prod_02!$C$11,$M$1,$B18,$K$1) -> 0 | ... N18: =_xll.DBRW($C$2,Input_Prod_02!$D$9,Input_Prod_02!$C$11,$M$1,$B18,$K$1) -> 0
B19: Câmbio Inicial UYU$/US$ | C19: =_xll.DBRW($C$2,Input_Prod_02!$D$9,Input_Prod_02!$C$11,$M$1,$B19,$K$1) -> 0 | D19: =_xll.DBRW($C$2,Input_Prod_02!$D$9,Input_Prod_02!$C$11,$M$1,$B19,$K$1) -> 0 | E19: =_xll.DBRW($C$2,Input_Prod_02!$D$9,Input_Prod_02!$C$11,$M$1,$B19,$K$1) -> 0 | F19: =_xll.DBRW($C$2,Input_Prod_02!$D$9,Input_Prod_02!$C$11,$M$1,$B19,$K$1) -> 0 | G19: =_xll.DBRW($C$2,Input_Prod_02!$D$9,Input_Prod_02!$C$11,$M$1,$B19,$K$1) -> 0 | H19: =_xll.DBRW($C$2,Input_Prod_02!$D$9,Input_Prod_02!$C$11,$M$1,$B19,$K$1) -> 0 | I19: =_xll.DBRW($C$2,Input_Prod_02!$D$9,Input_Prod_02!$C$11,$M$1,$B19,$K$1) -> 0 | J19: =_xll.DBRW($C$2,Input_Prod_02!$D$9,Input_Prod_02!$C$11,$M$1,$B19,$K$1) -> 0 | ... N19: =_xll.DBRW($C$2,Input_Prod_02!$D$9,Input_Prod_02!$C$11,$M$1,$B19,$K$1) -> 0
B20: Câmbio Médio UYU$/US$ | C20: =_xll.DBRW($C$2,Input_Prod_02!$D$9,Input_Prod_02!$C$11,$M$1,$B20,$K$1) -> 0 | D20: =_xll.DBRW($C$2,Input_Prod_02!$D$9,Input_Prod_02!$C$11,$M$1,$B20,$K$1) -> 0 | E20: =_xll.DBRW($C$2,Input_Prod_02!$D$9,Input_Prod_02!$C$11,$M$1,$B20,$K$1) -> 0 | F20: =_xll.DBRW($C$2,Input_Prod_02!$D$9,Input_Prod_02!$C$11,$M$1,$B20,$K$1) -> 0 | G20: =_xll.DBRW($C$2,Input_Prod_02!$D$9,Input_Prod_02!$C$11,$M$1,$B20,$K$1) -> 0 | H20: =_xll.DBRW($C$2,Input_Prod_02!$D$9,Input_Prod_02!$C$11,$M$1,$B20,$K$1) -> 0 | I20: =_xll.DBRW($C$2,Input_Prod_02!$D$9,Input_Prod_02!$C$11,$M$1,$B20,$K$1) -> 0 | J20: =_xll.DBRW($C$2,Input_Prod_02!$D$9,Input_Prod_02!$C$11,$M$1,$B20,$K$1) -> 0 | ... N20: =_xll.DBRW($C$2,Input_Prod_02!$D$9,Input_Prod_02!$C$11,$M$1,$B20,$K$1) -> 0
B21: Câmbio Final UYU$/US$ | C21: =_xll.DBRW($C$2,Input_Prod_02!$D$9,Input_Prod_02!$C$11,$M$1,$B21,$K$1) -> 0 | D21: =_xll.DBRW($C$2,Input_Prod_02!$D$9,Input_Prod_02!$C$11,$M$1,$B21,$K$1) -> 0 | E21: =_xll.DBRW($C$2,Input_Prod_02!$D$9,Input_Prod_02!$C$11,$M$1,$B21,$K$1) -> 0 | F21: =_xll.DBRW($C$2,Input_Prod_02!$D$9,Input_Prod_02!$C$11,$M$1,$B21,$K$1) -> 0 | G21: =_xll.DBRW($C$2,Input_Prod_02!$D$9,Input_Prod_02!$C$11,$M$1,$B21,$K$1) -> 0 | H21: =_xll.DBRW($C$2,Input_Prod_02!$D$9,Input_Prod_02!$C$11,$M$1,$B21,$K$1) -> 0 | I21: =_xll.DBRW($C$2,Input_Prod_02!$D$9,Input_Prod_02!$C$11,$M$1,$B21,$K$1) -> 0 | J21: =_xll.DBRW($C$2,Input_Prod_02!$D$9,Input_Prod_02!$C$11,$M$1,$B21,$K$1) -> 0 | ... N21: =_xll.DBRW($C$2,Input_Prod_02!$D$9,Input_Prod_02!$C$11,$M$1,$B21,$K$1) -> 0
B22: Câmbio Inicial ARS$/US$ | C22: =_xll.DBRW($C$2,Input_Prod_02!$D$9,Input_Prod_02!$C$11,$M$1,$B22,$K$1) -> 0 | D22: =_xll.DBRW($C$2,Input_Prod_02!$D$9,Input_Prod_02!$C$11,$M$1,$B22,$K$1) -> 0 | E22: =_xll.DBRW($C$2,Input_Prod_02!$D$9,Input_Prod_02!$C$11,$M$1,$B22,$K$1) -> 0 | F22: =_xll.DBRW($C$2,Input_Prod_02!$D$9,Input_Prod_02!$C$11,$M$1,$B22,$K$1) -> 0 | G22: =_xll.DBRW($C$2,Input_Prod_02!$D$9,Input_Prod_02!$C$11,$M$1,$B22,$K$1) -> 0 | H22: =_xll.DBRW($C$2,Input_Prod_02!$D$9,Input_Prod_02!$C$11,$M$1,$B22,$K$1) -> 0 | I22: =_xll.DBRW($C$2,Input_Prod_02!$D$9,Input_Prod_02!$C$11,$M$1,$B22,$K$1) -> 0 | J22: =_xll.DBRW($C$2,Input_Prod_02!$D$9,Input_Prod_02!$C$11,$M$1,$B22,$K$1) -> 0 | ... N22: =_xll.DBRW($C$2,Input_Prod_02!$D$9,Input_Prod_02!$C$11,$M$1,$B22,$K$1) -> 0
B23: Câmbio Médio ARS$/US$ | C23: =_xll.DBRW($C$2,Input_Prod_02!$D$9,Input_Prod_02!$C$11,$M$1,$B23,$K$1) -> 0 | D23: =_xll.DBRW($C$2,Input_Prod_02!$D$9,Input_Prod_02!$C$11,$M$1,$B23,$K$1) -> 0 | E23: =_xll.DBRW($C$2,Input_Prod_02!$D$9,Input_Prod_02!$C$11,$M$1,$B23,$K$1) -> 0 | F23: =_xll.DBRW($C$2,Input_Prod_02!$D$9,Input_Prod_02!$C$11,$M$1,$B23,$K$1) -> 0 | G23: =_xll.DBRW($C$2,Input_Prod_02!$D$9,Input_Prod_02!$C$11,$M$1,$B23,$K$1) -> 0 | H23: =_xll.DBRW($C$2,Input_Prod_02!$D$9,Input_Prod_02!$C$11,$M$1,$B23,$K$1) -> 0 | I23: =_xll.DBRW($C$2,Input_Prod_02!$D$9,Input_Prod_02!$C$11,$M$1,$B23,$K$1) -> 0 | J23: =_xll.DBRW($C$2,Input_Prod_02!$D$9,Input_Prod_02!$C$11,$M$1,$B23,$K$1) -> 0 | ... N23: =_xll.DBRW($C$2,Input_Prod_02!$D$9,Input_Prod_02!$C$11,$M$1,$B23,$K$1) -> 0
B24: Câmbio Final ARS$/US$ | C24: =_xll.DBRW($C$2,Input_Prod_02!$D$9,Input_Prod_02!$C$11,$M$1,$B24,$K$1) -> 0 | D24: =_xll.DBRW($C$2,Input_Prod_02!$D$9,Input_Prod_02!$C$11,$M$1,$B24,$K$1) -> 0 | E24: =_xll.DBRW($C$2,Input_Prod_02!$D$9,Input_Prod_02!$C$11,$M$1,$B24,$K$1) -> 0 | F24: =_xll.DBRW($C$2,Input_Prod_02!$D$9,Input_Prod_02!$C$11,$M$1,$B24,$K$1) -> 0 | G24: =_xll.DBRW($C$2,Input_Prod_02!$D$9,Input_Prod_02!$C$11,$M$1,$B24,$K$1) -> 0 | H24: =_xll.DBRW($C$2,Input_Prod_02!$D$9,Input_Prod_02!$C$11,$M$1,$B24,$K$1) -> 0 | I24: =_xll.DBRW($C$2,Input_Prod_02!$D$9,Input_Prod_02!$C$11,$M$1,$B24,$K$1) -> 0 | J24: =_xll.DBRW($C$2,Input_Prod_02!$D$9,Input_Prod_02!$C$11,$M$1,$B24,$K$1) -> 0 | ... N24: =_xll.DBRW($C$2,Input_Prod_02!$D$9,Input_Prod_02!$C$11,$M$1,$B24,$K$1) -> 0
... B27: Number of Days | C27: =_xll.DBRW($C$2,Input_Prod_02!$D$9,Input_Prod_02!$C$11,$M$1,$B27,$K$1) -> 31 | D27: =_xll.DBRW($C$2,Input_Prod_02!$D$9,Input_Prod_02!$C$11,$M$1,$B27,$K$1) -> 31 | E27: =_xll.DBRW($C$2,Input_Prod_02!$D$9,Input_Prod_02!$C$11,$M$1,$B27,$K$1) -> 31 | F27: =_xll.DBRW($C$2,Input_Prod_02!$D$9,Input_Prod_02!$C$11,$M$1,$B27,$K$1) -> 31 | G27: =_xll.DBRW($C$2,Input_Prod_02!$D$9,Input_Prod_02!$C$11,$M$1,$B27,$K$1) -> 31 | H27: =_xll.DBRW($C$2,Input_Prod_02!$D$9,Input_Prod_02!$C$11,$M$1,$B27,$K$1) -> 31 | I27: =_xll.DBRW($C$2,Input_Prod_02!$D$9,Input_Prod_02!$C$11,$M$1,$B27,$K$1) -> 31 | J27: =_xll.DBRW($C$2,Input_Prod_02!$D$9,Input_Prod_02!$C$11,$M$1,$B27,$K$1) -> 31 | ... N27: =_xll.DBRW($C$2,Input_Prod_02!$D$9,Input_Prod_02!$C$11,$M$1,$B27,$K$1) -> 31
B30: NET REVENUES | D30: Products: | E30: =_xll.SUBNM("CONS_VC:ALL.D.Products","Nivel_0","PRODRM010 - Ready Mix","Código e Descrição") -> PRODRM010 - Ready Mix
C33: =$D$9&"."&C11 -> 2026.01 | D33: =$D$9&"."&D11 -> 2026.02 | E33: =$D$9&"."&E11 -> 2026.03 | F33: =$D$9&"."&F11 -> 2026.04 | G33: =$D$9&"."&G11 -> 2026.05 | H33: =$D$9&"."&H11 -> 2026.06 | I33: =$D$9&"."&I11 -> 2026.07 | J33: =$D$9&"."&J11 -> 2026.08 | ... N33: =$D$9&"."&N11 -> 2026.12
B34: Reference Price [$/ton] | C34: =_xll.DBRW($B$1,Input_Prod_02!$D$9,Input_Prod_02!C$11,$M$1,Input_Prod_02!$G$9,$J$9,Input_Prod_02!$E$30,Input_Prod_02!$B34,$L$1,$K$1) -> 0 | D34: =_xll.DBRW($B$1,Input_Prod_02!$D$9,Input_Prod_02!D$11,$M$1,Input_Prod_02!$G$9,$J$9,Input_Prod_02!$E$30,Input_Prod_02!$B34,$L$1,$K$1) -> 0 | E34: =_xll.DBRW($B$1,Input_Prod_02!$D$9,Input_Prod_02!E$11,$M$1,Input_Prod_02!$G$9,$J$9,Input_Prod_02!$E$30,Input_Prod_02!$B34,$L$1,$K$1) -> 0 | F34: =_xll.DBRW($B$1,Input_Prod_02!$D$9,Input_Prod_02!F$11,$M$1,Input_Prod_02!$G$9,$J$9,Input_Prod_02!$E$30,Input_Prod_02!$B34,$L$1,$K$1) -> 0 | G34: =_xll.DBRW($B$1,Input_Prod_02!$D$9,Input_Prod_02!G$11,$M$1,Input_Prod_02!$G$9,$J$9,Input_Prod_02!$E$30,Input_Prod_02!$B34,$L$1,$K$1) -> 0 | H34: =_xll.DBRW($B$1,Input_Prod_02!$D$9,Input_Prod_02!H$11,$M$1,Input_Prod_02!$G$9,$J$9,Input_Prod_02!$E$30,Input_Prod_02!$B34,$L$1,$K$1) -> 0 | I34: =_xll.DBRW($B$1,Input_Prod_02!$D$9,Input_Prod_02!I$11,$M$1,Input_Prod_02!$G$9,$J$9,Input_Prod_02!$E$30,Input_Prod_02!$B34,$L$1,$K$1) -> 0 | J34: =_xll.DBRW($B$1,Input_Prod_02!$D$9,Input_Prod_02!J$11,$M$1,Input_Prod_02!$G$9,$J$9,Input_Prod_02!$E$30,Input_Prod_02!$B34,$L$1,$K$1) -> 0 | ... N34: =_xll.DBRW($B$1,Input_Prod_02!$D$9,Input_Prod_02!N$11,$M$1,Input_Prod_02!$G$9,$J$9,Input_Prod_02!$E$30,Input_Prod_02!$B34,$L$1,$K$1) -> 0
B35: Local Market Sales Volume [kt] | C35: =_xll.DBRW($B$1,Input_Prod_02!$D$9,Input_Prod_02!C$11,$M$1,Input_Prod_02!$G$9,$J$9,Input_Prod_02!$E$30,Input_Prod_02!$B35,$L$1,$K$1) -> 0 | D35: =_xll.DBRW($B$1,Input_Prod_02!$D$9,Input_Prod_02!D$11,$M$1,Input_Prod_02!$G$9,$J$9,Input_Prod_02!$E$30,Input_Prod_02!$B35,$L$1,$K$1) -> 0 | E35: =_xll.DBRW($B$1,Input_Prod_02!$D$9,Input_Prod_02!E$11,$M$1,Input_Prod_02!$G$9,$J$9,Input_Prod_02!$E$30,Input_Prod_02!$B35,$L$1,$K$1) -> 0 | F35: =_xll.DBRW($B$1,Input_Prod_02!$D$9,Input_Prod_02!F$11,$M$1,Input_Prod_02!$G$9,$J$9,Input_Prod_02!$E$30,Input_Prod_02!$B35,$L$1,$K$1) -> 0 | G35: =_xll.DBRW($B$1,Input_Prod_02!$D$9,Input_Prod_02!G$11,$M$1,Input_Prod_02!$G$9,$J$9,Input_Prod_02!$E$30,Input_Prod_02!$B35,$L$1,$K$1) -> 0 | H35: =_xll.DBRW($B$1,Input_Prod_02!$D$9,Input_Prod_02!H$11,$M$1,Input_Prod_02!$G$9,$J$9,Input_Prod_02!$E$30,Input_Prod_02!$B35,$L$1,$K$1) -> 0 | I35: =_xll.DBRW($B$1,Input_Prod_02!$D$9,Input_Prod_02!I$11,$M$1,Input_Prod_02!$G$9,$J$9,Input_Prod_02!$E$30,Input_Prod_02!$B35,$L$1,$K$1) -> 0 | J35: =_xll.DBRW($B$1,Input_Prod_02!$D$9,Input_Prod_02!J$11,$M$1,Input_Prod_02!$G$9,$J$9,Input_Prod_02!$E$30,Input_Prod_02!$B35,$L$1,$K$1) -> 0 | ... N35: =_xll.DBRW($B$1,Input_Prod_02!$D$9,Input_Prod_02!N$11,$M$1,Input_Prod_02!$G$9,$J$9,Input_Prod_02!$E$30,Input_Prod_02!$B35,$L$1,$K$1) -> 0
B36: Export Market Sales Volume [kt] | C36: =_xll.DBRW($B$1,Input_Prod_02!$D$9,Input_Prod_02!C$11,$M$1,Input_Prod_02!$G$9,$J$9,Input_Prod_02!$E$30,Input_Prod_02!$B36,$L$1,$K$1) -> 85.63 | D36: =_xll.DBRW($B$1,Input_Prod_02!$D$9,Input_Prod_02!D$11,$M$1,Input_Prod_02!$G$9,$J$9,Input_Prod_02!$E$30,Input_Prod_02!$B36,$L$1,$K$1) -> 138.79 | E36: =_xll.DBRW($B$1,Input_Prod_02!$D$9,Input_Prod_02!E$11,$M$1,Input_Prod_02!$G$9,$J$9,Input_Prod_02!$E$30,Input_Prod_02!$B36,$L$1,$K$1) -> 166.4 | F36: =_xll.DBRW($B$1,Input_Prod_02!$D$9,Input_Prod_02!F$11,$M$1,Input_Prod_02!$G$9,$J$9,Input_Prod_02!$E$30,Input_Prod_02!$B36,$L$1,$K$1) -> 259.62 | G36: =_xll.DBRW($B$1,Input_Prod_02!$D$9,Input_Prod_02!G$11,$M$1,Input_Prod_02!$G$9,$J$9,Input_Prod_02!$E$30,Input_Prod_02!$B36,$L$1,$K$1) -> 312.52 | H36: =_xll.DBRW($B$1,Input_Prod_02!$D$9,Input_Prod_02!H$11,$M$1,Input_Prod_02!$G$9,$J$9,Input_Prod_02!$E$30,Input_Prod_02!$B36,$L$1,$K$1) -> 339.09 | I36: =_xll.DBRW($B$1,Input_Prod_02!$D$9,Input_Prod_02!I$11,$M$1,Input_Prod_02!$G$9,$J$9,Input_Prod_02!$E$30,Input_Prod_02!$B36,$L$1,$K$1) -> 354.24 | J36: =_xll.DBRW($B$1,Input_Prod_02!$D$9,Input_Prod_02!J$11,$M$1,Input_Prod_02!$G$9,$J$9,Input_Prod_02!$E$30,Input_Prod_02!$B36,$L$1,$K$1) -> 378.98 | ... N36: =_xll.DBRW($B$1,Input_Prod_02!$D$9,Input_Prod_02!N$11,$M$1,Input_Prod_02!$G$9,$J$9,Input_Prod_02!$E$30,Input_Prod_02!$B36,$L$1,$K$1) -> 160.47
B37: Third Part Sales Volume [kt] | C37: =_xll.DBRW($B$1,Input_Prod_02!$D$9,Input_Prod_02!C$11,$M$1,Input_Prod_02!$G$9,$J$9,Input_Prod_02!$E$30,Input_Prod_02!$B37,$L$1,$K$1) -> 0 | D37: =_xll.DBRW($B$1,Input_Prod_02!$D$9,Input_Prod_02!D$11,$M$1,Input_Prod_02!$G$9,$J$9,Input_Prod_02!$E$30,Input_Prod_02!$B37,$L$1,$K$1) -> 0 | E37: =_xll.DBRW($B$1,Input_Prod_02!$D$9,Input_Prod_02!E$11,$M$1,Input_Prod_02!$G$9,$J$9,Input_Prod_02!$E$30,Input_Prod_02!$B37,$L$1,$K$1) -> 0 | F37: =_xll.DBRW($B$1,Input_Prod_02!$D$9,Input_Prod_02!F$11,$M$1,Input_Prod_02!$G$9,$J$9,Input_Prod_02!$E$30,Input_Prod_02!$B37,$L$1,$K$1) -> 0 | G37: =_xll.DBRW($B$1,Input_Prod_02!$D$9,Input_Prod_02!G$11,$M$1,Input_Prod_02!$G$9,$J$9,Input_Prod_02!$E$30,Input_Prod_02!$B37,$L$1,$K$1) -> 0 | H37: =_xll.DBRW($B$1,Input_Prod_02!$D$9,Input_Prod_02!H$11,$M$1,Input_Prod_02!$G$9,$J$9,Input_Prod_02!$E$30,Input_Prod_02!$B37,$L$1,$K$1) -> 0 | I37: =_xll.DBRW($B$1,Input_Prod_02!$D$9,Input_Prod_02!I$11,$M$1,Input_Prod_02!$G$9,$J$9,Input_Prod_02!$E$30,Input_Prod_02!$B37,$L$1,$K$1) -> 0 | J37: =_xll.DBRW($B$1,Input_Prod_02!$D$9,Input_Prod_02!J$11,$M$1,Input_Prod_02!$G$9,$J$9,Input_Prod_02!$E$30,Input_Prod_02!$B37,$L$1,$K$1) -> 0 | ... N37: =_xll.DBRW($B$1,Input_Prod_02!$D$9,Input_Prod_02!N$11,$M$1,Input_Prod_02!$G$9,$J$9,Input_Prod_02!$E$30,Input_Prod_02!$B37,$L$1,$K$1) -> 0
B38: Local Market Price Premium [$/ton] | C38: =_xll.DBRW($B$1,Input_Prod_02!$D$9,Input_Prod_02!C$11,$M$1,Input_Prod_02!$G$9,$J$9,Input_Prod_02!$E$30,Input_Prod_02!$B38,$L$1,$K$1) -> 0 | D38: =_xll.DBRW($B$1,Input_Prod_02!$D$9,Input_Prod_02!D$11,$M$1,Input_Prod_02!$G$9,$J$9,Input_Prod_02!$E$30,Input_Prod_02!$B38,$L$1,$K$1) -> 0 | E38: =_xll.DBRW($B$1,Input_Prod_02!$D$9,Input_Prod_02!E$11,$M$1,Input_Prod_02!$G$9,$J$9,Input_Prod_02!$E$30,Input_Prod_02!$B38,$L$1,$K$1) -> 0 | F38: =_xll.DBRW($B$1,Input_Prod_02!$D$9,Input_Prod_02!F$11,$M$1,Input_Prod_02!$G$9,$J$9,Input_Prod_02!$E$30,Input_Prod_02!$B38,$L$1,$K$1) -> 0 | G38: =_xll.DBRW($B$1,Input_Prod_02!$D$9,Input_Prod_02!G$11,$M$1,Input_Prod_02!$G$9,$J$9,Input_Prod_02!$E$30,Input_Prod_02!$B38,$L$1,$K$1) -> 0 | H38: =_xll.DBRW($B$1,Input_Prod_02!$D$9,Input_Prod_02!H$11,$M$1,Input_Prod_02!$G$9,$J$9,Input_Prod_02!$E$30,Input_Prod_02!$B38,$L$1,$K$1) -> 0 | I38: =_xll.DBRW($B$1,Input_Prod_02!$D$9,Input_Prod_02!I$11,$M$1,Input_Prod_02!$G$9,$J$9,Input_Prod_02!$E$30,Input_Prod_02!$B38,$L$1,$K$1) -> 0 | J38: =_xll.DBRW($B$1,Input_Prod_02!$D$9,Input_Prod_02!J$11,$M$1,Input_Prod_02!$G$9,$J$9,Input_Prod_02!$E$30,Input_Prod_02!$B38,$L$1,$K$1) -> 0 | ... N38: =_xll.DBRW($B$1,Input_Prod_02!$D$9,Input_Prod_02!N$11,$M$1,Input_Prod_02!$G$9,$J$9,Input_Prod_02!$E$30,Input_Prod_02!$B38,$L$1,$K$1) -> 0
B39: Export Market Price Premium [$/ton] | C39: =_xll.DBRW($B$1,Input_Prod_02!$D$9,Input_Prod_02!C$11,$M$1,Input_Prod_02!$G$9,$J$9,Input_Prod_02!$E$30,Input_Prod_02!$B39,$L$1,$K$1) -> 204.28085 | D39: =_xll.DBRW($B$1,Input_Prod_02!$D$9,Input_Prod_02!D$11,$M$1,Input_Prod_02!$G$9,$J$9,Input_Prod_02!$E$30,Input_Prod_02!$B39,$L$1,$K$1) -> 211.37389 | E39: =_xll.DBRW($B$1,Input_Prod_02!$D$9,Input_Prod_02!E$11,$M$1,Input_Prod_02!$G$9,$J$9,Input_Prod_02!$E$30,Input_Prod_02!$B39,$L$1,$K$1) -> 207.49497 | F39: =_xll.DBRW($B$1,Input_Prod_02!$D$9,Input_Prod_02!F$11,$M$1,Input_Prod_02!$G$9,$J$9,Input_Prod_02!$E$30,Input_Prod_02!$B39,$L$1,$K$1) -> 197.65714 | G39: =_xll.DBRW($B$1,Input_Prod_02!$D$9,Input_Prod_02!G$11,$M$1,Input_Prod_02!$G$9,$J$9,Input_Prod_02!$E$30,Input_Prod_02!$B39,$L$1,$K$1) -> 197.44742 | H39: =_xll.DBRW($B$1,Input_Prod_02!$D$9,Input_Prod_02!H$11,$M$1,Input_Prod_02!$G$9,$J$9,Input_Prod_02!$E$30,Input_Prod_02!$B39,$L$1,$K$1) -> 198.0545 | I39: =_xll.DBRW($B$1,Input_Prod_02!$D$9,Input_Prod_02!I$11,$M$1,Input_Prod_02!$G$9,$J$9,Input_Prod_02!$E$30,Input_Prod_02!$B39,$L$1,$K$1) -> 200.53728 | J39: =_xll.DBRW($B$1,Input_Prod_02!$D$9,Input_Prod_02!J$11,$M$1,Input_Prod_02!$G$9,$J$9,Input_Prod_02!$E$30,Input_Prod_02!$B39,$L$1,$K$1) -> 198.91153 | ... N39: =_xll.DBRW($B$1,Input_Prod_02!$D$9,Input_Prod_02!N$11,$M$1,Input_Prod_02!$G$9,$J$9,Input_Prod_02!$E$30,Input_Prod_02!$B39,$L$1,$K$1) -> 207.88976
B40: % Operational Tax | C40: =_xll.DBRW($B$1,Input_Prod_02!$D$9,Input_Prod_02!C$11,$M$1,Input_Prod_02!$G$9,$J$9,Input_Prod_02!$E$30,Input_Prod_02!$B40,$L$1,$K$1) -> 0 | D40: =_xll.DBRW($B$1,Input_Prod_02!$D$9,Input_Prod_02!D$11,$M$1,Input_Prod_02!$G$9,$J$9,Input_Prod_02!$E$30,Input_Prod_02!$B40,$L$1,$K$1) -> 0 | E40: =_xll.DBRW($B$1,Input_Prod_02!$D$9,Input_Prod_02!E$11,$M$1,Input_Prod_02!$G$9,$J$9,Input_Prod_02!$E$30,Input_Prod_02!$B40,$L$1,$K$1) -> 0 | F40: =_xll.DBRW($B$1,Input_Prod_02!$D$9,Input_Prod_02!F$11,$M$1,Input_Prod_02!$G$9,$J$9,Input_Prod_02!$E$30,Input_Prod_02!$B40,$L$1,$K$1) -> 0 | G40: =_xll.DBRW($B$1,Input_Prod_02!$D$9,Input_Prod_02!G$11,$M$1,Input_Prod_02!$G$9,$J$9,Input_Prod_02!$E$30,Input_Prod_02!$B40,$L$1,$K$1) -> 0 | H40: =_xll.DBRW($B$1,Input_Prod_02!$D$9,Input_Prod_02!H$11,$M$1,Input_Prod_02!$G$9,$J$9,Input_Prod_02!$E$30,Input_Prod_02!$B40,$L$1,$K$1) -> 0 | I40: =_xll.DBRW($B$1,Input_Prod_02!$D$9,Input_Prod_02!I$11,$M$1,Input_Prod_02!$G$9,$J$9,Input_Prod_02!$E$30,Input_Prod_02!$B40,$L$1,$K$1) -> 0 | J40: =_xll.DBRW($B$1,Input_Prod_02!$D$9,Input_Prod_02!J$11,$M$1,Input_Prod_02!$G$9,$J$9,Input_Prod_02!$E$30,Input_Prod_02!$B40,$L$1,$K$1) -> 0 | ... N40: =_xll.DBRW($B$1,Input_Prod_02!$D$9,Input_Prod_02!N$11,$M$1,Input_Prod_02!$G$9,$J$9,Input_Prod_02!$E$30,Input_Prod_02!$B40,$L$1,$K$1) -> 0
B41: Gross Revenue [$MM] | C41: =_xll.DBRW($B$2,Input_Prod_02!$D$9,Input_Prod_02!C$11,$M$1,Input_Prod_02!$G$9,$J$9,$E$30,$K$2,$B$41) -> 17.492569 | D41: =_xll.DBRW($B$2,Input_Prod_02!$D$9,Input_Prod_02!D$11,$M$1,Input_Prod_02!$G$9,$J$9,$E$30,$K$2,$B$41) -> 29.336582 | E41: =_xll.DBRW($B$2,Input_Prod_02!$D$9,Input_Prod_02!E$11,$M$1,Input_Prod_02!$G$9,$J$9,$E$30,$K$2,$B$41) -> 34.527162 | F41: =_xll.DBRW($B$2,Input_Prod_02!$D$9,Input_Prod_02!F$11,$M$1,Input_Prod_02!$G$9,$J$9,$E$30,$K$2,$B$41) -> 51.315748 | G41: =_xll.DBRW($B$2,Input_Prod_02!$D$9,Input_Prod_02!G$11,$M$1,Input_Prod_02!$G$9,$J$9,$E$30,$K$2,$B$41) -> 61.706268 | H41: =_xll.DBRW($B$2,Input_Prod_02!$D$9,Input_Prod_02!H$11,$M$1,Input_Prod_02!$G$9,$J$9,$E$30,$K$2,$B$41) -> 67.158301 | I41: =_xll.DBRW($B$2,Input_Prod_02!$D$9,Input_Prod_02!I$11,$M$1,Input_Prod_02!$G$9,$J$9,$E$30,$K$2,$B$41) -> 71.038326 | J41: =_xll.DBRW($B$2,Input_Prod_02!$D$9,Input_Prod_02!J$11,$M$1,Input_Prod_02!$G$9,$J$9,$E$30,$K$2,$B$41) -> 75.38349 | ... N41: =_xll.DBRW($B$2,Input_Prod_02!$D$9,Input_Prod_02!N$11,$M$1,Input_Prod_02!$G$9,$J$9,$E$30,$K$2,$B$41) -> 33.36007
B42: Net Revenue [$MM] | C42: =_xll.DBRW($B$2,Input_Prod_02!$D$9,Input_Prod_02!C$11,$M$1,Input_Prod_02!$G$9,$J$9,$E$30,$K$2,$B$42) -> 17.492569 | D42: =_xll.DBRW($B$2,Input_Prod_02!$D$9,Input_Prod_02!D$11,$M$1,Input_Prod_02!$G$9,$J$9,$E$30,$K$2,$B$42) -> 29.336582 | E42: =_xll.DBRW($B$2,Input_Prod_02!$D$9,Input_Prod_02!E$11,$M$1,Input_Prod_02!$G$9,$J$9,$E$30,$K$2,$B$42) -> 34.527162 | F42: =_xll.DBRW($B$2,Input_Prod_02!$D$9,Input_Prod_02!F$11,$M$1,Input_Prod_02!$G$9,$J$9,$E$30,$K$2,$B$42) -> 51.315748 | G42: =_xll.DBRW($B$2,Input_Prod_02!$D$9,Input_Prod_02!G$11,$M$1,Input_Prod_02!$G$9,$J$9,$E$30,$K$2,$B$42) -> 61.706268 | H42: =_xll.DBRW($B$2,Input_Prod_02!$D$9,Input_Prod_02!H$11,$M$1,Input_Prod_02!$G$9,$J$9,$E$30,$K$2,$B$42) -> 67.158301 | I42: =_xll.DBRW($B$2,Input_Prod_02!$D$9,Input_Prod_02!I$11,$M$1,Input_Prod_02!$G$9,$J$9,$E$30,$K$2,$B$42) -> 71.038326 | J42: =_xll.DBRW($B$2,Input_Prod_02!$D$9,Input_Prod_02!J$11,$M$1,Input_Prod_02!$G$9,$J$9,$E$30,$K$2,$B$42) -> 75.38349 | ... N42: =_xll.DBRW($B$2,Input_Prod_02!$D$9,Input_Prod_02!N$11,$M$1,Input_Prod_02!$G$9,$J$9,$E$30,$K$2,$B$42) -> 33.36007
B46: CONTRIBUTION MARGIN
C49: =$D$9&"."&C$11 -> 2026.01 | D49: =$D$9&"."&D$11 -> 2026.02 | E49: =$D$9&"."&E$11 -> 2026.03 | F49: =$D$9&"."&F$11 -> 2026.04 | G49: =$D$9&"."&G$11 -> 2026.05 | H49: =$D$9&"."&H$11 -> 2026.06 | I49: =$D$9&"."&I$11 -> 2026.07 | J49: =$D$9&"."&J$11 -> 2026.08 | ... N49: =$D$9&"."&N$11 -> 2026.12
B50: Final Variable Sales Expenses | C50: =_xll.DBRW($B$1,Input_Prod_02!$D$9,Input_Prod_02!C$11,$M$1,Input_Prod_02!$G$9,$J$9,$E$30,Input_Prod_02!$B50,$L$1,$K$1) -> 0 | D50: =_xll.DBRW($B$1,Input_Prod_02!$D$9,Input_Prod_02!D$11,$M$1,Input_Prod_02!$G$9,$J$9,$E$30,Input_Prod_02!$B50,$L$1,$K$1) -> 0 | E50: =_xll.DBRW($B$1,Input_Prod_02!$D$9,Input_Prod_02!E$11,$M$1,Input_Prod_02!$G$9,$J$9,$E$30,Input_Prod_02!$B50,$L$1,$K$1) -> 0 | F50: =_xll.DBRW($B$1,Input_Prod_02!$D$9,Input_Prod_02!F$11,$M$1,Input_Prod_02!$G$9,$J$9,$E$30,Input_Prod_02!$B50,$L$1,$K$1) -> 0 | G50: =_xll.DBRW($B$1,Input_Prod_02!$D$9,Input_Prod_02!G$11,$M$1,Input_Prod_02!$G$9,$J$9,$E$30,Input_Prod_02!$B50,$L$1,$K$1) -> 0 | H50: =_xll.DBRW($B$1,Input_Prod_02!$D$9,Input_Prod_02!H$11,$M$1,Input_Prod_02!$G$9,$J$9,$E$30,Input_Prod_02!$B50,$L$1,$K$1) -> 0 | I50: =_xll.DBRW($B$1,Input_Prod_02!$D$9,Input_Prod_02!I$11,$M$1,Input_Prod_02!$G$9,$J$9,$E$30,Input_Prod_02!$B50,$L$1,$K$1) -> 0 | J50: =_xll.DBRW($B$1,Input_Prod_02!$D$9,Input_Prod_02!J$11,$M$1,Input_Prod_02!$G$9,$J$9,$E$30,Input_Prod_02!$B50,$L$1,$K$1) -> 0 | ... N50: =_xll.DBRW($B$1,Input_Prod_02!$D$9,Input_Prod_02!N$11,$M$1,Input_Prod_02!$G$9,$J$9,$E$30,Input_Prod_02!$B50,$L$1,$K$1) -> 0
B51: Other Variable Costs | C51: =_xll.DBRW($B$1,Input_Prod_02!$D$9,Input_Prod_02!C$11,$M$1,Input_Prod_02!$G$9,$J$9,$E$30,Input_Prod_02!$B51,$L$1,$K$1) -> 11.665254 | D51: =_xll.DBRW($B$1,Input_Prod_02!$D$9,Input_Prod_02!D$11,$M$1,Input_Prod_02!$G$9,$J$9,$E$30,Input_Prod_02!$B51,$L$1,$K$1) -> 17.865808 | E51: =_xll.DBRW($B$1,Input_Prod_02!$D$9,Input_Prod_02!E$11,$M$1,Input_Prod_02!$G$9,$J$9,$E$30,Input_Prod_02!$B51,$L$1,$K$1) -> 21.231732 | F51: =_xll.DBRW($B$1,Input_Prod_02!$D$9,Input_Prod_02!F$11,$M$1,Input_Prod_02!$G$9,$J$9,$E$30,Input_Prod_02!$B51,$L$1,$K$1) -> 30.673704 | G51: =_xll.DBRW($B$1,Input_Prod_02!$D$9,Input_Prod_02!G$11,$M$1,Input_Prod_02!$G$9,$J$9,$E$30,Input_Prod_02!$B51,$L$1,$K$1) -> 36.756721 | H51: =_xll.DBRW($B$1,Input_Prod_02!$D$9,Input_Prod_02!H$11,$M$1,Input_Prod_02!$G$9,$J$9,$E$30,Input_Prod_02!$B51,$L$1,$K$1) -> 39.658936 | I51: =_xll.DBRW($B$1,Input_Prod_02!$D$9,Input_Prod_02!I$11,$M$1,Input_Prod_02!$G$9,$J$9,$E$30,Input_Prod_02!$B51,$L$1,$K$1) -> 41.703705 | J51: =_xll.DBRW($B$1,Input_Prod_02!$D$9,Input_Prod_02!J$11,$M$1,Input_Prod_02!$G$9,$J$9,$E$30,Input_Prod_02!$B51,$L$1,$K$1) -> 44.125326 | ... N51: =_xll.DBRW($B$1,Input_Prod_02!$D$9,Input_Prod_02!N$11,$M$1,Input_Prod_02!$G$9,$J$9,$E$30,Input_Prod_02!$B51,$L$1,$K$1) -> 19.378156
B52: Fixed Costs | C52: =_xll.DBRW($B$1,Input_Prod_02!$D$9,Input_Prod_02!C$11,$M$1,Input_Prod_02!$G$9,$J$9,$E$30,Input_Prod_02!$B52,$L$1,$K$1) -> 0 | D52: =_xll.DBRW($B$1,Input_Prod_02!$D$9,Input_Prod_02!D$11,$M$1,Input_Prod_02!$G$9,$J$9,$E$30,Input_Prod_02!$B52,$L$1,$K$1) -> 0 | E52: =_xll.DBRW($B$1,Input_Prod_02!$D$9,Input_Prod_02!E$11,$M$1,Input_Prod_02!$G$9,$J$9,$E$30,Input_Prod_02!$B52,$L$1,$K$1) -> 0 | F52: =_xll.DBRW($B$1,Input_Prod_02!$D$9,Input_Prod_02!F$11,$M$1,Input_Prod_02!$G$9,$J$9,$E$30,Input_Prod_02!$B52,$L$1,$K$1) -> 0 | G52: =_xll.DBRW($B$1,Input_Prod_02!$D$9,Input_Prod_02!G$11,$M$1,Input_Prod_02!$G$9,$J$9,$E$30,Input_Prod_02!$B52,$L$1,$K$1) -> 0 | H52: =_xll.DBRW($B$1,Input_Prod_02!$D$9,Input_Prod_02!H$11,$M$1,Input_Prod_02!$G$9,$J$9,$E$30,Input_Prod_02!$B52,$L$1,$K$1) -> 0 | I52: =_xll.DBRW($B$1,Input_Prod_02!$D$9,Input_Prod_02!I$11,$M$1,Input_Prod_02!$G$9,$J$9,$E$30,Input_Prod_02!$B52,$L$1,$K$1) -> 0 | J52: =_xll.DBRW($B$1,Input_Prod_02!$D$9,Input_Prod_02!J$11,$M$1,Input_Prod_02!$G$9,$J$9,$E$30,Input_Prod_02!$B52,$L$1,$K$1) -> 0 | ... N52: =_xll.DBRW($B$1,Input_Prod_02!$D$9,Input_Prod_02!N$11,$M$1,Input_Prod_02!$G$9,$J$9,$E$30,Input_Prod_02!$B52,$L$1,$K$1) -> 0
B53: Operating Expenses | C53: =_xll.DBRW($B$1,Input_Prod_02!$D$9,Input_Prod_02!C$11,$M$1,Input_Prod_02!$G$9,$J$9,$E$30,Input_Prod_02!$B53,$L$1,$K$1) -> 0 | D53: =_xll.DBRW($B$1,Input_Prod_02!$D$9,Input_Prod_02!D$11,$M$1,Input_Prod_02!$G$9,$J$9,$E$30,Input_Prod_02!$B53,$L$1,$K$1) -> 0 | E53: =_xll.DBRW($B$1,Input_Prod_02!$D$9,Input_Prod_02!E$11,$M$1,Input_Prod_02!$G$9,$J$9,$E$30,Input_Prod_02!$B53,$L$1,$K$1) -> 0 | F53: =_xll.DBRW($B$1,Input_Prod_02!$D$9,Input_Prod_02!F$11,$M$1,Input_Prod_02!$G$9,$J$9,$E$30,Input_Prod_02!$B53,$L$1,$K$1) -> 0 | G53: =_xll.DBRW($B$1,Input_Prod_02!$D$9,Input_Prod_02!G$11,$M$1,Input_Prod_02!$G$9,$J$9,$E$30,Input_Prod_02!$B53,$L$1,$K$1) -> 0 | H53: =_xll.DBRW($B$1,Input_Prod_02!$D$9,Input_Prod_02!H$11,$M$1,Input_Prod_02!$G$9,$J$9,$E$30,Input_Prod_02!$B53,$L$1,$K$1) -> 0 | I53: =_xll.DBRW($B$1,Input_Prod_02!$D$9,Input_Prod_02!I$11,$M$1,Input_Prod_02!$G$9,$J$9,$E$30,Input_Prod_02!$B53,$L$1,$K$1) -> 0 | J53: =_xll.DBRW($B$1,Input_Prod_02!$D$9,Input_Prod_02!J$11,$M$1,Input_Prod_02!$G$9,$J$9,$E$30,Input_Prod_02!$B53,$L$1,$K$1) -> 0 | ... N53: =_xll.DBRW($B$1,Input_Prod_02!$D$9,Input_Prod_02!N$11,$M$1,Input_Prod_02!$G$9,$J$9,$E$30,Input_Prod_02!$B53,$L$1,$K$1) -> 0
B54: Other | C54: =_xll.DBRW($B$1,Input_Prod_02!$D$9,Input_Prod_02!C$11,$M$1,Input_Prod_02!$G$9,$J$9,$E$30,Input_Prod_02!$B54,$L$1,$K$1) -> 0 | D54: =_xll.DBRW($B$1,Input_Prod_02!$D$9,Input_Prod_02!D$11,$M$1,Input_Prod_02!$G$9,$J$9,$E$30,Input_Prod_02!$B54,$L$1,$K$1) -> 0 | E54: =_xll.DBRW($B$1,Input_Prod_02!$D$9,Input_Prod_02!E$11,$M$1,Input_Prod_02!$G$9,$J$9,$E$30,Input_Prod_02!$B54,$L$1,$K$1) -> 0 | F54: =_xll.DBRW($B$1,Input_Prod_02!$D$9,Input_Prod_02!F$11,$M$1,Input_Prod_02!$G$9,$J$9,$E$30,Input_Prod_02!$B54,$L$1,$K$1) -> 0 | G54: =_xll.DBRW($B$1,Input_Prod_02!$D$9,Input_Prod_02!G$11,$M$1,Input_Prod_02!$G$9,$J$9,$E$30,Input_Prod_02!$B54,$L$1,$K$1) -> 0 | H54: =_xll.DBRW($B$1,Input_Prod_02!$D$9,Input_Prod_02!H$11,$M$1,Input_Prod_02!$G$9,$J$9,$E$30,Input_Prod_02!$B54,$L$1,$K$1) -> 0 | I54: =_xll.DBRW($B$1,Input_Prod_02!$D$9,Input_Prod_02!I$11,$M$1,Input_Prod_02!$G$9,$J$9,$E$30,Input_Prod_02!$B54,$L$1,$K$1) -> 0 | J54: =_xll.DBRW($B$1,Input_Prod_02!$D$9,Input_Prod_02!J$11,$M$1,Input_Prod_02!$G$9,$J$9,$E$30,Input_Prod_02!$B54,$L$1,$K$1) -> 0 | ... N54: =_xll.DBRW($B$1,Input_Prod_02!$D$9,Input_Prod_02!N$11,$M$1,Input_Prod_02!$G$9,$J$9,$E$30,Input_Prod_02!$B54,$L$1,$K$1) -> 0
B55: EBITDA | C55: =_xll.DBRW($B$3,Input_Prod_02!$D$9,Input_Prod_02!C$11,$M$1,Input_Prod_02!$G$9,$J$9,$E$30,Input_Prod_02!$B55,$K$1) -> 5.8273151 | D55: =_xll.DBRW($B$3,Input_Prod_02!$D$9,Input_Prod_02!D$11,$M$1,Input_Prod_02!$G$9,$J$9,$E$30,Input_Prod_02!$B55,$K$1) -> 11.470774 | E55: =_xll.DBRW($B$3,Input_Prod_02!$D$9,Input_Prod_02!E$11,$M$1,Input_Prod_02!$G$9,$J$9,$E$30,Input_Prod_02!$B55,$K$1) -> 13.29543 | F55: =_xll.DBRW($B$3,Input_Prod_02!$D$9,Input_Prod_02!F$11,$M$1,Input_Prod_02!$G$9,$J$9,$E$30,Input_Prod_02!$B55,$K$1) -> 20.642044 | G55: =_xll.DBRW($B$3,Input_Prod_02!$D$9,Input_Prod_02!G$11,$M$1,Input_Prod_02!$G$9,$J$9,$E$30,Input_Prod_02!$B55,$K$1) -> 24.949547 | H55: =_xll.DBRW($B$3,Input_Prod_02!$D$9,Input_Prod_02!H$11,$M$1,Input_Prod_02!$G$9,$J$9,$E$30,Input_Prod_02!$B55,$K$1) -> 27.499365 | I55: =_xll.DBRW($B$3,Input_Prod_02!$D$9,Input_Prod_02!I$11,$M$1,Input_Prod_02!$G$9,$J$9,$E$30,Input_Prod_02!$B55,$K$1) -> 29.334622 | J55: =_xll.DBRW($B$3,Input_Prod_02!$D$9,Input_Prod_02!J$11,$M$1,Input_Prod_02!$G$9,$J$9,$E$30,Input_Prod_02!$B55,$K$1) -> 31.258164 | ... N55: =_xll.DBRW($B$3,Input_Prod_02!$D$9,Input_Prod_02!N$11,$M$1,Input_Prod_02!$G$9,$J$9,$E$30,Input_Prod_02!$B55,$K$1) -> 13.981914
B58: Operating Profit
C60: =$D$9&"."&C$11 -> 2026.01 | D60: =$D$9&"."&D$11 -> 2026.02 | E60: =$D$9&"."&E$11 -> 2026.03 | F60: =$D$9&"."&F$11 -> 2026.04 | G60: =$D$9&"."&G$11 -> 2026.05 | H60: =$D$9&"."&H$11 -> 2026.06 | I60: =$D$9&"."&I$11 -> 2026.07 | J60: =$D$9&"."&J$11 -> 2026.08 | ... N60: =$D$9&"."&N$11 -> 2026.12
B61: Depreciation / amortization / depletion - Corporate | C61: =_xll.DBRW($B$1,Input_Prod_02!$D$9,Input_Prod_02!C$11,$M$1,Input_Prod_02!$G$9,$J$9,$E$30,Input_Prod_02!$B61,$L$1,$K$1) -> 0 | D61: =_xll.DBRW($B$1,Input_Prod_02!$D$9,Input_Prod_02!D$11,$M$1,Input_Prod_02!$G$9,$J$9,$E$30,Input_Prod_02!$B61,$L$1,$K$1) -> 0 | E61: =_xll.DBRW($B$1,Input_Prod_02!$D$9,Input_Prod_02!E$11,$M$1,Input_Prod_02!$G$9,$J$9,$E$30,Input_Prod_02!$B61,$L$1,$K$1) -> 0 | F61: =_xll.DBRW($B$1,Input_Prod_02!$D$9,Input_Prod_02!F$11,$M$1,Input_Prod_02!$G$9,$J$9,$E$30,Input_Prod_02!$B61,$L$1,$K$1) -> 0 | G61: =_xll.DBRW($B$1,Input_Prod_02!$D$9,Input_Prod_02!G$11,$M$1,Input_Prod_02!$G$9,$J$9,$E$30,Input_Prod_02!$B61,$L$1,$K$1) -> 0 | H61: =_xll.DBRW($B$1,Input_Prod_02!$D$9,Input_Prod_02!H$11,$M$1,Input_Prod_02!$G$9,$J$9,$E$30,Input_Prod_02!$B61,$L$1,$K$1) -> 0 | I61: =_xll.DBRW($B$1,Input_Prod_02!$D$9,Input_Prod_02!I$11,$M$1,Input_Prod_02!$G$9,$J$9,$E$30,Input_Prod_02!$B61,$L$1,$K$1) -> 0 | J61: =_xll.DBRW($B$1,Input_Prod_02!$D$9,Input_Prod_02!J$11,$M$1,Input_Prod_02!$G$9,$J$9,$E$30,Input_Prod_02!$B61,$L$1,$K$1) -> 0 | ... N61: =_xll.DBRW($B$1,Input_Prod_02!$D$9,Input_Prod_02!N$11,$M$1,Input_Prod_02!$G$9,$J$9,$E$30,Input_Prod_02!$B61,$L$1,$K$1) -> 0
B62: EBITDA | C62: =_xll.DBRW($B$3,Input_Prod_02!$D$9,Input_Prod_02!C$11,$M$1,Input_Prod_02!$G$9,$J$9,$E$30,Input_Prod_02!$B62,$K$1) -> 5.8273151 | D62: =_xll.DBRW($B$3,Input_Prod_02!$D$9,Input_Prod_02!D$11,$M$1,Input_Prod_02!$G$9,$J$9,$E$30,Input_Prod_02!$B62,$K$1) -> 11.470774 | E62: =_xll.DBRW($B$3,Input_Prod_02!$D$9,Input_Prod_02!E$11,$M$1,Input_Prod_02!$G$9,$J$9,$E$30,Input_Prod_02!$B62,$K$1) -> 13.29543 | F62: =_xll.DBRW($B$3,Input_Prod_02!$D$9,Input_Prod_02!F$11,$M$1,Input_Prod_02!$G$9,$J$9,$E$30,Input_Prod_02!$B62,$K$1) -> 20.642044 | G62: =_xll.DBRW($B$3,Input_Prod_02!$D$9,Input_Prod_02!G$11,$M$1,Input_Prod_02!$G$9,$J$9,$E$30,Input_Prod_02!$B62,$K$1) -> 24.949547 | H62: =_xll.DBRW($B$3,Input_Prod_02!$D$9,Input_Prod_02!H$11,$M$1,Input_Prod_02!$G$9,$J$9,$E$30,Input_Prod_02!$B62,$K$1) -> 27.499365 | I62: =_xll.DBRW($B$3,Input_Prod_02!$D$9,Input_Prod_02!I$11,$M$1,Input_Prod_02!$G$9,$J$9,$E$30,Input_Prod_02!$B62,$K$1) -> 29.334622 | J62: =_xll.DBRW($B$3,Input_Prod_02!$D$9,Input_Prod_02!J$11,$M$1,Input_Prod_02!$G$9,$J$9,$E$30,Input_Prod_02!$B62,$K$1) -> 31.258164 | ... N62: =_xll.DBRW($B$3,Input_Prod_02!$D$9,Input_Prod_02!N$11,$M$1,Input_Prod_02!$G$9,$J$9,$E$30,Input_Prod_02!$B62,$K$1) -> 13.981914
B63: Operating Profit | C63: =_xll.DBRW($B$3,Input_Prod_02!$D$9,Input_Prod_02!C$11,$M$1,Input_Prod_02!$G$9,Input_Prod_02!$J$9,$E$30,Input_Prod_02!$B63,$K$1) -> 5.8273151 | D63: =_xll.DBRW($B$3,Input_Prod_02!$D$9,Input_Prod_02!D$11,$M$1,Input_Prod_02!$G$9,Input_Prod_02!$J$9,$E$30,Input_Prod_02!$B63,$K$1) -> 11.470774 | E63: =_xll.DBRW($B$3,Input_Prod_02!$D$9,Input_Prod_02!E$11,$M$1,Input_Prod_02!$G$9,Input_Prod_02!$J$9,$E$30,Input_Prod_02!$B63,$K$1) -> 13.29543 | F63: =_xll.DBRW($B$3,Input_Prod_02!$D$9,Input_Prod_02!F$11,$M$1,Input_Prod_02!$G$9,Input_Prod_02!$J$9,$E$30,Input_Prod_02!$B63,$K$1) -> 20.642044 | G63: =_xll.DBRW($B$3,Input_Prod_02!$D$9,Input_Prod_02!G$11,$M$1,Input_Prod_02!$G$9,Input_Prod_02!$J$9,$E$30,Input_Prod_02!$B63,$K$1) -> 24.949547 | H63: =_xll.DBRW($B$3,Input_Prod_02!$D$9,Input_Prod_02!H$11,$M$1,Input_Prod_02!$G$9,Input_Prod_02!$J$9,$E$30,Input_Prod_02!$B63,$K$1) -> 27.499365 | I63: =_xll.DBRW($B$3,Input_Prod_02!$D$9,Input_Prod_02!I$11,$M$1,Input_Prod_02!$G$9,Input_Prod_02!$J$9,$E$30,Input_Prod_02!$B63,$K$1) -> 29.334622 | J63: =_xll.DBRW($B$3,Input_Prod_02!$D$9,Input_Prod_02!J$11,$M$1,Input_Prod_02!$G$9,Input_Prod_02!$J$9,$E$30,Input_Prod_02!$B63,$K$1) -> 31.258164 | ... N63: =_xll.DBRW($B$3,Input_Prod_02!$D$9,Input_Prod_02!N$11,$M$1,Input_Prod_02!$G$9,Input_Prod_02!$J$9,$E$30,Input_Prod_02!$B63,$K$1) -> 13.981914
B66: Profit Before Income Tax
C68: =$D$9&"."&C$11 -> 2026.01 | D68: =$D$9&"."&D$11 -> 2026.02 | E68: =$D$9&"."&E$11 -> 2026.03 | F68: =$D$9&"."&F$11 -> 2026.04 | G68: =$D$9&"."&G$11 -> 2026.05 | H68: =$D$9&"."&H$11 -> 2026.06 | I68: =$D$9&"."&I$11 -> 2026.07 | J68: =$D$9&"."&J$11 -> 2026.08 | ... N68: =$D$9&"."&N$11 -> 2026.12
B69: Equity Pick-Up Results | C69: =_xll.DBRW($B$1,Input_Prod_02!$D$9,Input_Prod_02!C$11,$M$1,Input_Prod_02!$G$9,$J$9,$E$30,Input_Prod_02!$B69,$L$1,$K$1) -> 0 | D69: =_xll.DBRW($B$1,Input_Prod_02!$D$9,Input_Prod_02!D$11,$M$1,Input_Prod_02!$G$9,$J$9,$E$30,Input_Prod_02!$B69,$L$1,$K$1) -> 0 | E69: =_xll.DBRW($B$1,Input_Prod_02!$D$9,Input_Prod_02!E$11,$M$1,Input_Prod_02!$G$9,$J$9,$E$30,Input_Prod_02!$B69,$L$1,$K$1) -> 0 | F69: =_xll.DBRW($B$1,Input_Prod_02!$D$9,Input_Prod_02!F$11,$M$1,Input_Prod_02!$G$9,$J$9,$E$30,Input_Prod_02!$B69,$L$1,$K$1) -> 0 | G69: =_xll.DBRW($B$1,Input_Prod_02!$D$9,Input_Prod_02!G$11,$M$1,Input_Prod_02!$G$9,$J$9,$E$30,Input_Prod_02!$B69,$L$1,$K$1) -> 0 | H69: =_xll.DBRW($B$1,Input_Prod_02!$D$9,Input_Prod_02!H$11,$M$1,Input_Prod_02!$G$9,$J$9,$E$30,Input_Prod_02!$B69,$L$1,$K$1) -> 0 | I69: =_xll.DBRW($B$1,Input_Prod_02!$D$9,Input_Prod_02!I$11,$M$1,Input_Prod_02!$G$9,$J$9,$E$30,Input_Prod_02!$B69,$L$1,$K$1) -> 0 | J69: =_xll.DBRW($B$1,Input_Prod_02!$D$9,Input_Prod_02!J$11,$M$1,Input_Prod_02!$G$9,$J$9,$E$30,Input_Prod_02!$B69,$L$1,$K$1) -> 0 | ... N69: =_xll.DBRW($B$1,Input_Prod_02!$D$9,Input_Prod_02!N$11,$M$1,Input_Prod_02!$G$9,$J$9,$E$30,Input_Prod_02!$B69,$L$1,$K$1) -> 0
B70: Other Non Operating Results | C70: =_xll.DBRW($B$1,Input_Prod_02!$D$9,Input_Prod_02!C$11,$M$1,Input_Prod_02!$G$9,$J$9,$E$30,Input_Prod_02!$B70,$L$1,$K$1) -> 0 | D70: =_xll.DBRW($B$1,Input_Prod_02!$D$9,Input_Prod_02!D$11,$M$1,Input_Prod_02!$G$9,$J$9,$E$30,Input_Prod_02!$B70,$L$1,$K$1) -> 0 | E70: =_xll.DBRW($B$1,Input_Prod_02!$D$9,Input_Prod_02!E$11,$M$1,Input_Prod_02!$G$9,$J$9,$E$30,Input_Prod_02!$B70,$L$1,$K$1) -> 0 | F70: =_xll.DBRW($B$1,Input_Prod_02!$D$9,Input_Prod_02!F$11,$M$1,Input_Prod_02!$G$9,$J$9,$E$30,Input_Prod_02!$B70,$L$1,$K$1) -> 0 | G70: =_xll.DBRW($B$1,Input_Prod_02!$D$9,Input_Prod_02!G$11,$M$1,Input_Prod_02!$G$9,$J$9,$E$30,Input_Prod_02!$B70,$L$1,$K$1) -> 0 | H70: =_xll.DBRW($B$1,Input_Prod_02!$D$9,Input_Prod_02!H$11,$M$1,Input_Prod_02!$G$9,$J$9,$E$30,Input_Prod_02!$B70,$L$1,$K$1) -> 0 | I70: =_xll.DBRW($B$1,Input_Prod_02!$D$9,Input_Prod_02!I$11,$M$1,Input_Prod_02!$G$9,$J$9,$E$30,Input_Prod_02!$B70,$L$1,$K$1) -> 0 | J70: =_xll.DBRW($B$1,Input_Prod_02!$D$9,Input_Prod_02!J$11,$M$1,Input_Prod_02!$G$9,$J$9,$E$30,Input_Prod_02!$B70,$L$1,$K$1) -> 0 | ... N70: =_xll.DBRW($B$1,Input_Prod_02!$D$9,Input_Prod_02!N$11,$M$1,Input_Prod_02!$G$9,$J$9,$E$30,Input_Prod_02!$B70,$L$1,$K$1) -> 0
B71: Financial Results | C71: =_xll.DBRW($B$3,Input_Prod_02!$D$9,Input_Prod_02!C$11,$M$1,Input_Prod_02!$G$9,Input_Prod_02!$J$9,$E$30,Input_Prod_02!$B71,$K$1) -> 0 | D71: =_xll.DBRW($B$3,Input_Prod_02!$D$9,Input_Prod_02!D$11,$M$1,Input_Prod_02!$G$9,Input_Prod_02!$J$9,$E$30,Input_Prod_02!$B71,$K$1) -> 0 | E71: =_xll.DBRW($B$3,Input_Prod_02!$D$9,Input_Prod_02!E$11,$M$1,Input_Prod_02!$G$9,Input_Prod_02!$J$9,$E$30,Input_Prod_02!$B71,$K$1) -> 0 | F71: =_xll.DBRW($B$3,Input_Prod_02!$D$9,Input_Prod_02!F$11,$M$1,Input_Prod_02!$G$9,Input_Prod_02!$J$9,$E$30,Input_Prod_02!$B71,$K$1) -> 0 | G71: =_xll.DBRW($B$3,Input_Prod_02!$D$9,Input_Prod_02!G$11,$M$1,Input_Prod_02!$G$9,Input_Prod_02!$J$9,$E$30,Input_Prod_02!$B71,$K$1) -> 0 | H71: =_xll.DBRW($B$3,Input_Prod_02!$D$9,Input_Prod_02!H$11,$M$1,Input_Prod_02!$G$9,Input_Prod_02!$J$9,$E$30,Input_Prod_02!$B71,$K$1) -> 0 | I71: =_xll.DBRW($B$3,Input_Prod_02!$D$9,Input_Prod_02!I$11,$M$1,Input_Prod_02!$G$9,Input_Prod_02!$J$9,$E$30,Input_Prod_02!$B71,$K$1) -> 0 | J71: =_xll.DBRW($B$3,Input_Prod_02!$D$9,Input_Prod_02!J$11,$M$1,Input_Prod_02!$G$9,Input_Prod_02!$J$9,$E$30,Input_Prod_02!$B71,$K$1) -> 0 | ... N71: =_xll.DBRW($B$3,Input_Prod_02!$D$9,Input_Prod_02!N$11,$M$1,Input_Prod_02!$G$9,Input_Prod_02!$J$9,$E$30,Input_Prod_02!$B71,$K$1) -> 0
B72: Profit Before Income Tax | C72: =_xll.DBRW($B$3,Input_Prod_02!$D$9,Input_Prod_02!C$11,$M$1,Input_Prod_02!$G$9,Input_Prod_02!$J$9,$E$30,Input_Prod_02!$B72,$K$1) -> 5.8273151 | D72: =_xll.DBRW($B$3,Input_Prod_02!$D$9,Input_Prod_02!D$11,$M$1,Input_Prod_02!$G$9,Input_Prod_02!$J$9,$E$30,Input_Prod_02!$B72,$K$1) -> 11.470774 | E72: =_xll.DBRW($B$3,Input_Prod_02!$D$9,Input_Prod_02!E$11,$M$1,Input_Prod_02!$G$9,Input_Prod_02!$J$9,$E$30,Input_Prod_02!$B72,$K$1) -> 13.29543 | F72: =_xll.DBRW($B$3,Input_Prod_02!$D$9,Input_Prod_02!F$11,$M$1,Input_Prod_02!$G$9,Input_Prod_02!$J$9,$E$30,Input_Prod_02!$B72,$K$1) -> 20.642044 | G72: =_xll.DBRW($B$3,Input_Prod_02!$D$9,Input_Prod_02!G$11,$M$1,Input_Prod_02!$G$9,Input_Prod_02!$J$9,$E$30,Input_Prod_02!$B72,$K$1) -> 24.949547 | H72: =_xll.DBRW($B$3,Input_Prod_02!$D$9,Input_Prod_02!H$11,$M$1,Input_Prod_02!$G$9,Input_Prod_02!$J$9,$E$30,Input_Prod_02!$B72,$K$1) -> 27.499365 | I72: =_xll.DBRW($B$3,Input_Prod_02!$D$9,Input_Prod_02!I$11,$M$1,Input_Prod_02!$G$9,Input_Prod_02!$J$9,$E$30,Input_Prod_02!$B72,$K$1) -> 29.334622 | J72: =_xll.DBRW($B$3,Input_Prod_02!$D$9,Input_Prod_02!J$11,$M$1,Input_Prod_02!$G$9,Input_Prod_02!$J$9,$E$30,Input_Prod_02!$B72,$K$1) -> 31.258164 | ... N72: =_xll.DBRW($B$3,Input_Prod_02!$D$9,Input_Prod_02!N$11,$M$1,Input_Prod_02!$G$9,Input_Prod_02!$J$9,$E$30,Input_Prod_02!$B72,$K$1) -> 13.981914
B75: Net Profit Before Minority Int.
C77: =$D$9&"."&C$11 -> 2026.01 | D77: =$D$9&"."&D$11 -> 2026.02 | E77: =$D$9&"."&E$11 -> 2026.03 | F77: =$D$9&"."&F$11 -> 2026.04 | G77: =$D$9&"."&G$11 -> 2026.05 | H77: =$D$9&"."&H$11 -> 2026.06 | I77: =$D$9&"."&I$11 -> 2026.07 | J77: =$D$9&"."&J$11 -> 2026.08 | ... N77: =$D$9&"."&N$11 -> 2026.12
B78: Additions/Low IT Income Statement | C78: =_xll.DBRW($B$1,Input_Prod_02!$D$9,Input_Prod_02!C$11,$M$1,Input_Prod_02!$G$9,$J$9,$E$30,Input_Prod_02!$B78,$L$1,$K$1) -> 0 | D78: =_xll.DBRW($B$1,Input_Prod_02!$D$9,Input_Prod_02!D$11,$M$1,Input_Prod_02!$G$9,$J$9,$E$30,Input_Prod_02!$B78,$L$1,$K$1) -> 0 | E78: =_xll.DBRW($B$1,Input_Prod_02!$D$9,Input_Prod_02!E$11,$M$1,Input_Prod_02!$G$9,$J$9,$E$30,Input_Prod_02!$B78,$L$1,$K$1) -> 0 | F78: =_xll.DBRW($B$1,Input_Prod_02!$D$9,Input_Prod_02!F$11,$M$1,Input_Prod_02!$G$9,$J$9,$E$30,Input_Prod_02!$B78,$L$1,$K$1) -> 0 | G78: =_xll.DBRW($B$1,Input_Prod_02!$D$9,Input_Prod_02!G$11,$M$1,Input_Prod_02!$G$9,$J$9,$E$30,Input_Prod_02!$B78,$L$1,$K$1) -> 0 | H78: =_xll.DBRW($B$1,Input_Prod_02!$D$9,Input_Prod_02!H$11,$M$1,Input_Prod_02!$G$9,$J$9,$E$30,Input_Prod_02!$B78,$L$1,$K$1) -> 0 | I78: =_xll.DBRW($B$1,Input_Prod_02!$D$9,Input_Prod_02!I$11,$M$1,Input_Prod_02!$G$9,$J$9,$E$30,Input_Prod_02!$B78,$L$1,$K$1) -> 0 | J78: =_xll.DBRW($B$1,Input_Prod_02!$D$9,Input_Prod_02!J$11,$M$1,Input_Prod_02!$G$9,$J$9,$E$30,Input_Prod_02!$B78,$L$1,$K$1) -> 0 | ... N78: =_xll.DBRW($B$1,Input_Prod_02!$D$9,Input_Prod_02!N$11,$M$1,Input_Prod_02!$G$9,$J$9,$E$30,Input_Prod_02!$B78,$L$1,$K$1) -> 0
B79: % Income Tax | C79: =_xll.DBRW($C$1,Input_Prod_02!$D$9,Input_Prod_02!C$11,$M$1,$J$9,Input_Prod_02!$B79,$K$1) -> 0 | D79: =_xll.DBRW($C$1,Input_Prod_02!$D$9,Input_Prod_02!D$11,$M$1,$J$9,Input_Prod_02!$B79,$K$1) -> 0 | E79: =_xll.DBRW($C$1,Input_Prod_02!$D$9,Input_Prod_02!E$11,$M$1,$J$9,Input_Prod_02!$B79,$K$1) -> 0 | F79: =_xll.DBRW($C$1,Input_Prod_02!$D$9,Input_Prod_02!F$11,$M$1,$J$9,Input_Prod_02!$B79,$K$1) -> 0 | G79: =_xll.DBRW($C$1,Input_Prod_02!$D$9,Input_Prod_02!G$11,$M$1,$J$9,Input_Prod_02!$B79,$K$1) -> 0 | H79: =_xll.DBRW($C$1,Input_Prod_02!$D$9,Input_Prod_02!H$11,$M$1,$J$9,Input_Prod_02!$B79,$K$1) -> 0 | I79: =_xll.DBRW($C$1,Input_Prod_02!$D$9,Input_Prod_02!I$11,$M$1,$J$9,Input_Prod_02!$B79,$K$1) -> 0 | J79: =_xll.DBRW($C$1,Input_Prod_02!$D$9,Input_Prod_02!J$11,$M$1,$J$9,Input_Prod_02!$B79,$K$1) -> 0 | ... N79: =_xll.DBRW($C$1,Input_Prod_02!$D$9,Input_Prod_02!N$11,$M$1,$J$9,Input_Prod_02!$B79,$K$1) -> 0
B80: Income Tax | C80: =_xll.DBRW($B$3,Input_Prod_02!$D$9,Input_Prod_02!C$11,$M$1,Input_Prod_02!$G$9,Input_Prod_02!$J$9,$E$30,Input_Prod_02!$B80,$K$1) -> 0 | D80: =_xll.DBRW($B$3,Input_Prod_02!$D$9,Input_Prod_02!D$11,$M$1,Input_Prod_02!$G$9,Input_Prod_02!$J$9,$E$30,Input_Prod_02!$B80,$K$1) -> 0 | E80: =_xll.DBRW($B$3,Input_Prod_02!$D$9,Input_Prod_02!E$11,$M$1,Input_Prod_02!$G$9,Input_Prod_02!$J$9,$E$30,Input_Prod_02!$B80,$K$1) -> 0 | F80: =_xll.DBRW($B$3,Input_Prod_02!$D$9,Input_Prod_02!F$11,$M$1,Input_Prod_02!$G$9,Input_Prod_02!$J$9,$E$30,Input_Prod_02!$B80,$K$1) -> 0 | G80: =_xll.DBRW($B$3,Input_Prod_02!$D$9,Input_Prod_02!G$11,$M$1,Input_Prod_02!$G$9,Input_Prod_02!$J$9,$E$30,Input_Prod_02!$B80,$K$1) -> 0 | H80: =_xll.DBRW($B$3,Input_Prod_02!$D$9,Input_Prod_02!H$11,$M$1,Input_Prod_02!$G$9,Input_Prod_02!$J$9,$E$30,Input_Prod_02!$B80,$K$1) -> 0 | I80: =_xll.DBRW($B$3,Input_Prod_02!$D$9,Input_Prod_02!I$11,$M$1,Input_Prod_02!$G$9,Input_Prod_02!$J$9,$E$30,Input_Prod_02!$B80,$K$1) -> 0 | J80: =_xll.DBRW($B$3,Input_Prod_02!$D$9,Input_Prod_02!J$11,$M$1,Input_Prod_02!$G$9,Input_Prod_02!$J$9,$E$30,Input_Prod_02!$B80,$K$1) -> 0 | ... N80: =_xll.DBRW($B$3,Input_Prod_02!$D$9,Input_Prod_02!N$11,$M$1,Input_Prod_02!$G$9,Input_Prod_02!$J$9,$E$30,Input_Prod_02!$B80,$K$1) -> 0
B81: Net Profit Before Minority Int. | C81: =_xll.DBRW($B$3,Input_Prod_02!$D$9,Input_Prod_02!C$11,$M$1,Input_Prod_02!$G$9,Input_Prod_02!$J$9,$E$30,Input_Prod_02!$B81,$K$1) -> 5.8273151 | D81: =_xll.DBRW($B$3,Input_Prod_02!$D$9,Input_Prod_02!D$11,$M$1,Input_Prod_02!$G$9,Input_Prod_02!$J$9,$E$30,Input_Prod_02!$B81,$K$1) -> 11.470774 | E81: =_xll.DBRW($B$3,Input_Prod_02!$D$9,Input_Prod_02!E$11,$M$1,Input_Prod_02!$G$9,Input_Prod_02!$J$9,$E$30,Input_Prod_02!$B81,$K$1) -> 13.29543 | F81: =_xll.DBRW($B$3,Input_Prod_02!$D$9,Input_Prod_02!F$11,$M$1,Input_Prod_02!$G$9,Input_Prod_02!$J$9,$E$30,Input_Prod_02!$B81,$K$1) -> 20.642044 | G81: =_xll.DBRW($B$3,Input_Prod_02!$D$9,Input_Prod_02!G$11,$M$1,Input_Prod_02!$G$9,Input_Prod_02!$J$9,$E$30,Input_Prod_02!$B81,$K$1) -> 24.949547 | H81: =_xll.DBRW($B$3,Input_Prod_02!$D$9,Input_Prod_02!H$11,$M$1,Input_Prod_02!$G$9,Input_Prod_02!$J$9,$E$30,Input_Prod_02!$B81,$K$1) -> 27.499365 | I81: =_xll.DBRW($B$3,Input_Prod_02!$D$9,Input_Prod_02!I$11,$M$1,Input_Prod_02!$G$9,Input_Prod_02!$J$9,$E$30,Input_Prod_02!$B81,$K$1) -> 29.334622 | J81: =_xll.DBRW($B$3,Input_Prod_02!$D$9,Input_Prod_02!J$11,$M$1,Input_Prod_02!$G$9,Input_Prod_02!$J$9,$E$30,Input_Prod_02!$B81,$K$1) -> 31.258164 | ... N81: =_xll.DBRW($B$3,Input_Prod_02!$D$9,Input_Prod_02!N$11,$M$1,Input_Prod_02!$G$9,Input_Prod_02!$J$9,$E$30,Input_Prod_02!$B81,$K$1) -> 13.981914
B84: Net Profit
C86: =$D$9&"."&C$11 -> 2026.01 | D86: =$D$9&"."&D$11 -> 2026.02 | E86: =$D$9&"."&E$11 -> 2026.03 | F86: =$D$9&"."&F$11 -> 2026.04 | G86: =$D$9&"."&G$11 -> 2026.05 | H86: =$D$9&"."&H$11 -> 2026.06 | I86: =$D$9&"."&I$11 -> 2026.07 | J86: =$D$9&"."&J$11 -> 2026.08 | ... N86: =$D$9&"."&N$11 -> 2026.12
B87: % Minoritários | C87: =_xll.DBRW($C$1,Input_Prod_02!$D$9,Input_Prod_02!C$11,$M$1,$J$9,Input_Prod_02!$B87,$K$1) -> 0.17 | D87: =_xll.DBRW($C$1,Input_Prod_02!$D$9,Input_Prod_02!D$11,$M$1,$J$9,Input_Prod_02!$B87,$K$1) -> 0.17 | E87: =_xll.DBRW($C$1,Input_Prod_02!$D$9,Input_Prod_02!E$11,$M$1,$J$9,Input_Prod_02!$B87,$K$1) -> 0.17 | F87: =_xll.DBRW($C$1,Input_Prod_02!$D$9,Input_Prod_02!F$11,$M$1,$J$9,Input_Prod_02!$B87,$K$1) -> 0.17 | G87: =_xll.DBRW($C$1,Input_Prod_02!$D$9,Input_Prod_02!G$11,$M$1,$J$9,Input_Prod_02!$B87,$K$1) -> 0.17 | H87: =_xll.DBRW($C$1,Input_Prod_02!$D$9,Input_Prod_02!H$11,$M$1,$J$9,Input_Prod_02!$B87,$K$1) -> 0.17 | I87: =_xll.DBRW($C$1,Input_Prod_02!$D$9,Input_Prod_02!I$11,$M$1,$J$9,Input_Prod_02!$B87,$K$1) -> 0.17 | J87: =_xll.DBRW($C$1,Input_Prod_02!$D$9,Input_Prod_02!J$11,$M$1,$J$9,Input_Prod_02!$B87,$K$1) -> 0.17 | ... N87: =_xll.DBRW($C$1,Input_Prod_02!$D$9,Input_Prod_02!N$11,$M$1,$J$9,Input_Prod_02!$B87,$K$1) -> 0.17
B88: Minority Interests | C88: =_xll.DBRW($B$3,Input_Prod_02!$D$9,Input_Prod_02!C$11,$M$1,Input_Prod_02!$G$9,Input_Prod_02!$J$9,$E$30,Input_Prod_02!$B88,$K$1) -> 0.99064356 | D88: =_xll.DBRW($B$3,Input_Prod_02!$D$9,Input_Prod_02!D$11,$M$1,Input_Prod_02!$G$9,Input_Prod_02!$J$9,$E$30,Input_Prod_02!$B88,$K$1) -> 1.9500316 | E88: =_xll.DBRW($B$3,Input_Prod_02!$D$9,Input_Prod_02!E$11,$M$1,Input_Prod_02!$G$9,Input_Prod_02!$J$9,$E$30,Input_Prod_02!$B88,$K$1) -> 2.2602231 | F88: =_xll.DBRW($B$3,Input_Prod_02!$D$9,Input_Prod_02!F$11,$M$1,Input_Prod_02!$G$9,Input_Prod_02!$J$9,$E$30,Input_Prod_02!$B88,$K$1) -> 3.5091474 | G88: =_xll.DBRW($B$3,Input_Prod_02!$D$9,Input_Prod_02!G$11,$M$1,Input_Prod_02!$G$9,Input_Prod_02!$J$9,$E$30,Input_Prod_02!$B88,$K$1) -> 4.241423 | H88: =_xll.DBRW($B$3,Input_Prod_02!$D$9,Input_Prod_02!H$11,$M$1,Input_Prod_02!$G$9,Input_Prod_02!$J$9,$E$30,Input_Prod_02!$B88,$K$1) -> 4.6748921 | I88: =_xll.DBRW($B$3,Input_Prod_02!$D$9,Input_Prod_02!I$11,$M$1,Input_Prod_02!$G$9,Input_Prod_02!$J$9,$E$30,Input_Prod_02!$B88,$K$1) -> 4.9868857 | J88: =_xll.DBRW($B$3,Input_Prod_02!$D$9,Input_Prod_02!J$11,$M$1,Input_Prod_02!$G$9,Input_Prod_02!$J$9,$E$30,Input_Prod_02!$B88,$K$1) -> 5.3138879 | ... N88: =_xll.DBRW($B$3,Input_Prod_02!$D$9,Input_Prod_02!N$11,$M$1,Input_Prod_02!$G$9,Input_Prod_02!$J$9,$E$30,Input_Prod_02!$B88,$K$1) -> 2.3769253
B89: Net Profit | C89: =_xll.DBRW($B$3,Input_Prod_02!$D$9,Input_Prod_02!C$11,$M$1,Input_Prod_02!$G$9,Input_Prod_02!$J$9,$E$30,Input_Prod_02!$B89,$K$1) -> 4.8366715 | D89: =_xll.DBRW($B$3,Input_Prod_02!$D$9,Input_Prod_02!D$11,$M$1,Input_Prod_02!$G$9,Input_Prod_02!$J$9,$E$30,Input_Prod_02!$B89,$K$1) -> 9.5207424 | E89: =_xll.DBRW($B$3,Input_Prod_02!$D$9,Input_Prod_02!E$11,$M$1,Input_Prod_02!$G$9,Input_Prod_02!$J$9,$E$30,Input_Prod_02!$B89,$K$1) -> 11.035207 | F89: =_xll.DBRW($B$3,Input_Prod_02!$D$9,Input_Prod_02!F$11,$M$1,Input_Prod_02!$G$9,Input_Prod_02!$J$9,$E$30,Input_Prod_02!$B89,$K$1) -> 17.132896 | G89: =_xll.DBRW($B$3,Input_Prod_02!$D$9,Input_Prod_02!G$11,$M$1,Input_Prod_02!$G$9,Input_Prod_02!$J$9,$E$30,Input_Prod_02!$B89,$K$1) -> 20.708124 | H89: =_xll.DBRW($B$3,Input_Prod_02!$D$9,Input_Prod_02!H$11,$M$1,Input_Prod_02!$G$9,Input_Prod_02!$J$9,$E$30,Input_Prod_02!$B89,$K$1) -> 22.824473 | I89: =_xll.DBRW($B$3,Input_Prod_02!$D$9,Input_Prod_02!I$11,$M$1,Input_Prod_02!$G$9,Input_Prod_02!$J$9,$E$30,Input_Prod_02!$B89,$K$1) -> 24.347736 | J89: =_xll.DBRW($B$3,Input_Prod_02!$D$9,Input_Prod_02!J$11,$M$1,Input_Prod_02!$G$9,Input_Prod_02!$J$9,$E$30,Input_Prod_02!$B89,$K$1) -> 25.944276 | ... N89: =_xll.DBRW($B$3,Input_Prod_02!$D$9,Input_Prod_02!N$11,$M$1,Input_Prod_02!$G$9,Input_Prod_02!$J$9,$E$30,Input_Prod_02!$B89,$K$1) -> 11.604988

Sheet Input_Prod_03
B1: =_xll.VIEW("CONS_VC:STG.100.DataBase_Uploads",D9) -> CONS_VC:STG.100.DataBase_Uploads:-7526985492045866792 | C1: =_xll.VIEW("CONS_VC:ALL.015.Region_Assumptions") -> CONS_VC:ALL.015.Region_Assumptions:-752698549-241339904 | D1: =_xll.VIEW("CONS_VC:DFS.120.Financial_Results") -> CONS_VC:DFS.120.Financial_Results:-752698549676160401 | K1: Value | L1: N/A | M1: =_xll.SUBNM("CONS_VC:ALL.D.Version","","T4") -> T4 | N1: PROD099
B2: =_xll.VIEW("CONS_VC:REV.100.Revenue_Consolidated") -> CONS_VC:REV.100.Revenue_Consolidated:-752698549-457517290 | C2: =_xll.VIEW("CONS_VC:ALL.010.Economic_Assumptions") -> CONS_VC:ALL.010.Economic_Assumptions:-75269854983039568 | D2: =_xll.VIEW("CONS_VC:DFS.140.Indirect_Cash_Flow") -> CONS_VC:DFS.140.Indirect_Cash_Flow:-7526985491698026309 | K2: Total Market | N2: Total Products
B3: =_xll.VIEW("CONS_VC:DFS.100.Profit_and_Loss") -> CONS_VC:DFS.100.Profit_and_Loss:-752698549-945800542 | C3: =_xll.VIEW("CONS_VC:DFS.160.Working_Capital") -> CONS_VC:DFS.160.Working_Capital:-752698549-1249916083 | D3: =_xll.VIEW("CONS_VC:ALL.004.Uploads_Status_Planning") -> CONS_VC:ALL.004.Uploads_Status_Planning:-7526985491976163719 | G3: Flag
B4: =_xll.VIEW("CONS_VC:ALL.001.Actual_Control") -> CONS_VC:ALL.001.Actual_Control:-752698549101777348 | C4: =_xll.VIEW("CONS_VC:DFS.180.Gross_Debt") -> CONS_VC:DFS.180.Gross_Debt:-752698549-2064243330
C5: =_xll.DBRW(Input_Prod_03!$B$4,Input_Prod_03!$D$9,Input_Prod_03!C11,$M$1,$G$3) -> PLAN | D5: =_xll.DBRW(Input_Prod_03!$B$4,Input_Prod_03!$D$9,Input_Prod_03!D11,$M$1,$G$3) -> PLAN | E5: =_xll.DBRW(Input_Prod_03!$B$4,Input_Prod_03!$D$9,Input_Prod_03!E11,$M$1,$G$3) -> PLAN | F5: =_xll.DBRW(Input_Prod_03!$B$4,Input_Prod_03!$D$9,Input_Prod_03!F11,$M$1,$G$3) -> PLAN | G5: =_xll.DBRW(Input_Prod_03!$B$4,Input_Prod_03!$D$9,Input_Prod_03!G11,$M$1,$G$3) -> PLAN | H5: =_xll.DBRW(Input_Prod_03!$B$4,Input_Prod_03!$D$9,Input_Prod_03!H11,$M$1,$G$3) -> PLAN | I5: =_xll.DBRW(Input_Prod_03!$B$4,Input_Prod_03!$D$9,Input_Prod_03!I11,$M$1,$G$3) -> PLAN | J5: =_xll.DBRW(Input_Prod_03!$B$4,Input_Prod_03!$D$9,Input_Prod_03!J11,$M$1,$G$3) -> PLAN | ... N5: =_xll.DBRW(Input_Prod_03!$B$4,Input_Prod_03!$D$9,Input_Prod_03!N11,$M$1,$G$3) -> PLAN
L7: System Input Status: | N7: =_xll.DBRW($D$3,$M$1,$J$9,"Status") -> Closed
B8: GLOBAL ASSUMPTIONS
C9: Year: | D9: =_xll.SUBNM("CONS_VC:ALL.D.Year","SYS_Picklist","2026","MEMBER_NAME") -> 2026 | F9: Currency: | G9: =_xll.SUBNM("CONS_VC:ALL.D.Currency","PAX","USD","Nome alternativo") -> USD | I9: Region: | J9: =_xll.SUBNM("CONS_VC:ALL.D.Region","Nível 0","VCNA","MEMBER_NAME") -> VCNA
C11: 01 | D11: 02 | E11: 03 | F11: 04 | G11: 05 | H11: 06 | I11: 07 | J11: 08 | K11: 09 | L11: 10 | M11: 11 | N11: 12
C12: =$D$9&"."&C11 -> 2026.01 | D12: =$D$9&"."&D11 -> 2026.02 | E12: =$D$9&"."&E11 -> 2026.03 | F12: =$D$9&"."&F11 -> 2026.04 | G12: =$D$9&"."&G11 -> 2026.05 | H12: =$D$9&"."&H11 -> 2026.06 | I12: =$D$9&"."&I11 -> 2026.07 | J12: =$D$9&"."&J11 -> 2026.08 | ... N12: =$D$9&"."&N11 -> 2026.12
B13: Begining FX Rate R$/US$ | C13: =_xll.DBRW($C$2,Input_Prod_03!$D$9,Input_Prod_03!$C$11,$M$1,$B13,$K$1) -> 0 | D13: =_xll.DBRW($C$2,Input_Prod_03!$D$9,Input_Prod_03!$C$11,$M$1,$B13,$K$1) -> 0 | E13: =_xll.DBRW($C$2,Input_Prod_03!$D$9,Input_Prod_03!$C$11,$M$1,$B13,$K$1) -> 0 | F13: =_xll.DBRW($C$2,Input_Prod_03!$D$9,Input_Prod_03!$C$11,$M$1,$B13,$K$1) -> 0 | G13: =_xll.DBRW($C$2,Input_Prod_03!$D$9,Input_Prod_03!$C$11,$M$1,$B13,$K$1) -> 0 | H13: =_xll.DBRW($C$2,Input_Prod_03!$D$9,Input_Prod_03!$C$11,$M$1,$B13,$K$1) -> 0 | I13: =_xll.DBRW($C$2,Input_Prod_03!$D$9,Input_Prod_03!$C$11,$M$1,$B13,$K$1) -> 0 | J13: =_xll.DBRW($C$2,Input_Prod_03!$D$9,Input_Prod_03!$C$11,$M$1,$B13,$K$1) -> 0 | ... N13: =_xll.DBRW($C$2,Input_Prod_03!$D$9,Input_Prod_03!$C$11,$M$1,$B13,$K$1) -> 0
B14: Average FX Rate R$/US$ | C14: =_xll.DBRW($C$2,Input_Prod_03!$D$9,Input_Prod_03!$C$11,$M$1,$B14,$K$1) -> 0 | D14: =_xll.DBRW($C$2,Input_Prod_03!$D$9,Input_Prod_03!$C$11,$M$1,$B14,$K$1) -> 0 | E14: =_xll.DBRW($C$2,Input_Prod_03!$D$9,Input_Prod_03!$C$11,$M$1,$B14,$K$1) -> 0 | F14: =_xll.DBRW($C$2,Input_Prod_03!$D$9,Input_Prod_03!$C$11,$M$1,$B14,$K$1) -> 0 | G14: =_xll.DBRW($C$2,Input_Prod_03!$D$9,Input_Prod_03!$C$11,$M$1,$B14,$K$1) -> 0 | H14: =_xll.DBRW($C$2,Input_Prod_03!$D$9,Input_Prod_03!$C$11,$M$1,$B14,$K$1) -> 0 | I14: =_xll.DBRW($C$2,Input_Prod_03!$D$9,Input_Prod_03!$C$11,$M$1,$B14,$K$1) -> 0 | J14: =_xll.DBRW($C$2,Input_Prod_03!$D$9,Input_Prod_03!$C$11,$M$1,$B14,$K$1) -> 0 | ... N14: =_xll.DBRW($C$2,Input_Prod_03!$D$9,Input_Prod_03!$C$11,$M$1,$B14,$K$1) -> 0
B15: Final FX Rate R$/US$ | C15: =_xll.DBRW($C$2,Input_Prod_03!$D$9,Input_Prod_03!$C$11,$M$1,$B15,$K$1) -> 0 | D15: =_xll.DBRW($C$2,Input_Prod_03!$D$9,Input_Prod_03!$C$11,$M$1,$B15,$K$1) -> 0 | E15: =_xll.DBRW($C$2,Input_Prod_03!$D$9,Input_Prod_03!$C$11,$M$1,$B15,$K$1) -> 0 | F15: =_xll.DBRW($C$2,Input_Prod_03!$D$9,Input_Prod_03!$C$11,$M$1,$B15,$K$1) -> 0 | G15: =_xll.DBRW($C$2,Input_Prod_03!$D$9,Input_Prod_03!$C$11,$M$1,$B15,$K$1) -> 0 | H15: =_xll.DBRW($C$2,Input_Prod_03!$D$9,Input_Prod_03!$C$11,$M$1,$B15,$K$1) -> 0 | I15: =_xll.DBRW($C$2,Input_Prod_03!$D$9,Input_Prod_03!$C$11,$M$1,$B15,$K$1) -> 0 | J15: =_xll.DBRW($C$2,Input_Prod_03!$D$9,Input_Prod_03!$C$11,$M$1,$B15,$K$1) -> 0 | ... N15: =_xll.DBRW($C$2,Input_Prod_03!$D$9,Input_Prod_03!$C$11,$M$1,$B15,$K$1) -> 0
B16: Begining FX Rate US$/EUR | C16: =_xll.DBRW($C$2,Input_Prod_03!$D$9,Input_Prod_03!$C$11,$M$1,$B16,$K$1) -> 0 | D16: =_xll.DBRW($C$2,Input_Prod_03!$D$9,Input_Prod_03!$C$11,$M$1,$B16,$K$1) -> 0 | E16: =_xll.DBRW($C$2,Input_Prod_03!$D$9,Input_Prod_03!$C$11,$M$1,$B16,$K$1) -> 0 | F16: =_xll.DBRW($C$2,Input_Prod_03!$D$9,Input_Prod_03!$C$11,$M$1,$B16,$K$1) -> 0 | G16: =_xll.DBRW($C$2,Input_Prod_03!$D$9,Input_Prod_03!$C$11,$M$1,$B16,$K$1) -> 0 | H16: =_xll.DBRW($C$2,Input_Prod_03!$D$9,Input_Prod_03!$C$11,$M$1,$B16,$K$1) -> 0 | I16: =_xll.DBRW($C$2,Input_Prod_03!$D$9,Input_Prod_03!$C$11,$M$1,$B16,$K$1) -> 0 | J16: =_xll.DBRW($C$2,Input_Prod_03!$D$9,Input_Prod_03!$C$11,$M$1,$B16,$K$1) -> 0 | ... N16: =_xll.DBRW($C$2,Input_Prod_03!$D$9,Input_Prod_03!$C$11,$M$1,$B16,$K$1) -> 0
B17: Average FX Rate US$/EUR | C17: =_xll.DBRW($C$2,Input_Prod_03!$D$9,Input_Prod_03!$C$11,$M$1,$B17,$K$1) -> 5 | D17: =_xll.DBRW($C$2,Input_Prod_03!$D$9,Input_Prod_03!$C$11,$M$1,$B17,$K$1) -> 5 | E17: =_xll.DBRW($C$2,Input_Prod_03!$D$9,Input_Prod_03!$C$11,$M$1,$B17,$K$1) -> 5 | F17: =_xll.DBRW($C$2,Input_Prod_03!$D$9,Input_Prod_03!$C$11,$M$1,$B17,$K$1) -> 5 | G17: =_xll.DBRW($C$2,Input_Prod_03!$D$9,Input_Prod_03!$C$11,$M$1,$B17,$K$1) -> 5 | H17: =_xll.DBRW($C$2,Input_Prod_03!$D$9,Input_Prod_03!$C$11,$M$1,$B17,$K$1) -> 5 | I17: =_xll.DBRW($C$2,Input_Prod_03!$D$9,Input_Prod_03!$C$11,$M$1,$B17,$K$1) -> 5 | J17: =_xll.DBRW($C$2,Input_Prod_03!$D$9,Input_Prod_03!$C$11,$M$1,$B17,$K$1) -> 5 | ... N17: =_xll.DBRW($C$2,Input_Prod_03!$D$9,Input_Prod_03!$C$11,$M$1,$B17,$K$1) -> 5
B18: Final FX Rate US$/EUR | C18: =_xll.DBRW($C$2,Input_Prod_03!$D$9,Input_Prod_03!$C$11,$M$1,$B18,$K$1) -> 0 | D18: =_xll.DBRW($C$2,Input_Prod_03!$D$9,Input_Prod_03!$C$11,$M$1,$B18,$K$1) -> 0 | E18: =_xll.DBRW($C$2,Input_Prod_03!$D$9,Input_Prod_03!$C$11,$M$1,$B18,$K$1) -> 0 | F18: =_xll.DBRW($C$2,Input_Prod_03!$D$9,Input_Prod_03!$C$11,$M$1,$B18,$K$1) -> 0 | G18: =_xll.DBRW($C$2,Input_Prod_03!$D$9,Input_Prod_03!$C$11,$M$1,$B18,$K$1) -> 0 | H18: =_xll.DBRW($C$2,Input_Prod_03!$D$9,Input_Prod_03!$C$11,$M$1,$B18,$K$1) -> 0 | I18: =_xll.DBRW($C$2,Input_Prod_03!$D$9,Input_Prod_03!$C$11,$M$1,$B18,$K$1) -> 0 | J18: =_xll.DBRW($C$2,Input_Prod_03!$D$9,Input_Prod_03!$C$11,$M$1,$B18,$K$1) -> 0 | ... N18: =_xll.DBRW($C$2,Input_Prod_03!$D$9,Input_Prod_03!$C$11,$M$1,$B18,$K$1) -> 0
B19: Câmbio Inicial UYU$/US$ | C19: =_xll.DBRW($C$2,Input_Prod_03!$D$9,Input_Prod_03!$C$11,$M$1,$B19,$K$1) -> 0 | D19: =_xll.DBRW($C$2,Input_Prod_03!$D$9,Input_Prod_03!$C$11,$M$1,$B19,$K$1) -> 0 | E19: =_xll.DBRW($C$2,Input_Prod_03!$D$9,Input_Prod_03!$C$11,$M$1,$B19,$K$1) -> 0 | F19: =_xll.DBRW($C$2,Input_Prod_03!$D$9,Input_Prod_03!$C$11,$M$1,$B19,$K$1) -> 0 | G19: =_xll.DBRW($C$2,Input_Prod_03!$D$9,Input_Prod_03!$C$11,$M$1,$B19,$K$1) -> 0 | H19: =_xll.DBRW($C$2,Input_Prod_03!$D$9,Input_Prod_03!$C$11,$M$1,$B19,$K$1) -> 0 | I19: =_xll.DBRW($C$2,Input_Prod_03!$D$9,Input_Prod_03!$C$11,$M$1,$B19,$K$1) -> 0 | J19: =_xll.DBRW($C$2,Input_Prod_03!$D$9,Input_Prod_03!$C$11,$M$1,$B19,$K$1) -> 0 | ... N19: =_xll.DBRW($C$2,Input_Prod_03!$D$9,Input_Prod_03!$C$11,$M$1,$B19,$K$1) -> 0
B20: Câmbio Médio UYU$/US$ | C20: =_xll.DBRW($C$2,Input_Prod_03!$D$9,Input_Prod_03!$C$11,$M$1,$B20,$K$1) -> 0 | D20: =_xll.DBRW($C$2,Input_Prod_03!$D$9,Input_Prod_03!$C$11,$M$1,$B20,$K$1) -> 0 | E20: =_xll.DBRW($C$2,Input_Prod_03!$D$9,Input_Prod_03!$C$11,$M$1,$B20,$K$1) -> 0 | F20: =_xll.DBRW($C$2,Input_Prod_03!$D$9,Input_Prod_03!$C$11,$M$1,$B20,$K$1) -> 0 | G20: =_xll.DBRW($C$2,Input_Prod_03!$D$9,Input_Prod_03!$C$11,$M$1,$B20,$K$1) -> 0 | H20: =_xll.DBRW($C$2,Input_Prod_03!$D$9,Input_Prod_03!$C$11,$M$1,$B20,$K$1) -> 0 | I20: =_xll.DBRW($C$2,Input_Prod_03!$D$9,Input_Prod_03!$C$11,$M$1,$B20,$K$1) -> 0 | J20: =_xll.DBRW($C$2,Input_Prod_03!$D$9,Input_Prod_03!$C$11,$M$1,$B20,$K$1) -> 0 | ... N20: =_xll.DBRW($C$2,Input_Prod_03!$D$9,Input_Prod_03!$C$11,$M$1,$B20,$K$1) -> 0
B21: Câmbio Final UYU$/US$ | C21: =_xll.DBRW($C$2,Input_Prod_03!$D$9,Input_Prod_03!$C$11,$M$1,$B21,$K$1) -> 0 | D21: =_xll.DBRW($C$2,Input_Prod_03!$D$9,Input_Prod_03!$C$11,$M$1,$B21,$K$1) -> 0 | E21: =_xll.DBRW($C$2,Input_Prod_03!$D$9,Input_Prod_03!$C$11,$M$1,$B21,$K$1) -> 0 | F21: =_xll.DBRW($C$2,Input_Prod_03!$D$9,Input_Prod_03!$C$11,$M$1,$B21,$K$1) -> 0 | G21: =_xll.DBRW($C$2,Input_Prod_03!$D$9,Input_Prod_03!$C$11,$M$1,$B21,$K$1) -> 0 | H21: =_xll.DBRW($C$2,Input_Prod_03!$D$9,Input_Prod_03!$C$11,$M$1,$B21,$K$1) -> 0 | I21: =_xll.DBRW($C$2,Input_Prod_03!$D$9,Input_Prod_03!$C$11,$M$1,$B21,$K$1) -> 0 | J21: =_xll.DBRW($C$2,Input_Prod_03!$D$9,Input_Prod_03!$C$11,$M$1,$B21,$K$1) -> 0 | ... N21: =_xll.DBRW($C$2,Input_Prod_03!$D$9,Input_Prod_03!$C$11,$M$1,$B21,$K$1) -> 0
B22: Câmbio Inicial ARS$/US$ | C22: =_xll.DBRW($C$2,Input_Prod_03!$D$9,Input_Prod_03!$C$11,$M$1,$B22,$K$1) -> 0 | D22: =_xll.DBRW($C$2,Input_Prod_03!$D$9,Input_Prod_03!$C$11,$M$1,$B22,$K$1) -> 0 | E22: =_xll.DBRW($C$2,Input_Prod_03!$D$9,Input_Prod_03!$C$11,$M$1,$B22,$K$1) -> 0 | F22: =_xll.DBRW($C$2,Input_Prod_03!$D$9,Input_Prod_03!$C$11,$M$1,$B22,$K$1) -> 0 | G22: =_xll.DBRW($C$2,Input_Prod_03!$D$9,Input_Prod_03!$C$11,$M$1,$B22,$K$1) -> 0 | H22: =_xll.DBRW($C$2,Input_Prod_03!$D$9,Input_Prod_03!$C$11,$M$1,$B22,$K$1) -> 0 | I22: =_xll.DBRW($C$2,Input_Prod_03!$D$9,Input_Prod_03!$C$11,$M$1,$B22,$K$1) -> 0 | J22: =_xll.DBRW($C$2,Input_Prod_03!$D$9,Input_Prod_03!$C$11,$M$1,$B22,$K$1) -> 0 | ... N22: =_xll.DBRW($C$2,Input_Prod_03!$D$9,Input_Prod_03!$C$11,$M$1,$B22,$K$1) -> 0
B23: Câmbio Médio ARS$/US$ | C23: =_xll.DBRW($C$2,Input_Prod_03!$D$9,Input_Prod_03!$C$11,$M$1,$B23,$K$1) -> 0 | D23: =_xll.DBRW($C$2,Input_Prod_03!$D$9,Input_Prod_03!$C$11,$M$1,$B23,$K$1) -> 0 | E23: =_xll.DBRW($C$2,Input_Prod_03!$D$9,Input_Prod_03!$C$11,$M$1,$B23,$K$1) -> 0 | F23: =_xll.DBRW($C$2,Input_Prod_03!$D$9,Input_Prod_03!$C$11,$M$1,$B23,$K$1) -> 0 | G23: =_xll.DBRW($C$2,Input_Prod_03!$D$9,Input_Prod_03!$C$11,$M$1,$B23,$K$1) -> 0 | H23: =_xll.DBRW($C$2,Input_Prod_03!$D$9,Input_Prod_03!$C$11,$M$1,$B23,$K$1) -> 0 | I23: =_xll.DBRW($C$2,Input_Prod_03!$D$9,Input_Prod_03!$C$11,$M$1,$B23,$K$1) -> 0 | J23: =_xll.DBRW($C$2,Input_Prod_03!$D$9,Input_Prod_03!$C$11,$M$1,$B23,$K$1) -> 0 | ... N23: =_xll.DBRW($C$2,Input_Prod_03!$D$9,Input_Prod_03!$C$11,$M$1,$B23,$K$1) -> 0
B24: Câmbio Final ARS$/US$ | C24: =_xll.DBRW($C$2,Input_Prod_03!$D$9,Input_Prod_03!$C$11,$M$1,$B24,$K$1) -> 0 | D24: =_xll.DBRW($C$2,Input_Prod_03!$D$9,Input_Prod_03!$C$11,$M$1,$B24,$K$1) -> 0 | E24: =_xll.DBRW($C$2,Input_Prod_03!$D$9,Input_Prod_03!$C$11,$M$1,$B24,$K$1) -> 0 | F24: =_xll.DBRW($C$2,Input_Prod_03!$D$9,Input_Prod_03!$C$11,$M$1,$B24,$K$1) -> 0 | G24: =_xll.DBRW($C$2,Input_Prod_03!$D$9,Input_Prod_03!$C$11,$M$1,$B24,$K$1) -> 0 | H24: =_xll.DBRW($C$2,Input_Prod_03!$D$9,Input_Prod_03!$C$11,$M$1,$B24,$K$1) -> 0 | I24: =_xll.DBRW($C$2,Input_Prod_03!$D$9,Input_Prod_03!$C$11,$M$1,$B24,$K$1) -> 0 | J24: =_xll.DBRW($C$2,Input_Prod_03!$D$9,Input_Prod_03!$C$11,$M$1,$B24,$K$1) -> 0 | ... N24: =_xll.DBRW($C$2,Input_Prod_03!$D$9,Input_Prod_03!$C$11,$M$1,$B24,$K$1) -> 0
... B27: Number of Days | C27: =_xll.DBRW($C$2,Input_Prod_03!$D$9,Input_Prod_03!$C$11,$M$1,$B27,$K$1) -> 31 | D27: =_xll.DBRW($C$2,Input_Prod_03!$D$9,Input_Prod_03!$C$11,$M$1,$B27,$K$1) -> 31 | E27: =_xll.DBRW($C$2,Input_Prod_03!$D$9,Input_Prod_03!$C$11,$M$1,$B27,$K$1) -> 31 | F27: =_xll.DBRW($C$2,Input_Prod_03!$D$9,Input_Prod_03!$C$11,$M$1,$B27,$K$1) -> 31 | G27: =_xll.DBRW($C$2,Input_Prod_03!$D$9,Input_Prod_03!$C$11,$M$1,$B27,$K$1) -> 31 | H27: =_xll.DBRW($C$2,Input_Prod_03!$D$9,Input_Prod_03!$C$11,$M$1,$B27,$K$1) -> 31 | I27: =_xll.DBRW($C$2,Input_Prod_03!$D$9,Input_Prod_03!$C$11,$M$1,$B27,$K$1) -> 31 | J27: =_xll.DBRW($C$2,Input_Prod_03!$D$9,Input_Prod_03!$C$11,$M$1,$B27,$K$1) -> 31 | ... N27: =_xll.DBRW($C$2,Input_Prod_03!$D$9,Input_Prod_03!$C$11,$M$1,$B27,$K$1) -> 31
B30: NET REVENUES | D30: Products: | E30: =_xll.SUBNM("CONS_VC:ALL.D.Products","Nivel_0","PRODAG010 - Aggregates","Código e Descrição") -> PRODAG010 - Aggregates
C33: =$D$9&"."&C11 -> 2026.01 | D33: =$D$9&"."&D11 -> 2026.02 | E33: =$D$9&"."&E11 -> 2026.03 | F33: =$D$9&"."&F11 -> 2026.04 | G33: =$D$9&"."&G11 -> 2026.05 | H33: =$D$9&"."&H11 -> 2026.06 | I33: =$D$9&"."&I11 -> 2026.07 | J33: =$D$9&"."&J11 -> 2026.08 | ... N33: =$D$9&"."&N11 -> 2026.12
B34: Reference Price [$/ton] | C34: =_xll.DBRW($B$1,Input_Prod_03!$D$9,Input_Prod_03!C$11,$M$1,Input_Prod_03!$G$9,$J$9,Input_Prod_03!$E$30,Input_Prod_03!$B34,$L$1,$K$1) -> 0 | D34: =_xll.DBRW($B$1,Input_Prod_03!$D$9,Input_Prod_03!D$11,$M$1,Input_Prod_03!$G$9,$J$9,Input_Prod_03!$E$30,Input_Prod_03!$B34,$L$1,$K$1) -> 0 | E34: =_xll.DBRW($B$1,Input_Prod_03!$D$9,Input_Prod_03!E$11,$M$1,Input_Prod_03!$G$9,$J$9,Input_Prod_03!$E$30,Input_Prod_03!$B34,$L$1,$K$1) -> 0 | F34: =_xll.DBRW($B$1,Input_Prod_03!$D$9,Input_Prod_03!F$11,$M$1,Input_Prod_03!$G$9,$J$9,Input_Prod_03!$E$30,Input_Prod_03!$B34,$L$1,$K$1) -> 0 | G34: =_xll.DBRW($B$1,Input_Prod_03!$D$9,Input_Prod_03!G$11,$M$1,Input_Prod_03!$G$9,$J$9,Input_Prod_03!$E$30,Input_Prod_03!$B34,$L$1,$K$1) -> 0 | H34: =_xll.DBRW($B$1,Input_Prod_03!$D$9,Input_Prod_03!H$11,$M$1,Input_Prod_03!$G$9,$J$9,Input_Prod_03!$E$30,Input_Prod_03!$B34,$L$1,$K$1) -> 0 | I34: =_xll.DBRW($B$1,Input_Prod_03!$D$9,Input_Prod_03!I$11,$M$1,Input_Prod_03!$G$9,$J$9,Input_Prod_03!$E$30,Input_Prod_03!$B34,$L$1,$K$1) -> 0 | J34: =_xll.DBRW($B$1,Input_Prod_03!$D$9,Input_Prod_03!J$11,$M$1,Input_Prod_03!$G$9,$J$9,Input_Prod_03!$E$30,Input_Prod_03!$B34,$L$1,$K$1) -> 0 | ... N34: =_xll.DBRW($B$1,Input_Prod_03!$D$9,Input_Prod_03!N$11,$M$1,Input_Prod_03!$G$9,$J$9,Input_Prod_03!$E$30,Input_Prod_03!$B34,$L$1,$K$1) -> 0
