Workbook
Name Current_year: #REF!
Name CurrentForecast: #REF!
Name CurrentForecast: #REF!
Name CurrentMonth: #REF!
Name CurrentMonth: #REF!
Name Currentyear: #REF!
Name CurrentYear: #REF!
Name mes: #REF!
Name Month: #REF!
Name MonthName: #REF!
Name PriorYear: #REF!
Name PriorYear: #REF!
Name TM1RPTDATARNG4065595: 'EBITDA - Fx'!$23:$23
Name TM1RPTFMTIDCOL4065595: 'EBITDA - Fx'!$A$1:$A$10
Name TM1RPTFMTRNG4065595: 'EBITDA - Fx'!$B$1:$F$10
Name TM1RPTQRYRNG4065595: 'EBITDA - Fx'!$B$11
Name TM1RPTVIEWRNG4065595: 'EBITDA - Fx'!$B$12

Sheet Cognos_Office_Connection_Cache
B1: [Modelo Global Result.xlsx]Value Tree 1 - Fx'!A23
B2: Global
B3: VCBR
B4: VCEAA
B5: CORP
B6: ESPA
B7: TURK
B8: VCLATAM
B9: ARTI
B10: ITACA
B11: VCNA
B12: VCOTHERS
... B33: VCNA

Sheet Home

Sheet Summary  - Fx
A1: Cubo
A2: CONS_VC:DFS.200.KPIs
A3: CONS_VC:DFS.100.Profit_and_loss
A4: CONS_VC:DFS.140.Indirect_Cash_Flow
A5: CONS_VC:DFS.180.Gross_Debt
A6: CONS_VC:REV.100.Revenue_Consolidated
A8: Ano
A9: =_xll.SUBNM("CONS_VC:ALL.D.Year","","2025") -> RECALC_0_7_
A11: Mês
A12: =_xll.SUBNM("CONS_VC:ALL.D.Month",,"Total YTD","MEMBER_NAME") -> RECALC_0_9_
A13: =_xll.SUBNM("CONS_VC:ALL.D.Month",,"Year","MEMBER_NAME") -> RECALC_0_10_
A14: =_xll.SUBNM("CONS_VC:ALL.D.Month",,"01","MEMBER_NAME") -> RECALC_0_494_
A16: Versão
A22: Currency
A23: =_xll.SUBNM("CONS_VC:ALL.D.Currency","","BRL Conv.") -> RECALC_0_496_
A24: =_xll.SUBNM("CONS_VC:ALL.D.Currency","","USD Conv.") -> RECALC_0_497_
A25: =_xll.SUBNM("CONS_VC:ALL.D.Currency","","EUR Conv.") -> RECALC_0_498_
A28: Region
A29: =_xll.SUBNM("CONS_VC:ALL.D.Region","","Global") -> RECALC_0_495_
A30: VCBR
A31: VCNA
A32: VCEAA
A33: VCLATAM
A35: Produto
A36: =_xll.SUBNM("CONS_VC:ALL.D.Products","","Total Products") -> RECALC_0_11_
A38: Accounts_PNL
A39: Net Profit
A41: Accounts_ICF
A42: Change in cash
A45: DFS.100.Profil_and_Loss
A46: Global EBITDA Month | B46: Formato
A47: {=_xll.DBR($A$3,$A$9,$A$14,Summary!$L$4,$A$23,$A$29,$A$36,"EBITDA","Total Value")} -> RECALC_1_501_ | B47: ="R$ "& ROUND(A47,0) & " M" -> #VALUE!
A48: {=IFERROR((_xll.DBR($A$3,$A$9,$A$14,Summary!$L$4,$A$23,$A$29,$A$36,"EBITDA","Total Value") - _xll.DBR($A$3,$A$9,$A$14,Summary!$N$4,$A$23,$A$29,$A$36,"EBITDA","Total Value"))/ _xll.DBR($A$3,$A$9,$A$14,Summary!$N$4,$A$23,$A$29,$A$36,"EBITDA","Total Value"),0) &"%" & " vs. Budget"} -> 0% vs. Budget
A50: Global EBITDA YTD | B50: Formato
A51: {=_xll.DBR($A$3,$A$9,$A$12,Summary!$L$4,$A$23,$A$29,$A$36,"EBITDA","Total Value")} -> RECALC_1_522_ | B51: ="R$ "& ROUND(A51,0) & " M" -> #VALUE!
A52: {=IFERROR((_xll.DBR($A$3,$A$9,$A$12,Summary!$L$4,$A$23,$A$29,$A$36,"EBITDA","Total Value") - _xll.DBR($A$3,$A$9,$A$12,Summary!$N$4,$A$23,$A$29,$A$36,"EBITDA","Total Value"))/ _xll.DBR($A$3,$A$9,$A$12,Summary!$N$4,$A$23,$A$29,$A$36,"EBITDA","Total Value"),0) &"%" & " vs. Budget"} -> 0% vs. Budget
A54: Global EBITDA Full Year | B54: Formato
A55: {=_xll.DBR($A$3,$A$9,$A$13,Summary!$L$4,$A$23,$A$29,$A$36,"EBITDA","Total Value")} -> RECALC_1_504_ | B55: ="R$ "& ROUND(A55,0) & " M" -> #VALUE!
A56: {=IFERROR((_xll.DBR($A$3,$A$9,$A$13,Summary!$L$4,$A$23,$A$29,$A$36,"EBITDA","Total Value") - _xll.DBR($A$3,$A$9,$A$13,Summary!$N$4,$A$23,$A$29,$A$36,"EBITDA","Total Value"))/ _xll.DBR($A$3,$A$9,$A$13,Summary!$N$4,$A$23,$A$29,$A$36,"EBITDA","Total Value"),0) &"%" & " vs. Budget"} -> 0% vs. Budget
A58: Regions | B58: Formato
A59: VCBR
A60: {=_xll.DBR($A$3,$A$9,$A$14,Summary!$J$4,$A$23,$A$30,$A$36,"EBITDA","Total Value")} -> RECALC_1_512_ | B60: L300
A61: {=_xll.DBR($A$3,$A$9,$A$14,Summary!$L$4,$A$23,$A$30,$A$36,"EBITDA","Total Value")} -> RECALC_1_509_ | B61: RF
A62: =IFERROR((A60-A61)/A61,0) -> 0
A64: VCBR
A65: {=_xll.DBR($A$3,$A$9,$A$12,Summary!$J$4,$A$23,$A$30,$A$36,"EBITDA","Total Value")} -> RECALC_1_506_ | B65: L300
A66: {=_xll.DBR($A$3,$A$9,$A$12,Summary!$L$4,$A$23,$A$30,$A$36,"EBITDA","Total Value")} -> RECALC_1_503_ | B66: RF
A67: =IFERROR((A65-A66)/A66,0) -> 0
A69: VCBR
A70: {=_xll.DBR($A$3,$A$9,$A$13,Summary!$J$4,$A$23,$A$30,$A$36,"EBITDA","Total Value")} -> RECALC_1_519_ | B70: L300
A71: {=_xll.DBR($A$3,$A$9,$A$13,Summary!$L$4,$A$23,$A$30,$A$36,"EBITDA","Total Value")} -> RECALC_1_518_ | B71: RF
A72: {=_xll.DBR($A$3,$A$9,$A$13,Summary!$L$4,$A$23,$A$30,$A$36,B72,"Total Value")} -> RECALC_1_500_ | B72: EBITDA Econômico
A74: VCNA
A75: {=_xll.DBR($A$3,$A$9,$A$14,Summary!$J$4,$A$24,$A$31,$A$36,"EBITDA","Total Value")} -> RECALC_1_514_ | B75: L300
A76: {=_xll.DBR($A$3,$A$9,$A$14,Summary!$L$4,$A$24,$A$31,$A$36,"EBITDA","Total Value")} -> RECALC_1_511_ | B76: RF
A77: =IFERROR((A75-A76)/A76,0) -> 0
A79: VCNA
A80: {=_xll.DBR($A$3,$A$9,$A$12,Summary!$J$4,$A$24,$A$31,$A$36,"EBITDA","Total Value")} -> RECALC_1_517_ | B80: L300
A81: {=_xll.DBR($A$3,$A$9,$A$12,Summary!$L$4,$A$24,$A$31,$A$36,"EBITDA","Total Value")} -> RECALC_1_508_ | B81: RF
A82: =IFERROR((A80-A81)/A81,0) -> 0
A84: VCNA
A85: {=_xll.DBR($A$3,$A$9,$A$13,Summary!$J$4,$A$24,$A$31,$A$36,"EBITDA","Total Value")} -> RECALC_1_516_ | B85: L300
A86: {=_xll.DBR($A$3,$A$9,$A$13,Summary!$L$4,$A$24,$A$31,$A$36,"EBITDA","Total Value")} -> RECALC_1_507_ | B86: RF
A87: {=_xll.DBR($A$3,$A$9,$A$13,Summary!$L$4,$A$24,$A$31,$A$36,B87,"Total Value")} -> RECALC_1_499_ | B87: EBITDA Econômico
A88: =IFERROR((A86-A87)/A87,0) -> 0
A90: VCEA
A91: {=_xll.DBR($A$3,$A$9,$A$14,Summary!$J$4,$A$25,$A$32,$A$36,"EBITDA","Total Value")} -> RECALC_1_510_ | B91: L300
A92: {=_xll.DBR($A$3,$A$9,$A$14,Summary!$L$4,$A$25,$A$32,$A$36,"EBITDA","Total Value")} -> RECALC_1_515_ | B92: RF
A93: =IFERROR((#REF!-#REF!)/#REF!,0) -> 0
A95: VCEA
A96: {=_xll.DBR($A$3,$A$9,$A$12,Summary!$J$4,$A$25,$A$32,$A$36,"EBITDA","Total Value")} -> RECALC_1_505_ | B96: L300
A97: {=_xll.DBR($A$3,$A$9,$A$12,Summary!$L$4,$A$25,$A$32,$A$36,"EBITDA","Total Value")} -> RECALC_1_521_ | B97: RF
A98: =IFERROR((A96-A97)/A97,0) -> 0
A100: VCEA
A101: {=_xll.DBR($A$3,$A$9,$A$13,Summary!$J$4,$A$25,$A$32,$A$36,"EBITDA","Total Value")} -> RECALC_1_520_ | B101: L300
A102: =_xll.DBR($A$3,$A$9,$A$13,Summary!$L$4,$A$25,$A$32,$A$36,"EBITDA","Total Value") -> RECALC_1_524_ | B102: RF
A103: {=_xll.DBR($A$3,$A$9,$A$13,Summary!$L$4,$A$25,$A$32,$A$36,B103,"Total Value")} -> RECALC_1_525_ | B103: EBITDA Econômico
A104: =IFERROR((A101-A102)/A102,0) -> 0
A106: VCLatam
A107: {=_xll.DBR($A$3,$A$9,$A$14,Summary!$J$4,$A$24,$A$33,$A$36,"EBITDA","Total Value")} -> RECALC_1_526_ | B107: L300
A108: {=_xll.DBR($A$3,$A$9,$A$14,Summary!$L$4,$A$24,$A$33,$A$36,"EBITDA","Total Value")} -> RECALC_1_528_ | B108: RF
A109: =IFERROR((#REF!-#REF!)/#REF!,0) -> 0
A111: VCLatam
A112: {=_xll.DBR($A$3,$A$9,$A$12,Summary!$J$4,$A$24,$A$33,$A$36,"EBITDA","Total Value")} -> RECALC_1_527_ | B112: L300
A113: {=_xll.DBR($A$3,$A$9,$A$12,Summary!$L$4,$A$24,$A$33,$A$36,"EBITDA","Total Value")} -> RECALC_1_529_ | B113: RF
A114: =IFERROR((A112-A113)/A113,0) -> 0
A116: VCLatam
A117: {=_xll.DBR($A$3,$A$9,$A$13,Summary!$J$4,$A$24,$A$33,$A$36,"EBITDA","Total Value")} -> RECALC_1_530_ | B117: L300
A118: =_xll.DBR($A$3,$A$9,$A$13,Summary!$L$4,$A$24,$A$33,$A$36,"EBITDA","Total Value") -> RECALC_1_533_ | B118: RF
A119: {=_xll.DBR($A$3,$A$9,$A$13,Summary!$L$4,$A$24,$A$33,$A$36,B119,"Total Value")} -> RECALC_1_532_ | B119: EBITDA Econômico
A120: =IFERROR((A117-A118)/A118,0) -> 0

Sheet Summary
D2: Summary
D4: Global EBITDA | J4: =_xll.SUBNM("CONS_VC:ALL.D.Version",,"L300","MEMBER_NAME") -> RECALC_0_4_ | L4: =_xll.SUBNM("CONS_VC:ALL.D.Version",,"RF","Descrição") -> RECALC_0_5_ | N4: Budget
I6: Regions EBITDA
D7: Month
D16: YTD
D28: Full Year

Sheet Cement Volumes & Prices - Fx
A1: =_xll.VIEW("CONS_VC:REV.100.Revenue_Consolidated",$A$2,"!","!",$A$9,$A$10,'Cement Volumes & Prices'!$O$3,$A$4,$A$11) -> CONS_VC:REV.100.Revenue_Consolidated:205767106-196713936
A2: ='Cement Volumes & Prices'!$L$3 -> RECALC_0_531_
A4: =_xll.SUBNM("CONS_VC:ALL.D.Market","","Total Market") -> RECALC_0_573_
A9: =_xll.SUBNM("CONS_VC:ALL.D.Currency","Default","BRL","MEMBER_NAME") -> RECALC_0_33_ | C9: Jan | D9: Feb | E9: Mar | F9: Apr | G9: May | H9: Jun | I9: Jul | J9: Aug | K9: Sep | L9: Oct | M9: Nov | N9: Dec
A10: =_xll.SUBNM("CONS_VC:ALL.D.Region","Default","VCBR","MEMBER_NAME") -> RECALC_0_577_ | B10: ='Cement Volumes & Prices'!$S$3 -> RECALC_0_536_ | C10: =_xll.DBRW($A$1,$A$2,C$9,$B10,$A9,$A10,'Cement Volumes & Prices'!$O$3,$A$4,$A11) -> RECALC_1_631_ | D10: =_xll.DBRW($A$1,$A$2,D$9,$B10,$A9,$A10,'Cement Volumes & Prices'!$O$3,$A$4,$A11) -> RECALC_1_783_ | E10: =_xll.DBRW($A$1,$A$2,E$9,$B10,$A9,$A10,'Cement Volumes & Prices'!$O$3,$A$4,$A11) -> RECALC_1_662_ | F10: =_xll.DBRW($A$1,$A$2,F$9,$B10,$A9,$A10,'Cement Volumes & Prices'!$O$3,$A$4,$A11) -> RECALC_1_711_ | G10: =_xll.DBRW($A$1,$A$2,G$9,$B10,$A9,$A10,'Cement Volumes & Prices'!$O$3,$A$4,$A11) -> RECALC_1_785_ | H10: =_xll.DBRW($A$1,$A$2,H$9,$B10,$A9,$A10,'Cement Volumes & Prices'!$O$3,$A$4,$A11) -> RECALC_1_749_ | I10: =_xll.DBRW($A$1,$A$2,I$9,$B10,$A9,$A10,'Cement Volumes & Prices'!$O$3,$A$4,$A11) -> RECALC_1_691_ | J10: =_xll.DBRW($A$1,$A$2,J$9,$B10,$A9,$A10,'Cement Volumes & Prices'!$O$3,$A$4,$A11) -> RECALC_1_731_ | ... N10: =_xll.DBRW($A$1,$A$2,N$9,$B10,$A9,$A10,'Cement Volumes & Prices'!$O$3,$A$4,$A11) -> RECALC_1_730_
A11: =_xll.SUBNM("CONS_VC:REV.M.100.Revenue_Consolidated","Default","Sales Volume [kt]") -> RECALC_0_562_ | B11: ='Cement Volumes & Prices'!$U$3 -> RECALC_0_537_ | C11: =_xll.DBRW($A$1,$A$2,C$9,$B11,$A9,$A10,'Cement Volumes & Prices'!$O$3,$A$4,$A11) -> RECALC_1_647_ | D11: =_xll.DBRW($A$1,$A$2,D$9,$B11,$A9,$A10,'Cement Volumes & Prices'!$O$3,$A$4,$A11) -> RECALC_1_757_ | E11: =_xll.DBRW($A$1,$A$2,E$9,$B11,$A9,$A10,'Cement Volumes & Prices'!$O$3,$A$4,$A11) -> RECALC_1_602_ | F11: =_xll.DBRW($A$1,$A$2,F$9,$B11,$A9,$A10,'Cement Volumes & Prices'!$O$3,$A$4,$A11) -> RECALC_1_714_ | G11: =_xll.DBRW($A$1,$A$2,G$9,$B11,$A9,$A10,'Cement Volumes & Prices'!$O$3,$A$4,$A11) -> RECALC_1_734_ | H11: =_xll.DBRW($A$1,$A$2,H$9,$B11,$A9,$A10,'Cement Volumes & Prices'!$O$3,$A$4,$A11) -> RECALC_1_645_ | I11: =_xll.DBRW($A$1,$A$2,I$9,$B11,$A9,$A10,'Cement Volumes & Prices'!$O$3,$A$4,$A11) -> RECALC_1_614_ | J11: =_xll.DBRW($A$1,$A$2,J$9,$B11,$A9,$A10,'Cement Volumes & Prices'!$O$3,$A$4,$A11) -> RECALC_1_651_ | ... N11: =_xll.DBRW($A$1,$A$2,N$9,$B11,$A9,$A10,'Cement Volumes & Prices'!$O$3,$A$4,$A11) -> RECALC_1_621_
A13: =_xll.SUBNM("CONS_VC:ALL.D.Currency","Default","USD","MEMBER_NAME") -> RECALC_0_561_ | C13: Jan | D13: Feb | E13: Mar | F13: Apr | G13: May | H13: Jun | I13: Jul | J13: Aug | K13: Sep | L13: Oct | M13: Nov | N13: Dec
A14: =_xll.SUBNM("CONS_VC:ALL.D.Region","Default","VCNA","MEMBER_NAME") -> RECALC_0_571_ | B14: ='Cement Volumes & Prices'!$S$3 -> RECALC_0_536_ | C14: =_xll.DBRW($A$1,$A$2,C$9,$B14,$A13,$A14,'Cement Volumes & Prices'!$O$3,$A$4,$A15) -> RECALC_1_637_ | D14: =_xll.DBRW($A$1,$A$2,D$9,$B14,$A13,$A14,'Cement Volumes & Prices'!$O$3,$A$4,$A15) -> RECALC_1_649_ | E14: =_xll.DBRW($A$1,$A$2,E$9,$B14,$A13,$A14,'Cement Volumes & Prices'!$O$3,$A$4,$A15) -> RECALC_1_608_ | F14: =_xll.DBRW($A$1,$A$2,F$9,$B14,$A13,$A14,'Cement Volumes & Prices'!$O$3,$A$4,$A15) -> RECALC_1_673_ | G14: =_xll.DBRW($A$1,$A$2,G$9,$B14,$A13,$A14,'Cement Volumes & Prices'!$O$3,$A$4,$A15) -> RECALC_1_773_ | H14: =_xll.DBRW($A$1,$A$2,H$9,$B14,$A13,$A14,'Cement Volumes & Prices'!$O$3,$A$4,$A15) -> RECALC_1_703_ | I14: =_xll.DBRW($A$1,$A$2,I$9,$B14,$A13,$A14,'Cement Volumes & Prices'!$O$3,$A$4,$A15) -> RECALC_1_716_ | J14: =_xll.DBRW($A$1,$A$2,J$9,$B14,$A13,$A14,'Cement Volumes & Prices'!$O$3,$A$4,$A15) -> RECALC_1_725_ | ... N14: =_xll.DBRW($A$1,$A$2,N$9,$B14,$A13,$A14,'Cement Volumes & Prices'!$O$3,$A$4,$A15) -> RECALC_1_664_
A15: =_xll.SUBNM("CONS_VC:REV.M.100.Revenue_Consolidated","Default","Sales Volume [kt]") -> RECALC_0_562_ | B15: ='Cement Volumes & Prices'!$U$3 -> RECALC_0_537_ | C15: =_xll.DBRW($A$1,$A$2,C$9,$B15,$A13,$A14,'Cement Volumes & Prices'!$O$3,$A$4,$A15) -> RECALC_1_782_ | D15: =_xll.DBRW($A$1,$A$2,D$9,$B15,$A13,$A14,'Cement Volumes & Prices'!$O$3,$A$4,$A15) -> RECALC_1_635_ | E15: =_xll.DBRW($A$1,$A$2,E$9,$B15,$A13,$A14,'Cement Volumes & Prices'!$O$3,$A$4,$A15) -> RECALC_1_619_ | F15: =_xll.DBRW($A$1,$A$2,F$9,$B15,$A13,$A14,'Cement Volumes & Prices'!$O$3,$A$4,$A15) -> RECALC_1_625_ | G15: =_xll.DBRW($A$1,$A$2,G$9,$B15,$A13,$A14,'Cement Volumes & Prices'!$O$3,$A$4,$A15) -> RECALC_1_790_ | H15: =_xll.DBRW($A$1,$A$2,H$9,$B15,$A13,$A14,'Cement Volumes & Prices'!$O$3,$A$4,$A15) -> RECALC_1_661_ | I15: =_xll.DBRW($A$1,$A$2,I$9,$B15,$A13,$A14,'Cement Volumes & Prices'!$O$3,$A$4,$A15) -> RECALC_1_607_ | J15: =_xll.DBRW($A$1,$A$2,J$9,$B15,$A13,$A14,'Cement Volumes & Prices'!$O$3,$A$4,$A15) -> RECALC_1_756_ | ... N15: =_xll.DBRW($A$1,$A$2,N$9,$B15,$A13,$A14,'Cement Volumes & Prices'!$O$3,$A$4,$A15) -> RECALC_1_626_
A17: =_xll.SUBNM("CONS_VC:ALL.D.Currency","Default","EUR","MEMBER_NAME") -> RECALC_0_574_ | C17: Jan | D17: Feb | E17: Mar | F17: Apr | G17: May | H17: Jun | I17: Jul | J17: Aug | K17: Sep | L17: Oct | M17: Nov | N17: Dec
A18: =_xll.SUBNM("CONS_VC:ALL.D.Region","Default","VCEAA","MEMBER_NAME") -> RECALC_0_579_ | B18: ='Cement Volumes & Prices'!$S$3 -> RECALC_0_536_ | C18: =_xll.DBRW($A$1,$A$2,C$9,$B18,$A17,$A18,'Cement Volumes & Prices'!$O$3,$A$4,$A19) -> RECALC_1_692_ | D18: =_xll.DBRW($A$1,$A$2,D$9,$B18,$A17,$A18,'Cement Volumes & Prices'!$O$3,$A$4,$A19) -> RECALC_1_613_ | E18: =_xll.DBRW($A$1,$A$2,E$9,$B18,$A17,$A18,'Cement Volumes & Prices'!$O$3,$A$4,$A19) -> RECALC_1_786_ | F18: =_xll.DBRW($A$1,$A$2,F$9,$B18,$A17,$A18,'Cement Volumes & Prices'!$O$3,$A$4,$A19) -> RECALC_1_776_ | G18: =_xll.DBRW($A$1,$A$2,G$9,$B18,$A17,$A18,'Cement Volumes & Prices'!$O$3,$A$4,$A19) -> RECALC_1_685_ | H18: =_xll.DBRW($A$1,$A$2,H$9,$B18,$A17,$A18,'Cement Volumes & Prices'!$O$3,$A$4,$A19) -> RECALC_1_766_ | I18: =_xll.DBRW($A$1,$A$2,I$9,$B18,$A17,$A18,'Cement Volumes & Prices'!$O$3,$A$4,$A19) -> RECALC_1_609_ | J18: =_xll.DBRW($A$1,$A$2,J$9,$B18,$A17,$A18,'Cement Volumes & Prices'!$O$3,$A$4,$A19) -> RECALC_1_754_ | ... N18: =_xll.DBRW($A$1,$A$2,N$9,$B18,$A17,$A18,'Cement Volumes & Prices'!$O$3,$A$4,$A19) -> RECALC_1_671_
A19: =_xll.SUBNM("CONS_VC:REV.M.100.Revenue_Consolidated","Default","Sales Volume [kt]") -> RECALC_0_562_ | B19: ='Cement Volumes & Prices'!$U$3 -> RECALC_0_537_ | C19: =_xll.DBRW($A$1,$A$2,C$9,$B19,$A17,$A18,'Cement Volumes & Prices'!$O$3,$A$4,$A19) -> RECALC_1_717_ | D19: =_xll.DBRW($A$1,$A$2,D$9,$B19,$A17,$A18,'Cement Volumes & Prices'!$O$3,$A$4,$A19) -> RECALC_1_760_ | E19: =_xll.DBRW($A$1,$A$2,E$9,$B19,$A17,$A18,'Cement Volumes & Prices'!$O$3,$A$4,$A19) -> RECALC_1_615_ | F19: =_xll.DBRW($A$1,$A$2,F$9,$B19,$A17,$A18,'Cement Volumes & Prices'!$O$3,$A$4,$A19) -> RECALC_1_702_ | G19: =_xll.DBRW($A$1,$A$2,G$9,$B19,$A17,$A18,'Cement Volumes & Prices'!$O$3,$A$4,$A19) -> RECALC_1_696_ | H19: =_xll.DBRW($A$1,$A$2,H$9,$B19,$A17,$A18,'Cement Volumes & Prices'!$O$3,$A$4,$A19) -> RECALC_1_745_ | I19: =_xll.DBRW($A$1,$A$2,I$9,$B19,$A17,$A18,'Cement Volumes & Prices'!$O$3,$A$4,$A19) -> RECALC_1_670_ | J19: =_xll.DBRW($A$1,$A$2,J$9,$B19,$A17,$A18,'Cement Volumes & Prices'!$O$3,$A$4,$A19) -> RECALC_1_709_ | ... N19: =_xll.DBRW($A$1,$A$2,N$9,$B19,$A17,$A18,'Cement Volumes & Prices'!$O$3,$A$4,$A19) -> RECALC_1_737_
A21: =_xll.SUBNM("CONS_VC:ALL.D.Currency","Default","USD","MEMBER_NAME") -> RECALC_0_561_ | C21: Jan | D21: Feb | E21: Mar | F21: Apr | G21: May | H21: Jun | I21: Jul | J21: Aug | K21: Sep | L21: Oct | M21: Nov | N21: Dec
A22: =_xll.SUBNM("CONS_VC:ALL.D.Region","Default","VCLATAM Incl. AVEL","MEMBER_NAME") -> RECALC_0_580_ | B22: ='Cement Volumes & Prices'!$S$3 -> RECALC_0_536_ | C22: =_xll.DBRW($A$1,$A$2,C$9,$B22,$A21,$A22,'Cement Volumes & Prices'!$O$3,$A$4,$A23) -> RECALC_1_629_ | D22: =_xll.DBRW($A$1,$A$2,D$9,$B22,$A21,$A22,'Cement Volumes & Prices'!$O$3,$A$4,$A23) -> RECALC_1_656_ | E22: =_xll.DBRW($A$1,$A$2,E$9,$B22,$A21,$A22,'Cement Volumes & Prices'!$O$3,$A$4,$A23) -> RECALC_1_686_ | F22: =_xll.DBRW($A$1,$A$2,F$9,$B22,$A21,$A22,'Cement Volumes & Prices'!$O$3,$A$4,$A23) -> RECALC_1_774_ | G22: =_xll.DBRW($A$1,$A$2,G$9,$B22,$A21,$A22,'Cement Volumes & Prices'!$O$3,$A$4,$A23) -> RECALC_1_699_ | H22: =_xll.DBRW($A$1,$A$2,H$9,$B22,$A21,$A22,'Cement Volumes & Prices'!$O$3,$A$4,$A23) -> RECALC_1_603_ | I22: =_xll.DBRW($A$1,$A$2,I$9,$B22,$A21,$A22,'Cement Volumes & Prices'!$O$3,$A$4,$A23) -> RECALC_1_672_ | J22: =_xll.DBRW($A$1,$A$2,J$9,$B22,$A21,$A22,'Cement Volumes & Prices'!$O$3,$A$4,$A23) -> RECALC_1_761_ | ... N22: =_xll.DBRW($A$1,$A$2,N$9,$B22,$A21,$A22,'Cement Volumes & Prices'!$O$3,$A$4,$A23) -> RECALC_1_679_
A23: =_xll.SUBNM("CONS_VC:REV.M.100.Revenue_Consolidated","Default","Sales Volume [kt]") -> RECALC_0_562_ | B23: ='Cement Volumes & Prices'!$U$3 -> RECALC_0_537_ | C23: =_xll.DBRW($A$1,$A$2,C$9,$B23,$A21,$A22,'Cement Volumes & Prices'!$O$3,$A$4,$A23) -> RECALC_1_689_ | D23: =_xll.DBRW($A$1,$A$2,D$9,$B23,$A21,$A22,'Cement Volumes & Prices'!$O$3,$A$4,$A23) -> RECALC_1_648_ | E23: =_xll.DBRW($A$1,$A$2,E$9,$B23,$A21,$A22,'Cement Volumes & Prices'!$O$3,$A$4,$A23) -> RECALC_1_680_ | F23: =_xll.DBRW($A$1,$A$2,F$9,$B23,$A21,$A22,'Cement Volumes & Prices'!$O$3,$A$4,$A23) -> RECALC_1_750_ | G23: =_xll.DBRW($A$1,$A$2,G$9,$B23,$A21,$A22,'Cement Volumes & Prices'!$O$3,$A$4,$A23) -> RECALC_1_767_ | H23: =_xll.DBRW($A$1,$A$2,H$9,$B23,$A21,$A22,'Cement Volumes & Prices'!$O$3,$A$4,$A23) -> RECALC_1_683_ | I23: =_xll.DBRW($A$1,$A$2,I$9,$B23,$A21,$A22,'Cement Volumes & Prices'!$O$3,$A$4,$A23) -> RECALC_1_688_ | J23: =_xll.DBRW($A$1,$A$2,J$9,$B23,$A21,$A22,'Cement Volumes & Prices'!$O$3,$A$4,$A23) -> RECALC_1_610_ | ... N23: =_xll.DBRW($A$1,$A$2,N$9,$B23,$A21,$A22,'Cement Volumes & Prices'!$O$3,$A$4,$A23) -> RECALC_1_759_
A26: =_xll.SUBNM("CONS_VC:ALL.D.Currency","Default","BRL","MEMBER_NAME") -> RECALC_0_33_ | C26: Jan | D26: Feb | E26: Mar | F26: Apr | G26: May | H26: Jun | I26: Jul | J26: Aug | K26: Sep | L26: Oct | M26: Nov | N26: Dec
A27: =_xll.SUBNM("CONS_VC:ALL.D.Region","Default","VCBR","MEMBER_NAME") -> RECALC_0_577_ | B27: ='Cement Volumes & Prices'!$S$3 -> RECALC_0_536_ | C27: =_xll.DBRW($A$1,$A$2,C$9,$B27,$A26,$A27,'Cement Volumes & Prices'!$O$3,$A$4,$A28) -> RECALC_1_701_ | D27: =_xll.DBRW($A$1,$A$2,D$9,$B27,$A26,$A27,'Cement Volumes & Prices'!$O$3,$A$4,$A28) -> RECALC_1_618_ | E27: =_xll.DBRW($A$1,$A$2,E$9,$B27,$A26,$A27,'Cement Volumes & Prices'!$O$3,$A$4,$A28) -> RECALC_1_634_ | F27: =_xll.DBRW($A$1,$A$2,F$9,$B27,$A26,$A27,'Cement Volumes & Prices'!$O$3,$A$4,$A28) -> RECALC_1_650_ | G27: =_xll.DBRW($A$1,$A$2,G$9,$B27,$A26,$A27,'Cement Volumes & Prices'!$O$3,$A$4,$A28) -> RECALC_1_640_ | H27: =_xll.DBRW($A$1,$A$2,H$9,$B27,$A26,$A27,'Cement Volumes & Prices'!$O$3,$A$4,$A28) -> RECALC_1_605_ | I27: =_xll.DBRW($A$1,$A$2,I$9,$B27,$A26,$A27,'Cement Volumes & Prices'!$O$3,$A$4,$A28) -> RECALC_1_739_ | J27: =_xll.DBRW($A$1,$A$2,J$9,$B27,$A26,$A27,'Cement Volumes & Prices'!$O$3,$A$4,$A28) -> RECALC_1_744_ | ... N27: =_xll.DBRW($A$1,$A$2,N$9,$B27,$A26,$A27,'Cement Volumes & Prices'!$O$3,$A$4,$A28) -> RECALC_1_700_
A28: =_xll.SUBNM("CONS_VC:REV.M.100.Revenue_Consolidated","Default","Price Premium [$/ton]") -> RECALC_0_560_ | B28: ='Cement Volumes & Prices'!$U$3 -> RECALC_0_537_ | C28: =_xll.DBRW($A$1,$A$2,C$9,$B28,$A26,$A27,'Cement Volumes & Prices'!$O$3,$A$4,$A28) -> RECALC_1_636_ | D28: =_xll.DBRW($A$1,$A$2,D$9,$B28,$A26,$A27,'Cement Volumes & Prices'!$O$3,$A$4,$A28) -> RECALC_1_644_ | E28: =_xll.DBRW($A$1,$A$2,E$9,$B28,$A26,$A27,'Cement Volumes & Prices'!$O$3,$A$4,$A28) -> RECALC_1_713_ | F28: =_xll.DBRW($A$1,$A$2,F$9,$B28,$A26,$A27,'Cement Volumes & Prices'!$O$3,$A$4,$A28) -> RECALC_1_715_ | G28: =_xll.DBRW($A$1,$A$2,G$9,$B28,$A26,$A27,'Cement Volumes & Prices'!$O$3,$A$4,$A28) -> RECALC_1_655_ | H28: =_xll.DBRW($A$1,$A$2,H$9,$B28,$A26,$A27,'Cement Volumes & Prices'!$O$3,$A$4,$A28) -> RECALC_1_617_ | I28: =_xll.DBRW($A$1,$A$2,I$9,$B28,$A26,$A27,'Cement Volumes & Prices'!$O$3,$A$4,$A28) -> RECALC_1_752_ | J28: =_xll.DBRW($A$1,$A$2,J$9,$B28,$A26,$A27,'Cement Volumes & Prices'!$O$3,$A$4,$A28) -> RECALC_1_678_ | ... N28: =_xll.DBRW($A$1,$A$2,N$9,$B28,$A26,$A27,'Cement Volumes & Prices'!$O$3,$A$4,$A28) -> RECALC_1_770_
A30: =_xll.SUBNM("CONS_VC:ALL.D.Currency","Default","USD","MEMBER_NAME") -> RECALC_0_561_ | C30: Jan | D30: Feb | E30: Mar | F30: Apr | G30: May | H30: Jun | I30: Jul | J30: Aug | K30: Sep | L30: Oct | M30: Nov | N30: Dec
A31: =_xll.SUBNM("CONS_VC:ALL.D.Region","Default","VCNA","MEMBER_NAME") -> RECALC_0_571_ | B31: ='Cement Volumes & Prices'!$S$3 -> RECALC_0_536_ | C31: =_xll.DBRW($A$1,$A$2,C$9,$B31,$A30,$A31,'Cement Volumes & Prices'!$O$3,$A$4,$A32) -> RECALC_1_708_ | D31: =_xll.DBRW($A$1,$A$2,D$9,$B31,$A30,$A31,'Cement Volumes & Prices'!$O$3,$A$4,$A32) -> RECALC_1_720_ | E31: =_xll.DBRW($A$1,$A$2,E$9,$B31,$A30,$A31,'Cement Volumes & Prices'!$O$3,$A$4,$A32) -> RECALC_1_694_ | F31: =_xll.DBRW($A$1,$A$2,F$9,$B31,$A30,$A31,'Cement Volumes & Prices'!$O$3,$A$4,$A32) -> RECALC_1_657_ | G31: =_xll.DBRW($A$1,$A$2,G$9,$B31,$A30,$A31,'Cement Volumes & Prices'!$O$3,$A$4,$A32) -> RECALC_1_633_ | H31: =_xll.DBRW($A$1,$A$2,H$9,$B31,$A30,$A31,'Cement Volumes & Prices'!$O$3,$A$4,$A32) -> RECALC_1_764_ | I31: =_xll.DBRW($A$1,$A$2,I$9,$B31,$A30,$A31,'Cement Volumes & Prices'!$O$3,$A$4,$A32) -> RECALC_1_627_ | J31: =_xll.DBRW($A$1,$A$2,J$9,$B31,$A30,$A31,'Cement Volumes & Prices'!$O$3,$A$4,$A32) -> RECALC_1_665_ | ... N31: =_xll.DBRW($A$1,$A$2,N$9,$B31,$A30,$A31,'Cement Volumes & Prices'!$O$3,$A$4,$A32) -> RECALC_1_771_
A32: =_xll.SUBNM("CONS_VC:REV.M.100.Revenue_Consolidated","Default","Price Premium [$/ton]") -> RECALC_0_560_ | B32: ='Cement Volumes & Prices'!$U$3 -> RECALC_0_537_ | C32: =_xll.DBRW($A$1,$A$2,C$9,$B32,$A30,$A31,'Cement Volumes & Prices'!$O$3,$A$4,$A32) -> RECALC_1_693_ | D32: =_xll.DBRW($A$1,$A$2,D$9,$B32,$A30,$A31,'Cement Volumes & Prices'!$O$3,$A$4,$A32) -> RECALC_1_722_ | E32: =_xll.DBRW($A$1,$A$2,E$9,$B32,$A30,$A31,'Cement Volumes & Prices'!$O$3,$A$4,$A32) -> RECALC_1_604_ | F32: =_xll.DBRW($A$1,$A$2,F$9,$B32,$A30,$A31,'Cement Volumes & Prices'!$O$3,$A$4,$A32) -> RECALC_1_698_ | G32: =_xll.DBRW($A$1,$A$2,G$9,$B32,$A30,$A31,'Cement Volumes & Prices'!$O$3,$A$4,$A32) -> RECALC_1_630_ | H32: =_xll.DBRW($A$1,$A$2,H$9,$B32,$A30,$A31,'Cement Volumes & Prices'!$O$3,$A$4,$A32) -> RECALC_1_669_ | I32: =_xll.DBRW($A$1,$A$2,I$9,$B32,$A30,$A31,'Cement Volumes & Prices'!$O$3,$A$4,$A32) -> RECALC_1_763_ | J32: =_xll.DBRW($A$1,$A$2,J$9,$B32,$A30,$A31,'Cement Volumes & Prices'!$O$3,$A$4,$A32) -> RECALC_1_624_ | ... N32: =_xll.DBRW($A$1,$A$2,N$9,$B32,$A30,$A31,'Cement Volumes & Prices'!$O$3,$A$4,$A32) -> RECALC_1_781_
A34: =_xll.SUBNM("CONS_VC:ALL.D.Currency","Default","EUR","MEMBER_NAME") -> RECALC_0_574_ | C34: Jan | D34: Feb | E34: Mar | F34: Apr | G34: May | H34: Jun | I34: Jul | J34: Aug | K34: Sep | L34: Oct | M34: Nov | N34: Dec
A35: =_xll.SUBNM("CONS_VC:ALL.D.Region","Default","VCEAA","MEMBER_NAME") -> RECALC_0_579_ | B35: ='Cement Volumes & Prices'!$S$3 -> RECALC_0_536_ | C35: =_xll.DBRW($A$1,$A$2,C$9,$B35,$A34,$A35,'Cement Volumes & Prices'!$O$3,$A$4,$A36) -> RECALC_1_639_ | D35: =_xll.DBRW($A$1,$A$2,D$9,$B35,$A34,$A35,'Cement Volumes & Prices'!$O$3,$A$4,$A36) -> RECALC_1_726_ | E35: =_xll.DBRW($A$1,$A$2,E$9,$B35,$A34,$A35,'Cement Volumes & Prices'!$O$3,$A$4,$A36) -> RECALC_1_710_ | F35: =_xll.DBRW($A$1,$A$2,F$9,$B35,$A34,$A35,'Cement Volumes & Prices'!$O$3,$A$4,$A36) -> RECALC_1_616_ | G35: =_xll.DBRW($A$1,$A$2,G$9,$B35,$A34,$A35,'Cement Volumes & Prices'!$O$3,$A$4,$A36) -> RECALC_1_741_ | H35: =_xll.DBRW($A$1,$A$2,H$9,$B35,$A34,$A35,'Cement Volumes & Prices'!$O$3,$A$4,$A36) -> RECALC_1_652_ | I35: =_xll.DBRW($A$1,$A$2,I$9,$B35,$A34,$A35,'Cement Volumes & Prices'!$O$3,$A$4,$A36) -> RECALC_1_787_ | J35: =_xll.DBRW($A$1,$A$2,J$9,$B35,$A34,$A35,'Cement Volumes & Prices'!$O$3,$A$4,$A36) -> RECALC_1_784_ | ... N35: =_xll.DBRW($A$1,$A$2,N$9,$B35,$A34,$A35,'Cement Volumes & Prices'!$O$3,$A$4,$A36) -> RECALC_1_643_
A36: =_xll.SUBNM("CONS_VC:REV.M.100.Revenue_Consolidated","Default","Price Premium [$/ton]") -> RECALC_0_560_ | B36: ='Cement Volumes & Prices'!$U$3 -> RECALC_0_537_ | C36: =_xll.DBRW($A$1,$A$2,C$9,$B36,$A34,$A35,'Cement Volumes & Prices'!$O$3,$A$4,$A36) -> RECALC_1_732_ | D36: =_xll.DBRW($A$1,$A$2,D$9,$B36,$A34,$A35,'Cement Volumes & Prices'!$O$3,$A$4,$A36) -> RECALC_1_681_ | E36: =_xll.DBRW($A$1,$A$2,E$9,$B36,$A34,$A35,'Cement Volumes & Prices'!$O$3,$A$4,$A36) -> RECALC_1_632_ | F36: =_xll.DBRW($A$1,$A$2,F$9,$B36,$A34,$A35,'Cement Volumes & Prices'!$O$3,$A$4,$A36) -> RECALC_1_733_ | G36: =_xll.DBRW($A$1,$A$2,G$9,$B36,$A34,$A35,'Cement Volumes & Prices'!$O$3,$A$4,$A36) -> RECALC_1_758_ | H36: =_xll.DBRW($A$1,$A$2,H$9,$B36,$A34,$A35,'Cement Volumes & Prices'!$O$3,$A$4,$A36) -> RECALC_1_638_ | I36: =_xll.DBRW($A$1,$A$2,I$9,$B36,$A34,$A35,'Cement Volumes & Prices'!$O$3,$A$4,$A36) -> RECALC_1_677_ | J36: =_xll.DBRW($A$1,$A$2,J$9,$B36,$A34,$A35,'Cement Volumes & Prices'!$O$3,$A$4,$A36) -> RECALC_1_628_ | ... N36: =_xll.DBRW($A$1,$A$2,N$9,$B36,$A34,$A35,'Cement Volumes & Prices'!$O$3,$A$4,$A36) -> RECALC_1_658_
A38: =_xll.SUBNM("CONS_VC:ALL.D.Currency","Default","USD","MEMBER_NAME") -> RECALC_0_561_ | C38: Jan | D38: Feb | E38: Mar | F38: Apr | G38: May | H38: Jun | I38: Jul | J38: Aug | K38: Sep | L38: Oct | M38: Nov | N38: Dec
A39: =_xll.SUBNM("CONS_VC:ALL.D.Region","Default","VCLATAM Incl. AVEL","MEMBER_NAME") -> RECALC_0_580_ | B39: ='Cement Volumes & Prices'!$S$3 -> RECALC_0_536_ | C39: =_xll.DBRW($A$1,$A$2,C$9,$B39,$A38,$A39,'Cement Volumes & Prices'!$O$3,$A$4,$A40) -> RECALC_1_642_ | D39: =_xll.DBRW($A$1,$A$2,D$9,$B39,$A38,$A39,'Cement Volumes & Prices'!$O$3,$A$4,$A40) -> RECALC_1_718_ | E39: =_xll.DBRW($A$1,$A$2,E$9,$B39,$A38,$A39,'Cement Volumes & Prices'!$O$3,$A$4,$A40) -> RECALC_1_676_ | F39: =_xll.DBRW($A$1,$A$2,F$9,$B39,$A38,$A39,'Cement Volumes & Prices'!$O$3,$A$4,$A40) -> RECALC_1_777_ | G39: =_xll.DBRW($A$1,$A$2,G$9,$B39,$A38,$A39,'Cement Volumes & Prices'!$O$3,$A$4,$A40) -> RECALC_1_765_ | H39: =_xll.DBRW($A$1,$A$2,H$9,$B39,$A38,$A39,'Cement Volumes & Prices'!$O$3,$A$4,$A40) -> RECALC_1_740_ | I39: =_xll.DBRW($A$1,$A$2,I$9,$B39,$A38,$A39,'Cement Volumes & Prices'!$O$3,$A$4,$A40) -> RECALC_1_667_ | J39: =_xll.DBRW($A$1,$A$2,J$9,$B39,$A38,$A39,'Cement Volumes & Prices'!$O$3,$A$4,$A40) -> RECALC_1_727_ | ... N39: =_xll.DBRW($A$1,$A$2,N$9,$B39,$A38,$A39,'Cement Volumes & Prices'!$O$3,$A$4,$A40) -> RECALC_1_654_
A40: =_xll.SUBNM("CONS_VC:REV.M.100.Revenue_Consolidated","Default","Price Premium [$/ton]") -> RECALC_0_560_ | B40: ='Cement Volumes & Prices'!$U$3 -> RECALC_0_537_ | C40: =_xll.DBRW($A$1,$A$2,C$9,$B40,$A38,$A39,'Cement Volumes & Prices'!$O$3,$A$4,$A40) -> RECALC_1_653_ | D40: =_xll.DBRW($A$1,$A$2,D$9,$B40,$A38,$A39,'Cement Volumes & Prices'!$O$3,$A$4,$A40) -> RECALC_1_612_ | E40: =_xll.DBRW($A$1,$A$2,E$9,$B40,$A38,$A39,'Cement Volumes & Prices'!$O$3,$A$4,$A40) -> RECALC_1_723_ | F40: =_xll.DBRW($A$1,$A$2,F$9,$B40,$A38,$A39,'Cement Volumes & Prices'!$O$3,$A$4,$A40) -> RECALC_1_779_ | G40: =_xll.DBRW($A$1,$A$2,G$9,$B40,$A38,$A39,'Cement Volumes & Prices'!$O$3,$A$4,$A40) -> RECALC_1_663_ | H40: =_xll.DBRW($A$1,$A$2,H$9,$B40,$A38,$A39,'Cement Volumes & Prices'!$O$3,$A$4,$A40) -> RECALC_1_742_ | I40: =_xll.DBRW($A$1,$A$2,I$9,$B40,$A38,$A39,'Cement Volumes & Prices'!$O$3,$A$4,$A40) -> RECALC_1_719_ | J40: =_xll.DBRW($A$1,$A$2,J$9,$B40,$A38,$A39,'Cement Volumes & Prices'!$O$3,$A$4,$A40) -> RECALC_1_721_ | ... N40: =_xll.DBRW($A$1,$A$2,N$9,$B40,$A38,$A39,'Cement Volumes & Prices'!$O$3,$A$4,$A40) -> RECALC_1_687_

Sheet Cement Volumes & Prices
B3: =O3&" Volumes & Prices – Overview" -> RECALC_0_534_ Volumes & Prices – Overview | K3: Year: | L3: =_xll.SUBNM("CONS_VC:ALL.D.Year","Sys_Picklist","2026","MEMBER_NAME") -> RECALC_0_531_ | N3: Product: | O3: =_xll.SUBNM("CONS_VC:ALL.D.Products","default","Cement Group") -> RECALC_0_534_ | S3: =_xll.SUBNM("CONS_VC:ALL.D.Version","Sys.Report","L300","Descrição") -> RECALC_0_536_ | U3: =_xll.SUBNM("CONS_VC:ALL.D.Version","Sys.Report","RF","Descrição") -> RECALC_0_537_

Sheet EBITDA - Fx
A1: [Begin Format Range]
A2: 0 | B2: Nome do elemento | C2: 123.45679 | D2: 123.45679 | E2: 123.45679 | F2: 123.45679
A3: 1 | B3: Nome do elemento | C3: 123.45679 | D3: 123.45679 | E3: 123.45679 | F3: 123.45679
A4: 2 | B4: Nome do elemento | C4: 123.45679 | D4: 123.45679 | E4: 123.45679 | F4: 123.45679
A5: 3 | B5: Nome do elemento | C5: 123.45679 | D5: 123.45679 | E5: 123.45679 | F5: 123.45679
A6: 4 | B6: Nome do elemento | C6: 123.45679 | D6: 123.45679 | E6: 123.45679 | F6: 123.45679
A7: 5 | B7: Nome do elemento | C7: 123.45679 | D7: 123.45679 | E7: 123.45679 | F7: 123.45679
A8: Default | B8: Nome do elemento | C8: 123.45679 | D8: 123.45679 | E8: 123.45679 | F8: 123.45679
A9: Leaf | B9: Nome do elemento | C9: 123.45679 | D9: 123.45679 | E9: 123.45679 | F9: 123.45679
A10: [End Format Range]
B11: {DRILLDOWNMEMBER({[DFS.D.Accounts_PnL].[DFS.D.Accounts_PnL].[EBITDA]} , {[DFS.D.Accounts_PnL].[DFS.D.Accounts_PnL].[EBITDA]})}
B12: =_xll.TM1RPTVIEW("CONS_VC:DFS.100.Profit_and_Loss:4065595",0,_xll.TM1RPTTITLE("CONS_VC:ALL.D.Year",$B$14),_xll.TM1RPTTITLE("CONS_VC:DFS.M.100.Profit_and_Loss",$B$15),_xll.TM1RPTTITLE("CONS_VC:ALL.D.Version",$B$16),_xll.TM1RPTTITLE("CONS_VC:ALL.D.Currency",EBITDA!$B$5),_xll.TM1RPTTITLE("CONS_VC:ALL.D.Region",$B$18),_xll.TM1RPTTITLE("CONS_VC:ALL.D.Products",$B$19),TM1RPTFMTRNG4065595,TM1RPTFMTIDCOL4065595) -> CONS_VC:DFS.100.Profit_and_Loss:4065595
B13: Year
B14: =_xll.SUBNM("CONS_VC:ALL.D.Year",,"2025") -> RECALC_0_7_
B15: =_xll.SUBNM("CONS_VC:DFS.M.100.Profit_and_Loss",,"Total Value") -> RECALC_0_551_
B16: =_xll.SUBNM("CONS_VC:ALL.D.Version","Sys.Report","Actual","Descrição") -> RECALC_0_539_
B18: =_xll.SUBNM("CONS_VC:ALL.D.Region",,"Global") -> RECALC_0_495_
B19: =_xll.SUBNM("CONS_VC:ALL.D.Products",,"Total Products") -> RECALC_0_11_
B20: =_xll.TM1RPTROW($B$12,"CONS_VC:DFS.D.Accounts_PnL",,,,FALSE,B$11) -> pending__Modelo Global Result.xlsx:EBITDA - Fx:TM1RPTDATARNG:4065595
B22: Quarter View | D22: Q1 | E22: Q2 | F22: Q3 | G22: Q4 | I22: Full Year View | K22: Versão | L22: Actual | M22: L300 | N22: RF | O22: RF | P22: RF | Q22: RF | R22: RF | S22: Actual | T22: RF
A23: =IF(_xll.TM1RPTELISCONSOLIDATED($B$20,EBITDA!$C$6),IF(_xll.TM1RPTELLEV($B$20,EBITDA!$C$6)<=5,_xll.TM1RPTELLEV($B$20,EBITDA!$C$6),"Default"),"Leaf") -> #VALUE! | B23: Actual | C23: 2024 | D23: =_xll.DBRW($B$12,$C$23,D$22,$B23,EBITDA!$B$5,$B$18,$B$19,EBITDA!$C$6,$B$15) -> RECALC_1_575_ | E23: =_xll.DBRW($B$12,$C$23,E$22,$B23,EBITDA!$B$5,$B$18,$B$19,EBITDA!$C$6,$B$15) -> RECALC_1_598_ | F23: =_xll.DBRW($B$12,$C$23,F$22,$B23,EBITDA!$B$5,$B$18,$B$19,EBITDA!$C$6,$B$15) -> RECALC_1_597_ | G23: =_xll.DBRW($B$12,$C$23,G$22,$B23,EBITDA!$B$5,$B$18,$B$19,EBITDA!$C$6,$B$15) -> RECALC_1_594_ | K23: Empresa | L23: Global | M23: Global | N23: VCBR | O23: VCNA | P23: VCEAA | Q23: VCLATAM | R23: VCOTHERS | S23: Fx | T23: Global
B24: L300 | C24: L300 | D24: =_xll.DBRW($B$12,$B$14,D$22,$B24,EBITDA!$B$5,$B$18,$B$19,EBITDA!$C$6,$B$15) -> RECALC_1_570_ | E24: =_xll.DBRW($B$12,$B$14,E$22,$B24,EBITDA!$B$5,$B$18,$B$19,EBITDA!$C$6,$B$15) -> RECALC_1_576_ | F24: =_xll.DBRW($B$12,$B$14,F$22,$B24,EBITDA!$B$5,$B$18,$B$19,EBITDA!$C$6,$B$15) -> RECALC_1_593_ | G24: =_xll.DBRW($B$12,$B$14,G$22,$B24,EBITDA!$B$5,$B$18,$B$19,EBITDA!$C$6,$B$15) -> RECALC_1_592_ | L24: =B14-1 -> #VALUE! | M24: L300 | N24: VCBR | O24: VCNA | P24: VCEA | Q24: VCLATAM | R24: Others | S24: FX | T24: =B14 -> RECALC_0_7_
B25: RF | C25: 2025 | D25: =_xll.DBRW($B$12,$B$14,D$22,$B25,EBITDA!$B$5,$B$18,$B$19,EBITDA!$C$6,$B$15) -> RECALC_1_553_ | E25: =_xll.DBRW($B$12,$B$14,E$22,$B25,EBITDA!$B$5,$B$18,$B$19,EBITDA!$C$6,$B$15) -> RECALC_1_569_ | F25: =_xll.DBRW($B$12,$B$14,F$22,$B25,EBITDA!$B$5,$B$18,$B$19,EBITDA!$C$6,$B$15) -> RECALC_1_556_ | G25: =_xll.DBRW($B$12,$B$14,G$22,$B25,EBITDA!$B$5,$B$18,$B$19,EBITDA!$C$6,$B$15) -> RECALC_1_586_ | L25: =_xll.DBRW($B$12,$B$14,$B$13,L$22,EBITDA!$B$5,L$23,$B$19,EBITDA!$AC$6,$B$15) -> RECALC_1_583_ | M25: =_xll.DBRW($B$12,$B$14,$B$13,M$22,EBITDA!$B$5,M$23,$B$19,EBITDA!$AC$6,$B$15) -> RECALC_1_558_ | N25: =_xll.DBRW($B$12,$B$14,$B$13,N$22,EBITDA!$B$5,N$23,$B$19,EBITDA!$AC$6,$B$15) -> RECALC_1_554_ | O25: =_xll.DBRW($B$12,$B$14,$B$13,O$22,EBITDA!$B$5,O$23,$B$19,EBITDA!$AC$6,$B$15) -> RECALC_1_590_ | P25: =_xll.DBRW($B$12,$B$14,$B$13,P$22,EBITDA!$B$5,P$23,$B$19,EBITDA!$AC$6,$B$15) -> RECALC_1_587_ | Q25: =_xll.DBRW($B$12,$B$14,$B$13,Q$22,EBITDA!$B$5,Q$23,$B$19,EBITDA!$AC$6,$B$15) -> RECALC_1_589_ | R25: =_xll.DBRW($B$12,$B$14,$B$13,R$22,EBITDA!$B$5,R$23,$B$19,EBITDA!$AC$6,$B$15) -> RECALC_1_559_ | S25: =_xll.DBRW($B$12,$B$14,$B$13,S$22,EBITDA!$B$5,S$23,$B$19,EBITDA!$AC$6,$B$15) -> RECALC_1_596_ | T25: =_xll.DBRW($B$12,$B$14,$B$13,T$22,EBITDA!$B$5,T$23,$B$19,EBITDA!$AC$6,$B$15) -> RECALC_1_572_
K26: L300 | N26: =_xll.DBRW($B$12,$B$14,$B$13,$K$26,EBITDA!$B$5,N$23,$B$19,EBITDA!$AC$6,$B$15) -> RECALC_1_582_ | O26: =_xll.DBRW($B$12,$B$14,$B$13,$K$26,EBITDA!$B$5,O$23,$B$19,EBITDA!$AC$6,$B$15) -> RECALC_1_557_ | P26: =_xll.DBRW($B$12,$B$14,$B$13,$K$26,EBITDA!$B$5,P$23,$B$19,EBITDA!$AC$6,$B$15) -> RECALC_1_584_ | Q26: =_xll.DBRW($B$12,$B$14,$B$13,$K$26,EBITDA!$B$5,Q$23,$B$19,EBITDA!$AC$6,$B$15) -> RECALC_1_581_ | R26: =_xll.DBRW($B$12,$B$14,$B$13,$K$26,EBITDA!$B$5,R$23,$B$19,EBITDA!$AC$6,$B$15) -> RECALC_1_591_
N27: =N25-N26 -> #VALUE! | O27: =O25-O26 -> #VALUE! | P27: =P25-P26 -> #VALUE! | Q27: =Q25-Q26 -> #VALUE! | R27: =R25-R26 -> #VALUE!
M29: =T25-M25 -> #VALUE!
B30: EBITDA/Net Revenue (%) | D30: Q1 | E30: Q2 | F30: Q3 | G30: Q4
C31: 2024 | D31: =_xll.DBRW($B$12,$C$23,D$22,$B23,EBITDA!$B$5,$B$18,$B$19,$B30,$B$15) -> RECALC_1_567_ | E31: =_xll.DBRW($B$12,$C$23,E$22,$B23,EBITDA!$B$5,$B$18,$B$19,$B30,$B$15) -> RECALC_1_565_ | F31: =_xll.DBRW($B$12,$C$23,F$22,$B23,EBITDA!$B$5,$B$18,$B$19,$B30,$B$15) -> RECALC_1_555_ | G31: =_xll.DBRW($B$12,$C$23,G$22,$B23,EBITDA!$B$5,$B$18,$B$19,$B30,$B$15) -> RECALC_1_568_
C32: L300 | D32: =_xll.DBRW($B$12,$B$14,D$22,$B24,EBITDA!$B$5,$B$18,$B$19,$B30,$B$15) -> RECALC_1_578_ | E32: =_xll.DBRW($B$12,$B$14,E$22,$B24,EBITDA!$B$5,$B$18,$B$19,$B30,$B$15) -> RECALC_1_566_ | F32: =_xll.DBRW($B$12,$B$14,F$22,$B24,EBITDA!$B$5,$B$18,$B$19,$B30,$B$15) -> RECALC_1_552_ | G32: =_xll.DBRW($B$12,$B$14,G$22,$B24,EBITDA!$B$5,$B$18,$B$19,$B30,$B$15) -> RECALC_1_588_ | L32: 6965 | M32: -87 | N32: =SUM(L32:M32) -> 6878 | O32: =SUM(L32-N32) -> 87
C33: 2025 | D33: =_xll.DBRW($B$12,$B$14,D$22,$B25,EBITDA!$B$5,$B$18,$B$19,$B30,$B$15) -> RECALC_1_595_ | E33: =_xll.DBRW($B$12,$B$14,E$22,$B25,EBITDA!$B$5,$B$18,$B$19,$B30,$B$15) -> RECALC_1_585_ | F33: =_xll.DBRW($B$12,$B$14,F$22,$B25,EBITDA!$B$5,$B$18,$B$19,$B30,$B$15) -> RECALC_1_564_ | G33: =_xll.DBRW($B$12,$B$14,G$22,$B25,EBITDA!$B$5,$B$18,$B$19,$B30,$B$15) -> RECALC_1_563_
L34: -87 | M34: -112 | N34: 163 | O34: 83 | P34: 5 | Q34: -139

Sheet EBITDA
B5: =_xll.SUBNM("CONS_VC:ALL.D.Currency","Default","BRL Conv.") -> RECALC_0_70_
C6: =_xll.SUBNM("CONS_VC:DFS.D.Accounts_PnL","Default","EBITDA") -> RECALC_0_112_ | AC6: =_xll.SUBNM("CONS_VC:DFS.D.Accounts_PnL","Default","EBITDA") -> RECALC_0_112_
C7: QoQ Overview | AC7: Full Year
A26: ="Margin " &'EBITDA - Fx'!B20 -> Margin pending__Modelo Global Result.xlsx:EBITDA - Fx:TM1RPTDATARNG:4065595 | E26: ='EBITDA - Fx'!D31 -> RECALC_1_567_ | F26: ='EBITDA - Fx'!D32 -> RECALC_1_578_ | G26: ='EBITDA - Fx'!D33 -> RECALC_1_595_ | J26: ='EBITDA - Fx'!E31 -> RECALC_1_565_ | K26: ='EBITDA - Fx'!E32 -> RECALC_1_566_ | L26: ='EBITDA - Fx'!E33 -> RECALC_1_585_ | N26: ='EBITDA - Fx'!F31 -> RECALC_1_555_ | O26: ='EBITDA - Fx'!F32 -> RECALC_1_552_ | P26: ='EBITDA - Fx'!F33 -> RECALC_1_564_ | S26: ='EBITDA - Fx'!G31 -> RECALC_1_568_ | T26: ='EBITDA - Fx'!G32 -> RECALC_1_588_ | U26: ='EBITDA - Fx'!G33 -> RECALC_1_563_

Sheet Cash Generation - Fx
A1: =_xll.VIEW("CONS_VC:DFS.140.Indirect_Cash_Flow",$B$2,"!","!",$B$5,$B$6,'Cash Generation'!$C$7,$B$3) -> CONS_VC:DFS.140.Indirect_Cash_Flow:205767106-2015365241
A2: ALL.D.Year | B2: =_xll.SUBNM("CONS_VC:ALL.D.Year","","2025") -> RECALC_0_7_
A3: DFS.M.140.Indirect_Cash_Flow | B3: =_xll.SUBNM("CONS_VC:DFS.M.140.Indirect_Cash_Flow","","Total Value") -> RECALC_0_535_
A4: DFS.D.Accounts_ICF
A5: ALL.D.Currency | B5: =_xll.SUBNM("CONS_VC:ALL.D.Currency","","BRL Conv.") -> RECALC_0_496_
A6: ALL.D.Region | B6: =_xll.SUBNM("CONS_VC:ALL.D.Region","","Global") -> RECALC_0_495_
B8: Q1 | C8: Q2 | D8: Q3 | E8: Q4
A9: Actual | B9: =_xll.DBRW($A$1,$B$2,B$8,$A9,$B$5,$B$6,'Cash Generation'!$C$7,$B$3) -> RECALC_1_549_ | C9: =_xll.DBRW($A$1,$B$2,C$8,$A9,$B$5,$B$6,'Cash Generation'!$C$7,$B$3) -> RECALC_1_547_ | D9: =_xll.DBRW($A$1,$B$2,D$8,$A9,$B$5,$B$6,'Cash Generation'!$C$7,$B$3) -> RECALC_1_540_ | E9: =_xll.DBRW($A$1,$B$2,E$8,$A9,$B$5,$B$6,'Cash Generation'!$C$7,$B$3) -> RECALC_1_546_
A10: L300 | B10: =_xll.DBRW($A$1,$B$2,B$8,$A10,$B$5,$B$6,'Cash Generation'!$C$7,$B$3) -> RECALC_1_545_ | C10: =_xll.DBRW($A$1,$B$2,C$8,$A10,$B$5,$B$6,'Cash Generation'!$C$7,$B$3) -> RECALC_1_543_ | D10: =_xll.DBRW($A$1,$B$2,D$8,$A10,$B$5,$B$6,'Cash Generation'!$C$7,$B$3) -> RECALC_1_550_ | E10: =_xll.DBRW($A$1,$B$2,E$8,$A10,$B$5,$B$6,'Cash Generation'!$C$7,$B$3) -> RECALC_1_548_
A11: RF | B11: =_xll.DBRW($A$1,$B$2,B$8,$A11,$B$5,$B$6,'Cash Generation'!$C$7,$B$3) -> RECALC_1_541_ | C11: =_xll.DBRW($A$1,$B$2,C$8,$A11,$B$5,$B$6,'Cash Generation'!$C$7,$B$3) -> RECALC_1_544_ | D11: =_xll.DBRW($A$1,$B$2,D$8,$A11,$B$5,$B$6,'Cash Generation'!$C$7,$B$3) -> RECALC_1_542_ | E11: =_xll.DBRW($A$1,$B$2,E$8,$A11,$B$5,$B$6,'Cash Generation'!$C$7,$B$3) -> RECALC_1_538_

Sheet Cash Generation
C7: =_xll.SUBNM("CONS_VC:DFS.D.Accounts_ICF","Default","Cash generation before financing") -> RECALC_0_87_ | AC7: EBIT – Full Year
C8: QoQ Overview

Sheet Menu
A1: Cubo
A2: CONS_VC:DFS.200.KPIs
A3: CONS_VC:DFS.100.Profit_and_loss
A4: CONS_VC:DFS.140.Indirect_Cash_Flow
A5: CONS_VC:DFS.180.Gross_Debt
A6: CONS_VC:REV.100.Revenue_Consolidated
A8: Ano
A9: =_xll.SUBNM("CONS_VC:ALL.D.Year","","2025") -> RECALC_0_7_
A11: Mês
A12: =_xll.SUBNM("CONS_VC:ALL.D.Month",,"Total YTD","MEMBER_NAME") -> RECALC_0_9_
A13: =_xll.SUBNM("CONS_VC:ALL.D.Month",,"Year","MEMBER_NAME") -> RECALC_0_10_
A15: Versão
A18: Currency
A19: =_xll.SUBNM("CONS_VC:ALL.D.Currency","","BRL") -> RECALC_0_8_
A21: Region
A22: =_xll.SUBNM("CONS_VC:ALL.D.Region","","VCBR") -> RECALC_0_6_
A24: Produto
A25: =_xll.SUBNM("CONS_VC:ALL.D.Products","","Total Products") -> RECALC_0_11_
A27: Accounts_PNL
A28: Net Profit
A30: DFM.100.Profil_and_Loss
A31: Value

Sheet Planilha3
A1: =_xll.VIEW("CONS_VC:DFS.100.Profit_and_Loss",'Value Tree TESTE'!$F$3,"!",'Value Tree TESTE'!$H$3,'Value Tree TESTE'!$F$4,'Value Tree TESTE'!$H$4,$B$7,"!",$B$3) -> CONS_VC:DFS.100.Profit_and_Loss:2057671061844175
A2: ALL.D.Year
A3: DFS.M.100.Profit_and_Loss | B3: =_xll.SUBNM("CONS_VC:DFS.M.100.Profit_and_Loss","","Value") -> RECALC_0_122_
A4: ALL.D.Version
A5: ALL.D.Currency
A6: ALL.D.Region
A7: ALL.D.Products | B7: =_xll.SUBNM("CONS_VC:ALL.D.Products","","Total Products") -> RECALC_0_11_
B9: Year
A10: Net Profit
A12: =_xll.VIEW("CONS_VC:DFS.140.Indirect_Cash_Flow",$B$13,$B$14,$B$15,$B$16,$B$17,"!","!") -> CONS_VC:DFS.140.Indirect_Cash_Flow:2057671061262658909
A13: ALL.D.Year | B13: =_xll.SUBNM("CONS_VC:ALL.D.Year","","2025") -> RECALC_0_7_
A14: ALL.D.Month | B14: =_xll.SUBNM("CONS_VC:ALL.D.Month","Default","Jan","Desc") -> RECALC_0_45_
A15: ALL.D.Version | B15: =_xll.SUBNM("CONS_VC:ALL.D.Version","","T4") -> RECALC_0_30_
A16: ALL.D.Currency | B16: =_xll.SUBNM("CONS_VC:ALL.D.Currency","","BRL") -> RECALC_0_8_
A17: ALL.D.Region | B17: =_xll.SUBNM("CONS_VC:ALL.D.Region","","VCBR") -> RECALC_0_6_
B19: Total Value | C19: Value | D19: Adjustments
A20: EBITDA | B20: =_xll.DBRW($A$12,$B$13,$B$14,$B$15,$B$16,$B$17,$A20,B$19) -> RECALC_1_428_ | C20: =_xll.DBRW($A$12,$B$13,$B$14,$B$15,$B$16,$B$17,$A20,C$19) -> RECALC_1_460_ | D20: =_xll.DBRW($A$12,$B$13,$B$14,$B$15,$B$16,$B$17,$A20,D$19) -> RECALC_1_392_
A21: Income tax on transactions | B21: =_xll.DBRW($A$12,$B$13,$B$14,$B$15,$B$16,$B$17,$A21,B$19) -> RECALC_1_268_ | C21: =_xll.DBRW($A$12,$B$13,$B$14,$B$15,$B$16,$B$17,$A21,C$19) -> RECALC_1_212_ | D21: =_xll.DBRW($A$12,$B$13,$B$14,$B$15,$B$16,$B$17,$A21,D$19) -> RECALC_1_344_
A22: Working capital | B22: =_xll.DBRW($A$12,$B$13,$B$14,$B$15,$B$16,$B$17,$A22,B$19) -> RECALC_1_335_ | C22: =_xll.DBRW($A$12,$B$13,$B$14,$B$15,$B$16,$B$17,$A22,C$19) -> RECALC_1_258_ | D22: =_xll.DBRW($A$12,$B$13,$B$14,$B$15,$B$16,$B$17,$A22,D$19) -> RECALC_1_438_
A23: Non expansion capex | B23: =_xll.DBRW($A$12,$B$13,$B$14,$B$15,$B$16,$B$17,$A23,B$19) -> RECALC_1_407_ | C23: =_xll.DBRW($A$12,$B$13,$B$14,$B$15,$B$16,$B$17,$A23,C$19) -> RECALC_1_482_ | D23: =_xll.DBRW($A$12,$B$13,$B$14,$B$15,$B$16,$B$17,$A23,D$19) -> RECALC_1_440_
A24: Dividends received | B24: =_xll.DBRW($A$12,$B$13,$B$14,$B$15,$B$16,$B$17,$A24,B$19) -> RECALC_1_474_ | C24: =_xll.DBRW($A$12,$B$13,$B$14,$B$15,$B$16,$B$17,$A24,C$19) -> RECALC_1_437_ | D24: =_xll.DBRW($A$12,$B$13,$B$14,$B$15,$B$16,$B$17,$A24,D$19) -> RECALC_1_316_
A25: Financial Results | B25: =_xll.DBRW($A$12,$B$13,$B$14,$B$15,$B$16,$B$17,$A25,B$19) -> RECALC_1_485_ | C25: =_xll.DBRW($A$12,$B$13,$B$14,$B$15,$B$16,$B$17,$A25,C$19) -> RECALC_1_176_ | D25: =_xll.DBRW($A$12,$B$13,$B$14,$B$15,$B$16,$B$17,$A25,D$19) -> RECALC_1_424_
A26: Debt Amortization | B26: =_xll.DBRW($A$12,$B$13,$B$14,$B$15,$B$16,$B$17,$A26,B$19) -> RECALC_1_373_ | C26: =_xll.DBRW($A$12,$B$13,$B$14,$B$15,$B$16,$B$17,$A26,C$19) -> RECALC_1_224_ | D26: =_xll.DBRW($A$12,$B$13,$B$14,$B$15,$B$16,$B$17,$A26,D$19) -> RECALC_1_315_
A27: Financial Revenue | B27: =_xll.DBRW($A$12,$B$13,$B$14,$B$15,$B$16,$B$17,$A27,B$19) -> RECALC_1_473_ | C27: =_xll.DBRW($A$12,$B$13,$B$14,$B$15,$B$16,$B$17,$A27,C$19) -> RECALC_1_188_ | D27: =_xll.DBRW($A$12,$B$13,$B$14,$B$15,$B$16,$B$17,$A27,D$19) -> RECALC_1_365_
A28: Other Financial Expenses | B28: =_xll.DBRW($A$12,$B$13,$B$14,$B$15,$B$16,$B$17,$A28,B$19) -> RECALC_1_475_ | C28: =_xll.DBRW($A$12,$B$13,$B$14,$B$15,$B$16,$B$17,$A28,C$19) -> RECALC_1_297_ | D28: =_xll.DBRW($A$12,$B$13,$B$14,$B$15,$B$16,$B$17,$A28,D$19) -> RECALC_1_468_
A29: Derivatives settlement | B29: =_xll.DBRW($A$12,$B$13,$B$14,$B$15,$B$16,$B$17,$A29,B$19) -> RECALC_1_251_ | C29: =_xll.DBRW($A$12,$B$13,$B$14,$B$15,$B$16,$B$17,$A29,C$19) -> RECALC_1_226_ | D29: =_xll.DBRW($A$12,$B$13,$B$14,$B$15,$B$16,$B$17,$A29,D$19) -> RECALC_1_304_
A30: Tax on Financial Revenue | B30: =_xll.DBRW($A$12,$B$13,$B$14,$B$15,$B$16,$B$17,$A30,B$19) -> RECALC_1_278_ | C30: =_xll.DBRW($A$12,$B$13,$B$14,$B$15,$B$16,$B$17,$A30,C$19) -> RECALC_1_326_ | D30: =_xll.DBRW($A$12,$B$13,$B$14,$B$15,$B$16,$B$17,$A30,D$19) -> RECALC_1_423_
A31: Other | B31: =_xll.DBRW($A$12,$B$13,$B$14,$B$15,$B$16,$B$17,$A31,B$19) -> RECALC_1_400_ | C31: =_xll.DBRW($A$12,$B$13,$B$14,$B$15,$B$16,$B$17,$A31,C$19) -> RECALC_1_217_ | D31: =_xll.DBRW($A$12,$B$13,$B$14,$B$15,$B$16,$B$17,$A31,D$19) -> RECALC_1_168_
... A44: Funding | B44: =_xll.DBRW($A$12,$B$13,$B$14,$B$15,$B$16,$B$17,$A44,B$19) -> RECALC_1_381_ | C44: =_xll.DBRW($A$12,$B$13,$B$14,$B$15,$B$16,$B$17,$A44,C$19) -> RECALC_1_271_ | D44: =_xll.DBRW($A$12,$B$13,$B$14,$B$15,$B$16,$B$17,$A44,D$19) -> RECALC_1_206_
A45: Change in cash | C45: =_xll.DBRW($A$12,$B$13,$B$14,$B$15,$B$16,$B$17,$A45,C$19) -> RECALC_1_261_ | D45: =_xll.DBRW($A$12,$B$13,$B$14,$B$15,$B$16,$B$17,$A45,D$19) -> RECALC_1_353_
A46: Initial Cash Balance | B46: =_xll.DBRW($A$12,$B$13,$B$14,$B$15,$B$16,$B$17,$A46,B$19) -> RECALC_1_185_ | C46: =_xll.DBRW($A$12,$B$13,$B$14,$B$15,$B$16,$B$17,$A46,C$19) -> RECALC_1_413_ | D46: =_xll.DBRW($A$12,$B$13,$B$14,$B$15,$B$16,$B$17,$A46,D$19) -> RECALC_1_361_
A47: Final Cash Position | B47: =_xll.DBRW($A$12,$B$13,$B$14,$B$15,$B$16,$B$17,$A47,B$19) -> RECALC_1_230_ | C47: =_xll.DBRW($A$12,$B$13,$B$14,$B$15,$B$16,$B$17,$A47,C$19) -> RECALC_1_331_ | D47: =_xll.DBRW($A$12,$B$13,$B$14,$B$15,$B$16,$B$17,$A47,D$19) -> RECALC_1_219_
A48: Final Cash Position Aux | B48: =_xll.DBRW($A$12,$B$13,$B$14,$B$15,$B$16,$B$17,$A48,B$19) -> RECALC_1_355_ | C48: =_xll.DBRW($A$12,$B$13,$B$14,$B$15,$B$16,$B$17,$A48,C$19) -> RECALC_1_254_ | D48: =_xll.DBRW($A$12,$B$13,$B$14,$B$15,$B$16,$B$17,$A48,D$19) -> RECALC_1_457_
A49: Final Debt Position | B49: =_xll.DBRW($A$12,$B$13,$B$14,$B$15,$B$16,$B$17,$A49,B$19) -> RECALC_1_402_ | C49: =_xll.DBRW($A$12,$B$13,$B$14,$B$15,$B$16,$B$17,$A49,C$19) -> RECALC_1_463_ | D49: =_xll.DBRW($A$12,$B$13,$B$14,$B$15,$B$16,$B$17,$A49,D$19) -> RECALC_1_272_
A50: MTM | B50: =_xll.DBRW($A$12,$B$13,$B$14,$B$15,$B$16,$B$17,$A50,B$19) -> RECALC_1_264_ | C50: =_xll.DBRW($A$12,$B$13,$B$14,$B$15,$B$16,$B$17,$A50,C$19) -> RECALC_1_253_ | D50: =_xll.DBRW($A$12,$B$13,$B$14,$B$15,$B$16,$B$17,$A50,D$19) -> RECALC_1_169_
A51: Final Net Debt | B51: =_xll.DBRW($A$12,$B$13,$B$14,$B$15,$B$16,$B$17,$A51,B$19) -> RECALC_1_340_ | C51: =_xll.DBRW($A$12,$B$13,$B$14,$B$15,$B$16,$B$17,$A51,C$19) -> RECALC_1_209_ | D51: =_xll.DBRW($A$12,$B$13,$B$14,$B$15,$B$16,$B$17,$A51,D$19) -> RECALC_1_414_
A52: Adj EBITDA LTM | B52: =_xll.DBRW($A$12,$B$13,$B$14,$B$15,$B$16,$B$17,$A52,B$19) -> RECALC_1_374_ | C52: =_xll.DBRW($A$12,$B$13,$B$14,$B$15,$B$16,$B$17,$A52,C$19) -> RECALC_1_421_ | D52: =_xll.DBRW($A$12,$B$13,$B$14,$B$15,$B$16,$B$17,$A52,D$19) -> RECALC_1_443_
A53: Adjusts LTM | B53: =_xll.DBRW($A$12,$B$13,$B$14,$B$15,$B$16,$B$17,$A53,B$19) -> RECALC_1_358_ | C53: =_xll.DBRW($A$12,$B$13,$B$14,$B$15,$B$16,$B$17,$A53,C$19) -> RECALC_1_229_ | D53: =_xll.DBRW($A$12,$B$13,$B$14,$B$15,$B$16,$B$17,$A53,D$19) -> RECALC_1_493_
A54: Leverage | B54: =_xll.DBRW($A$12,$B$13,$B$14,$B$15,$B$16,$B$17,$A54,B$19) -> RECALC_1_284_ | C54: =_xll.DBRW($A$12,$B$13,$B$14,$B$15,$B$16,$B$17,$A54,C$19) -> RECALC_1_282_ | D54: =_xll.DBRW($A$12,$B$13,$B$14,$B$15,$B$16,$B$17,$A54,D$19) -> RECALC_1_262_
A56: CONS_VC:DFS.200.KPIs
A57: CONS_VC:DFS.100.Profit_and_loss
A58: CONS_VC:DFS.140.Indirect_Cash_Flow
A59: CONS_VC:DFS.180.Gross_Debt
A60: CONS_VC:REV.100.Revenue_Consolidated

Sheet Planilha1
A1: =_xll.VIEW("CONS_VC:DFS.200.KPIs",$B$2,$B$3,$B$4,$B$5,$B$6,$B$7,"!","!") -> CONS_VC:DFS.200.KPIs:205767106-1430385332
A2: ALL.D.Year | B2: =_xll.SUBNM("CONS_VC:ALL.D.Year","","2025") -> RECALC_0_7_
A3: ALL.D.Month | B3: =_xll.SUBNM("CONS_VC:ALL.D.Month","Default","Jan","Desc") -> RECALC_0_45_
A4: ALL.D.Version | B4: =_xll.SUBNM("CONS_VC:ALL.D.Version","","T4") -> RECALC_0_30_
A5: ALL.D.Currency | B5: =_xll.SUBNM("CONS_VC:ALL.D.Currency","Default","BRL","MEMBER_NAME") -> RECALC_0_33_
A6: ALL.D.Region | B6: =_xll.SUBNM("CONS_VC:ALL.D.Region","","VCBR") -> RECALC_0_6_
A7: ALL.D.Products | B7: =_xll.SUBNM("CONS_VC:ALL.D.Products","Default","PROD099 - Others","Código e Descrição") -> RECALC_0_67_
B9: Value | C9: Aux
A10: Production volume (kt) | B10: =_xll.DBRW($A$1,$B$2,$B$3,$B$4,$B$5,$B$6,$B$7,$A10,B$9) -> RECALC_1_296_ | C10: =_xll.DBRW($A$1,$B$2,$B$3,$B$4,$B$5,$B$6,$B$7,$A10,C$9) -> RECALC_1_325_
A11: Thermal Sub. (%) | B11: =_xll.DBRW($A$1,$B$2,$B$3,$B$4,$B$5,$B$6,$B$7,$A11,B$9) -> RECALC_1_389_ | C11: =_xll.DBRW($A$1,$B$2,$B$3,$B$4,$B$5,$B$6,$B$7,$A11,C$9) -> RECALC_1_489_
A12: Thermal C. (kcal/t kk) | B12: =_xll.DBRW($A$1,$B$2,$B$3,$B$4,$B$5,$B$6,$B$7,$A12,B$9) -> RECALC_1_323_ | C12: =_xll.DBRW($A$1,$B$2,$B$3,$B$4,$B$5,$B$6,$B$7,$A12,C$9) -> RECALC_1_246_
A13: Petcoke Price (LMU/t) | B13: =_xll.DBRW($A$1,$B$2,$B$3,$B$4,$B$5,$B$6,$B$7,$A13,B$9) -> RECALC_1_267_ | C13: =_xll.DBRW($A$1,$B$2,$B$3,$B$4,$B$5,$B$6,$B$7,$A13,C$9) -> RECALC_1_306_
A14: CO2 Gross (kg/ton) | B14: =_xll.DBRW($A$1,$B$2,$B$3,$B$4,$B$5,$B$6,$B$7,$A14,B$9) -> RECALC_1_177_ | C14: =_xll.DBRW($A$1,$B$2,$B$3,$B$4,$B$5,$B$6,$B$7,$A14,C$9) -> RECALC_1_270_
A15: CO2 Net (kg/ton) | B15: =_xll.DBRW($A$1,$B$2,$B$3,$B$4,$B$5,$B$6,$B$7,$A15,B$9) -> RECALC_1_470_ | C15: =_xll.DBRW($A$1,$B$2,$B$3,$B$4,$B$5,$B$6,$B$7,$A15,C$9) -> RECALC_1_294_
A16: Power Price (LMU/MWh) | B16: =_xll.DBRW($A$1,$B$2,$B$3,$B$4,$B$5,$B$6,$B$7,$A16,B$9) -> RECALC_1_241_ | C16: =_xll.DBRW($A$1,$B$2,$B$3,$B$4,$B$5,$B$6,$B$7,$A16,C$9) -> RECALC_1_399_
A17: Power Cons. (kWh/t) | B17: =_xll.DBRW($A$1,$B$2,$B$3,$B$4,$B$5,$B$6,$B$7,$A17,B$9) -> RECALC_1_277_ | C17: =_xll.DBRW($A$1,$B$2,$B$3,$B$4,$B$5,$B$6,$B$7,$A17,C$9) -> RECALC_1_431_
A18: Clinker Factor (%) | B18: =_xll.DBRW($A$1,$B$2,$B$3,$B$4,$B$5,$B$6,$B$7,$A18,B$9) -> RECALC_1_210_ | C18: =_xll.DBRW($A$1,$B$2,$B$3,$B$4,$B$5,$B$6,$B$7,$A18,C$9) -> RECALC_1_321_
A19: Cash Cost (LMU/t) | B19: =_xll.DBRW($A$1,$B$2,$B$3,$B$4,$B$5,$B$6,$B$7,$A19,B$9) -> RECALC_1_371_ | C19: =_xll.DBRW($A$1,$B$2,$B$3,$B$4,$B$5,$B$6,$B$7,$A19,C$9) -> RECALC_1_252_
A20: Cement Var. Costs (LMU/t) | B20: =_xll.DBRW($A$1,$B$2,$B$3,$B$4,$B$5,$B$6,$B$7,$A20,B$9) -> RECALC_1_222_ | C20: =_xll.DBRW($A$1,$B$2,$B$3,$B$4,$B$5,$B$6,$B$7,$A20,C$9) -> RECALC_1_337_
A21: Fuel (LMU/t) | B21: =_xll.DBRW($A$1,$B$2,$B$3,$B$4,$B$5,$B$6,$B$7,$A21,B$9) -> RECALC_1_487_ | C21: =_xll.DBRW($A$1,$B$2,$B$3,$B$4,$B$5,$B$6,$B$7,$A21,C$9) -> RECALC_1_202_
... A58: % ROIC | B58: =_xll.DBRW($A$1,$B$2,$B$3,$B$4,$B$5,$B$6,$B$7,$A58,B$9) -> RECALC_1_309_ | C58: =_xll.DBRW($A$1,$B$2,$B$3,$B$4,$B$5,$B$6,$B$7,$A58,C$9) -> RECALC_1_471_

Sheet Planilha2
B2: Cement Net FOB (€/t) | C2: Preço do Cimento | D2: Cobo de Receita | E2: Produto Cimento
B3: SG&A (€M) | C3: ZBB total

Sheet Value Tree TESTE
C1: 9 | M1: IFRS16 adj
A2: Cubo
A3: CONS_VC:DFS.200.KPIs | K3: + | M3: YTD | O3: FY | R3: + | T3: YTD | V3: FY | Y3: + | AA3: YTD | AC3: FY | AF3: - | AH3: YTD | AJ3: FY | AM3: + | AO3: YTD | AQ3: FY
A4: CONS_VC:DFS.100.Profit_and_loss | L4: Net Debt (€M) | S4: Net Rev. (€M) | Z4: Cement Volume (kt) | AG4: Fuel (€/t) | AN4: Thermal Sub. (%)
A5: CONS_VC:DFS.140.Indirect_Cash_Flow | B5: =B7 -> 0 | K5: =A17 -> RECALC_0_5_ | L5: =L7 -> 1 | M5: {=_xll.DBRW('Value Tree TESTE'!A6,A10,A13,K5,A20,A23,"Closing Balance Debt","Total Value")} -> RECALC_1_227_ | N5: =N7 -> 1 | O5: {=_xll.DBRW('Value Tree TESTE'!A6,A10,A14,K5,A20,A23,"Closing Balance Debt","Total Value")} -> RECALC_1_456_ | R5: =A17 -> RECALC_0_5_ | S5: =S7 -> 0 | T5: {=_xll.DBR(A4,A10,A13,R5,A20,A23,"PROD099 - Others","Net Revenue","Value")} -> RECALC_1_305_ | U5: =U7 -> -1 | V5: {=_xll.DBR(A4,A10,A14,R5,A20,A23,"PROD099 - Others","Net Revenue","Value")} -> RECALC_1_288_ | Y5: =A17 -> RECALC_0_5_ | Z5: =Z7 -> 1 | AA5: =_xll.DBRW(A3,A10,A13,Y5,A20,A23,"PROD099 - Others","Volume","Value") -> RECALC_1_425_ | AB5: =AB7 -> 0 | AC5: =_xll.DBRW(A3,A10,A14,Y5,A20,A23,"PROD099 - Others","Volume","Value") -> RECALC_1_426_ | AF5: =A17 -> RECALC_0_5_ | AG5: =AG7 -> #VALUE! | AH5: =_xll.DBRW('Value Tree TESTE'!A3,A10,A13,AF5,A20,A23,"PROD099 - Others","Fuel (LMU/t)","Value") -> RECALC_1_303_ | AI5: =AI7 -> #VALUE! | AJ5: =_xll.DBRW('Value Tree TESTE'!A3,A10,A14,AF5,A20,A23,"PROD099 - Others","Fuel (LMU/t)","Value") -> RECALC_1_386_ | AM5: =A17 -> RECALC_0_5_ | AN5: =AN7 -> #VALUE! | AO5: =_xll.DBRW('Value Tree TESTE'!A3,A10,A13,AM5,A20,A23,"PROD099 - Others","Thermal Sub. (%)","Value") -> RECALC_1_266_ | AP5: =AP7 -> #REF! | AQ5: =_xll.DBRW('Value Tree TESTE'!A3,A10,A14,AM5,A20,A23,"PROD099 - Others","Thermal Sub. (%)","Value") -> RECALC_1_244_ | AS5: 54.4 | AT5: #REF!
A6: CONS_VC:DFS.180.Gross_Debt | B6: =B7 -> 0 | K6: =A18 -> RECALC_0_4_ | L6: =L7 -> 1 | M6: {=_xll.DBRW('Value Tree TESTE'!A6,A10,A13,K6,A20,A23,"Closing Balance Debt","Total Value")} -> RECALC_1_171_ | N6: =N7 -> 1 | O6: {=_xll.DBRW('Value Tree TESTE'!A6,A10,A14,K6,A20,A23,"Closing Balance Debt","Total Value")} -> RECALC_1_260_ | R6: =A18 -> RECALC_0_4_ | S6: =S7 -> 0 | T6: {=_xll.DBR(A4,A10,A13,R6,A20,A23,"PROD099 - Others","Net Revenue","Value")} -> RECALC_1_175_ | U6: =U7 -> -1 | V6: {=_xll.DBR(A4,A10,A14,R6,A20,A23,"PROD099 - Others","Net Revenue","Value")} -> RECALC_1_416_ | Y6: =A18 -> RECALC_0_4_ | Z6: =Z7 -> 1 | AA6: =_xll.DBRW(A3,A10,A13,Y6,A20,A23,"PROD099 - Others","Volume","Value") -> RECALC_1_184_ | AB6: =AB7 -> 0 | AC6: =_xll.DBRW(A3,A10,A14,Y6,A20,A23,"PROD099 - Others","Volume","Value") -> RECALC_1_191_ | AF6: =A18 -> RECALC_0_4_ | AG6: =AG7 -> #VALUE! | AH6: =_xll.DBRW('Value Tree TESTE'!A3,A10,A13,AF6,A20,A23,"PROD099 - Others","Fuel (LMU/t)","Value") -> RECALC_1_276_ | AI6: =AI7 -> #VALUE! | AJ6: =_xll.DBRW('Value Tree TESTE'!A3,A10,A14,AF6,A20,A23,"PROD099 - Others","Fuel (LMU/t)","Value") -> RECALC_1_395_ | AM6: =A18 -> RECALC_0_4_ | AN6: =AN7 -> #VALUE! | AO6: =_xll.DBRW('Value Tree TESTE'!A3,A10,A13,AM6,A20,A23,"PROD099 - Others","Thermal Sub. (%)","Value") -> RECALC_1_320_ | AP6: =AP7 -> #REF! | AQ6: =_xll.DBRW('Value Tree TESTE'!A3,A10,A14,AM6,A20,A23,"PROD099 - Others","Thermal Sub. (%)","Value") -> RECALC_1_376_ | AS6: 54.5 | AT6: #REF!
A7: CONS_VC:REV.100.Revenue_Consolidated | K7: L500 | L7: =IF(K3="+",IF(M5>M7,1,IF(M5>=M6,0,-1)),IF(K3="-",IF(M5<M7,1,IF(M5<=M6,0,-1)))) -> 1 | M7: {=_xll.DBRW('Value Tree TESTE'!A6,A10,A13,K7,A20,A23,"Closing Balance Debt","Total Value")} -> RECALC_1_140_ | N7: =IF(K3="+",IF(O5>O7,1,IF(O5>=O6,0,-1)),IF(K3="-",IF(O5<O7,1,IF(O5<=O6,0,-1)))) -> 1 | O7: {=_xll.DBRW('Value Tree TESTE'!A6,A10,A14,K7,A20,A23,"Closing Balance Debt","Total Value")} -> RECALC_1_141_ | R7: L500 | S7: =IF(R3="+",IF(T5>T7,1,IF(T5>=T6,0,-1)),IF(R3="-",IF(T5<T7,1,IF(T5<=T6,0,-1)))) -> 0 | T7: {=_xll.DBR(A4,A10,A13,R7,A20,A23,"PROD099 - Others","Net Revenue","Value")} -> RECALC_1_78_ | U7: =IF(R3="+",IF(V5>V7,1,IF(V5>=V6,0,-1)),IF(R3="-",IF(V5<V7,1,IF(V5<=V6,0,-1)))) -> -1 | V7: {=_xll.DBR(A4,A10,A14,R7,A20,A23,"PROD099 - Others","Net Revenue","Value")} -> RECALC_1_82_ | Y7: L500 | Z7: =IF(Y3="+",IF(AA5>AA7,1,IF(AA5>=AA6,0,-1)),IF(Y3="-",IF(AA5<AA7,1,IF(AA5<=AA6,0,-1)))) -> 1 | AA7: =_xll.DBRW(A3,A10,A13,Y7,A20,A23,"PROD099 - Others","Volume","Value") -> RECALC_1_145_ | AB7: =IF(Y3="+",IF(AC5>AC7,1,IF(AC5>=AC6,0,-1)),IF(Y3="-",IF(AC5<AC7,1,IF(AC5<=AC6,0,-1)))) -> 0 | AC7: =_xll.DBRW(A3,A10,A14,Y7,A20,A23,"PROD099 - Others","Volume","Value") -> RECALC_1_79_ | AF7: L500 | AG7: =IF(AF3="+",IF(AH5>AH7*(1+IF(AH7>0,$C$4,-$C$4)),0,IF(AH5>=AH6*(1+IF(AH6>0,-$C$4,$C$4)),0,-1)),IF(AF3="-",IF(AH5<AH7*(1+IF(AH7>0,-$C$4,$C$4)),0,IF(AH5<=AH6*(1+IF(AH6>0,$C$4,-$C$4)),0,-1)))) -> #VALUE! | AH7: =_xll.DBRW('Value Tree TESTE'!A3,A10,A13,AF7,A20,A23,"PROD099 - Others","Fuel (LMU/t)","Value") -> RECALC_1_111_ | AI7: =IF(AF3="+",IF(AJ5>AJ7*(1+IF(AJ7>0,$C$4,-$C$4)),0,IF(AJ5>=AJ6*(1+IF(AJ6>0,-$C$4,$C$4)),0,-1)),IF(AF3="-",IF(AJ5<AJ7*(1+IF(AJ7>0,-$C$4,$C$4)),0,IF(AJ5<=AJ6*(1+IF(AJ6>0,$C$4,-$C$4)),0,-1)))) -> #VALUE! | AJ7: =_xll.DBRW('Value Tree TESTE'!A3,A10,A14,AF7,A20,A23,"PROD099 - Others","Fuel (LMU/t)","Value") -> RECALC_1_138_ | AM7: L500 | AN7: =IF(AM3="+",IF(AO5>AO7*(1+IF(AO7>0,$C$4,-$C$4)),1,IF(AO5>=AO6*(1+IF(AO6>0,-$C$4,$C$4)),0,-1)),IF(AM3="-",IF(AO5<AO7*(1+IF(AO7>0,-$C$4,$C$4)),1,IF(AO5<=AO6*(1+IF(AO6>0,$C$4,-$C$4)),0,-1)))) -> #VALUE! | AO7: =_xll.DBRW('Value Tree TESTE'!A3,A10,A13,AM7,A20,A23,"PROD099 - Others","Thermal Sub. (%)","Value") -> RECALC_1_144_ | AP7: =IF(AM3="+",IF(AT5>AQ7*(1+IF(AQ7>0,$C$4,-$C$4)),0,IF(AT5>=AT6*(1+IF(AT6>0,-$C$4,$C$4)),0,-1)),IF(AM3="-",IF(AT5<AQ7*(1+IF(AQ7>0,-$C$4,$C$4)),0,IF(AT5<=AT6*(1+IF(AT6>0,$C$4,-$C$4)),0,-1)))) -> #REF! | AQ7: =_xll.DBRW('Value Tree TESTE'!A3,A10,A14,AM7,A20,A23,"PROD099 - Others","Thermal Sub. (%)","Value") -> RECALC_1_83_
AS8: 5
A9: Ano | D9: + | F9: YTD | H9: FY | K9: + | M9: YTD | O9: FY | R9: + | T9: YTD | V9: FY | Y9: + | AA9: YTD | AC9: FY | AF9: - | AH9: YTD | AJ9: FY | AM9: - | AO9: YTD | AQ9: FY
A10: =_xll.SUBNM("CONS_VC:ALL.D.Year","","2025") -> RECALC_0_7_ | E10: Net Profit (€M) | F10: Net Profit (€M) | L10: EBITDA (€M) | S10: EBITDA Oth. BUs. (€M) | Z10: Cement Net FOB (€/t) | AG10: CO2 Gross (kg/ton) | AN10: Thermal C. (kcal/t kk)
D11: =A17 -> RECALC_0_5_ | E11: =E13 -> #REF! | F11: =_xll.DBRW('Value Tree TESTE'!A4,'Value Tree TESTE'!A10,'Value Tree TESTE'!A13,D11,'Value Tree TESTE'!A20,'Value Tree TESTE'!A23,'Value Tree TESTE'!A26,'Value Tree TESTE'!A29,A36) -> RECALC_1_439_ | G11: =G13 -> #VALUE! | H11: =_xll.DBRW('Value Tree TESTE'!A4,'Value Tree TESTE'!A10,'Value Tree TESTE'!A14,D11,'Value Tree TESTE'!A20,'Value Tree TESTE'!A23,'Value Tree TESTE'!A26,'Value Tree TESTE'!A29,A36) -> RECALC_1_172_ | K11: =A17 -> RECALC_0_5_ | L11: =L13 -> #VALUE! | M11: =_xll.DBRW('Value Tree TESTE'!A3,A10,A13,K11,A20,A23,"PROD099 - Others","EBITDA LTM","Value") -> RECALC_1_388_ | N11: =N13 -> #VALUE! | O11: =_xll.DBRW('Value Tree TESTE'!A3,A10,A14,K11,A20,A23,"PROD099 - Others","EBITDA LTM","Value") -> RECALC_1_446_ | R11: =A17 -> RECALC_0_5_ | S11: =S13 -> #VALUE! | T11: =_xll.DBRW('Value Tree TESTE'!A3,A10,A13,R11,A20,A23,"Total Products","EBITDA LTM","Value")-_xll.DBRW('Value Tree TESTE'!A3,A10,A13,R11,A20,A23,"PRODCE010 - Cement","EBITDA LTM","Value") -> #VALUE! | U11: =U13 -> #VALUE! | V11: =_xll.DBRW('Value Tree TESTE'!A3,A10,A14,R11,A20,A23,"Total Products","EBITDA LTM","Value")-_xll.DBRW('Value Tree TESTE'!A3,A10,A14,R11,A20,A23,"PRODCE010 - Cement","EBITDA LTM","Value") -> #VALUE! | Y11: =A17 -> RECALC_0_5_ | Z11: =Z13 -> #VALUE! | AA11: {=_xll.DBRW(A7,A10,A13,Y11,A20,A23,"PROD099","Total Market","Reference Price [$/ton]")} -> RECALC_1_476_ | AB11: =AB13 -> #VALUE! | AC11: {=_xll.DBRW(A7,A10,A14,Y11,A20,A23,"PROD099","Total Market","Reference Price [$/ton]")} -> RECALC_1_398_ | AF11: =A17 -> RECALC_0_5_ | AG11: =AG13 -> #VALUE! | AH11: =_xll.DBRW('Value Tree TESTE'!A3,A10,A13,AF11,A20,A23,"PROD099 - Others","CO2 Gross (kg/ton)","Value") -> RECALC_1_391_ | AI11: =AI13 -> #VALUE! | AJ11: =_xll.DBRW('Value Tree TESTE'!A3,A10,A14,AF11,A20,A23,"PROD099 - Others","CO2 Gross (kg/ton)","Value") -> RECALC_1_302_ | AM11: =A17 -> RECALC_0_5_ | AN11: =AN13 -> #VALUE! | AO11: =_xll.DBRW(A3,A10,A13,AM11,A20,A23,"PROD099 - Others","Thermal C. (kcal/t kk)","Value") -> RECALC_1_432_ | AP11: =AP13 -> #REF! | AQ11: =_xll.DBRW(A3,A10,A14,AM11,A20,A23,"PROD099 - Others","Thermal C. (kcal/t kk)","Value") -> RECALC_1_237_ | AS11: 812 | AT11: #REF!
A12: Mês | D12: =A18 -> RECALC_0_4_ | E12: =E13 -> #REF! | F12: =_xll.DBRW('Value Tree TESTE'!A4,'Value Tree TESTE'!A10,'Value Tree TESTE'!A13,D12,'Value Tree TESTE'!A20,'Value Tree TESTE'!A23,'Value Tree TESTE'!A26,'Value Tree TESTE'!A29,A36) -> RECALC_1_369_ | G12: =G13 -> #VALUE! | H12: =_xll.DBRW('Value Tree TESTE'!A4,'Value Tree TESTE'!A10,'Value Tree TESTE'!A14,D12,'Value Tree TESTE'!A20,'Value Tree TESTE'!A23,'Value Tree TESTE'!A26,'Value Tree TESTE'!A29,A36) -> RECALC_1_201_ | K12: =A18 -> RECALC_0_4_ | L12: =L13 -> #VALUE! | M12: =_xll.DBRW('Value Tree TESTE'!A3,A10,A13,K12,A20,A23,"PROD099 - Others","EBITDA LTM","Value") -> RECALC_1_225_ | N12: =N13 -> #VALUE! | O12: =_xll.DBRW('Value Tree TESTE'!A3,A10,A14,K12,A20,A23,"PROD099 - Others","EBITDA LTM","Value") -> RECALC_1_377_ | R12: =A18 -> RECALC_0_4_ | S12: =S13 -> #VALUE! | T12: =_xll.DBRW('Value Tree TESTE'!A3,A10,A13,R12,A20,A23,"Total Products","EBITDA LTM","Value")-_xll.DBRW('Value Tree TESTE'!A3,A10,A13,R12,A20,A23,"PRODCE010 - Cement","EBITDA LTM","Value") -> #VALUE! | U12: =U13 -> #VALUE! | V12: =_xll.DBRW('Value Tree TESTE'!A3,A10,A14,R12,A20,A23,"Total Products","EBITDA LTM","Value")-_xll.DBRW('Value Tree TESTE'!A3,A10,A14,R12,A20,A23,"PRODCE010 - Cement","EBITDA LTM","Value") -> #VALUE! | Y12: =A18 -> RECALC_0_4_ | Z12: =Z13 -> #VALUE! | AA12: {=_xll.DBRW(A7,A10,A13,Y12,A20,A23,"PROD099","Total Market","Reference Price [$/ton]")} -> RECALC_1_319_ | AB12: =AB13 -> #VALUE! | AC12: {=_xll.DBRW(A7,A10,A14,Y12,A20,A23,"PROD099","Total Market","Reference Price [$/ton]")} -> RECALC_1_417_ | AF12: =A18 -> RECALC_0_4_ | AG12: =AG13 -> #VALUE! | AH12: =_xll.DBRW('Value Tree TESTE'!A3,A10,A13,AF12,A20,A23,"PROD099 - Others","CO2 Gross (kg/ton)","Value") -> RECALC_1_181_ | AI12: =AI13 -> #VALUE! | AJ12: =_xll.DBRW('Value Tree TESTE'!A3,A10,A14,AF12,A20,A23,"PROD099 - Others","CO2 Gross (kg/ton)","Value") -> RECALC_1_363_ | AM12: =A18 -> RECALC_0_4_ | AN12: =AN13 -> #VALUE! | AO12: =_xll.DBRW(A3,A10,A13,AM12,A20,A23,"PROD099 - Others","Thermal C. (kcal/t kk)","Value") -> RECALC_1_408_ | AP12: =AP13 -> #REF! | AQ12: =_xll.DBRW(A3,A10,A14,AM12,A20,A23,"PROD099 - Others","Thermal C. (kcal/t kk)","Value") -> RECALC_1_214_ | AS12: 810 | AT12: #REF!
A13: =_xll.SUBNM("CONS_VC:ALL.D.Month",,"Total YTD","MEMBER_NAME") -> RECALC_0_9_ | D13: L500 | E13: =IF(D9="+",IF(#REF!>F13*(1+IF(F13>0,$C$4,-$C$4)),1,IF(#REF!>=F12*(1+IF(F12>0,-$C$4,$C$4)),0,-1)),IF(D9="-",IF(#REF!<F13*(1+IF(F13>0,-$C$4,$C$4)),1,IF(#REF!<=F12*(1+IF(F12>0,$C$4,-$C$4)),0,-1)))) -> #REF! | F13: =_xll.DBRW('Value Tree TESTE'!A4,'Value Tree TESTE'!A10,'Value Tree TESTE'!A13,D13,'Value Tree TESTE'!A20,'Value Tree TESTE'!A23,'Value Tree TESTE'!A26,'Value Tree TESTE'!A29,A36) -> RECALC_1_158_ | G13: =IF(D9="+",IF(H11>H13*(1+IF(H13>0,$C$4,-$C$4)),1,IF(H11>=H12*(1+IF(H12>0,-$C$4,$C$4)),0,-1)),IF(D9="-",IF(H11<H13*(1+IF(H13>0,-$C$4,$C$4)),1,IF(H11<=H12*(1+IF(H12>0,$C$4,-$C$4)),0,-1)))) -> #VALUE! | H13: =_xll.DBRW('Value Tree TESTE'!A4,'Value Tree TESTE'!A10,'Value Tree TESTE'!A14,D13,'Value Tree TESTE'!A20,'Value Tree TESTE'!A23,'Value Tree TESTE'!A26,'Value Tree TESTE'!A29,A36) -> RECALC_1_127_ | K13: L500 | L13: =IF(K9="+",IF(M11>M13*(1+IF(M13>0,$C$4,-$C$4)),1,IF(M11>=M12*(1+IF(M12>0,-$C$4,$C$4)),0,-1)),IF(K9="-",IF(M11<M13*(1+IF(M13>0,-$C$4,$C$4)),1,IF(M11<=M12*(1+IF(M12>0,$C$4,-$C$4)),0,-1)))) -> #VALUE! | M13: =_xll.DBRW('Value Tree TESTE'!A3,A10,A13,K13,A20,A23,"PROD099 - Others","EBITDA LTM","Value") -> RECALC_1_151_ | N13: =IF(K9="+",IF(O11>O13*(1+IF(O13>0,$C$4,-$C$4)),1,IF(O11>=O12*(1+IF(O12>0,-$C$4,$C$4)),0,-1)),IF(K9="-",IF(O11<O13*(1+IF(O13>0,-$C$4,$C$4)),1,IF(O11<=O12*(1+IF(O12>0,$C$4,-$C$4)),0,-1)))) -> #VALUE! | O13: =_xll.DBRW('Value Tree TESTE'!A3,A10,A14,K13,A20,A23,"PROD099 - Others","EBITDA LTM","Value") -> RECALC_1_106_ | R13: L500 | S13: =IF(R9="+",IF(T11>T13,1,IF(T11>=T12,0,-1)),IF(R9="-",IF(T11<T13,1,IF(T11<=T12,0,-1)))) -> #VALUE! | T13: =_xll.DBRW('Value Tree TESTE'!A3,A10,A13,R13,A20,A23,"Total Products","EBITDA LTM","Value")-_xll.DBRW('Value Tree TESTE'!A3,A10,A13,R13,A20,A23,"PRODCE010 - Cement","EBITDA LTM","Value") -> #VALUE! | U13: =IF(R9="+",IF(V11>V13,1,IF(V11>=V12,0,-1)),IF(R9="-",IF(V11<V13,1,IF(V11<=V12,0,-1)))) -> #VALUE! | V13: =_xll.DBRW('Value Tree TESTE'!A3,A10,A14,R13,A20,A23,"Total Products","EBITDA LTM","Value")-_xll.DBRW('Value Tree TESTE'!A3,A10,A14,R13,A20,A23,"PRODCE010 - Cement","EBITDA LTM","Value") -> #VALUE! | Y13: L500 | Z13: =IF(Y9="+",IF(AA11>AA13*(1+IF(AA13>0,$C$4,-$C$4)),1,IF(AA11>=AA12*(1+IF(AA12>0,-$C$4,$C$4)),0,-1)),IF(Y9="-",IF(AA11<AA13*(1+IF(AA13>0,-$C$4,$C$4)),1,IF(AA11<=AA12*(1+IF(AA12>0,$C$4,-$C$4)),0,-1)))) -> #VALUE! | AA13: {=_xll.DBRW(A7,A10,A13,Y13,A20,A23,"PROD099","Total Market","Reference Price [$/ton]")} -> RECALC_1_93_ | AB13: =IF(Y9="+",IF(AC11>AC13*(1+IF(AC13>0,$C$4,-$C$4)),1,IF(AC11>=AC12*(1+IF(AC12>0,-$C$4,$C$4)),0,-1)),IF(Y9="-",IF(AC11<AC13*(1+IF(AC13>0,-$C$4,$C$4)),1,IF(AC11<=AC12*(1+IF(AC12>0,$C$4,-$C$4)),0,-1)))) -> #VALUE! | AC13: {=_xll.DBRW(A7,A10,A14,Y13,A20,A23,"PROD099","Total Market","Reference Price [$/ton]")} -> RECALC_1_116_ | AF13: L500 | AG13: =IF(AF9="+",IF(AH11>AH13*(1+IF(AH13>0,$C$4,-$C$4)),0,IF(AH11>=AH12*(1+IF(AH12>0,-$C$4,$C$4)),0,-1)),IF(AF9="-",IF(AH11<AH13*(1+IF(AH13>0,-$C$4,$C$4)),0,IF(AH11<=AH12*(1+IF(AH12>0,$C$4,-$C$4)),0,-1)))) -> #VALUE! | AH13: =_xll.DBRW('Value Tree TESTE'!A3,A10,A13,AF13,A20,A23,"PROD099 - Others","CO2 Gross (kg/ton)","Value") -> RECALC_1_131_ | AI13: =IF(AF9="+",IF(AJ11>AJ13*(1+IF(AJ13>0,$C$4,-$C$4)),0,IF(AJ11>=AJ12*(1+IF(AJ12>0,-$C$4,$C$4)),0,-1)),IF(AF9="-",IF(AJ11<AJ13*(1+IF(AJ13>0,-$C$4,$C$4)),0,IF(AJ11<=AJ12*(1+IF(AJ12>0,$C$4,-$C$4)),0,-1)))) -> #VALUE! | AJ13: =_xll.DBRW('Value Tree TESTE'!A3,A10,A14,AF13,A20,A23,"PROD099 - Others","CO2 Gross (kg/ton)","Value") -> RECALC_1_149_ | AM13: L500 | AN13: =IF(AM9="+",IF(AO11>AO13*(1+IF(AO13>0,$C$4,-$C$4)),0,IF(AO11>=AO12*(1+IF(AO12>0,-$C$4,$C$4)),0,-1)),IF(AM9="-",IF(AO11<AO13*(1+IF(AO13>0,-$C$4,$C$4)),0,IF(AO11<=AO12*(1+IF(AO12>0,$C$4,-$C$4)),0,-1)))) -> #VALUE! | AO13: =_xll.DBRW(A3,A10,A13,AM13,A20,A23,"PROD099 - Others","Thermal C. (kcal/t kk)","Value") -> RECALC_1_89_ | AP13: =IF(AM9="+",IF(AT11>AQ13*(1+IF(AQ13>0,$C$4,-$C$4)),0,IF(AT11>=AT12*(1+IF(AT12>0,-$C$4,$C$4)),0,-1)),IF(AM9="-",IF(AT11<AQ13*(1+IF(AQ13>0,-$C$4,$C$4)),0,IF(AT11<=AT12*(1+IF(AT12>0,$C$4,-$C$4)),0,-1)))) -> #REF! | AQ13: =_xll.DBRW(A3,A10,A14,AM13,A20,A23,"PROD099 - Others","Thermal C. (kcal/t kk)","Value") -> RECALC_1_143_
A14: =_xll.SUBNM("CONS_VC:ALL.D.Month",,"Year","MEMBER_NAME") -> RECALC_0_10_
D15: + | F15: YTD | H15: FY | K15: + | M15: YTD | O15: FY | AF15: - | AH15: YTD | AJ15: FY | AM15: - | AO15: YTD | AQ15: FY
A16: Versão | E16: FCF (€M) | L16: Capex (€M) | AG16: CO2 Net (kg/ton) | AN16: Petcoke Price (USD/t)
A17: =_xll.SUBNM("CONS_VC:ALL.D.Version",,"RF","Descrição") -> RECALC_0_5_ | D17: =A17 -> RECALC_0_5_ | E17: =E19 -> #REF! | F17: =_xll.DBRW('Value Tree TESTE'!A5,'Value Tree TESTE'!A10,A13,D17,A20,A23,'Value Tree TESTE'!A32,'Value Tree TESTE'!A39) -> RECALC_1_436_ | G17: =G19 -> #VALUE! | H17: =_xll.DBRW('Value Tree TESTE'!A5,'Value Tree TESTE'!A10,A14,D17,A20,A23,'Value Tree TESTE'!A32,'Value Tree TESTE'!A39) -> RECALC_1_211_ | K17: =A17 -> RECALC_0_5_ | L17: =L19 -> #VALUE! | M17: =_xll.DBRW('Value Tree TESTE'!A5,A10,A13,K17,A20,A23,"Expansion Capex",Planilha3!B$19) -> RECALC_1_364_ | N17: =N19 -> #VALUE! | O17: =_xll.DBRW('Value Tree TESTE'!A5,A10,A14,K17,A20,A23,"Expansion Capex",Planilha3!B$19) -> RECALC_1_223_ | AF17: =A17 -> RECALC_0_5_ | AG17: =AG19 -> #VALUE! | AH17: =_xll.DBRW(A3,A10,A13,AF17,A20,A23,"PROD099 - Others","CO2 Net (kg/ton)","Value") -> RECALC_1_269_ | AI17: =AI19 -> #VALUE! | AJ17: =_xll.DBRW(A3,A10,A14,AF17,A20,A23,"PROD099 - Others","CO2 Net (kg/ton)","Value") -> RECALC_1_187_ | AM17: =A17 -> RECALC_0_5_ | AN17: =AN19 -> #VALUE! | AO17: =_xll.DBRW(A3,A10,A13,AM17,A20,A23,"PROD099 - Others","Petcoke Price (LMU/t)","Value") -> RECALC_1_221_ | AP17: =AP19 -> #VALUE! | AQ17: =_xll.DBRW(A3,A10,A14,AM17,A20,A23,"PROD099 - Others","Petcoke Price (LMU/t)","Value") -> RECALC_1_256_
A18: =_xll.SUBNM("CONS_VC:ALL.D.Version",,"L300","MEMBER_NAME") -> RECALC_0_4_ | D18: =A18 -> RECALC_0_4_ | E18: =E19 -> #REF! | F18: =_xll.DBRW('Value Tree TESTE'!A5,'Value Tree TESTE'!A10,A13,D18,A20,A23,'Value Tree TESTE'!A32,'Value Tree TESTE'!A39) -> RECALC_1_354_ | G18: =G19 -> #VALUE! | H18: =_xll.DBRW('Value Tree TESTE'!A5,'Value Tree TESTE'!A10,A14,D18,A20,A23,'Value Tree TESTE'!A32,'Value Tree TESTE'!A39) -> RECALC_1_360_ | K18: =A18 -> RECALC_0_4_ | L18: =L19 -> #VALUE! | M18: =_xll.DBRW('Value Tree TESTE'!A5,A10,A13,K18,A20,A23,"Expansion Capex",Planilha3!B$19) -> RECALC_1_291_ | N18: =N19 -> #VALUE! | O18: =_xll.DBRW('Value Tree TESTE'!A5,A10,A14,K18,A20,A23,"Expansion Capex",Planilha3!B$19) -> RECALC_1_192_ | AF18: =A18 -> RECALC_0_4_ | AG18: =AG19 -> #VALUE! | AH18: =_xll.DBRW(A3,A10,A13,AF18,A20,A23,"PROD099 - Others","CO2 Net (kg/ton)","Value") -> RECALC_1_491_ | AI18: =AI19 -> #VALUE! | AJ18: =_xll.DBRW(A3,A10,A14,AF18,A20,A23,"PROD099 - Others","CO2 Net (kg/ton)","Value") -> RECALC_1_352_ | AM18: =A18 -> RECALC_0_4_ | AN18: =AN19 -> #VALUE! | AO18: =_xll.DBRW(A3,A10,A13,AM18,A20,A23,"PROD099 - Others","Petcoke Price (LMU/t)","Value") -> RECALC_1_295_ | AP18: =AP19 -> #VALUE! | AQ18: =_xll.DBRW(A3,A10,A14,AM18,A20,A23,"PROD099 - Others","Petcoke Price (LMU/t)","Value") -> RECALC_1_419_
A19: Currency | D19: L500 | E19: =IF(D15="+",IF(#REF!>F19*(1+IF(F19>0,$C$4,-$C$4)),1,IF(#REF!>=F18*(1+IF(F18>0,-$C$4,$C$4)),0,-1)),IF(D15="-",IF(#REF!<F19*(1+IF(F19>0,-$C$4,$C$4)),1,IF(#REF!<=F18*(1+IF(F18>0,$C$4,-$C$4)),0,-1)))) -> #REF! | F19: =_xll.DBRW('Value Tree TESTE'!A5,'Value Tree TESTE'!A10,A13,D19,A20,A23,'Value Tree TESTE'!A32,'Value Tree TESTE'!A39) -> RECALC_1_109_ | G19: =IF(D15="+",IF(H17>H19*(1+IF(H19>0,$C$4,-$C$4)),1,IF(H17>=H18*(1+IF(H18>0,-$C$4,$C$4)),0,-1)),IF(D15="-",IF(H17<H19*(1+IF(H19>0,-$C$4,$C$4)),1,IF(H17<=H18*(1+IF(H18>0,$C$4,-$C$4)),0,-1)))) -> #VALUE! | H19: =_xll.DBRW('Value Tree TESTE'!A5,'Value Tree TESTE'!A10,A14,D19,A20,A23,'Value Tree TESTE'!A32,'Value Tree TESTE'!A39) -> RECALC_1_107_ | K19: L500 | L19: =IF(K15="+",IF(M17>M19*(1+IF(M19>0,$C$4,-$C$4)),1,IF(M17>=M18*(1+IF(M18>0,-$C$4,$C$4)),0,-1)),IF(K15="-",IF(M17<M19*(1+IF(M19>0,-$C$4,$C$4)),1,IF(M17<=M18*(1+IF(M18>0,$C$4,-$C$4)),0,-1)))) -> #VALUE! | M19: =_xll.DBRW('Value Tree TESTE'!A5,A10,A13,K19,A20,A23,"Expansion Capex",Planilha3!B$19) -> RECALC_1_115_ | N19: =IF(K15="+",IF(O17>O19*(1+IF(O19>0,$C$4,-$C$4)),1,IF(O17>=O18*(1+IF(O18>0,-$C$4,$C$4)),0,-1)),IF(K15="-",IF(O17<O19*(1+IF(O19>0,-$C$4,$C$4)),1,IF(O17<=O18*(1+IF(O18>0,$C$4,-$C$4)),0,-1)))) -> #VALUE! | O19: =_xll.DBRW('Value Tree TESTE'!A5,A10,A14,K19,A20,A23,"Expansion Capex",Planilha3!B$19) -> RECALC_1_150_ | AF19: L500 | AG19: =IF(AF15="+",IF(AH17>AH19*(1+IF(AH19>0,$C$4,-$C$4)),0,IF(AH17>=AH18*(1+IF(AH18>0,-$C$4,$C$4)),0,-1)),IF(AF15="-",IF(AH17<AH19*(1+IF(AH19>0,-$C$4,$C$4)),0,IF(AH17<=AH18*(1+IF(AH18>0,$C$4,-$C$4)),0,-1)))) -> #VALUE! | AH19: =_xll.DBRW(A3,A10,A13,AF19,A20,A23,"PROD099 - Others","CO2 Net (kg/ton)","Value") -> RECALC_1_132_ | AI19: =IF(AF15="+",IF(AJ17>AJ19*(1+IF(AJ19>0,$C$4,-$C$4)),0,IF(AJ17>=AJ18*(1+IF(AJ18>0,-$C$4,$C$4)),0,-1)),IF(AF15="-",IF(AJ17<AJ19*(1+IF(AJ19>0,-$C$4,$C$4)),0,IF(AJ17<=AJ18*(1+IF(AJ18>0,$C$4,-$C$4)),0,-1)))) -> #VALUE! | AJ19: =_xll.DBRW(A3,A10,A14,AF19,A20,A23,"PROD099 - Others","CO2 Net (kg/ton)","Value") -> RECALC_1_110_ | AM19: L500 | AN19: =IF(AM15="+",IF(AO17>AO19*(1+IF(AO19>0,$C$4,-$C$4)),0,IF(AO17>=AO18*(1+IF(AO18>0,-$C$4,$C$4)),0,-1)),IF(AM15="-",IF(AO17<AO19*(1+IF(AO19>0,-$C$4,$C$4)),0,IF(AO17<=AO18*(1+IF(AO18>0,$C$4,-$C$4)),0,-1)))) -> #VALUE! | AO19: =_xll.DBRW(A3,A10,A13,AM19,A20,A23,"PROD099 - Others","Petcoke Price (LMU/t)","Value") -> RECALC_1_136_ | AP19: =IF(AM15="+",IF(AQ17>AQ19*(1+IF(AQ19>0,$C$4,-$C$4)),0,IF(AQ17>=AQ18*(1+IF(AQ18>0,-$C$4,$C$4)),0,-1)),IF(AM15="-",IF(AQ17<AQ19*(1+IF(AQ19>0,-$C$4,$C$4)),0,IF(AQ17<=AQ18*(1+IF(AQ18>0,$C$4,-$C$4)),0,-1)))) -> #VALUE! | AQ19: =_xll.DBRW(A3,A10,A14,AM19,A20,A23,"PROD099 - Others","Petcoke Price (LMU/t)","Value") -> RECALC_1_154_
A20: =_xll.SUBNM("CONS_VC:ALL.D.Currency","","BRL") -> RECALC_0_8_
D21: + | E21: =V20 -> 0 | F21: YTD | H21: FY | K21: + | M21: YTD | O21: FY | R21: - | T21: YTD | V21: FY | Y21: - | AA21: YTD | AC21: FY | AF21: - | AH21: YTD | AJ21: FY | AM21: - | AO21: YTD | AQ21: FY
A22: Region | E22: ROIC (%) | L22: ∆ WK Capital (€M) | S22: Cem. Cash Cost (€/t) | Z22: Cement Var. Costs (€/t) | AG22: Power (€/t) | AN22: Power Price (€/MWh)
A23: =_xll.SUBNM("CONS_VC:ALL.D.Region","","VCBR") -> RECALC_0_6_ | D23: =A17 -> RECALC_0_5_ | E23: =E25 -> 1 | F23: =_xll.DBRW('Value Tree TESTE'!A3,A10,A13,D23,A20,A23,A26,"% ROIC","Value") -> RECALC_1_455_ | G23: =G25 -> 1 | H23: =_xll.DBRW('Value Tree TESTE'!A3,A10,A14,D23,A20,A23,A26,"% ROIC","Value") -> RECALC_1_343_ | K23: =A17 -> RECALC_0_5_ | L23: =L25 -> #VALUE! | M23: =_xll.DBRW('Value Tree TESTE'!A3,A10,A13,K23,A20,A23,"PROD099 - Others","Working Capital Balance","Value") -> RECALC_1_290_ | N23: =N25 -> #VALUE! | O23: =_xll.DBRW('Value Tree TESTE'!A3,A10,A14,K23,A20,A23,"PROD099 - Others","Working Capital Balance","Value") -> RECALC_1_245_ | R23: =A17 -> RECALC_0_5_ | S23: =S25 -> #VALUE! | T23: =AA23+AA29 -> #VALUE! | U23: =U25 -> #VALUE! | V23: =AC23+AC29 -> #VALUE! | Y23: =A17 -> RECALC_0_5_ | Z23: =Z25 -> 0 | AA23: =SUM(AH5,AH23,AH29,AH35) -> 0 | AB23: =AB25 -> 0 | AC23: =SUM(AJ5,AJ23,AJ29,AJ35) -> 0 | AF23: =A17 -> RECALC_0_5_ | AG23: =AG25 -> #VALUE! | AH23: =_xll.DBRW('Value Tree TESTE'!A3,A10,A13,AF23,A20,A23,"PROD099 - Others","Power (LMU/t)","Value") -> RECALC_1_287_ | AI23: =AI25 -> #VALUE! | AJ23: =_xll.DBRW('Value Tree TESTE'!A3,A10,A14,AF23,A20,A23,"PROD099 - Others","Power (LMU/t)","Value") -> RECALC_1_396_ | AM23: =A17 -> RECALC_0_5_ | AN23: =AN25 -> #VALUE! | AO23: =_xll.DBRW(A3,A10,A13,AM23,A20,A23,"PROD099 - Others","Power Price (LMU/MWh)","Value") -> RECALC_1_472_ | AP23: =AP25 -> #VALUE! | AQ23: =_xll.DBRW(A3,A10,A14,AM23,A20,A23,"PROD099 - Others","Power Price (LMU/MWh)","Value") -> RECALC_1_327_
D24: =A18 -> RECALC_0_4_ | E24: =E25 -> 1 | F24: =_xll.DBRW('Value Tree TESTE'!A3,A10,A13,D24,A20,A23,A26,"% ROIC","Value") -> RECALC_1_283_ | G24: =G25 -> 1 | H24: =_xll.DBRW('Value Tree TESTE'!A3,A10,A14,D24,A20,A23,A26,"% ROIC","Value") -> RECALC_1_483_ | K24: =A18 -> RECALC_0_4_ | L24: =L25 -> #VALUE! | M24: =_xll.DBRW('Value Tree TESTE'!A3,A10,A13,K24,A20,A23,"PROD099 - Others","Working Capital Balance","Value") -> RECALC_1_349_ | N24: =N25 -> #VALUE! | O24: =_xll.DBRW('Value Tree TESTE'!A3,A10,A14,K24,A20,A23,"PROD099 - Others","Working Capital Balance","Value") -> RECALC_1_322_ | R24: =A18 -> RECALC_0_4_ | S24: =S25 -> #VALUE! | T24: =AA24+AA30 -> #VALUE! | U24: =U25 -> #VALUE! | V24: =AC24+AC30 -> #VALUE! | Y24: =A18 -> RECALC_0_4_ | Z24: =Z25 -> 0 | AA24: =SUM(AH6,AH24,AH30,AH36) -> 0 | AB24: =AB25 -> 0 | AC24: =SUM(AJ6,AJ24,AJ30,AJ36) -> 0 | AF24: =A18 -> RECALC_0_4_ | AG24: =AG25 -> #VALUE! | AH24: =_xll.DBRW('Value Tree TESTE'!A3,A10,A13,AF24,A20,A23,"PROD099 - Others","Power (LMU/t)","Value") -> RECALC_1_234_ | AI24: =AI25 -> #VALUE! | AJ24: =_xll.DBRW('Value Tree TESTE'!A3,A10,A14,AF24,A20,A23,"PROD099 - Others","Power (LMU/t)","Value") -> RECALC_1_310_ | AM24: =A18 -> RECALC_0_4_ | AN24: =AN25 -> #VALUE! | AO24: =_xll.DBRW(A3,A10,A13,AM24,A20,A23,"PROD099 - Others","Power Price (LMU/MWh)","Value") -> RECALC_1_250_ | AP24: =AP25 -> #VALUE! | AQ24: =_xll.DBRW(A3,A10,A14,AM24,A20,A23,"PROD099 - Others","Power Price (LMU/MWh)","Value") -> RECALC_1_279_
A25: Produto | D25: L500 | E25: =IF(D21="+",IF(F23>F25,1,IF(F23>=F24,0,-1)),IF(D21="-",IF(F23<F25,1,IF(F23<=F24,0,-1)))) -> 1 | F25: =_xll.DBRW('Value Tree TESTE'!A3,A10,A13,D25,A20,A23,A26,"% ROIC","Value") -> RECALC_1_155_ | G25: =IF(D21="+",IF(H23>H25,1,IF(H23>=H24,0,-1)),IF(D21="-",IF(H23<H25,1,IF(H23<=H24,0,-1)))) -> 1 | H25: =_xll.DBRW('Value Tree TESTE'!A3,A10,A14,D25,A20,A23,A26,"% ROIC","Value") -> RECALC_1_153_ | K25: L500 | L25: =IF(K21="+",IF(M23>M25*(1+IF(M25>0,$C$4,-$C$4)),1,IF(M23>=M24*(1+IF(M24>0,-$C$4,$C$4)),0,-1)),IF(K21="-",IF(M23<M25*(1+IF(M25>0,-$C$4,$C$4)),1,IF(M23<=M24*(1+IF(M24>0,$C$4,-$C$4)),0,-1)))) -> #VALUE! | M25: =_xll.DBRW('Value Tree TESTE'!A3,A10,A13,K25,A20,A23,"PROD099 - Others","Working Capital Balance","Value") -> RECALC_1_113_ | N25: =IF(K21="+",IF(O23>O25*(1+IF(O25>0,$C$4,-$C$4)),1,IF(O23>=O24*(1+IF(O24>0,-$C$4,$C$4)),0,-1)),IF(K21="-",IF(O23<O25*(1+IF(O25>0,-$C$4,$C$4)),1,IF(O23<=O24*(1+IF(O24>0,$C$4,-$C$4)),0,-1)))) -> #VALUE! | O25: =_xll.DBRW('Value Tree TESTE'!A3,A10,A14,K25,A20,A23,"PROD099 - Others","Working Capital Balance","Value") -> RECALC_1_161_ | R25: L500 | S25: =IF(R21="+",IF(T23>T25*(1+IF(T25>0,$C$4,-$C$4)),1,IF(T23>=T24*(1+IF(T24>0,-$C$4,$C$4)),0,-1)),IF(R21="-",IF(T23<T25*(1+IF(T25>0,-$C$4,$C$4)),1,IF(T23<=T24*(1+IF(T24>0,$C$4,-$C$4)),0,-1)))) -> #VALUE! | T25: =AA25+AA31 -> #VALUE! | U25: =IF(R21="+",IF(V23>V25*(1+IF(V25>0,$C$4,-$C$4)),1,IF(V23>=V24*(1+IF(V24>0,-$C$4,$C$4)),0,-1)),IF(R21="-",IF(V23<V25*(1+IF(V25>0,-$C$4,$C$4)),1,IF(V23<=V24*(1+IF(V24>0,$C$4,-$C$4)),0,-1)))) -> #VALUE! | V25: =AC25+AC31 -> #VALUE! | Y25: L500 | Z25: =IF(Y21="+",IF(AA23>AA25*(1+IF(AA25>0,$C$4,-$C$4)),0,IF(AA23>=AA24*(1+IF(AA24>0,-$C$4,$C$4)),0,-1)),IF(Y21="-",IF(AA23<AA25*(1+IF(AA25>0,-$C$4,$C$4)),0,IF(AA23<=AA24*(1+IF(AA24>0,$C$4,-$C$4)),0,-1)))) -> 0 | AA25: =SUM(AH7,AH25,AH31,AH37) -> 0 | AB25: =IF(Y21="+",IF(AC23>AC25*(1+IF(AC25>0,$C$4,-$C$4)),0,IF(AC23>=AC24*(1+IF(AC24>0,-$C$4,$C$4)),0,-1)),IF(Y21="-",IF(AC23<AC25*(1+IF(AC25>0,-$C$4,$C$4)),0,IF(AC23<=AC24*(1+IF(AC24>0,$C$4,-$C$4)),0,-1)))) -> 0 | AC25: =SUM(AJ7,AJ25,AJ31,AJ37) -> 0 | AF25: L500 | AG25: =IF(AF21="+",IF(AH23>AH25*(1+IF(AH25>0,$C$4,-$C$4)),0,IF(AH23>=AH24*(1+IF(AH24>0,-$C$4,$C$4)),0,-1)),IF(AF21="-",IF(AH23<AH25*(1+IF(AH25>0,-$C$4,$C$4)),0,IF(AH23<=AH24*(1+IF(AH24>0,$C$4,-$C$4)),0,-1)))) -> #VALUE! | AH25: =_xll.DBRW('Value Tree TESTE'!A3,A10,A13,AF25,A20,A23,"PROD099 - Others","Power (LMU/t)","Value") -> RECALC_1_146_ | AI25: =IF(AF21="+",IF(AJ23>AJ25*(1+IF(AJ25>0,$C$4,-$C$4)),0,IF(AJ23>=AJ24*(1+IF(AJ24>0,-$C$4,$C$4)),0,-1)),IF(AF21="-",IF(AJ23<AJ25*(1+IF(AJ25>0,-$C$4,$C$4)),0,IF(AJ23<=AJ24*(1+IF(AJ24>0,$C$4,-$C$4)),0,-1)))) -> #VALUE! | AJ25: =_xll.DBRW('Value Tree TESTE'!A3,A10,A14,AF25,A20,A23,"PROD099 - Others","Power (LMU/t)","Value") -> RECALC_1_139_ | AM25: L500 | AN25: =IF(AM21="+",IF(AO23>AO25*(1+IF(AO25>0,$C$4,-$C$4)),0,IF(AO23>=AO24*(1+IF(AO24>0,-$C$4,$C$4)),0,-1)),IF(AM21="-",IF(AO23<AO25*(1+IF(AO25>0,-$C$4,$C$4)),0,IF(AO23<=AO24*(1+IF(AO24>0,$C$4,-$C$4)),0,-1)))) -> #VALUE! | AO25: =_xll.DBRW(A3,A10,A13,AM25,A20,A23,"PROD099 - Others","Power Price (LMU/MWh)","Value") -> RECALC_1_81_ | AP25: =IF(AM21="+",IF(AQ23>AQ25*(1+IF(AQ25>0,$C$4,-$C$4)),0,IF(AQ23>=AQ24*(1+IF(AQ24>0,-$C$4,$C$4)),0,-1)),IF(AM21="-",IF(AQ23<AQ25*(1+IF(AQ25>0,-$C$4,$C$4)),0,IF(AQ23<=AQ24*(1+IF(AQ24>0,$C$4,-$C$4)),0,-1)))) -> #VALUE! | AQ25: =_xll.DBRW(A3,A10,A14,AM25,A20,A23,"PROD099 - Others","Power Price (LMU/MWh)","Value") -> RECALC_1_166_ | AU25: =S25 -> #VALUE!
A26: =_xll.SUBNM("CONS_VC:ALL.D.Products","","Total Products") -> RECALC_0_11_
K27: + | M27: YTD | O27: FY | R27: - | T27: YTD | V27: FY | Y27: - | AA27: YTD | AC27: FY | AF27: - | AH27: YTD | AJ27: FY | AM27: - | AO27: YTD | AQ27: FY
A28: Accounts_PNL | L28: Income Tax (€M) | S28: Fixed Cost (€M) | Z28: Cement Fix. Costs (€/t) | AG28: Raw Material (€/t) | AN28: Power Cons. (kWh/t)
A29: Net Profit | K29: =A17 -> RECALC_0_5_ | L29: =L31 -> #VALUE! | M29: =_xll.DBRW('Value Tree TESTE'!A3,A10,A13,K29,A20,A23,"PROD099 - Others","Income Tax LTM","Value") -> RECALC_1_406_ | N29: =N31 -> #VALUE! | O29: =_xll.DBRW('Value Tree TESTE'!A3,A10,A14,K29,A20,A23,"PROD099 - Others","Income Tax LTM","Value") -> RECALC_1_238_ | R29: =A17 -> RECALC_0_5_ | S29: =S31 -> #VALUE! | T29: {=_xll.DBRW(A4,A10,A13,R29,A20,A23,"PROD099","Fixed Costs","Total Value")} -> RECALC_1_422_ | U29: -109.89654 | V29: {=_xll.DBRW(A4,A10,A14,R29,A20,A23,"PROD099","Fixed Costs","Total Value")} -> RECALC_1_213_ | Y29: =A17 -> RECALC_0_5_ | Z29: =Z31 -> #VALUE! | AA29: =_xll.DBRW('Value Tree TESTE'!A3,A10,A13,Y29,A20,A23,"PROD099 - Others","Cement Fix. Costs (LMU/t)","Value") -> RECALC_1_220_ | AB29: =AB31 -> #VALUE! | AC29: =_xll.DBRW('Value Tree TESTE'!A3,A10,A14,Y29,A20,A23,"PROD099 - Others","Cement Fix. Costs (LMU/t)","Value") -> RECALC_1_180_ | AF29: =A17 -> RECALC_0_5_ | AG29: =AG31 -> #VALUE! | AH29: =_xll.DBRW('Value Tree TESTE'!A3,A10,A13,AF29,A20,A23,"PROD099 - Others","Raw Material (LMU/t)","Value") -> RECALC_1_342_ | AI29: =AI31 -> #VALUE! | AJ29: =_xll.DBRW('Value Tree TESTE'!A3,A10,A14,AF29,A20,A23,"PROD099 - Others","Raw Material (LMU/t)","Value") -> RECALC_1_427_ | AM29: =A17 -> RECALC_0_5_ | AN29: =AN31 -> #VALUE! | AO29: =_xll.DBRW(A3,A10,A13,AM29,A20,A23,"PROD099 - Others","Power Cons. (kWh/t)","Value") -> RECALC_1_488_ | AP29: 94.454379 | AQ29: =_xll.DBRW(A3,A10,A14,AM29,A20,A23,"PROD099 - Others","Power Cons. (kWh/t)","Value") -> RECALC_1_477_
K30: =A18 -> RECALC_0_4_ | L30: =L31 -> #VALUE! | M30: =_xll.DBRW('Value Tree TESTE'!A3,A10,A13,K30,A20,A23,"PROD099 - Others","Income Tax LTM","Value") -> RECALC_1_231_ | N30: =N31 -> #VALUE! | O30: =_xll.DBRW('Value Tree TESTE'!A3,A10,A14,K30,A20,A23,"PROD099 - Others","Income Tax LTM","Value") -> RECALC_1_286_ | R30: =A18 -> RECALC_0_4_ | S30: =S31 -> #VALUE! | T30: {=_xll.DBRW(A4,A10,A13,R30,A20,A23,"PROD099","Fixed Costs","Total Value")} -> RECALC_1_236_ | U30: =U31 -> #VALUE! | V30: {=_xll.DBRW(A4,A10,A14,R30,A20,A23,"PROD099","Fixed Costs","Total Value")} -> RECALC_1_328_ | Y30: =A18 -> RECALC_0_4_ | Z30: =Z31 -> #VALUE! | AA30: =_xll.DBRW('Value Tree TESTE'!A3,A10,A13,Y30,A20,A23,"PROD099 - Others","Cement Fix. Costs (LMU/t)","Value") -> RECALC_1_469_ | AB30: =AB31 -> #VALUE! | AC30: =_xll.DBRW('Value Tree TESTE'!A3,A10,A14,Y30,A20,A23,"PROD099 - Others","Cement Fix. Costs (LMU/t)","Value") -> RECALC_1_458_ | AF30: =A18 -> RECALC_0_4_ | AG30: =AG31 -> #VALUE! | AH30: =_xll.DBRW('Value Tree TESTE'!A3,A10,A13,AF30,A20,A23,"PROD099 - Others","Raw Material (LMU/t)","Value") -> RECALC_1_459_ | AI30: =AI31 -> #VALUE! | AJ30: =_xll.DBRW('Value Tree TESTE'!A3,A10,A14,AF30,A20,A23,"PROD099 - Others","Raw Material (LMU/t)","Value") -> RECALC_1_348_ | AM30: =A18 -> RECALC_0_4_ | AN30: =AN31 -> #VALUE! | AO30: =_xll.DBRW(A3,A10,A13,AM30,A20,A23,"PROD099 - Others","Power Cons. (kWh/t)","Value") -> RECALC_1_484_ | AP30: =AP31 -> #VALUE! | AQ30: =_xll.DBRW(A3,A10,A14,AM30,A20,A23,"PROD099 - Others","Power Cons. (kWh/t)","Value") -> RECALC_1_228_
A31: Accounts_ICF | K31: L500 | L31: =IF(K27="+",IF(M29>M31*(1+IF(M31>0,$C$4,-$C$4)),0,IF(M29>=M30*(1+IF(M30>0,-$C$4,$C$4)),0,-1)),IF(K27="-",IF(M29<M31*(1+IF(M31>0,-$C$4,$C$4)),0,IF(M29<=M30*(1+IF(M30>0,$C$4,-$C$4)),0,-1)))) -> #VALUE! | M31: =_xll.DBRW('Value Tree TESTE'!A3,A10,A13,K31,A20,A23,"PROD099 - Others","Income Tax LTM","Value") -> RECALC_1_148_ | N31: =IF(K27="+",IF(O29>O31*(1+IF(O31>0,$C$4,-$C$4)),0,IF(O29>=O30*(1+IF(O30>0,-$C$4,$C$4)),0,-1)),IF(K27="-",IF(O29<O31*(1+IF(O31>0,-$C$4,$C$4)),0,IF(O29<=O30*(1+IF(O30>0,$C$4,-$C$4)),0,-1)))) -> #VALUE! | O31: =_xll.DBRW('Value Tree TESTE'!A3,A10,A14,K31,A20,A23,"PROD099 - Others","Income Tax LTM","Value") -> RECALC_1_142_ | R31: L500 | S31: =IF(R27="+",IF(T29>T31*(1+IF(T31>0,$C$4,-$C$4)),0,IF(T29>=T30*(1+IF(T30>0,-$C$4,$C$4)),0,-1)),IF(R27="-",IF(T29<T31*(1+IF(T31>0,-$C$4,$C$4)),0,IF(T29<=T30*(1+IF(T30>0,$C$4,-$C$4)),0,-1)))) -> #VALUE! | T31: {=_xll.DBRW(A4,A10,A13,R31,A20,A23,"PROD099","Fixed Costs","Total Value")} -> RECALC_1_147_ | U31: =IF(R27="+",IF(V29>V31*(1+IF(V31>0,$C$4,-$C$4)),0,IF(V29>=V30*(1+IF(V30>0,-$C$4,$C$4)),0,-1)),IF(R27="-",IF(V29<V31*(1+IF(V31>0,-$C$4,$C$4)),0,IF(V29<=V30*(1+IF(V30>0,$C$4,-$C$4)),0,-1)))) -> #VALUE! | V31: {=_xll.DBRW(A4,A10,A14,R31,A20,A23,"PROD099","Fixed Costs","Total Value")} -> RECALC_1_162_ | Y31: L500 | Z31: =IF(Y27="+",IF(AA29>AA31*(1+IF(AA31>0,$C$4,-$C$4)),0,IF(AA29>=AA30*(1+IF(AA30>0,-$C$4,$C$4)),0,-1)),IF(Y27="-",IF(AA29<AA31*(1+IF(AA31>0,-$C$4,$C$4)),0,IF(AA29<=AA30*(1+IF(AA30>0,$C$4,-$C$4)),0,-1)))) -> #VALUE! | AA31: =_xll.DBRW('Value Tree TESTE'!A3,A10,A13,Y31,A20,A23,"PROD099 - Others","Cement Fix. Costs (LMU/t)","Value") -> RECALC_1_94_ | AB31: =IF(Y27="+",IF(AC29>AC31*(1+IF(AC31>0,$C$4,-$C$4)),0,IF(AC29>=AC30*(1+IF(AC30>0,-$C$4,$C$4)),0,-1)),IF(Y27="-",IF(AC29<AC31*(1+IF(AC31>0,-$C$4,$C$4)),0,IF(AC29<=AC30*(1+IF(AC30>0,$C$4,-$C$4)),0,-1)))) -> #VALUE! | AC31: =_xll.DBRW('Value Tree TESTE'!A3,A10,A14,Y31,A20,A23,"PROD099 - Others","Cement Fix. Costs (LMU/t)","Value") -> RECALC_1_167_ | AF31: L500 | AG31: =IF(AF27="+",IF(AH29>AH31*(1+IF(AH31>0,$C$4,-$C$4)),0,IF(AH29>=AH30*(1+IF(AH30>0,-$C$4,$C$4)),0,-1)),IF(AF27="-",IF(AH29<AH31*(1+IF(AH31>0,-$C$4,$C$4)),0,IF(AH29<=AH30*(1+IF(AH30>0,$C$4,-$C$4)),0,-1)))) -> #VALUE! | AH31: =_xll.DBRW('Value Tree TESTE'!A3,A10,A13,AF31,A20,A23,"PROD099 - Others","Raw Material (LMU/t)","Value") -> RECALC_1_152_ | AI31: =IF(AF27="+",IF(AJ29>AJ31*(1+IF(AJ31>0,$C$4,-$C$4)),0,IF(AJ29>=AJ30*(1+IF(AJ30>0,-$C$4,$C$4)),0,-1)),IF(AF27="-",IF(AJ29<AJ31*(1+IF(AJ31>0,-$C$4,$C$4)),0,IF(AJ29<=AJ30*(1+IF(AJ30>0,$C$4,-$C$4)),0,-1)))) -> #VALUE! | AJ31: =_xll.DBRW('Value Tree TESTE'!A3,A10,A14,AF31,A20,A23,"PROD099 - Others","Raw Material (LMU/t)","Value") -> RECALC_1_130_ | AM31: L500 | AN31: =IF(AM27="+",IF(AO29>AO31*(1+IF(AO31>0,$C$4,-$C$4)),0,IF(AO29>=AO30*(1+IF(AO30>0,-$C$4,$C$4)),0,-1)),IF(AM27="-",IF(AO29<AO31*(1+IF(AO31>0,-$C$4,$C$4)),0,IF(AO29<=AO30*(1+IF(AO30>0,$C$4,-$C$4)),0,-1)))) -> #VALUE! | AO31: =_xll.DBRW(A3,A10,A13,AM31,A20,A23,"PROD099 - Others","Power Cons. (kWh/t)","Value") -> RECALC_1_137_ | AP31: =IF(AM27="+",IF(AQ29>AQ31*(1+IF(AQ31>0,$C$4,-$C$4)),0,IF(AQ29>=AQ30*(1+IF(AQ30>0,-$C$4,$C$4)),0,-1)),IF(AM27="-",IF(AQ29<AQ31*(1+IF(AQ31>0,-$C$4,$C$4)),0,IF(AQ29<=AQ30*(1+IF(AQ30>0,$C$4,-$C$4)),0,-1)))) -> #VALUE! | AQ31: =_xll.DBRW(A3,A10,A14,AM31,A20,A23,"PROD099 - Others","Power Cons. (kWh/t)","Value") -> RECALC_1_160_ | AU31: =AG31 -> #VALUE!
A32: Change in cash
K33: + | M33: YTD | O33: FY | R33: - | T33: YTD | V33: FY | Y33: - | AA33: YTD | AC33: FY | AF33: - | AH33: YTD | AJ33: FY | AM33: - | AO33: YTD | AQ33: FY
L34: Fin. Results / FX / Oth (€M) | S34: SG&A (€M) | Z34: FC+SG&A/Net Sales (%) | AG34: Other Variable (€/t) | AN34: Clinker Factor (%)
A35: DFS.100.Profil_and_Loss | K35: =A17 -> RECALC_0_5_ | L35: =L37 -> #VALUE! | M35: =_xll.DBRW(A5,A10,A13,K35,A20,A23,"Financial Results",Planilha3!B$19)+_xll.DBRW(A5,A10,A13,K35,A20,A23,"FX/Others",Planilha3!B$19)+_xll.DBRW(A5,A10,A13,K35,A20,A23,"Other",Planilha3!B$19) -> #VALUE! | N35: =N37 -> #VALUE! | O35: =_xll.DBRW(A5,A10,A14,K35,A20,A23,"Financial Results",Planilha3!B$19)+_xll.DBRW(A5,A10,A14,K35,A20,A23,"FX/Others",Planilha3!B$19)+_xll.DBRW(A5,A10,A14,K35,A20,A23,"Other",Planilha3!B$19) -> #VALUE! | R35: =A17 -> RECALC_0_5_ | S35: =S37 -> #VALUE! | T35: =_xll.DBRW('Value Tree TESTE'!A3,A10,A13,R35,A20,A23,"PROD099 - Others","ZBB Total","Value") -> RECALC_1_235_ | U35: =U37 -> -1 | V35: =_xll.DBRW('Value Tree TESTE'!A3,A10,A14,R35,A20,A23,"PROD099 - Others","ZBB Total","Value") -> RECALC_1_204_ | Y35: =A17 -> RECALC_0_5_ | Z35: =Z37 -> #VALUE! | AA35: =(T29+T35)/T5 -> #VALUE! | AB35: =AB37 -> #VALUE! | AC35: =(V29+V35)/V5 -> #VALUE! | AF35: =A17 -> RECALC_0_5_ | AG35: =AG37 -> #VALUE! | AH35: =_xll.DBRW(A3,A10,A13,AF35,A20,A23,"PROD099 - Others","Other Variable (LMU/t)","Value") -> RECALC_1_339_ | AI35: =AI37 -> #VALUE! | AJ35: =_xll.DBRW(A3,A10,A14,AF35,A20,A23,"PROD099 - Others","Other Variable (LMU/t)","Value") -> RECALC_1_318_ | AM35: =A17 -> RECALC_0_5_ | AN35: =AN37 -> #VALUE! | AO35: =_xll.DBRW(A3,A10,A13,AM35,A20,A23,"PROD099 - Others","Clinker Factor (%)","Value") -> RECALC_1_429_ | AP35: =AP37 -> #REF! | AQ35: =_xll.DBRW(A3,A10,A14,AM35,A20,A23,"PROD099 - Others","Clinker Factor (%)","Value") -> RECALC_1_281_ | AS35: 75 | AT35: #REF!
A36: Value | K36: =A18 -> RECALC_0_4_ | L36: =L37 -> #VALUE! | M36: =_xll.DBRW(A5,A10,A13,K36,A20,A23,"Financial Results",Planilha3!B$19)+_xll.DBRW(A5,A10,A13,K36,A20,A23,"FX/Others",Planilha3!B$19)+_xll.DBRW(A5,A10,A13,K36,A20,A23,"Other",Planilha3!B$19) -> #VALUE! | N36: =N37 -> #VALUE! | O36: =_xll.DBRW(A5,A10,A14,K36,A20,A23,"Financial Results",Planilha3!B$19)+_xll.DBRW(A5,A10,A14,K36,A20,A23,"FX/Others",Planilha3!B$19)+_xll.DBRW(A5,A10,A14,K36,A20,A23,"Other",Planilha3!B$19) -> #VALUE! | R36: =A18 -> RECALC_0_4_ | S36: =S37 -> #VALUE! | T36: =_xll.DBRW('Value Tree TESTE'!A3,A10,A13,R36,A20,A23,"PROD099 - Others","ZBB Total","Value") -> RECALC_1_239_ | U36: =U37 -> -1 | V36: =_xll.DBRW('Value Tree TESTE'!A3,A10,A14,R36,A20,A23,"PROD099 - Others","ZBB Total","Value") -> RECALC_1_194_ | Y36: =A18 -> RECALC_0_4_ | Z36: =Z37 -> #VALUE! | AA36: =(T30+T36)/T6 -> #VALUE! | AB36: =AB37 -> #VALUE! | AC36: =(V30+V36)/V6 -> #VALUE! | AF36: =A18 -> RECALC_0_4_ | AG36: =AG37 -> #VALUE! | AH36: =_xll.DBRW(A3,A10,A13,AF36,A20,A23,"PROD099 - Others","Other Variable (LMU/t)","Value") -> RECALC_1_330_ | AI36: =AI37 -> #VALUE! | AJ36: =_xll.DBRW(A3,A10,A14,AF36,A20,A23,"PROD099 - Others","Other Variable (LMU/t)","Value") -> RECALC_1_451_ | AM36: =A18 -> RECALC_0_4_ | AN36: =AN37 -> #VALUE! | AO36: =_xll.DBRW(A3,A10,A13,AM36,A20,A23,"PROD099 - Others","Clinker Factor (%)","Value") -> RECALC_1_405_ | AP36: =AP37 -> #REF! | AQ36: =_xll.DBRW(A3,A10,A14,AM36,A20,A23,"PROD099 - Others","Clinker Factor (%)","Value") -> RECALC_1_255_ | AS36: 75 | AT36: #REF!
K37: L500 | L37: =IF(K33="+",IF(M35>M37*(1+IF(M37>0,$C$4,-$C$4)),0,IF(M35>=M36*(1+IF(M36>0,-$C$4,$C$4)),0,-1)),IF(K33="-",IF(M35<M37*(1+IF(M37>0,-$C$4,$C$4)),0,IF(M35<=M36*(1+IF(M36>0,$C$4,-$C$4)),0,-1)))) -> #VALUE! | M37: =_xll.DBRW(A5,A10,A13,K37,A20,A23,"Financial Results",Planilha3!B$19)+_xll.DBRW(A5,A10,A13,K37,A20,A23,"FX/Others",Planilha3!B$19)+_xll.DBRW(A5,A10,A13,K37,A20,A23,"Other",Planilha3!B$19) -> #VALUE! | N37: =IF(K33="+",IF(O35>O37*(1+IF(O37>0,$C$4,-$C$4)),0,IF(O35>=O36*(1+IF(O36>0,-$C$4,$C$4)),0,-1)),IF(K33="-",IF(O35<O37*(1+IF(O37>0,-$C$4,$C$4)),0,IF(O35<=O36*(1+IF(O36>0,$C$4,-$C$4)),0,-1)))) -> #VALUE! | O37: =_xll.DBRW(A5,A10,A14,K37,A20,A23,"Financial Results",Planilha3!B$19)+_xll.DBRW(A5,A10,A14,K37,A20,A23,"FX/Others",Planilha3!B$19)+_xll.DBRW(A5,A10,A14,K37,A20,A23,"Other",Planilha3!B$19) -> #VALUE! | R37: L500 | S37: =IF(R33="+",IF(T35>T37*(1+IF(T37>0,$C$4,-$C$4)),0,IF(T35>=T36*(1+IF(T36>0,-$C$4,$C$4)),0,-1)),IF(R33="-",IF(T35<T37*(1+IF(T37>0,-$C$4,$C$4)),0,IF(T35<=T36*(1+IF(T36>0,$C$4,-$C$4)),0,-1)))) -> #VALUE! | T37: =_xll.DBRW('Value Tree TESTE'!A3,A10,A13,R37,A20,A23,"PROD099 - Others","ZBB Total","Value") -> RECALC_1_108_ | U37: =IF(R33="+",IF(V35>V37,1,IF(V35>=V36,0,-1)),IF(R33="-",IF(V35<V37,1,IF(V35<=V36,0,-1)))) -> -1 | V37: =_xll.DBRW('Value Tree TESTE'!A3,A10,A14,R37,A20,A23,"PROD099 - Others","ZBB Total","Value") -> RECALC_1_124_ | Y37: L500 | Z37: =IF(Y33="+",IF(AA35>AA37,1,IF(AA35>=AA36,0,-1)),IF(Y33="-",IF(AA35<AA37,1,IF(AA35<=AA36,0,-1)))) -> #VALUE! | AA37: =(T30+T36)/T7 -> #VALUE! | AB37: =IF(Y33="+",IF(AC35>AC37,1,IF(AC35>=AC36,0,-1)),IF(Y33="-",IF(AC35<AC37,1,IF(AC35<=AC36,0,-1)))) -> #VALUE! | AC37: =(V30+V36)/V7 -> #VALUE! | AF37: L500 | AG37: =IF(AF33="+",IF(AH35>AH37*(1+IF(AH37>0,$C$4,-$C$4)),0,IF(AH35>=AH36*(1+IF(AH36>0,-$C$4,$C$4)),0,-1)),IF(AF33="-",IF(AH35<AH37*(1+IF(AH37>0,-$C$4,$C$4)),0,IF(AH35<=AH36*(1+IF(AH36>0,$C$4,-$C$4)),0,-1)))) -> #VALUE! | AH37: =_xll.DBRW(A3,A10,A13,AF37,A20,A23,"PROD099 - Others","Other Variable (LMU/t)","Value") -> RECALC_1_114_ | AI37: =IF(AF33="+",IF(AJ35>AJ37*(1+IF(AJ37>0,$C$4,-$C$4)),0,IF(AJ35>=AJ36*(1+IF(AJ36>0,-$C$4,$C$4)),0,-1)),IF(AF33="-",IF(AJ35<AJ37*(1+IF(AJ37>0,-$C$4,$C$4)),0,IF(AJ35<=AJ36*(1+IF(AJ36>0,$C$4,-$C$4)),0,-1)))) -> #VALUE! | AJ37: =_xll.DBRW(A3,A10,A14,AF37,A20,A23,"PROD099 - Others","Other Variable (LMU/t)","Value") -> RECALC_1_159_ | AM37: L500 | AN37: =IF(AM33="+",IF(AO35>AO37*(1+IF(AO37>0,$C$4,-$C$4)),0,IF(AO35>=AO36*(1+IF(AO36>0,-$C$4,$C$4)),0,-1)),IF(AM33="-",IF(AO35<AO37*(1+IF(AO37>0,-$C$4,$C$4)),0,IF(AO35<=AO36*(1+IF(AO36>0,$C$4,-$C$4)),0,-1)))) -> #VALUE! | AO37: =_xll.DBRW(A3,A10,A13,AM37,A20,A23,"PROD099 - Others","Clinker Factor (%)","Value") -> RECALC_1_80_ | AP37: =IF(AM33="+",IF(AT35>AQ37*(1+IF(AQ37>0,$C$4,-$C$4)),0,IF(AT35>=AT36*(1+IF(AT36>0,-$C$4,$C$4)),0,-1)),IF(AM33="-",IF(AT35<AQ37*(1+IF(AQ37>0,-$C$4,$C$4)),0,IF(AT35<=AT36*(1+IF(AT36>0,$C$4,-$C$4)),0,-1)))) -> #REF! | AQ37: =_xll.DBRW(A3,A10,A14,AM37,A20,A23,"PROD099 - Others","Clinker Factor (%)","Value") -> RECALC_1_77_
A38: DFS.M.140.Indirect_Cash_Flow
A39: Total Value
D42: + | F42: Higher is better
D43: - | F43: Lower is better
E45: Driver Name | G45: FY
D46: RF | F46: YTD Actual | H46: FY RF
D47: L300 | F47: YTD L300 | H47: FY L300
V48: =CA48+CA56 -> 0
E49: Better than L500
C50: 0.02 | E50: Better than L300, worse than L500
E51: Worse than L300
H53: 102 | J53: -98
H54: 100 | J54: -100
H55: 98 | J55: -102 | W55: =CA56 -> 0
V56: =CA48+CA56 -> 0
F57: Cambiada la fórmula
F58: =IF(Z33="+";IF(AB35>AB37*(1+IF(AB37>0;$A$4;-$A$4));1;IF(AB35>=AB36*(1+IF(AB36>0;-$A$4;$A$4));0;-1));IF(Z33="-";IF(AB35<AB37*(1+IF(AB37>0;-$A$4;$A$4));1;IF(AB35<=AB36*(1+IF(AB36>0;$A$4;-$A$4));0;-1))))
F59: por
F60: =IF(Z33="+";IF(AB35>AB37*(1+IF(AB37>0;$A$4;-$A$4));0;IF(AB35>=AB36*(1+IF(AB36>0;-$A$4;$A$4));0;-1));IF(Z33="-";IF(AB35<AB37*(1+IF(AB37>0;-$A$4;$A$4));0;IF(AB35<=AB36*(1+IF(AB36>0;$A$4;-$A$4));0;-1))))
A62: DFS.200.KPIs
A63: Value

Sheet Value Tree 1 - Fx
A2: Cubo
A3: CONS_VC:DFS.200.KPIs
A4: CONS_VC:DFS.100.Profit_and_loss
A5: CONS_VC:DFS.140.Indirect_Cash_Flow | AC5: EBITDA LTM
A6: CONS_VC:DFS.180.Gross_Debt | R6: =$A$13 -> RECALC_0_9_ | V6: =$A$14 -> RECALC_0_10_ | AC6: =$A$13 -> RECALC_0_9_ | AF6: =$A$13 -> RECALC_0_9_ | AJ6: =$A$14 -> RECALC_0_10_ | AM6: =$A$14 -> RECALC_0_10_ | AZ6: =$A$13 -> RECALC_0_9_ | BD6: =$A$14 -> RECALC_0_10_
A7: CONS_VC:REV.100.Revenue_Consolidated | Q7: Net Debt (M) | AB7: EBITDA (BRL M) Mg. EBITDA - VCBR | AS7: EBITDA VCBR Breakdown (BRL M)
G8: =$A$13 -> RECALC_0_9_ | K8: =$A$14 -> RECALC_0_10_ | P8: ='Value Tree 1'!$F$4 -> RECALC_0_5_ | R8: {=_xll.DBRW(A6,A10,R6,P8,A20,A23,"Closing Balance Debt",A39)} -> RECALC_1_52_ | V8: {=_xll.DBRW(A6,A10,V6,P8,A20,A23,"Closing Balance Debt",A39)} -> RECALC_1_47_ | AA8: ='Value Tree 1'!$F$4 -> RECALC_0_5_ | AC8: =_xll.DBRW($A$3,$A$10,AC$6,$AA8,$AQ8,$AP8,"Total Products","EBITDA LTM","Value") -> RECALC_1_21_ | AJ8: =_xll.DBRW($A$3,$A$10,AJ$6,$AA8,$AQ8,$AP8,"Total Products","EBITDA LTM","Value") -> RECALC_1_23_ | AP8: =_xll.SUBNM("CONS_VC:ALL.D.Region","","VCBR") -> RECALC_0_6_ | AQ8: BRL Conv. | AS8: Cement | AZ8: =_xll.DBRW($A$3,$A$10,AZ$6,$BX8,$BT8,$BV8,$BZ8,"EBITDA LTM","Value") -> RECALC_1_103_ | BD8: =_xll.DBRW($A$3,$A$10,BD$6,$BX8,$BT8,$BV8,$BZ8,"EBITDA LTM","Value") -> RECALC_1_97_ | BT8: BRL Conv. | BV8: VCBR | BX8: RF | BZ8: PRODCE010 - Cement
A9: Ano | F9: Net Debt / Adj EBITDA (x) | P9: ='Value Tree 1'!$F$5 -> RECALC_0_4_ | R9: {=_xll.DBRW(A6,A10,R6,P9,A20,A23,"Closing Balance Debt",A39)} -> RECALC_1_76_ | V9: {=_xll.DBRW(A6,A10,V6,P9,A20,A23,"Closing Balance Debt",A39)} -> RECALC_1_84_ | AA9: ='Value Tree 1'!$F$5 -> RECALC_0_4_ | AC9: =_xll.DBRW($A$3,$A$10,AC$6,$AA9,$AQ9,$AP9,"Total Products","EBITDA LTM","Value") -> RECALC_1_20_ | AJ9: =_xll.DBRW($A$3,$A$10,AJ$6,$AA9,$AQ9,$AP9,"Total Products","EBITDA LTM","Value") -> RECALC_1_22_ | AP9: =_xll.SUBNM("CONS_VC:ALL.D.Region","","VCBR") -> RECALC_0_6_ | AQ9: BRL Conv. | AS9: Ready Mix | AZ9: =_xll.DBRW($A$3,$A$10,AZ$6,$BX9,$BT9,$BV9,$BZ9,"EBITDA LTM","Value") -> RECALC_1_32_ | BD9: =_xll.DBRW($A$3,$A$10,BD$6,$BX9,$BT9,$BV9,$BZ9,"EBITDA LTM","Value") -> RECALC_1_95_ | BT9: BRL Conv. | BV9: VCBR | BX9: RF | BZ9: PRODRM010 - Ready Mix
A10: =_xll.SUBNM("CONS_VC:ALL.D.Year","","2025") -> RECALC_0_7_ | E10: ='Value Tree 1'!$F$4 -> RECALC_0_5_ | G10: =_xll.DBRW(A6,A10,G8,E10,A20,A23,"Closing Balance Debt",A39)/_xll.DBRW(A3,A10,G8,E10,A20,A23,"Total Products","EBITDA Adjacências","Value") -> #VALUE! | K10: =_xll.DBRW(A6,A10,K8,E10,A20,A23,"Closing Balance Debt",A39)/_xll.DBRW(A3,A10,K8,E10,A20,A23,"Total Products","EBITDA Adjacências","Value") -> #VALUE! | R10: =$A$13 -> RECALC_0_9_ | V10: =$A$14 -> RECALC_0_10_ | AB10: EBIT (BRL M) Mg. EBIT - VCBR | AS10: Aggregates | AZ10: =_xll.DBRW($A$3,$A$10,AZ$6,$BX10,$BT10,$BV10,$BZ10,"EBITDA LTM","Value") -> RECALC_1_41_ | BD10: =_xll.DBRW($A$3,$A$10,BD$6,$BX10,$BT10,$BV10,$BZ10,"EBITDA LTM","Value") -> RECALC_1_39_ | BT10: BRL Conv. | BV10: VCBR | BX10: RF | BZ10: PRODAG010 - Aggregates
E11: ='Value Tree 1'!$F$5 -> RECALC_0_4_ | G11: =_xll.DBRW(A6,A10,G8,E11,A20,A23,"Closing Balance Debt",A39)/_xll.DBRW(A3,A10,G8,E11,A20,A23,"Total Products","EBITDA Adjacências","Value") -> #VALUE! | K11: =_xll.DBRW(A6,A10,K8,E11,A20,A23,"Closing Balance Debt",A39)/_xll.DBRW(A3,A10,K8,E11,A20,A23,"Total Products","EBITDA Adjacências","Value") -> #VALUE! | Q11: EBITDA (M) | AA11: ='Value Tree 1'!$F$4 -> RECALC_0_5_ | AP11: =_xll.SUBNM("CONS_VC:ALL.D.Region","","VCBR") -> RECALC_0_6_ | AQ11: BRL Conv. | AS11: Mortars | AZ11: =_xll.DBRW($A$3,$A$10,AZ$6,$BX11,$BT11,$BV11,$BZ11,"EBITDA LTM","Value") -> RECALC_1_65_ | BD11: =_xll.DBRW($A$3,$A$10,BD$6,$BX11,$BT11,$BV11,$BZ11,"EBITDA LTM","Value") -> RECALC_1_105_ | BT11: BRL Conv. | BV11: VCBR | BX11: RF | BZ11: PRODMT010 - Mortars
A12: Mês | G12: =$A$13 -> RECALC_0_9_ | K12: =$A$14 -> RECALC_0_10_ | P12: ='Value Tree 1'!$F$4 -> RECALC_0_5_ | R12: =_xll.DBRW(A3,A10,R10,P12,A20,A23,"Total Products","EBITDA LTM","Value") -> RECALC_1_117_ | V12: =_xll.DBRW(A3,A10,V10,P12,A20,A23,"Total Products","EBITDA LTM","Value") -> RECALC_1_29_ | AA12: ='Value Tree 1'!$F$5 -> RECALC_0_4_ | AP12: =_xll.SUBNM("CONS_VC:ALL.D.Region","","VCBR") -> RECALC_0_6_ | AQ12: BRL Conv. | AS12: Agric Lime | AZ12: =_xll.DBRW($A$3,$A$10,AZ$6,$BX12,$BT12,$BV12,$BZ12,"EBITDA LTM","Value") -> RECALC_1_99_ | BD12: =_xll.DBRW($A$3,$A$10,BD$6,$BX12,$BT12,$BV12,$BZ12,"EBITDA LTM","Value") -> RECALC_1_102_ | BT12: BRL Conv. | BV12: VCBR | BX12: RF | BZ12: PRODAL010 - Ag. Lime
A13: =_xll.SUBNM("CONS_VC:ALL.D.Month",,"Total YTD","MEMBER_NAME") -> RECALC_0_9_ | F13: Net Profit (M) | P13: ='Value Tree 1'!$F$5 -> RECALC_0_4_ | R13: =_xll.DBRW(A3,A10,R10,P13,A20,A23,"Total Products","EBITDA LTM","Value") -> RECALC_1_119_ | V13: =_xll.DBRW(A3,A10,V10,P13,A20,A23,"Total Products","EBITDA LTM","Value") -> RECALC_1_27_ | AS13: Lime | AZ13: =_xll.DBRW($A$3,$A$10,AZ$6,$BX13,$BT13,$BV13,$BZ13,"EBITDA LTM","Value") -> RECALC_1_43_ | BD13: =_xll.DBRW($A$3,$A$10,BD$6,$BX13,$BT13,$BV13,$BZ13,"EBITDA LTM","Value") -> RECALC_1_71_ | BT13: BRL Conv. | BV13: VCBR | BX13: RF | BZ13: PRODLM010 - Lime
A14: =_xll.SUBNM("CONS_VC:ALL.D.Month",,"Year","MEMBER_NAME") -> RECALC_0_10_ | E14: ='Value Tree 1'!$F$4 -> RECALC_0_5_ | G14: =_xll.DBRW(A4,A10,G12,E14,A20,A23,A26,A29,A36) -> RECALC_1_59_ | K14: =_xll.DBRW(A4,A10,K12,E14,A20,A23,A26,A29,A36) -> RECALC_1_98_ | R14: =$A$13 -> RECALC_0_9_ | V14: =$A$14 -> RECALC_0_10_ | AS14: Motz | AZ14: =_xll.DBRW($A$3,$A$10,AZ$6,$BX14,$BT14,$BV14,$BZ14,"EBITDA LTM","Value") -> RECALC_1_62_ | BD14: =_xll.DBRW($A$3,$A$10,BD$6,$BX14,$BT14,$BV14,$BZ14,"EBITDA LTM","Value") -> RECALC_1_34_ | BT14: BRL Conv. | BV14: VCBR | BX14: RF | BZ14: PRODMZ010 - Motz
E15: ='Value Tree 1'!$F$5 -> RECALC_0_4_ | G15: =_xll.DBRW(A4,A10,G12,E15,A20,A23,A26,A29,A36) -> RECALC_1_57_ | K15: =_xll.DBRW(A4,A10,K12,E15,A20,A23,A26,A29,A36) -> RECALC_1_44_ | Q15: EBIT (M)
A16: Versão | P16: ='Value Tree 1'!$F$4 -> RECALC_0_5_ | R16: =_xll.DBRW(A3,A10,R14,P16,A20,A23,"Total Products","EBIT","Value") -> RECALC_1_36_ | V16: =_xll.DBRW(A3,A10,V14,P16,A20,A23,"Total Products","EBIT","Value") -> RECALC_1_121_ | AC16: =$A$13 -> RECALC_0_9_ | AF16: =$A$13 -> RECALC_0_9_ | AJ16: Year | AM16: Year | AZ16: =$A$13 -> RECALC_0_9_ | BD16: =$A$14 -> RECALC_0_10_
P17: ='Value Tree 1'!$F$5 -> RECALC_0_4_ | R17: =_xll.DBRW(A3,A10,R14,P17,A20,A23,"Total Products","EBIT","Value") -> RECALC_1_55_ | V17: =_xll.DBRW(A3,A10,V14,P17,A20,A23,"Total Products","EBIT","Value") -> RECALC_1_58_ | AB17: EBITDA (USD M) Mg. EBITDA - VCNA | AS17: EBITDA VCNA Breakdown (USD M)
AA18: ='Value Tree 1'!$F$4 -> RECALC_0_5_ | AC18: =_xll.DBRW($A$3,$A$10,AC$16,$AA18,$AQ18,$AP18,"Total Products","EBITDA LTM","Value") -> RECALC_1_17_ | AJ18: =_xll.DBRW($A$3,$A$10,AJ$16,$AA18,$AQ18,$AP18,"Total Products","EBITDA LTM","Value") -> RECALC_1_12_ | AP18: VCNA | AQ18: USD Conv. | AS18: Cement | AZ18: =_xll.DBRW($A$3,$A$10,AZ$16,$BX18,$BT18,$BV18,$BZ18,"EBITDA LTM","Value") -> RECALC_1_91_ | BD18: =_xll.DBRW($A$3,$A$10,BD$16,$BX18,$BT18,$BV18,$BZ18,"EBITDA LTM","Value") -> RECALC_1_100_ | BT18: USD Conv. | BV18: VCNA | BX18: RF | BZ18: PRODCE010 - Cement
A19: Currency | R19: =$A$13 -> RECALC_0_9_ | V19: =$A$14 -> RECALC_0_10_ | AA19: ='Value Tree 1'!$F$5 -> RECALC_0_4_ | AC19: =_xll.DBRW($A$3,$A$10,AC$16,$AA19,$AQ19,$AP19,"Total Products","EBITDA LTM","Value") -> RECALC_1_16_ | AJ19: =_xll.DBRW($A$3,$A$10,AJ$16,$AA19,$AQ19,$AP19,"Total Products","EBITDA LTM","Value") -> RECALC_1_13_ | AP19: VCNA | AQ19: USD Conv. | AS19: Ready Mix | AZ19: =_xll.DBRW($A$3,$A$10,AZ$16,$BX19,$BT19,$BV19,$BZ19,"EBITDA LTM","Value") -> RECALC_1_66_ | BD19: =_xll.DBRW($A$3,$A$10,BD$16,$BX19,$BT19,$BV19,$BZ19,"EBITDA LTM","Value") -> RECALC_1_56_ | BT19: USD Conv. | BV19: VCNA | BX19: RF | BZ19: PRODRM010 - Ready Mix
A20: =_xll.SUBNM("CONS_VC:ALL.D.Currency","","BRL") -> RECALC_0_8_ | Q20: Capex (M) | AB20: EBIT (USD M) Mg. EBITDA - VCNA | AS20: Aggregates | AZ20: =_xll.DBRW($A$3,$A$10,AZ$16,$BX20,$BT20,$BV20,$BZ20,"EBITDA LTM","Value") -> RECALC_1_104_ | BD20: =_xll.DBRW($A$3,$A$10,BD$16,$BX20,$BT20,$BV20,$BZ20,"EBITDA LTM","Value") -> RECALC_1_60_ | BT20: USD Conv. | BV20: VCNA | BX20: RF | BZ20: PRODAG010 - Aggregates
P21: ='Value Tree 1'!$F$4 -> RECALC_0_5_ | R21: =_xll.DBRW(A5,A10,R19,P21,A20,A23,"Expansion Capex",A39) -> RECALC_1_69_ | V21: =_xll.DBRW(A5,A10,V19,P21,A20,A23,"Expansion Capex",A39) -> RECALC_1_49_ | AA21: ='Value Tree 1'!$F$4 -> RECALC_0_5_ | AP21: VCNA | AQ21: USD Conv. | AS21: Corporate | AZ21: =_xll.DBRW($A$3,$A$10,AZ$16,$BX21,$BT21,$BV21,$BZ21,"EBITDA LTM","Value") -> RECALC_1_68_ | BD21: =_xll.DBRW($A$3,$A$10,BD$16,$BX21,$BT21,$BV21,$BZ21,"EBITDA LTM","Value") -> RECALC_1_63_ | BT21: USD Conv. | BV21: VCNA | BX21: RF | BZ21: PRODCORP - Corporate
A22: Region | P22: ='Value Tree 1'!$F$5 -> RECALC_0_4_ | R22: =_xll.DBRW(A5,A10,R19,P22,A20,A23,"Expansion Capex",A39) -> RECALC_1_90_ | V22: =_xll.DBRW(A5,A10,V19,P22,A20,A23,"Expansion Capex",A39) -> RECALC_1_126_ | AA22: ='Value Tree 1'!$F$5 -> RECALC_0_4_ | AP22: VCNA | AQ22: USD Conv.
A23: =_xll.SUBNM("CONS_VC:ALL.D.Region","DEFAuLT","Global") -> RECALC_0_3_ | G23: =$A$13 -> RECALC_0_9_ | K23: =$A$14 -> RECALC_0_10_ | R23: =$A$13 -> RECALC_0_9_ | V23: =$A$14 -> RECALC_0_10_
F24: FCF (M) | Q24: WK Capital (M) | AC24: =$A$13 -> RECALC_0_9_ | AF24: =$A$13 -> RECALC_0_9_ | AJ24: Year | AM24: Year | AZ24: =$A$13 -> RECALC_0_9_ | BD24: =$A$14 -> RECALC_0_10_ | BI24: =$A$13 -> RECALC_0_9_ | BM24: =$A$14 -> RECALC_0_10_
A25: Produto | E25: ='Value Tree 1'!$F$4 -> RECALC_0_5_ | G25: =_xll.DBRW('Value Tree TESTE'!A5,A10,G23,E25,A20,A23,A32,'Value Tree TESTE'!A39) -> RECALC_1_96_ | K25: =_xll.DBRW('Value Tree TESTE'!A5,A10,K23,E25,A20,A23,A32,'Value Tree TESTE'!A39) -> RECALC_1_125_ | P25: ='Value Tree 1'!$F$4 -> RECALC_0_5_ | R25: =_xll.DBRW(A3,A10,R23,P25,A20,A23,"Total Products","Working Capital Balance","Value") -> RECALC_1_38_ | V25: =_xll.DBRW(A3,A10,V23,P25,A20,A23,"Total Products","Working Capital Balance","Value") -> RECALC_1_54_ | AB25: EBITDA (EUR M) Mg. EBITDA - VCEA | AS25: EBITDA VCEA Breakdown (EUR M) | BH25: EBITDA VCEA (LMU M)
A26: =_xll.SUBNM("CONS_VC:ALL.D.Products","","Total Products") -> RECALC_0_11_ | E26: ='Value Tree 1'!$F$5 -> RECALC_0_4_ | G26: =_xll.DBRW('Value Tree TESTE'!A5,A10,G23,E26,A20,A23,A32,'Value Tree TESTE'!A39) -> RECALC_1_51_ | K26: =_xll.DBRW('Value Tree TESTE'!A5,A10,K23,E26,A20,A23,A32,'Value Tree TESTE'!A39) -> RECALC_1_40_ | P26: ='Value Tree 1'!$F$5 -> RECALC_0_4_ | R26: =_xll.DBRW(A3,A10,R23,P26,A20,A23,"Total Products","Working Capital Balance","Value") -> RECALC_1_64_ | V26: =_xll.DBRW(A3,A10,V23,P26,A20,A23,"Total Products","Working Capital Balance","Value") -> RECALC_1_46_ | AA26: ='Value Tree 1'!$F$4 -> RECALC_0_5_ | AP26: VCEAA | AQ26: EUR Conv. | AS26: Spain | AZ26: =_xll.DBRW($A$3,$A$10,AZ$24,$BX26,$BT26,$BV26,$BZ26,"EBITDA LTM","Value") -> RECALC_1_50_ | BD26: =_xll.DBRW($A$3,$A$10,BD$24,$BX26,$BT26,$BV26,$BZ26,"EBITDA LTM","Value") -> RECALC_1_42_ | BI26: =_xll.DBRW($A$3,$A$10,BI$24,$CH26,$CD26,$CF26,$CJ26,"EBITDA LTM","Value") -> RECALC_1_86_ | BM26: =_xll.DBRW($A$3,$A$10,BM$24,$CH26,$CD26,$CF26,$CJ26,"EBITDA LTM","Value") -> RECALC_1_28_ | BT26: EUR Conv. | BV26: VCEAA | BX26: RF | BZ26: Total Products | CD26: EUR | CF26: VCEAA | CH26: RF | CJ26: Total Products
G27: =$A$13 -> RECALC_0_9_ | K27: =$A$14 -> RECALC_0_10_ | R27: =$A$13 -> RECALC_0_9_ | V27: =$A$14 -> RECALC_0_10_ | AA27: ='Value Tree 1'!$F$5 -> RECALC_0_4_ | AP27: VCEAA | AQ27: EUR Conv. | AS27: Turkey | AZ27: =_xll.DBRW($A$3,$A$10,AZ$24,$BX27,$BT27,$BV27,$BZ27,"EBITDA LTM","Value") -> RECALC_1_50_ | BD27: =_xll.DBRW($A$3,$A$10,BD$24,$BX27,$BT27,$BV27,$BZ27,"EBITDA LTM","Value") -> RECALC_1_42_ | BI27: =_xll.DBRW($A$3,$A$10,BI$24,$CH27,$CD27,$CF27,$CJ27,"EBITDA LTM","Value") -> RECALC_1_35_ | BM27: =_xll.DBRW($A$3,$A$10,BM$24,$CH27,$CD27,$CF27,$CJ27,"EBITDA LTM","Value") -> RECALC_1_26_ | BT27: EUR Conv. | BV27: VCEAA | BX27: RF | BZ27: Total Products | CD27: TRY | CF27: VCEAA | CH27: RF | CJ27: Total Products
A28: Accounts_PNL | F28: ROIC (%) | Q28: Income Tax (M) | AB28: EBIT (EUR M) Mg. EBITDA - VCEA | AS28: Corporate | AZ28: =_xll.DBRW($A$3,$A$10,AZ$24,$BX28,$BT28,$BV28,$BZ28,"EBITDA LTM","Value") -> RECALC_1_50_ | BD28: =_xll.DBRW($A$3,$A$10,BD$24,$BX28,$BT28,$BV28,$BZ28,"EBITDA LTM","Value") -> RECALC_1_42_ | BI28: =_xll.DBRW($A$3,$A$10,BI$24,$CH28,$CD28,$CF28,$CJ28,"EBITDA LTM","Value") -> RECALC_1_86_ | BM28: =_xll.DBRW($A$3,$A$10,BM$24,$CH28,$CD28,$CF28,$CJ28,"EBITDA LTM","Value") -> RECALC_1_28_ | BT28: EUR Conv. | BV28: VCEAA | BX28: RF | BZ28: Total Products | CD28: EUR | CF28: VCEAA | CH28: RF | CJ28: Total Products
A29: Net Profit | E29: ='Value Tree 1'!$F$4 -> RECALC_0_5_ | G29: =_xll.DBRW(A3,A10,G27,E29,A20,A23,A26,"% ROIC","Value") -> RECALC_1_75_ | K29: =_xll.DBRW(A3,A10,K27,E29,A20,A23,A26,"% ROIC","Value") -> RECALC_1_74_ | P29: ='Value Tree 1'!$F$4 -> RECALC_0_5_ | R29: =_xll.DBRW(A3,A10,R27,P29,A20,A23,"Total Products","Income Tax LTM","Value") -> RECALC_1_120_ | V29: =_xll.DBRW(A3,A10,V27,P29,A20,A23,"Total Products","Income Tax LTM","Value") -> RECALC_1_88_ | AA29: ='Value Tree 1'!$F$4 -> RECALC_0_5_ | AP29: VCEAA | AQ29: EUR Conv.
E30: ='Value Tree 1'!$F$5 -> RECALC_0_4_ | G30: =_xll.DBRW(A3,A10,G27,E30,A20,A23,A26,"% ROIC","Value") -> RECALC_1_61_ | K30: =_xll.DBRW(A3,A10,K27,E30,A20,A23,A26,"% ROIC","Value") -> RECALC_1_72_ | P30: ='Value Tree 1'!$F$5 -> RECALC_0_4_ | R30: =_xll.DBRW(A3,A10,R27,P30,A20,A23,"Total Products","Income Tax LTM","Value") -> RECALC_1_118_ | V30: =_xll.DBRW(A3,A10,V27,P30,A20,A23,"Total Products","Income Tax LTM","Value") -> RECALC_1_37_ | AA30: ='Value Tree 1'!$F$5 -> RECALC_0_4_ | AP30: VCEAA | AQ30: EUR Conv.
A31: Accounts_ICF | R31: =$A$13 -> RECALC_0_9_ | V31: =$A$14 -> RECALC_0_10_
A32: Change in cash | Q32: Fin. Results (M) | AC32: =$A$13 -> RECALC_0_9_ | AF32: =$A$13 -> RECALC_0_9_ | AJ32: Year | AM32: Year | AZ32: =$A$13 -> RECALC_0_9_ | BD32: =$A$14 -> RECALC_0_10_ | BI32: =$A$13 -> RECALC_0_9_ | BM32: =$A$14 -> RECALC_0_10_
P33: ='Value Tree 1'!$F$4 -> RECALC_0_5_ | R33: =_xll.DBRW(A5,A10,R31,P33,A20,A23,"Financial Results",A39) -> RECALC_1_31_ | V33: =_xll.DBRW(A5,A10,V31,P33,A20,A23,"Financial Results",A39) -> RECALC_1_101_ | AB33: EBITDA (USD M) Mg. EBITDA - VCLatam | AS33: EBITDA VCLatam Breakdown (USD M) | BH33: EBITDA VCLatam (LMU M)
P34: ='Value Tree 1'!$F$5 -> RECALC_0_4_ | R34: =_xll.DBRW(A5,A10,R31,P34,A20,A23,"Financial Results",A39) -> RECALC_1_73_ | V34: =_xll.DBRW(A5,A10,V31,P34,A20,A23,"Financial Results",A39) -> RECALC_1_92_ | AA34: ='Value Tree 1'!$F$4 -> RECALC_0_5_ | AP34: VCLatam | AQ34: USD Conv. | AS34: Itacamba | AZ34: =_xll.DBRW($A$3,$A$10,AZ$32,$BX34,$BT34,$BV34,$BZ34,"EBITDA LTM","Value") -> RECALC_1_18_ | BD34: =_xll.DBRW($A$3,$A$10,BD$32,$BX34,$BT34,$BV34,$BZ34,"EBITDA LTM","Value") -> RECALC_1_19_ | BI34: =_xll.DBRW($A$3,$A$10,BI$32,$CH34,$CD34,$CF34,$CJ34,"EBITDA LTM","Value") -> RECALC_1_15_ | BM34: =_xll.DBRW($A$3,$A$10,BM$32,$CH34,$CD34,$CF34,$CJ34,"EBITDA LTM","Value") -> RECALC_1_25_ | BT34: USD Conv. | BV34: VCLatam | BX34: RF | BZ34: Total Products | CD34: BOB | CF34: VCLatam | CH34: RF | CJ34: Total Products
A35: DFS.100.Profil_and_Loss | AA35: ='Value Tree 1'!$F$5 -> RECALC_0_4_ | AP35: VCLatam | AQ35: USD Conv. | AS35: Artigas | AZ35: =_xll.DBRW($A$3,$A$10,AZ$32,$BX35,$BT35,$BV35,$BZ35,"EBITDA LTM","Value") -> RECALC_1_18_ | BD35: =_xll.DBRW($A$3,$A$10,BD$32,$BX35,$BT35,$BV35,$BZ35,"EBITDA LTM","Value") -> RECALC_1_19_ | BI35: =_xll.DBRW($A$3,$A$10,BI$32,$CH35,$CD35,$CF35,$CJ35,"EBITDA LTM","Value") -> RECALC_1_14_ | BM35: =_xll.DBRW($A$3,$A$10,BM$32,$CH35,$CD35,$CF35,$CJ35,"EBITDA LTM","Value") -> RECALC_1_24_ | BT35: USD Conv. | BV35: VCLatam | BX35: RF | BZ35: Total Products | CD35: UYU | CF35: VCLatam | CH35: RF | CJ35: Total Products
A36: Value | AB36: EBIT (USD M) Mg. EBITDA - VCLatam
AA37: ='Value Tree 1'!$F$4 -> RECALC_0_5_ | AP37: VCLatam | AQ37: USD Conv.
A38: DFS.M.140.Indirect_Cash_Flow | AA38: ='Value Tree 1'!$F$5 -> RECALC_0_4_ | AP38: VCLatam | AQ38: USD Conv.
A39: Total Value
A61: DFS.200.KPIs
A62: Value

Sheet Value Tree 1
F4: =_xll.SUBNM("CONS_VC:ALL.D.Version",,"RF","Descrição") -> RECALC_0_5_
F5: =_xll.SUBNM("CONS_VC:ALL.D.Version",,"L300","MEMBER_NAME") -> RECALC_0_4_
Q7: Net Debt (M) | AB7: EBITDA (BRL M) Mg. EBITDA - VCBR | AS7: EBITDA VCBR Breakdown (BRL M)
R8: ='Value Tree 1 - Fx'!R8 -> RECALC_1_52_ | V8: ='Value Tree 1 - Fx'!V8 -> RECALC_1_47_ | AC8: ='Value Tree 1 - Fx'!AC8 -> RECALC_1_21_ | AF8: ='Value Tree 1 - Fx'!AF8 -> 0 | AJ8: ='Value Tree 1 - Fx'!AJ8 -> RECALC_1_23_ | AM8: ='Value Tree 1 - Fx'!AM8 -> 0 | AS8: Cement | AZ8: ='Value Tree 1 - Fx'!AZ8 -> RECALC_1_103_ | BD8: ='Value Tree 1 - Fx'!BD8 -> RECALC_1_97_
F9: Net Debt / Adj EBITDA (x) | R9: ='Value Tree 1 - Fx'!R9 -> RECALC_1_76_ | V9: ='Value Tree 1 - Fx'!V9 -> RECALC_1_84_ | AC9: ='Value Tree 1 - Fx'!AC9 -> RECALC_1_20_ | AF9: ='Value Tree 1 - Fx'!AF9 -> 0 | AJ9: ='Value Tree 1 - Fx'!AJ9 -> RECALC_1_22_ | AM9: ='Value Tree 1 - Fx'!AM9 -> 0 | AS9: Ready Mix | AZ9: ='Value Tree 1 - Fx'!AZ9 -> RECALC_1_32_ | BD9: ='Value Tree 1 - Fx'!BD9 -> RECALC_1_95_
G10: ='Value Tree 1 - Fx'!G10 -> #VALUE! | K10: ='Value Tree 1 - Fx'!K10 -> #VALUE! | AB10: EBIT (BRL M) Mg. EBIT - VCBR | AS10: Aggregates | AZ10: ='Value Tree 1 - Fx'!AZ10 -> RECALC_1_41_ | BD10: ='Value Tree 1 - Fx'!BD10 -> RECALC_1_39_
G11: ='Value Tree 1 - Fx'!G11 -> #VALUE! | K11: ='Value Tree 1 - Fx'!K11 -> #VALUE! | Q11: EBITDA (M) | AC11: ='Value Tree 1 - Fx'!AC11 -> 0 | AF11: ='Value Tree 1 - Fx'!AF11 -> 0 | AJ11: ='Value Tree 1 - Fx'!AJ11 -> 0 | AM11: ='Value Tree 1 - Fx'!AM11 -> 0 | AS11: Mortars | AZ11: ='Value Tree 1 - Fx'!AZ11 -> RECALC_1_65_ | BD11: ='Value Tree 1 - Fx'!BD11 -> RECALC_1_105_
R12: ='Value Tree 1 - Fx'!R12 -> RECALC_1_117_ | V12: ='Value Tree 1 - Fx'!V12 -> RECALC_1_29_ | AC12: ='Value Tree 1 - Fx'!AC12 -> 0 | AF12: ='Value Tree 1 - Fx'!AF12 -> 0 | AJ12: ='Value Tree 1 - Fx'!AJ12 -> 0 | AM12: ='Value Tree 1 - Fx'!AM12 -> 0 | AS12: Agric Lime | AZ12: ='Value Tree 1 - Fx'!AZ12 -> RECALC_1_99_ | BD12: ='Value Tree 1 - Fx'!BD12 -> RECALC_1_102_
F13: Net Profit (M) | R13: ='Value Tree 1 - Fx'!R13 -> RECALC_1_119_ | V13: ='Value Tree 1 - Fx'!V13 -> RECALC_1_27_ | AS13: Lime | AZ13: ='Value Tree 1 - Fx'!AZ13 -> RECALC_1_43_ | BD13: ='Value Tree 1 - Fx'!BD13 -> RECALC_1_71_
G14: ='Value Tree 1 - Fx'!G14 -> RECALC_1_59_ | K14: ='Value Tree 1 - Fx'!K14 -> RECALC_1_98_ | AS14: Motz | AZ14: ='Value Tree 1 - Fx'!AZ14 -> RECALC_1_62_ | BD14: ='Value Tree 1 - Fx'!BD14 -> RECALC_1_34_
G15: ='Value Tree 1 - Fx'!G15 -> RECALC_1_57_ | K15: ='Value Tree 1 - Fx'!K15 -> RECALC_1_44_ | Q15: EBIT (M)
R16: ='Value Tree 1 - Fx'!R16 -> RECALC_1_36_ | V16: ='Value Tree 1 - Fx'!V16 -> RECALC_1_121_
R17: ='Value Tree 1 - Fx'!R17 -> RECALC_1_55_ | V17: ='Value Tree 1 - Fx'!V17 -> RECALC_1_58_ | AB17: EBITDA (USD M) Mg. EBITDA - VCNA | AS17: EBITDA VCNA Breakdown (USD M)
AC18: ='Value Tree 1 - Fx'!AC18 -> RECALC_1_17_ | AF18: ='Value Tree 1 - Fx'!AF18 -> 0 | AJ18: ='Value Tree 1 - Fx'!AJ18 -> RECALC_1_12_ | AM18: ='Value Tree 1 - Fx'!AM18 -> 0 | AS18: Cement | AZ18: ='Value Tree 1 - Fx'!AZ18 -> RECALC_1_91_ | BD18: ='Value Tree 1 - Fx'!BD18 -> RECALC_1_100_
AC19: ='Value Tree 1 - Fx'!AC19 -> RECALC_1_16_ | AF19: ='Value Tree 1 - Fx'!AF19 -> 0 | AJ19: ='Value Tree 1 - Fx'!AJ19 -> RECALC_1_13_ | AM19: ='Value Tree 1 - Fx'!AM19 -> 0 | AS19: Ready Mix | AZ19: ='Value Tree 1 - Fx'!AZ19 -> RECALC_1_66_ | BD19: ='Value Tree 1 - Fx'!BD19 -> RECALC_1_56_
Q20: Capex (M) | AB20: EBIT (USD M) Mg. EBITDA - VCNA | AS20: Aggregates | AZ20: ='Value Tree 1 - Fx'!AZ20 -> RECALC_1_104_ | BD20: ='Value Tree 1 - Fx'!BD20 -> RECALC_1_60_
R21: ='Value Tree 1 - Fx'!R21 -> RECALC_1_69_ | V21: ='Value Tree 1 - Fx'!V21 -> RECALC_1_49_ | AC21: ='Value Tree 1 - Fx'!AC21 -> 0 | AF21: ='Value Tree 1 - Fx'!AF21 -> 0 | AJ21: ='Value Tree 1 - Fx'!AJ21 -> 0 | AM21: ='Value Tree 1 - Fx'!AM21 -> 0 | AS21: Corporate | AZ21: ='Value Tree 1 - Fx'!AZ21 -> RECALC_1_68_ | BD21: ='Value Tree 1 - Fx'!BD21 -> RECALC_1_63_
R22: ='Value Tree 1 - Fx'!R22 -> RECALC_1_90_ | V22: ='Value Tree 1 - Fx'!V22 -> RECALC_1_126_ | AC22: ='Value Tree 1 - Fx'!AC22 -> 0 | AF22: ='Value Tree 1 - Fx'!AF22 -> 0 | AJ22: ='Value Tree 1 - Fx'!AJ22 -> 0 | AM22: ='Value Tree 1 - Fx'!AM22 -> 0
F24: FCF (M) | Q24: WK Capital (M)
G25: ='Value Tree 1 - Fx'!G25 -> RECALC_1_96_ | K25: ='Value Tree 1 - Fx'!K25 -> RECALC_1_125_ | R25: ='Value Tree 1 - Fx'!R25 -> RECALC_1_38_ | V25: ='Value Tree 1 - Fx'!V25 -> RECALC_1_54_ | AB25: EBITDA (EUR M) Mg. EBITDA - VCEA | AS25: EBITDA VCEA Breakdown (EUR M) | BH25: EBITDA VCEA (LMU M)
G26: ='Value Tree 1 - Fx'!G26 -> RECALC_1_51_ | K26: ='Value Tree 1 - Fx'!K26 -> RECALC_1_40_ | R26: ='Value Tree 1 - Fx'!R26 -> RECALC_1_64_ | V26: ='Value Tree 1 - Fx'!V26 -> RECALC_1_46_ | AC26: ='Value Tree 1 - Fx'!AC26 -> 0 | AF26: ='Value Tree 1 - Fx'!AF26 -> 0 | AJ26: ='Value Tree 1 - Fx'!AJ26 -> 0 | AM26: ='Value Tree 1 - Fx'!AM26 -> 0 | AS26: Spain | AZ26: ='Value Tree 1 - Fx'!AZ26 -> RECALC_1_50_ | BD26: ='Value Tree 1 - Fx'!BD26 -> RECALC_1_42_ | BI26: ='Value Tree 1 - Fx'!BI26 -> RECALC_1_86_ | BM26: ='Value Tree 1 - Fx'!BM26 -> RECALC_1_28_
AC27: ='Value Tree 1 - Fx'!AC27 -> 0 | AF27: ='Value Tree 1 - Fx'!AF27 -> 0 | AJ27: ='Value Tree 1 - Fx'!AJ27 -> 0 | AM27: ='Value Tree 1 - Fx'!AM27 -> 0 | AS27: Turkey | AZ27: ='Value Tree 1 - Fx'!AZ27 -> RECALC_1_50_ | BD27: ='Value Tree 1 - Fx'!BD27 -> RECALC_1_42_ | BI27: ='Value Tree 1 - Fx'!BI27 -> RECALC_1_35_ | BM27: ='Value Tree 1 - Fx'!BM27 -> RECALC_1_26_
F28: ROIC (%) | Q28: Income Tax (M) | AB28: EBIT (EUR M) Mg. EBITDA - VCEA | AS28: Corporate | AZ28: ='Value Tree 1 - Fx'!AZ28 -> RECALC_1_50_ | BD28: ='Value Tree 1 - Fx'!BD28 -> RECALC_1_42_ | BI28: ='Value Tree 1 - Fx'!BI28 -> RECALC_1_86_ | BM28: ='Value Tree 1 - Fx'!BM28 -> RECALC_1_28_
G29: ='Value Tree 1 - Fx'!G29 -> RECALC_1_75_ | K29: ='Value Tree 1 - Fx'!K29 -> RECALC_1_74_ | R29: ='Value Tree 1 - Fx'!R29 -> RECALC_1_120_ | V29: ='Value Tree 1 - Fx'!V29 -> RECALC_1_88_ | AC29: ='Value Tree 1 - Fx'!AC29 -> 0 | AF29: ='Value Tree 1 - Fx'!AF29 -> 0 | AJ29: ='Value Tree 1 - Fx'!AJ29 -> 0 | AM29: ='Value Tree 1 - Fx'!AM29 -> 0
G30: ='Value Tree 1 - Fx'!G30 -> RECALC_1_61_ | K30: ='Value Tree 1 - Fx'!K30 -> RECALC_1_72_ | R30: ='Value Tree 1 - Fx'!R30 -> RECALC_1_118_ | V30: ='Value Tree 1 - Fx'!V30 -> RECALC_1_37_ | AC30: ='Value Tree 1 - Fx'!AC30 -> 0 | AF30: ='Value Tree 1 - Fx'!AF30 -> 0 | AJ30: ='Value Tree 1 - Fx'!AJ30 -> 0 | AM30: ='Value Tree 1 - Fx'!AM30 -> 0
Q32: Fin. Results (M)
R33: ='Value Tree 1 - Fx'!R33 -> RECALC_1_31_ | V33: ='Value Tree 1 - Fx'!V33 -> RECALC_1_101_ | AB33: EBITDA (USD M) Mg. EBITDA - VCLatam | AS33: EBITDA VCLatam Breakdown (USD M) | BH33: EBITDA VCLatam (LMU M)
R34: ='Value Tree 1 - Fx'!R34 -> RECALC_1_73_ | V34: ='Value Tree 1 - Fx'!V34 -> RECALC_1_92_ | AC34: ='Value Tree 1 - Fx'!AC34 -> 0 | AF34: ='Value Tree 1 - Fx'!AF34 -> 0 | AJ34: ='Value Tree 1 - Fx'!AJ34 -> 0 | AM34: ='Value Tree 1 - Fx'!AM34 -> 0 | AS34: Itacamba | AZ34: ='Value Tree 1 - Fx'!AZ34 -> RECALC_1_18_ | BD34: ='Value Tree 1 - Fx'!BD34 -> RECALC_1_19_ | BI34: ='Value Tree 1 - Fx'!BI34 -> RECALC_1_15_ | BM34: ='Value Tree 1 - Fx'!BM34 -> RECALC_1_25_
AC35: ='Value Tree 1 - Fx'!AC35 -> 0 | AF35: ='Value Tree 1 - Fx'!AF35 -> 0 | AJ35: ='Value Tree 1 - Fx'!AJ35 -> 0 | AM35: ='Value Tree 1 - Fx'!AM35 -> 0 | AS35: Artigas | AZ35: ='Value Tree 1 - Fx'!AZ35 -> RECALC_1_18_ | BD35: ='Value Tree 1 - Fx'!BD35 -> RECALC_1_19_ | BI35: ='Value Tree 1 - Fx'!BI35 -> RECALC_1_14_ | BM35: ='Value Tree 1 - Fx'!BM35 -> RECALC_1_24_
AB36: EBIT (USD M) Mg. EBITDA - VCLatam
AC37: ='Value Tree 1 - Fx'!AC37 -> 0 | AF37: ='Value Tree 1 - Fx'!AF37 -> 0 | AJ37: ='Value Tree 1 - Fx'!AJ37 -> 0 | AM37: ='Value Tree 1 - Fx'!AM37 -> 0
AC38: ='Value Tree 1 - Fx'!AC38 -> 0 | AF38: ='Value Tree 1 - Fx'!AF38 -> 0 | AJ38: ='Value Tree 1 - Fx'!AJ38 -> 0 | AM38: ='Value Tree 1 - Fx'!AM38 -> 0
