Workbook
Name ID: "8cf5af60-f32c-4d17-a048-978f4aaf10e7"

Sheet Cons_Region
B1: =_xll.VIEW("CONS_VC_PRD:STG.100.DataBase_Uploads",F12) -> CONS_VC_PRD:STG.100.DataBase_Uploads:1238482367-298299361 | C1: =_xll.VIEW("CONS_VC_PRD:ALL.015.Region_Assumptions") -> CONS_VC_PRD:ALL.015.Region_Assumptions:1238482367-1481494521 | D1: =_xll.VIEW("CONS_VC_PRD:DFS.120.Financial_Results") -> CONS_VC_PRD:DFS.120.Financial_Results:1238482367-1083526962 | K1: Value | L1: N/A | M1: =_xll.SUBNM("CONS_VC_PRD:ALL.D.Version","","T3") -> T3 | N1: PROD099
B2: =_xll.VIEW("CONS_VC_PRD:REV.100.Revenue_Consolidated") -> CONS_VC_PRD:REV.100.Revenue_Consolidated:1238482367-226826383 | C2: =_xll.VIEW("CONS_VC_PRD:ALL.010.Economic_Assumptions") -> CONS_VC_PRD:ALL.010.Economic_Assumptions:1238482367145679083 | D2: =_xll.VIEW("CONS_VC_PRD:DFS.140.Indirect_Cash_Flow") -> CONS_VC_PRD:DFS.140.Indirect_Cash_Flow:1238482367-1117995735 | K2: Total Market | N2: Total Products
B3: =_xll.VIEW("CONS_VC_PRD:DFS.100.Profit_and_Loss") -> CONS_VC_PRD:DFS.100.Profit_and_Loss:123848236720210810 | C3: =_xll.VIEW("CONS_VC_PRD:DFS.160.Working_Capital") -> CONS_VC_PRD:DFS.160.Working_Capital:1238482367-2032607141 | D3: =_xll.VIEW("CONS_VC_PRD:ALL.004.Uploads_Status_Planning") -> CONS_VC_PRD:ALL.004.Uploads_Status_Planning:1238482367-886898250 | G3: Flag
B4: =_xll.VIEW("CONS_VC_PRD:ALL.001.Actual_Control") -> CONS_VC_PRD:ALL.001.Actual_Control:1238482367-2039581856 | C4: =_xll.VIEW("CONS_VC_PRD:DFS.180.Gross_Debt") -> CONS_VC_PRD:DFS.180.Gross_Debt:1238482367-1307852146
C5: =_xll.DBRW(Cons_Region!$B$4,Cons_Region!$F$12,Cons_Region!C15,$M$1,$G$3) -> ACTUAL | D5: =_xll.DBRW(Cons_Region!$B$4,Cons_Region!$F$12,Cons_Region!D15,$M$1,$G$3) | E5: =_xll.DBRW(Cons_Region!$B$4,Cons_Region!$F$12,Cons_Region!E15,$M$1,$G$3) | F5: =_xll.DBRW(Cons_Region!$B$4,Cons_Region!$F$12,Cons_Region!F15,$M$1,$G$3) | G5: =_xll.DBRW(Cons_Region!$B$4,Cons_Region!$F$12,Cons_Region!G15,$M$1,$G$3) | H5: =_xll.DBRW(Cons_Region!$B$4,Cons_Region!$F$12,Cons_Region!H15,$M$1,$G$3) | I5: =_xll.DBRW(Cons_Region!$B$4,Cons_Region!$F$12,Cons_Region!I15,$M$1,$G$3) | J5: =_xll.DBRW(Cons_Region!$B$4,Cons_Region!$F$12,Cons_Region!J15,$M$1,$G$3) | ... N5: =_xll.DBRW(Cons_Region!$B$4,Cons_Region!$F$12,Cons_Region!N15,$M$1,$G$3)
B7: Global Assumptions - Input
C12: =_xll.SUBNM("CONS_VC_PRD:ALL.D.Region","Nível 0","VCBR","MEMBER_NAME") -> VCBR | F12: =_xll.SUBNM("CONS_VC_PRD:ALL.D.Year","SYS_Picklist","2026","MEMBER_NAME") -> 2026 | H12: =_xll.SUBNM("CONS_VC_PRD:ALL.D.Currency","PAX","BRL","Nome alternativo") -> BRL | J12: Input Status: | K12: =_xll.DBRW($D$3,$M$1,$C$12,"Financial_Planning","Status") -> Open
O14: =$F$12+1 -> 2027 | P14: =$F$12+2 -> 2028 | Q14: =$F$12+3 -> 2029 | R14: =$F$12+4 -> 2030 | S14: =$F$12+5 -> 2031
C15: 01 | D15: 02 | E15: 03 | F15: 04 | G15: 05 | H15: 06 | I15: 07 | J15: 08 | K15: 09 | L15: 10 | M15: 11 | N15: 12 | O15: PE | P15: PE | Q15: PE | R15: PE | S15: PE
C16: =$F$12&"."&C15 -> 2026.01 | D16: =$F$12&"."&D15 -> 2026.02 | E16: =$F$12&"."&E15 -> 2026.03 | F16: =$F$12&"."&F15 -> 2026.04 | G16: =$F$12&"."&G15 -> 2026.05 | H16: =$F$12&"."&H15 -> 2026.06 | I16: =$F$12&"."&I15 -> 2026.07 | J16: =$F$12&"."&J15 -> 2026.08 | ... N16: =$F$12&"."&N15 -> 2026.12 | O16: PE | P16: PE | Q16: PE | R16: PE | S16: PE
B17: Begining FX Rate R$/US$ | C17: =_xll.DBRW($C$2,Cons_Region!$F$12,Cons_Region!$C$15,$M$1,$B17,$K$1) -> 0 | D17: =_xll.DBRW($C$2,Cons_Region!$F$12,Cons_Region!$C$15,$M$1,$B17,$K$1) -> 0 | E17: =_xll.DBRW($C$2,Cons_Region!$F$12,Cons_Region!$C$15,$M$1,$B17,$K$1) -> 0 | F17: =_xll.DBRW($C$2,Cons_Region!$F$12,Cons_Region!$C$15,$M$1,$B17,$K$1) -> 0 | G17: =_xll.DBRW($C$2,Cons_Region!$F$12,Cons_Region!$C$15,$M$1,$B17,$K$1) -> 0 | H17: =_xll.DBRW($C$2,Cons_Region!$F$12,Cons_Region!$C$15,$M$1,$B17,$K$1) -> 0 | I17: =_xll.DBRW($C$2,Cons_Region!$F$12,Cons_Region!$C$15,$M$1,$B17,$K$1) -> 0 | J17: =_xll.DBRW($C$2,Cons_Region!$F$12,Cons_Region!$C$15,$M$1,$B17,$K$1) -> 0 | ... N17: =_xll.DBRW($C$2,Cons_Region!$F$12,Cons_Region!$C$15,$M$1,$B17,$K$1) -> 0 | O17: =_xll.DBRW($C$2,$O$14,$O$16,$M$1,$B17,$K$1) -> 0 | P17: =_xll.DBRW($C$2,$O$14,$O$16,$M$1,$B17,$K$1) -> 0 | Q17: =_xll.DBRW($C$2,$O$14,$O$16,$M$1,$B17,$K$1) -> 0 | R17: =_xll.DBRW($C$2,$O$14,$O$16,$M$1,$B17,$K$1) -> 0 | S17: =_xll.DBRW($C$2,$O$14,$O$16,$M$1,$B17,$K$1) -> 0
B18: Average FX Rate R$/US$ | C18: =_xll.DBRW($C$2,Cons_Region!$F$12,Cons_Region!$C$15,$M$1,$B18,$K$1) -> 0 | D18: =_xll.DBRW($C$2,Cons_Region!$F$12,Cons_Region!$C$15,$M$1,$B18,$K$1) -> 0 | E18: =_xll.DBRW($C$2,Cons_Region!$F$12,Cons_Region!$C$15,$M$1,$B18,$K$1) -> 0 | F18: =_xll.DBRW($C$2,Cons_Region!$F$12,Cons_Region!$C$15,$M$1,$B18,$K$1) -> 0 | G18: =_xll.DBRW($C$2,Cons_Region!$F$12,Cons_Region!$C$15,$M$1,$B18,$K$1) -> 0 | H18: =_xll.DBRW($C$2,Cons_Region!$F$12,Cons_Region!$C$15,$M$1,$B18,$K$1) -> 0 | I18: =_xll.DBRW($C$2,Cons_Region!$F$12,Cons_Region!$C$15,$M$1,$B18,$K$1) -> 0 | J18: =_xll.DBRW($C$2,Cons_Region!$F$12,Cons_Region!$C$15,$M$1,$B18,$K$1) -> 0 | ... N18: =_xll.DBRW($C$2,Cons_Region!$F$12,Cons_Region!$C$15,$M$1,$B18,$K$1) -> 0 | O18: =_xll.DBRW($C$2,$O$14,$O$16,$M$1,$B18,$K$1) -> 0 | P18: =_xll.DBRW($C$2,$O$14,$O$16,$M$1,$B18,$K$1) -> 0 | Q18: =_xll.DBRW($C$2,$O$14,$O$16,$M$1,$B18,$K$1) -> 0 | R18: =_xll.DBRW($C$2,$O$14,$O$16,$M$1,$B18,$K$1) -> 0 | S18: =_xll.DBRW($C$2,$O$14,$O$16,$M$1,$B18,$K$1) -> 0
B19: Final FX Rate R$/US$ | C19: =_xll.DBRW($C$2,Cons_Region!$F$12,Cons_Region!$C$15,$M$1,$B19,$K$1) -> 0 | D19: =_xll.DBRW($C$2,Cons_Region!$F$12,Cons_Region!$C$15,$M$1,$B19,$K$1) -> 0 | E19: =_xll.DBRW($C$2,Cons_Region!$F$12,Cons_Region!$C$15,$M$1,$B19,$K$1) -> 0 | F19: =_xll.DBRW($C$2,Cons_Region!$F$12,Cons_Region!$C$15,$M$1,$B19,$K$1) -> 0 | G19: =_xll.DBRW($C$2,Cons_Region!$F$12,Cons_Region!$C$15,$M$1,$B19,$K$1) -> 0 | H19: =_xll.DBRW($C$2,Cons_Region!$F$12,Cons_Region!$C$15,$M$1,$B19,$K$1) -> 0 | I19: =_xll.DBRW($C$2,Cons_Region!$F$12,Cons_Region!$C$15,$M$1,$B19,$K$1) -> 0 | J19: =_xll.DBRW($C$2,Cons_Region!$F$12,Cons_Region!$C$15,$M$1,$B19,$K$1) -> 0 | ... N19: =_xll.DBRW($C$2,Cons_Region!$F$12,Cons_Region!$C$15,$M$1,$B19,$K$1) -> 0 | O19: =_xll.DBRW($C$2,$O$14,$O$16,$M$1,$B19,$K$1) -> 0 | P19: =_xll.DBRW($C$2,$O$14,$O$16,$M$1,$B19,$K$1) -> 0 | Q19: =_xll.DBRW($C$2,$O$14,$O$16,$M$1,$B19,$K$1) -> 0 | R19: =_xll.DBRW($C$2,$O$14,$O$16,$M$1,$B19,$K$1) -> 0 | S19: =_xll.DBRW($C$2,$O$14,$O$16,$M$1,$B19,$K$1) -> 0
B20: Begining FX Rate US$/EUR | C20: =_xll.DBRW($C$2,Cons_Region!$F$12,Cons_Region!$C$15,$M$1,$B20,$K$1) -> 0 | D20: =_xll.DBRW($C$2,Cons_Region!$F$12,Cons_Region!$C$15,$M$1,$B20,$K$1) -> 0 | E20: =_xll.DBRW($C$2,Cons_Region!$F$12,Cons_Region!$C$15,$M$1,$B20,$K$1) -> 0 | F20: =_xll.DBRW($C$2,Cons_Region!$F$12,Cons_Region!$C$15,$M$1,$B20,$K$1) -> 0 | G20: =_xll.DBRW($C$2,Cons_Region!$F$12,Cons_Region!$C$15,$M$1,$B20,$K$1) -> 0 | H20: =_xll.DBRW($C$2,Cons_Region!$F$12,Cons_Region!$C$15,$M$1,$B20,$K$1) -> 0 | I20: =_xll.DBRW($C$2,Cons_Region!$F$12,Cons_Region!$C$15,$M$1,$B20,$K$1) -> 0 | J20: =_xll.DBRW($C$2,Cons_Region!$F$12,Cons_Region!$C$15,$M$1,$B20,$K$1) -> 0 | ... N20: =_xll.DBRW($C$2,Cons_Region!$F$12,Cons_Region!$C$15,$M$1,$B20,$K$1) -> 0 | O20: =_xll.DBRW($C$2,$O$14,$O$16,$M$1,$B20,$K$1) -> 0 | P20: =_xll.DBRW($C$2,$O$14,$O$16,$M$1,$B20,$K$1) -> 0 | Q20: =_xll.DBRW($C$2,$O$14,$O$16,$M$1,$B20,$K$1) -> 0 | R20: =_xll.DBRW($C$2,$O$14,$O$16,$M$1,$B20,$K$1) -> 0 | S20: =_xll.DBRW($C$2,$O$14,$O$16,$M$1,$B20,$K$1) -> 0
B21: Average FX Rate US$/EUR | C21: =_xll.DBRW($C$2,Cons_Region!$F$12,Cons_Region!$C$15,$M$1,$B21,$K$1) -> 5 | D21: =_xll.DBRW($C$2,Cons_Region!$F$12,Cons_Region!$C$15,$M$1,$B21,$K$1) -> 5 | E21: =_xll.DBRW($C$2,Cons_Region!$F$12,Cons_Region!$C$15,$M$1,$B21,$K$1) -> 5 | F21: =_xll.DBRW($C$2,Cons_Region!$F$12,Cons_Region!$C$15,$M$1,$B21,$K$1) -> 5 | G21: =_xll.DBRW($C$2,Cons_Region!$F$12,Cons_Region!$C$15,$M$1,$B21,$K$1) -> 5 | H21: =_xll.DBRW($C$2,Cons_Region!$F$12,Cons_Region!$C$15,$M$1,$B21,$K$1) -> 5 | I21: =_xll.DBRW($C$2,Cons_Region!$F$12,Cons_Region!$C$15,$M$1,$B21,$K$1) -> 5 | J21: =_xll.DBRW($C$2,Cons_Region!$F$12,Cons_Region!$C$15,$M$1,$B21,$K$1) -> 5 | ... N21: =_xll.DBRW($C$2,Cons_Region!$F$12,Cons_Region!$C$15,$M$1,$B21,$K$1) -> 5 | O21: =_xll.DBRW($C$2,$O$14,$O$16,$M$1,$B21,$K$1) -> 0 | P21: =_xll.DBRW($C$2,$O$14,$O$16,$M$1,$B21,$K$1) -> 0 | Q21: =_xll.DBRW($C$2,$O$14,$O$16,$M$1,$B21,$K$1) -> 0 | R21: =_xll.DBRW($C$2,$O$14,$O$16,$M$1,$B21,$K$1) -> 0 | S21: =_xll.DBRW($C$2,$O$14,$O$16,$M$1,$B21,$K$1) -> 0
B22: Final FX Rate US$/EUR | C22: =_xll.DBRW($C$2,Cons_Region!$F$12,Cons_Region!$C$15,$M$1,$B22,$K$1) -> 0 | D22: =_xll.DBRW($C$2,Cons_Region!$F$12,Cons_Region!$C$15,$M$1,$B22,$K$1) -> 0 | E22: =_xll.DBRW($C$2,Cons_Region!$F$12,Cons_Region!$C$15,$M$1,$B22,$K$1) -> 0 | F22: =_xll.DBRW($C$2,Cons_Region!$F$12,Cons_Region!$C$15,$M$1,$B22,$K$1) -> 0 | G22: =_xll.DBRW($C$2,Cons_Region!$F$12,Cons_Region!$C$15,$M$1,$B22,$K$1) -> 0 | H22: =_xll.DBRW($C$2,Cons_Region!$F$12,Cons_Region!$C$15,$M$1,$B22,$K$1) -> 0 | I22: =_xll.DBRW($C$2,Cons_Region!$F$12,Cons_Region!$C$15,$M$1,$B22,$K$1) -> 0 | J22: =_xll.DBRW($C$2,Cons_Region!$F$12,Cons_Region!$C$15,$M$1,$B22,$K$1) -> 0 | ... N22: =_xll.DBRW($C$2,Cons_Region!$F$12,Cons_Region!$C$15,$M$1,$B22,$K$1) -> 0 | O22: =_xll.DBRW($C$2,$O$14,$O$16,$M$1,$B22,$K$1) -> 0 | P22: =_xll.DBRW($C$2,$O$14,$O$16,$M$1,$B22,$K$1) -> 0 | Q22: =_xll.DBRW($C$2,$O$14,$O$16,$M$1,$B22,$K$1) -> 0 | R22: =_xll.DBRW($C$2,$O$14,$O$16,$M$1,$B22,$K$1) -> 0 | S22: =_xll.DBRW($C$2,$O$14,$O$16,$M$1,$B22,$K$1) -> 0
B23: Câmbio Inicial UYU$/US$ | C23: =_xll.DBRW($C$2,Cons_Region!$F$12,Cons_Region!$C$15,$M$1,$B23,$K$1) -> 0 | D23: =_xll.DBRW($C$2,Cons_Region!$F$12,Cons_Region!$C$15,$M$1,$B23,$K$1) -> 0 | E23: =_xll.DBRW($C$2,Cons_Region!$F$12,Cons_Region!$C$15,$M$1,$B23,$K$1) -> 0 | F23: =_xll.DBRW($C$2,Cons_Region!$F$12,Cons_Region!$C$15,$M$1,$B23,$K$1) -> 0 | G23: =_xll.DBRW($C$2,Cons_Region!$F$12,Cons_Region!$C$15,$M$1,$B23,$K$1) -> 0 | H23: =_xll.DBRW($C$2,Cons_Region!$F$12,Cons_Region!$C$15,$M$1,$B23,$K$1) -> 0 | I23: =_xll.DBRW($C$2,Cons_Region!$F$12,Cons_Region!$C$15,$M$1,$B23,$K$1) -> 0 | J23: =_xll.DBRW($C$2,Cons_Region!$F$12,Cons_Region!$C$15,$M$1,$B23,$K$1) -> 0 | ... N23: =_xll.DBRW($C$2,Cons_Region!$F$12,Cons_Region!$C$15,$M$1,$B23,$K$1) -> 0 | O23: =_xll.DBRW($C$2,$O$14,$O$16,$M$1,$B23,$K$1) -> 0 | P23: =_xll.DBRW($C$2,$O$14,$O$16,$M$1,$B23,$K$1) -> 0 | Q23: =_xll.DBRW($C$2,$O$14,$O$16,$M$1,$B23,$K$1) -> 0 | R23: =_xll.DBRW($C$2,$O$14,$O$16,$M$1,$B23,$K$1) -> 0 | S23: =_xll.DBRW($C$2,$O$14,$O$16,$M$1,$B23,$K$1) -> 0
B24: Câmbio Médio UYU$/US$ | C24: =_xll.DBRW($C$2,Cons_Region!$F$12,Cons_Region!$C$15,$M$1,$B24,$K$1) -> 0 | D24: =_xll.DBRW($C$2,Cons_Region!$F$12,Cons_Region!$C$15,$M$1,$B24,$K$1) -> 0 | E24: =_xll.DBRW($C$2,Cons_Region!$F$12,Cons_Region!$C$15,$M$1,$B24,$K$1) -> 0 | F24: =_xll.DBRW($C$2,Cons_Region!$F$12,Cons_Region!$C$15,$M$1,$B24,$K$1) -> 0 | G24: =_xll.DBRW($C$2,Cons_Region!$F$12,Cons_Region!$C$15,$M$1,$B24,$K$1) -> 0 | H24: =_xll.DBRW($C$2,Cons_Region!$F$12,Cons_Region!$C$15,$M$1,$B24,$K$1) -> 0 | I24: =_xll.DBRW($C$2,Cons_Region!$F$12,Cons_Region!$C$15,$M$1,$B24,$K$1) -> 0 | J24: =_xll.DBRW($C$2,Cons_Region!$F$12,Cons_Region!$C$15,$M$1,$B24,$K$1) -> 0 | ... N24: =_xll.DBRW($C$2,Cons_Region!$F$12,Cons_Region!$C$15,$M$1,$B24,$K$1) -> 0 | O24: =_xll.DBRW($C$2,$O$14,$O$16,$M$1,$B24,$K$1) -> 0 | P24: =_xll.DBRW($C$2,$O$14,$O$16,$M$1,$B24,$K$1) -> 0 | Q24: =_xll.DBRW($C$2,$O$14,$O$16,$M$1,$B24,$K$1) -> 0 | R24: =_xll.DBRW($C$2,$O$14,$O$16,$M$1,$B24,$K$1) -> 0 | S24: =_xll.DBRW($C$2,$O$14,$O$16,$M$1,$B24,$K$1) -> 0
B25: Câmbio Final UYU$/US$ | C25: =_xll.DBRW($C$2,Cons_Region!$F$12,Cons_Region!$C$15,$M$1,$B25,$K$1) -> 0 | D25: =_xll.DBRW($C$2,Cons_Region!$F$12,Cons_Region!$C$15,$M$1,$B25,$K$1) -> 0 | E25: =_xll.DBRW($C$2,Cons_Region!$F$12,Cons_Region!$C$15,$M$1,$B25,$K$1) -> 0 | F25: =_xll.DBRW($C$2,Cons_Region!$F$12,Cons_Region!$C$15,$M$1,$B25,$K$1) -> 0 | G25: =_xll.DBRW($C$2,Cons_Region!$F$12,Cons_Region!$C$15,$M$1,$B25,$K$1) -> 0 | H25: =_xll.DBRW($C$2,Cons_Region!$F$12,Cons_Region!$C$15,$M$1,$B25,$K$1) -> 0 | I25: =_xll.DBRW($C$2,Cons_Region!$F$12,Cons_Region!$C$15,$M$1,$B25,$K$1) -> 0 | J25: =_xll.DBRW($C$2,Cons_Region!$F$12,Cons_Region!$C$15,$M$1,$B25,$K$1) -> 0 | ... N25: =_xll.DBRW($C$2,Cons_Region!$F$12,Cons_Region!$C$15,$M$1,$B25,$K$1) -> 0 | O25: =_xll.DBRW($C$2,$O$14,$O$16,$M$1,$B25,$K$1) -> 0 | P25: =_xll.DBRW($C$2,$O$14,$O$16,$M$1,$B25,$K$1) -> 0 | Q25: =_xll.DBRW($C$2,$O$14,$O$16,$M$1,$B25,$K$1) -> 0 | R25: =_xll.DBRW($C$2,$O$14,$O$16,$M$1,$B25,$K$1) -> 0 | S25: =_xll.DBRW($C$2,$O$14,$O$16,$M$1,$B25,$K$1) -> 0
B26: Câmbio Inicial ARS$/US$ | C26: =_xll.DBRW($C$2,Cons_Region!$F$12,Cons_Region!$C$15,$M$1,$B26,$K$1) -> 0 | D26: =_xll.DBRW($C$2,Cons_Region!$F$12,Cons_Region!$C$15,$M$1,$B26,$K$1) -> 0 | E26: =_xll.DBRW($C$2,Cons_Region!$F$12,Cons_Region!$C$15,$M$1,$B26,$K$1) -> 0 | F26: =_xll.DBRW($C$2,Cons_Region!$F$12,Cons_Region!$C$15,$M$1,$B26,$K$1) -> 0 | G26: =_xll.DBRW($C$2,Cons_Region!$F$12,Cons_Region!$C$15,$M$1,$B26,$K$1) -> 0 | H26: =_xll.DBRW($C$2,Cons_Region!$F$12,Cons_Region!$C$15,$M$1,$B26,$K$1) -> 0 | I26: =_xll.DBRW($C$2,Cons_Region!$F$12,Cons_Region!$C$15,$M$1,$B26,$K$1) -> 0 | J26: =_xll.DBRW($C$2,Cons_Region!$F$12,Cons_Region!$C$15,$M$1,$B26,$K$1) -> 0 | ... N26: =_xll.DBRW($C$2,Cons_Region!$F$12,Cons_Region!$C$15,$M$1,$B26,$K$1) -> 0 | O26: =_xll.DBRW($C$2,$O$14,$O$16,$M$1,$B26,$K$1) -> 0 | P26: =_xll.DBRW($C$2,$O$14,$O$16,$M$1,$B26,$K$1) -> 0 | Q26: =_xll.DBRW($C$2,$O$14,$O$16,$M$1,$B26,$K$1) -> 0 | R26: =_xll.DBRW($C$2,$O$14,$O$16,$M$1,$B26,$K$1) -> 0 | S26: =_xll.DBRW($C$2,$O$14,$O$16,$M$1,$B26,$K$1) -> 0
B27: Câmbio Médio ARS$/US$ | C27: =_xll.DBRW($C$2,Cons_Region!$F$12,Cons_Region!$C$15,$M$1,$B27,$K$1) -> 0 | D27: =_xll.DBRW($C$2,Cons_Region!$F$12,Cons_Region!$C$15,$M$1,$B27,$K$1) -> 0 | E27: =_xll.DBRW($C$2,Cons_Region!$F$12,Cons_Region!$C$15,$M$1,$B27,$K$1) -> 0 | F27: =_xll.DBRW($C$2,Cons_Region!$F$12,Cons_Region!$C$15,$M$1,$B27,$K$1) -> 0 | G27: =_xll.DBRW($C$2,Cons_Region!$F$12,Cons_Region!$C$15,$M$1,$B27,$K$1) -> 0 | H27: =_xll.DBRW($C$2,Cons_Region!$F$12,Cons_Region!$C$15,$M$1,$B27,$K$1) -> 0 | I27: =_xll.DBRW($C$2,Cons_Region!$F$12,Cons_Region!$C$15,$M$1,$B27,$K$1) -> 0 | J27: =_xll.DBRW($C$2,Cons_Region!$F$12,Cons_Region!$C$15,$M$1,$B27,$K$1) -> 0 | ... N27: =_xll.DBRW($C$2,Cons_Region!$F$12,Cons_Region!$C$15,$M$1,$B27,$K$1) -> 0 | O27: =_xll.DBRW($C$2,$O$14,$O$16,$M$1,$B27,$K$1) -> 0 | P27: =_xll.DBRW($C$2,$O$14,$O$16,$M$1,$B27,$K$1) -> 0 | Q27: =_xll.DBRW($C$2,$O$14,$O$16,$M$1,$B27,$K$1) -> 0 | R27: =_xll.DBRW($C$2,$O$14,$O$16,$M$1,$B27,$K$1) -> 0 | S27: =_xll.DBRW($C$2,$O$14,$O$16,$M$1,$B27,$K$1) -> 0
B28: Câmbio Final ARS$/US$ | C28: =_xll.DBRW($C$2,Cons_Region!$F$12,Cons_Region!$C$15,$M$1,$B28,$K$1) -> 0 | D28: =_xll.DBRW($C$2,Cons_Region!$F$12,Cons_Region!$C$15,$M$1,$B28,$K$1) -> 0 | E28: =_xll.DBRW($C$2,Cons_Region!$F$12,Cons_Region!$C$15,$M$1,$B28,$K$1) -> 0 | F28: =_xll.DBRW($C$2,Cons_Region!$F$12,Cons_Region!$C$15,$M$1,$B28,$K$1) -> 0 | G28: =_xll.DBRW($C$2,Cons_Region!$F$12,Cons_Region!$C$15,$M$1,$B28,$K$1) -> 0 | H28: =_xll.DBRW($C$2,Cons_Region!$F$12,Cons_Region!$C$15,$M$1,$B28,$K$1) -> 0 | I28: =_xll.DBRW($C$2,Cons_Region!$F$12,Cons_Region!$C$15,$M$1,$B28,$K$1) -> 0 | J28: =_xll.DBRW($C$2,Cons_Region!$F$12,Cons_Region!$C$15,$M$1,$B28,$K$1) -> 0 | ... N28: =_xll.DBRW($C$2,Cons_Region!$F$12,Cons_Region!$C$15,$M$1,$B28,$K$1) -> 0 | O28: =_xll.DBRW($C$2,$O$14,$O$16,$M$1,$B28,$K$1) -> 0 | P28: =_xll.DBRW($C$2,$O$14,$O$16,$M$1,$B28,$K$1) -> 0 | Q28: =_xll.DBRW($C$2,$O$14,$O$16,$M$1,$B28,$K$1) -> 0 | R28: =_xll.DBRW($C$2,$O$14,$O$16,$M$1,$B28,$K$1) -> 0 | S28: =_xll.DBRW($C$2,$O$14,$O$16,$M$1,$B28,$K$1) -> 0
... B30: American CPI | C30: =_xll.DBRW($C$2,Cons_Region!$F$12,Cons_Region!$C$15,$M$1,$B30,$K$1) -> 0 | D30: =_xll.DBRW($C$2,Cons_Region!$F$12,Cons_Region!$C$15,$M$1,$B30,$K$1) -> 0 | E30: =_xll.DBRW($C$2,Cons_Region!$F$12,Cons_Region!$C$15,$M$1,$B30,$K$1) -> 0 | F30: =_xll.DBRW($C$2,Cons_Region!$F$12,Cons_Region!$C$15,$M$1,$B30,$K$1) -> 0 | G30: =_xll.DBRW($C$2,Cons_Region!$F$12,Cons_Region!$C$15,$M$1,$B30,$K$1) -> 0 | H30: =_xll.DBRW($C$2,Cons_Region!$F$12,Cons_Region!$C$15,$M$1,$B30,$K$1) -> 0 | I30: =_xll.DBRW($C$2,Cons_Region!$F$12,Cons_Region!$C$15,$M$1,$B30,$K$1) -> 0 | J30: =_xll.DBRW($C$2,Cons_Region!$F$12,Cons_Region!$C$15,$M$1,$B30,$K$1) -> 0 | ... N30: =_xll.DBRW($C$2,Cons_Region!$F$12,Cons_Region!$C$15,$M$1,$B30,$K$1) -> 0 | O30: =_xll.DBRW($C$2,$O$14,$O$16,$M$1,$B30,$K$1) -> 0 | P30: =_xll.DBRW($C$2,$O$14,$O$16,$M$1,$B30,$K$1) -> 0 | Q30: =_xll.DBRW($C$2,$O$14,$O$16,$M$1,$B30,$K$1) -> 0 | R30: =_xll.DBRW($C$2,$O$14,$O$16,$M$1,$B30,$K$1) -> 0 | S30: =_xll.DBRW($C$2,$O$14,$O$16,$M$1,$B30,$K$1) -> 0
B31: Number of Days | C31: =_xll.DBRW($C$2,Cons_Region!$F$12,C$15,$M$1,$B31,$K$1) -> 31 | D31: =_xll.DBRW($C$2,Cons_Region!$F$12,D$15,$M$1,$B31,$K$1) -> 28 | E31: =_xll.DBRW($C$2,Cons_Region!$F$12,E$15,$M$1,$B31,$K$1) -> 31 | F31: =_xll.DBRW($C$2,Cons_Region!$F$12,F$15,$M$1,$B31,$K$1) -> 30 | G31: =_xll.DBRW($C$2,Cons_Region!$F$12,G$15,$M$1,$B31,$K$1) -> 31 | H31: =_xll.DBRW($C$2,Cons_Region!$F$12,H$15,$M$1,$B31,$K$1) -> 30 | I31: =_xll.DBRW($C$2,Cons_Region!$F$12,I$15,$M$1,$B31,$K$1) -> 31 | J31: =_xll.DBRW($C$2,Cons_Region!$F$12,J$15,$M$1,$B31,$K$1) -> 31 | ... N31: =_xll.DBRW($C$2,Cons_Region!$F$12,N$15,$M$1,$B31,$K$1) -> 31 | O31: =_xll.DBRW($C$2,$O$14,$O$16,$M$1,$B31,$K$1) -> 0 | P31: =_xll.DBRW($C$2,$O$14,$O$16,$M$1,$B31,$K$1) -> 0 | Q31: =_xll.DBRW($C$2,$O$14,$O$16,$M$1,$B31,$K$1) -> 0 | R31: =_xll.DBRW($C$2,$O$14,$O$16,$M$1,$B31,$K$1) -> 0 | S31: =_xll.DBRW($C$2,$O$14,$O$16,$M$1,$B31,$K$1) -> 0
B34: NET REVENUES
O36: =$F$12+1 -> 2027 | P36: =$F$12+2 -> 2028 | Q36: =$F$12+3 -> 2029 | R36: =$F$12+4 -> 2030 | S36: =$F$12+5 -> 2031
C37: =$F$12&"."&C15 -> 2026.01 | D37: =$F$12&"."&D15 -> 2026.02 | E37: =$F$12&"."&E15 -> 2026.03 | F37: =$F$12&"."&F15 -> 2026.04 | G37: =$F$12&"."&G15 -> 2026.05 | H37: =$F$12&"."&H15 -> 2026.06 | I37: =$F$12&"."&I15 -> 2026.07 | J37: =$F$12&"."&J15 -> 2026.08 | ... N37: =$F$12&"."&N15 -> 2026.12 | O37: PE | P37: PE | Q37: PE | R37: PE | S37: PE
B38: % Operational Tax | C38: =_xll.DBRW($B$2,Cons_Region!$F$12,Cons_Region!C$15,$M$1,Cons_Region!$H$12,Cons_Region!$C$12,$N$2,$K$2,$B$38) -> 0 | D38: =_xll.DBRW($B$2,Cons_Region!$F$12,Cons_Region!D$15,$M$1,Cons_Region!$H$12,Cons_Region!$C$12,$N$2,$K$2,$B$38) -> 0.3246 | E38: =_xll.DBRW($B$2,Cons_Region!$F$12,Cons_Region!E$15,$M$1,Cons_Region!$H$12,Cons_Region!$C$12,$N$2,$K$2,$B$38) -> 0.3331 | F38: =_xll.DBRW($B$2,Cons_Region!$F$12,Cons_Region!F$15,$M$1,Cons_Region!$H$12,Cons_Region!$C$12,$N$2,$K$2,$B$38) -> 0.3356 | G38: =_xll.DBRW($B$2,Cons_Region!$F$12,Cons_Region!G$15,$M$1,Cons_Region!$H$12,Cons_Region!$C$12,$N$2,$K$2,$B$38) -> 0.3349 | H38: =_xll.DBRW($B$2,Cons_Region!$F$12,Cons_Region!H$15,$M$1,Cons_Region!$H$12,Cons_Region!$C$12,$N$2,$K$2,$B$38) -> 0.3303 | I38: =_xll.DBRW($B$2,Cons_Region!$F$12,Cons_Region!I$15,$M$1,Cons_Region!$H$12,Cons_Region!$C$12,$N$2,$K$2,$B$38) -> 0.3308 | J38: =_xll.DBRW($B$2,Cons_Region!$F$12,Cons_Region!J$15,$M$1,Cons_Region!$H$12,Cons_Region!$C$12,$N$2,$K$2,$B$38) -> 0.3269 | ... N38: =_xll.DBRW($B$2,Cons_Region!$F$12,Cons_Region!N$15,$M$1,Cons_Region!$H$12,Cons_Region!$C$12,$N$2,$K$2,$B$38) -> 0.3524 | O38: =_xll.DBRW($B$2,O36,Cons_Region!O$15,$M$1,Cons_Region!$H$12,Cons_Region!$C$12,$N$2,$K$2,$B$38) -> 0 | P38: =_xll.DBRW($B$2,P36,Cons_Region!P$15,$M$1,Cons_Region!$H$12,Cons_Region!$C$12,$N$2,$K$2,$B$38) -> 0 | Q38: =_xll.DBRW($B$2,Q36,Cons_Region!Q$15,$M$1,Cons_Region!$H$12,Cons_Region!$C$12,$N$2,$K$2,$B$38) -> 0 | R38: =_xll.DBRW($B$2,R36,Cons_Region!R$15,$M$1,Cons_Region!$H$12,Cons_Region!$C$12,$N$2,$K$2,$B$38) -> 0 | S38: =_xll.DBRW($B$2,S36,Cons_Region!S$15,$M$1,Cons_Region!$H$12,Cons_Region!$C$12,$N$2,$K$2,$B$38) -> 0
B39: Gross Revenue [$MM] | C39: =_xll.DBRW($B$2,Cons_Region!$F$12,Cons_Region!C$15,$M$1,Cons_Region!$H$12,Cons_Region!$C$12,$N$2,$K$2,$B$39) -> 0 | D39: =_xll.DBRW($B$2,Cons_Region!$F$12,Cons_Region!D$15,$M$1,Cons_Region!$H$12,Cons_Region!$C$12,$N$2,$K$2,$B$39) -> 1595.2141 | E39: =_xll.DBRW($B$2,Cons_Region!$F$12,Cons_Region!E$15,$M$1,Cons_Region!$H$12,Cons_Region!$C$12,$N$2,$K$2,$B$39) -> 1894.3089 | F39: =_xll.DBRW($B$2,Cons_Region!$F$12,Cons_Region!F$15,$M$1,Cons_Region!$H$12,Cons_Region!$C$12,$N$2,$K$2,$B$39) -> 1765.3017 | G39: =_xll.DBRW($B$2,Cons_Region!$F$12,Cons_Region!G$15,$M$1,Cons_Region!$H$12,Cons_Region!$C$12,$N$2,$K$2,$B$39) -> 1910.8408 | H39: =_xll.DBRW($B$2,Cons_Region!$F$12,Cons_Region!H$15,$M$1,Cons_Region!$H$12,Cons_Region!$C$12,$N$2,$K$2,$B$39) -> 1969.8936 | I39: =_xll.DBRW($B$2,Cons_Region!$F$12,Cons_Region!I$15,$M$1,Cons_Region!$H$12,Cons_Region!$C$12,$N$2,$K$2,$B$39) -> 2129.565 | J39: =_xll.DBRW($B$2,Cons_Region!$F$12,Cons_Region!J$15,$M$1,Cons_Region!$H$12,Cons_Region!$C$12,$N$2,$K$2,$B$39) -> 2150.9372 | ... N39: =_xll.DBRW($B$2,Cons_Region!$F$12,Cons_Region!N$15,$M$1,Cons_Region!$H$12,Cons_Region!$C$12,$N$2,$K$2,$B$39) -> 1664.1683 | O39: =_xll.DBRW($B$2,O$36,Cons_Region!O$15,$M$1,Cons_Region!$H$12,Cons_Region!$C$12,$N$2,$K$2,$B$39) -> 0 | P39: =_xll.DBRW($B$2,P$36,Cons_Region!P$15,$M$1,Cons_Region!$H$12,Cons_Region!$C$12,$N$2,$K$2,$B$39) -> 0 | Q39: =_xll.DBRW($B$2,Q$36,Cons_Region!Q$15,$M$1,Cons_Region!$H$12,Cons_Region!$C$12,$N$2,$K$2,$B$39) -> 0 | R39: =_xll.DBRW($B$2,R$36,Cons_Region!R$15,$M$1,Cons_Region!$H$12,Cons_Region!$C$12,$N$2,$K$2,$B$39) -> 0 | S39: =_xll.DBRW($B$2,S$36,Cons_Region!S$15,$M$1,Cons_Region!$H$12,Cons_Region!$C$12,$N$2,$K$2,$B$39) -> 0
B40: Net Revenue [$MM] | C40: =_xll.DBRW($B$2,Cons_Region!$F$12,Cons_Region!C$15,$M$1,Cons_Region!$H$12,Cons_Region!$C$12,$N$2,$K$2,$B$40) -> 0 | D40: =_xll.DBRW($B$2,Cons_Region!$F$12,Cons_Region!D$15,$M$1,Cons_Region!$H$12,Cons_Region!$C$12,$N$2,$K$2,$B$40) -> 1204.2987 | E40: =_xll.DBRW($B$2,Cons_Region!$F$12,Cons_Region!E$15,$M$1,Cons_Region!$H$12,Cons_Region!$C$12,$N$2,$K$2,$B$40) -> 1420.9804 | F40: =_xll.DBRW($B$2,Cons_Region!$F$12,Cons_Region!F$15,$M$1,Cons_Region!$H$12,Cons_Region!$C$12,$N$2,$K$2,$B$40) -> 1321.7294 | G40: =_xll.DBRW($B$2,Cons_Region!$F$12,Cons_Region!G$15,$M$1,Cons_Region!$H$12,Cons_Region!$C$12,$N$2,$K$2,$B$40) -> 1431.4486 | H40: =_xll.DBRW($B$2,Cons_Region!$F$12,Cons_Region!H$15,$M$1,Cons_Region!$H$12,Cons_Region!$C$12,$N$2,$K$2,$B$40) -> 1480.789 | I40: =_xll.DBRW($B$2,Cons_Region!$F$12,Cons_Region!I$15,$M$1,Cons_Region!$H$12,Cons_Region!$C$12,$N$2,$K$2,$B$40) -> 1600.2142 | J40: =_xll.DBRW($B$2,Cons_Region!$F$12,Cons_Region!J$15,$M$1,Cons_Region!$H$12,Cons_Region!$C$12,$N$2,$K$2,$B$40) -> 1621.0244 | ... N40: =_xll.DBRW($B$2,Cons_Region!$F$12,Cons_Region!N$15,$M$1,Cons_Region!$H$12,Cons_Region!$C$12,$N$2,$K$2,$B$40) -> 1230.5297 | O40: =_xll.DBRW($B$2,O$36,Cons_Region!O$15,$M$1,Cons_Region!$H$12,Cons_Region!$C$12,$N$2,$K$2,$B$39) -> 0 | P40: =_xll.DBRW($B$2,P$36,Cons_Region!P$15,$M$1,Cons_Region!$H$12,Cons_Region!$C$12,$N$2,$K$2,$B$39) -> 0 | Q40: =_xll.DBRW($B$2,Q$36,Cons_Region!Q$15,$M$1,Cons_Region!$H$12,Cons_Region!$C$12,$N$2,$K$2,$B$39) -> 0 | R40: =_xll.DBRW($B$2,R$36,Cons_Region!R$15,$M$1,Cons_Region!$H$12,Cons_Region!$C$12,$N$2,$K$2,$B$39) -> 0 | S40: =_xll.DBRW($B$2,S$36,Cons_Region!S$15,$M$1,Cons_Region!$H$12,Cons_Region!$C$12,$N$2,$K$2,$B$39) -> 0
B44: CONTRIBUTION MARGIN
O46: =$F$12+1 -> 2027 | P46: =$F$12+2 -> 2028 | Q46: =$F$12+3 -> 2029 | R46: =$F$12+4 -> 2030 | S46: =$F$12+5 -> 2031
C47: =$F$12&"."&C$15 -> 2026.01 | D47: =$F$12&"."&D$15 -> 2026.02 | E47: =$F$12&"."&E$15 -> 2026.03 | F47: =$F$12&"."&F$15 -> 2026.04 | G47: =$F$12&"."&G$15 -> 2026.05 | H47: =$F$12&"."&H$15 -> 2026.06 | I47: =$F$12&"."&I$15 -> 2026.07 | J47: =$F$12&"."&J$15 -> 2026.08 | ... N47: =$F$12&"."&N$15 -> 2026.12 | O47: PE | P47: PE | Q47: PE | R47: PE | S47: PE
A48: EXP.010.001 | B48: Final Variable Sales Expenses | C48: =_xll.DBRW($B$1,Cons_Region!$F$12,Cons_Region!C$15,$M$1,Cons_Region!$H$12,Cons_Region!$C$12,$N$2,$A48,$L$1,$K$1) -> 0 | D48: =_xll.DBRW($B$1,Cons_Region!$F$12,Cons_Region!D$15,$M$1,Cons_Region!$H$12,Cons_Region!$C$12,$N$2,$A48,$L$1,$K$1) -> 168.802 | E48: =_xll.DBRW($B$1,Cons_Region!$F$12,Cons_Region!E$15,$M$1,Cons_Region!$H$12,Cons_Region!$C$12,$N$2,$A48,$L$1,$K$1) -> 205.1198 | F48: =_xll.DBRW($B$1,Cons_Region!$F$12,Cons_Region!F$15,$M$1,Cons_Region!$H$12,Cons_Region!$C$12,$N$2,$A48,$L$1,$K$1) -> 199.2509 | G48: =_xll.DBRW($B$1,Cons_Region!$F$12,Cons_Region!G$15,$M$1,Cons_Region!$H$12,Cons_Region!$C$12,$N$2,$A48,$L$1,$K$1) -> 216.5219 | H48: =_xll.DBRW($B$1,Cons_Region!$F$12,Cons_Region!H$15,$M$1,Cons_Region!$H$12,Cons_Region!$C$12,$N$2,$A48,$L$1,$K$1) -> 222.5475 | I48: =_xll.DBRW($B$1,Cons_Region!$F$12,Cons_Region!I$15,$M$1,Cons_Region!$H$12,Cons_Region!$C$12,$N$2,$A48,$L$1,$K$1) -> 237.5144 | J48: =_xll.DBRW($B$1,Cons_Region!$F$12,Cons_Region!J$15,$M$1,Cons_Region!$H$12,Cons_Region!$C$12,$N$2,$A48,$L$1,$K$1) -> 239.9574 | ... N48: =_xll.DBRW($B$1,Cons_Region!$F$12,Cons_Region!N$15,$M$1,Cons_Region!$H$12,Cons_Region!$C$12,$N$2,$A48,$L$1,$K$1) -> 185.971 | O48: =_xll.DBRW($B$1,O$36,Cons_Region!O$15,$M$1,Cons_Region!$H$12,Cons_Region!$C$12,$N$2,$A48,$L$1,$K$1) -> 0 | P48: =_xll.DBRW($B$1,P$36,Cons_Region!P$15,$M$1,Cons_Region!$H$12,Cons_Region!$C$12,$N$2,$A48,$L$1,$K$1) -> 0 | Q48: =_xll.DBRW($B$1,Q$36,Cons_Region!Q$15,$M$1,Cons_Region!$H$12,Cons_Region!$C$12,$N$2,$A48,$L$1,$K$1) -> 0 | R48: =_xll.DBRW($B$1,R$36,Cons_Region!R$15,$M$1,Cons_Region!$H$12,Cons_Region!$C$12,$N$2,$A48,$L$1,$K$1) -> 0 | S48: =_xll.DBRW($B$1,S$36,Cons_Region!S$15,$M$1,Cons_Region!$H$12,Cons_Region!$C$12,$N$2,$A48,$L$1,$K$1) -> 0
A49: CST.010.001 | B49: Other Variable Costs | C49: =_xll.DBRW($B$1,Cons_Region!$F$12,Cons_Region!C$15,$M$1,Cons_Region!$H$12,Cons_Region!$C$12,$N$2,$A49,$L$1,$K$1) -> 0 | D49: =_xll.DBRW($B$1,Cons_Region!$F$12,Cons_Region!D$15,$M$1,Cons_Region!$H$12,Cons_Region!$C$12,$N$2,$A49,$L$1,$K$1) -> 598.8773 | E49: =_xll.DBRW($B$1,Cons_Region!$F$12,Cons_Region!E$15,$M$1,Cons_Region!$H$12,Cons_Region!$C$12,$N$2,$A49,$L$1,$K$1) -> 675.2484 | F49: =_xll.DBRW($B$1,Cons_Region!$F$12,Cons_Region!F$15,$M$1,Cons_Region!$H$12,Cons_Region!$C$12,$N$2,$A49,$L$1,$K$1) -> 594.5248 | G49: =_xll.DBRW($B$1,Cons_Region!$F$12,Cons_Region!G$15,$M$1,Cons_Region!$H$12,Cons_Region!$C$12,$N$2,$A49,$L$1,$K$1) -> 612.4205 | H49: =_xll.DBRW($B$1,Cons_Region!$F$12,Cons_Region!H$15,$M$1,Cons_Region!$H$12,Cons_Region!$C$12,$N$2,$A49,$L$1,$K$1) -> 629.7126 | I49: =_xll.DBRW($B$1,Cons_Region!$F$12,Cons_Region!I$15,$M$1,Cons_Region!$H$12,Cons_Region!$C$12,$N$2,$A49,$L$1,$K$1) -> 680.9529 | J49: =_xll.DBRW($B$1,Cons_Region!$F$12,Cons_Region!J$15,$M$1,Cons_Region!$H$12,Cons_Region!$C$12,$N$2,$A49,$L$1,$K$1) -> 694.0405 | ... N49: =_xll.DBRW($B$1,Cons_Region!$F$12,Cons_Region!N$15,$M$1,Cons_Region!$H$12,Cons_Region!$C$12,$N$2,$A49,$L$1,$K$1) -> 530.3109 | O49: =_xll.DBRW($B$1,O$36,Cons_Region!O$15,$M$1,Cons_Region!$H$12,Cons_Region!$C$12,$N$2,$A49,$L$1,$K$1) -> 0 | P49: =_xll.DBRW($B$1,P$36,Cons_Region!P$15,$M$1,Cons_Region!$H$12,Cons_Region!$C$12,$N$2,$A49,$L$1,$K$1) -> 0 | Q49: =_xll.DBRW($B$1,Q$36,Cons_Region!Q$15,$M$1,Cons_Region!$H$12,Cons_Region!$C$12,$N$2,$A49,$L$1,$K$1) -> 0 | R49: =_xll.DBRW($B$1,R$36,Cons_Region!R$15,$M$1,Cons_Region!$H$12,Cons_Region!$C$12,$N$2,$A49,$L$1,$K$1) -> 0 | S49: =_xll.DBRW($B$1,S$36,Cons_Region!S$15,$M$1,Cons_Region!$H$12,Cons_Region!$C$12,$N$2,$A49,$L$1,$K$1) -> 0
A50: CST.020.001 | B50: Fixed Costs | C50: =_xll.DBRW($B$1,Cons_Region!$F$12,Cons_Region!C$15,$M$1,Cons_Region!$H$12,Cons_Region!$C$12,$N$2,$A50,$L$1,$K$1) -> 0 | D50: =_xll.DBRW($B$1,Cons_Region!$F$12,Cons_Region!D$15,$M$1,Cons_Region!$H$12,Cons_Region!$C$12,$N$2,$A50,$L$1,$K$1) -> 174.4091 | E50: =_xll.DBRW($B$1,Cons_Region!$F$12,Cons_Region!E$15,$M$1,Cons_Region!$H$12,Cons_Region!$C$12,$N$2,$A50,$L$1,$K$1) -> 212.3951 | F50: =_xll.DBRW($B$1,Cons_Region!$F$12,Cons_Region!F$15,$M$1,Cons_Region!$H$12,Cons_Region!$C$12,$N$2,$A50,$L$1,$K$1) -> 193.3931 | G50: =_xll.DBRW($B$1,Cons_Region!$F$12,Cons_Region!G$15,$M$1,Cons_Region!$H$12,Cons_Region!$C$12,$N$2,$A50,$L$1,$K$1) -> 189.3711 | H50: =_xll.DBRW($B$1,Cons_Region!$F$12,Cons_Region!H$15,$M$1,Cons_Region!$H$12,Cons_Region!$C$12,$N$2,$A50,$L$1,$K$1) -> 189.6201 | I50: =_xll.DBRW($B$1,Cons_Region!$F$12,Cons_Region!I$15,$M$1,Cons_Region!$H$12,Cons_Region!$C$12,$N$2,$A50,$L$1,$K$1) -> 181.5719 | J50: =_xll.DBRW($B$1,Cons_Region!$F$12,Cons_Region!J$15,$M$1,Cons_Region!$H$12,Cons_Region!$C$12,$N$2,$A50,$L$1,$K$1) -> 175.1754 | ... N50: =_xll.DBRW($B$1,Cons_Region!$F$12,Cons_Region!N$15,$M$1,Cons_Region!$H$12,Cons_Region!$C$12,$N$2,$A50,$L$1,$K$1) -> 152.984 | O50: =_xll.DBRW($B$1,O$36,Cons_Region!O$15,$M$1,Cons_Region!$H$12,Cons_Region!$C$12,$N$2,$A50,$L$1,$K$1) -> 0 | P50: =_xll.DBRW($B$1,P$36,Cons_Region!P$15,$M$1,Cons_Region!$H$12,Cons_Region!$C$12,$N$2,$A50,$L$1,$K$1) -> 0 | Q50: =_xll.DBRW($B$1,Q$36,Cons_Region!Q$15,$M$1,Cons_Region!$H$12,Cons_Region!$C$12,$N$2,$A50,$L$1,$K$1) -> 0 | R50: =_xll.DBRW($B$1,R$36,Cons_Region!R$15,$M$1,Cons_Region!$H$12,Cons_Region!$C$12,$N$2,$A50,$L$1,$K$1) -> 0 | S50: =_xll.DBRW($B$1,S$36,Cons_Region!S$15,$M$1,Cons_Region!$H$12,Cons_Region!$C$12,$N$2,$A50,$L$1,$K$1) -> 0
A51: EXP.020.001 | B51: Operating Expenses | C51: =_xll.DBRW($B$1,Cons_Region!$F$12,Cons_Region!C$15,$M$1,Cons_Region!$H$12,Cons_Region!$C$12,$N$2,$A51,$L$1,$K$1) -> 0 | D51: =_xll.DBRW($B$1,Cons_Region!$F$12,Cons_Region!D$15,$M$1,Cons_Region!$H$12,Cons_Region!$C$12,$N$2,$A51,$L$1,$K$1) -> 117.0107 | E51: =_xll.DBRW($B$1,Cons_Region!$F$12,Cons_Region!E$15,$M$1,Cons_Region!$H$12,Cons_Region!$C$12,$N$2,$A51,$L$1,$K$1) -> 124.1856 | F51: =_xll.DBRW($B$1,Cons_Region!$F$12,Cons_Region!F$15,$M$1,Cons_Region!$H$12,Cons_Region!$C$12,$N$2,$A51,$L$1,$K$1) -> 129.2842 | G51: =_xll.DBRW($B$1,Cons_Region!$F$12,Cons_Region!G$15,$M$1,Cons_Region!$H$12,Cons_Region!$C$12,$N$2,$A51,$L$1,$K$1) -> 147.9149 | H51: =_xll.DBRW($B$1,Cons_Region!$F$12,Cons_Region!H$15,$M$1,Cons_Region!$H$12,Cons_Region!$C$12,$N$2,$A51,$L$1,$K$1) -> 130.73 | I51: =_xll.DBRW($B$1,Cons_Region!$F$12,Cons_Region!I$15,$M$1,Cons_Region!$H$12,Cons_Region!$C$12,$N$2,$A51,$L$1,$K$1) -> 123.315 | J51: =_xll.DBRW($B$1,Cons_Region!$F$12,Cons_Region!J$15,$M$1,Cons_Region!$H$12,Cons_Region!$C$12,$N$2,$A51,$L$1,$K$1) -> 128.4872 | ... N51: =_xll.DBRW($B$1,Cons_Region!$F$12,Cons_Region!N$15,$M$1,Cons_Region!$H$12,Cons_Region!$C$12,$N$2,$A51,$L$1,$K$1) -> 123.5418 | O51: =_xll.DBRW($B$1,O$36,Cons_Region!O$15,$M$1,Cons_Region!$H$12,Cons_Region!$C$12,$N$2,$A51,$L$1,$K$1) -> 0 | P51: =_xll.DBRW($B$1,P$36,Cons_Region!P$15,$M$1,Cons_Region!$H$12,Cons_Region!$C$12,$N$2,$A51,$L$1,$K$1) -> 0 | Q51: =_xll.DBRW($B$1,Q$36,Cons_Region!Q$15,$M$1,Cons_Region!$H$12,Cons_Region!$C$12,$N$2,$A51,$L$1,$K$1) -> 0 | R51: =_xll.DBRW($B$1,R$36,Cons_Region!R$15,$M$1,Cons_Region!$H$12,Cons_Region!$C$12,$N$2,$A51,$L$1,$K$1) -> 0 | S51: =_xll.DBRW($B$1,S$36,Cons_Region!S$15,$M$1,Cons_Region!$H$12,Cons_Region!$C$12,$N$2,$A51,$L$1,$K$1) -> 0
A52: OOR.010.001 | B52: Other | C52: =_xll.DBRW($B$1,Cons_Region!$F$12,Cons_Region!C$15,$M$1,Cons_Region!$H$12,Cons_Region!$C$12,$N$2,$A52,$L$1,$K$1) -> 0 | D52: =_xll.DBRW($B$1,Cons_Region!$F$12,Cons_Region!D$15,$M$1,Cons_Region!$H$12,Cons_Region!$C$12,$N$2,$A52,$L$1,$K$1) -> 0 | E52: =_xll.DBRW($B$1,Cons_Region!$F$12,Cons_Region!E$15,$M$1,Cons_Region!$H$12,Cons_Region!$C$12,$N$2,$A52,$L$1,$K$1) -> 0 | F52: =_xll.DBRW($B$1,Cons_Region!$F$12,Cons_Region!F$15,$M$1,Cons_Region!$H$12,Cons_Region!$C$12,$N$2,$A52,$L$1,$K$1) -> 0 | G52: =_xll.DBRW($B$1,Cons_Region!$F$12,Cons_Region!G$15,$M$1,Cons_Region!$H$12,Cons_Region!$C$12,$N$2,$A52,$L$1,$K$1) -> 0 | H52: =_xll.DBRW($B$1,Cons_Region!$F$12,Cons_Region!H$15,$M$1,Cons_Region!$H$12,Cons_Region!$C$12,$N$2,$A52,$L$1,$K$1) -> 0 | I52: =_xll.DBRW($B$1,Cons_Region!$F$12,Cons_Region!I$15,$M$1,Cons_Region!$H$12,Cons_Region!$C$12,$N$2,$A52,$L$1,$K$1) -> 0 | J52: =_xll.DBRW($B$1,Cons_Region!$F$12,Cons_Region!J$15,$M$1,Cons_Region!$H$12,Cons_Region!$C$12,$N$2,$A52,$L$1,$K$1) -> 0 | ... N52: =_xll.DBRW($B$1,Cons_Region!$F$12,Cons_Region!N$15,$M$1,Cons_Region!$H$12,Cons_Region!$C$12,$N$2,$A52,$L$1,$K$1) -> 0 | O52: =_xll.DBRW($B$1,O$36,Cons_Region!O$15,$M$1,Cons_Region!$H$12,Cons_Region!$C$12,$N$2,$A52,$L$1,$K$1) -> 0 | P52: =_xll.DBRW($B$1,P$36,Cons_Region!P$15,$M$1,Cons_Region!$H$12,Cons_Region!$C$12,$N$2,$A52,$L$1,$K$1) -> 0 | Q52: =_xll.DBRW($B$1,Q$36,Cons_Region!Q$15,$M$1,Cons_Region!$H$12,Cons_Region!$C$12,$N$2,$A52,$L$1,$K$1) -> 0 | R52: =_xll.DBRW($B$1,R$36,Cons_Region!R$15,$M$1,Cons_Region!$H$12,Cons_Region!$C$12,$N$2,$A52,$L$1,$K$1) -> 0 | S52: =_xll.DBRW($B$1,S$36,Cons_Region!S$15,$M$1,Cons_Region!$H$12,Cons_Region!$C$12,$N$2,$A52,$L$1,$K$1) -> 0
A53: DRE.099.004 | B53: EBITDA | C53: =_xll.DBRW($B$3,Cons_Region!$F$12,Cons_Region!C$15,$M$1,Cons_Region!$H$12,Cons_Region!$C$12,$N$2,$A53,$K$1) -> 0 | D53: =_xll.DBRW($B$3,Cons_Region!$F$12,Cons_Region!D$15,$M$1,Cons_Region!$H$12,Cons_Region!$C$12,$N$2,$A53,$K$1) -> 164.97952 | E53: =_xll.DBRW($B$3,Cons_Region!$F$12,Cons_Region!E$15,$M$1,Cons_Region!$H$12,Cons_Region!$C$12,$N$2,$A53,$K$1) -> 211.55466 | F53: =_xll.DBRW($B$3,Cons_Region!$F$12,Cons_Region!F$15,$M$1,Cons_Region!$H$12,Cons_Region!$C$12,$N$2,$A53,$K$1) -> 218.04976 | G53: =_xll.DBRW($B$3,Cons_Region!$F$12,Cons_Region!G$15,$M$1,Cons_Region!$H$12,Cons_Region!$C$12,$N$2,$A53,$K$1) -> 280.17124 | H53: =_xll.DBRW($B$3,Cons_Region!$F$12,Cons_Region!H$15,$M$1,Cons_Region!$H$12,Cons_Region!$C$12,$N$2,$A53,$K$1) -> 316.88202 | I53: =_xll.DBRW($B$3,Cons_Region!$F$12,Cons_Region!I$15,$M$1,Cons_Region!$H$12,Cons_Region!$C$12,$N$2,$A53,$K$1) -> 391.21588 | J53: =_xll.DBRW($B$3,Cons_Region!$F$12,Cons_Region!J$15,$M$1,Cons_Region!$H$12,Cons_Region!$C$12,$N$2,$A53,$K$1) -> 391.12058 | ... N53: =_xll.DBRW($B$3,Cons_Region!$F$12,Cons_Region!N$15,$M$1,Cons_Region!$H$12,Cons_Region!$C$12,$N$2,$A53,$K$1) -> 274.94186 | O53: =_xll.DBRW($B$3,O$14,Cons_Region!O$15,$M$1,Cons_Region!$H$12,Cons_Region!$C$12,$N$2,$A53,$K$1) -> 0 | P53: =_xll.DBRW($B$3,P$14,Cons_Region!P$15,$M$1,Cons_Region!$H$12,Cons_Region!$C$12,$N$2,$A53,$K$1) -> 0 | Q53: =_xll.DBRW($B$3,Q$14,Cons_Region!Q$15,$M$1,Cons_Region!$H$12,Cons_Region!$C$12,$N$2,$A53,$K$1) -> 0 | R53: =_xll.DBRW($B$3,R$14,Cons_Region!R$15,$M$1,Cons_Region!$H$12,Cons_Region!$C$12,$N$2,$A53,$K$1) -> 0 | S53: =_xll.DBRW($B$3,S$14,Cons_Region!S$15,$M$1,Cons_Region!$H$12,Cons_Region!$C$12,$N$2,$A53,$K$1) -> 0
B56: Operating Profit
O57: =$F$12+1 -> 2027 | P57: =$F$12+2 -> 2028 | Q57: =$F$12+3 -> 2029 | R57: =$F$12+4 -> 2030 | S57: =$F$12+5 -> 2031
C58: =$F$12&"."&C$15 -> 2026.01 | D58: =$F$12&"."&D$15 -> 2026.02 | E58: =$F$12&"."&E$15 -> 2026.03 | F58: =$F$12&"."&F$15 -> 2026.04 | G58: =$F$12&"."&G$15 -> 2026.05 | H58: =$F$12&"."&H$15 -> 2026.06 | I58: =$F$12&"."&I$15 -> 2026.07 | J58: =$F$12&"."&J$15 -> 2026.08 | ... N58: =$F$12&"."&N$15 -> 2026.12 | O58: PE | P58: PE | Q58: PE | R58: PE | S58: PE
A59: DEP.010.001 | B59: Depreciation / amortization / depletion - Corporate | C59: =_xll.DBRW($B$1,Cons_Region!$F$12,Cons_Region!C$15,$M$1,Cons_Region!$H$12,Cons_Region!$C$12,$N$2,$A59,$L$1,$K$1) -> 0 | D59: =_xll.DBRW($B$1,Cons_Region!$F$12,Cons_Region!D$15,$M$1,Cons_Region!$H$12,Cons_Region!$C$12,$N$2,$A59,$L$1,$K$1) -> 102.5138 | E59: =_xll.DBRW($B$1,Cons_Region!$F$12,Cons_Region!E$15,$M$1,Cons_Region!$H$12,Cons_Region!$C$12,$N$2,$A59,$L$1,$K$1) -> 100.0189 | F59: =_xll.DBRW($B$1,Cons_Region!$F$12,Cons_Region!F$15,$M$1,Cons_Region!$H$12,Cons_Region!$C$12,$N$2,$A59,$L$1,$K$1) -> 98.6799 | G59: =_xll.DBRW($B$1,Cons_Region!$F$12,Cons_Region!G$15,$M$1,Cons_Region!$H$12,Cons_Region!$C$12,$N$2,$A59,$L$1,$K$1) -> 99.0133 | H59: =_xll.DBRW($B$1,Cons_Region!$F$12,Cons_Region!H$15,$M$1,Cons_Region!$H$12,Cons_Region!$C$12,$N$2,$A59,$L$1,$K$1) -> 97.09 | I59: =_xll.DBRW($B$1,Cons_Region!$F$12,Cons_Region!I$15,$M$1,Cons_Region!$H$12,Cons_Region!$C$12,$N$2,$A59,$L$1,$K$1) -> 103.2944 | J59: =_xll.DBRW($B$1,Cons_Region!$F$12,Cons_Region!J$15,$M$1,Cons_Region!$H$12,Cons_Region!$C$12,$N$2,$A59,$L$1,$K$1) -> 103.3413 | ... N59: =_xll.DBRW($B$1,Cons_Region!$F$12,Cons_Region!N$15,$M$1,Cons_Region!$H$12,Cons_Region!$C$12,$N$2,$A59,$L$1,$K$1) -> 104.0032 | O59: =_xll.DBRW($B$1,O$36,Cons_Region!O$15,$M$1,Cons_Region!$H$12,Cons_Region!$C$12,$N$2,$A59,$L$1,$K$1) -> 0 | P59: =_xll.DBRW($B$1,P$36,Cons_Region!P$15,$M$1,Cons_Region!$H$12,Cons_Region!$C$12,$N$2,$A59,$L$1,$K$1) -> 0 | Q59: =_xll.DBRW($B$1,Q$36,Cons_Region!Q$15,$M$1,Cons_Region!$H$12,Cons_Region!$C$12,$N$2,$A59,$L$1,$K$1) -> 0 | R59: =_xll.DBRW($B$1,R$36,Cons_Region!R$15,$M$1,Cons_Region!$H$12,Cons_Region!$C$12,$N$2,$A59,$L$1,$K$1) -> 0 | S59: =_xll.DBRW($B$1,S$36,Cons_Region!S$15,$M$1,Cons_Region!$H$12,Cons_Region!$C$12,$N$2,$A59,$L$1,$K$1) -> 0
A60: DRE.099.004 | B60: EBITDA | C60: =_xll.DBRW($B$3,Cons_Region!$F$12,Cons_Region!C$15,$M$1,Cons_Region!$H$12,Cons_Region!$C$12,$N$2,$A60,$K$1) -> 0 | D60: =_xll.DBRW($B$3,Cons_Region!$F$12,Cons_Region!D$15,$M$1,Cons_Region!$H$12,Cons_Region!$C$12,$N$2,$A60,$K$1) -> 164.97952 | E60: =_xll.DBRW($B$3,Cons_Region!$F$12,Cons_Region!E$15,$M$1,Cons_Region!$H$12,Cons_Region!$C$12,$N$2,$A60,$K$1) -> 211.55466 | F60: =_xll.DBRW($B$3,Cons_Region!$F$12,Cons_Region!F$15,$M$1,Cons_Region!$H$12,Cons_Region!$C$12,$N$2,$A60,$K$1) -> 218.04976 | G60: =_xll.DBRW($B$3,Cons_Region!$F$12,Cons_Region!G$15,$M$1,Cons_Region!$H$12,Cons_Region!$C$12,$N$2,$A60,$K$1) -> 280.17124 | H60: =_xll.DBRW($B$3,Cons_Region!$F$12,Cons_Region!H$15,$M$1,Cons_Region!$H$12,Cons_Region!$C$12,$N$2,$A60,$K$1) -> 316.88202 | I60: =_xll.DBRW($B$3,Cons_Region!$F$12,Cons_Region!I$15,$M$1,Cons_Region!$H$12,Cons_Region!$C$12,$N$2,$A60,$K$1) -> 391.21588 | J60: =_xll.DBRW($B$3,Cons_Region!$F$12,Cons_Region!J$15,$M$1,Cons_Region!$H$12,Cons_Region!$C$12,$N$2,$A60,$K$1) -> 391.12058 | ... N60: =_xll.DBRW($B$3,Cons_Region!$F$12,Cons_Region!N$15,$M$1,Cons_Region!$H$12,Cons_Region!$C$12,$N$2,$A60,$K$1) -> 274.94186 | O60: =_xll.DBRW($B$3,O$14,Cons_Region!O$15,$M$1,Cons_Region!$H$12,Cons_Region!$C$12,$N$2,$A60,$K$1) -> 0 | P60: =_xll.DBRW($B$3,P$14,Cons_Region!P$15,$M$1,Cons_Region!$H$12,Cons_Region!$C$12,$N$2,$A60,$K$1) -> 0 | Q60: =_xll.DBRW($B$3,Q$14,Cons_Region!Q$15,$M$1,Cons_Region!$H$12,Cons_Region!$C$12,$N$2,$A60,$K$1) -> 0 | R60: =_xll.DBRW($B$3,R$14,Cons_Region!R$15,$M$1,Cons_Region!$H$12,Cons_Region!$C$12,$N$2,$A60,$K$1) -> 0 | S60: =_xll.DBRW($B$3,S$14,Cons_Region!S$15,$M$1,Cons_Region!$H$12,Cons_Region!$C$12,$N$2,$A60,$K$1) -> 0
A61: DRE.099.006 | B61: Operating Profit | C61: =_xll.DBRW($B$3,Cons_Region!$F$12,Cons_Region!C$15,$M$1,Cons_Region!$H$12,Cons_Region!$C$12,$N$2,$A61,$K$1) -> 0 | D61: =_xll.DBRW($B$3,Cons_Region!$F$12,Cons_Region!D$15,$M$1,Cons_Region!$H$12,Cons_Region!$C$12,$N$2,$A61,$K$1) -> 62.465723 | E61: =_xll.DBRW($B$3,Cons_Region!$F$12,Cons_Region!E$15,$M$1,Cons_Region!$H$12,Cons_Region!$C$12,$N$2,$A61,$K$1) -> 111.53576 | F61: =_xll.DBRW($B$3,Cons_Region!$F$12,Cons_Region!F$15,$M$1,Cons_Region!$H$12,Cons_Region!$C$12,$N$2,$A61,$K$1) -> 119.36986 | G61: =_xll.DBRW($B$3,Cons_Region!$F$12,Cons_Region!G$15,$M$1,Cons_Region!$H$12,Cons_Region!$C$12,$N$2,$A61,$K$1) -> 181.15794 | H61: =_xll.DBRW($B$3,Cons_Region!$F$12,Cons_Region!H$15,$M$1,Cons_Region!$H$12,Cons_Region!$C$12,$N$2,$A61,$K$1) -> 219.79202 | I61: =_xll.DBRW($B$3,Cons_Region!$F$12,Cons_Region!I$15,$M$1,Cons_Region!$H$12,Cons_Region!$C$12,$N$2,$A61,$K$1) -> 287.92148 | J61: =_xll.DBRW($B$3,Cons_Region!$F$12,Cons_Region!J$15,$M$1,Cons_Region!$H$12,Cons_Region!$C$12,$N$2,$A61,$K$1) -> 287.77928 | ... N61: =_xll.DBRW($B$3,Cons_Region!$F$12,Cons_Region!N$15,$M$1,Cons_Region!$H$12,Cons_Region!$C$12,$N$2,$A61,$K$1) -> 170.93866 | O61: =_xll.DBRW($B$3,O$14,Cons_Region!O$15,$M$1,Cons_Region!$H$12,Cons_Region!$C$12,$N$2,$A61,$K$1) -> 0 | P61: =_xll.DBRW($B$3,P$14,Cons_Region!P$15,$M$1,Cons_Region!$H$12,Cons_Region!$C$12,$N$2,$A61,$K$1) -> 0 | Q61: =_xll.DBRW($B$3,Q$14,Cons_Region!Q$15,$M$1,Cons_Region!$H$12,Cons_Region!$C$12,$N$2,$A61,$K$1) -> 0 | R61: =_xll.DBRW($B$3,R$14,Cons_Region!R$15,$M$1,Cons_Region!$H$12,Cons_Region!$C$12,$N$2,$A61,$K$1) -> 0 | S61: =_xll.DBRW($B$3,S$14,Cons_Region!S$15,$M$1,Cons_Region!$H$12,Cons_Region!$C$12,$N$2,$A61,$K$1) -> 0
B64: Profit Before Income Tax
O65: =$F$12+1 -> 2027 | P65: =$F$12+2 -> 2028 | Q65: =$F$12+3 -> 2029 | R65: =$F$12+4 -> 2030 | S65: =$F$12+5 -> 2031
C66: =$F$12&"."&C$15 -> 2026.01 | D66: =$F$12&"."&D$15 -> 2026.02 | E66: =$F$12&"."&E$15 -> 2026.03 | F66: =$F$12&"."&F$15 -> 2026.04 | G66: =$F$12&"."&G$15 -> 2026.05 | H66: =$F$12&"."&H$15 -> 2026.06 | I66: =$F$12&"."&I$15 -> 2026.07 | J66: =$F$12&"."&J$15 -> 2026.08 | ... N66: =$F$12&"."&N$15 -> 2026.12 | O66: PE | P66: PE | Q66: PE | R66: PE | S66: PE
A67: NOP.010.001 | B67: Equity Pick-Up Results | C67: =_xll.DBRW($B$1,Cons_Region!$F$12,Cons_Region!C$15,$M$1,Cons_Region!$H$12,Cons_Region!$C$12,$N$1,$A67,$L$1,$K$1) -> 0 | D67: =_xll.DBRW($B$1,Cons_Region!$F$12,Cons_Region!D$15,$M$1,Cons_Region!$H$12,Cons_Region!$C$12,$N$1,$A67,$L$1,$K$1) -> -0.8388 | E67: =_xll.DBRW($B$1,Cons_Region!$F$12,Cons_Region!E$15,$M$1,Cons_Region!$H$12,Cons_Region!$C$12,$N$1,$A67,$L$1,$K$1) -> -0.2702 | F67: =_xll.DBRW($B$1,Cons_Region!$F$12,Cons_Region!F$15,$M$1,Cons_Region!$H$12,Cons_Region!$C$12,$N$1,$A67,$L$1,$K$1) -> -0.2702 | G67: =_xll.DBRW($B$1,Cons_Region!$F$12,Cons_Region!G$15,$M$1,Cons_Region!$H$12,Cons_Region!$C$12,$N$1,$A67,$L$1,$K$1) -> -0.2702 | H67: =_xll.DBRW($B$1,Cons_Region!$F$12,Cons_Region!H$15,$M$1,Cons_Region!$H$12,Cons_Region!$C$12,$N$1,$A67,$L$1,$K$1) -> -0.2702 | I67: =_xll.DBRW($B$1,Cons_Region!$F$12,Cons_Region!I$15,$M$1,Cons_Region!$H$12,Cons_Region!$C$12,$N$1,$A67,$L$1,$K$1) -> -0.2702 | J67: =_xll.DBRW($B$1,Cons_Region!$F$12,Cons_Region!J$15,$M$1,Cons_Region!$H$12,Cons_Region!$C$12,$N$1,$A67,$L$1,$K$1) -> -0.2702 | ... N67: =_xll.DBRW($B$1,Cons_Region!$F$12,Cons_Region!N$15,$M$1,Cons_Region!$H$12,Cons_Region!$C$12,$N$1,$A67,$L$1,$K$1) -> -0.2702 | O67: =_xll.DBRW($B$1,O$65,Cons_Region!O$15,$M$1,Cons_Region!$H$12,Cons_Region!$C$12,$N$1,$A67,$L$1,$K$1) -> 0 | P67: =_xll.DBRW($B$1,P$65,Cons_Region!P$15,$M$1,Cons_Region!$H$12,Cons_Region!$C$12,$N$1,$A67,$L$1,$K$1) -> 0 | Q67: =_xll.DBRW($B$1,Q$65,Cons_Region!Q$15,$M$1,Cons_Region!$H$12,Cons_Region!$C$12,$N$1,$A67,$L$1,$K$1) -> 0 | R67: =_xll.DBRW($B$1,R$65,Cons_Region!R$15,$M$1,Cons_Region!$H$12,Cons_Region!$C$12,$N$1,$A67,$L$1,$K$1) -> 0 | S67: =_xll.DBRW($B$1,S$65,Cons_Region!S$15,$M$1,Cons_Region!$H$12,Cons_Region!$C$12,$N$1,$A67,$L$1,$K$1) -> 0
A68: NOR.010.001 | B68: Other Non Operating Results | C68: =_xll.DBRW($B$1,Cons_Region!$F$12,Cons_Region!C$15,$M$1,Cons_Region!$H$12,Cons_Region!$C$12,$N$1,$A68,$L$1,$K$1) -> 0 | D68: =_xll.DBRW($B$1,Cons_Region!$F$12,Cons_Region!D$15,$M$1,Cons_Region!$H$12,Cons_Region!$C$12,$N$1,$A68,$L$1,$K$1) -> 0 | E68: =_xll.DBRW($B$1,Cons_Region!$F$12,Cons_Region!E$15,$M$1,Cons_Region!$H$12,Cons_Region!$C$12,$N$1,$A68,$L$1,$K$1) -> 9.4798 | F68: =_xll.DBRW($B$1,Cons_Region!$F$12,Cons_Region!F$15,$M$1,Cons_Region!$H$12,Cons_Region!$C$12,$N$1,$A68,$L$1,$K$1) -> 0 | G68: =_xll.DBRW($B$1,Cons_Region!$F$12,Cons_Region!G$15,$M$1,Cons_Region!$H$12,Cons_Region!$C$12,$N$1,$A68,$L$1,$K$1) -> 0 | H68: =_xll.DBRW($B$1,Cons_Region!$F$12,Cons_Region!H$15,$M$1,Cons_Region!$H$12,Cons_Region!$C$12,$N$1,$A68,$L$1,$K$1) -> 11.2753 | I68: =_xll.DBRW($B$1,Cons_Region!$F$12,Cons_Region!I$15,$M$1,Cons_Region!$H$12,Cons_Region!$C$12,$N$1,$A68,$L$1,$K$1) -> 0 | J68: =_xll.DBRW($B$1,Cons_Region!$F$12,Cons_Region!J$15,$M$1,Cons_Region!$H$12,Cons_Region!$C$12,$N$1,$A68,$L$1,$K$1) -> 0 | ... N68: =_xll.DBRW($B$1,Cons_Region!$F$12,Cons_Region!N$15,$M$1,Cons_Region!$H$12,Cons_Region!$C$12,$N$1,$A68,$L$1,$K$1) -> 6.3771 | O68: =_xll.DBRW($B$1,O$65,Cons_Region!O$15,$M$1,Cons_Region!$H$12,Cons_Region!$C$12,$N$1,$A68,$L$1,$K$1) -> 0 | P68: =_xll.DBRW($B$1,P$65,Cons_Region!P$15,$M$1,Cons_Region!$H$12,Cons_Region!$C$12,$N$1,$A68,$L$1,$K$1) -> 0 | Q68: =_xll.DBRW($B$1,Q$65,Cons_Region!Q$15,$M$1,Cons_Region!$H$12,Cons_Region!$C$12,$N$1,$A68,$L$1,$K$1) -> 0 | R68: =_xll.DBRW($B$1,R$65,Cons_Region!R$15,$M$1,Cons_Region!$H$12,Cons_Region!$C$12,$N$1,$A68,$L$1,$K$1) -> 0 | S68: =_xll.DBRW($B$1,S$65,Cons_Region!S$15,$M$1,Cons_Region!$H$12,Cons_Region!$C$12,$N$1,$A68,$L$1,$K$1) -> 0
A69: Financial Results | B69: Financial Results | C69: =_xll.DBRW($B$3,Cons_Region!$F$12,Cons_Region!C$15,$M$1,Cons_Region!$H$12,Cons_Region!$C$12,$N$2,$A69,$K$1) -> 0 | D69: =_xll.DBRW($B$3,Cons_Region!$F$12,Cons_Region!D$15,$M$1,Cons_Region!$H$12,Cons_Region!$C$12,$N$2,$A69,$K$1) -> -44.1677 | E69: =_xll.DBRW($B$3,Cons_Region!$F$12,Cons_Region!E$15,$M$1,Cons_Region!$H$12,Cons_Region!$C$12,$N$2,$A69,$K$1) -> 8.5256 | F69: =_xll.DBRW($B$3,Cons_Region!$F$12,Cons_Region!F$15,$M$1,Cons_Region!$H$12,Cons_Region!$C$12,$N$2,$A69,$K$1) -> 2.1057 | G69: =_xll.DBRW($B$3,Cons_Region!$F$12,Cons_Region!G$15,$M$1,Cons_Region!$H$12,Cons_Region!$C$12,$N$2,$A69,$K$1) -> 2.3552 | H69: =_xll.DBRW($B$3,Cons_Region!$F$12,Cons_Region!H$15,$M$1,Cons_Region!$H$12,Cons_Region!$C$12,$N$2,$A69,$K$1) -> -4.3591 | I69: =_xll.DBRW($B$3,Cons_Region!$F$12,Cons_Region!I$15,$M$1,Cons_Region!$H$12,Cons_Region!$C$12,$N$2,$A69,$K$1) -> -3.1509 | J69: =_xll.DBRW($B$3,Cons_Region!$F$12,Cons_Region!J$15,$M$1,Cons_Region!$H$12,Cons_Region!$C$12,$N$2,$A69,$K$1) -> -10.6908 | ... N69: =_xll.DBRW($B$3,Cons_Region!$F$12,Cons_Region!N$15,$M$1,Cons_Region!$H$12,Cons_Region!$C$12,$N$2,$A69,$K$1) -> 0 | O69: =_xll.DBRW($B$3,O$14,Cons_Region!O$15,$M$1,Cons_Region!$H$12,Cons_Region!$C$12,$N$2,$A69,$K$1) -> 0 | P69: =_xll.DBRW($B$3,P$14,Cons_Region!P$15,$M$1,Cons_Region!$H$12,Cons_Region!$C$12,$N$2,$A69,$K$1) -> 0 | Q69: =_xll.DBRW($B$3,Q$14,Cons_Region!Q$15,$M$1,Cons_Region!$H$12,Cons_Region!$C$12,$N$2,$A69,$K$1) -> 0 | R69: =_xll.DBRW($B$3,R$14,Cons_Region!R$15,$M$1,Cons_Region!$H$12,Cons_Region!$C$12,$N$2,$A69,$K$1) -> 0 | S69: =_xll.DBRW($B$3,S$14,Cons_Region!S$15,$M$1,Cons_Region!$H$12,Cons_Region!$C$12,$N$2,$A69,$K$1) -> 0
A70: Profit Before Income Tax | B70: Profit Before Income Tax | C70: =_xll.DBRW($B$3,Cons_Region!$F$12,Cons_Region!C$15,$M$1,Cons_Region!$H$12,Cons_Region!$C$12,$N$2,$A70,$K$1) -> 0 | D70: =_xll.DBRW($B$3,Cons_Region!$F$12,Cons_Region!D$15,$M$1,Cons_Region!$H$12,Cons_Region!$C$12,$N$2,$A70,$K$1) -> 17.459223 | E70: =_xll.DBRW($B$3,Cons_Region!$F$12,Cons_Region!E$15,$M$1,Cons_Region!$H$12,Cons_Region!$C$12,$N$2,$A70,$K$1) -> 129.27096 | F70: =_xll.DBRW($B$3,Cons_Region!$F$12,Cons_Region!F$15,$M$1,Cons_Region!$H$12,Cons_Region!$C$12,$N$2,$A70,$K$1) -> 121.20536 | G70: =_xll.DBRW($B$3,Cons_Region!$F$12,Cons_Region!G$15,$M$1,Cons_Region!$H$12,Cons_Region!$C$12,$N$2,$A70,$K$1) -> 183.24294 | H70: =_xll.DBRW($B$3,Cons_Region!$F$12,Cons_Region!H$15,$M$1,Cons_Region!$H$12,Cons_Region!$C$12,$N$2,$A70,$K$1) -> 226.43802 | I70: =_xll.DBRW($B$3,Cons_Region!$F$12,Cons_Region!I$15,$M$1,Cons_Region!$H$12,Cons_Region!$C$12,$N$2,$A70,$K$1) -> 284.50038 | J70: =_xll.DBRW($B$3,Cons_Region!$F$12,Cons_Region!J$15,$M$1,Cons_Region!$H$12,Cons_Region!$C$12,$N$2,$A70,$K$1) -> 276.81828 | ... N70: =_xll.DBRW($B$3,Cons_Region!$F$12,Cons_Region!N$15,$M$1,Cons_Region!$H$12,Cons_Region!$C$12,$N$2,$A70,$K$1) -> 177.04556 | O70: =_xll.DBRW($B$3,O$14,Cons_Region!O$15,$M$1,Cons_Region!$H$12,Cons_Region!$C$12,$N$2,$A70,$K$1) -> 0 | P70: =_xll.DBRW($B$3,P$14,Cons_Region!P$15,$M$1,Cons_Region!$H$12,Cons_Region!$C$12,$N$2,$A70,$K$1) -> 0 | Q70: =_xll.DBRW($B$3,Q$14,Cons_Region!Q$15,$M$1,Cons_Region!$H$12,Cons_Region!$C$12,$N$2,$A70,$K$1) -> 0 | R70: =_xll.DBRW($B$3,R$14,Cons_Region!R$15,$M$1,Cons_Region!$H$12,Cons_Region!$C$12,$N$2,$A70,$K$1) -> 0 | S70: =_xll.DBRW($B$3,S$14,Cons_Region!S$15,$M$1,Cons_Region!$H$12,Cons_Region!$C$12,$N$2,$A70,$K$1) -> 0
B73: Net Profit Before Minority Int.
O74: =$F$12+1 -> 2027 | P74: =$F$12+2 -> 2028 | Q74: =$F$12+3 -> 2029 | R74: =$F$12+4 -> 2030 | S74: =$F$12+5 -> 2031
C75: =$F$12&"."&C$15 -> 2026.01 | D75: =$F$12&"."&D$15 -> 2026.02 | E75: =$F$12&"."&E$15 -> 2026.03 | F75: =$F$12&"."&F$15 -> 2026.04 | G75: =$F$12&"."&G$15 -> 2026.05 | H75: =$F$12&"."&H$15 -> 2026.06 | I75: =$F$12&"."&I$15 -> 2026.07 | J75: =$F$12&"."&J$15 -> 2026.08 | ... N75: =$F$12&"."&N$15 -> 2026.12 | O75: PE | P75: PE | Q75: PE | R75: PE | S75: PE
A76: NOP.020.001 | B76: Additions/Low IT Income Statement | C76: =_xll.DBRW($B$1,Cons_Region!$F$12,Cons_Region!C$15,$M$1,Cons_Region!$H$12,Cons_Region!$C$12,$N$1,$A76,$L$1,$K$1) -> 0 | D76: =_xll.DBRW($B$1,Cons_Region!$F$12,Cons_Region!D$15,$M$1,Cons_Region!$H$12,Cons_Region!$C$12,$N$1,$A76,$L$1,$K$1) -> 0 | E76: =_xll.DBRW($B$1,Cons_Region!$F$12,Cons_Region!E$15,$M$1,Cons_Region!$H$12,Cons_Region!$C$12,$N$1,$A76,$L$1,$K$1) -> 0 | F76: =_xll.DBRW($B$1,Cons_Region!$F$12,Cons_Region!F$15,$M$1,Cons_Region!$H$12,Cons_Region!$C$12,$N$1,$A76,$L$1,$K$1) -> 0 | G76: =_xll.DBRW($B$1,Cons_Region!$F$12,Cons_Region!G$15,$M$1,Cons_Region!$H$12,Cons_Region!$C$12,$N$1,$A76,$L$1,$K$1) -> 0 | H76: =_xll.DBRW($B$1,Cons_Region!$F$12,Cons_Region!H$15,$M$1,Cons_Region!$H$12,Cons_Region!$C$12,$N$1,$A76,$L$1,$K$1) -> 0 | I76: =_xll.DBRW($B$1,Cons_Region!$F$12,Cons_Region!I$15,$M$1,Cons_Region!$H$12,Cons_Region!$C$12,$N$1,$A76,$L$1,$K$1) -> 0 | J76: =_xll.DBRW($B$1,Cons_Region!$F$12,Cons_Region!J$15,$M$1,Cons_Region!$H$12,Cons_Region!$C$12,$N$1,$A76,$L$1,$K$1) -> 0 | ... N76: =_xll.DBRW($B$1,Cons_Region!$F$12,Cons_Region!N$15,$M$1,Cons_Region!$H$12,Cons_Region!$C$12,$N$1,$A76,$L$1,$K$1) -> 0 | O76: =_xll.DBRW($B$1,O$65,Cons_Region!O$15,$M$1,Cons_Region!$H$12,Cons_Region!$C$12,$N$1,$A76,$L$1,$K$1) -> 0 | P76: =_xll.DBRW($B$1,P$65,Cons_Region!P$15,$M$1,Cons_Region!$H$12,Cons_Region!$C$12,$N$1,$A76,$L$1,$K$1) -> 0 | Q76: =_xll.DBRW($B$1,Q$65,Cons_Region!Q$15,$M$1,Cons_Region!$H$12,Cons_Region!$C$12,$N$1,$A76,$L$1,$K$1) -> 0 | R76: =_xll.DBRW($B$1,R$65,Cons_Region!R$15,$M$1,Cons_Region!$H$12,Cons_Region!$C$12,$N$1,$A76,$L$1,$K$1) -> 0 | S76: =_xll.DBRW($B$1,S$65,Cons_Region!S$15,$M$1,Cons_Region!$H$12,Cons_Region!$C$12,$N$1,$A76,$L$1,$K$1) -> 0
A77: DRE.099.014 | B77: % Income Tax | C77: =_xll.DBRW($B$3,Cons_Region!$F$12,Cons_Region!C$15,$M$1,Cons_Region!$H$12,Cons_Region!$C$12,$N$2,$A77,$K$1) -> 0 | D77: =_xll.DBRW($B$3,Cons_Region!$F$12,Cons_Region!D$15,$M$1,Cons_Region!$H$12,Cons_Region!$C$12,$N$2,$A77,$K$1) -> 0 | E77: =_xll.DBRW($B$3,Cons_Region!$F$12,Cons_Region!E$15,$M$1,Cons_Region!$H$12,Cons_Region!$C$12,$N$2,$A77,$K$1) -> 0 | F77: =_xll.DBRW($B$3,Cons_Region!$F$12,Cons_Region!F$15,$M$1,Cons_Region!$H$12,Cons_Region!$C$12,$N$2,$A77,$K$1) -> 0 | G77: =_xll.DBRW($B$3,Cons_Region!$F$12,Cons_Region!G$15,$M$1,Cons_Region!$H$12,Cons_Region!$C$12,$N$2,$A77,$K$1) -> 0 | H77: =_xll.DBRW($B$3,Cons_Region!$F$12,Cons_Region!H$15,$M$1,Cons_Region!$H$12,Cons_Region!$C$12,$N$2,$A77,$K$1) -> 0 | I77: =_xll.DBRW($B$3,Cons_Region!$F$12,Cons_Region!I$15,$M$1,Cons_Region!$H$12,Cons_Region!$C$12,$N$2,$A77,$K$1) -> 0 | J77: =_xll.DBRW($B$3,Cons_Region!$F$12,Cons_Region!J$15,$M$1,Cons_Region!$H$12,Cons_Region!$C$12,$N$2,$A77,$K$1) -> 0 | ... N77: =_xll.DBRW($B$3,Cons_Region!$F$12,Cons_Region!N$15,$M$1,Cons_Region!$H$12,Cons_Region!$C$12,$N$2,$A77,$K$1) -> 0 | O77: =_xll.DBRW($B$3,O$14,Cons_Region!O$15,$M$1,Cons_Region!$H$12,Cons_Region!$C$12,$N$2,$A77,$K$1) -> 0 | P77: =_xll.DBRW($B$3,P$14,Cons_Region!P$15,$M$1,Cons_Region!$H$12,Cons_Region!$C$12,$N$2,$A77,$K$1) -> 0 | Q77: =_xll.DBRW($B$3,Q$14,Cons_Region!Q$15,$M$1,Cons_Region!$H$12,Cons_Region!$C$12,$N$2,$A77,$K$1) -> 0 | R77: =_xll.DBRW($B$3,R$14,Cons_Region!R$15,$M$1,Cons_Region!$H$12,Cons_Region!$C$12,$N$2,$A77,$K$1) -> 0 | S77: =_xll.DBRW($B$3,S$14,Cons_Region!S$15,$M$1,Cons_Region!$H$12,Cons_Region!$C$12,$N$2,$A77,$K$1) -> 0
A78: DRE.099.010 | B78: Income Tax | C78: =_xll.DBRW($B$1,Cons_Region!$F$12,Cons_Region!C$15,$M$1,Cons_Region!$H$12,Cons_Region!$C$12,$N$1,$A78,$L$1,$K$1) -> 0 | D78: =_xll.DBRW($B$1,Cons_Region!$F$12,Cons_Region!D$15,$M$1,Cons_Region!$H$12,Cons_Region!$C$12,$N$1,$A78,$L$1,$K$1) -> 0 | E78: =_xll.DBRW($B$1,Cons_Region!$F$12,Cons_Region!E$15,$M$1,Cons_Region!$H$12,Cons_Region!$C$12,$N$1,$A78,$L$1,$K$1) -> 0 | F78: =_xll.DBRW($B$1,Cons_Region!$F$12,Cons_Region!F$15,$M$1,Cons_Region!$H$12,Cons_Region!$C$12,$N$1,$A78,$L$1,$K$1) -> 0 | G78: =_xll.DBRW($B$1,Cons_Region!$F$12,Cons_Region!G$15,$M$1,Cons_Region!$H$12,Cons_Region!$C$12,$N$1,$A78,$L$1,$K$1) -> 0 | H78: =_xll.DBRW($B$1,Cons_Region!$F$12,Cons_Region!H$15,$M$1,Cons_Region!$H$12,Cons_Region!$C$12,$N$1,$A78,$L$1,$K$1) -> 0 | I78: =_xll.DBRW($B$1,Cons_Region!$F$12,Cons_Region!I$15,$M$1,Cons_Region!$H$12,Cons_Region!$C$12,$N$1,$A78,$L$1,$K$1) -> 0 | J78: =_xll.DBRW($B$1,Cons_Region!$F$12,Cons_Region!J$15,$M$1,Cons_Region!$H$12,Cons_Region!$C$12,$N$1,$A78,$L$1,$K$1) -> 0 | ... N78: =_xll.DBRW($B$1,Cons_Region!$F$12,Cons_Region!N$15,$M$1,Cons_Region!$H$12,Cons_Region!$C$12,$N$1,$A78,$L$1,$K$1) -> 0 | O78: =_xll.DBRW($B$1,O$65,Cons_Region!O$15,$M$1,Cons_Region!$H$12,Cons_Region!$C$12,$N$1,$A78,$L$1,$K$1) -> 0 | P78: =_xll.DBRW($B$1,P$65,Cons_Region!P$15,$M$1,Cons_Region!$H$12,Cons_Region!$C$12,$N$1,$A78,$L$1,$K$1) -> 0 | Q78: =_xll.DBRW($B$1,Q$65,Cons_Region!Q$15,$M$1,Cons_Region!$H$12,Cons_Region!$C$12,$N$1,$A78,$L$1,$K$1) -> 0 | R78: =_xll.DBRW($B$1,R$65,Cons_Region!R$15,$M$1,Cons_Region!$H$12,Cons_Region!$C$12,$N$1,$A78,$L$1,$K$1) -> 0 | S78: =_xll.DBRW($B$1,S$65,Cons_Region!S$15,$M$1,Cons_Region!$H$12,Cons_Region!$C$12,$N$1,$A78,$L$1,$K$1) -> 0
A79: DRE.099.011 | B79: Net Profit Before Minority Int. | C79: =_xll.DBRW($B$3,Cons_Region!$F$12,Cons_Region!C$15,$M$1,Cons_Region!$H$12,Cons_Region!$C$12,$N$2,$A79,$K$1) -> 0 | D79: =_xll.DBRW($B$3,Cons_Region!$F$12,Cons_Region!D$15,$M$1,Cons_Region!$H$12,Cons_Region!$C$12,$N$2,$A79,$K$1) -> 17.459223 | E79: =_xll.DBRW($B$3,Cons_Region!$F$12,Cons_Region!E$15,$M$1,Cons_Region!$H$12,Cons_Region!$C$12,$N$2,$A79,$K$1) -> 129.27096 | F79: =_xll.DBRW($B$3,Cons_Region!$F$12,Cons_Region!F$15,$M$1,Cons_Region!$H$12,Cons_Region!$C$12,$N$2,$A79,$K$1) -> 121.20536 | G79: =_xll.DBRW($B$3,Cons_Region!$F$12,Cons_Region!G$15,$M$1,Cons_Region!$H$12,Cons_Region!$C$12,$N$2,$A79,$K$1) -> 183.24294 | H79: =_xll.DBRW($B$3,Cons_Region!$F$12,Cons_Region!H$15,$M$1,Cons_Region!$H$12,Cons_Region!$C$12,$N$2,$A79,$K$1) -> 226.43802 | I79: =_xll.DBRW($B$3,Cons_Region!$F$12,Cons_Region!I$15,$M$1,Cons_Region!$H$12,Cons_Region!$C$12,$N$2,$A79,$K$1) -> 284.50038 | J79: =_xll.DBRW($B$3,Cons_Region!$F$12,Cons_Region!J$15,$M$1,Cons_Region!$H$12,Cons_Region!$C$12,$N$2,$A79,$K$1) -> 276.81828 | ... N79: =_xll.DBRW($B$3,Cons_Region!$F$12,Cons_Region!N$15,$M$1,Cons_Region!$H$12,Cons_Region!$C$12,$N$2,$A79,$K$1) -> 177.04556 | O79: =_xll.DBRW($B$3,O$14,Cons_Region!O$15,$M$1,Cons_Region!$H$12,Cons_Region!$C$12,$N$2,$A79,$K$1) -> 0 | P79: =_xll.DBRW($B$3,P$14,Cons_Region!P$15,$M$1,Cons_Region!$H$12,Cons_Region!$C$12,$N$2,$A79,$K$1) -> 0 | Q79: =_xll.DBRW($B$3,Q$14,Cons_Region!Q$15,$M$1,Cons_Region!$H$12,Cons_Region!$C$12,$N$2,$A79,$K$1) -> 0 | R79: =_xll.DBRW($B$3,R$14,Cons_Region!R$15,$M$1,Cons_Region!$H$12,Cons_Region!$C$12,$N$2,$A79,$K$1) -> 0 | S79: =_xll.DBRW($B$3,S$14,Cons_Region!S$15,$M$1,Cons_Region!$H$12,Cons_Region!$C$12,$N$2,$A79,$K$1) -> 0
B82: Net Profit
O83: =$F$12+1 -> 2027 | P83: =$F$12+2 -> 2028 | Q83: =$F$12+3 -> 2029 | R83: =$F$12+4 -> 2030 | S83: =$F$12+5 -> 2031
C84: =$F$12&"."&C$15 -> 2026.01 | D84: =$F$12&"."&D$15 -> 2026.02 | E84: =$F$12&"."&E$15 -> 2026.03 | F84: =$F$12&"."&F$15 -> 2026.04 | G84: =$F$12&"."&G$15 -> 2026.05 | H84: =$F$12&"."&H$15 -> 2026.06 | I84: =$F$12&"."&I$15 -> 2026.07 | J84: =$F$12&"."&J$15 -> 2026.08 | ... N84: =$F$12&"."&N$15 -> 2026.12 | O84: PE | P84: PE | Q84: PE | R84: PE | S84: PE
B85: % Minoritários | C85: =_xll.DBRW($C$1,Cons_Region!$F$12,Cons_Region!C$15,$M$1,Cons_Region!$C$12,Cons_Region!$B85,$K$1) -> 0 | D85: =_xll.DBRW($C$1,Cons_Region!$F$12,Cons_Region!D$15,$M$1,Cons_Region!$C$12,Cons_Region!$B85,$K$1) -> 0 | E85: =_xll.DBRW($C$1,Cons_Region!$F$12,Cons_Region!E$15,$M$1,Cons_Region!$C$12,Cons_Region!$B85,$K$1) -> 0 | F85: =_xll.DBRW($C$1,Cons_Region!$F$12,Cons_Region!F$15,$M$1,Cons_Region!$C$12,Cons_Region!$B85,$K$1) -> 0 | G85: =_xll.DBRW($C$1,Cons_Region!$F$12,Cons_Region!G$15,$M$1,Cons_Region!$C$12,Cons_Region!$B85,$K$1) -> 0 | H85: =_xll.DBRW($C$1,Cons_Region!$F$12,Cons_Region!H$15,$M$1,Cons_Region!$C$12,Cons_Region!$B85,$K$1) -> 0 | I85: =_xll.DBRW($C$1,Cons_Region!$F$12,Cons_Region!I$15,$M$1,Cons_Region!$C$12,Cons_Region!$B85,$K$1) -> 0 | J85: =_xll.DBRW($C$1,Cons_Region!$F$12,Cons_Region!J$15,$M$1,Cons_Region!$C$12,Cons_Region!$B85,$K$1) -> 0 | ... N85: =_xll.DBRW($C$1,Cons_Region!$F$12,Cons_Region!N$15,$M$1,Cons_Region!$C$12,Cons_Region!$B85,$K$1) -> 0 | O85: =_xll.DBRW($C$1,O$83,Cons_Region!O$15,$M$1,Cons_Region!$C$12,Cons_Region!$B85,$K$1) -> 0 | P85: =_xll.DBRW($C$1,P$83,Cons_Region!P$15,$M$1,Cons_Region!$C$12,Cons_Region!$B85,$K$1) -> 0 | Q85: =_xll.DBRW($C$1,Q$83,Cons_Region!Q$15,$M$1,Cons_Region!$C$12,Cons_Region!$B85,$K$1) -> 0 | R85: =_xll.DBRW($C$1,R$83,Cons_Region!R$15,$M$1,Cons_Region!$C$12,Cons_Region!$B85,$K$1) -> 0 | S85: =_xll.DBRW($C$1,S$83,Cons_Region!S$15,$M$1,Cons_Region!$C$12,Cons_Region!$B85,$K$1) -> 0
A86: DRE.099.012 | B86: Minority Interests | C86: =_xll.DBRW($B$3,Cons_Region!$F$12,Cons_Region!C$15,$M$1,Cons_Region!$H$12,Cons_Region!$C$12,$N$2,$A86,$K$1) -> 0 | D86: =_xll.DBRW($B$3,Cons_Region!$F$12,Cons_Region!D$15,$M$1,Cons_Region!$H$12,Cons_Region!$C$12,$N$2,$A86,$K$1) -> 0 | E86: =_xll.DBRW($B$3,Cons_Region!$F$12,Cons_Region!E$15,$M$1,Cons_Region!$H$12,Cons_Region!$C$12,$N$2,$A86,$K$1) -> 0 | F86: =_xll.DBRW($B$3,Cons_Region!$F$12,Cons_Region!F$15,$M$1,Cons_Region!$H$12,Cons_Region!$C$12,$N$2,$A86,$K$1) -> 0 | G86: =_xll.DBRW($B$3,Cons_Region!$F$12,Cons_Region!G$15,$M$1,Cons_Region!$H$12,Cons_Region!$C$12,$N$2,$A86,$K$1) -> 0 | H86: =_xll.DBRW($B$3,Cons_Region!$F$12,Cons_Region!H$15,$M$1,Cons_Region!$H$12,Cons_Region!$C$12,$N$2,$A86,$K$1) -> 0 | I86: =_xll.DBRW($B$3,Cons_Region!$F$12,Cons_Region!I$15,$M$1,Cons_Region!$H$12,Cons_Region!$C$12,$N$2,$A86,$K$1) -> 0 | J86: =_xll.DBRW($B$3,Cons_Region!$F$12,Cons_Region!J$15,$M$1,Cons_Region!$H$12,Cons_Region!$C$12,$N$2,$A86,$K$1) -> 0 | ... N86: =_xll.DBRW($B$3,Cons_Region!$F$12,Cons_Region!N$15,$M$1,Cons_Region!$H$12,Cons_Region!$C$12,$N$2,$A86,$K$1) -> 0 | O86: =_xll.DBRW($B$3,O$14,Cons_Region!O$15,$M$1,Cons_Region!$H$12,Cons_Region!$C$12,$N$2,$A86,$K$1) -> 0 | P86: =_xll.DBRW($B$3,P$14,Cons_Region!P$15,$M$1,Cons_Region!$H$12,Cons_Region!$C$12,$N$2,$A86,$K$1) -> 0 | Q86: =_xll.DBRW($B$3,Q$14,Cons_Region!Q$15,$M$1,Cons_Region!$H$12,Cons_Region!$C$12,$N$2,$A86,$K$1) -> 0 | R86: =_xll.DBRW($B$3,R$14,Cons_Region!R$15,$M$1,Cons_Region!$H$12,Cons_Region!$C$12,$N$2,$A86,$K$1) -> 0 | S86: =_xll.DBRW($B$3,S$14,Cons_Region!S$15,$M$1,Cons_Region!$H$12,Cons_Region!$C$12,$N$2,$A86,$K$1) -> 0
A87: DRE.099.013 | B87: Net Profit | C87: =_xll.DBRW($B$3,Cons_Region!$F$12,Cons_Region!C$15,$M$1,Cons_Region!$H$12,Cons_Region!$C$12,$N$2,$A87,$K$1) -> 0 | D87: =_xll.DBRW($B$3,Cons_Region!$F$12,Cons_Region!D$15,$M$1,Cons_Region!$H$12,Cons_Region!$C$12,$N$2,$A87,$K$1) -> 17.459223 | E87: =_xll.DBRW($B$3,Cons_Region!$F$12,Cons_Region!E$15,$M$1,Cons_Region!$H$12,Cons_Region!$C$12,$N$2,$A87,$K$1) -> 129.27096 | F87: =_xll.DBRW($B$3,Cons_Region!$F$12,Cons_Region!F$15,$M$1,Cons_Region!$H$12,Cons_Region!$C$12,$N$2,$A87,$K$1) -> 121.20536 | G87: =_xll.DBRW($B$3,Cons_Region!$F$12,Cons_Region!G$15,$M$1,Cons_Region!$H$12,Cons_Region!$C$12,$N$2,$A87,$K$1) -> 183.24294 | H87: =_xll.DBRW($B$3,Cons_Region!$F$12,Cons_Region!H$15,$M$1,Cons_Region!$H$12,Cons_Region!$C$12,$N$2,$A87,$K$1) -> 226.43802 | I87: =_xll.DBRW($B$3,Cons_Region!$F$12,Cons_Region!I$15,$M$1,Cons_Region!$H$12,Cons_Region!$C$12,$N$2,$A87,$K$1) -> 284.50038 | J87: =_xll.DBRW($B$3,Cons_Region!$F$12,Cons_Region!J$15,$M$1,Cons_Region!$H$12,Cons_Region!$C$12,$N$2,$A87,$K$1) -> 276.81828 | ... N87: =_xll.DBRW($B$3,Cons_Region!$F$12,Cons_Region!N$15,$M$1,Cons_Region!$H$12,Cons_Region!$C$12,$N$2,$A87,$K$1) -> 177.04556 | O87: =_xll.DBRW($B$3,O$14,Cons_Region!O$15,$M$1,Cons_Region!$H$12,Cons_Region!$C$12,$N$2,$A87,$K$1) -> 0 | P87: =_xll.DBRW($B$3,P$14,Cons_Region!P$15,$M$1,Cons_Region!$H$12,Cons_Region!$C$12,$N$2,$A87,$K$1) -> 0 | Q87: =_xll.DBRW($B$3,Q$14,Cons_Region!Q$15,$M$1,Cons_Region!$H$12,Cons_Region!$C$12,$N$2,$A87,$K$1) -> 0 | R87: =_xll.DBRW($B$3,R$14,Cons_Region!R$15,$M$1,Cons_Region!$H$12,Cons_Region!$C$12,$N$2,$A87,$K$1) -> 0 | S87: =_xll.DBRW($B$3,S$14,Cons_Region!S$15,$M$1,Cons_Region!$H$12,Cons_Region!$C$12,$N$2,$A87,$K$1) -> 0
B90: Working Capital - KPIs Assets Accounts
O91: =$F$12+1 -> 2027 | P91: =$F$12+2 -> 2028 | Q91: =$F$12+3 -> 2029 | R91: =$F$12+4 -> 2030 | S91: =$F$12+5 -> 2031
C92: =$F$12&"."&C$15 -> 2026.01 | D92: =$F$12&"."&D$15 -> 2026.02 | E92: =$F$12&"."&E$15 -> 2026.03 | F92: =$F$12&"."&F$15 -> 2026.04 | G92: =$F$12&"."&G$15 -> 2026.05 | H92: =$F$12&"."&H$15 -> 2026.06 | I92: =$F$12&"."&I$15 -> 2026.07 | J92: =$F$12&"."&J$15 -> 2026.08 | ... N92: =$F$12&"."&N$15 -> 2026.12 | O92: PE | P92: PE | Q92: PE | R92: PE | S92: PE
A93: WKC.030.002 | B93: Account Receivable - Days o/ Rev | C93: =_xll.DBRW($B$1,Cons_Region!$F$12,Cons_Region!C$15,$M$1,Cons_Region!$H$12,Cons_Region!$C$12,$N$1,$A93,$L$1,$K$1) -> 0 | D93: =_xll.DBRW($B$1,Cons_Region!$F$12,Cons_Region!D$15,$M$1,Cons_Region!$H$12,Cons_Region!$C$12,$N$1,$A93,$L$1,$K$1) -> 18.8177 | E93: =_xll.DBRW($B$1,Cons_Region!$F$12,Cons_Region!E$15,$M$1,Cons_Region!$H$12,Cons_Region!$C$12,$N$1,$A93,$L$1,$K$1) -> 19.9162 | F93: =_xll.DBRW($B$1,Cons_Region!$F$12,Cons_Region!F$15,$M$1,Cons_Region!$H$12,Cons_Region!$C$12,$N$1,$A93,$L$1,$K$1) -> 18.9779 | G93: =_xll.DBRW($B$1,Cons_Region!$F$12,Cons_Region!G$15,$M$1,Cons_Region!$H$12,Cons_Region!$C$12,$N$1,$A93,$L$1,$K$1) -> 20.2775 | H93: =_xll.DBRW($B$1,Cons_Region!$F$12,Cons_Region!H$15,$M$1,Cons_Region!$H$12,Cons_Region!$C$12,$N$1,$A93,$L$1,$K$1) -> 20.052 | I93: =_xll.DBRW($B$1,Cons_Region!$F$12,Cons_Region!I$15,$M$1,Cons_Region!$H$12,Cons_Region!$C$12,$N$1,$A93,$L$1,$K$1) -> 18.8443 | J93: =_xll.DBRW($B$1,Cons_Region!$F$12,Cons_Region!J$15,$M$1,Cons_Region!$H$12,Cons_Region!$C$12,$N$1,$A93,$L$1,$K$1) -> 19.7798 | ... N93: =_xll.DBRW($B$1,Cons_Region!$F$12,Cons_Region!N$15,$M$1,Cons_Region!$H$12,Cons_Region!$C$12,$N$1,$A93,$L$1,$K$1) -> 0 | O93: =_xll.DBRW($B$1,O$65,Cons_Region!O$15,$M$1,Cons_Region!$H$12,Cons_Region!$C$12,$N$1,$A93,$L$1,$K$1) -> 0 | P93: =_xll.DBRW($B$1,P$65,Cons_Region!P$15,$M$1,Cons_Region!$H$12,Cons_Region!$C$12,$N$1,$A93,$L$1,$K$1) -> 0 | Q93: =_xll.DBRW($B$1,Q$65,Cons_Region!Q$15,$M$1,Cons_Region!$H$12,Cons_Region!$C$12,$N$1,$A93,$L$1,$K$1) -> 0 | R93: =_xll.DBRW($B$1,R$65,Cons_Region!R$15,$M$1,Cons_Region!$H$12,Cons_Region!$C$12,$N$1,$A93,$L$1,$K$1) -> 0 | S93: =_xll.DBRW($B$1,S$65,Cons_Region!S$15,$M$1,Cons_Region!$H$12,Cons_Region!$C$12,$N$1,$A93,$L$1,$K$1) -> 0
A94: WKC.010.011 | B94: Finished Product Inventory - Days o/ CPS - Other | C94: =_xll.DBRW($B$1,Cons_Region!$F$12,Cons_Region!C$15,$M$1,Cons_Region!$H$12,Cons_Region!$C$12,$N$1,$A94,$L$1,$K$1) -> 0 | D94: =_xll.DBRW($B$1,Cons_Region!$F$12,Cons_Region!D$15,$M$1,Cons_Region!$H$12,Cons_Region!$C$12,$N$1,$A94,$L$1,$K$1) -> 0 | E94: =_xll.DBRW($B$1,Cons_Region!$F$12,Cons_Region!E$15,$M$1,Cons_Region!$H$12,Cons_Region!$C$12,$N$1,$A94,$L$1,$K$1) -> 0 | F94: =_xll.DBRW($B$1,Cons_Region!$F$12,Cons_Region!F$15,$M$1,Cons_Region!$H$12,Cons_Region!$C$12,$N$1,$A94,$L$1,$K$1) -> 0 | G94: =_xll.DBRW($B$1,Cons_Region!$F$12,Cons_Region!G$15,$M$1,Cons_Region!$H$12,Cons_Region!$C$12,$N$1,$A94,$L$1,$K$1) -> 0 | H94: =_xll.DBRW($B$1,Cons_Region!$F$12,Cons_Region!H$15,$M$1,Cons_Region!$H$12,Cons_Region!$C$12,$N$1,$A94,$L$1,$K$1) -> 0 | I94: =_xll.DBRW($B$1,Cons_Region!$F$12,Cons_Region!I$15,$M$1,Cons_Region!$H$12,Cons_Region!$C$12,$N$1,$A94,$L$1,$K$1) -> 0 | J94: =_xll.DBRW($B$1,Cons_Region!$F$12,Cons_Region!J$15,$M$1,Cons_Region!$H$12,Cons_Region!$C$12,$N$1,$A94,$L$1,$K$1) -> 0 | ... N94: =_xll.DBRW($B$1,Cons_Region!$F$12,Cons_Region!N$15,$M$1,Cons_Region!$H$12,Cons_Region!$C$12,$N$1,$A94,$L$1,$K$1) -> 0 | O94: =_xll.DBRW($B$1,O$65,Cons_Region!O$15,$M$1,Cons_Region!$H$12,Cons_Region!$C$12,$N$1,$A94,$L$1,$K$1) -> 0 | P94: =_xll.DBRW($B$1,P$65,Cons_Region!P$15,$M$1,Cons_Region!$H$12,Cons_Region!$C$12,$N$1,$A94,$L$1,$K$1) -> 0 | Q94: =_xll.DBRW($B$1,Q$65,Cons_Region!Q$15,$M$1,Cons_Region!$H$12,Cons_Region!$C$12,$N$1,$A94,$L$1,$K$1) -> 0 | R94: =_xll.DBRW($B$1,R$65,Cons_Region!R$15,$M$1,Cons_Region!$H$12,Cons_Region!$C$12,$N$1,$A94,$L$1,$K$1) -> 0 | S94: =_xll.DBRW($B$1,S$65,Cons_Region!S$15,$M$1,Cons_Region!$H$12,Cons_Region!$C$12,$N$1,$A94,$L$1,$K$1) -> 0
A95: WKC.010.012 | B95: Product in Process Inventory- Days o/ CPS | C95: =_xll.DBRW($B$1,Cons_Region!$F$12,Cons_Region!C$15,$M$1,Cons_Region!$H$12,Cons_Region!$C$12,$N$1,$A95,$L$1,$K$1) -> 0 | D95: =_xll.DBRW($B$1,Cons_Region!$F$12,Cons_Region!D$15,$M$1,Cons_Region!$H$12,Cons_Region!$C$12,$N$1,$A95,$L$1,$K$1) -> 0 | E95: =_xll.DBRW($B$1,Cons_Region!$F$12,Cons_Region!E$15,$M$1,Cons_Region!$H$12,Cons_Region!$C$12,$N$1,$A95,$L$1,$K$1) -> 0 | F95: =_xll.DBRW($B$1,Cons_Region!$F$12,Cons_Region!F$15,$M$1,Cons_Region!$H$12,Cons_Region!$C$12,$N$1,$A95,$L$1,$K$1) -> 0 | G95: =_xll.DBRW($B$1,Cons_Region!$F$12,Cons_Region!G$15,$M$1,Cons_Region!$H$12,Cons_Region!$C$12,$N$1,$A95,$L$1,$K$1) -> 0 | H95: =_xll.DBRW($B$1,Cons_Region!$F$12,Cons_Region!H$15,$M$1,Cons_Region!$H$12,Cons_Region!$C$12,$N$1,$A95,$L$1,$K$1) -> 0 | I95: =_xll.DBRW($B$1,Cons_Region!$F$12,Cons_Region!I$15,$M$1,Cons_Region!$H$12,Cons_Region!$C$12,$N$1,$A95,$L$1,$K$1) -> 0 | J95: =_xll.DBRW($B$1,Cons_Region!$F$12,Cons_Region!J$15,$M$1,Cons_Region!$H$12,Cons_Region!$C$12,$N$1,$A95,$L$1,$K$1) -> 0 | ... N95: =_xll.DBRW($B$1,Cons_Region!$F$12,Cons_Region!N$15,$M$1,Cons_Region!$H$12,Cons_Region!$C$12,$N$1,$A95,$L$1,$K$1) -> 0 | O95: =_xll.DBRW($B$1,O$65,Cons_Region!O$15,$M$1,Cons_Region!$H$12,Cons_Region!$C$12,$N$1,$A95,$L$1,$K$1) -> 0 | P95: =_xll.DBRW($B$1,P$65,Cons_Region!P$15,$M$1,Cons_Region!$H$12,Cons_Region!$C$12,$N$1,$A95,$L$1,$K$1) -> 0 | Q95: =_xll.DBRW($B$1,Q$65,Cons_Region!Q$15,$M$1,Cons_Region!$H$12,Cons_Region!$C$12,$N$1,$A95,$L$1,$K$1) -> 0 | R95: =_xll.DBRW($B$1,R$65,Cons_Region!R$15,$M$1,Cons_Region!$H$12,Cons_Region!$C$12,$N$1,$A95,$L$1,$K$1) -> 0 | S95: =_xll.DBRW($B$1,S$65,Cons_Region!S$15,$M$1,Cons_Region!$H$12,Cons_Region!$C$12,$N$1,$A95,$L$1,$K$1) -> 0
A96: WKC.010.013 | B96: Concentrate Inventory - Days o/ VC | C96: =_xll.DBRW($B$1,Cons_Region!$F$12,Cons_Region!C$15,$M$1,Cons_Region!$H$12,Cons_Region!$C$12,$N$1,$A96,$L$1,$K$1) -> 0 | D96: =_xll.DBRW($B$1,Cons_Region!$F$12,Cons_Region!D$15,$M$1,Cons_Region!$H$12,Cons_Region!$C$12,$N$1,$A96,$L$1,$K$1) -> 0 | E96: =_xll.DBRW($B$1,Cons_Region!$F$12,Cons_Region!E$15,$M$1,Cons_Region!$H$12,Cons_Region!$C$12,$N$1,$A96,$L$1,$K$1) -> 0 | F96: =_xll.DBRW($B$1,Cons_Region!$F$12,Cons_Region!F$15,$M$1,Cons_Region!$H$12,Cons_Region!$C$12,$N$1,$A96,$L$1,$K$1) -> 0 | G96: =_xll.DBRW($B$1,Cons_Region!$F$12,Cons_Region!G$15,$M$1,Cons_Region!$H$12,Cons_Region!$C$12,$N$1,$A96,$L$1,$K$1) -> 0 | H96: =_xll.DBRW($B$1,Cons_Region!$F$12,Cons_Region!H$15,$M$1,Cons_Region!$H$12,Cons_Region!$C$12,$N$1,$A96,$L$1,$K$1) -> 0 | I96: =_xll.DBRW($B$1,Cons_Region!$F$12,Cons_Region!I$15,$M$1,Cons_Region!$H$12,Cons_Region!$C$12,$N$1,$A96,$L$1,$K$1) -> 0 | J96: =_xll.DBRW($B$1,Cons_Region!$F$12,Cons_Region!J$15,$M$1,Cons_Region!$H$12,Cons_Region!$C$12,$N$1,$A96,$L$1,$K$1) -> 0 | ... N96: =_xll.DBRW($B$1,Cons_Region!$F$12,Cons_Region!N$15,$M$1,Cons_Region!$H$12,Cons_Region!$C$12,$N$1,$A96,$L$1,$K$1) -> 0 | O96: =_xll.DBRW($B$1,O$65,Cons_Region!O$15,$M$1,Cons_Region!$H$12,Cons_Region!$C$12,$N$1,$A96,$L$1,$K$1) -> 0 | P96: =_xll.DBRW($B$1,P$65,Cons_Region!P$15,$M$1,Cons_Region!$H$12,Cons_Region!$C$12,$N$1,$A96,$L$1,$K$1) -> 0 | Q96: =_xll.DBRW($B$1,Q$65,Cons_Region!Q$15,$M$1,Cons_Region!$H$12,Cons_Region!$C$12,$N$1,$A96,$L$1,$K$1) -> 0 | R96: =_xll.DBRW($B$1,R$65,Cons_Region!R$15,$M$1,Cons_Region!$H$12,Cons_Region!$C$12,$N$1,$A96,$L$1,$K$1) -> 0 | S96: =_xll.DBRW($B$1,S$65,Cons_Region!S$15,$M$1,Cons_Region!$H$12,Cons_Region!$C$12,$N$1,$A96,$L$1,$K$1) -> 0
A97: WKC.010.014 | B97: MRO Inventory - Days o/ FC | C97: =_xll.DBRW($B$1,Cons_Region!$F$12,Cons_Region!C$15,$M$1,Cons_Region!$H$12,Cons_Region!$C$12,$N$1,$A97,$L$1,$K$1) -> 0 | D97: =_xll.DBRW($B$1,Cons_Region!$F$12,Cons_Region!D$15,$M$1,Cons_Region!$H$12,Cons_Region!$C$12,$N$1,$A97,$L$1,$K$1) -> 0 | E97: =_xll.DBRW($B$1,Cons_Region!$F$12,Cons_Region!E$15,$M$1,Cons_Region!$H$12,Cons_Region!$C$12,$N$1,$A97,$L$1,$K$1) -> 0 | F97: =_xll.DBRW($B$1,Cons_Region!$F$12,Cons_Region!F$15,$M$1,Cons_Region!$H$12,Cons_Region!$C$12,$N$1,$A97,$L$1,$K$1) -> 0 | G97: =_xll.DBRW($B$1,Cons_Region!$F$12,Cons_Region!G$15,$M$1,Cons_Region!$H$12,Cons_Region!$C$12,$N$1,$A97,$L$1,$K$1) -> 0 | H97: =_xll.DBRW($B$1,Cons_Region!$F$12,Cons_Region!H$15,$M$1,Cons_Region!$H$12,Cons_Region!$C$12,$N$1,$A97,$L$1,$K$1) -> 0 | I97: =_xll.DBRW($B$1,Cons_Region!$F$12,Cons_Region!I$15,$M$1,Cons_Region!$H$12,Cons_Region!$C$12,$N$1,$A97,$L$1,$K$1) -> 0 | J97: =_xll.DBRW($B$1,Cons_Region!$F$12,Cons_Region!J$15,$M$1,Cons_Region!$H$12,Cons_Region!$C$12,$N$1,$A97,$L$1,$K$1) -> 0 | ... N97: =_xll.DBRW($B$1,Cons_Region!$F$12,Cons_Region!N$15,$M$1,Cons_Region!$H$12,Cons_Region!$C$12,$N$1,$A97,$L$1,$K$1) -> 0 | O97: =_xll.DBRW($B$1,O$65,Cons_Region!O$15,$M$1,Cons_Region!$H$12,Cons_Region!$C$12,$N$1,$A97,$L$1,$K$1) -> 0 | P97: =_xll.DBRW($B$1,P$65,Cons_Region!P$15,$M$1,Cons_Region!$H$12,Cons_Region!$C$12,$N$1,$A97,$L$1,$K$1) -> 0 | Q97: =_xll.DBRW($B$1,Q$65,Cons_Region!Q$15,$M$1,Cons_Region!$H$12,Cons_Region!$C$12,$N$1,$A97,$L$1,$K$1) -> 0 | R97: =_xll.DBRW($B$1,R$65,Cons_Region!R$15,$M$1,Cons_Region!$H$12,Cons_Region!$C$12,$N$1,$A97,$L$1,$K$1) -> 0 | S97: =_xll.DBRW($B$1,S$65,Cons_Region!S$15,$M$1,Cons_Region!$H$12,Cons_Region!$C$12,$N$1,$A97,$L$1,$K$1) -> 0
A98: WKC.010.007 | B98: Input Inventory- Days o/ VC | C98: =_xll.DBRW($B$1,Cons_Region!$F$12,Cons_Region!C$15,$M$1,Cons_Region!$H$12,Cons_Region!$C$12,$N$1,$A98,$L$1,$K$1) -> 0 | D98: =_xll.DBRW($B$1,Cons_Region!$F$12,Cons_Region!D$15,$M$1,Cons_Region!$H$12,Cons_Region!$C$12,$N$1,$A98,$L$1,$K$1) -> 89.2401 | E98: =_xll.DBRW($B$1,Cons_Region!$F$12,Cons_Region!E$15,$M$1,Cons_Region!$H$12,Cons_Region!$C$12,$N$1,$A98,$L$1,$K$1) -> 86.5003 | F98: =_xll.DBRW($B$1,Cons_Region!$F$12,Cons_Region!F$15,$M$1,Cons_Region!$H$12,Cons_Region!$C$12,$N$1,$A98,$L$1,$K$1) -> 93.5029 | G98: =_xll.DBRW($B$1,Cons_Region!$F$12,Cons_Region!G$15,$M$1,Cons_Region!$H$12,Cons_Region!$C$12,$N$1,$A98,$L$1,$K$1) -> 89.0644 | H98: =_xll.DBRW($B$1,Cons_Region!$F$12,Cons_Region!H$15,$M$1,Cons_Region!$H$12,Cons_Region!$C$12,$N$1,$A98,$L$1,$K$1) -> 83.8152 | I98: =_xll.DBRW($B$1,Cons_Region!$F$12,Cons_Region!I$15,$M$1,Cons_Region!$H$12,Cons_Region!$C$12,$N$1,$A98,$L$1,$K$1) -> 78.3222 | J98: =_xll.DBRW($B$1,Cons_Region!$F$12,Cons_Region!J$15,$M$1,Cons_Region!$H$12,Cons_Region!$C$12,$N$1,$A98,$L$1,$K$1) -> 77.4834 | ... N98: =_xll.DBRW($B$1,Cons_Region!$F$12,Cons_Region!N$15,$M$1,Cons_Region!$H$12,Cons_Region!$C$12,$N$1,$A98,$L$1,$K$1) -> 0 | O98: =_xll.DBRW($B$1,O$65,Cons_Region!O$15,$M$1,Cons_Region!$H$12,Cons_Region!$C$12,$N$1,$A98,$L$1,$K$1) -> 0 | P98: =_xll.DBRW($B$1,P$65,Cons_Region!P$15,$M$1,Cons_Region!$H$12,Cons_Region!$C$12,$N$1,$A98,$L$1,$K$1) -> 0 | Q98: =_xll.DBRW($B$1,Q$65,Cons_Region!Q$15,$M$1,Cons_Region!$H$12,Cons_Region!$C$12,$N$1,$A98,$L$1,$K$1) -> 0 | R98: =_xll.DBRW($B$1,R$65,Cons_Region!R$15,$M$1,Cons_Region!$H$12,Cons_Region!$C$12,$N$1,$A98,$L$1,$K$1) -> 0 | S98: =_xll.DBRW($B$1,S$65,Cons_Region!S$15,$M$1,Cons_Region!$H$12,Cons_Region!$C$12,$N$1,$A98,$L$1,$K$1) -> 0
A99: WKC.010.015 | B99: Opex Advancement - Days o/ VC | C99: =_xll.DBRW($B$1,Cons_Region!$F$12,Cons_Region!C$15,$M$1,Cons_Region!$H$12,Cons_Region!$C$12,$N$1,$A99,$L$1,$K$1) -> 0 | D99: =_xll.DBRW($B$1,Cons_Region!$F$12,Cons_Region!D$15,$M$1,Cons_Region!$H$12,Cons_Region!$C$12,$N$1,$A99,$L$1,$K$1) -> 0 | E99: =_xll.DBRW($B$1,Cons_Region!$F$12,Cons_Region!E$15,$M$1,Cons_Region!$H$12,Cons_Region!$C$12,$N$1,$A99,$L$1,$K$1) -> 0 | F99: =_xll.DBRW($B$1,Cons_Region!$F$12,Cons_Region!F$15,$M$1,Cons_Region!$H$12,Cons_Region!$C$12,$N$1,$A99,$L$1,$K$1) -> 0 | G99: =_xll.DBRW($B$1,Cons_Region!$F$12,Cons_Region!G$15,$M$1,Cons_Region!$H$12,Cons_Region!$C$12,$N$1,$A99,$L$1,$K$1) -> 0 | H99: =_xll.DBRW($B$1,Cons_Region!$F$12,Cons_Region!H$15,$M$1,Cons_Region!$H$12,Cons_Region!$C$12,$N$1,$A99,$L$1,$K$1) -> 0 | I99: =_xll.DBRW($B$1,Cons_Region!$F$12,Cons_Region!I$15,$M$1,Cons_Region!$H$12,Cons_Region!$C$12,$N$1,$A99,$L$1,$K$1) -> 0 | J99: =_xll.DBRW($B$1,Cons_Region!$F$12,Cons_Region!J$15,$M$1,Cons_Region!$H$12,Cons_Region!$C$12,$N$1,$A99,$L$1,$K$1) -> 0 | ... N99: =_xll.DBRW($B$1,Cons_Region!$F$12,Cons_Region!N$15,$M$1,Cons_Region!$H$12,Cons_Region!$C$12,$N$1,$A99,$L$1,$K$1) -> 0 | O99: =_xll.DBRW($B$1,O$65,Cons_Region!O$15,$M$1,Cons_Region!$H$12,Cons_Region!$C$12,$N$1,$A99,$L$1,$K$1) -> 0 | P99: =_xll.DBRW($B$1,P$65,Cons_Region!P$15,$M$1,Cons_Region!$H$12,Cons_Region!$C$12,$N$1,$A99,$L$1,$K$1) -> 0 | Q99: =_xll.DBRW($B$1,Q$65,Cons_Region!Q$15,$M$1,Cons_Region!$H$12,Cons_Region!$C$12,$N$1,$A99,$L$1,$K$1) -> 0 | R99: =_xll.DBRW($B$1,R$65,Cons_Region!R$15,$M$1,Cons_Region!$H$12,Cons_Region!$C$12,$N$1,$A99,$L$1,$K$1) -> 0 | S99: =_xll.DBRW($B$1,S$65,Cons_Region!S$15,$M$1,Cons_Region!$H$12,Cons_Region!$C$12,$N$1,$A99,$L$1,$K$1) -> 0
A100: WKC.010.009 | B100: Other Accounts Receivables - Days o/ DSO | C100: =_xll.DBRW($B$1,Cons_Region!$F$12,Cons_Region!C$15,$M$1,Cons_Region!$H$12,Cons_Region!$C$12,$N$1,$A100,$L$1,$K$1) -> 0 | D100: =_xll.DBRW($B$1,Cons_Region!$F$12,Cons_Region!D$15,$M$1,Cons_Region!$H$12,Cons_Region!$C$12,$N$1,$A100,$L$1,$K$1) -> 2.2722 | E100: =_xll.DBRW($B$1,Cons_Region!$F$12,Cons_Region!E$15,$M$1,Cons_Region!$H$12,Cons_Region!$C$12,$N$1,$A100,$L$1,$K$1) -> 1.9215 | F100: =_xll.DBRW($B$1,Cons_Region!$F$12,Cons_Region!F$15,$M$1,Cons_Region!$H$12,Cons_Region!$C$12,$N$1,$A100,$L$1,$K$1) -> 1.9738 | G100: =_xll.DBRW($B$1,Cons_Region!$F$12,Cons_Region!G$15,$M$1,Cons_Region!$H$12,Cons_Region!$C$12,$N$1,$A100,$L$1,$K$1) -> 1.8309 | H100: =_xll.DBRW($B$1,Cons_Region!$F$12,Cons_Region!H$15,$M$1,Cons_Region!$H$12,Cons_Region!$C$12,$N$1,$A100,$L$1,$K$1) -> 1.4998 | I100: =_xll.DBRW($B$1,Cons_Region!$F$12,Cons_Region!I$15,$M$1,Cons_Region!$H$12,Cons_Region!$C$12,$N$1,$A100,$L$1,$K$1) -> 1.3398 | J100: =_xll.DBRW($B$1,Cons_Region!$F$12,Cons_Region!J$15,$M$1,Cons_Region!$H$12,Cons_Region!$C$12,$N$1,$A100,$L$1,$K$1) -> 1.2502 | ... N100: =_xll.DBRW($B$1,Cons_Region!$F$12,Cons_Region!N$15,$M$1,Cons_Region!$H$12,Cons_Region!$C$12,$N$1,$A100,$L$1,$K$1) -> 0 | O100: =_xll.DBRW($B$1,O$65,Cons_Region!O$15,$M$1,Cons_Region!$H$12,Cons_Region!$C$12,$N$1,$A100,$L$1,$K$1) -> 0 | P100: =_xll.DBRW($B$1,P$65,Cons_Region!P$15,$M$1,Cons_Region!$H$12,Cons_Region!$C$12,$N$1,$A100,$L$1,$K$1) -> 0 | Q100: =_xll.DBRW($B$1,Q$65,Cons_Region!Q$15,$M$1,Cons_Region!$H$12,Cons_Region!$C$12,$N$1,$A100,$L$1,$K$1) -> 0 | R100: =_xll.DBRW($B$1,R$65,Cons_Region!R$15,$M$1,Cons_Region!$H$12,Cons_Region!$C$12,$N$1,$A100,$L$1,$K$1) -> 0 | S100: =_xll.DBRW($B$1,S$65,Cons_Region!S$15,$M$1,Cons_Region!$H$12,Cons_Region!$C$12,$N$1,$A100,$L$1,$K$1) -> 0
B102: Working Capital - KPIs Liabilities Accounts
O103: =$F$12+1 -> 2027 | P103: =$F$12+2 -> 2028 | Q103: =$F$12+3 -> 2029 | R103: =$F$12+4 -> 2030 | S103: =$F$12+5 -> 2031
C104: =$F$12&"."&C$15 -> 2026.01 | D104: =$F$12&"."&D$15 -> 2026.02 | E104: =$F$12&"."&E$15 -> 2026.03 | F104: =$F$12&"."&F$15 -> 2026.04 | G104: =$F$12&"."&G$15 -> 2026.05 | H104: =$F$12&"."&H$15 -> 2026.06 | I104: =$F$12&"."&I$15 -> 2026.07 | J104: =$F$12&"."&J$15 -> 2026.08 | ... N104: =$F$12&"."&N$15 -> 2026.12 | O104: PE | P104: PE | Q104: PE | R104: PE | S104: PE
A105: WKC.020.001 | B105: Suppliers - Days o/ VC (DPO) | C105: =_xll.DBRW($B$1,Cons_Region!$F$12,Cons_Region!C$15,$M$1,Cons_Region!$H$12,Cons_Region!$C$12,$N$1,$A105,$L$1,$K$1) -> 0 | D105: =_xll.DBRW($B$1,Cons_Region!$F$12,Cons_Region!D$15,$M$1,Cons_Region!$H$12,Cons_Region!$C$12,$N$1,$A105,$L$1,$K$1) -> 103.2521 | E105: =_xll.DBRW($B$1,Cons_Region!$F$12,Cons_Region!E$15,$M$1,Cons_Region!$H$12,Cons_Region!$C$12,$N$1,$A105,$L$1,$K$1) -> 105.2088 | F105: =_xll.DBRW($B$1,Cons_Region!$F$12,Cons_Region!F$15,$M$1,Cons_Region!$H$12,Cons_Region!$C$12,$N$1,$A105,$L$1,$K$1) -> 123.7089 | G105: =_xll.DBRW($B$1,Cons_Region!$F$12,Cons_Region!G$15,$M$1,Cons_Region!$H$12,Cons_Region!$C$12,$N$1,$A105,$L$1,$K$1) -> 127.7015 | H105: =_xll.DBRW($B$1,Cons_Region!$F$12,Cons_Region!H$15,$M$1,Cons_Region!$H$12,Cons_Region!$C$12,$N$1,$A105,$L$1,$K$1) -> 125.3896 | I105: =_xll.DBRW($B$1,Cons_Region!$F$12,Cons_Region!I$15,$M$1,Cons_Region!$H$12,Cons_Region!$C$12,$N$1,$A105,$L$1,$K$1) -> 118.1795 | J105: =_xll.DBRW($B$1,Cons_Region!$F$12,Cons_Region!J$15,$M$1,Cons_Region!$H$12,Cons_Region!$C$12,$N$1,$A105,$L$1,$K$1) -> 110.2768 | ... N105: =_xll.DBRW($B$1,Cons_Region!$F$12,Cons_Region!N$15,$M$1,Cons_Region!$H$12,Cons_Region!$C$12,$N$1,$A105,$L$1,$K$1) -> 0 | O105: =_xll.DBRW($B$1,O$65,Cons_Region!O$15,$M$1,Cons_Region!$H$12,Cons_Region!$C$12,$N$1,$A105,$L$1,$K$1) -> 0 | P105: =_xll.DBRW($B$1,P$65,Cons_Region!P$15,$M$1,Cons_Region!$H$12,Cons_Region!$C$12,$N$1,$A105,$L$1,$K$1) -> 0 | Q105: =_xll.DBRW($B$1,Q$65,Cons_Region!Q$15,$M$1,Cons_Region!$H$12,Cons_Region!$C$12,$N$1,$A105,$L$1,$K$1) -> 0 | R105: =_xll.DBRW($B$1,R$65,Cons_Region!R$15,$M$1,Cons_Region!$H$12,Cons_Region!$C$12,$N$1,$A105,$L$1,$K$1) -> 0 | S105: =_xll.DBRW($B$1,S$65,Cons_Region!S$15,$M$1,Cons_Region!$H$12,Cons_Region!$C$12,$N$1,$A105,$L$1,$K$1) -> 0
A106: WKC.020.003 | B106: Operating Taxes Payable - % o/ Rev. | C106: =_xll.DBRW($B$1,Cons_Region!$F$12,Cons_Region!C$15,$M$1,Cons_Region!$H$12,Cons_Region!$C$12,$N$1,$A106,$L$1,$K$1) -> 0 | D106: =_xll.DBRW($B$1,Cons_Region!$F$12,Cons_Region!D$15,$M$1,Cons_Region!$H$12,Cons_Region!$C$12,$N$1,$A106,$L$1,$K$1) -> 0.0797 | E106: =_xll.DBRW($B$1,Cons_Region!$F$12,Cons_Region!E$15,$M$1,Cons_Region!$H$12,Cons_Region!$C$12,$N$1,$A106,$L$1,$K$1) -> 0.0468 | F106: =_xll.DBRW($B$1,Cons_Region!$F$12,Cons_Region!F$15,$M$1,Cons_Region!$H$12,Cons_Region!$C$12,$N$1,$A106,$L$1,$K$1) -> 0.044 | G106: =_xll.DBRW($B$1,Cons_Region!$F$12,Cons_Region!G$15,$M$1,Cons_Region!$H$12,Cons_Region!$C$12,$N$1,$A106,$L$1,$K$1) -> 0.0563 | H106: =_xll.DBRW($B$1,Cons_Region!$F$12,Cons_Region!H$15,$M$1,Cons_Region!$H$12,Cons_Region!$C$12,$N$1,$A106,$L$1,$K$1) -> 0.0497 | I106: =_xll.DBRW($B$1,Cons_Region!$F$12,Cons_Region!I$15,$M$1,Cons_Region!$H$12,Cons_Region!$C$12,$N$1,$A106,$L$1,$K$1) -> 0.0681 | J106: =_xll.DBRW($B$1,Cons_Region!$F$12,Cons_Region!J$15,$M$1,Cons_Region!$H$12,Cons_Region!$C$12,$N$1,$A106,$L$1,$K$1) -> 0.0551 | ... N106: =_xll.DBRW($B$1,Cons_Region!$F$12,Cons_Region!N$15,$M$1,Cons_Region!$H$12,Cons_Region!$C$12,$N$1,$A106,$L$1,$K$1) -> 0 | O106: =_xll.DBRW($B$1,O$65,Cons_Region!O$15,$M$1,Cons_Region!$H$12,Cons_Region!$C$12,$N$1,$A106,$L$1,$K$1) -> 0 | P106: =_xll.DBRW($B$1,P$65,Cons_Region!P$15,$M$1,Cons_Region!$H$12,Cons_Region!$C$12,$N$1,$A106,$L$1,$K$1) -> 0 | Q106: =_xll.DBRW($B$1,Q$65,Cons_Region!Q$15,$M$1,Cons_Region!$H$12,Cons_Region!$C$12,$N$1,$A106,$L$1,$K$1) -> 0 | R106: =_xll.DBRW($B$1,R$65,Cons_Region!R$15,$M$1,Cons_Region!$H$12,Cons_Region!$C$12,$N$1,$A106,$L$1,$K$1) -> 0 | S106: =_xll.DBRW($B$1,S$65,Cons_Region!S$15,$M$1,Cons_Region!$H$12,Cons_Region!$C$12,$N$1,$A106,$L$1,$K$1) -> 0
A107: WKC.020.007 | B107: Labor Obligations - Days o/ FC | C107: =_xll.DBRW($B$1,Cons_Region!$F$12,Cons_Region!C$15,$M$1,Cons_Region!$H$12,Cons_Region!$C$12,$N$1,$A107,$L$1,$K$1) -> 0 | D107: =_xll.DBRW($B$1,Cons_Region!$F$12,Cons_Region!D$15,$M$1,Cons_Region!$H$12,Cons_Region!$C$12,$N$1,$A107,$L$1,$K$1) -> 0 | E107: =_xll.DBRW($B$1,Cons_Region!$F$12,Cons_Region!E$15,$M$1,Cons_Region!$H$12,Cons_Region!$C$12,$N$1,$A107,$L$1,$K$1) -> 0 | F107: =_xll.DBRW($B$1,Cons_Region!$F$12,Cons_Region!F$15,$M$1,Cons_Region!$H$12,Cons_Region!$C$12,$N$1,$A107,$L$1,$K$1) -> 0 | G107: =_xll.DBRW($B$1,Cons_Region!$F$12,Cons_Region!G$15,$M$1,Cons_Region!$H$12,Cons_Region!$C$12,$N$1,$A107,$L$1,$K$1) -> 0 | H107: =_xll.DBRW($B$1,Cons_Region!$F$12,Cons_Region!H$15,$M$1,Cons_Region!$H$12,Cons_Region!$C$12,$N$1,$A107,$L$1,$K$1) -> 0 | I107: =_xll.DBRW($B$1,Cons_Region!$F$12,Cons_Region!I$15,$M$1,Cons_Region!$H$12,Cons_Region!$C$12,$N$1,$A107,$L$1,$K$1) -> 0 | J107: =_xll.DBRW($B$1,Cons_Region!$F$12,Cons_Region!J$15,$M$1,Cons_Region!$H$12,Cons_Region!$C$12,$N$1,$A107,$L$1,$K$1) -> 0 | ... N107: =_xll.DBRW($B$1,Cons_Region!$F$12,Cons_Region!N$15,$M$1,Cons_Region!$H$12,Cons_Region!$C$12,$N$1,$A107,$L$1,$K$1) -> 0 | O107: =_xll.DBRW($B$1,O$65,Cons_Region!O$15,$M$1,Cons_Region!$H$12,Cons_Region!$C$12,$N$1,$A107,$L$1,$K$1) -> 0 | P107: =_xll.DBRW($B$1,P$65,Cons_Region!P$15,$M$1,Cons_Region!$H$12,Cons_Region!$C$12,$N$1,$A107,$L$1,$K$1) -> 0 | Q107: =_xll.DBRW($B$1,Q$65,Cons_Region!Q$15,$M$1,Cons_Region!$H$12,Cons_Region!$C$12,$N$1,$A107,$L$1,$K$1) -> 0 | R107: =_xll.DBRW($B$1,R$65,Cons_Region!R$15,$M$1,Cons_Region!$H$12,Cons_Region!$C$12,$N$1,$A107,$L$1,$K$1) -> 0 | S107: =_xll.DBRW($B$1,S$65,Cons_Region!S$15,$M$1,Cons_Region!$H$12,Cons_Region!$C$12,$N$1,$A107,$L$1,$K$1) -> 0
A108: WKC.020.006 | B108: Other Accounts Payable - Days o/ CPS | C108: =_xll.DBRW($B$1,Cons_Region!$F$12,Cons_Region!C$15,$M$1,Cons_Region!$H$12,Cons_Region!$C$12,$N$1,$A108,$L$1,$K$1) -> 0 | D108: =_xll.DBRW($B$1,Cons_Region!$F$12,Cons_Region!D$15,$M$1,Cons_Region!$H$12,Cons_Region!$C$12,$N$1,$A108,$L$1,$K$1) -> 11.0928 | E108: =_xll.DBRW($B$1,Cons_Region!$F$12,Cons_Region!E$15,$M$1,Cons_Region!$H$12,Cons_Region!$C$12,$N$1,$A108,$L$1,$K$1) -> 11.3412 | F108: =_xll.DBRW($B$1,Cons_Region!$F$12,Cons_Region!F$15,$M$1,Cons_Region!$H$12,Cons_Region!$C$12,$N$1,$A108,$L$1,$K$1) -> 13.3984 | G108: =_xll.DBRW($B$1,Cons_Region!$F$12,Cons_Region!G$15,$M$1,Cons_Region!$H$12,Cons_Region!$C$12,$N$1,$A108,$L$1,$K$1) -> 14.4897 | H108: =_xll.DBRW($B$1,Cons_Region!$F$12,Cons_Region!H$15,$M$1,Cons_Region!$H$12,Cons_Region!$C$12,$N$1,$A108,$L$1,$K$1) -> 16.0635 | I108: =_xll.DBRW($B$1,Cons_Region!$F$12,Cons_Region!I$15,$M$1,Cons_Region!$H$12,Cons_Region!$C$12,$N$1,$A108,$L$1,$K$1) -> 15.012 | J108: =_xll.DBRW($B$1,Cons_Region!$F$12,Cons_Region!J$15,$M$1,Cons_Region!$H$12,Cons_Region!$C$12,$N$1,$A108,$L$1,$K$1) -> 15.8001 | ... N108: =_xll.DBRW($B$1,Cons_Region!$F$12,Cons_Region!N$15,$M$1,Cons_Region!$H$12,Cons_Region!$C$12,$N$1,$A108,$L$1,$K$1) -> 0 | O108: =_xll.DBRW($B$1,O$65,Cons_Region!O$15,$M$1,Cons_Region!$H$12,Cons_Region!$C$12,$N$1,$A108,$L$1,$K$1) -> 0 | P108: =_xll.DBRW($B$1,P$65,Cons_Region!P$15,$M$1,Cons_Region!$H$12,Cons_Region!$C$12,$N$1,$A108,$L$1,$K$1) -> 0 | Q108: =_xll.DBRW($B$1,Q$65,Cons_Region!Q$15,$M$1,Cons_Region!$H$12,Cons_Region!$C$12,$N$1,$A108,$L$1,$K$1) -> 0 | R108: =_xll.DBRW($B$1,R$65,Cons_Region!R$15,$M$1,Cons_Region!$H$12,Cons_Region!$C$12,$N$1,$A108,$L$1,$K$1) -> 0 | S108: =_xll.DBRW($B$1,S$65,Cons_Region!S$15,$M$1,Cons_Region!$H$12,Cons_Region!$C$12,$N$1,$A108,$L$1,$K$1) -> 0
B111: Working Capital - Assets Account Balance
O112: =$F$12+1 -> 2027 | P112: =$F$12+2 -> 2028 | Q112: =$F$12+3 -> 2029 | R112: =$F$12+4 -> 2030 | S112: =$F$12+5 -> 2031
C113: =$F$12&"."&C$15 -> 2026.01 | D113: =$F$12&"."&D$15 -> 2026.02 | E113: =$F$12&"."&E$15 -> 2026.03 | F113: =$F$12&"."&F$15 -> 2026.04 | G113: =$F$12&"."&G$15 -> 2026.05 | H113: =$F$12&"."&H$15 -> 2026.06 | I113: =$F$12&"."&I$15 -> 2026.07 | J113: =$F$12&"."&J$15 -> 2026.08 | ... N113: =$F$12&"."&N$15 -> 2026.12 | O113: PE | P113: PE | Q113: PE | R113: PE | S113: PE
A114: WKC.099.005 | B114: PROJECTED BALANCE - ASSETS | C114: =_xll.DBRW($C$3,Cons_Region!$F$12,Cons_Region!C$15,$M$1,Cons_Region!$H$12,Cons_Region!$C$12,$A114,$K$1) -> 0 | D114: =_xll.DBRW($C$3,Cons_Region!$F$12,Cons_Region!D$15,$M$1,Cons_Region!$H$12,Cons_Region!$C$12,$A114,$K$1) -> 3110.242 | E114: =_xll.DBRW($C$3,Cons_Region!$F$12,Cons_Region!E$15,$M$1,Cons_Region!$H$12,Cons_Region!$C$12,$A114,$K$1) -> 3218.598 | F114: =_xll.DBRW($C$3,Cons_Region!$F$12,Cons_Region!F$15,$M$1,Cons_Region!$H$12,Cons_Region!$C$12,$A114,$K$1) -> 3085.8622 | G114: =_xll.DBRW($C$3,Cons_Region!$F$12,Cons_Region!G$15,$M$1,Cons_Region!$H$12,Cons_Region!$C$12,$A114,$K$1) -> 3122.2741 | H114: =_xll.DBRW($C$3,Cons_Region!$F$12,Cons_Region!H$15,$M$1,Cons_Region!$H$12,Cons_Region!$C$12,$A114,$K$1) -> 3174.4747 | I114: =_xll.DBRW($C$3,Cons_Region!$F$12,Cons_Region!I$15,$M$1,Cons_Region!$H$12,Cons_Region!$C$12,$A114,$K$1) -> 3107.0027 | J114: =_xll.DBRW($C$3,Cons_Region!$F$12,Cons_Region!J$15,$M$1,Cons_Region!$H$12,Cons_Region!$C$12,$A114,$K$1) -> 3193.8977 | ... N114: =_xll.DBRW($C$3,Cons_Region!$F$12,Cons_Region!N$15,$M$1,Cons_Region!$H$12,Cons_Region!$C$12,$A114,$K$1) -> 0 | O114: =_xll.DBRW($C$3,O$14,Cons_Region!O$15,$M$1,Cons_Region!$H$12,Cons_Region!$C$12,$A114,$K$1) -> 0 | P114: =_xll.DBRW($C$3,P$14,Cons_Region!P$15,$M$1,Cons_Region!$H$12,Cons_Region!$C$12,$A114,$K$1) -> 0 | Q114: =_xll.DBRW($C$3,Q$14,Cons_Region!Q$15,$M$1,Cons_Region!$H$12,Cons_Region!$C$12,$A114,$K$1) -> 0 | R114: =_xll.DBRW($C$3,R$14,Cons_Region!R$15,$M$1,Cons_Region!$H$12,Cons_Region!$C$12,$A114,$K$1) -> 0 | S114: =_xll.DBRW($C$3,S$14,Cons_Region!S$15,$M$1,Cons_Region!$H$12,Cons_Region!$C$12,$A114,$K$1) -> 0
A115: WKC.010.001 | B115: Accounts Receivable | C115: =_xll.DBRW($C$3,Cons_Region!$F$12,Cons_Region!C$15,$M$1,Cons_Region!$H$12,Cons_Region!$C$12,$A115,$K$1) -> 0 | D115: =_xll.DBRW($C$3,Cons_Region!$F$12,Cons_Region!D$15,$M$1,Cons_Region!$H$12,Cons_Region!$C$12,$A115,$K$1) -> 1072.0807 | E115: =_xll.DBRW($C$3,Cons_Region!$F$12,Cons_Region!E$15,$M$1,Cons_Region!$H$12,Cons_Region!$C$12,$A115,$K$1) -> 1217.014 | F115: =_xll.DBRW($C$3,Cons_Region!$F$12,Cons_Region!F$15,$M$1,Cons_Region!$H$12,Cons_Region!$C$12,$A115,$K$1) -> 1116.724 | G115: =_xll.DBRW($C$3,Cons_Region!$F$12,Cons_Region!G$15,$M$1,Cons_Region!$H$12,Cons_Region!$C$12,$A115,$K$1) -> 1249.9056 | H115: =_xll.DBRW($C$3,Cons_Region!$F$12,Cons_Region!H$15,$M$1,Cons_Region!$H$12,Cons_Region!$C$12,$A115,$K$1) -> 1316.6769 | I115: =_xll.DBRW($C$3,Cons_Region!$F$12,Cons_Region!I$15,$M$1,Cons_Region!$H$12,Cons_Region!$C$12,$A115,$K$1) -> 1294.5214 | J115: =_xll.DBRW($C$3,Cons_Region!$F$12,Cons_Region!J$15,$M$1,Cons_Region!$H$12,Cons_Region!$C$12,$A115,$K$1) -> 1372.4229 | ... N115: =_xll.DBRW($C$3,Cons_Region!$F$12,Cons_Region!N$15,$M$1,Cons_Region!$H$12,Cons_Region!$C$12,$A115,$K$1) -> 0 | O115: =_xll.DBRW($C$3,O$14,Cons_Region!O$15,$M$1,Cons_Region!$H$12,Cons_Region!$C$12,$A115,$K$1) -> 0 | P115: =_xll.DBRW($C$3,P$14,Cons_Region!P$15,$M$1,Cons_Region!$H$12,Cons_Region!$C$12,$A115,$K$1) -> 0 | Q115: =_xll.DBRW($C$3,Q$14,Cons_Region!Q$15,$M$1,Cons_Region!$H$12,Cons_Region!$C$12,$A115,$K$1) -> 0 | R115: =_xll.DBRW($C$3,R$14,Cons_Region!R$15,$M$1,Cons_Region!$H$12,Cons_Region!$C$12,$A115,$K$1) -> 0 | S115: =_xll.DBRW($C$3,S$14,Cons_Region!S$15,$M$1,Cons_Region!$H$12,Cons_Region!$C$12,$A115,$K$1) -> 0
A116: WKC.010.002 | B116: Finished Product Inventory | C116: =_xll.DBRW($C$3,Cons_Region!$F$12,Cons_Region!C$15,$M$1,Cons_Region!$H$12,Cons_Region!$C$12,$A116,$K$1) -> 0 | D116: =_xll.DBRW($C$3,Cons_Region!$F$12,Cons_Region!D$15,$M$1,Cons_Region!$H$12,Cons_Region!$C$12,$A116,$K$1) -> 0 | E116: =_xll.DBRW($C$3,Cons_Region!$F$12,Cons_Region!E$15,$M$1,Cons_Region!$H$12,Cons_Region!$C$12,$A116,$K$1) -> 0 | F116: =_xll.DBRW($C$3,Cons_Region!$F$12,Cons_Region!F$15,$M$1,Cons_Region!$H$12,Cons_Region!$C$12,$A116,$K$1) -> 0 | G116: =_xll.DBRW($C$3,Cons_Region!$F$12,Cons_Region!G$15,$M$1,Cons_Region!$H$12,Cons_Region!$C$12,$A116,$K$1) -> 0 | H116: =_xll.DBRW($C$3,Cons_Region!$F$12,Cons_Region!H$15,$M$1,Cons_Region!$H$12,Cons_Region!$C$12,$A116,$K$1) -> 0 | I116: =_xll.DBRW($C$3,Cons_Region!$F$12,Cons_Region!I$15,$M$1,Cons_Region!$H$12,Cons_Region!$C$12,$A116,$K$1) -> 0 | J116: =_xll.DBRW($C$3,Cons_Region!$F$12,Cons_Region!J$15,$M$1,Cons_Region!$H$12,Cons_Region!$C$12,$A116,$K$1) -> 0 | ... N116: =_xll.DBRW($C$3,Cons_Region!$F$12,Cons_Region!N$15,$M$1,Cons_Region!$H$12,Cons_Region!$C$12,$A116,$K$1) -> 0 | O116: =_xll.DBRW($C$3,O$14,Cons_Region!O$15,$M$1,Cons_Region!$H$12,Cons_Region!$C$12,$A116,$K$1) -> 0 | P116: =_xll.DBRW($C$3,P$14,Cons_Region!P$15,$M$1,Cons_Region!$H$12,Cons_Region!$C$12,$A116,$K$1) -> 0 | Q116: =_xll.DBRW($C$3,Q$14,Cons_Region!Q$15,$M$1,Cons_Region!$H$12,Cons_Region!$C$12,$A116,$K$1) -> 0 | R116: =_xll.DBRW($C$3,R$14,Cons_Region!R$15,$M$1,Cons_Region!$H$12,Cons_Region!$C$12,$A116,$K$1) -> 0 | S116: =_xll.DBRW($C$3,S$14,Cons_Region!S$15,$M$1,Cons_Region!$H$12,Cons_Region!$C$12,$A116,$K$1) -> 0
A117: WKC.010.003 | B117: Product in Process Inventory | C117: =_xll.DBRW($C$3,Cons_Region!$F$12,Cons_Region!C$15,$M$1,Cons_Region!$H$12,Cons_Region!$C$12,$A117,$K$1) -> 0 | D117: =_xll.DBRW($C$3,Cons_Region!$F$12,Cons_Region!D$15,$M$1,Cons_Region!$H$12,Cons_Region!$C$12,$A117,$K$1) -> 0 | E117: =_xll.DBRW($C$3,Cons_Region!$F$12,Cons_Region!E$15,$M$1,Cons_Region!$H$12,Cons_Region!$C$12,$A117,$K$1) -> 0 | F117: =_xll.DBRW($C$3,Cons_Region!$F$12,Cons_Region!F$15,$M$1,Cons_Region!$H$12,Cons_Region!$C$12,$A117,$K$1) -> 0 | G117: =_xll.DBRW($C$3,Cons_Region!$F$12,Cons_Region!G$15,$M$1,Cons_Region!$H$12,Cons_Region!$C$12,$A117,$K$1) -> 0 | H117: =_xll.DBRW($C$3,Cons_Region!$F$12,Cons_Region!H$15,$M$1,Cons_Region!$H$12,Cons_Region!$C$12,$A117,$K$1) -> 0 | I117: =_xll.DBRW($C$3,Cons_Region!$F$12,Cons_Region!I$15,$M$1,Cons_Region!$H$12,Cons_Region!$C$12,$A117,$K$1) -> 0 | J117: =_xll.DBRW($C$3,Cons_Region!$F$12,Cons_Region!J$15,$M$1,Cons_Region!$H$12,Cons_Region!$C$12,$A117,$K$1) -> 0 | ... N117: =_xll.DBRW($C$3,Cons_Region!$F$12,Cons_Region!N$15,$M$1,Cons_Region!$H$12,Cons_Region!$C$12,$A117,$K$1) -> 0 | O117: =_xll.DBRW($C$3,O$14,Cons_Region!O$15,$M$1,Cons_Region!$H$12,Cons_Region!$C$12,$A117,$K$1) -> 0 | P117: =_xll.DBRW($C$3,P$14,Cons_Region!P$15,$M$1,Cons_Region!$H$12,Cons_Region!$C$12,$A117,$K$1) -> 0 | Q117: =_xll.DBRW($C$3,Q$14,Cons_Region!Q$15,$M$1,Cons_Region!$H$12,Cons_Region!$C$12,$A117,$K$1) -> 0 | R117: =_xll.DBRW($C$3,R$14,Cons_Region!R$15,$M$1,Cons_Region!$H$12,Cons_Region!$C$12,$A117,$K$1) -> 0 | S117: =_xll.DBRW($C$3,S$14,Cons_Region!S$15,$M$1,Cons_Region!$H$12,Cons_Region!$C$12,$A117,$K$1) -> 0
A118: WKC.010.017 | B118: Concentrate Inventory | C118: =_xll.DBRW($C$3,Cons_Region!$F$12,Cons_Region!C$15,$M$1,Cons_Region!$H$12,Cons_Region!$C$12,$A118,$K$1) -> 0 | D118: =_xll.DBRW($C$3,Cons_Region!$F$12,Cons_Region!D$15,$M$1,Cons_Region!$H$12,Cons_Region!$C$12,$A118,$K$1) -> 0 | E118: =_xll.DBRW($C$3,Cons_Region!$F$12,Cons_Region!E$15,$M$1,Cons_Region!$H$12,Cons_Region!$C$12,$A118,$K$1) -> 0 | F118: =_xll.DBRW($C$3,Cons_Region!$F$12,Cons_Region!F$15,$M$1,Cons_Region!$H$12,Cons_Region!$C$12,$A118,$K$1) -> 0 | G118: =_xll.DBRW($C$3,Cons_Region!$F$12,Cons_Region!G$15,$M$1,Cons_Region!$H$12,Cons_Region!$C$12,$A118,$K$1) -> 0 | H118: =_xll.DBRW($C$3,Cons_Region!$F$12,Cons_Region!H$15,$M$1,Cons_Region!$H$12,Cons_Region!$C$12,$A118,$K$1) -> 0 | I118: =_xll.DBRW($C$3,Cons_Region!$F$12,Cons_Region!I$15,$M$1,Cons_Region!$H$12,Cons_Region!$C$12,$A118,$K$1) -> 0 | J118: =_xll.DBRW($C$3,Cons_Region!$F$12,Cons_Region!J$15,$M$1,Cons_Region!$H$12,Cons_Region!$C$12,$A118,$K$1) -> 0 | ... N118: =_xll.DBRW($C$3,Cons_Region!$F$12,Cons_Region!N$15,$M$1,Cons_Region!$H$12,Cons_Region!$C$12,$A118,$K$1) -> 0 | O118: =_xll.DBRW($C$3,O$14,Cons_Region!O$15,$M$1,Cons_Region!$H$12,Cons_Region!$C$12,$A118,$K$1) -> 0 | P118: =_xll.DBRW($C$3,P$14,Cons_Region!P$15,$M$1,Cons_Region!$H$12,Cons_Region!$C$12,$A118,$K$1) -> 0 | Q118: =_xll.DBRW($C$3,Q$14,Cons_Region!Q$15,$M$1,Cons_Region!$H$12,Cons_Region!$C$12,$A118,$K$1) -> 0 | R118: =_xll.DBRW($C$3,R$14,Cons_Region!R$15,$M$1,Cons_Region!$H$12,Cons_Region!$C$12,$A118,$K$1) -> 0 | S118: =_xll.DBRW($C$3,S$14,Cons_Region!S$15,$M$1,Cons_Region!$H$12,Cons_Region!$C$12,$A118,$K$1) -> 0
A119: WKC.010.004 | B119: MRO Inventory | C119: =_xll.DBRW($C$3,Cons_Region!$F$12,Cons_Region!C$15,$M$1,Cons_Region!$H$12,Cons_Region!$C$12,$A119,$K$1) -> 0 | D119: =_xll.DBRW($C$3,Cons_Region!$F$12,Cons_Region!D$15,$M$1,Cons_Region!$H$12,Cons_Region!$C$12,$A119,$K$1) -> 0 | E119: =_xll.DBRW($C$3,Cons_Region!$F$12,Cons_Region!E$15,$M$1,Cons_Region!$H$12,Cons_Region!$C$12,$A119,$K$1) -> 0 | F119: =_xll.DBRW($C$3,Cons_Region!$F$12,Cons_Region!F$15,$M$1,Cons_Region!$H$12,Cons_Region!$C$12,$A119,$K$1) -> 0 | G119: =_xll.DBRW($C$3,Cons_Region!$F$12,Cons_Region!G$15,$M$1,Cons_Region!$H$12,Cons_Region!$C$12,$A119,$K$1) -> 0 | H119: =_xll.DBRW($C$3,Cons_Region!$F$12,Cons_Region!H$15,$M$1,Cons_Region!$H$12,Cons_Region!$C$12,$A119,$K$1) -> 0 | I119: =_xll.DBRW($C$3,Cons_Region!$F$12,Cons_Region!I$15,$M$1,Cons_Region!$H$12,Cons_Region!$C$12,$A119,$K$1) -> 0 | J119: =_xll.DBRW($C$3,Cons_Region!$F$12,Cons_Region!J$15,$M$1,Cons_Region!$H$12,Cons_Region!$C$12,$A119,$K$1) -> 0 | ... N119: =_xll.DBRW($C$3,Cons_Region!$F$12,Cons_Region!N$15,$M$1,Cons_Region!$H$12,Cons_Region!$C$12,$A119,$K$1) -> 0 | O119: =_xll.DBRW($C$3,O$14,Cons_Region!O$15,$M$1,Cons_Region!$H$12,Cons_Region!$C$12,$A119,$K$1) -> 0 | P119: =_xll.DBRW($C$3,P$14,Cons_Region!P$15,$M$1,Cons_Region!$H$12,Cons_Region!$C$12,$A119,$K$1) -> 0 | Q119: =_xll.DBRW($C$3,Q$14,Cons_Region!Q$15,$M$1,Cons_Region!$H$12,Cons_Region!$C$12,$A119,$K$1) -> 0 | R119: =_xll.DBRW($C$3,R$14,Cons_Region!R$15,$M$1,Cons_Region!$H$12,Cons_Region!$C$12,$A119,$K$1) -> 0 | S119: =_xll.DBRW($C$3,S$14,Cons_Region!S$15,$M$1,Cons_Region!$H$12,Cons_Region!$C$12,$A119,$K$1) -> 0
A120: WKC.010.008 | B120: Other Inputs Inventory | C120: =_xll.DBRW($C$3,Cons_Region!$F$12,Cons_Region!C$15,$M$1,Cons_Region!$H$12,Cons_Region!$C$12,$A120,$K$1) -> 0 | D120: =_xll.DBRW($C$3,Cons_Region!$F$12,Cons_Region!D$15,$M$1,Cons_Region!$H$12,Cons_Region!$C$12,$A120,$K$1) -> 1908.7096 | E120: =_xll.DBRW($C$3,Cons_Region!$F$12,Cons_Region!E$15,$M$1,Cons_Region!$H$12,Cons_Region!$C$12,$A120,$K$1) -> 1884.1674 | F120: =_xll.DBRW($C$3,Cons_Region!$F$12,Cons_Region!F$15,$M$1,Cons_Region!$H$12,Cons_Region!$C$12,$A120,$K$1) -> 1852.9931 | G120: =_xll.DBRW($C$3,Cons_Region!$F$12,Cons_Region!G$15,$M$1,Cons_Region!$H$12,Cons_Region!$C$12,$A120,$K$1) -> 1759.5118 | H120: =_xll.DBRW($C$3,Cons_Region!$F$12,Cons_Region!H$15,$M$1,Cons_Region!$H$12,Cons_Region!$C$12,$A120,$K$1) -> 1759.3163 | I120: =_xll.DBRW($C$3,Cons_Region!$F$12,Cons_Region!I$15,$M$1,Cons_Region!$H$12,Cons_Region!$C$12,$A120,$K$1) -> 1720.4429 | J120: =_xll.DBRW($C$3,Cons_Region!$F$12,Cons_Region!J$15,$M$1,Cons_Region!$H$12,Cons_Region!$C$12,$A120,$K$1) -> 1734.7296 | ... N120: =_xll.DBRW($C$3,Cons_Region!$F$12,Cons_Region!N$15,$M$1,Cons_Region!$H$12,Cons_Region!$C$12,$A120,$K$1) -> 0 | O120: =_xll.DBRW($C$3,O$14,Cons_Region!O$15,$M$1,Cons_Region!$H$12,Cons_Region!$C$12,$A120,$K$1) -> 0 | P120: =_xll.DBRW($C$3,P$14,Cons_Region!P$15,$M$1,Cons_Region!$H$12,Cons_Region!$C$12,$A120,$K$1) -> 0 | Q120: =_xll.DBRW($C$3,Q$14,Cons_Region!Q$15,$M$1,Cons_Region!$H$12,Cons_Region!$C$12,$A120,$K$1) -> 0 | R120: =_xll.DBRW($C$3,R$14,Cons_Region!R$15,$M$1,Cons_Region!$H$12,Cons_Region!$C$12,$A120,$K$1) -> 0 | S120: =_xll.DBRW($C$3,S$14,Cons_Region!S$15,$M$1,Cons_Region!$H$12,Cons_Region!$C$12,$A120,$K$1) -> 0
A121: WKC.010.005 | B121: Opex Adavancement | C121: =_xll.DBRW($C$3,Cons_Region!$F$12,Cons_Region!C$15,$M$1,Cons_Region!$H$12,Cons_Region!$C$12,$A121,$K$1) -> 0 | D121: =_xll.DBRW($C$3,Cons_Region!$F$12,Cons_Region!D$15,$M$1,Cons_Region!$H$12,Cons_Region!$C$12,$A121,$K$1) -> 0 | E121: =_xll.DBRW($C$3,Cons_Region!$F$12,Cons_Region!E$15,$M$1,Cons_Region!$H$12,Cons_Region!$C$12,$A121,$K$1) -> 0 | F121: =_xll.DBRW($C$3,Cons_Region!$F$12,Cons_Region!F$15,$M$1,Cons_Region!$H$12,Cons_Region!$C$12,$A121,$K$1) -> 0 | G121: =_xll.DBRW($C$3,Cons_Region!$F$12,Cons_Region!G$15,$M$1,Cons_Region!$H$12,Cons_Region!$C$12,$A121,$K$1) -> 0 | H121: =_xll.DBRW($C$3,Cons_Region!$F$12,Cons_Region!H$15,$M$1,Cons_Region!$H$12,Cons_Region!$C$12,$A121,$K$1) -> 0 | I121: =_xll.DBRW($C$3,Cons_Region!$F$12,Cons_Region!I$15,$M$1,Cons_Region!$H$12,Cons_Region!$C$12,$A121,$K$1) -> 0 | J121: =_xll.DBRW($C$3,Cons_Region!$F$12,Cons_Region!J$15,$M$1,Cons_Region!$H$12,Cons_Region!$C$12,$A121,$K$1) -> 0 | ... N121: =_xll.DBRW($C$3,Cons_Region!$F$12,Cons_Region!N$15,$M$1,Cons_Region!$H$12,Cons_Region!$C$12,$A121,$K$1) -> 0 | O121: =_xll.DBRW($C$3,O$14,Cons_Region!O$15,$M$1,Cons_Region!$H$12,Cons_Region!$C$12,$A121,$K$1) -> 0 | P121: =_xll.DBRW($C$3,P$14,Cons_Region!P$15,$M$1,Cons_Region!$H$12,Cons_Region!$C$12,$A121,$K$1) -> 0 | Q121: =_xll.DBRW($C$3,Q$14,Cons_Region!Q$15,$M$1,Cons_Region!$H$12,Cons_Region!$C$12,$A121,$K$1) -> 0 | R121: =_xll.DBRW($C$3,R$14,Cons_Region!R$15,$M$1,Cons_Region!$H$12,Cons_Region!$C$12,$A121,$K$1) -> 0 | S121: =_xll.DBRW($C$3,S$14,Cons_Region!S$15,$M$1,Cons_Region!$H$12,Cons_Region!$C$12,$A121,$K$1) -> 0
A122: WKC.010.006 | B122: Other Accounts Receivable | C122: =_xll.DBRW($C$3,Cons_Region!$F$12,Cons_Region!C$15,$M$1,Cons_Region!$H$12,Cons_Region!$C$12,$A122,$K$1) -> 0 | D122: =_xll.DBRW($C$3,Cons_Region!$F$12,Cons_Region!D$15,$M$1,Cons_Region!$H$12,Cons_Region!$C$12,$A122,$K$1) -> 129.45162 | E122: =_xll.DBRW($C$3,Cons_Region!$F$12,Cons_Region!E$15,$M$1,Cons_Region!$H$12,Cons_Region!$C$12,$A122,$K$1) -> 117.4166 | F122: =_xll.DBRW($C$3,Cons_Region!$F$12,Cons_Region!F$15,$M$1,Cons_Region!$H$12,Cons_Region!$C$12,$A122,$K$1) -> 116.14509 | G122: =_xll.DBRW($C$3,Cons_Region!$F$12,Cons_Region!G$15,$M$1,Cons_Region!$H$12,Cons_Region!$C$12,$A122,$K$1) -> 112.85672 | H122: =_xll.DBRW($C$3,Cons_Region!$F$12,Cons_Region!H$15,$M$1,Cons_Region!$H$12,Cons_Region!$C$12,$A122,$K$1) -> 98.481549 | I122: =_xll.DBRW($C$3,Cons_Region!$F$12,Cons_Region!I$15,$M$1,Cons_Region!$H$12,Cons_Region!$C$12,$A122,$K$1) -> 92.038427 | J122: =_xll.DBRW($C$3,Cons_Region!$F$12,Cons_Region!J$15,$M$1,Cons_Region!$H$12,Cons_Region!$C$12,$A122,$K$1) -> 86.745218 | ... N122: =_xll.DBRW($C$3,Cons_Region!$F$12,Cons_Region!N$15,$M$1,Cons_Region!$H$12,Cons_Region!$C$12,$A122,$K$1) -> 0 | O122: =_xll.DBRW($C$3,O$14,Cons_Region!O$15,$M$1,Cons_Region!$H$12,Cons_Region!$C$12,$A122,$K$1) -> 0 | P122: =_xll.DBRW($C$3,P$14,Cons_Region!P$15,$M$1,Cons_Region!$H$12,Cons_Region!$C$12,$A122,$K$1) -> 0 | Q122: =_xll.DBRW($C$3,Q$14,Cons_Region!Q$15,$M$1,Cons_Region!$H$12,Cons_Region!$C$12,$A122,$K$1) -> 0 | R122: =_xll.DBRW($C$3,R$14,Cons_Region!R$15,$M$1,Cons_Region!$H$12,Cons_Region!$C$12,$A122,$K$1) -> 0 | S122: =_xll.DBRW($C$3,S$14,Cons_Region!S$15,$M$1,Cons_Region!$H$12,Cons_Region!$C$12,$A122,$K$1) -> 0
B125: Working Capital - Liabilities Account Balance
O126: =$F$12+1 -> 2027 | P126: =$F$12+2 -> 2028 | Q126: =$F$12+3 -> 2029 | R126: =$F$12+4 -> 2030 | S126: =$F$12+5 -> 2031
C127: =$F$12&"."&C$15 -> 2026.01 | D127: =$F$12&"."&D$15 -> 2026.02 | E127: =$F$12&"."&E$15 -> 2026.03 | F127: =$F$12&"."&F$15 -> 2026.04 | G127: =$F$12&"."&G$15 -> 2026.05 | H127: =$F$12&"."&H$15 -> 2026.06 | I127: =$F$12&"."&I$15 -> 2026.07 | J127: =$F$12&"."&J$15 -> 2026.08 | ... N127: =$F$12&"."&N$15 -> 2026.12 | O127: PE | P127: PE | Q127: PE | R127: PE | S127: PE
A128: WKC.099.009 | B128: PROJECTED BALANCE - LIABILITIES | C128: =_xll.DBRW($C$3,Cons_Region!$F$12,Cons_Region!C$15,$M$1,Cons_Region!$H$12,Cons_Region!$C$12,$A128,$K$1) -> 0 | D128: =_xll.DBRW($C$3,Cons_Region!$F$12,Cons_Region!D$15,$M$1,Cons_Region!$H$12,Cons_Region!$C$12,$A128,$K$1) -> 2610.7415 | E128: =_xll.DBRW($C$3,Cons_Region!$F$12,Cons_Region!E$15,$M$1,Cons_Region!$H$12,Cons_Region!$C$12,$A128,$K$1) -> 2682.9218 | F128: =_xll.DBRW($C$3,Cons_Region!$F$12,Cons_Region!F$15,$M$1,Cons_Region!$H$12,Cons_Region!$C$12,$A128,$K$1) -> 2861.651 | G128: =_xll.DBRW($C$3,Cons_Region!$F$12,Cons_Region!G$15,$M$1,Cons_Region!$H$12,Cons_Region!$C$12,$A128,$K$1) -> 2978.1627 | H128: =_xll.DBRW($C$3,Cons_Region!$F$12,Cons_Region!H$15,$M$1,Cons_Region!$H$12,Cons_Region!$C$12,$A128,$K$1) -> 3144.2873 | I128: =_xll.DBRW($C$3,Cons_Region!$F$12,Cons_Region!I$15,$M$1,Cons_Region!$H$12,Cons_Region!$C$12,$A128,$K$1) -> 3122.6164 | J128: =_xll.DBRW($C$3,Cons_Region!$F$12,Cons_Region!J$15,$M$1,Cons_Region!$H$12,Cons_Region!$C$12,$A128,$K$1) -> 3001.2624 | ... N128: =_xll.DBRW($C$3,Cons_Region!$F$12,Cons_Region!N$15,$M$1,Cons_Region!$H$12,Cons_Region!$C$12,$A128,$K$1) -> 0 | O128: =_xll.DBRW($C$3,O$14,Cons_Region!O$15,$M$1,Cons_Region!$H$12,Cons_Region!$C$12,$A128,$K$1) -> 0 | P128: =_xll.DBRW($C$3,P$14,Cons_Region!P$15,$M$1,Cons_Region!$H$12,Cons_Region!$C$12,$A128,$K$1) -> 0 | Q128: =_xll.DBRW($C$3,Q$14,Cons_Region!Q$15,$M$1,Cons_Region!$H$12,Cons_Region!$C$12,$A128,$K$1) -> 0 | R128: =_xll.DBRW($C$3,R$14,Cons_Region!R$15,$M$1,Cons_Region!$H$12,Cons_Region!$C$12,$A128,$K$1) -> 0 | S128: =_xll.DBRW($C$3,S$14,Cons_Region!S$15,$M$1,Cons_Region!$H$12,Cons_Region!$C$12,$A128,$K$1) -> 0
A129: WKC.020.002 | B129: Suppliers | C129: =_xll.DBRW($C$3,Cons_Region!$F$12,Cons_Region!C$15,$M$1,Cons_Region!$H$12,Cons_Region!$C$12,$A129,$K$1) -> 0 | D129: =_xll.DBRW($C$3,Cons_Region!$F$12,Cons_Region!D$15,$M$1,Cons_Region!$H$12,Cons_Region!$C$12,$A129,$K$1) -> 2208.405 | E129: =_xll.DBRW($C$3,Cons_Region!$F$12,Cons_Region!E$15,$M$1,Cons_Region!$H$12,Cons_Region!$C$12,$A129,$K$1) -> 2291.6798 | F129: =_xll.DBRW($C$3,Cons_Region!$F$12,Cons_Region!F$15,$M$1,Cons_Region!$H$12,Cons_Region!$C$12,$A129,$K$1) -> 2451.6003 | G129: =_xll.DBRW($C$3,Cons_Region!$F$12,Cons_Region!G$15,$M$1,Cons_Region!$H$12,Cons_Region!$C$12,$A129,$K$1) -> 2522.807 | H129: =_xll.DBRW($C$3,Cons_Region!$F$12,Cons_Region!H$15,$M$1,Cons_Region!$H$12,Cons_Region!$C$12,$A129,$K$1) -> 2631.9804 | I129: =_xll.DBRW($C$3,Cons_Region!$F$12,Cons_Region!I$15,$M$1,Cons_Region!$H$12,Cons_Region!$C$12,$A129,$K$1) -> 2595.9572 | J129: =_xll.DBRW($C$3,Cons_Region!$F$12,Cons_Region!J$15,$M$1,Cons_Region!$H$12,Cons_Region!$C$12,$A129,$K$1) -> 2468.9215 | ... N129: =_xll.DBRW($C$3,Cons_Region!$F$12,Cons_Region!N$15,$M$1,Cons_Region!$H$12,Cons_Region!$C$12,$A129,$K$1) -> 0 | O129: =_xll.DBRW($C$3,O$14,Cons_Region!O$15,$M$1,Cons_Region!$H$12,Cons_Region!$C$12,$A129,$K$1) -> 0 | P129: =_xll.DBRW($C$3,P$14,Cons_Region!P$15,$M$1,Cons_Region!$H$12,Cons_Region!$C$12,$A129,$K$1) -> 0 | Q129: =_xll.DBRW($C$3,Q$14,Cons_Region!Q$15,$M$1,Cons_Region!$H$12,Cons_Region!$C$12,$A129,$K$1) -> 0 | R129: =_xll.DBRW($C$3,R$14,Cons_Region!R$15,$M$1,Cons_Region!$H$12,Cons_Region!$C$12,$A129,$K$1) -> 0 | S129: =_xll.DBRW($C$3,S$14,Cons_Region!S$15,$M$1,Cons_Region!$H$12,Cons_Region!$C$12,$A129,$K$1) -> 0
...

Sheet Opening
C1: =_xll.VIEW("CONS_VC_PRD:STG.100.DataBase_Uploads",G13) -> CONS_VC_PRD:STG.100.DataBase_Uploads:12384823671237949904 | E1: =_xll.VIEW("CONS_VC_PRD:ALL.015.Region_Assumptions") -> CONS_VC_PRD:ALL.015.Region_Assumptions:1238482367336302825 | F1: =_xll.VIEW("CONS_VC_PRD:DFS.120.Financial_Results") -> CONS_VC_PRD:DFS.120.Financial_Results:1238482367756964870 | M1: Value | N1: N/A | O1: =_xll.SUBNM("CONS_VC_PRD:ALL.D.Version","","T3") -> T3 | P1: PROD099
C2: =_xll.VIEW("CONS_VC_PRD:REV.100.Revenue_Consolidated") -> CONS_VC_PRD:REV.100.Revenue_Consolidated:12384823671892466621 | E2: =_xll.VIEW("CONS_VC_PRD:ALL.010.Economic_Assumptions") -> CONS_VC_PRD:ALL.010.Economic_Assumptions:12384823671117458081 | F2: =_xll.VIEW("CONS_VC_PRD:DFS.140.Indirect_Cash_Flow") -> CONS_VC_PRD:DFS.140.Indirect_Cash_Flow:12384823672022746056 | M2: Total Market | P2: Total Products
C3: =_xll.VIEW("CONS_VC_PRD:DFS.100.Profit_and_Loss") -> CONS_VC_PRD:DFS.100.Profit_and_Loss:1238482367-656224029 | E3: =_xll.VIEW("CONS_VC_PRD:DFS.160.Working_Capital") -> CONS_VC_PRD:DFS.160.Working_Capital:12384823671881473188 | F3: =_xll.VIEW("CONS_VC_PRD:ALL.004.Uploads_Status_Planning") -> CONS_VC_PRD:ALL.004.Uploads_Status_Planning:1238482367629058957 | I3: Flag
C4: =_xll.VIEW("CONS_VC_PRD:ALL.001.Actual_Control") -> CONS_VC_PRD:ALL.001.Actual_Control:1238482367343083193 | E4: =_xll.VIEW("CONS_VC_PRD:DFS.180.Gross_Debt") -> CONS_VC_PRD:DFS.180.Gross_Debt:12384823671210914551
E5: =_xll.DBRW(Opening!$C$4,Opening!$G$13,Opening!E11,$O$1,$I$3) -> ACTUAL | F5: =_xll.DBRW(Opening!$C$4,Opening!$G$13,Opening!F11,$O$1,$I$3) | G5: =_xll.DBRW(Opening!$C$4,Opening!$G$13,Opening!G11,$O$1,$I$3) | H5: =_xll.DBRW(Opening!$C$4,Opening!$G$13,Opening!H11,$O$1,$I$3) | I5: =_xll.DBRW(Opening!$C$4,Opening!$G$13,Opening!I11,$O$1,$I$3) | J5: =_xll.DBRW(Opening!$C$4,Opening!$G$13,Opening!J11,$O$1,$I$3) | K5: =_xll.DBRW(Opening!$C$4,Opening!$G$13,Opening!K11,$O$1,$I$3) | L5: =_xll.DBRW(Opening!$C$4,Opening!$G$13,Opening!L11,$O$1,$I$3) | ... P5: =_xll.DBRW(Opening!$C$4,Opening!$G$13,Opening!P11,$O$1,$I$3)
C7: Dre - Other OP. Results
E11: 01 | F11: 02 | G11: 03 | H11: 04 | I11: 05 | J11: 06 | K11: 07 | L11: 08 | M11: 09 | N11: 10 | O11: 11 | P11: 12
D13: =_xll.SUBNM("CONS_VC_PRD:ALL.D.Region","Nível 0","ESPA","MEMBER_NAME") -> ESPA | G13: =_xll.SUBNM("CONS_VC_PRD:ALL.D.Year","SYS_Picklist","2026","MEMBER_NAME") -> 2026 | I13: =_xll.SUBNM("CONS_VC_PRD:ALL.D.Currency","PAX","EUR","Nome alternativo") -> EUR | K13: Input Status: | L13: =_xll.DBRW($F$3,$O$1,$D$13,"Financial_Planning","Status") -> Open
Q15: =$G$13+1 -> 2027 | R15: =$G$13+2 -> 2028 | S15: =$G$13+3 -> 2029 | T15: =$G$13+4 -> 2030 | U15: =$G$13+5 -> 2031
E16: =$G$13&"."&E$11 -> 2026.01 | F16: =$G$13&"."&F$11 -> 2026.02 | G16: =$G$13&"."&G$11 -> 2026.03 | H16: =$G$13&"."&H$11 -> 2026.04 | I16: =$G$13&"."&I$11 -> 2026.05 | J16: =$G$13&"."&J$11 -> 2026.06 | K16: =$G$13&"."&K$11 -> 2026.07 | L16: =$G$13&"."&L$11 -> 2026.08 | ... P16: =$G$13&"."&P$11 -> 2026.12 | Q16: PE | R16: PE | S16: PE | T16: PE | U16: PE
A17: OOR.010.001 | B17: Total Accounts Line | C17: Other | D17: Total Accounts Line | E17: =_xll.DBRW($C$1,Opening!$G$13,Opening!E$11,$O$1,Opening!$I$13,Opening!$D$13,$P$1,$A17,$D17,$M$1) -> 0 | F17: =_xll.DBRW($C$1,Opening!$G$13,Opening!F$11,$O$1,Opening!$I$13,Opening!$D$13,$P$1,$A17,$D17,$M$1) -> 0 | G17: =_xll.DBRW($C$1,Opening!$G$13,Opening!G$11,$O$1,Opening!$I$13,Opening!$D$13,$P$1,$A17,$D17,$M$1) -> 0 | H17: =_xll.DBRW($C$1,Opening!$G$13,Opening!H$11,$O$1,Opening!$I$13,Opening!$D$13,$P$1,$A17,$D17,$M$1) -> 0 | I17: =_xll.DBRW($C$1,Opening!$G$13,Opening!I$11,$O$1,Opening!$I$13,Opening!$D$13,$P$1,$A17,$D17,$M$1) -> 0 | J17: =_xll.DBRW($C$1,Opening!$G$13,Opening!J$11,$O$1,Opening!$I$13,Opening!$D$13,$P$1,$A17,$D17,$M$1) -> 0 | K17: =_xll.DBRW($C$1,Opening!$G$13,Opening!K$11,$O$1,Opening!$I$13,Opening!$D$13,$P$1,$A17,$D17,$M$1) -> 0 | L17: =_xll.DBRW($C$1,Opening!$G$13,Opening!L$11,$O$1,Opening!$I$13,Opening!$D$13,$P$1,$A17,$D17,$M$1) -> 0 | ... P17: =_xll.DBRW($C$1,Opening!$G$13,Opening!P$11,$O$1,Opening!$I$13,Opening!$D$13,$P$1,$A17,$D17,$M$1) -> 0 | Q17: =_xll.DBRW($C$1,Q$15,$Q$16,$O$1,Opening!$I$13,Opening!$D$13,$P$1,$A17,$D17,$M$1) -> 0 | R17: =_xll.DBRW($C$1,R$15,$Q$16,$O$1,Opening!$I$13,Opening!$D$13,$P$1,$A17,$D17,$M$1) -> 0 | S17: =_xll.DBRW($C$1,S$15,$Q$16,$O$1,Opening!$I$13,Opening!$D$13,$P$1,$A17,$D17,$M$1) -> 0 | T17: =_xll.DBRW($C$1,T$15,$Q$16,$O$1,Opening!$I$13,Opening!$D$13,$P$1,$A17,$D17,$M$1) -> 0 | U17: =_xll.DBRW($C$1,U$15,$Q$16,$O$1,Opening!$I$13,Opening!$D$13,$P$1,$A17,$D17,$M$1) -> 0
A18: OOR.010.001 | B18: ACL.OOR.010.001.01 | C18: Other | D18: Other Op. Results - Asset Write-off | E18: =_xll.DBRW($C$1,Opening!$G$13,Opening!E$11,$O$1,Opening!$I$13,Opening!$D$13,$P$1,$A18,$B18,$M$1) -> 0 | F18: =_xll.DBRW($C$1,Opening!$G$13,Opening!F$11,$O$1,Opening!$I$13,Opening!$D$13,$P$1,$A18,$B18,$M$1) -> 0 | G18: =_xll.DBRW($C$1,Opening!$G$13,Opening!G$11,$O$1,Opening!$I$13,Opening!$D$13,$P$1,$A18,$B18,$M$1) -> 0 | H18: =_xll.DBRW($C$1,Opening!$G$13,Opening!H$11,$O$1,Opening!$I$13,Opening!$D$13,$P$1,$A18,$B18,$M$1) -> 0 | I18: =_xll.DBRW($C$1,Opening!$G$13,Opening!I$11,$O$1,Opening!$I$13,Opening!$D$13,$P$1,$A18,$B18,$M$1) -> 0 | J18: =_xll.DBRW($C$1,Opening!$G$13,Opening!J$11,$O$1,Opening!$I$13,Opening!$D$13,$P$1,$A18,$B18,$M$1) -> 0 | K18: =_xll.DBRW($C$1,Opening!$G$13,Opening!K$11,$O$1,Opening!$I$13,Opening!$D$13,$P$1,$A18,$B18,$M$1) -> 0 | L18: =_xll.DBRW($C$1,Opening!$G$13,Opening!L$11,$O$1,Opening!$I$13,Opening!$D$13,$P$1,$A18,$B18,$M$1) -> 0 | ... P18: =_xll.DBRW($C$1,Opening!$G$13,Opening!P$11,$O$1,Opening!$I$13,Opening!$D$13,$P$1,$A18,$B18,$M$1) -> 0 | Q18: =_xll.DBRW($C$1,Q$15,$Q$16,$O$1,Opening!$I$13,Opening!$D$13,$P$1,$A18,$B18,$M$1) -> 0 | R18: =_xll.DBRW($C$1,R$15,$Q$16,$O$1,Opening!$I$13,Opening!$D$13,$P$1,$A18,$B18,$M$1) -> 0 | S18: =_xll.DBRW($C$1,S$15,$Q$16,$O$1,Opening!$I$13,Opening!$D$13,$P$1,$A18,$B18,$M$1) -> 0 | T18: =_xll.DBRW($C$1,T$15,$Q$16,$O$1,Opening!$I$13,Opening!$D$13,$P$1,$A18,$B18,$M$1) -> 0 | U18: =_xll.DBRW($C$1,U$15,$Q$16,$O$1,Opening!$I$13,Opening!$D$13,$P$1,$A18,$B18,$M$1) -> 0
A19: OOR.010.001 | B19: ACL.OOR.010.001.02 | C19: Other | D19: Slow moving | E19: =_xll.DBRW($C$1,Opening!$G$13,Opening!E$11,$O$1,Opening!$I$13,Opening!$D$13,$P$1,$A19,$B19,$M$1) -> 0 | F19: =_xll.DBRW($C$1,Opening!$G$13,Opening!F$11,$O$1,Opening!$I$13,Opening!$D$13,$P$1,$A19,$B19,$M$1) -> 0 | G19: =_xll.DBRW($C$1,Opening!$G$13,Opening!G$11,$O$1,Opening!$I$13,Opening!$D$13,$P$1,$A19,$B19,$M$1) -> 0 | H19: =_xll.DBRW($C$1,Opening!$G$13,Opening!H$11,$O$1,Opening!$I$13,Opening!$D$13,$P$1,$A19,$B19,$M$1) -> 0 | I19: =_xll.DBRW($C$1,Opening!$G$13,Opening!I$11,$O$1,Opening!$I$13,Opening!$D$13,$P$1,$A19,$B19,$M$1) -> 0 | J19: =_xll.DBRW($C$1,Opening!$G$13,Opening!J$11,$O$1,Opening!$I$13,Opening!$D$13,$P$1,$A19,$B19,$M$1) -> 0 | K19: =_xll.DBRW($C$1,Opening!$G$13,Opening!K$11,$O$1,Opening!$I$13,Opening!$D$13,$P$1,$A19,$B19,$M$1) -> 0 | L19: =_xll.DBRW($C$1,Opening!$G$13,Opening!L$11,$O$1,Opening!$I$13,Opening!$D$13,$P$1,$A19,$B19,$M$1) -> 0 | ... P19: =_xll.DBRW($C$1,Opening!$G$13,Opening!P$11,$O$1,Opening!$I$13,Opening!$D$13,$P$1,$A19,$B19,$M$1) -> 0 | Q19: =_xll.DBRW($C$1,Q$15,$Q$16,$O$1,Opening!$I$13,Opening!$D$13,$P$1,$A19,$B19,$M$1) -> 0 | R19: =_xll.DBRW($C$1,R$15,$Q$16,$O$1,Opening!$I$13,Opening!$D$13,$P$1,$A19,$B19,$M$1) -> 0 | S19: =_xll.DBRW($C$1,S$15,$Q$16,$O$1,Opening!$I$13,Opening!$D$13,$P$1,$A19,$B19,$M$1) -> 0 | T19: =_xll.DBRW($C$1,T$15,$Q$16,$O$1,Opening!$I$13,Opening!$D$13,$P$1,$A19,$B19,$M$1) -> 0 | U19: =_xll.DBRW($C$1,U$15,$Q$16,$O$1,Opening!$I$13,Opening!$D$13,$P$1,$A19,$B19,$M$1) -> 0
A20: OOR.010.001 | B20: ACL.OOR.010.001.03 | C20: Other | D20: Clinker | E20: =_xll.DBRW($C$1,Opening!$G$13,Opening!E$11,$O$1,Opening!$I$13,Opening!$D$13,$P$1,$A20,$B20,$M$1) -> 0 | F20: =_xll.DBRW($C$1,Opening!$G$13,Opening!F$11,$O$1,Opening!$I$13,Opening!$D$13,$P$1,$A20,$B20,$M$1) -> 0 | G20: =_xll.DBRW($C$1,Opening!$G$13,Opening!G$11,$O$1,Opening!$I$13,Opening!$D$13,$P$1,$A20,$B20,$M$1) -> 0 | H20: =_xll.DBRW($C$1,Opening!$G$13,Opening!H$11,$O$1,Opening!$I$13,Opening!$D$13,$P$1,$A20,$B20,$M$1) -> 0 | I20: =_xll.DBRW($C$1,Opening!$G$13,Opening!I$11,$O$1,Opening!$I$13,Opening!$D$13,$P$1,$A20,$B20,$M$1) -> 0 | J20: =_xll.DBRW($C$1,Opening!$G$13,Opening!J$11,$O$1,Opening!$I$13,Opening!$D$13,$P$1,$A20,$B20,$M$1) -> 0 | K20: =_xll.DBRW($C$1,Opening!$G$13,Opening!K$11,$O$1,Opening!$I$13,Opening!$D$13,$P$1,$A20,$B20,$M$1) -> 0 | L20: =_xll.DBRW($C$1,Opening!$G$13,Opening!L$11,$O$1,Opening!$I$13,Opening!$D$13,$P$1,$A20,$B20,$M$1) -> 0 | ... P20: =_xll.DBRW($C$1,Opening!$G$13,Opening!P$11,$O$1,Opening!$I$13,Opening!$D$13,$P$1,$A20,$B20,$M$1) -> 0 | Q20: =_xll.DBRW($C$1,Q$15,$Q$16,$O$1,Opening!$I$13,Opening!$D$13,$P$1,$A20,$B20,$M$1) -> 0 | R20: =_xll.DBRW($C$1,R$15,$Q$16,$O$1,Opening!$I$13,Opening!$D$13,$P$1,$A20,$B20,$M$1) -> 0 | S20: =_xll.DBRW($C$1,S$15,$Q$16,$O$1,Opening!$I$13,Opening!$D$13,$P$1,$A20,$B20,$M$1) -> 0 | T20: =_xll.DBRW($C$1,T$15,$Q$16,$O$1,Opening!$I$13,Opening!$D$13,$P$1,$A20,$B20,$M$1) -> 0 | U20: =_xll.DBRW($C$1,U$15,$Q$16,$O$1,Opening!$I$13,Opening!$D$13,$P$1,$A20,$B20,$M$1) -> 0
A21: OOR.010.001 | B21: ACL.OOR.010.001.04 | C21: Other | D21: Contingencies | E21: =_xll.DBRW($C$1,Opening!$G$13,Opening!E$11,$O$1,Opening!$I$13,Opening!$D$13,$P$1,$A21,$B21,$M$1) -> 0 | F21: =_xll.DBRW($C$1,Opening!$G$13,Opening!F$11,$O$1,Opening!$I$13,Opening!$D$13,$P$1,$A21,$B21,$M$1) -> 0 | G21: =_xll.DBRW($C$1,Opening!$G$13,Opening!G$11,$O$1,Opening!$I$13,Opening!$D$13,$P$1,$A21,$B21,$M$1) -> 0 | H21: =_xll.DBRW($C$1,Opening!$G$13,Opening!H$11,$O$1,Opening!$I$13,Opening!$D$13,$P$1,$A21,$B21,$M$1) -> 0 | I21: =_xll.DBRW($C$1,Opening!$G$13,Opening!I$11,$O$1,Opening!$I$13,Opening!$D$13,$P$1,$A21,$B21,$M$1) -> 0 | J21: =_xll.DBRW($C$1,Opening!$G$13,Opening!J$11,$O$1,Opening!$I$13,Opening!$D$13,$P$1,$A21,$B21,$M$1) -> 0 | K21: =_xll.DBRW($C$1,Opening!$G$13,Opening!K$11,$O$1,Opening!$I$13,Opening!$D$13,$P$1,$A21,$B21,$M$1) -> 0 | L21: =_xll.DBRW($C$1,Opening!$G$13,Opening!L$11,$O$1,Opening!$I$13,Opening!$D$13,$P$1,$A21,$B21,$M$1) -> 0 | ... P21: =_xll.DBRW($C$1,Opening!$G$13,Opening!P$11,$O$1,Opening!$I$13,Opening!$D$13,$P$1,$A21,$B21,$M$1) -> 0 | Q21: =_xll.DBRW($C$1,Q$15,$Q$16,$O$1,Opening!$I$13,Opening!$D$13,$P$1,$A21,$B21,$M$1) -> 0 | R21: =_xll.DBRW($C$1,R$15,$Q$16,$O$1,Opening!$I$13,Opening!$D$13,$P$1,$A21,$B21,$M$1) -> 0 | S21: =_xll.DBRW($C$1,S$15,$Q$16,$O$1,Opening!$I$13,Opening!$D$13,$P$1,$A21,$B21,$M$1) -> 0 | T21: =_xll.DBRW($C$1,T$15,$Q$16,$O$1,Opening!$I$13,Opening!$D$13,$P$1,$A21,$B21,$M$1) -> 0 | U21: =_xll.DBRW($C$1,U$15,$Q$16,$O$1,Opening!$I$13,Opening!$D$13,$P$1,$A21,$B21,$M$1) -> 0
A22: OOR.010.001 | B22: ACL.OOR.010.001.05 | C22: Other | D22: Non-recurring Expenses | E22: =_xll.DBRW($C$1,Opening!$G$13,Opening!E$11,$O$1,Opening!$I$13,Opening!$D$13,$P$1,$A22,$B22,$M$1) -> 0 | F22: =_xll.DBRW($C$1,Opening!$G$13,Opening!F$11,$O$1,Opening!$I$13,Opening!$D$13,$P$1,$A22,$B22,$M$1) -> 0 | G22: =_xll.DBRW($C$1,Opening!$G$13,Opening!G$11,$O$1,Opening!$I$13,Opening!$D$13,$P$1,$A22,$B22,$M$1) -> 0 | H22: =_xll.DBRW($C$1,Opening!$G$13,Opening!H$11,$O$1,Opening!$I$13,Opening!$D$13,$P$1,$A22,$B22,$M$1) -> 0 | I22: =_xll.DBRW($C$1,Opening!$G$13,Opening!I$11,$O$1,Opening!$I$13,Opening!$D$13,$P$1,$A22,$B22,$M$1) -> 0 | J22: =_xll.DBRW($C$1,Opening!$G$13,Opening!J$11,$O$1,Opening!$I$13,Opening!$D$13,$P$1,$A22,$B22,$M$1) -> 0 | K22: =_xll.DBRW($C$1,Opening!$G$13,Opening!K$11,$O$1,Opening!$I$13,Opening!$D$13,$P$1,$A22,$B22,$M$1) -> 0 | L22: =_xll.DBRW($C$1,Opening!$G$13,Opening!L$11,$O$1,Opening!$I$13,Opening!$D$13,$P$1,$A22,$B22,$M$1) -> 0 | ... P22: =_xll.DBRW($C$1,Opening!$G$13,Opening!P$11,$O$1,Opening!$I$13,Opening!$D$13,$P$1,$A22,$B22,$M$1) -> 0 | Q22: =_xll.DBRW($C$1,Q$15,$Q$16,$O$1,Opening!$I$13,Opening!$D$13,$P$1,$A22,$B22,$M$1) -> 0 | R22: =_xll.DBRW($C$1,R$15,$Q$16,$O$1,Opening!$I$13,Opening!$D$13,$P$1,$A22,$B22,$M$1) -> 0 | S22: =_xll.DBRW($C$1,S$15,$Q$16,$O$1,Opening!$I$13,Opening!$D$13,$P$1,$A22,$B22,$M$1) -> 0 | T22: =_xll.DBRW($C$1,T$15,$Q$16,$O$1,Opening!$I$13,Opening!$D$13,$P$1,$A22,$B22,$M$1) -> 0 | U22: =_xll.DBRW($C$1,U$15,$Q$16,$O$1,Opening!$I$13,Opening!$D$13,$P$1,$A22,$B22,$M$1) -> 0
A23: OOR.010.001 | B23: ACL.OOR.010.001.06 | C23: Other | D23: Gain on assets | E23: =_xll.DBRW($C$1,Opening!$G$13,Opening!E$11,$O$1,Opening!$I$13,Opening!$D$13,$P$1,$A23,$B23,$M$1) -> 0 | F23: =_xll.DBRW($C$1,Opening!$G$13,Opening!F$11,$O$1,Opening!$I$13,Opening!$D$13,$P$1,$A23,$B23,$M$1) -> 0 | G23: =_xll.DBRW($C$1,Opening!$G$13,Opening!G$11,$O$1,Opening!$I$13,Opening!$D$13,$P$1,$A23,$B23,$M$1) -> 0 | H23: =_xll.DBRW($C$1,Opening!$G$13,Opening!H$11,$O$1,Opening!$I$13,Opening!$D$13,$P$1,$A23,$B23,$M$1) -> 0 | I23: =_xll.DBRW($C$1,Opening!$G$13,Opening!I$11,$O$1,Opening!$I$13,Opening!$D$13,$P$1,$A23,$B23,$M$1) -> 0 | J23: =_xll.DBRW($C$1,Opening!$G$13,Opening!J$11,$O$1,Opening!$I$13,Opening!$D$13,$P$1,$A23,$B23,$M$1) -> 0 | K23: =_xll.DBRW($C$1,Opening!$G$13,Opening!K$11,$O$1,Opening!$I$13,Opening!$D$13,$P$1,$A23,$B23,$M$1) -> 0 | L23: =_xll.DBRW($C$1,Opening!$G$13,Opening!L$11,$O$1,Opening!$I$13,Opening!$D$13,$P$1,$A23,$B23,$M$1) -> 0 | ... P23: =_xll.DBRW($C$1,Opening!$G$13,Opening!P$11,$O$1,Opening!$I$13,Opening!$D$13,$P$1,$A23,$B23,$M$1) -> 0 | Q23: =_xll.DBRW($C$1,Q$15,$Q$16,$O$1,Opening!$I$13,Opening!$D$13,$P$1,$A23,$B23,$M$1) -> 0 | R23: =_xll.DBRW($C$1,R$15,$Q$16,$O$1,Opening!$I$13,Opening!$D$13,$P$1,$A23,$B23,$M$1) -> 0 | S23: =_xll.DBRW($C$1,S$15,$Q$16,$O$1,Opening!$I$13,Opening!$D$13,$P$1,$A23,$B23,$M$1) -> 0 | T23: =_xll.DBRW($C$1,T$15,$Q$16,$O$1,Opening!$I$13,Opening!$D$13,$P$1,$A23,$B23,$M$1) -> 0 | U23: =_xll.DBRW($C$1,U$15,$Q$16,$O$1,Opening!$I$13,Opening!$D$13,$P$1,$A23,$B23,$M$1) -> 0
A24: OOR.010.001 | B24: ACL.OOR.010.001.07 | C24: Other | D24: Tax benefits | E24: =_xll.DBRW($C$1,Opening!$G$13,Opening!E$11,$O$1,Opening!$I$13,Opening!$D$13,$P$1,$A24,$B24,$M$1) -> 0 | F24: =_xll.DBRW($C$1,Opening!$G$13,Opening!F$11,$O$1,Opening!$I$13,Opening!$D$13,$P$1,$A24,$B24,$M$1) -> 0 | G24: =_xll.DBRW($C$1,Opening!$G$13,Opening!G$11,$O$1,Opening!$I$13,Opening!$D$13,$P$1,$A24,$B24,$M$1) -> 0 | H24: =_xll.DBRW($C$1,Opening!$G$13,Opening!H$11,$O$1,Opening!$I$13,Opening!$D$13,$P$1,$A24,$B24,$M$1) -> 0 | I24: =_xll.DBRW($C$1,Opening!$G$13,Opening!I$11,$O$1,Opening!$I$13,Opening!$D$13,$P$1,$A24,$B24,$M$1) -> 0 | J24: =_xll.DBRW($C$1,Opening!$G$13,Opening!J$11,$O$1,Opening!$I$13,Opening!$D$13,$P$1,$A24,$B24,$M$1) -> 0 | K24: =_xll.DBRW($C$1,Opening!$G$13,Opening!K$11,$O$1,Opening!$I$13,Opening!$D$13,$P$1,$A24,$B24,$M$1) -> 0 | L24: =_xll.DBRW($C$1,Opening!$G$13,Opening!L$11,$O$1,Opening!$I$13,Opening!$D$13,$P$1,$A24,$B24,$M$1) -> 0 | ... P24: =_xll.DBRW($C$1,Opening!$G$13,Opening!P$11,$O$1,Opening!$I$13,Opening!$D$13,$P$1,$A24,$B24,$M$1) -> 0 | Q24: =_xll.DBRW($C$1,Q$15,$Q$16,$O$1,Opening!$I$13,Opening!$D$13,$P$1,$A24,$B24,$M$1) -> 0 | R24: =_xll.DBRW($C$1,R$15,$Q$16,$O$1,Opening!$I$13,Opening!$D$13,$P$1,$A24,$B24,$M$1) -> 0 | S24: =_xll.DBRW($C$1,S$15,$Q$16,$O$1,Opening!$I$13,Opening!$D$13,$P$1,$A24,$B24,$M$1) -> 0 | T24: =_xll.DBRW($C$1,T$15,$Q$16,$O$1,Opening!$I$13,Opening!$D$13,$P$1,$A24,$B24,$M$1) -> 0 | U24: =_xll.DBRW($C$1,U$15,$Q$16,$O$1,Opening!$I$13,Opening!$D$13,$P$1,$A24,$B24,$M$1) -> 0
A25: OOR.010.001 | B25: ACL.OOR.010.001.08 | C25: Other | D25: Other Op. Results - Machadinho | E25: =_xll.DBRW($C$1,Opening!$G$13,Opening!E$11,$O$1,Opening!$I$13,Opening!$D$13,$P$1,$A25,$B25,$M$1) -> 0 | F25: =_xll.DBRW($C$1,Opening!$G$13,Opening!F$11,$O$1,Opening!$I$13,Opening!$D$13,$P$1,$A25,$B25,$M$1) -> 0 | G25: =_xll.DBRW($C$1,Opening!$G$13,Opening!G$11,$O$1,Opening!$I$13,Opening!$D$13,$P$1,$A25,$B25,$M$1) -> 0 | H25: =_xll.DBRW($C$1,Opening!$G$13,Opening!H$11,$O$1,Opening!$I$13,Opening!$D$13,$P$1,$A25,$B25,$M$1) -> 0 | I25: =_xll.DBRW($C$1,Opening!$G$13,Opening!I$11,$O$1,Opening!$I$13,Opening!$D$13,$P$1,$A25,$B25,$M$1) -> 0 | J25: =_xll.DBRW($C$1,Opening!$G$13,Opening!J$11,$O$1,Opening!$I$13,Opening!$D$13,$P$1,$A25,$B25,$M$1) -> 0 | K25: =_xll.DBRW($C$1,Opening!$G$13,Opening!K$11,$O$1,Opening!$I$13,Opening!$D$13,$P$1,$A25,$B25,$M$1) -> 0 | L25: =_xll.DBRW($C$1,Opening!$G$13,Opening!L$11,$O$1,Opening!$I$13,Opening!$D$13,$P$1,$A25,$B25,$M$1) -> 0 | ... P25: =_xll.DBRW($C$1,Opening!$G$13,Opening!P$11,$O$1,Opening!$I$13,Opening!$D$13,$P$1,$A25,$B25,$M$1) -> 0 | Q25: =_xll.DBRW($C$1,Q$15,$Q$16,$O$1,Opening!$I$13,Opening!$D$13,$P$1,$A25,$B25,$M$1) -> 0 | R25: =_xll.DBRW($C$1,R$15,$Q$16,$O$1,Opening!$I$13,Opening!$D$13,$P$1,$A25,$B25,$M$1) -> 0 | S25: =_xll.DBRW($C$1,S$15,$Q$16,$O$1,Opening!$I$13,Opening!$D$13,$P$1,$A25,$B25,$M$1) -> 0 | T25: =_xll.DBRW($C$1,T$15,$Q$16,$O$1,Opening!$I$13,Opening!$D$13,$P$1,$A25,$B25,$M$1) -> 0 | U25: =_xll.DBRW($C$1,U$15,$Q$16,$O$1,Opening!$I$13,Opening!$D$13,$P$1,$A25,$B25,$M$1) -> 0
A26: OOR.010.001 | B26: ACL.OOR.010.001.09 | C26: Other | D26: MOTZ | E26: =_xll.DBRW($C$1,Opening!$G$13,Opening!E$11,$O$1,Opening!$I$13,Opening!$D$13,$P$1,$A26,$B26,$M$1) -> 0 | F26: =_xll.DBRW($C$1,Opening!$G$13,Opening!F$11,$O$1,Opening!$I$13,Opening!$D$13,$P$1,$A26,$B26,$M$1) -> 0 | G26: =_xll.DBRW($C$1,Opening!$G$13,Opening!G$11,$O$1,Opening!$I$13,Opening!$D$13,$P$1,$A26,$B26,$M$1) -> 0 | H26: =_xll.DBRW($C$1,Opening!$G$13,Opening!H$11,$O$1,Opening!$I$13,Opening!$D$13,$P$1,$A26,$B26,$M$1) -> 0 | I26: =_xll.DBRW($C$1,Opening!$G$13,Opening!I$11,$O$1,Opening!$I$13,Opening!$D$13,$P$1,$A26,$B26,$M$1) -> 0 | J26: =_xll.DBRW($C$1,Opening!$G$13,Opening!J$11,$O$1,Opening!$I$13,Opening!$D$13,$P$1,$A26,$B26,$M$1) -> 0 | K26: =_xll.DBRW($C$1,Opening!$G$13,Opening!K$11,$O$1,Opening!$I$13,Opening!$D$13,$P$1,$A26,$B26,$M$1) -> 0 | L26: =_xll.DBRW($C$1,Opening!$G$13,Opening!L$11,$O$1,Opening!$I$13,Opening!$D$13,$P$1,$A26,$B26,$M$1) -> 0 | ... P26: =_xll.DBRW($C$1,Opening!$G$13,Opening!P$11,$O$1,Opening!$I$13,Opening!$D$13,$P$1,$A26,$B26,$M$1) -> 0 | Q26: =_xll.DBRW($C$1,Q$15,$Q$16,$O$1,Opening!$I$13,Opening!$D$13,$P$1,$A26,$B26,$M$1) -> 0 | R26: =_xll.DBRW($C$1,R$15,$Q$16,$O$1,Opening!$I$13,Opening!$D$13,$P$1,$A26,$B26,$M$1) -> 0 | S26: =_xll.DBRW($C$1,S$15,$Q$16,$O$1,Opening!$I$13,Opening!$D$13,$P$1,$A26,$B26,$M$1) -> 0 | T26: =_xll.DBRW($C$1,T$15,$Q$16,$O$1,Opening!$I$13,Opening!$D$13,$P$1,$A26,$B26,$M$1) -> 0 | U26: =_xll.DBRW($C$1,U$15,$Q$16,$O$1,Opening!$I$13,Opening!$D$13,$P$1,$A26,$B26,$M$1) -> 0
A27: OOR.010.001 | B27: ACL.OOR.010.001.10 | C27: Other | D27: Non Op. Taxes | E27: =_xll.DBRW($C$1,Opening!$G$13,Opening!E$11,$O$1,Opening!$I$13,Opening!$D$13,$P$1,$A27,$B27,$M$1) -> 0 | F27: =_xll.DBRW($C$1,Opening!$G$13,Opening!F$11,$O$1,Opening!$I$13,Opening!$D$13,$P$1,$A27,$B27,$M$1) -> 0 | G27: =_xll.DBRW($C$1,Opening!$G$13,Opening!G$11,$O$1,Opening!$I$13,Opening!$D$13,$P$1,$A27,$B27,$M$1) -> 0 | H27: =_xll.DBRW($C$1,Opening!$G$13,Opening!H$11,$O$1,Opening!$I$13,Opening!$D$13,$P$1,$A27,$B27,$M$1) -> 0 | I27: =_xll.DBRW($C$1,Opening!$G$13,Opening!I$11,$O$1,Opening!$I$13,Opening!$D$13,$P$1,$A27,$B27,$M$1) -> 0 | J27: =_xll.DBRW($C$1,Opening!$G$13,Opening!J$11,$O$1,Opening!$I$13,Opening!$D$13,$P$1,$A27,$B27,$M$1) -> 0 | K27: =_xll.DBRW($C$1,Opening!$G$13,Opening!K$11,$O$1,Opening!$I$13,Opening!$D$13,$P$1,$A27,$B27,$M$1) -> 0 | L27: =_xll.DBRW($C$1,Opening!$G$13,Opening!L$11,$O$1,Opening!$I$13,Opening!$D$13,$P$1,$A27,$B27,$M$1) -> 0 | ... P27: =_xll.DBRW($C$1,Opening!$G$13,Opening!P$11,$O$1,Opening!$I$13,Opening!$D$13,$P$1,$A27,$B27,$M$1) -> 0 | Q27: =_xll.DBRW($C$1,Q$15,$Q$16,$O$1,Opening!$I$13,Opening!$D$13,$P$1,$A27,$B27,$M$1) -> 0 | R27: =_xll.DBRW($C$1,R$15,$Q$16,$O$1,Opening!$I$13,Opening!$D$13,$P$1,$A27,$B27,$M$1) -> 0 | S27: =_xll.DBRW($C$1,S$15,$Q$16,$O$1,Opening!$I$13,Opening!$D$13,$P$1,$A27,$B27,$M$1) -> 0 | T27: =_xll.DBRW($C$1,T$15,$Q$16,$O$1,Opening!$I$13,Opening!$D$13,$P$1,$A27,$B27,$M$1) -> 0 | U27: =_xll.DBRW($C$1,U$15,$Q$16,$O$1,Opening!$I$13,Opening!$D$13,$P$1,$A27,$B27,$M$1) -> 0
A28: OOR.010.001 | B28: ACL.OOR.010.001.11 | C28: Other | D28: Other products | E28: =_xll.DBRW($C$1,Opening!$G$13,Opening!E$11,$O$1,Opening!$I$13,Opening!$D$13,$P$1,$A28,$B28,$M$1) -> 0 | F28: =_xll.DBRW($C$1,Opening!$G$13,Opening!F$11,$O$1,Opening!$I$13,Opening!$D$13,$P$1,$A28,$B28,$M$1) -> 0 | G28: =_xll.DBRW($C$1,Opening!$G$13,Opening!G$11,$O$1,Opening!$I$13,Opening!$D$13,$P$1,$A28,$B28,$M$1) -> 0 | H28: =_xll.DBRW($C$1,Opening!$G$13,Opening!H$11,$O$1,Opening!$I$13,Opening!$D$13,$P$1,$A28,$B28,$M$1) -> 0 | I28: =_xll.DBRW($C$1,Opening!$G$13,Opening!I$11,$O$1,Opening!$I$13,Opening!$D$13,$P$1,$A28,$B28,$M$1) -> 0 | J28: =_xll.DBRW($C$1,Opening!$G$13,Opening!J$11,$O$1,Opening!$I$13,Opening!$D$13,$P$1,$A28,$B28,$M$1) -> 0 | K28: =_xll.DBRW($C$1,Opening!$G$13,Opening!K$11,$O$1,Opening!$I$13,Opening!$D$13,$P$1,$A28,$B28,$M$1) -> 0 | L28: =_xll.DBRW($C$1,Opening!$G$13,Opening!L$11,$O$1,Opening!$I$13,Opening!$D$13,$P$1,$A28,$B28,$M$1) -> 0 | ... P28: =_xll.DBRW($C$1,Opening!$G$13,Opening!P$11,$O$1,Opening!$I$13,Opening!$D$13,$P$1,$A28,$B28,$M$1) -> 0 | Q28: =_xll.DBRW($C$1,Q$15,$Q$16,$O$1,Opening!$I$13,Opening!$D$13,$P$1,$A28,$B28,$M$1) -> 0 | R28: =_xll.DBRW($C$1,R$15,$Q$16,$O$1,Opening!$I$13,Opening!$D$13,$P$1,$A28,$B28,$M$1) -> 0 | S28: =_xll.DBRW($C$1,S$15,$Q$16,$O$1,Opening!$I$13,Opening!$D$13,$P$1,$A28,$B28,$M$1) -> 0 | T28: =_xll.DBRW($C$1,T$15,$Q$16,$O$1,Opening!$I$13,Opening!$D$13,$P$1,$A28,$B28,$M$1) -> 0 | U28: =_xll.DBRW($C$1,U$15,$Q$16,$O$1,Opening!$I$13,Opening!$D$13,$P$1,$A28,$B28,$M$1) -> 0
A29: OOR.010.001 | B29: ACL.OOR.010.001.12 | C29: Other | D29: Non-recurring Revenues | E29: =_xll.DBRW($C$1,Opening!$G$13,Opening!E$11,$O$1,Opening!$I$13,Opening!$D$13,$P$1,$A29,$B29,$M$1) -> 0 | F29: =_xll.DBRW($C$1,Opening!$G$13,Opening!F$11,$O$1,Opening!$I$13,Opening!$D$13,$P$1,$A29,$B29,$M$1) -> 0 | G29: =_xll.DBRW($C$1,Opening!$G$13,Opening!G$11,$O$1,Opening!$I$13,Opening!$D$13,$P$1,$A29,$B29,$M$1) -> 0 | H29: =_xll.DBRW($C$1,Opening!$G$13,Opening!H$11,$O$1,Opening!$I$13,Opening!$D$13,$P$1,$A29,$B29,$M$1) -> 0 | I29: =_xll.DBRW($C$1,Opening!$G$13,Opening!I$11,$O$1,Opening!$I$13,Opening!$D$13,$P$1,$A29,$B29,$M$1) -> 0 | J29: =_xll.DBRW($C$1,Opening!$G$13,Opening!J$11,$O$1,Opening!$I$13,Opening!$D$13,$P$1,$A29,$B29,$M$1) -> 0 | K29: =_xll.DBRW($C$1,Opening!$G$13,Opening!K$11,$O$1,Opening!$I$13,Opening!$D$13,$P$1,$A29,$B29,$M$1) -> 0 | L29: =_xll.DBRW($C$1,Opening!$G$13,Opening!L$11,$O$1,Opening!$I$13,Opening!$D$13,$P$1,$A29,$B29,$M$1) -> 0 | ... P29: =_xll.DBRW($C$1,Opening!$G$13,Opening!P$11,$O$1,Opening!$I$13,Opening!$D$13,$P$1,$A29,$B29,$M$1) -> 0 | Q29: =_xll.DBRW($C$1,Q$15,$Q$16,$O$1,Opening!$I$13,Opening!$D$13,$P$1,$A29,$B29,$M$1) -> 0 | R29: =_xll.DBRW($C$1,R$15,$Q$16,$O$1,Opening!$I$13,Opening!$D$13,$P$1,$A29,$B29,$M$1) -> 0 | S29: =_xll.DBRW($C$1,S$15,$Q$16,$O$1,Opening!$I$13,Opening!$D$13,$P$1,$A29,$B29,$M$1) -> 0 | T29: =_xll.DBRW($C$1,T$15,$Q$16,$O$1,Opening!$I$13,Opening!$D$13,$P$1,$A29,$B29,$M$1) -> 0 | U29: =_xll.DBRW($C$1,U$15,$Q$16,$O$1,Opening!$I$13,Opening!$D$13,$P$1,$A29,$B29,$M$1) -> 0
... A33: OOR.010.001 | B33: N/A | C33: Other | D33: N/A | E33: =_xll.DBRW($C$1,Opening!$G$13,Opening!E$11,$O$1,Opening!$I$13,Opening!$D$13,$P$1,$A33,$B33,$M$1) -> 0 | F33: =_xll.DBRW($C$1,Opening!$G$13,Opening!F$11,$O$1,Opening!$I$13,Opening!$D$13,$P$1,$A33,$B33,$M$1) -> 0 | G33: =_xll.DBRW($C$1,Opening!$G$13,Opening!G$11,$O$1,Opening!$I$13,Opening!$D$13,$P$1,$A33,$B33,$M$1) -> 0 | H33: =_xll.DBRW($C$1,Opening!$G$13,Opening!H$11,$O$1,Opening!$I$13,Opening!$D$13,$P$1,$A33,$B33,$M$1) -> 0 | I33: =_xll.DBRW($C$1,Opening!$G$13,Opening!I$11,$O$1,Opening!$I$13,Opening!$D$13,$P$1,$A33,$B33,$M$1) -> 0 | J33: =_xll.DBRW($C$1,Opening!$G$13,Opening!J$11,$O$1,Opening!$I$13,Opening!$D$13,$P$1,$A33,$B33,$M$1) -> 0 | K33: =_xll.DBRW($C$1,Opening!$G$13,Opening!K$11,$O$1,Opening!$I$13,Opening!$D$13,$P$1,$A33,$B33,$M$1) -> 0 | L33: =_xll.DBRW($C$1,Opening!$G$13,Opening!L$11,$O$1,Opening!$I$13,Opening!$D$13,$P$1,$A33,$B33,$M$1) -> 0 | ... P33: =_xll.DBRW($C$1,Opening!$G$13,Opening!P$11,$O$1,Opening!$I$13,Opening!$D$13,$P$1,$A33,$B33,$M$1) -> 0 | Q33: =_xll.DBRW($C$1,Q$15,$Q$16,$O$1,Opening!$I$13,Opening!$D$13,$P$1,$A33,$B33,$M$1) -> 0 | R33: =_xll.DBRW($C$1,R$15,$Q$16,$O$1,Opening!$I$13,Opening!$D$13,$P$1,$A33,$B33,$M$1) -> 0 | S33: =_xll.DBRW($C$1,S$15,$Q$16,$O$1,Opening!$I$13,Opening!$D$13,$P$1,$A33,$B33,$M$1) -> 0 | T33: =_xll.DBRW($C$1,T$15,$Q$16,$O$1,Opening!$I$13,Opening!$D$13,$P$1,$A33,$B33,$M$1) -> 0 | U33: =_xll.DBRW($C$1,U$15,$Q$16,$O$1,Opening!$I$13,Opening!$D$13,$P$1,$A33,$B33,$M$1) -> 0
C36: DRE - OTHER NON OP. RESULTS
Q37: =$G$13+1 -> 2027 | R37: =$G$13+2 -> 2028 | S37: =$G$13+3 -> 2029 | T37: =$G$13+4 -> 2030 | U37: =$G$13+5 -> 2031
E38: =$G$13&"."&E$11 -> 2026.01 | F38: =$G$13&"."&F$11 -> 2026.02 | G38: =$G$13&"."&G$11 -> 2026.03 | H38: =$G$13&"."&H$11 -> 2026.04 | I38: =$G$13&"."&I$11 -> 2026.05 | J38: =$G$13&"."&J$11 -> 2026.06 | K38: =$G$13&"."&K$11 -> 2026.07 | L38: =$G$13&"."&L$11 -> 2026.08 | ... P38: =$G$13&"."&P$11 -> 2026.12 | Q38: PE | R38: PE | S38: PE | T38: PE | U38: PE
A39: NOR.010.001 | C39: Other Non Operating Results | D39: Total Accounts Line | E39: =_xll.DBRW($C$1,Opening!$G$13,Opening!E$11,$O$1,Opening!$I$13,Opening!$D$13,$P$1,$A39,$D39,$M$1) -> 0 | F39: =_xll.DBRW($C$1,Opening!$G$13,Opening!F$11,$O$1,Opening!$I$13,Opening!$D$13,$P$1,$A39,$D39,$M$1) -> 0 | G39: =_xll.DBRW($C$1,Opening!$G$13,Opening!G$11,$O$1,Opening!$I$13,Opening!$D$13,$P$1,$A39,$D39,$M$1) -> 0 | H39: =_xll.DBRW($C$1,Opening!$G$13,Opening!H$11,$O$1,Opening!$I$13,Opening!$D$13,$P$1,$A39,$D39,$M$1) -> 0 | I39: =_xll.DBRW($C$1,Opening!$G$13,Opening!I$11,$O$1,Opening!$I$13,Opening!$D$13,$P$1,$A39,$D39,$M$1) -> 0 | J39: =_xll.DBRW($C$1,Opening!$G$13,Opening!J$11,$O$1,Opening!$I$13,Opening!$D$13,$P$1,$A39,$D39,$M$1) -> 0 | K39: =_xll.DBRW($C$1,Opening!$G$13,Opening!K$11,$O$1,Opening!$I$13,Opening!$D$13,$P$1,$A39,$D39,$M$1) -> 0 | L39: =_xll.DBRW($C$1,Opening!$G$13,Opening!L$11,$O$1,Opening!$I$13,Opening!$D$13,$P$1,$A39,$D39,$M$1) -> 0 | ... P39: =_xll.DBRW($C$1,Opening!$G$13,Opening!P$11,$O$1,Opening!$I$13,Opening!$D$13,$P$1,$A39,$D39,$M$1) -> 0 | Q39: =_xll.DBRW($C$1,Q$37,$Q$16,$O$1,Opening!$I$13,Opening!$D$13,$P$1,$A39,$D39,$M$1) -> 0 | R39: =_xll.DBRW($C$1,R$37,$Q$16,$O$1,Opening!$I$13,Opening!$D$13,$P$1,$A39,$D39,$M$1) -> 0 | S39: =_xll.DBRW($C$1,S$37,$Q$16,$O$1,Opening!$I$13,Opening!$D$13,$P$1,$A39,$D39,$M$1) -> 0 | T39: =_xll.DBRW($C$1,T$37,$Q$16,$O$1,Opening!$I$13,Opening!$D$13,$P$1,$A39,$D39,$M$1) -> 0 | U39: =_xll.DBRW($C$1,U$37,$Q$16,$O$1,Opening!$I$13,Opening!$D$13,$P$1,$A39,$D39,$M$1) -> 0
A40: NOR.010.001 | B40: ACL.NOR.010.001.01 | C40: Other Non Operating Results | D40: Other Non Op. Results - ARO | E40: =_xll.DBRW($C$1,Opening!$G$13,Opening!E$11,$O$1,Opening!$I$13,Opening!$D$13,$P$1,$A40,$B40,$M$1) -> 0 | F40: =_xll.DBRW($C$1,Opening!$G$13,Opening!F$11,$O$1,Opening!$I$13,Opening!$D$13,$P$1,$A40,$B40,$M$1) -> 0 | G40: =_xll.DBRW($C$1,Opening!$G$13,Opening!G$11,$O$1,Opening!$I$13,Opening!$D$13,$P$1,$A40,$B40,$M$1) -> 0 | H40: =_xll.DBRW($C$1,Opening!$G$13,Opening!H$11,$O$1,Opening!$I$13,Opening!$D$13,$P$1,$A40,$B40,$M$1) -> 0 | I40: =_xll.DBRW($C$1,Opening!$G$13,Opening!I$11,$O$1,Opening!$I$13,Opening!$D$13,$P$1,$A40,$B40,$M$1) -> 0 | J40: =_xll.DBRW($C$1,Opening!$G$13,Opening!J$11,$O$1,Opening!$I$13,Opening!$D$13,$P$1,$A40,$B40,$M$1) -> 0 | K40: =_xll.DBRW($C$1,Opening!$G$13,Opening!K$11,$O$1,Opening!$I$13,Opening!$D$13,$P$1,$A40,$B40,$M$1) -> 0 | L40: =_xll.DBRW($C$1,Opening!$G$13,Opening!L$11,$O$1,Opening!$I$13,Opening!$D$13,$P$1,$A40,$B40,$M$1) -> 0 | ... P40: =_xll.DBRW($C$1,Opening!$G$13,Opening!P$11,$O$1,Opening!$I$13,Opening!$D$13,$P$1,$A40,$B40,$M$1) -> 0 | Q40: =_xll.DBRW($C$1,Q$15,$Q$16,$O$1,Opening!$I$13,Opening!$D$13,$P$1,$A40,$B40,$M$1) -> 0 | R40: =_xll.DBRW($C$1,R$15,$Q$16,$O$1,Opening!$I$13,Opening!$D$13,$P$1,$A40,$B40,$M$1) -> 0 | S40: =_xll.DBRW($C$1,S$15,$Q$16,$O$1,Opening!$I$13,Opening!$D$13,$P$1,$A40,$B40,$M$1) -> 0 | T40: =_xll.DBRW($C$1,T$15,$Q$16,$O$1,Opening!$I$13,Opening!$D$13,$P$1,$A40,$B40,$M$1) -> 0 | U40: =_xll.DBRW($C$1,U$15,$Q$16,$O$1,Opening!$I$13,Opening!$D$13,$P$1,$A40,$B40,$M$1) -> 0
A41: NOR.010.001 | B41: ACL.NOR.010.001.02 | C41: Other Non Operating Results | D41: Other Non Op. Results - FC x BPC Adjustment | E41: =_xll.DBRW($C$1,Opening!$G$13,Opening!E$11,$O$1,Opening!$I$13,Opening!$D$13,$P$1,$A41,$B41,$M$1) -> 0 | F41: =_xll.DBRW($C$1,Opening!$G$13,Opening!F$11,$O$1,Opening!$I$13,Opening!$D$13,$P$1,$A41,$B41,$M$1) -> 0 | G41: =_xll.DBRW($C$1,Opening!$G$13,Opening!G$11,$O$1,Opening!$I$13,Opening!$D$13,$P$1,$A41,$B41,$M$1) -> 0 | H41: =_xll.DBRW($C$1,Opening!$G$13,Opening!H$11,$O$1,Opening!$I$13,Opening!$D$13,$P$1,$A41,$B41,$M$1) -> 0 | I41: =_xll.DBRW($C$1,Opening!$G$13,Opening!I$11,$O$1,Opening!$I$13,Opening!$D$13,$P$1,$A41,$B41,$M$1) -> 0 | J41: =_xll.DBRW($C$1,Opening!$G$13,Opening!J$11,$O$1,Opening!$I$13,Opening!$D$13,$P$1,$A41,$B41,$M$1) -> 0 | K41: =_xll.DBRW($C$1,Opening!$G$13,Opening!K$11,$O$1,Opening!$I$13,Opening!$D$13,$P$1,$A41,$B41,$M$1) -> 0 | L41: =_xll.DBRW($C$1,Opening!$G$13,Opening!L$11,$O$1,Opening!$I$13,Opening!$D$13,$P$1,$A41,$B41,$M$1) -> 0 | ... P41: =_xll.DBRW($C$1,Opening!$G$13,Opening!P$11,$O$1,Opening!$I$13,Opening!$D$13,$P$1,$A41,$B41,$M$1) -> 0 | Q41: =_xll.DBRW($C$1,Q$15,$Q$16,$O$1,Opening!$I$13,Opening!$D$13,$P$1,$A41,$B41,$M$1) -> 0 | R41: =_xll.DBRW($C$1,R$15,$Q$16,$O$1,Opening!$I$13,Opening!$D$13,$P$1,$A41,$B41,$M$1) -> 0 | S41: =_xll.DBRW($C$1,S$15,$Q$16,$O$1,Opening!$I$13,Opening!$D$13,$P$1,$A41,$B41,$M$1) -> 0 | T41: =_xll.DBRW($C$1,T$15,$Q$16,$O$1,Opening!$I$13,Opening!$D$13,$P$1,$A41,$B41,$M$1) -> 0 | U41: =_xll.DBRW($C$1,U$15,$Q$16,$O$1,Opening!$I$13,Opening!$D$13,$P$1,$A41,$B41,$M$1) -> 0
A42: NOR.010.001 | B42: ACL.NOR.010.001.03 | C42: Other Non Operating Results | D42: Hyperinflation | E42: =_xll.DBRW($C$1,Opening!$G$13,Opening!E$11,$O$1,Opening!$I$13,Opening!$D$13,$P$1,$A42,$B42,$M$1) -> 0 | F42: =_xll.DBRW($C$1,Opening!$G$13,Opening!F$11,$O$1,Opening!$I$13,Opening!$D$13,$P$1,$A42,$B42,$M$1) -> 0 | G42: =_xll.DBRW($C$1,Opening!$G$13,Opening!G$11,$O$1,Opening!$I$13,Opening!$D$13,$P$1,$A42,$B42,$M$1) -> 0 | H42: =_xll.DBRW($C$1,Opening!$G$13,Opening!H$11,$O$1,Opening!$I$13,Opening!$D$13,$P$1,$A42,$B42,$M$1) -> 0 | I42: =_xll.DBRW($C$1,Opening!$G$13,Opening!I$11,$O$1,Opening!$I$13,Opening!$D$13,$P$1,$A42,$B42,$M$1) -> 0 | J42: =_xll.DBRW($C$1,Opening!$G$13,Opening!J$11,$O$1,Opening!$I$13,Opening!$D$13,$P$1,$A42,$B42,$M$1) -> 0 | K42: =_xll.DBRW($C$1,Opening!$G$13,Opening!K$11,$O$1,Opening!$I$13,Opening!$D$13,$P$1,$A42,$B42,$M$1) -> 0 | L42: =_xll.DBRW($C$1,Opening!$G$13,Opening!L$11,$O$1,Opening!$I$13,Opening!$D$13,$P$1,$A42,$B42,$M$1) -> 0 | ... P42: =_xll.DBRW($C$1,Opening!$G$13,Opening!P$11,$O$1,Opening!$I$13,Opening!$D$13,$P$1,$A42,$B42,$M$1) -> 0 | Q42: =_xll.DBRW($C$1,Q$15,$Q$16,$O$1,Opening!$I$13,Opening!$D$13,$P$1,$A42,$B42,$M$1) -> 0 | R42: =_xll.DBRW($C$1,R$15,$Q$16,$O$1,Opening!$I$13,Opening!$D$13,$P$1,$A42,$B42,$M$1) -> 0 | S42: =_xll.DBRW($C$1,S$15,$Q$16,$O$1,Opening!$I$13,Opening!$D$13,$P$1,$A42,$B42,$M$1) -> 0 | T42: =_xll.DBRW($C$1,T$15,$Q$16,$O$1,Opening!$I$13,Opening!$D$13,$P$1,$A42,$B42,$M$1) -> 0 | U42: =_xll.DBRW($C$1,U$15,$Q$16,$O$1,Opening!$I$13,Opening!$D$13,$P$1,$A42,$B42,$M$1) -> 0
A43: NOR.010.001 | B43: ACL.NOR.010.001.04 | C43: Other Non Operating Results | D43: Impairment | E43: =_xll.DBRW($C$1,Opening!$G$13,Opening!E$11,$O$1,Opening!$I$13,Opening!$D$13,$P$1,$A43,$B43,$M$1) -> 0 | F43: =_xll.DBRW($C$1,Opening!$G$13,Opening!F$11,$O$1,Opening!$I$13,Opening!$D$13,$P$1,$A43,$B43,$M$1) -> 0 | G43: =_xll.DBRW($C$1,Opening!$G$13,Opening!G$11,$O$1,Opening!$I$13,Opening!$D$13,$P$1,$A43,$B43,$M$1) -> 0 | H43: =_xll.DBRW($C$1,Opening!$G$13,Opening!H$11,$O$1,Opening!$I$13,Opening!$D$13,$P$1,$A43,$B43,$M$1) -> 0 | I43: =_xll.DBRW($C$1,Opening!$G$13,Opening!I$11,$O$1,Opening!$I$13,Opening!$D$13,$P$1,$A43,$B43,$M$1) -> 0 | J43: =_xll.DBRW($C$1,Opening!$G$13,Opening!J$11,$O$1,Opening!$I$13,Opening!$D$13,$P$1,$A43,$B43,$M$1) -> 0 | K43: =_xll.DBRW($C$1,Opening!$G$13,Opening!K$11,$O$1,Opening!$I$13,Opening!$D$13,$P$1,$A43,$B43,$M$1) -> 0 | L43: =_xll.DBRW($C$1,Opening!$G$13,Opening!L$11,$O$1,Opening!$I$13,Opening!$D$13,$P$1,$A43,$B43,$M$1) -> 0 | ... P43: =_xll.DBRW($C$1,Opening!$G$13,Opening!P$11,$O$1,Opening!$I$13,Opening!$D$13,$P$1,$A43,$B43,$M$1) -> 0 | Q43: =_xll.DBRW($C$1,Q$15,$Q$16,$O$1,Opening!$I$13,Opening!$D$13,$P$1,$A43,$B43,$M$1) -> 0 | R43: =_xll.DBRW($C$1,R$15,$Q$16,$O$1,Opening!$I$13,Opening!$D$13,$P$1,$A43,$B43,$M$1) -> 0 | S43: =_xll.DBRW($C$1,S$15,$Q$16,$O$1,Opening!$I$13,Opening!$D$13,$P$1,$A43,$B43,$M$1) -> 0 | T43: =_xll.DBRW($C$1,T$15,$Q$16,$O$1,Opening!$I$13,Opening!$D$13,$P$1,$A43,$B43,$M$1) -> 0 | U43: =_xll.DBRW($C$1,U$15,$Q$16,$O$1,Opening!$I$13,Opening!$D$13,$P$1,$A43,$B43,$M$1) -> 0
A44: NOR.010.001 | B44: ACL.NOR.010.001.05 | C44: Other Non Operating Results | D44: M&A Gain/Loss | E44: =_xll.DBRW($C$1,Opening!$G$13,Opening!E$11,$O$1,Opening!$I$13,Opening!$D$13,$P$1,$A44,$B44,$M$1) -> 0 | F44: =_xll.DBRW($C$1,Opening!$G$13,Opening!F$11,$O$1,Opening!$I$13,Opening!$D$13,$P$1,$A44,$B44,$M$1) -> 0 | G44: =_xll.DBRW($C$1,Opening!$G$13,Opening!G$11,$O$1,Opening!$I$13,Opening!$D$13,$P$1,$A44,$B44,$M$1) -> 0 | H44: =_xll.DBRW($C$1,Opening!$G$13,Opening!H$11,$O$1,Opening!$I$13,Opening!$D$13,$P$1,$A44,$B44,$M$1) -> 0 | I44: =_xll.DBRW($C$1,Opening!$G$13,Opening!I$11,$O$1,Opening!$I$13,Opening!$D$13,$P$1,$A44,$B44,$M$1) -> 0 | J44: =_xll.DBRW($C$1,Opening!$G$13,Opening!J$11,$O$1,Opening!$I$13,Opening!$D$13,$P$1,$A44,$B44,$M$1) -> 0 | K44: =_xll.DBRW($C$1,Opening!$G$13,Opening!K$11,$O$1,Opening!$I$13,Opening!$D$13,$P$1,$A44,$B44,$M$1) -> 0 | L44: =_xll.DBRW($C$1,Opening!$G$13,Opening!L$11,$O$1,Opening!$I$13,Opening!$D$13,$P$1,$A44,$B44,$M$1) -> 0 | ... P44: =_xll.DBRW($C$1,Opening!$G$13,Opening!P$11,$O$1,Opening!$I$13,Opening!$D$13,$P$1,$A44,$B44,$M$1) -> 0 | Q44: =_xll.DBRW($C$1,Q$15,$Q$16,$O$1,Opening!$I$13,Opening!$D$13,$P$1,$A44,$B44,$M$1) -> 0 | R44: =_xll.DBRW($C$1,R$15,$Q$16,$O$1,Opening!$I$13,Opening!$D$13,$P$1,$A44,$B44,$M$1) -> 0 | S44: =_xll.DBRW($C$1,S$15,$Q$16,$O$1,Opening!$I$13,Opening!$D$13,$P$1,$A44,$B44,$M$1) -> 0 | T44: =_xll.DBRW($C$1,T$15,$Q$16,$O$1,Opening!$I$13,Opening!$D$13,$P$1,$A44,$B44,$M$1) -> 0 | U44: =_xll.DBRW($C$1,U$15,$Q$16,$O$1,Opening!$I$13,Opening!$D$13,$P$1,$A44,$B44,$M$1) -> 0
A45: NOR.010.001 | B45: ACL.NOR.010.001.06 | C45: Other Non Operating Results | D45: MTM Energia | E45: =_xll.DBRW($C$1,Opening!$G$13,Opening!E$11,$O$1,Opening!$I$13,Opening!$D$13,$P$1,$A45,$B45,$M$1) -> 0 | F45: =_xll.DBRW($C$1,Opening!$G$13,Opening!F$11,$O$1,Opening!$I$13,Opening!$D$13,$P$1,$A45,$B45,$M$1) -> 0 | G45: =_xll.DBRW($C$1,Opening!$G$13,Opening!G$11,$O$1,Opening!$I$13,Opening!$D$13,$P$1,$A45,$B45,$M$1) -> 0 | H45: =_xll.DBRW($C$1,Opening!$G$13,Opening!H$11,$O$1,Opening!$I$13,Opening!$D$13,$P$1,$A45,$B45,$M$1) -> 0 | I45: =_xll.DBRW($C$1,Opening!$G$13,Opening!I$11,$O$1,Opening!$I$13,Opening!$D$13,$P$1,$A45,$B45,$M$1) -> 0 | J45: =_xll.DBRW($C$1,Opening!$G$13,Opening!J$11,$O$1,Opening!$I$13,Opening!$D$13,$P$1,$A45,$B45,$M$1) -> 0 | K45: =_xll.DBRW($C$1,Opening!$G$13,Opening!K$11,$O$1,Opening!$I$13,Opening!$D$13,$P$1,$A45,$B45,$M$1) -> 0 | L45: =_xll.DBRW($C$1,Opening!$G$13,Opening!L$11,$O$1,Opening!$I$13,Opening!$D$13,$P$1,$A45,$B45,$M$1) -> 0 | ... P45: =_xll.DBRW($C$1,Opening!$G$13,Opening!P$11,$O$1,Opening!$I$13,Opening!$D$13,$P$1,$A45,$B45,$M$1) -> 0 | Q45: =_xll.DBRW($C$1,Q$15,$Q$16,$O$1,Opening!$I$13,Opening!$D$13,$P$1,$A45,$B45,$M$1) -> 0 | R45: =_xll.DBRW($C$1,R$15,$Q$16,$O$1,Opening!$I$13,Opening!$D$13,$P$1,$A45,$B45,$M$1) -> 0 | S45: =_xll.DBRW($C$1,S$15,$Q$16,$O$1,Opening!$I$13,Opening!$D$13,$P$1,$A45,$B45,$M$1) -> 0 | T45: =_xll.DBRW($C$1,T$15,$Q$16,$O$1,Opening!$I$13,Opening!$D$13,$P$1,$A45,$B45,$M$1) -> 0 | U45: =_xll.DBRW($C$1,U$15,$Q$16,$O$1,Opening!$I$13,Opening!$D$13,$P$1,$A45,$B45,$M$1) -> 0
A46: NOR.010.001 | B46: ACL.NOR.010.001.07 | C46: Other Non Operating Results | D46: Discontinued operations | E46: =_xll.DBRW($C$1,Opening!$G$13,Opening!E$11,$O$1,Opening!$I$13,Opening!$D$13,$P$1,$A46,$B46,$M$1) -> 0 | F46: =_xll.DBRW($C$1,Opening!$G$13,Opening!F$11,$O$1,Opening!$I$13,Opening!$D$13,$P$1,$A46,$B46,$M$1) -> 0 | G46: =_xll.DBRW($C$1,Opening!$G$13,Opening!G$11,$O$1,Opening!$I$13,Opening!$D$13,$P$1,$A46,$B46,$M$1) -> 0 | H46: =_xll.DBRW($C$1,Opening!$G$13,Opening!H$11,$O$1,Opening!$I$13,Opening!$D$13,$P$1,$A46,$B46,$M$1) -> 0 | I46: =_xll.DBRW($C$1,Opening!$G$13,Opening!I$11,$O$1,Opening!$I$13,Opening!$D$13,$P$1,$A46,$B46,$M$1) -> 0 | J46: =_xll.DBRW($C$1,Opening!$G$13,Opening!J$11,$O$1,Opening!$I$13,Opening!$D$13,$P$1,$A46,$B46,$M$1) -> 0 | K46: =_xll.DBRW($C$1,Opening!$G$13,Opening!K$11,$O$1,Opening!$I$13,Opening!$D$13,$P$1,$A46,$B46,$M$1) -> 0 | L46: =_xll.DBRW($C$1,Opening!$G$13,Opening!L$11,$O$1,Opening!$I$13,Opening!$D$13,$P$1,$A46,$B46,$M$1) -> 0 | ... P46: =_xll.DBRW($C$1,Opening!$G$13,Opening!P$11,$O$1,Opening!$I$13,Opening!$D$13,$P$1,$A46,$B46,$M$1) -> 0 | Q46: =_xll.DBRW($C$1,Q$15,$Q$16,$O$1,Opening!$I$13,Opening!$D$13,$P$1,$A46,$B46,$M$1) -> 0 | R46: =_xll.DBRW($C$1,R$15,$Q$16,$O$1,Opening!$I$13,Opening!$D$13,$P$1,$A46,$B46,$M$1) -> 0 | S46: =_xll.DBRW($C$1,S$15,$Q$16,$O$1,Opening!$I$13,Opening!$D$13,$P$1,$A46,$B46,$M$1) -> 0 | T46: =_xll.DBRW($C$1,T$15,$Q$16,$O$1,Opening!$I$13,Opening!$D$13,$P$1,$A46,$B46,$M$1) -> 0 | U46: =_xll.DBRW($C$1,U$15,$Q$16,$O$1,Opening!$I$13,Opening!$D$13,$P$1,$A46,$B46,$M$1) -> 0
A47: NOR.010.001 | B47: ACL.NOR.010.001.08 | C47: Other Non Operating Results | D47: Results from assets sales | E47: =_xll.DBRW($C$1,Opening!$G$13,Opening!E$11,$O$1,Opening!$I$13,Opening!$D$13,$P$1,$A47,$B47,$M$1) -> 0 | F47: =_xll.DBRW($C$1,Opening!$G$13,Opening!F$11,$O$1,Opening!$I$13,Opening!$D$13,$P$1,$A47,$B47,$M$1) -> 0 | G47: =_xll.DBRW($C$1,Opening!$G$13,Opening!G$11,$O$1,Opening!$I$13,Opening!$D$13,$P$1,$A47,$B47,$M$1) -> 0 | H47: =_xll.DBRW($C$1,Opening!$G$13,Opening!H$11,$O$1,Opening!$I$13,Opening!$D$13,$P$1,$A47,$B47,$M$1) -> 0 | I47: =_xll.DBRW($C$1,Opening!$G$13,Opening!I$11,$O$1,Opening!$I$13,Opening!$D$13,$P$1,$A47,$B47,$M$1) -> 0 | J47: =_xll.DBRW($C$1,Opening!$G$13,Opening!J$11,$O$1,Opening!$I$13,Opening!$D$13,$P$1,$A47,$B47,$M$1) -> 0 | K47: =_xll.DBRW($C$1,Opening!$G$13,Opening!K$11,$O$1,Opening!$I$13,Opening!$D$13,$P$1,$A47,$B47,$M$1) -> 0 | L47: =_xll.DBRW($C$1,Opening!$G$13,Opening!L$11,$O$1,Opening!$I$13,Opening!$D$13,$P$1,$A47,$B47,$M$1) -> 0 | ... P47: =_xll.DBRW($C$1,Opening!$G$13,Opening!P$11,$O$1,Opening!$I$13,Opening!$D$13,$P$1,$A47,$B47,$M$1) -> 0 | Q47: =_xll.DBRW($C$1,Q$15,$Q$16,$O$1,Opening!$I$13,Opening!$D$13,$P$1,$A47,$B47,$M$1) -> 0 | R47: =_xll.DBRW($C$1,R$15,$Q$16,$O$1,Opening!$I$13,Opening!$D$13,$P$1,$A47,$B47,$M$1) -> 0 | S47: =_xll.DBRW($C$1,S$15,$Q$16,$O$1,Opening!$I$13,Opening!$D$13,$P$1,$A47,$B47,$M$1) -> 0 | T47: =_xll.DBRW($C$1,T$15,$Q$16,$O$1,Opening!$I$13,Opening!$D$13,$P$1,$A47,$B47,$M$1) -> 0 | U47: =_xll.DBRW($C$1,U$15,$Q$16,$O$1,Opening!$I$13,Opening!$D$13,$P$1,$A47,$B47,$M$1) -> 0
A48: NOR.010.001 | B48: ACL.NOR.010.001.09 | C48: Other Non Operating Results | D48: Trasaction costs | E48: =_xll.DBRW($C$1,Opening!$G$13,Opening!E$11,$O$1,Opening!$I$13,Opening!$D$13,$P$1,$A48,$B48,$M$1) -> 0 | F48: =_xll.DBRW($C$1,Opening!$G$13,Opening!F$11,$O$1,Opening!$I$13,Opening!$D$13,$P$1,$A48,$B48,$M$1) -> 0 | G48: =_xll.DBRW($C$1,Opening!$G$13,Opening!G$11,$O$1,Opening!$I$13,Opening!$D$13,$P$1,$A48,$B48,$M$1) -> 0 | H48: =_xll.DBRW($C$1,Opening!$G$13,Opening!H$11,$O$1,Opening!$I$13,Opening!$D$13,$P$1,$A48,$B48,$M$1) -> 0 | I48: =_xll.DBRW($C$1,Opening!$G$13,Opening!I$11,$O$1,Opening!$I$13,Opening!$D$13,$P$1,$A48,$B48,$M$1) -> 0 | J48: =_xll.DBRW($C$1,Opening!$G$13,Opening!J$11,$O$1,Opening!$I$13,Opening!$D$13,$P$1,$A48,$B48,$M$1) -> 0 | K48: =_xll.DBRW($C$1,Opening!$G$13,Opening!K$11,$O$1,Opening!$I$13,Opening!$D$13,$P$1,$A48,$B48,$M$1) -> 0 | L48: =_xll.DBRW($C$1,Opening!$G$13,Opening!L$11,$O$1,Opening!$I$13,Opening!$D$13,$P$1,$A48,$B48,$M$1) -> 0 | ... P48: =_xll.DBRW($C$1,Opening!$G$13,Opening!P$11,$O$1,Opening!$I$13,Opening!$D$13,$P$1,$A48,$B48,$M$1) -> 0 | Q48: =_xll.DBRW($C$1,Q$15,$Q$16,$O$1,Opening!$I$13,Opening!$D$13,$P$1,$A48,$B48,$M$1) -> 0 | R48: =_xll.DBRW($C$1,R$15,$Q$16,$O$1,Opening!$I$13,Opening!$D$13,$P$1,$A48,$B48,$M$1) -> 0 | S48: =_xll.DBRW($C$1,S$15,$Q$16,$O$1,Opening!$I$13,Opening!$D$13,$P$1,$A48,$B48,$M$1) -> 0 | T48: =_xll.DBRW($C$1,T$15,$Q$16,$O$1,Opening!$I$13,Opening!$D$13,$P$1,$A48,$B48,$M$1) -> 0 | U48: =_xll.DBRW($C$1,U$15,$Q$16,$O$1,Opening!$I$13,Opening!$D$13,$P$1,$A48,$B48,$M$1) -> 0
A49: NOR.010.001 | B49: ACL.NOR.010.001.10 | C49: Other Non Operating Results | D49: Other Non Op. Results - Others | E49: =_xll.DBRW($C$1,Opening!$G$13,Opening!E$11,$O$1,Opening!$I$13,Opening!$D$13,$P$1,$A49,$B49,$M$1) -> 0 | F49: =_xll.DBRW($C$1,Opening!$G$13,Opening!F$11,$O$1,Opening!$I$13,Opening!$D$13,$P$1,$A49,$B49,$M$1) -> 0 | G49: =_xll.DBRW($C$1,Opening!$G$13,Opening!G$11,$O$1,Opening!$I$13,Opening!$D$13,$P$1,$A49,$B49,$M$1) -> 0 | H49: =_xll.DBRW($C$1,Opening!$G$13,Opening!H$11,$O$1,Opening!$I$13,Opening!$D$13,$P$1,$A49,$B49,$M$1) -> 0 | I49: =_xll.DBRW($C$1,Opening!$G$13,Opening!I$11,$O$1,Opening!$I$13,Opening!$D$13,$P$1,$A49,$B49,$M$1) -> 0 | J49: =_xll.DBRW($C$1,Opening!$G$13,Opening!J$11,$O$1,Opening!$I$13,Opening!$D$13,$P$1,$A49,$B49,$M$1) -> 0 | K49: =_xll.DBRW($C$1,Opening!$G$13,Opening!K$11,$O$1,Opening!$I$13,Opening!$D$13,$P$1,$A49,$B49,$M$1) -> 0 | L49: =_xll.DBRW($C$1,Opening!$G$13,Opening!L$11,$O$1,Opening!$I$13,Opening!$D$13,$P$1,$A49,$B49,$M$1) -> 0 | ... P49: =_xll.DBRW($C$1,Opening!$G$13,Opening!P$11,$O$1,Opening!$I$13,Opening!$D$13,$P$1,$A49,$B49,$M$1) -> 0 | Q49: =_xll.DBRW($C$1,Q$15,$Q$16,$O$1,Opening!$I$13,Opening!$D$13,$P$1,$A49,$B49,$M$1) -> 0 | R49: =_xll.DBRW($C$1,R$15,$Q$16,$O$1,Opening!$I$13,Opening!$D$13,$P$1,$A49,$B49,$M$1) -> 0 | S49: =_xll.DBRW($C$1,S$15,$Q$16,$O$1,Opening!$I$13,Opening!$D$13,$P$1,$A49,$B49,$M$1) -> 0 | T49: =_xll.DBRW($C$1,T$15,$Q$16,$O$1,Opening!$I$13,Opening!$D$13,$P$1,$A49,$B49,$M$1) -> 0 | U49: =_xll.DBRW($C$1,U$15,$Q$16,$O$1,Opening!$I$13,Opening!$D$13,$P$1,$A49,$B49,$M$1) -> 0
A50: NOR.010.001 | B50: N/A | C50: Other Non Operating Results | D50: N/A | E50: =_xll.DBRW($C$1,Opening!$G$13,Opening!E$11,$O$1,Opening!$I$13,Opening!$D$13,$P$1,$A50,$B50,$M$1) -> 0 | F50: =_xll.DBRW($C$1,Opening!$G$13,Opening!F$11,$O$1,Opening!$I$13,Opening!$D$13,$P$1,$A50,$B50,$M$1) -> 0 | G50: =_xll.DBRW($C$1,Opening!$G$13,Opening!G$11,$O$1,Opening!$I$13,Opening!$D$13,$P$1,$A50,$B50,$M$1) -> 0 | H50: =_xll.DBRW($C$1,Opening!$G$13,Opening!H$11,$O$1,Opening!$I$13,Opening!$D$13,$P$1,$A50,$B50,$M$1) -> 0 | I50: =_xll.DBRW($C$1,Opening!$G$13,Opening!I$11,$O$1,Opening!$I$13,Opening!$D$13,$P$1,$A50,$B50,$M$1) -> 0 | J50: =_xll.DBRW($C$1,Opening!$G$13,Opening!J$11,$O$1,Opening!$I$13,Opening!$D$13,$P$1,$A50,$B50,$M$1) -> 0 | K50: =_xll.DBRW($C$1,Opening!$G$13,Opening!K$11,$O$1,Opening!$I$13,Opening!$D$13,$P$1,$A50,$B50,$M$1) -> 0 | L50: =_xll.DBRW($C$1,Opening!$G$13,Opening!L$11,$O$1,Opening!$I$13,Opening!$D$13,$P$1,$A50,$B50,$M$1) -> 0 | ... P50: =_xll.DBRW($C$1,Opening!$G$13,Opening!P$11,$O$1,Opening!$I$13,Opening!$D$13,$P$1,$A50,$B50,$M$1) -> 0 | Q50: =_xll.DBRW($C$1,Q$15,$Q$16,$O$1,Opening!$I$13,Opening!$D$13,$P$1,$A50,$B50,$M$1) -> 0 | R50: =_xll.DBRW($C$1,R$15,$Q$16,$O$1,Opening!$I$13,Opening!$D$13,$P$1,$A50,$B50,$M$1) -> 0 | S50: =_xll.DBRW($C$1,S$15,$Q$16,$O$1,Opening!$I$13,Opening!$D$13,$P$1,$A50,$B50,$M$1) -> 0 | T50: =_xll.DBRW($C$1,T$15,$Q$16,$O$1,Opening!$I$13,Opening!$D$13,$P$1,$A50,$B50,$M$1) -> 0 | U50: =_xll.DBRW($C$1,U$15,$Q$16,$O$1,Opening!$I$13,Opening!$D$13,$P$1,$A50,$B50,$M$1) -> 0
C53: CASH FLOW - DIVIDENDS RECEIVED
Q54: =$G$13+1 -> 2027 | R54: =$G$13+2 -> 2028 | S54: =$G$13+3 -> 2029 | T54: =$G$13+4 -> 2030 | U54: =$G$13+5 -> 2031
E55: =$G$13&"."&E$11 -> 2026.01 | F55: =$G$13&"."&F$11 -> 2026.02 | G55: =$G$13&"."&G$11 -> 2026.03 | H55: =$G$13&"."&H$11 -> 2026.04 | I55: =$G$13&"."&I$11 -> 2026.05 | J55: =$G$13&"."&J$11 -> 2026.06 | K55: =$G$13&"."&K$11 -> 2026.07 | L55: =$G$13&"."&L$11 -> 2026.08 | ... P55: =$G$13&"."&P$11 -> 2026.12 | Q55: PE | R55: PE | S55: PE | T55: PE | U55: PE
A56: FCF.040.001 | C56: Dividends Received (Paid) - Cash Flow | D56: Total Accounts Line | E56: =_xll.DBRW($C$1,Opening!$G$13,Opening!E$11,$O$1,Opening!$I$13,Opening!$D$13,$P$2,$A56,$D56,$M$1) -> 0 | F56: =_xll.DBRW($C$1,Opening!$G$13,Opening!F$11,$O$1,Opening!$I$13,Opening!$D$13,$P$2,$A56,$D56,$M$1) -> 0 | G56: =_xll.DBRW($C$1,Opening!$G$13,Opening!G$11,$O$1,Opening!$I$13,Opening!$D$13,$P$2,$A56,$D56,$M$1) -> 0 | H56: =_xll.DBRW($C$1,Opening!$G$13,Opening!H$11,$O$1,Opening!$I$13,Opening!$D$13,$P$2,$A56,$D56,$M$1) -> 0 | I56: =_xll.DBRW($C$1,Opening!$G$13,Opening!I$11,$O$1,Opening!$I$13,Opening!$D$13,$P$2,$A56,$D56,$M$1) -> 0 | J56: =_xll.DBRW($C$1,Opening!$G$13,Opening!J$11,$O$1,Opening!$I$13,Opening!$D$13,$P$2,$A56,$D56,$M$1) -> 0 | K56: =_xll.DBRW($C$1,Opening!$G$13,Opening!K$11,$O$1,Opening!$I$13,Opening!$D$13,$P$2,$A56,$D56,$M$1) -> 0 | L56: =_xll.DBRW($C$1,Opening!$G$13,Opening!L$11,$O$1,Opening!$I$13,Opening!$D$13,$P$2,$A56,$D56,$M$1) -> 0 | ... P56: =_xll.DBRW($C$1,Opening!$G$13,Opening!P$11,$O$1,Opening!$I$13,Opening!$D$13,$P$2,$A56,$D56,$M$1) -> 0 | Q56: =_xll.DBRW($C$1,Q$37,$Q$16,$O$1,Opening!$I$13,Opening!$D$13,$P$1,$A56,$D56,$M$1) -> 0 | R56: =_xll.DBRW($C$1,R$37,$Q$16,$O$1,Opening!$I$13,Opening!$D$13,$P$1,$A56,$D56,$M$1) -> 0 | S56: =_xll.DBRW($C$1,S$37,$Q$16,$O$1,Opening!$I$13,Opening!$D$13,$P$1,$A56,$D56,$M$1) -> 0 | T56: =_xll.DBRW($C$1,T$37,$Q$16,$O$1,Opening!$I$13,Opening!$D$13,$P$1,$A56,$D56,$M$1) -> 0 | U56: =_xll.DBRW($C$1,U$37,$Q$16,$O$1,Opening!$I$13,Opening!$D$13,$P$1,$A56,$D56,$M$1) -> 0
A57: FCF.040.001 | B57: ACL.FCF.040.001.01 | C57: Dividends Received (Paid) - Cash Flow | D57: Avellaneda | E57: =_xll.DBRW($C$1,Opening!$G$13,Opening!E$11,$O$1,Opening!$I$13,Opening!$D$13,$P$1,$A57,$B57,$M$1) -> 0 | F57: =_xll.DBRW($C$1,Opening!$G$13,Opening!F$11,$O$1,Opening!$I$13,Opening!$D$13,$P$1,$A57,$B57,$M$1) -> 0 | G57: =_xll.DBRW($C$1,Opening!$G$13,Opening!G$11,$O$1,Opening!$I$13,Opening!$D$13,$P$1,$A57,$B57,$M$1) -> 0 | H57: =_xll.DBRW($C$1,Opening!$G$13,Opening!H$11,$O$1,Opening!$I$13,Opening!$D$13,$P$1,$A57,$B57,$M$1) -> 0 | I57: =_xll.DBRW($C$1,Opening!$G$13,Opening!I$11,$O$1,Opening!$I$13,Opening!$D$13,$P$1,$A57,$B57,$M$1) -> 0 | J57: =_xll.DBRW($C$1,Opening!$G$13,Opening!J$11,$O$1,Opening!$I$13,Opening!$D$13,$P$1,$A57,$B57,$M$1) -> 0 | K57: =_xll.DBRW($C$1,Opening!$G$13,Opening!K$11,$O$1,Opening!$I$13,Opening!$D$13,$P$1,$A57,$B57,$M$1) -> 0 | L57: =_xll.DBRW($C$1,Opening!$G$13,Opening!L$11,$O$1,Opening!$I$13,Opening!$D$13,$P$1,$A57,$B57,$M$1) -> 0 | ... P57: =_xll.DBRW($C$1,Opening!$G$13,Opening!P$11,$O$1,Opening!$I$13,Opening!$D$13,$P$1,$A57,$B57,$M$1) -> 0 | Q57: =_xll.DBRW($C$1,Q$15,$Q$16,$O$1,Opening!$I$13,Opening!$D$13,$P$1,$A57,$B57,$M$1) -> 0 | R57: =_xll.DBRW($C$1,R$15,$Q$16,$O$1,Opening!$I$13,Opening!$D$13,$P$1,$A57,$B57,$M$1) -> 0 | S57: =_xll.DBRW($C$1,S$15,$Q$16,$O$1,Opening!$I$13,Opening!$D$13,$P$1,$A57,$B57,$M$1) -> 0 | T57: =_xll.DBRW($C$1,T$15,$Q$16,$O$1,Opening!$I$13,Opening!$D$13,$P$1,$A57,$B57,$M$1) -> 0 | U57: =_xll.DBRW($C$1,U$15,$Q$16,$O$1,Opening!$I$13,Opening!$D$13,$P$1,$A57,$B57,$M$1) -> 0
A58: FCF.040.001 | B58: ACL.FCF.040.001.02 | C58: Dividends Received (Paid) - Cash Flow | D58: Dividens Received from JVs | E58: =_xll.DBRW($C$1,Opening!$G$13,Opening!E$11,$O$1,Opening!$I$13,Opening!$D$13,$P$1,$A58,$B58,$M$1) -> 0 | F58: =_xll.DBRW($C$1,Opening!$G$13,Opening!F$11,$O$1,Opening!$I$13,Opening!$D$13,$P$1,$A58,$B58,$M$1) -> 0 | G58: =_xll.DBRW($C$1,Opening!$G$13,Opening!G$11,$O$1,Opening!$I$13,Opening!$D$13,$P$1,$A58,$B58,$M$1) -> 0 | H58: =_xll.DBRW($C$1,Opening!$G$13,Opening!H$11,$O$1,Opening!$I$13,Opening!$D$13,$P$1,$A58,$B58,$M$1) -> 0 | I58: =_xll.DBRW($C$1,Opening!$G$13,Opening!I$11,$O$1,Opening!$I$13,Opening!$D$13,$P$1,$A58,$B58,$M$1) -> 0 | J58: =_xll.DBRW($C$1,Opening!$G$13,Opening!J$11,$O$1,Opening!$I$13,Opening!$D$13,$P$1,$A58,$B58,$M$1) -> 0 | K58: =_xll.DBRW($C$1,Opening!$G$13,Opening!K$11,$O$1,Opening!$I$13,Opening!$D$13,$P$1,$A58,$B58,$M$1) -> 0 | L58: =_xll.DBRW($C$1,Opening!$G$13,Opening!L$11,$O$1,Opening!$I$13,Opening!$D$13,$P$1,$A58,$B58,$M$1) -> 0 | ... P58: =_xll.DBRW($C$1,Opening!$G$13,Opening!P$11,$O$1,Opening!$I$13,Opening!$D$13,$P$1,$A58,$B58,$M$1) -> 0 | Q58: =_xll.DBRW($C$1,Q$15,$Q$16,$O$1,Opening!$I$13,Opening!$D$13,$P$1,$A58,$B58,$M$1) -> 0 | R58: =_xll.DBRW($C$1,R$15,$Q$16,$O$1,Opening!$I$13,Opening!$D$13,$P$1,$A58,$B58,$M$1) -> 0 | S58: =_xll.DBRW($C$1,S$15,$Q$16,$O$1,Opening!$I$13,Opening!$D$13,$P$1,$A58,$B58,$M$1) -> 0 | T58: =_xll.DBRW($C$1,T$15,$Q$16,$O$1,Opening!$I$13,Opening!$D$13,$P$1,$A58,$B58,$M$1) -> 0 | U58: =_xll.DBRW($C$1,U$15,$Q$16,$O$1,Opening!$I$13,Opening!$D$13,$P$1,$A58,$B58,$M$1) -> 0
A59: FCF.040.001 | B59: ACL.FCF.040.001.03 | C59: Dividends Received (Paid) - Cash Flow | D59: Dividends received - Others | E59: =_xll.DBRW($C$1,Opening!$G$13,Opening!E$11,$O$1,Opening!$I$13,Opening!$D$13,$P$1,$A59,$B59,$M$1) -> 0 | F59: =_xll.DBRW($C$1,Opening!$G$13,Opening!F$11,$O$1,Opening!$I$13,Opening!$D$13,$P$1,$A59,$B59,$M$1) -> 0 | G59: =_xll.DBRW($C$1,Opening!$G$13,Opening!G$11,$O$1,Opening!$I$13,Opening!$D$13,$P$1,$A59,$B59,$M$1) -> 0 | H59: =_xll.DBRW($C$1,Opening!$G$13,Opening!H$11,$O$1,Opening!$I$13,Opening!$D$13,$P$1,$A59,$B59,$M$1) -> 0 | I59: =_xll.DBRW($C$1,Opening!$G$13,Opening!I$11,$O$1,Opening!$I$13,Opening!$D$13,$P$1,$A59,$B59,$M$1) -> 0 | J59: =_xll.DBRW($C$1,Opening!$G$13,Opening!J$11,$O$1,Opening!$I$13,Opening!$D$13,$P$1,$A59,$B59,$M$1) -> 0 | K59: =_xll.DBRW($C$1,Opening!$G$13,Opening!K$11,$O$1,Opening!$I$13,Opening!$D$13,$P$1,$A59,$B59,$M$1) -> 0 | L59: =_xll.DBRW($C$1,Opening!$G$13,Opening!L$11,$O$1,Opening!$I$13,Opening!$D$13,$P$1,$A59,$B59,$M$1) -> 0 | ... P59: =_xll.DBRW($C$1,Opening!$G$13,Opening!P$11,$O$1,Opening!$I$13,Opening!$D$13,$P$1,$A59,$B59,$M$1) -> 0 | Q59: =_xll.DBRW($C$1,Q$15,$Q$16,$O$1,Opening!$I$13,Opening!$D$13,$P$1,$A59,$B59,$M$1) -> 0 | R59: =_xll.DBRW($C$1,R$15,$Q$16,$O$1,Opening!$I$13,Opening!$D$13,$P$1,$A59,$B59,$M$1) -> 0 | S59: =_xll.DBRW($C$1,S$15,$Q$16,$O$1,Opening!$I$13,Opening!$D$13,$P$1,$A59,$B59,$M$1) -> 0 | T59: =_xll.DBRW($C$1,T$15,$Q$16,$O$1,Opening!$I$13,Opening!$D$13,$P$1,$A59,$B59,$M$1) -> 0 | U59: =_xll.DBRW($C$1,U$15,$Q$16,$O$1,Opening!$I$13,Opening!$D$13,$P$1,$A59,$B59,$M$1) -> 0
A60: FCF.040.001 | B60: N/A | C60: Dividends Received (Paid) - Cash Flow | D60: N/A | E60: =_xll.DBRW($C$1,Opening!$G$13,Opening!E$11,$O$1,Opening!$I$13,Opening!$D$13,$P$1,$A60,$B60,$M$1) -> 0 | F60: =_xll.DBRW($C$1,Opening!$G$13,Opening!F$11,$O$1,Opening!$I$13,Opening!$D$13,$P$1,$A60,$B60,$M$1) -> 0 | G60: =_xll.DBRW($C$1,Opening!$G$13,Opening!G$11,$O$1,Opening!$I$13,Opening!$D$13,$P$1,$A60,$B60,$M$1) -> 0 | H60: =_xll.DBRW($C$1,Opening!$G$13,Opening!H$11,$O$1,Opening!$I$13,Opening!$D$13,$P$1,$A60,$B60,$M$1) -> 0 | I60: =_xll.DBRW($C$1,Opening!$G$13,Opening!I$11,$O$1,Opening!$I$13,Opening!$D$13,$P$1,$A60,$B60,$M$1) -> 0 | J60: =_xll.DBRW($C$1,Opening!$G$13,Opening!J$11,$O$1,Opening!$I$13,Opening!$D$13,$P$1,$A60,$B60,$M$1) -> 0 | K60: =_xll.DBRW($C$1,Opening!$G$13,Opening!K$11,$O$1,Opening!$I$13,Opening!$D$13,$P$1,$A60,$B60,$M$1) -> 0 | L60: =_xll.DBRW($C$1,Opening!$G$13,Opening!L$11,$O$1,Opening!$I$13,Opening!$D$13,$P$1,$A60,$B60,$M$1) -> 0 | ... P60: =_xll.DBRW($C$1,Opening!$G$13,Opening!P$11,$O$1,Opening!$I$13,Opening!$D$13,$P$1,$A60,$B60,$M$1) -> 0 | Q60: =_xll.DBRW($C$1,Q$15,$Q$16,$O$1,Opening!$I$13,Opening!$D$13,$P$1,$A60,$B60,$M$1) -> 0 | R60: =_xll.DBRW($C$1,R$15,$Q$16,$O$1,Opening!$I$13,Opening!$D$13,$P$1,$A60,$B60,$M$1) -> 0 | S60: =_xll.DBRW($C$1,S$15,$Q$16,$O$1,Opening!$I$13,Opening!$D$13,$P$1,$A60,$B60,$M$1) -> 0 | T60: =_xll.DBRW($C$1,T$15,$Q$16,$O$1,Opening!$I$13,Opening!$D$13,$P$1,$A60,$B60,$M$1) -> 0 | U60: =_xll.DBRW($C$1,U$15,$Q$16,$O$1,Opening!$I$13,Opening!$D$13,$P$1,$A60,$B60,$M$1) -> 0
C63: CASH FLOW - NON EXPANSION CAPEX
Q64: =$G$13+1 -> 2027 | R64: =$G$13+2 -> 2028 | S64: =$G$13+3 -> 2029 | T64: =$G$13+4 -> 2030 | U64: =$G$13+5 -> 2031
E65: =$G$13&"."&E$11 -> 2026.01 | F65: =$G$13&"."&F$11 -> 2026.02 | G65: =$G$13&"."&G$11 -> 2026.03 | H65: =$G$13&"."&H$11 -> 2026.04 | I65: =$G$13&"."&I$11 -> 2026.05 | J65: =$G$13&"."&J$11 -> 2026.06 | K65: =$G$13&"."&K$11 -> 2026.07 | L65: =$G$13&"."&L$11 -> 2026.08 | ... P65: =$G$13&"."&P$11 -> 2026.12 | Q65: PE | R65: PE | S65: PE | T65: PE | U65: PE
A66: FCF.030.001 | C66: Non Expansion Capex | D66: Total Accounts Line | E66: =_xll.DBRW($C$1,Opening!$G$13,Opening!E$11,$O$1,Opening!$I$13,Opening!$D$13,$P$2,$A66,$D66,$M$1) -> 0 | F66: =_xll.DBRW($C$1,Opening!$G$13,Opening!F$11,$O$1,Opening!$I$13,Opening!$D$13,$P$2,$A66,$D66,$M$1) -> 0 | G66: =_xll.DBRW($C$1,Opening!$G$13,Opening!G$11,$O$1,Opening!$I$13,Opening!$D$13,$P$2,$A66,$D66,$M$1) -> 0 | H66: =_xll.DBRW($C$1,Opening!$G$13,Opening!H$11,$O$1,Opening!$I$13,Opening!$D$13,$P$2,$A66,$D66,$M$1) -> 0 | I66: =_xll.DBRW($C$1,Opening!$G$13,Opening!I$11,$O$1,Opening!$I$13,Opening!$D$13,$P$2,$A66,$D66,$M$1) -> 0 | J66: =_xll.DBRW($C$1,Opening!$G$13,Opening!J$11,$O$1,Opening!$I$13,Opening!$D$13,$P$2,$A66,$D66,$M$1) -> 0 | K66: =_xll.DBRW($C$1,Opening!$G$13,Opening!K$11,$O$1,Opening!$I$13,Opening!$D$13,$P$2,$A66,$D66,$M$1) -> 0 | L66: =_xll.DBRW($C$1,Opening!$G$13,Opening!L$11,$O$1,Opening!$I$13,Opening!$D$13,$P$2,$A66,$D66,$M$1) -> 0 | ... P66: =_xll.DBRW($C$1,Opening!$G$13,Opening!P$11,$O$1,Opening!$I$13,Opening!$D$13,$P$2,$A66,$D66,$M$1) -> 0 | Q66: =_xll.DBRW($C$1,Q$37,$Q$16,$O$1,Opening!$I$13,Opening!$D$13,$P$1,$A66,$D66,$M$1) -> 0 | R66: =_xll.DBRW($C$1,R$37,$Q$16,$O$1,Opening!$I$13,Opening!$D$13,$P$1,$A66,$D66,$M$1) -> 0 | S66: =_xll.DBRW($C$1,S$37,$Q$16,$O$1,Opening!$I$13,Opening!$D$13,$P$1,$A66,$D66,$M$1) -> 0 | T66: =_xll.DBRW($C$1,T$37,$Q$16,$O$1,Opening!$I$13,Opening!$D$13,$P$1,$A66,$D66,$M$1) -> 0 | U66: =_xll.DBRW($C$1,U$37,$Q$16,$O$1,Opening!$I$13,Opening!$D$13,$P$1,$A66,$D66,$M$1) -> 0
A67: FCF.030.001 | B67: ACL.FCF.030.001.01 | C67: Health Safety & Environment | D67: PRODCE010 - Cement | E67: =_xll.DBRW($C$1,Opening!$G$13,Opening!E$11,$O$1,Opening!$I$13,Opening!$D$13,$P$1,$A67,$B67,$M$1) -> 0 | F67: =_xll.DBRW($C$1,Opening!$G$13,Opening!F$11,$O$1,Opening!$I$13,Opening!$D$13,$P$1,$A67,$B67,$M$1) -> 0 | G67: =_xll.DBRW($C$1,Opening!$G$13,Opening!G$11,$O$1,Opening!$I$13,Opening!$D$13,$P$1,$A67,$B67,$M$1) -> 0 | H67: =_xll.DBRW($C$1,Opening!$G$13,Opening!H$11,$O$1,Opening!$I$13,Opening!$D$13,$P$1,$A67,$B67,$M$1) -> 0 | I67: =_xll.DBRW($C$1,Opening!$G$13,Opening!I$11,$O$1,Opening!$I$13,Opening!$D$13,$P$1,$A67,$B67,$M$1) -> 0 | J67: =_xll.DBRW($C$1,Opening!$G$13,Opening!J$11,$O$1,Opening!$I$13,Opening!$D$13,$P$1,$A67,$B67,$M$1) -> 0 | K67: =_xll.DBRW($C$1,Opening!$G$13,Opening!K$11,$O$1,Opening!$I$13,Opening!$D$13,$P$1,$A67,$B67,$M$1) -> 0 | L67: =_xll.DBRW($C$1,Opening!$G$13,Opening!L$11,$O$1,Opening!$I$13,Opening!$D$13,$P$1,$A67,$B67,$M$1) -> 0 | ... P67: =_xll.DBRW($C$1,Opening!$G$13,Opening!P$11,$O$1,Opening!$I$13,Opening!$D$13,$P$1,$A67,$B67,$M$1) -> 0 | Q67: =_xll.DBRW($C$1,Q$15,$Q$16,$O$1,Opening!$I$13,Opening!$D$13,$P$1,$A67,$B67,$M$1) -> 0 | R67: =_xll.DBRW($C$1,R$15,$Q$16,$O$1,Opening!$I$13,Opening!$D$13,$P$1,$A67,$B67,$M$1) -> 0 | S67: =_xll.DBRW($C$1,S$15,$Q$16,$O$1,Opening!$I$13,Opening!$D$13,$P$1,$A67,$B67,$M$1) -> 0 | T67: =_xll.DBRW($C$1,T$15,$Q$16,$O$1,Opening!$I$13,Opening!$D$13,$P$1,$A67,$B67,$M$1) -> 0 | U67: =_xll.DBRW($C$1,U$15,$Q$16,$O$1,Opening!$I$13,Opening!$D$13,$P$1,$A67,$B67,$M$1) -> 0
A68: FCF.030.001 | B68: ACL.FCF.030.001.01 | C68: Health Safety & Environment | D68: PRODAL010 - Ag. Lime | E68: =_xll.DBRW($C$1,Opening!$G$13,Opening!E$11,$O$1,Opening!$I$13,Opening!$D$13,$P$1,$A68,$B68,$M$1) -> 0 | F68: =_xll.DBRW($C$1,Opening!$G$13,Opening!F$11,$O$1,Opening!$I$13,Opening!$D$13,$P$1,$A68,$B68,$M$1) -> 0 | G68: =_xll.DBRW($C$1,Opening!$G$13,Opening!G$11,$O$1,Opening!$I$13,Opening!$D$13,$P$1,$A68,$B68,$M$1) -> 0 | H68: =_xll.DBRW($C$1,Opening!$G$13,Opening!H$11,$O$1,Opening!$I$13,Opening!$D$13,$P$1,$A68,$B68,$M$1) -> 0 | I68: =_xll.DBRW($C$1,Opening!$G$13,Opening!I$11,$O$1,Opening!$I$13,Opening!$D$13,$P$1,$A68,$B68,$M$1) -> 0 | J68: =_xll.DBRW($C$1,Opening!$G$13,Opening!J$11,$O$1,Opening!$I$13,Opening!$D$13,$P$1,$A68,$B68,$M$1) -> 0 | K68: =_xll.DBRW($C$1,Opening!$G$13,Opening!K$11,$O$1,Opening!$I$13,Opening!$D$13,$P$1,$A68,$B68,$M$1) -> 0 | L68: =_xll.DBRW($C$1,Opening!$G$13,Opening!L$11,$O$1,Opening!$I$13,Opening!$D$13,$P$1,$A68,$B68,$M$1) -> 0 | ... P68: =_xll.DBRW($C$1,Opening!$G$13,Opening!P$11,$O$1,Opening!$I$13,Opening!$D$13,$P$1,$A68,$B68,$M$1) -> 0 | Q68: =_xll.DBRW($C$1,Q$15,$Q$16,$O$1,Opening!$I$13,Opening!$D$13,$P$1,$A68,$B68,$M$1) -> 0 | R68: =_xll.DBRW($C$1,R$15,$Q$16,$O$1,Opening!$I$13,Opening!$D$13,$P$1,$A68,$B68,$M$1) -> 0 | S68: =_xll.DBRW($C$1,S$15,$Q$16,$O$1,Opening!$I$13,Opening!$D$13,$P$1,$A68,$B68,$M$1) -> 0 | T68: =_xll.DBRW($C$1,T$15,$Q$16,$O$1,Opening!$I$13,Opening!$D$13,$P$1,$A68,$B68,$M$1) -> 0 | U68: =_xll.DBRW($C$1,U$15,$Q$16,$O$1,Opening!$I$13,Opening!$D$13,$P$1,$A68,$B68,$M$1) -> 0
A69: FCF.030.001 | B69: ACL.FCF.030.001.01 | C69: Health Safety & Environment | D69: PRODAG010 - Aggregates | E69: =_xll.DBRW($C$1,Opening!$G$13,Opening!E$11,$O$1,Opening!$I$13,Opening!$D$13,$P$1,$A69,$B69,$M$1) -> 0 | F69: =_xll.DBRW($C$1,Opening!$G$13,Opening!F$11,$O$1,Opening!$I$13,Opening!$D$13,$P$1,$A69,$B69,$M$1) -> 0 | G69: =_xll.DBRW($C$1,Opening!$G$13,Opening!G$11,$O$1,Opening!$I$13,Opening!$D$13,$P$1,$A69,$B69,$M$1) -> 0 | H69: =_xll.DBRW($C$1,Opening!$G$13,Opening!H$11,$O$1,Opening!$I$13,Opening!$D$13,$P$1,$A69,$B69,$M$1) -> 0 | I69: =_xll.DBRW($C$1,Opening!$G$13,Opening!I$11,$O$1,Opening!$I$13,Opening!$D$13,$P$1,$A69,$B69,$M$1) -> 0 | J69: =_xll.DBRW($C$1,Opening!$G$13,Opening!J$11,$O$1,Opening!$I$13,Opening!$D$13,$P$1,$A69,$B69,$M$1) -> 0 | K69: =_xll.DBRW($C$1,Opening!$G$13,Opening!K$11,$O$1,Opening!$I$13,Opening!$D$13,$P$1,$A69,$B69,$M$1) -> 0 | L69: =_xll.DBRW($C$1,Opening!$G$13,Opening!L$11,$O$1,Opening!$I$13,Opening!$D$13,$P$1,$A69,$B69,$M$1) -> 0 | ... P69: =_xll.DBRW($C$1,Opening!$G$13,Opening!P$11,$O$1,Opening!$I$13,Opening!$D$13,$P$1,$A69,$B69,$M$1) -> 0 | Q69: =_xll.DBRW($C$1,Q$15,$Q$16,$O$1,Opening!$I$13,Opening!$D$13,$P$1,$A69,$B69,$M$1) -> 0 | R69: =_xll.DBRW($C$1,R$15,$Q$16,$O$1,Opening!$I$13,Opening!$D$13,$P$1,$A69,$B69,$M$1) -> 0 | S69: =_xll.DBRW($C$1,S$15,$Q$16,$O$1,Opening!$I$13,Opening!$D$13,$P$1,$A69,$B69,$M$1) -> 0 | T69: =_xll.DBRW($C$1,T$15,$Q$16,$O$1,Opening!$I$13,Opening!$D$13,$P$1,$A69,$B69,$M$1) -> 0 | U69: =_xll.DBRW($C$1,U$15,$Q$16,$O$1,Opening!$I$13,Opening!$D$13,$P$1,$A69,$B69,$M$1) -> 0
A70: FCF.030.001 | B70: ACL.FCF.030.001.01 | C70: Health Safety & Environment | D70: PRODCORP - Corporate | E70: =_xll.DBRW($C$1,Opening!$G$13,Opening!E$11,$O$1,Opening!$I$13,Opening!$D$13,$P$1,$A70,$B70,$M$1) -> 0 | F70: =_xll.DBRW($C$1,Opening!$G$13,Opening!F$11,$O$1,Opening!$I$13,Opening!$D$13,$P$1,$A70,$B70,$M$1) -> 0 | G70: =_xll.DBRW($C$1,Opening!$G$13,Opening!G$11,$O$1,Opening!$I$13,Opening!$D$13,$P$1,$A70,$B70,$M$1) -> 0 | H70: =_xll.DBRW($C$1,Opening!$G$13,Opening!H$11,$O$1,Opening!$I$13,Opening!$D$13,$P$1,$A70,$B70,$M$1) -> 0 | I70: =_xll.DBRW($C$1,Opening!$G$13,Opening!I$11,$O$1,Opening!$I$13,Opening!$D$13,$P$1,$A70,$B70,$M$1) -> 0 | J70: =_xll.DBRW($C$1,Opening!$G$13,Opening!J$11,$O$1,Opening!$I$13,Opening!$D$13,$P$1,$A70,$B70,$M$1) -> 0 | K70: =_xll.DBRW($C$1,Opening!$G$13,Opening!K$11,$O$1,Opening!$I$13,Opening!$D$13,$P$1,$A70,$B70,$M$1) -> 0 | L70: =_xll.DBRW($C$1,Opening!$G$13,Opening!L$11,$O$1,Opening!$I$13,Opening!$D$13,$P$1,$A70,$B70,$M$1) -> 0 | ... P70: =_xll.DBRW($C$1,Opening!$G$13,Opening!P$11,$O$1,Opening!$I$13,Opening!$D$13,$P$1,$A70,$B70,$M$1) -> 0 | Q70: =_xll.DBRW($C$1,Q$15,$Q$16,$O$1,Opening!$I$13,Opening!$D$13,$P$1,$A70,$B70,$M$1) -> 0 | R70: =_xll.DBRW($C$1,R$15,$Q$16,$O$1,Opening!$I$13,Opening!$D$13,$P$1,$A70,$B70,$M$1) -> 0 | S70: =_xll.DBRW($C$1,S$15,$Q$16,$O$1,Opening!$I$13,Opening!$D$13,$P$1,$A70,$B70,$M$1) -> 0 | T70: =_xll.DBRW($C$1,T$15,$Q$16,$O$1,Opening!$I$13,Opening!$D$13,$P$1,$A70,$B70,$M$1) -> 0 | U70: =_xll.DBRW($C$1,U$15,$Q$16,$O$1,Opening!$I$13,Opening!$D$13,$P$1,$A70,$B70,$M$1) -> 0
A71: FCF.030.001 | B71: ACL.FCF.030.001.01 | C71: Health Safety & Environment | D71: PRODLM010 - Lime | E71: =_xll.DBRW($C$1,Opening!$G$13,Opening!E$11,$O$1,Opening!$I$13,Opening!$D$13,$P$1,$A71,$B71,$M$1) -> 0 | F71: =_xll.DBRW($C$1,Opening!$G$13,Opening!F$11,$O$1,Opening!$I$13,Opening!$D$13,$P$1,$A71,$B71,$M$1) -> 0 | G71: =_xll.DBRW($C$1,Opening!$G$13,Opening!G$11,$O$1,Opening!$I$13,Opening!$D$13,$P$1,$A71,$B71,$M$1) -> 0 | H71: =_xll.DBRW($C$1,Opening!$G$13,Opening!H$11,$O$1,Opening!$I$13,Opening!$D$13,$P$1,$A71,$B71,$M$1) -> 0 | I71: =_xll.DBRW($C$1,Opening!$G$13,Opening!I$11,$O$1,Opening!$I$13,Opening!$D$13,$P$1,$A71,$B71,$M$1) -> 0 | J71: =_xll.DBRW($C$1,Opening!$G$13,Opening!J$11,$O$1,Opening!$I$13,Opening!$D$13,$P$1,$A71,$B71,$M$1) -> 0 | K71: =_xll.DBRW($C$1,Opening!$G$13,Opening!K$11,$O$1,Opening!$I$13,Opening!$D$13,$P$1,$A71,$B71,$M$1) -> 0 | L71: =_xll.DBRW($C$1,Opening!$G$13,Opening!L$11,$O$1,Opening!$I$13,Opening!$D$13,$P$1,$A71,$B71,$M$1) -> 0 | ... P71: =_xll.DBRW($C$1,Opening!$G$13,Opening!P$11,$O$1,Opening!$I$13,Opening!$D$13,$P$1,$A71,$B71,$M$1) -> 0 | Q71: =_xll.DBRW($C$1,Q$15,$Q$16,$O$1,Opening!$I$13,Opening!$D$13,$P$1,$A71,$B71,$M$1) -> 0 | R71: =_xll.DBRW($C$1,R$15,$Q$16,$O$1,Opening!$I$13,Opening!$D$13,$P$1,$A71,$B71,$M$1) -> 0 | S71: =_xll.DBRW($C$1,S$15,$Q$16,$O$1,Opening!$I$13,Opening!$D$13,$P$1,$A71,$B71,$M$1) -> 0 | T71: =_xll.DBRW($C$1,T$15,$Q$16,$O$1,Opening!$I$13,Opening!$D$13,$P$1,$A71,$B71,$M$1) -> 0 | U71: =_xll.DBRW($C$1,U$15,$Q$16,$O$1,Opening!$I$13,Opening!$D$13,$P$1,$A71,$B71,$M$1) -> 0
A72: FCF.030.001 | B72: ACL.FCF.030.001.01 | C72: Health Safety & Environment | D72: PRODMZ010 - Motz | E72: =_xll.DBRW($C$1,Opening!$G$13,Opening!E$11,$O$1,Opening!$I$13,Opening!$D$13,$P$1,$A72,$B72,$M$1) -> 0 | F72: =_xll.DBRW($C$1,Opening!$G$13,Opening!F$11,$O$1,Opening!$I$13,Opening!$D$13,$P$1,$A72,$B72,$M$1) -> 0 | G72: =_xll.DBRW($C$1,Opening!$G$13,Opening!G$11,$O$1,Opening!$I$13,Opening!$D$13,$P$1,$A72,$B72,$M$1) -> 0 | H72: =_xll.DBRW($C$1,Opening!$G$13,Opening!H$11,$O$1,Opening!$I$13,Opening!$D$13,$P$1,$A72,$B72,$M$1) -> 0 | I72: =_xll.DBRW($C$1,Opening!$G$13,Opening!I$11,$O$1,Opening!$I$13,Opening!$D$13,$P$1,$A72,$B72,$M$1) -> 0 | J72: =_xll.DBRW($C$1,Opening!$G$13,Opening!J$11,$O$1,Opening!$I$13,Opening!$D$13,$P$1,$A72,$B72,$M$1) -> 0 | K72: =_xll.DBRW($C$1,Opening!$G$13,Opening!K$11,$O$1,Opening!$I$13,Opening!$D$13,$P$1,$A72,$B72,$M$1) -> 0 | L72: =_xll.DBRW($C$1,Opening!$G$13,Opening!L$11,$O$1,Opening!$I$13,Opening!$D$13,$P$1,$A72,$B72,$M$1) -> 0 | ... P72: =_xll.DBRW($C$1,Opening!$G$13,Opening!P$11,$O$1,Opening!$I$13,Opening!$D$13,$P$1,$A72,$B72,$M$1) -> 0 | Q72: =_xll.DBRW($C$1,Q$15,$Q$16,$O$1,Opening!$I$13,Opening!$D$13,$P$1,$A72,$B72,$M$1) -> 0 | R72: =_xll.DBRW($C$1,R$15,$Q$16,$O$1,Opening!$I$13,Opening!$D$13,$P$1,$A72,$B72,$M$1) -> 0 | S72: =_xll.DBRW($C$1,S$15,$Q$16,$O$1,Opening!$I$13,Opening!$D$13,$P$1,$A72,$B72,$M$1) -> 0 | T72: =_xll.DBRW($C$1,T$15,$Q$16,$O$1,Opening!$I$13,Opening!$D$13,$P$1,$A72,$B72,$M$1) -> 0 | U72: =_xll.DBRW($C$1,U$15,$Q$16,$O$1,Opening!$I$13,Opening!$D$13,$P$1,$A72,$B72,$M$1) -> 0
A73: FCF.030.001 | B73: ACL.FCF.030.001.01 | C73: Health Safety & Environment | D73: PRODMT010 - Mortars | E73: =_xll.DBRW($C$1,Opening!$G$13,Opening!E$11,$O$1,Opening!$I$13,Opening!$D$13,$P$1,$A73,$B73,$M$1) -> 0 | F73: =_xll.DBRW($C$1,Opening!$G$13,Opening!F$11,$O$1,Opening!$I$13,Opening!$D$13,$P$1,$A73,$B73,$M$1) -> 0 | G73: =_xll.DBRW($C$1,Opening!$G$13,Opening!G$11,$O$1,Opening!$I$13,Opening!$D$13,$P$1,$A73,$B73,$M$1) -> 0 | H73: =_xll.DBRW($C$1,Opening!$G$13,Opening!H$11,$O$1,Opening!$I$13,Opening!$D$13,$P$1,$A73,$B73,$M$1) -> 0 | I73: =_xll.DBRW($C$1,Opening!$G$13,Opening!I$11,$O$1,Opening!$I$13,Opening!$D$13,$P$1,$A73,$B73,$M$1) -> 0 | J73: =_xll.DBRW($C$1,Opening!$G$13,Opening!J$11,$O$1,Opening!$I$13,Opening!$D$13,$P$1,$A73,$B73,$M$1) -> 0 | K73: =_xll.DBRW($C$1,Opening!$G$13,Opening!K$11,$O$1,Opening!$I$13,Opening!$D$13,$P$1,$A73,$B73,$M$1) -> 0 | L73: =_xll.DBRW($C$1,Opening!$G$13,Opening!L$11,$O$1,Opening!$I$13,Opening!$D$13,$P$1,$A73,$B73,$M$1) -> 0 | ... P73: =_xll.DBRW($C$1,Opening!$G$13,Opening!P$11,$O$1,Opening!$I$13,Opening!$D$13,$P$1,$A73,$B73,$M$1) -> 0 | Q73: =_xll.DBRW($C$1,Q$15,$Q$16,$O$1,Opening!$I$13,Opening!$D$13,$P$1,$A73,$B73,$M$1) -> 0 | R73: =_xll.DBRW($C$1,R$15,$Q$16,$O$1,Opening!$I$13,Opening!$D$13,$P$1,$A73,$B73,$M$1) -> 0 | S73: =_xll.DBRW($C$1,S$15,$Q$16,$O$1,Opening!$I$13,Opening!$D$13,$P$1,$A73,$B73,$M$1) -> 0 | T73: =_xll.DBRW($C$1,T$15,$Q$16,$O$1,Opening!$I$13,Opening!$D$13,$P$1,$A73,$B73,$M$1) -> 0 | U73: =_xll.DBRW($C$1,U$15,$Q$16,$O$1,Opening!$I$13,Opening!$D$13,$P$1,$A73,$B73,$M$1) -> 0
A74: FCF.030.001 | B74: ACL.FCF.030.001.01 | C74: Health Safety & Environment | D74: PRODRM010 - Ready Mix | E74: =_xll.DBRW($C$1,Opening!$G$13,Opening!E$11,$O$1,Opening!$I$13,Opening!$D$13,$P$1,$A74,$B74,$M$1) -> 0 | F74: =_xll.DBRW($C$1,Opening!$G$13,Opening!F$11,$O$1,Opening!$I$13,Opening!$D$13,$P$1,$A74,$B74,$M$1) -> 0 | G74: =_xll.DBRW($C$1,Opening!$G$13,Opening!G$11,$O$1,Opening!$I$13,Opening!$D$13,$P$1,$A74,$B74,$M$1) -> 0 | H74: =_xll.DBRW($C$1,Opening!$G$13,Opening!H$11,$O$1,Opening!$I$13,Opening!$D$13,$P$1,$A74,$B74,$M$1) -> 0 | I74: =_xll.DBRW($C$1,Opening!$G$13,Opening!I$11,$O$1,Opening!$I$13,Opening!$D$13,$P$1,$A74,$B74,$M$1) -> 0 | J74: =_xll.DBRW($C$1,Opening!$G$13,Opening!J$11,$O$1,Opening!$I$13,Opening!$D$13,$P$1,$A74,$B74,$M$1) -> 0 | K74: =_xll.DBRW($C$1,Opening!$G$13,Opening!K$11,$O$1,Opening!$I$13,Opening!$D$13,$P$1,$A74,$B74,$M$1) -> 0 | L74: =_xll.DBRW($C$1,Opening!$G$13,Opening!L$11,$O$1,Opening!$I$13,Opening!$D$13,$P$1,$A74,$B74,$M$1) -> 0 | ... P74: =_xll.DBRW($C$1,Opening!$G$13,Opening!P$11,$O$1,Opening!$I$13,Opening!$D$13,$P$1,$A74,$B74,$M$1) -> 0 | Q74: =_xll.DBRW($C$1,Q$15,$Q$16,$O$1,Opening!$I$13,Opening!$D$13,$P$1,$A74,$B74,$M$1) -> 0 | R74: =_xll.DBRW($C$1,R$15,$Q$16,$O$1,Opening!$I$13,Opening!$D$13,$P$1,$A74,$B74,$M$1) -> 0 | S74: =_xll.DBRW($C$1,S$15,$Q$16,$O$1,Opening!$I$13,Opening!$D$13,$P$1,$A74,$B74,$M$1) -> 0 | T74: =_xll.DBRW($C$1,T$15,$Q$16,$O$1,Opening!$I$13,Opening!$D$13,$P$1,$A74,$B74,$M$1) -> 0 | U74: =_xll.DBRW($C$1,U$15,$Q$16,$O$1,Opening!$I$13,Opening!$D$13,$P$1,$A74,$B74,$M$1) -> 0
A75: FCF.030.001 | B75: ACL.FCF.030.001.01 | C75: Health Safety & Environment | D75: PROD099 - Others | E75: =_xll.DBRW($C$1,Opening!$G$13,Opening!E$11,$O$1,Opening!$I$13,Opening!$D$13,$P$1,$A75,$B75,$M$1) -> 0 | F75: =_xll.DBRW($C$1,Opening!$G$13,Opening!F$11,$O$1,Opening!$I$13,Opening!$D$13,$P$1,$A75,$B75,$M$1) -> 0 | G75: =_xll.DBRW($C$1,Opening!$G$13,Opening!G$11,$O$1,Opening!$I$13,Opening!$D$13,$P$1,$A75,$B75,$M$1) -> 0 | H75: =_xll.DBRW($C$1,Opening!$G$13,Opening!H$11,$O$1,Opening!$I$13,Opening!$D$13,$P$1,$A75,$B75,$M$1) -> 0 | I75: =_xll.DBRW($C$1,Opening!$G$13,Opening!I$11,$O$1,Opening!$I$13,Opening!$D$13,$P$1,$A75,$B75,$M$1) -> 0 | J75: =_xll.DBRW($C$1,Opening!$G$13,Opening!J$11,$O$1,Opening!$I$13,Opening!$D$13,$P$1,$A75,$B75,$M$1) -> 0 | K75: =_xll.DBRW($C$1,Opening!$G$13,Opening!K$11,$O$1,Opening!$I$13,Opening!$D$13,$P$1,$A75,$B75,$M$1) -> 0 | L75: =_xll.DBRW($C$1,Opening!$G$13,Opening!L$11,$O$1,Opening!$I$13,Opening!$D$13,$P$1,$A75,$B75,$M$1) -> 0 | ... P75: =_xll.DBRW($C$1,Opening!$G$13,Opening!P$11,$O$1,Opening!$I$13,Opening!$D$13,$P$1,$A75,$B75,$M$1) -> 0 | Q75: =_xll.DBRW($C$1,Q$15,$Q$16,$O$1,Opening!$I$13,Opening!$D$13,$P$1,$A75,$B75,$M$1) -> 0 | R75: =_xll.DBRW($C$1,R$15,$Q$16,$O$1,Opening!$I$13,Opening!$D$13,$P$1,$A75,$B75,$M$1) -> 0 | S75: =_xll.DBRW($C$1,S$15,$Q$16,$O$1,Opening!$I$13,Opening!$D$13,$P$1,$A75,$B75,$M$1) -> 0 | T75: =_xll.DBRW($C$1,T$15,$Q$16,$O$1,Opening!$I$13,Opening!$D$13,$P$1,$A75,$B75,$M$1) -> 0 | U75: =_xll.DBRW($C$1,U$15,$Q$16,$O$1,Opening!$I$13,Opening!$D$13,$P$1,$A75,$B75,$M$1) -> 0
A76: FCF.030.001 | B76: ACL.FCF.030.001.02 | C76: Non expansion capex - IT | D76: PRODCE010 - Cement | E76: =_xll.DBRW($C$1,Opening!$G$13,Opening!E$11,$O$1,Opening!$I$13,Opening!$D$13,$P$1,$A76,$B76,$M$1) -> 0 | F76: =_xll.DBRW($C$1,Opening!$G$13,Opening!F$11,$O$1,Opening!$I$13,Opening!$D$13,$P$1,$A76,$B76,$M$1) -> 0 | G76: =_xll.DBRW($C$1,Opening!$G$13,Opening!G$11,$O$1,Opening!$I$13,Opening!$D$13,$P$1,$A76,$B76,$M$1) -> 0 | H76: =_xll.DBRW($C$1,Opening!$G$13,Opening!H$11,$O$1,Opening!$I$13,Opening!$D$13,$P$1,$A76,$B76,$M$1) -> 0 | I76: =_xll.DBRW($C$1,Opening!$G$13,Opening!I$11,$O$1,Opening!$I$13,Opening!$D$13,$P$1,$A76,$B76,$M$1) -> 0 | J76: =_xll.DBRW($C$1,Opening!$G$13,Opening!J$11,$O$1,Opening!$I$13,Opening!$D$13,$P$1,$A76,$B76,$M$1) -> 0 | K76: =_xll.DBRW($C$1,Opening!$G$13,Opening!K$11,$O$1,Opening!$I$13,Opening!$D$13,$P$1,$A76,$B76,$M$1) -> 0 | L76: =_xll.DBRW($C$1,Opening!$G$13,Opening!L$11,$O$1,Opening!$I$13,Opening!$D$13,$P$1,$A76,$B76,$M$1) -> 0 | ... P76: =_xll.DBRW($C$1,Opening!$G$13,Opening!P$11,$O$1,Opening!$I$13,Opening!$D$13,$P$1,$A76,$B76,$M$1) -> 0 | Q76: =_xll.DBRW($C$1,Q$15,$Q$16,$O$1,Opening!$I$13,Opening!$D$13,$P$1,$A76,$B76,$M$1) -> 0 | R76: =_xll.DBRW($C$1,R$15,$Q$16,$O$1,Opening!$I$13,Opening!$D$13,$P$1,$A76,$B76,$M$1) -> 0 | S76: =_xll.DBRW($C$1,S$15,$Q$16,$O$1,Opening!$I$13,Opening!$D$13,$P$1,$A76,$B76,$M$1) -> 0 | T76: =_xll.DBRW($C$1,T$15,$Q$16,$O$1,Opening!$I$13,Opening!$D$13,$P$1,$A76,$B76,$M$1) -> 0 | U76: =_xll.DBRW($C$1,U$15,$Q$16,$O$1,Opening!$I$13,Opening!$D$13,$P$1,$A76,$B76,$M$1) -> 0
A77: FCF.030.001 | B77: ACL.FCF.030.001.02 | C77: Non expansion capex - IT | D77: PRODAL010 - Ag. Lime | E77: =_xll.DBRW($C$1,Opening!$G$13,Opening!E$11,$O$1,Opening!$I$13,Opening!$D$13,$P$1,$A77,$B77,$M$1) -> 0 | F77: =_xll.DBRW($C$1,Opening!$G$13,Opening!F$11,$O$1,Opening!$I$13,Opening!$D$13,$P$1,$A77,$B77,$M$1) -> 0 | G77: =_xll.DBRW($C$1,Opening!$G$13,Opening!G$11,$O$1,Opening!$I$13,Opening!$D$13,$P$1,$A77,$B77,$M$1) -> 0 | H77: =_xll.DBRW($C$1,Opening!$G$13,Opening!H$11,$O$1,Opening!$I$13,Opening!$D$13,$P$1,$A77,$B77,$M$1) -> 0 | I77: =_xll.DBRW($C$1,Opening!$G$13,Opening!I$11,$O$1,Opening!$I$13,Opening!$D$13,$P$1,$A77,$B77,$M$1) -> 0 | J77: =_xll.DBRW($C$1,Opening!$G$13,Opening!J$11,$O$1,Opening!$I$13,Opening!$D$13,$P$1,$A77,$B77,$M$1) -> 0 | K77: =_xll.DBRW($C$1,Opening!$G$13,Opening!K$11,$O$1,Opening!$I$13,Opening!$D$13,$P$1,$A77,$B77,$M$1) -> 0 | L77: =_xll.DBRW($C$1,Opening!$G$13,Opening!L$11,$O$1,Opening!$I$13,Opening!$D$13,$P$1,$A77,$B77,$M$1) -> 0 | ... P77: =_xll.DBRW($C$1,Opening!$G$13,Opening!P$11,$O$1,Opening!$I$13,Opening!$D$13,$P$1,$A77,$B77,$M$1) -> 0 | Q77: =_xll.DBRW($C$1,Q$15,$Q$16,$O$1,Opening!$I$13,Opening!$D$13,$P$1,$A77,$B77,$M$1) -> 0 | R77: =_xll.DBRW($C$1,R$15,$Q$16,$O$1,Opening!$I$13,Opening!$D$13,$P$1,$A77,$B77,$M$1) -> 0 | S77: =_xll.DBRW($C$1,S$15,$Q$16,$O$1,Opening!$I$13,Opening!$D$13,$P$1,$A77,$B77,$M$1) -> 0 | T77: =_xll.DBRW($C$1,T$15,$Q$16,$O$1,Opening!$I$13,Opening!$D$13,$P$1,$A77,$B77,$M$1) -> 0 | U77: =_xll.DBRW($C$1,U$15,$Q$16,$O$1,Opening!$I$13,Opening!$D$13,$P$1,$A77,$B77,$M$1) -> 0
A78: FCF.030.001 | B78: ACL.FCF.030.001.02 | C78: Non expansion capex - IT | D78: PRODAG010 - Aggregates | E78: =_xll.DBRW($C$1,Opening!$G$13,Opening!E$11,$O$1,Opening!$I$13,Opening!$D$13,$P$1,$A78,$B78,$M$1) -> 0 | F78: =_xll.DBRW($C$1,Opening!$G$13,Opening!F$11,$O$1,Opening!$I$13,Opening!$D$13,$P$1,$A78,$B78,$M$1) -> 0 | G78: =_xll.DBRW($C$1,Opening!$G$13,Opening!G$11,$O$1,Opening!$I$13,Opening!$D$13,$P$1,$A78,$B78,$M$1) -> 0 | H78: =_xll.DBRW($C$1,Opening!$G$13,Opening!H$11,$O$1,Opening!$I$13,Opening!$D$13,$P$1,$A78,$B78,$M$1) -> 0 | I78: =_xll.DBRW($C$1,Opening!$G$13,Opening!I$11,$O$1,Opening!$I$13,Opening!$D$13,$P$1,$A78,$B78,$M$1) -> 0 | J78: =_xll.DBRW($C$1,Opening!$G$13,Opening!J$11,$O$1,Opening!$I$13,Opening!$D$13,$P$1,$A78,$B78,$M$1) -> 0 | K78: =_xll.DBRW($C$1,Opening!$G$13,Opening!K$11,$O$1,Opening!$I$13,Opening!$D$13,$P$1,$A78,$B78,$M$1) -> 0 | L78: =_xll.DBRW($C$1,Opening!$G$13,Opening!L$11,$O$1,Opening!$I$13,Opening!$D$13,$P$1,$A78,$B78,$M$1) -> 0 | ... P78: =_xll.DBRW($C$1,Opening!$G$13,Opening!P$11,$O$1,Opening!$I$13,Opening!$D$13,$P$1,$A78,$B78,$M$1) -> 0 | Q78: =_xll.DBRW($C$1,Q$15,$Q$16,$O$1,Opening!$I$13,Opening!$D$13,$P$1,$A78,$B78,$M$1) -> 0 | R78: =_xll.DBRW($C$1,R$15,$Q$16,$O$1,Opening!$I$13,Opening!$D$13,$P$1,$A78,$B78,$M$1) -> 0 | S78: =_xll.DBRW($C$1,S$15,$Q$16,$O$1,Opening!$I$13,Opening!$D$13,$P$1,$A78,$B78,$M$1) -> 0 | T78: =_xll.DBRW($C$1,T$15,$Q$16,$O$1,Opening!$I$13,Opening!$D$13,$P$1,$A78,$B78,$M$1) -> 0 | U78: =_xll.DBRW($C$1,U$15,$Q$16,$O$1,Opening!$I$13,Opening!$D$13,$P$1,$A78,$B78,$M$1) -> 0
... A111: FCF.030.001 | B111: ACL.FCF.030.001.05 | C111: Sustaining | D111: PROD099 - Others | E111: =_xll.DBRW($C$1,Opening!$G$13,Opening!E$11,$O$1,Opening!$I$13,Opening!$D$13,$P$1,$A111,$B111,$M$1) -> 0 | F111: =_xll.DBRW($C$1,Opening!$G$13,Opening!F$11,$O$1,Opening!$I$13,Opening!$D$13,$P$1,$A111,$B111,$M$1) -> 0 | G111: =_xll.DBRW($C$1,Opening!$G$13,Opening!G$11,$O$1,Opening!$I$13,Opening!$D$13,$P$1,$A111,$B111,$M$1) -> 0 | H111: =_xll.DBRW($C$1,Opening!$G$13,Opening!H$11,$O$1,Opening!$I$13,Opening!$D$13,$P$1,$A111,$B111,$M$1) -> 0 | I111: =_xll.DBRW($C$1,Opening!$G$13,Opening!I$11,$O$1,Opening!$I$13,Opening!$D$13,$P$1,$A111,$B111,$M$1) -> 0 | J111: =_xll.DBRW($C$1,Opening!$G$13,Opening!J$11,$O$1,Opening!$I$13,Opening!$D$13,$P$1,$A111,$B111,$M$1) -> 0 | K111: =_xll.DBRW($C$1,Opening!$G$13,Opening!K$11,$O$1,Opening!$I$13,Opening!$D$13,$P$1,$A111,$B111,$M$1) -> 0 | L111: =_xll.DBRW($C$1,Opening!$G$13,Opening!L$11,$O$1,Opening!$I$13,Opening!$D$13,$P$1,$A111,$B111,$M$1) -> 0 | ... P111: =_xll.DBRW($C$1,Opening!$G$13,Opening!P$11,$O$1,Opening!$I$13,Opening!$D$13,$P$1,$A111,$B111,$M$1) -> 0 | Q111: =_xll.DBRW($C$1,Q$15,$Q$16,$O$1,Opening!$I$13,Opening!$D$13,$P$1,$A111,$B111,$M$1) -> 0 | R111: =_xll.DBRW($C$1,R$15,$Q$16,$O$1,Opening!$I$13,Opening!$D$13,$P$1,$A111,$B111,$M$1) -> 0 | S111: =_xll.DBRW($C$1,S$15,$Q$16,$O$1,Opening!$I$13,Opening!$D$13,$P$1,$A111,$B111,$M$1) -> 0 | T111: =_xll.DBRW($C$1,T$15,$Q$16,$O$1,Opening!$I$13,Opening!$D$13,$P$1,$A111,$B111,$M$1) -> 0 | U111: =_xll.DBRW($C$1,U$15,$Q$16,$O$1,Opening!$I$13,Opening!$D$13,$P$1,$A111,$B111,$M$1) -> 0
C113: CASH FLOW - OTHER
Q114: =$G$13+1 -> 2027 | R114: =$G$13+2 -> 2028 | S114: =$G$13+3 -> 2029 | T114: =$G$13+4 -> 2030 | U114: =$G$13+5 -> 2031
E115: =$G$13&"."&E$11 -> 2026.01 | F115: =$G$13&"."&F$11 -> 2026.02 | G115: =$G$13&"."&G$11 -> 2026.03 | H115: =$G$13&"."&H$11 -> 2026.04 | I115: =$G$13&"."&I$11 -> 2026.05 | J115: =$G$13&"."&J$11 -> 2026.06 | K115: =$G$13&"."&K$11 -> 2026.07 | L115: =$G$13&"."&L$11 -> 2026.08 | ... P115: =$G$13&"."&P$11 -> 2026.12 | Q115: PE | R115: PE | S115: PE | T115: PE | U115: PE
A116: FCF.099.026 | C116: Other Change in Assets / Current Liabilities | D116: Total Accounts Line | E116: =_xll.DBRW($C$1,Opening!$G$13,Opening!E$11,$O$1,Opening!$I$13,Opening!$D$13,$P$2,$A116,$D116,$M$1) -> 0 | F116: =_xll.DBRW($C$1,Opening!$G$13,Opening!F$11,$O$1,Opening!$I$13,Opening!$D$13,$P$2,$A116,$D116,$M$1) -> 0 | G116: =_xll.DBRW($C$1,Opening!$G$13,Opening!G$11,$O$1,Opening!$I$13,Opening!$D$13,$P$2,$A116,$D116,$M$1) -> 0 | H116: =_xll.DBRW($C$1,Opening!$G$13,Opening!H$11,$O$1,Opening!$I$13,Opening!$D$13,$P$2,$A116,$D116,$M$1) -> 0 | I116: =_xll.DBRW($C$1,Opening!$G$13,Opening!I$11,$O$1,Opening!$I$13,Opening!$D$13,$P$2,$A116,$D116,$M$1) -> 0 | J116: =_xll.DBRW($C$1,Opening!$G$13,Opening!J$11,$O$1,Opening!$I$13,Opening!$D$13,$P$2,$A116,$D116,$M$1) -> 0 | K116: =_xll.DBRW($C$1,Opening!$G$13,Opening!K$11,$O$1,Opening!$I$13,Opening!$D$13,$P$2,$A116,$D116,$M$1) -> 0 | L116: =_xll.DBRW($C$1,Opening!$G$13,Opening!L$11,$O$1,Opening!$I$13,Opening!$D$13,$P$2,$A116,$D116,$M$1) -> 0 | ... P116: =_xll.DBRW($C$1,Opening!$G$13,Opening!P$11,$O$1,Opening!$I$13,Opening!$D$13,$P$2,$A116,$D116,$M$1) -> 0 | Q116: =_xll.DBRW($C$1,Q$37,$Q$16,$O$1,Opening!$I$13,Opening!$D$13,$P$1,$A116,$D116,$M$1) -> 0 | R116: =_xll.DBRW($C$1,R$37,$Q$16,$O$1,Opening!$I$13,Opening!$D$13,$P$1,$A116,$D116,$M$1) -> 0 | S116: =_xll.DBRW($C$1,S$37,$Q$16,$O$1,Opening!$I$13,Opening!$D$13,$P$1,$A116,$D116,$M$1) -> 0 | T116: =_xll.DBRW($C$1,T$37,$Q$16,$O$1,Opening!$I$13,Opening!$D$13,$P$1,$A116,$D116,$M$1) -> 0 | U116: =_xll.DBRW($C$1,U$37,$Q$16,$O$1,Opening!$I$13,Opening!$D$13,$P$1,$A116,$D116,$M$1) -> 0
A117: FCF.099.026 | B117: ACL.FCF.050.001.01 | C117: Other Change in Assets / Current Liabilities | D117: Other - ARO | E117: =_xll.DBRW($C$1,Opening!$G$13,Opening!E$11,$O$1,Opening!$I$13,Opening!$D$13,$P$1,$A117,$B117,$M$1) -> 0 | F117: =_xll.DBRW($C$1,Opening!$G$13,Opening!F$11,$O$1,Opening!$I$13,Opening!$D$13,$P$1,$A117,$B117,$M$1) -> 0 | G117: =_xll.DBRW($C$1,Opening!$G$13,Opening!G$11,$O$1,Opening!$I$13,Opening!$D$13,$P$1,$A117,$B117,$M$1) -> 0 | H117: =_xll.DBRW($C$1,Opening!$G$13,Opening!H$11,$O$1,Opening!$I$13,Opening!$D$13,$P$1,$A117,$B117,$M$1) -> 0 | I117: =_xll.DBRW($C$1,Opening!$G$13,Opening!I$11,$O$1,Opening!$I$13,Opening!$D$13,$P$1,$A117,$B117,$M$1) -> 0 | J117: =_xll.DBRW($C$1,Opening!$G$13,Opening!J$11,$O$1,Opening!$I$13,Opening!$D$13,$P$1,$A117,$B117,$M$1) -> 0 | K117: =_xll.DBRW($C$1,Opening!$G$13,Opening!K$11,$O$1,Opening!$I$13,Opening!$D$13,$P$1,$A117,$B117,$M$1) -> 0 | L117: =_xll.DBRW($C$1,Opening!$G$13,Opening!L$11,$O$1,Opening!$I$13,Opening!$D$13,$P$1,$A117,$B117,$M$1) -> 0 | ... P117: =_xll.DBRW($C$1,Opening!$G$13,Opening!P$11,$O$1,Opening!$I$13,Opening!$D$13,$P$1,$A117,$B117,$M$1) -> 0 | Q117: =_xll.DBRW($C$1,Q$15,$Q$16,$O$1,Opening!$I$13,Opening!$D$13,$P$1,$A117,$B117,$M$1) -> 0 | R117: =_xll.DBRW($C$1,R$15,$Q$16,$O$1,Opening!$I$13,Opening!$D$13,$P$1,$A117,$B117,$M$1) -> 0 | S117: =_xll.DBRW($C$1,S$15,$Q$16,$O$1,Opening!$I$13,Opening!$D$13,$P$1,$A117,$B117,$M$1) -> 0 | T117: =_xll.DBRW($C$1,T$15,$Q$16,$O$1,Opening!$I$13,Opening!$D$13,$P$1,$A117,$B117,$M$1) -> 0 | U117: =_xll.DBRW($C$1,U$15,$Q$16,$O$1,Opening!$I$13,Opening!$D$13,$P$1,$A117,$B117,$M$1) -> 0
A118: FCF.099.026 | B118: ACL.FCF.050.001.02 | C118: Other Change in Assets / Current Liabilities | D118: Other - Asset Write-off | E118: =_xll.DBRW($C$1,Opening!$G$13,Opening!E$11,$O$1,Opening!$I$13,Opening!$D$13,$P$1,$A118,$B118,$M$1) -> 0 | F118: =_xll.DBRW($C$1,Opening!$G$13,Opening!F$11,$O$1,Opening!$I$13,Opening!$D$13,$P$1,$A118,$B118,$M$1) -> 0 | G118: =_xll.DBRW($C$1,Opening!$G$13,Opening!G$11,$O$1,Opening!$I$13,Opening!$D$13,$P$1,$A118,$B118,$M$1) -> 0 | H118: =_xll.DBRW($C$1,Opening!$G$13,Opening!H$11,$O$1,Opening!$I$13,Opening!$D$13,$P$1,$A118,$B118,$M$1) -> 0 | I118: =_xll.DBRW($C$1,Opening!$G$13,Opening!I$11,$O$1,Opening!$I$13,Opening!$D$13,$P$1,$A118,$B118,$M$1) -> 0 | J118: =_xll.DBRW($C$1,Opening!$G$13,Opening!J$11,$O$1,Opening!$I$13,Opening!$D$13,$P$1,$A118,$B118,$M$1) -> 0 | K118: =_xll.DBRW($C$1,Opening!$G$13,Opening!K$11,$O$1,Opening!$I$13,Opening!$D$13,$P$1,$A118,$B118,$M$1) -> 0 | L118: =_xll.DBRW($C$1,Opening!$G$13,Opening!L$11,$O$1,Opening!$I$13,Opening!$D$13,$P$1,$A118,$B118,$M$1) -> 0 | ... P118: =_xll.DBRW($C$1,Opening!$G$13,Opening!P$11,$O$1,Opening!$I$13,Opening!$D$13,$P$1,$A118,$B118,$M$1) -> 0 | Q118: =_xll.DBRW($C$1,Q$15,$Q$16,$O$1,Opening!$I$13,Opening!$D$13,$P$1,$A118,$B118,$M$1) -> 0 | R118: =_xll.DBRW($C$1,R$15,$Q$16,$O$1,Opening!$I$13,Opening!$D$13,$P$1,$A118,$B118,$M$1) -> 0 | S118: =_xll.DBRW($C$1,S$15,$Q$16,$O$1,Opening!$I$13,Opening!$D$13,$P$1,$A118,$B118,$M$1) -> 0 | T118: =_xll.DBRW($C$1,T$15,$Q$16,$O$1,Opening!$I$13,Opening!$D$13,$P$1,$A118,$B118,$M$1) -> 0 | U118: =_xll.DBRW($C$1,U$15,$Q$16,$O$1,Opening!$I$13,Opening!$D$13,$P$1,$A118,$B118,$M$1) -> 0
A119: FCF.099.026 | B119: ACL.FCF.050.001.03 | C119: Other Change in Assets / Current Liabilities | D119: DIFAL | E119: =_xll.DBRW($C$1,Opening!$G$13,Opening!E$11,$O$1,Opening!$I$13,Opening!$D$13,$P$1,$A119,$B119,$M$1) -> 0 | F119: =_xll.DBRW($C$1,Opening!$G$13,Opening!F$11,$O$1,Opening!$I$13,Opening!$D$13,$P$1,$A119,$B119,$M$1) -> 0 | G119: =_xll.DBRW($C$1,Opening!$G$13,Opening!G$11,$O$1,Opening!$I$13,Opening!$D$13,$P$1,$A119,$B119,$M$1) -> 0 | H119: =_xll.DBRW($C$1,Opening!$G$13,Opening!H$11,$O$1,Opening!$I$13,Opening!$D$13,$P$1,$A119,$B119,$M$1) -> 0 | I119: =_xll.DBRW($C$1,Opening!$G$13,Opening!I$11,$O$1,Opening!$I$13,Opening!$D$13,$P$1,$A119,$B119,$M$1) -> 0 | J119: =_xll.DBRW($C$1,Opening!$G$13,Opening!J$11,$O$1,Opening!$I$13,Opening!$D$13,$P$1,$A119,$B119,$M$1) -> 0 | K119: =_xll.DBRW($C$1,Opening!$G$13,Opening!K$11,$O$1,Opening!$I$13,Opening!$D$13,$P$1,$A119,$B119,$M$1) -> 0 | L119: =_xll.DBRW($C$1,Opening!$G$13,Opening!L$11,$O$1,Opening!$I$13,Opening!$D$13,$P$1,$A119,$B119,$M$1) -> 0 | ... P119: =_xll.DBRW($C$1,Opening!$G$13,Opening!P$11,$O$1,Opening!$I$13,Opening!$D$13,$P$1,$A119,$B119,$M$1) -> 0 | Q119: =_xll.DBRW($C$1,Q$15,$Q$16,$O$1,Opening!$I$13,Opening!$D$13,$P$1,$A119,$B119,$M$1) -> 0 | R119: =_xll.DBRW($C$1,R$15,$Q$16,$O$1,Opening!$I$13,Opening!$D$13,$P$1,$A119,$B119,$M$1) -> 0 | S119: =_xll.DBRW($C$1,S$15,$Q$16,$O$1,Opening!$I$13,Opening!$D$13,$P$1,$A119,$B119,$M$1) -> 0 | T119: =_xll.DBRW($C$1,T$15,$Q$16,$O$1,Opening!$I$13,Opening!$D$13,$P$1,$A119,$B119,$M$1) -> 0 | U119: =_xll.DBRW($C$1,U$15,$Q$16,$O$1,Opening!$I$13,Opening!$D$13,$P$1,$A119,$B119,$M$1) -> 0
A120: FCF.099.026 | B120: ACL.FCF.050.001.04 | C120: Other Change in Assets / Current Liabilities | D120: Legal Deposits | E120: =_xll.DBRW($C$1,Opening!$G$13,Opening!E$11,$O$1,Opening!$I$13,Opening!$D$13,$P$1,$A120,$B120,$M$1) -> 0 | F120: =_xll.DBRW($C$1,Opening!$G$13,Opening!F$11,$O$1,Opening!$I$13,Opening!$D$13,$P$1,$A120,$B120,$M$1) -> 0 | G120: =_xll.DBRW($C$1,Opening!$G$13,Opening!G$11,$O$1,Opening!$I$13,Opening!$D$13,$P$1,$A120,$B120,$M$1) -> 0 | H120: =_xll.DBRW($C$1,Opening!$G$13,Opening!H$11,$O$1,Opening!$I$13,Opening!$D$13,$P$1,$A120,$B120,$M$1) -> 0 | I120: =_xll.DBRW($C$1,Opening!$G$13,Opening!I$11,$O$1,Opening!$I$13,Opening!$D$13,$P$1,$A120,$B120,$M$1) -> 0 | J120: =_xll.DBRW($C$1,Opening!$G$13,Opening!J$11,$O$1,Opening!$I$13,Opening!$D$13,$P$1,$A120,$B120,$M$1) -> 0 | K120: =_xll.DBRW($C$1,Opening!$G$13,Opening!K$11,$O$1,Opening!$I$13,Opening!$D$13,$P$1,$A120,$B120,$M$1) -> 0 | L120: =_xll.DBRW($C$1,Opening!$G$13,Opening!L$11,$O$1,Opening!$I$13,Opening!$D$13,$P$1,$A120,$B120,$M$1) -> 0 | ... P120: =_xll.DBRW($C$1,Opening!$G$13,Opening!P$11,$O$1,Opening!$I$13,Opening!$D$13,$P$1,$A120,$B120,$M$1) -> 0 | Q120: =_xll.DBRW($C$1,Q$15,$Q$16,$O$1,Opening!$I$13,Opening!$D$13,$P$1,$A120,$B120,$M$1) -> 0 | R120: =_xll.DBRW($C$1,R$15,$Q$16,$O$1,Opening!$I$13,Opening!$D$13,$P$1,$A120,$B120,$M$1) -> 0 | S120: =_xll.DBRW($C$1,S$15,$Q$16,$O$1,Opening!$I$13,Opening!$D$13,$P$1,$A120,$B120,$M$1) -> 0 | T120: =_xll.DBRW($C$1,T$15,$Q$16,$O$1,Opening!$I$13,Opening!$D$13,$P$1,$A120,$B120,$M$1) -> 0 | U120: =_xll.DBRW($C$1,U$15,$Q$16,$O$1,Opening!$I$13,Opening!$D$13,$P$1,$A120,$B120,$M$1) -> 0
A121: FCF.099.026 | B121: ACL.FCF.050.001.05 | C121: Other Change in Assets / Current Liabilities | D121: Proceeds on Sales of Assets not in EBITDA | E121: =_xll.DBRW($C$1,Opening!$G$13,Opening!E$11,$O$1,Opening!$I$13,Opening!$D$13,$P$1,$A121,$B121,$M$1) -> 0 | F121: =_xll.DBRW($C$1,Opening!$G$13,Opening!F$11,$O$1,Opening!$I$13,Opening!$D$13,$P$1,$A121,$B121,$M$1) -> 0 | G121: =_xll.DBRW($C$1,Opening!$G$13,Opening!G$11,$O$1,Opening!$I$13,Opening!$D$13,$P$1,$A121,$B121,$M$1) -> 0 | H121: =_xll.DBRW($C$1,Opening!$G$13,Opening!H$11,$O$1,Opening!$I$13,Opening!$D$13,$P$1,$A121,$B121,$M$1) -> 0 | I121: =_xll.DBRW($C$1,Opening!$G$13,Opening!I$11,$O$1,Opening!$I$13,Opening!$D$13,$P$1,$A121,$B121,$M$1) -> 0 | J121: =_xll.DBRW($C$1,Opening!$G$13,Opening!J$11,$O$1,Opening!$I$13,Opening!$D$13,$P$1,$A121,$B121,$M$1) -> 0 | K121: =_xll.DBRW($C$1,Opening!$G$13,Opening!K$11,$O$1,Opening!$I$13,Opening!$D$13,$P$1,$A121,$B121,$M$1) -> 0 | L121: =_xll.DBRW($C$1,Opening!$G$13,Opening!L$11,$O$1,Opening!$I$13,Opening!$D$13,$P$1,$A121,$B121,$M$1) -> 0 | ... P121: =_xll.DBRW($C$1,Opening!$G$13,Opening!P$11,$O$1,Opening!$I$13,Opening!$D$13,$P$1,$A121,$B121,$M$1) -> 0 | Q121: =_xll.DBRW($C$1,Q$15,$Q$16,$O$1,Opening!$I$13,Opening!$D$13,$P$1,$A121,$B121,$M$1) -> 0 | R121: =_xll.DBRW($C$1,R$15,$Q$16,$O$1,Opening!$I$13,Opening!$D$13,$P$1,$A121,$B121,$M$1) -> 0 | S121: =_xll.DBRW($C$1,S$15,$Q$16,$O$1,Opening!$I$13,Opening!$D$13,$P$1,$A121,$B121,$M$1) -> 0 | T121: =_xll.DBRW($C$1,T$15,$Q$16,$O$1,Opening!$I$13,Opening!$D$13,$P$1,$A121,$B121,$M$1) -> 0 | U121: =_xll.DBRW($C$1,U$15,$Q$16,$O$1,Opening!$I$13,Opening!$D$13,$P$1,$A121,$B121,$M$1) -> 0
A122: FCF.099.026 | B122: ACL.FCF.050.001.06 | C122: Other Change in Assets / Current Liabilities | D122: Provision/ payments and other variation on Long asset & Liabilities Operations | E122: =_xll.DBRW($C$1,Opening!$G$13,Opening!E$11,$O$1,Opening!$I$13,Opening!$D$13,$P$1,$A122,$B122,$M$1) -> 0 | F122: =_xll.DBRW($C$1,Opening!$G$13,Opening!F$11,$O$1,Opening!$I$13,Opening!$D$13,$P$1,$A122,$B122,$M$1) -> 0 | G122: =_xll.DBRW($C$1,Opening!$G$13,Opening!G$11,$O$1,Opening!$I$13,Opening!$D$13,$P$1,$A122,$B122,$M$1) -> 0 | H122: =_xll.DBRW($C$1,Opening!$G$13,Opening!H$11,$O$1,Opening!$I$13,Opening!$D$13,$P$1,$A122,$B122,$M$1) -> 0 | I122: =_xll.DBRW($C$1,Opening!$G$13,Opening!I$11,$O$1,Opening!$I$13,Opening!$D$13,$P$1,$A122,$B122,$M$1) -> 0 | J122: =_xll.DBRW($C$1,Opening!$G$13,Opening!J$11,$O$1,Opening!$I$13,Opening!$D$13,$P$1,$A122,$B122,$M$1) -> 0 | K122: =_xll.DBRW($C$1,Opening!$G$13,Opening!K$11,$O$1,Opening!$I$13,Opening!$D$13,$P$1,$A122,$B122,$M$1) -> 0 | L122: =_xll.DBRW($C$1,Opening!$G$13,Opening!L$11,$O$1,Opening!$I$13,Opening!$D$13,$P$1,$A122,$B122,$M$1) -> 0 | ... P122: =_xll.DBRW($C$1,Opening!$G$13,Opening!P$11,$O$1,Opening!$I$13,Opening!$D$13,$P$1,$A122,$B122,$M$1) -> 0 | Q122: =_xll.DBRW($C$1,Q$15,$Q$16,$O$1,Opening!$I$13,Opening!$D$13,$P$1,$A122,$B122,$M$1) -> 0 | R122: =_xll.DBRW($C$1,R$15,$Q$16,$O$1,Opening!$I$13,Opening!$D$13,$P$1,$A122,$B122,$M$1) -> 0 | S122: =_xll.DBRW($C$1,S$15,$Q$16,$O$1,Opening!$I$13,Opening!$D$13,$P$1,$A122,$B122,$M$1) -> 0 | T122: =_xll.DBRW($C$1,T$15,$Q$16,$O$1,Opening!$I$13,Opening!$D$13,$P$1,$A122,$B122,$M$1) -> 0 | U122: =_xll.DBRW($C$1,U$15,$Q$16,$O$1,Opening!$I$13,Opening!$D$13,$P$1,$A122,$B122,$M$1) -> 0
A123: FCF.099.026 | B123: ACL.FCF.050.001.07 | C123: Other Change in Assets / Current Liabilities | D123: Other - Others | E123: =_xll.DBRW($C$1,Opening!$G$13,Opening!E$11,$O$1,Opening!$I$13,Opening!$D$13,$P$1,$A123,$B123,$M$1) -> 0 | F123: =_xll.DBRW($C$1,Opening!$G$13,Opening!F$11,$O$1,Opening!$I$13,Opening!$D$13,$P$1,$A123,$B123,$M$1) -> 0 | G123: =_xll.DBRW($C$1,Opening!$G$13,Opening!G$11,$O$1,Opening!$I$13,Opening!$D$13,$P$1,$A123,$B123,$M$1) -> 0 | H123: =_xll.DBRW($C$1,Opening!$G$13,Opening!H$11,$O$1,Opening!$I$13,Opening!$D$13,$P$1,$A123,$B123,$M$1) -> 0 | I123: =_xll.DBRW($C$1,Opening!$G$13,Opening!I$11,$O$1,Opening!$I$13,Opening!$D$13,$P$1,$A123,$B123,$M$1) -> 0 | J123: =_xll.DBRW($C$1,Opening!$G$13,Opening!J$11,$O$1,Opening!$I$13,Opening!$D$13,$P$1,$A123,$B123,$M$1) -> 0 | K123: =_xll.DBRW($C$1,Opening!$G$13,Opening!K$11,$O$1,Opening!$I$13,Opening!$D$13,$P$1,$A123,$B123,$M$1) -> 0 | L123: =_xll.DBRW($C$1,Opening!$G$13,Opening!L$11,$O$1,Opening!$I$13,Opening!$D$13,$P$1,$A123,$B123,$M$1) -> 0 | ... P123: =_xll.DBRW($C$1,Opening!$G$13,Opening!P$11,$O$1,Opening!$I$13,Opening!$D$13,$P$1,$A123,$B123,$M$1) -> 0 | Q123: =_xll.DBRW($C$1,Q$15,$Q$16,$O$1,Opening!$I$13,Opening!$D$13,$P$1,$A123,$B123,$M$1) -> 0 | R123: =_xll.DBRW($C$1,R$15,$Q$16,$O$1,Opening!$I$13,Opening!$D$13,$P$1,$A123,$B123,$M$1) -> 0 | S123: =_xll.DBRW($C$1,S$15,$Q$16,$O$1,Opening!$I$13,Opening!$D$13,$P$1,$A123,$B123,$M$1) -> 0 | T123: =_xll.DBRW($C$1,T$15,$Q$16,$O$1,Opening!$I$13,Opening!$D$13,$P$1,$A123,$B123,$M$1) -> 0 | U123: =_xll.DBRW($C$1,U$15,$Q$16,$O$1,Opening!$I$13,Opening!$D$13,$P$1,$A123,$B123,$M$1) -> 0
A124: FCF.099.026 | B124: N/A | C124: Other Change in Assets / Current Liabilities | D124: N/A | E124: =_xll.DBRW($C$1,Opening!$G$13,Opening!E$11,$O$1,Opening!$I$13,Opening!$D$13,$P$1,$A124,$B124,$M$1) -> 0 | F124: =_xll.DBRW($C$1,Opening!$G$13,Opening!F$11,$O$1,Opening!$I$13,Opening!$D$13,$P$1,$A124,$B124,$M$1) -> 0 | G124: =_xll.DBRW($C$1,Opening!$G$13,Opening!G$11,$O$1,Opening!$I$13,Opening!$D$13,$P$1,$A124,$B124,$M$1) -> 0 | H124: =_xll.DBRW($C$1,Opening!$G$13,Opening!H$11,$O$1,Opening!$I$13,Opening!$D$13,$P$1,$A124,$B124,$M$1) -> 0 | I124: =_xll.DBRW($C$1,Opening!$G$13,Opening!I$11,$O$1,Opening!$I$13,Opening!$D$13,$P$1,$A124,$B124,$M$1) -> 0 | J124: =_xll.DBRW($C$1,Opening!$G$13,Opening!J$11,$O$1,Opening!$I$13,Opening!$D$13,$P$1,$A124,$B124,$M$1) -> 0 | K124: =_xll.DBRW($C$1,Opening!$G$13,Opening!K$11,$O$1,Opening!$I$13,Opening!$D$13,$P$1,$A124,$B124,$M$1) -> 0 | L124: =_xll.DBRW($C$1,Opening!$G$13,Opening!L$11,$O$1,Opening!$I$13,Opening!$D$13,$P$1,$A124,$B124,$M$1) -> 0 | ... P124: =_xll.DBRW($C$1,Opening!$G$13,Opening!P$11,$O$1,Opening!$I$13,Opening!$D$13,$P$1,$A124,$B124,$M$1) -> 0 | Q124: =_xll.DBRW($C$1,Q$15,$Q$16,$O$1,Opening!$I$13,Opening!$D$13,$P$1,$A124,$B124,$M$1) -> 0 | R124: =_xll.DBRW($C$1,R$15,$Q$16,$O$1,Opening!$I$13,Opening!$D$13,$P$1,$A124,$B124,$M$1) -> 0 | S124: =_xll.DBRW($C$1,S$15,$Q$16,$O$1,Opening!$I$13,Opening!$D$13,$P$1,$A124,$B124,$M$1) -> 0 | T124: =_xll.DBRW($C$1,T$15,$Q$16,$O$1,Opening!$I$13,Opening!$D$13,$P$1,$A124,$B124,$M$1) -> 0 | U124: =_xll.DBRW($C$1,U$15,$Q$16,$O$1,Opening!$I$13,Opening!$D$13,$P$1,$A124,$B124,$M$1) -> 0
C127: CASH FLOW - INV/DIV IN SUBSIDIARIES AND AFFILIATES
Q128: =$G$13+1 -> 2027 | R128: =$G$13+2 -> 2028 | S128: =$G$13+3 -> 2029 | T128: =$G$13+4 -> 2030 | U128: =$G$13+5 -> 2031
E129: =$G$13&"."&E$11 -> 2026.01 | F129: =$G$13&"."&F$11 -> 2026.02 | G129: =$G$13&"."&G$11 -> 2026.03 | H129: =$G$13&"."&H$11 -> 2026.04 | I129: =$G$13&"."&I$11 -> 2026.05 | J129: =$G$13&"."&J$11 -> 2026.06 | K129: =$G$13&"."&K$11 -> 2026.07 | L129: =$G$13&"."&L$11 -> 2026.08 | ... P129: =$G$13&"."&P$11 -> 2026.12 | Q129: PE | R129: PE | S129: PE | T129: PE | U129: PE
A130: FCF.099.028 | C130: Investments in Associates and Subsidiaries | D130: Total Accounts Line | E130: =_xll.DBRW($C$1,Opening!$G$13,Opening!E$11,$O$1,Opening!$I$13,Opening!$D$13,$P$2,$A130,$D130,$M$1) -> 0 | F130: =_xll.DBRW($C$1,Opening!$G$13,Opening!F$11,$O$1,Opening!$I$13,Opening!$D$13,$P$2,$A130,$D130,$M$1) -> 0 | G130: =_xll.DBRW($C$1,Opening!$G$13,Opening!G$11,$O$1,Opening!$I$13,Opening!$D$13,$P$2,$A130,$D130,$M$1) -> 0 | H130: =_xll.DBRW($C$1,Opening!$G$13,Opening!H$11,$O$1,Opening!$I$13,Opening!$D$13,$P$2,$A130,$D130,$M$1) -> 0 | I130: =_xll.DBRW($C$1,Opening!$G$13,Opening!I$11,$O$1,Opening!$I$13,Opening!$D$13,$P$2,$A130,$D130,$M$1) -> 0 | J130: =_xll.DBRW($C$1,Opening!$G$13,Opening!J$11,$O$1,Opening!$I$13,Opening!$D$13,$P$2,$A130,$D130,$M$1) -> 0 | K130: =_xll.DBRW($C$1,Opening!$G$13,Opening!K$11,$O$1,Opening!$I$13,Opening!$D$13,$P$2,$A130,$D130,$M$1) -> 0 | L130: =_xll.DBRW($C$1,Opening!$G$13,Opening!L$11,$O$1,Opening!$I$13,Opening!$D$13,$P$2,$A130,$D130,$M$1) -> 0 | ... P130: =_xll.DBRW($C$1,Opening!$G$13,Opening!P$11,$O$1,Opening!$I$13,Opening!$D$13,$P$2,$A130,$D130,$M$1) -> 0 | Q130: =_xll.DBRW($C$1,Q$37,$Q$16,$O$1,Opening!$I$13,Opening!$D$13,$P$1,$A130,$D130,$M$1) -> 0 | R130: =_xll.DBRW($C$1,R$37,$Q$16,$O$1,Opening!$I$13,Opening!$D$13,$P$1,$A130,$D130,$M$1) -> 0 | S130: =_xll.DBRW($C$1,S$37,$Q$16,$O$1,Opening!$I$13,Opening!$D$13,$P$1,$A130,$D130,$M$1) -> 0 | T130: =_xll.DBRW($C$1,T$37,$Q$16,$O$1,Opening!$I$13,Opening!$D$13,$P$1,$A130,$D130,$M$1) -> 0 | U130: =_xll.DBRW($C$1,U$37,$Q$16,$O$1,Opening!$I$13,Opening!$D$13,$P$1,$A130,$D130,$M$1) -> 0
A131: FCF.099.028 | B131: ACL.FCF.060.000.01 | C131: Investments in Associates and Subsidiaries | D131: Pangea | E131: =_xll.DBRW($C$1,Opening!$G$13,Opening!E$11,$O$1,Opening!$I$13,Opening!$D$13,$P$1,$A131,$B131,$M$1) -> 0 | F131: =_xll.DBRW($C$1,Opening!$G$13,Opening!F$11,$O$1,Opening!$I$13,Opening!$D$13,$P$1,$A131,$B131,$M$1) -> 0 | G131: =_xll.DBRW($C$1,Opening!$G$13,Opening!G$11,$O$1,Opening!$I$13,Opening!$D$13,$P$1,$A131,$B131,$M$1) -> 0 | H131: =_xll.DBRW($C$1,Opening!$G$13,Opening!H$11,$O$1,Opening!$I$13,Opening!$D$13,$P$1,$A131,$B131,$M$1) -> 0 | I131: =_xll.DBRW($C$1,Opening!$G$13,Opening!I$11,$O$1,Opening!$I$13,Opening!$D$13,$P$1,$A131,$B131,$M$1) -> 0 | J131: =_xll.DBRW($C$1,Opening!$G$13,Opening!J$11,$O$1,Opening!$I$13,Opening!$D$13,$P$1,$A131,$B131,$M$1) -> 0 | K131: =_xll.DBRW($C$1,Opening!$G$13,Opening!K$11,$O$1,Opening!$I$13,Opening!$D$13,$P$1,$A131,$B131,$M$1) -> 0 | L131: =_xll.DBRW($C$1,Opening!$G$13,Opening!L$11,$O$1,Opening!$I$13,Opening!$D$13,$P$1,$A131,$B131,$M$1) -> 0 | ... P131: =_xll.DBRW($C$1,Opening!$G$13,Opening!P$11,$O$1,Opening!$I$13,Opening!$D$13,$P$1,$A131,$B131,$M$1) -> 0 | Q131: =_xll.DBRW($C$1,Q$15,$Q$16,$O$1,Opening!$I$13,Opening!$D$13,$P$1,$A131,$B131,$M$1) -> 0 | R131: =_xll.DBRW($C$1,R$15,$Q$16,$O$1,Opening!$I$13,Opening!$D$13,$P$1,$A131,$B131,$M$1) -> 0 | S131: =_xll.DBRW($C$1,S$15,$Q$16,$O$1,Opening!$I$13,Opening!$D$13,$P$1,$A131,$B131,$M$1) -> 0 | T131: =_xll.DBRW($C$1,T$15,$Q$16,$O$1,Opening!$I$13,Opening!$D$13,$P$1,$A131,$B131,$M$1) -> 0 | U131: =_xll.DBRW($C$1,U$15,$Q$16,$O$1,Opening!$I$13,Opening!$D$13,$P$1,$A131,$B131,$M$1) -> 0
A132: FCF.099.028 | B132: ACL.FCF.060.000.02 | C132: Investments in Associates and Subsidiaries | D132: Project 1 | E132: =_xll.DBRW($C$1,Opening!$G$13,Opening!E$11,$O$1,Opening!$I$13,Opening!$D$13,$P$1,$A132,$B132,$M$1) -> 0 | F132: =_xll.DBRW($C$1,Opening!$G$13,Opening!F$11,$O$1,Opening!$I$13,Opening!$D$13,$P$1,$A132,$B132,$M$1) -> 0 | G132: =_xll.DBRW($C$1,Opening!$G$13,Opening!G$11,$O$1,Opening!$I$13,Opening!$D$13,$P$1,$A132,$B132,$M$1) -> 0 | H132: =_xll.DBRW($C$1,Opening!$G$13,Opening!H$11,$O$1,Opening!$I$13,Opening!$D$13,$P$1,$A132,$B132,$M$1) -> 0 | I132: =_xll.DBRW($C$1,Opening!$G$13,Opening!I$11,$O$1,Opening!$I$13,Opening!$D$13,$P$1,$A132,$B132,$M$1) -> 0 | J132: =_xll.DBRW($C$1,Opening!$G$13,Opening!J$11,$O$1,Opening!$I$13,Opening!$D$13,$P$1,$A132,$B132,$M$1) -> 0 | K132: =_xll.DBRW($C$1,Opening!$G$13,Opening!K$11,$O$1,Opening!$I$13,Opening!$D$13,$P$1,$A132,$B132,$M$1) -> 0 | L132: =_xll.DBRW($C$1,Opening!$G$13,Opening!L$11,$O$1,Opening!$I$13,Opening!$D$13,$P$1,$A132,$B132,$M$1) -> 0 | ... P132: =_xll.DBRW($C$1,Opening!$G$13,Opening!P$11,$O$1,Opening!$I$13,Opening!$D$13,$P$1,$A132,$B132,$M$1) -> 0 | Q132: =_xll.DBRW($C$1,Q$15,$Q$16,$O$1,Opening!$I$13,Opening!$D$13,$P$1,$A132,$B132,$M$1) -> 0 | R132: =_xll.DBRW($C$1,R$15,$Q$16,$O$1,Opening!$I$13,Opening!$D$13,$P$1,$A132,$B132,$M$1) -> 0 | S132: =_xll.DBRW($C$1,S$15,$Q$16,$O$1,Opening!$I$13,Opening!$D$13,$P$1,$A132,$B132,$M$1) -> 0 | T132: =_xll.DBRW($C$1,T$15,$Q$16,$O$1,Opening!$I$13,Opening!$D$13,$P$1,$A132,$B132,$M$1) -> 0 | U132: =_xll.DBRW($C$1,U$15,$Q$16,$O$1,Opening!$I$13,Opening!$D$13,$P$1,$A132,$B132,$M$1) -> 0
A133: FCF.099.028 | B133: ACL.FCF.060.000.03 | C133: Investments in Associates and Subsidiaries | D133: Project 2 | E133: =_xll.DBRW($C$1,Opening!$G$13,Opening!E$11,$O$1,Opening!$I$13,Opening!$D$13,$P$1,$A133,$B133,$M$1) -> 0 | F133: =_xll.DBRW($C$1,Opening!$G$13,Opening!F$11,$O$1,Opening!$I$13,Opening!$D$13,$P$1,$A133,$B133,$M$1) -> 0 | G133: =_xll.DBRW($C$1,Opening!$G$13,Opening!G$11,$O$1,Opening!$I$13,Opening!$D$13,$P$1,$A133,$B133,$M$1) -> 0 | H133: =_xll.DBRW($C$1,Opening!$G$13,Opening!H$11,$O$1,Opening!$I$13,Opening!$D$13,$P$1,$A133,$B133,$M$1) -> 0 | I133: =_xll.DBRW($C$1,Opening!$G$13,Opening!I$11,$O$1,Opening!$I$13,Opening!$D$13,$P$1,$A133,$B133,$M$1) -> 0 | J133: =_xll.DBRW($C$1,Opening!$G$13,Opening!J$11,$O$1,Opening!$I$13,Opening!$D$13,$P$1,$A133,$B133,$M$1) -> 0 | K133: =_xll.DBRW($C$1,Opening!$G$13,Opening!K$11,$O$1,Opening!$I$13,Opening!$D$13,$P$1,$A133,$B133,$M$1) -> 0 | L133: =_xll.DBRW($C$1,Opening!$G$13,Opening!L$11,$O$1,Opening!$I$13,Opening!$D$13,$P$1,$A133,$B133,$M$1) -> 0 | ... P133: =_xll.DBRW($C$1,Opening!$G$13,Opening!P$11,$O$1,Opening!$I$13,Opening!$D$13,$P$1,$A133,$B133,$M$1) -> 0 | Q133: =_xll.DBRW($C$1,Q$15,$Q$16,$O$1,Opening!$I$13,Opening!$D$13,$P$1,$A133,$B133,$M$1) -> 0 | R133: =_xll.DBRW($C$1,R$15,$Q$16,$O$1,Opening!$I$13,Opening!$D$13,$P$1,$A133,$B133,$M$1) -> 0 | S133: =_xll.DBRW($C$1,S$15,$Q$16,$O$1,Opening!$I$13,Opening!$D$13,$P$1,$A133,$B133,$M$1) -> 0 | T133: =_xll.DBRW($C$1,T$15,$Q$16,$O$1,Opening!$I$13,Opening!$D$13,$P$1,$A133,$B133,$M$1) -> 0 | U133: =_xll.DBRW($C$1,U$15,$Q$16,$O$1,Opening!$I$13,Opening!$D$13,$P$1,$A133,$B133,$M$1) -> 0
A134: FCF.099.028 | B134: ACL.FCF.060.000.04 | C134: Investments in Associates and Subsidiaries | D134: Project 3 | E134: =_xll.DBRW($C$1,Opening!$G$13,Opening!E$11,$O$1,Opening!$I$13,Opening!$D$13,$P$1,$A134,$B134,$M$1) -> 0 | F134: =_xll.DBRW($C$1,Opening!$G$13,Opening!F$11,$O$1,Opening!$I$13,Opening!$D$13,$P$1,$A134,$B134,$M$1) -> 0 | G134: =_xll.DBRW($C$1,Opening!$G$13,Opening!G$11,$O$1,Opening!$I$13,Opening!$D$13,$P$1,$A134,$B134,$M$1) -> 0 | H134: =_xll.DBRW($C$1,Opening!$G$13,Opening!H$11,$O$1,Opening!$I$13,Opening!$D$13,$P$1,$A134,$B134,$M$1) -> 0 | I134: =_xll.DBRW($C$1,Opening!$G$13,Opening!I$11,$O$1,Opening!$I$13,Opening!$D$13,$P$1,$A134,$B134,$M$1) -> 0 | J134: =_xll.DBRW($C$1,Opening!$G$13,Opening!J$11,$O$1,Opening!$I$13,Opening!$D$13,$P$1,$A134,$B134,$M$1) -> 0 | K134: =_xll.DBRW($C$1,Opening!$G$13,Opening!K$11,$O$1,Opening!$I$13,Opening!$D$13,$P$1,$A134,$B134,$M$1) -> 0 | L134: =_xll.DBRW($C$1,Opening!$G$13,Opening!L$11,$O$1,Opening!$I$13,Opening!$D$13,$P$1,$A134,$B134,$M$1) -> 0 | ... P134: =_xll.DBRW($C$1,Opening!$G$13,Opening!P$11,$O$1,Opening!$I$13,Opening!$D$13,$P$1,$A134,$B134,$M$1) -> 0 | Q134: =_xll.DBRW($C$1,Q$15,$Q$16,$O$1,Opening!$I$13,Opening!$D$13,$P$1,$A134,$B134,$M$1) -> 0 | R134: =_xll.DBRW($C$1,R$15,$Q$16,$O$1,Opening!$I$13,Opening!$D$13,$P$1,$A134,$B134,$M$1) -> 0 | S134: =_xll.DBRW($C$1,S$15,$Q$16,$O$1,Opening!$I$13,Opening!$D$13,$P$1,$A134,$B134,$M$1) -> 0 | T134: =_xll.DBRW($C$1,T$15,$Q$16,$O$1,Opening!$I$13,Opening!$D$13,$P$1,$A134,$B134,$M$1) -> 0 | U134: =_xll.DBRW($C$1,U$15,$Q$16,$O$1,Opening!$I$13,Opening!$D$13,$P$1,$A134,$B134,$M$1) -> 0
